Workbook

Sheet 0_INSTRUCTIONS
A1: FLA RETURN AUTOMATION TOOL – COMPLETE WORKFLOW FOR TRAINEES
A3: 📋 HOW THIS TOOL WORKS
A4: This workbook has 3 key sheets that must be completed in ORDER:
A5: 1️⃣ APPLICABILITY → Tick Yes/No for what applies to the company
A6: 2️⃣ FINANCIALS → Enter balance sheet & P&L data (Companies Act 2013 format)
A7: 3️⃣ FLA RETURN → Auto-generated output ready to file on FLAIR portal
A9: 🎯 STEP-BY-STEP WORKFLOW FOR TRAINEES
A10: Step 1: Open 1_APPLICABILITY sheet
A11: • Read each applicability item carefully
A12: • Set 'Yes' or 'No' in column C for each item
A13: • This controls which fields appear in the Financials and FLA Return sheets
A14: • Example: If 'Has FDI ≥10%' = No, then FDI investor fields will be greyed out
... A48: ❌ Forgetting to convert share counts from 'in lakhs' to actuals

Sheet 1_APPLICABILITY
A1: FLA RETURN – APPLICABILITY CHECKER | Set Yes/No for each item below
A2: Complete this sheet FIRST. The Financials Input and FLA Return sheets will show only relevant fields based on your selections.
B3: Applicability Item | C3: Applicable? (Yes / No) | D3: What this means
B5: ▌ SECTION III – FOREIGN LIABILITIES (Inward Investment)
B6: Has FDI ≥10% (Block 1 Sec III) | C6: Yes | D6: NR investor holds 10%+ equity in your company
B7: Has FDI <10% (Block 2 Sec III) | C7: No | D7: NR investor holds <10% equity in your company
B8: Has Portfolio Investment in India (Block 3) | C8: No | D8: FIIs/portfolio investors hold equity/debt NOT under FDI scheme
B9: Has Other Foreign Liabilities (Block 4) | C9: Yes | D9: Liabilities to unrelated foreign parties: trade credit, ECB, deposits
B10: ▌ SECTION IV – FOREIGN ASSETS (Outward Investment)
B11: Has ODI ≥10% Abroad (Block 1 Sec IV) | C11: Yes | D11: Your company holds 10%+ equity in a foreign DIE
B12: Has DI <10% Abroad (Block 2 Sec IV) | C12: No | D12: Your company holds <10% equity in a foreign entity
B13: Has Portfolio Investment Abroad (Block 3) | C13: No | D13: Portfolio investments in foreign entities
B14: Has Other Foreign Claims (Block 4) | C14: Yes | D14: Claims on unrelated foreign parties: receivables, loans given
B15: ▌ ADDITIONAL APPLICABILITY
B16: Has Reverse Investment (Claims on FDI/ODI counterparty) | C16: No | D16: Your company has invested back into the FDI investor / DIE holds investment in you
B17: Has ECB / Foreign Loans (Unrelated parties) | C17: Yes | D17: External Commercial Borrowings from unrelated foreign lenders
B18: Is Listed Company | C18: No | D18: Shares listed on BSE/NSE – market value per share required in Section I
B19: Has Technical Foreign Collaboration | C19: No | D19: Technical collaboration agreement with a foreign entity
B20: Merged / Amalgamated During the Year | C20: No | D20: Company merged or amalgamated in the reporting FY
B21: Has Participating Preference Shares | C21: No | D21: Company has issued participating preference shares
B22: Has Non-Participating Preference Shares | C22: No | D22: Company has issued non-participating preference shares
B23: Had Disinvestment During the Year | C23: No | D23: NR shareholding decreased due to buyback/transfer in the year
B26: Has CCDs / CCPs issued to Portfolio investors (non-FDI) | C26: No | D26: Company has issued CCDs/CCPs to NR investors not holding equity (Block 3 Sec III)
B27: Has Trade Receivables from NR parties | C27: No | D27: Outstanding receivables from foreign related or unrelated parties
B28: Has Trade Payables to NR parties | C28: No | D28: Outstanding payables to foreign suppliers, FDI investors, or related parties
A29: ℹ️ After completing this sheet, go to 2_FINANCIALS to enter company data. Fields not applicable will be greyed out automatically.

Sheet 2_FINANCIALS
A1: FLA RETURN – FINANCIALS INPUT SHEET | Fill ONLY the 🟡 Yellow cells. 🟢 Green = auto-calculated. Grey = not required for your company.
A2: 🟡 Yellow cells = YOU enter the number / text | 🟢 Green cells = leave them alone (auto-calculated) | Grey cells = not applicable for your company based on Applicability sheet
B3: What to Enter | C3: PREVIOUS YEAR (PY) End-March | D3: CURRENT YEAR (FY) End-March | E3: 📌 Where to find this in your documents | F3: FLA Field Ref
A4: SECTION I – COMPANY & FILING DETAILS
A5: Part A – Basic Company Info (these fields are pre-filled on FLAIR portal – just verify them)
A6: ℹ️ For text fields (name, CIN, email etc.) — type in the PY column. The FY column is not needed for text fields.
A7: 🏢 SOURCE DOCUMENT: MCA Master Data / Certificate of Incorporation / FLAIR portal
B8: Company Name | D8: 0 | E8: Exact name as per MCA/ROC records | F8: Sec I: Name
B9: CIN (Corporate Identification Number) | C9: 0 | D9: 0 | E9: 21-digit CIN on Certificate of Incorporation | F9: Sec I: CIN
B10: PAN (Permanent Account Number) | C10: 0 | D10: 0 | E10: 10-char PAN on Income Tax documents | F10: Sec I: PAN
B11: Filing Year (e.g. 2025 for FY 2024-25) | D11: 0 | E11: Enter year of filing e.g. type 2025 | F11: Sec I: Year
B12: Contact Person Name (authorised signatory) | D12: 0 | E12: CFO, CS, or Director authorised to sign | F12: Sec I: Contact
B13: Telephone No. (with STD code) | D13: 0 | E13: e.g. 044-23456789 | F13: Sec I: Tel
B14: Mobile No. (10 digits) | D14: 0 | E14: OTP for FLAIR login comes here | F14: Sec I: Mobile
B15: Contact Email | D15: 0 | E15: Active email used for FLAIR portal login | F15: Sec I: Email
B16: Designation of Contact Person | D16: 0 | E16: e.g. CFO / Company Secretary / Director | F16: Sec I: Designation
B17: Company Website (if any) | D17: 0 | E17: Leave blank if none | F17: Sec I: Website
B18: NIC Code (Business Activity Code) | D18: 0 | E18: 2-digit code from ANNEX tab in this file (e.g. 62 for IT services) | F18: Sec I: NIC Code
B19: Is company listed on BSE/NSE? (Yes/No) | C19: ='1_APPLICABILITY'!C18 -> No | D19: 0 | E19: Check if shares are listed on any stock exchange | F19: Sec I: Listed
B20: Is company an AMC? (Yes/No) | D20: 0 | E20: Asset Management Company – usually No | F20: Sec I: AMC
B21: Technical Foreign Collaboration? (Yes/No) | C21: ='1_APPLICABILITY'!C19 -> No | D21: 0 | E21: Foreign tech collaboration agreement exists? | F21: Sec I: Tech Collab
B22: Did company carry on business activity in FY? (Yes/No) | D22: 0 | E22: Did company earn any revenue this year? | F22: Sec I: Business Act
B23: Did company merge/amalgamate during FY? (Yes/No) | C23: ='1_APPLICABILITY'!C20 -> No | D23: 0 | E23: Merger/amalgamation happened this year? | F23: Sec I: Merged
A24: Part B – Share Capital Details
A25: 📋 SOURCE DOCUMENT: Notes to Accounts → Share Capital (in Annual Report / Audited Financials)
A26: ℹ️ IMPORTANT: Enter number of shares in ACTUALS (not in lakhs). Face value in ₹ per share. Example: If 10,00,000 shares of ₹10 each → enter 1000000 in shares column and 10 in face value column.
B27: Equity Shares – Total number of shares issued & fully paid | C27: 0 | D27: 0 | E27: Notes to Accounts > Share Capital > Equity Shares issued and fully paid up (line item showing actual number) | F27: Sec II 1(a)
B28: Face Value per Equity Share (₹ per share) | C28: 0 | D28: 0 | E28: Notes to Accounts > Share Capital (e.g. 'Equity shares of ₹10 each' → enter 10) | F28: Sec I: FV Equity
B29: Participating Preference Shares – No. of shares (Only if marked Yes in Applicability sheet) | C29: =IF('1_APPLICABILITY'!C21="Yes","","N/A – set applicability to Yes") -> N/A – set applicability to Yes | D29: =IF('1_APPLICABILITY'!C21="Yes","","N/A – set applicability to Yes") -> N/A – set applicability to Yes | E29: Notes to Accounts > Share Capital > Preference Shares (participating type) | F29: Sec II 1(b)
B30: Face Value per Participating Preference Share (₹/share) | C30: =IF('1_APPLICABILITY'!C21="Yes","","N/A – set applicability to Yes") -> N/A – set applicability to Yes | D30: =IF('1_APPLICABILITY'!C21="Yes","","N/A – set applicability to Yes") -> N/A – set applicability to Yes | E30: Notes to Accounts > Share Capital | F30: Sec I: FV Part.Pref
B31: Non-Participating Preference Shares – No. of shares (Only if marked Yes in Applicability sheet) | C31: =IF('1_APPLICABILITY'!C22="Yes","","N/A – set applicability to Yes") -> N/A – set applicability to Yes | D31: =IF('1_APPLICABILITY'!C22="Yes","","N/A – set applicability to Yes") -> N/A – set applicability to Yes | E31: Notes to Accounts > Share Capital > Non-participating preference shares | F31: Sec II 1.2
B32: Face Value per Non-Participating Preference Share (₹/share) | C32: =IF('1_APPLICABILITY'!C22="Yes","","N/A – set applicability to Yes") -> N/A – set applicability to Yes | D32: =IF('1_APPLICABILITY'!C22="Yes","","N/A – set applicability to Yes") -> N/A – set applicability to Yes | E32: Notes to Accounts > Share Capital | F32: Sec I: FV Non-Part.Pref
B33: Market Price per Equity Share on 31-March (₹/share) — Listed companies only | C33: =IF('1_APPLICABILITY'!C18="Yes","","N/A – set applicability to Yes") -> N/A – set applicability to Yes | D33: =IF('1_APPLICABILITY'!C18="Yes","","N/A – set applicability to Yes") -> N/A – set applicability to Yes | E33: BSE/NSE website: closing price of company's equity share on 31-March of the year | F33: Sec I: Market Value
A34: SECTION II – FINANCIAL DATA (from Audited Financial Statements)
A35: Part C – From the PROFIT & LOSS STATEMENT
A36: 💰 SOURCE DOCUMENT: Profit & Loss Statement / Statement of Profit & Loss
A37: ℹ️ All amounts in ₹ LAKHS. Example: If P&L shows ₹50,00,000 → enter 50.00. If ₹2,00,00,000 → enter 200.00. Loss amounts: enter as negative number e.g. -75.00
B38: Profit (or Loss) BEFORE Tax — PBT (last line before 'Less: Tax Expense') | C38: 0 | D38: 0 | E38: P&L Statement → look for 'Profit Before Tax' or 'PBT'. If loss, enter negative. | F38: Sec II 3.1
B39: Profit (or Loss) AFTER Tax — PAT / Net Profit (very last line of P&L) | C39: 0 | D39: 0 | E39: P&L Statement → last line 'Profit for the year' or 'Net Profit/(Loss)'. If loss, enter negative. | F39: Sec II 3.2
B40: Dividend Paid during the year (₹ Lakhs) (Interim + Final combined) | C40: 0 | D40: 0 | E40: P&L Statement OR Notes to Accounts → search for 'Dividend paid/declared on equity shares'. | F40: Sec II 3.3
B41: Tax on Dividend (₹ Lakhs) (Dividend Distribution Tax – DDT, if any) | C41: 0 | D41: 0 | E41: Notes to Accounts or P&L → 'Tax on Dividend' or 'DDT'. Usually 0 after 2020. | F41: Sec II 3.4
B42: ✅ Retained Profit = PAT minus Dividend (auto-calculated) | C42: =IF(C39=0,0,C39-C40) -> 0 | D42: =IF(D39=0,0,D39-D40) -> 0 | E42: Auto-calculated: PAT minus Dividend Paid | F42: Sec II 3.5
A43: Part D – From the BALANCE SHEET → Equity Side
A44: 📊 SOURCE DOCUMENT: Balance Sheet → Sources of Funds / Equity & Liabilities side
A45: ℹ️ All amounts in ₹ LAKHS. Net Worth is auto-calculated from shares × face value + Reserves & Surplus.
B46: Reserves & Surplus – TOTAL (₹ Lakhs) (all reserves combined) | C46: 0 | D46: 0 | E46: Balance Sheet → Equity side → 'Reserves and Surplus' total line. | F46: Sec II 4.1
B47: Of which: P&L Account Balance (₹ Lakhs) (the accumulated surplus/deficit in reserves) | C47: 0 | D47: 0 | E47: Notes to Reserves & Surplus → look for 'Surplus / Balance in Statement of P&L'. This is one component of total Reserves. | F47: Sec II 4.2
B48: ✅ Net Worth = Paid-up Capital + Reserves & Surplus (auto-calculated) | C48: =IFERROR((C27*C28)/100000+C46,0) -> 0 | D48: =IFERROR((D27*D28)/100000+D46,0) -> 0 | E48: Auto-calculated: (No. of Equity Shares × Face Value) ÷ 1,00,000 + Reserves & Surplus | F48: Sec II 4.3
A49: Part E – From the PROFIT & LOSS STATEMENT → Revenue & Purchases
A50: 📈 SOURCE DOCUMENT: Profit & Loss Statement → Revenue from Operations & Cost of Materials/Purchases
B51: Domestic Sales – Revenue from domestic customers (₹ Lakhs) | C51: 0 | D51: 0 | E51: P&L → 'Revenue from Operations' or 'Domestic Turnover'. Exclude exports. | F51: Sec II 5.1
B52: Export Sales – Revenue from overseas customers (₹ Lakhs) (foreign exchange earnings) | C52: 0 | D52: 0 | E52: P&L → 'Export Turnover' OR Notes to Accounts → 'Foreign Exchange Earnings'. If nil, enter 0. | F52: Sec II 5.2
B53: ✅ Total Sales = Domestic Sales + Export Sales (auto-calculated) | C53: =C51+C52 -> 0 | D53: =D51+D52 -> 0 | E53: Auto-calculated | F53: Sec II 5.3
B54: Domestic Purchases – from Indian suppliers (₹ Lakhs) | C54: 0 | D54: 0 | E54: P&L → 'Cost of Materials Consumed' or 'Purchases of Stock-in-trade' – domestic portion. | F54: Sec II 5.4
B55: Import Purchases – from overseas suppliers (₹ Lakhs) (CIF value of imports) | C55: 0 | D55: 0 | E55: Notes to Accounts → 'CIF value of imports' or 'Foreign Exchange Used for Imports'. If nil, enter 0. | F55: Sec II 5.5
B56: ✅ Total Purchases = Domestic + Import Purchases (auto-calculated) | C56: =C54+C55 -> 0 | D56: =D54+D55 -> 0 | E56: Auto-calculated | F56: Sec II 5.6
A57: Part F – Employee Count
A58: 👥 SOURCE DOCUMENT: HR Records / Annual Report / Directors' Report
B59: Number of Employees on Payroll as at 31-March (actual count, not in lakhs) | C59: 0 | D59: 0 | E59: HR register / Annual Report → 'Number of employees' as of March 31. Includes all full-time employees. | F59: Sec II 6.1
A60: SECTION II – NON-RESIDENT (NR) SHAREHOLDER BREAKDOWN
A61: Part G – Number of Equity Shares held by each category of Non-Resident (NR) investor
A62: 📂 SOURCE DOCUMENT: Shareholding Pattern (MGT-7 / Annual Return) OR Register of Members
A63: ℹ️ Enter actual NUMBER OF SHARES (not %) held by each NR investor category. If a category has no NR investors, enter 0. Source: Shareholding Pattern filed with RoC or from your Register of Members.
B64: Foreign Individuals (NR individual investors from overseas) | C64: 0 | D64: 0 | E64: Shareholding Pattern / Register of Members – individual foreign investors | F64: Sec II 2.1 item 1
B65: Foreign Companies (overseas companies holding equity) | C65: 0 | D65: 0 | E65: Register of Members – foreign corporate shareholders | F65: Sec II 2.1 item 2
B66: FIIs – Foreign Institutional Investors (SEBI-registered foreign funds) | C66: 0 | D66: 0 | E66: Shareholding Pattern – FII/FPI category | F66: Sec II 2.1 item 3
B67: FVCIs – Foreign Venture Capital Investors (SEBI-registered FVCI) | C67: 0 | D67: 0 | E67: Register of Members – FVCI investors | F67: Sec II 2.1 item 4
B68: Foreign Trusts | C68: 0 | D68: 0 | E68: Register of Members – foreign trusts | F68: Sec II 2.1 item 5
B69: Foreign Private Equity Funds | C69: 0 | D69: 0 | E69: Register of Members – PE fund investors | F69: Sec II 2.1 item 6
B70: Foreign Pension / Provident Funds | C70: 0 | D70: 0 | E70: Register of Members – pension/provident funds | F70: Sec II 2.1 item 7
B71: Sovereign Wealth Funds | C71: 0 | D71: 0 | E71: Register of Members – sovereign wealth fund investors | F71: Sec II 2.1 item 8
B72: Foreign Partnership / Proprietorship Firms | C72: 0 | D72: 0 | E72: Register of Members – foreign firm investors | F72: Sec II 2.1 item 9
B73: Foreign Financial Institutions (banks, insurance companies etc.) | C73: 0 | D73: 0 | E73: Register of Members – foreign FI investors | F73: Sec II 2.1 item 10
B74: NRIs / PIOs (Non-Resident Indians / Persons of Indian Origin) | C74: 0 | D74: 0 | E74: Shareholding Pattern – NRI category | F74: Sec II 2.1 item 11
B75: Non-Participating Preference Shares held by NR investors (Only if marked Yes in Applicability sheet) | C75: =IF('1_APPLICABILITY'!C22="Yes","","N/A – set applicability to Yes") -> N/A – set applicability to Yes | D75: =IF('1_APPLICABILITY'!C22="Yes","","N/A – set applicability to Yes") -> N/A – set applicability to Yes | E75: Register of Members – NR holders of non-participating preference shares | F75: Sec II 2.2
B76: ✅ TOTAL NR Equity Shares – Sum of all categories above (auto-calculated) | C76: =SUM(C64:C74) -> 0 | D76: =SUM(D64:D74) -> 0 | E76: Auto-calculated – sum of all NR investor categories | F76: Sec II 2.1 TOTAL
A77: SECTION III – FOREIGN LIABILITIES (Money/equity owed TO non-residents) — Fill only if applicable
A78: ℹ️ This section appears only if you marked 'Yes' for relevant items in the Applicability sheet. Grey cells = not required for your company. All amounts in ₹ LAKHS.
A79: Block 1 – FDI ≥10% : Details of each Foreign Direct Investor holding 10% or more equity
A80: 🌐 SOURCE DOCUMENT: FCGPR Filing Receipts / KYC Documents of NR investors / Register of Members
A81: FDI Investor 1
B82: Investor 1: Full Name of NR Company / Individual | D82: =IF('1_APPLICABILITY'!C6="Yes","","N/A – set applicability to Yes") | E82: FCGPR receipt filed with RBI / KYC documents of the investor | F82: Sec III B1: Investor Name
B83: Investor 1: Country (country of incorporation / residence of NR investor) | D83: =IF('1_APPLICABILITY'!C6="Yes","","N/A – set applicability to Yes") | E83: FCGPR receipt / KYC – investor's country of incorporation or residence | F83: Sec III B1: Country
B84: Investor 1: % Equity holding in your company (PY and FY) | C84: =IF('1_APPLICABILITY'!C6="Yes","","N/A – set applicability to Yes") | D84: =IF('1_APPLICABILITY'!C6="Yes","","N/A – set applicability to Yes") | E84: FCGPR / Register of Members → percentage shareholding of this investor (e.g. 51.00) | F84: Sec III B1: Equity %
B85: ✅ Investor 1: Equity Capital (₹ Lakhs) = Net Worth × % holding (auto-calculated) | C85: =IF('1_APPLICABILITY'!C6="Yes",IFERROR(C48*C84/100,0),"N/A") -> 0 | D85: =IF('1_APPLICABILITY'!C6="Yes",IFERROR(D48*D84/100,0),"N/A") -> 0 | E85: Auto-calculated: Net Worth × % holding ÷ 100 | F85: Sec III B1.1: Equity Cap
B86: Investor 1: Reverse Investment – Liabilities TO this investor (₹ Lakhs) (Amount your company owes this investor from your reverse investment) | C86: =IF('1_APPLICABILITY'!C16="Yes","","N/A – set applicability to Yes") -> N/A – set applicability to Yes | D86: =IF('1_APPLICABILITY'!C16="Yes","","N/A – set applicability to Yes") -> N/A – set applicability to Yes | E86: Balance Sheet: Any amount your company has invested BACK into this FDI investor; treat as liability | F86: Sec III B1 item 1.1
B87: Investor 1: Reverse Investment – Claims ON this investor (₹ Lakhs) (Amount this investor owes your company from reverse investment) | C87: =IF('1_APPLICABILITY'!C16="Yes","","N/A – set applicability to Yes") -> N/A – set applicability to Yes | D87: =IF('1_APPLICABILITY'!C16="Yes","","N/A – set applicability to Yes") -> N/A – set applicability to Yes | E87: Balance Sheet: Receivables/investment your company made into this FDI investor's entity | F87: Sec III B1 item 1.2
B88: Investor 1: Other Liabilities to this investor (₹ Lakhs) (Trade payables + ECB loans + CCDs/CCPs issued to THIS specific investor) | C88: =IF('1_APPLICABILITY'!C6="Yes","","N/A – set applicability to Yes") | D88: =IF('1_APPLICABILITY'!C6="Yes","","N/A – set applicability to Yes") | E88: Balance Sheet: Trade Creditors/Payables to THIS specific FDI investor + any ECB from this investor + CCD/CCP issued to this investor. Source: RPT Schedule / Notes | F88: Sec III B1 item 2.1
B89: Investor 1: Other Claims on this investor (₹ Lakhs) (Trade receivables owed BY this investor TO your company) | C89: =IF('1_APPLICABILITY'!C6="Yes","","N/A – set applicability to Yes") | D89: =IF('1_APPLICABILITY'!C6="Yes","","N/A – set applicability to Yes") | E89: Balance Sheet: Trade Debtors/Receivables from THIS specific FDI investor. Source: Related Party Transaction schedule | F89: Sec III B1 item 2.2
B90: Investor 1: Disinvestment amount during year (₹ Lakhs) (Only if NR% decreased due to buyback / transfer) | C90: =IF('1_APPLICABILITY'!C23="Yes","","N/A – set applicability to Yes") -> N/A – set applicability to Yes | D90: =IF('1_APPLICABILITY'!C23="Yes","","N/A – set applicability to Yes") -> N/A – set applicability to Yes | E90: If NR investor sold/transferred shares back or company bought back → enter reduction amount | F90: Sec III B1 item 3
B91: Investor 1: Month of FIRST FDI received from this investor (e.g. Apr, Jan, Mar) | D91: =IF('1_APPLICABILITY'!C6="Yes","","N/A – set applicability to Yes") | E91: FCGPR filing date with RBI / Date of first share allotment to this investor in Register of Members | F91: Sec III B1: Month 1st FDI
B92: Investor 1: Year of FIRST FDI received from this investor (e.g. 2019) | C92: =IF('1_APPLICABILITY'!C6="Yes","","N/A – set applicability to Yes") | D92: =IF('1_APPLICABILITY'!C6="Yes","","N/A – set applicability to Yes") | E92: FCGPR filing date with RBI / Year of first share allotment in Register of Members | F92: Sec III B1: Year 1st FDI
A93: FDI Investor 2
B94: Investor 2: Full Name of NR Company / Individual | D94: =IF('1_APPLICABILITY'!C6="Yes","","N/A – set applicability to Yes") | E94: FCGPR receipt filed with RBI / KYC documents of the investor | F94: Sec III B1: Investor Name
B95: Investor 2: Country (country of incorporation / residence of NR investor) | D95: =IF('1_APPLICABILITY'!C6="Yes","","N/A – set applicability to Yes") | E95: FCGPR receipt / KYC – investor's country of incorporation or residence | F95: Sec III B1: Country
B96: Investor 2: % Equity holding in your company (PY and FY) | C96: =IF('1_APPLICABILITY'!C6="Yes","","N/A – set applicability to Yes") | D96: =IF('1_APPLICABILITY'!C6="Yes","","N/A – set applicability to Yes") | E96: FCGPR / Register of Members → percentage shareholding of this investor (e.g. 51.00) | F96: Sec III B1: Equity %
B97: ✅ Investor 2: Equity Capital (₹ Lakhs) = Net Worth × % holding (auto-calculated) | C97: =IF('1_APPLICABILITY'!C6="Yes",IFERROR(C48*C96/100,0),"N/A") -> 0 | D97: =IF('1_APPLICABILITY'!C6="Yes",IFERROR(D48*D96/100,0),"N/A") -> 0 | E97: Auto-calculated: Net Worth × % holding ÷ 100 | F97: Sec III B1.1 Equity Cap
B98: Investor 2: Reverse Investment – Liabilities TO this investor (₹ Lakhs) (Amount your company owes this investor from your reverse investment) | C98: =IF('1_APPLICABILITY'!C16="Yes","","N/A – set applicability to Yes") -> N/A – set applicability to Yes | D98: =IF('1_APPLICABILITY'!C16="Yes","","N/A – set applicability to Yes") -> N/A – set applicability to Yes | E98: Balance Sheet: Any amount your company has invested BACK into this FDI investor; treat as liability | F98: Sec III B1 item 1.1
B99: Investor 2: Reverse Investment – Claims ON this investor (₹ Lakhs) (Amount this investor owes your company from reverse investment) | C99: =IF('1_APPLICABILITY'!C16="Yes","","N/A – set applicability to Yes") -> N/A – set applicability to Yes | D99: =IF('1_APPLICABILITY'!C16="Yes","","N/A – set applicability to Yes") -> N/A – set applicability to Yes | E99: Balance Sheet: Receivables/investment your company made into this FDI investor's entity | F99: Sec III B1 item 1.2
B100: Investor 2: Other Liabilities to this investor (₹ Lakhs) (Trade payables + ECB loans + CCDs/CCPs issued to THIS specific investor) | C100: =IF('1_APPLICABILITY'!C6="Yes","","N/A – set applicability to Yes") | D100: =IF('1_APPLICABILITY'!C6="Yes","","N/A – set applicability to Yes") | E100: Balance Sheet: Trade Creditors/Payables to THIS specific FDI investor + any ECB from this investor + CCD/CCP issued to this investor. Source: RPT Schedule / Notes | F100: Sec III B1 item 2.1
...

Sheet 3_FLA_RETURN
A1: FLA RETURN – FORM | Auto-filled from Financials Input | RBI FLAIR Portal Format
A2: 🟢 Green = auto-filled from Financials sheet | 🟡 Yellow = verify/enter manually | Grey = N/A based on applicability
A3: SECTION I – IDENTIFICATION PARTICULARS
A4: Sr. | B4: Item No. | C4: Field Name (as per RBI FLAIR portal) | D4: Value | F4: Notes | G4: SOURCE
A5: 1 | B5: — | C5: Company Name* | D5: ='2_FINANCIALS'!D8 -> 0 | F5: Pre-filled on FLAIR – verify | G5: FINANCIALS
A6: 2 | B6: — | C6: CIN* | D6: ='2_FINANCIALS'!C9 -> 0 | G6: PREFILL
A7: 3 | B7: — | C7: PAN* | D7: ='2_FINANCIALS'!C10 -> 0 | G7: PREFILL
A8: 4 | B8: — | C8: Filing Year* | D8: ='2_FINANCIALS'!D11 -> 0 | G8: Enter year of filing e.g. type 2025
A9: 5 | B9: — | C9: Contact Person Name* | D9: ='2_FINANCIALS'!D12 -> 0 | G9: PREVIOUS FLA
A10: 6 | B10: — | C10: Telephone No.* | D10: ='2_FINANCIALS'!D13 -> 0 | G10: PREVIOUS FLA
A11: 7 | B11: — | C11: Mobile No.* | D11: ='2_FINANCIALS'!D14 -> 0 | G11: PREVIOUS FLA
A12: 8 | B12: — | C12: Email of Contact Person* | D12: ='2_FINANCIALS'!D15 -> 0 | G12: PREVIOUS FLA
A13: 9 | B13: — | C13: Designation* | D13: ='2_FINANCIALS'!D16 -> 0 | G13: PREVIOUS FLA
A14: 10 | B14: — | C14: Website | D14: ='2_FINANCIALS'!D17 -> 0 | G14: PREVIOUS FLA
A15: 11 | B15: — | C15: Account Closing Date* | D15: =DATE('2_FINANCIALS'!D11,3,31) -> 91 | F15: Auto: 31-March of filing year | G15: FINANCIALS - CURRENT YEAR FOR WHICH FILING IS BEING DONE
A16: 12 | B16: — | C16: Nature of Business (NIC Code)* | D16: ='2_FINANCIALS'!D18 -> 0 | G16: PREVIOUS FLA
A17: 13 | B17: — | C17: Whether Listed (Y/N)* | D17: ='2_FINANCIALS'!C19 -> No | G17: PREVIOUS FLA
A18: 14 | B18: — | C18: Whether Merged/Amalgamated (Y/N)* | D18: =IF('1_APPLICABILITY'!C20="Yes",'2_FINANCIALS'!D23,"N/A") -> N/A | G18: PREVIOUS FLA
A19: 15 | B19: — | C19: Whether AMC (Y/N)* | D19: ='2_FINANCIALS'!D20 -> 0 | G19: PREVIOUS FLA
A20: 16 | B20: — | C20: Technical Foreign Collaboration (Y/N)* | D20: =IF('1_APPLICABILITY'!C19="Yes",'2_FINANCIALS'!D21,"N/A") -> N/A | G20: PREVIOUS FLA
A21: 17 | B21: — | C21: Business Activity during FY (Y/N)* | D21: ='2_FINANCIALS'!D22 -> 0 | G21: Did company earn any revenue this year?
A22: 18 | B22: — | C22: Type of Company* | D22: → enter on FLAIR portal | F22: Dropdown on portal | G22: PREVIOUS FLA
A23: 19 | B23: — | C23: Inward FDI Identification* | D23: → enter on FLAIR portal | F23: Dropdown on portal | G23: PREVIOUS FLA
A24: Share Face Value Table (₹ per share – Actuals)
A25: Sr. | B25: Item No. | C25: Field Name (as per RBI FLAIR portal) | D25: End-March PY | E25: End-March FY | F25: Source
A26: 20 | B26: — | C26: Ordinary/Equity Shares – No. of shares | D26: ='2_FINANCIALS'!C27 -> 0 | E26: ='2_FINANCIALS'!D27 -> 0 | F26: Balance Sheet > Notes: Share Capital | G26: FINANCIALS + LIST OF SHAREHOLDER
A27: 21 | B27: — | C27: Ordinary/Equity – Face Value (₹/share) | D27: ='2_FINANCIALS'!C28 -> 0 | E27: ='2_FINANCIALS'!D28 -> 0 | G27: FINANCIALS + LIST OF SHAREHOLDER
A28: 22 | B28: — | C28: Participating Preference – No. of shares | D28: =IF('1_APPLICABILITY'!C21="Yes",'2_FINANCIALS'!C29,"N/A") -> N/A | E28: =IF('1_APPLICABILITY'!C21="Yes",'2_FINANCIALS'!D29,"N/A") -> N/A | G28: FINANCIALS + LIST OF SHAREHOLDER
A29: 23 | B29: — | C29: Participating Preference – Face Value (₹/sh) | D29: =IF('1_APPLICABILITY'!C21="Yes",'2_FINANCIALS'!C30,"N/A") -> N/A | E29: =IF('1_APPLICABILITY'!C21="Yes",'2_FINANCIALS'!D30,"N/A") -> N/A | G29: FINANCIALS + LIST OF SHAREHOLDER
A30: 24 | B30: — | C30: Non-Part. Preference – No. of shares | D30: =IF('1_APPLICABILITY'!C22="Yes",'2_FINANCIALS'!C31,"N/A") -> N/A | E30: =IF('1_APPLICABILITY'!C22="Yes",'2_FINANCIALS'!D31,"N/A") -> N/A | G30: FINANCIALS + LIST OF SHAREHOLDER
A31: 25 | B31: — | C31: Non-Part. Preference – Face Value (₹/sh) | D31: =IF('1_APPLICABILITY'!C22="Yes",'2_FINANCIALS'!C32,"N/A") -> N/A | E31: =IF('1_APPLICABILITY'!C22="Yes",'2_FINANCIALS'!D32,"N/A") -> N/A | G31: FINANCIALS + LIST OF SHAREHOLDER
A32: 26 | B32: — | C32: Market Value per Equity Share (₹/sh) – Listed only | D32: =IF('1_APPLICABILITY'!C18="Yes",'2_FINANCIALS'!C33,"N/A") -> N/A | E32: =IF('1_APPLICABILITY'!C18="Yes",'2_FINANCIALS'!D33,"N/A") -> N/A
A33: SECTION II – FINANCIAL DETAILS
A34: 1. Total Paid-Up Capital
A35: Sr. | B35: Item No. | C35: Field Name (as per RBI FLAIR portal) | D35: Shares (Actuals) PY | E35: Shares (Actuals) FY | F35: Amount Auto-calc on portal
A36: 27 | B36: 1(a) | C36: Ordinary / Equity Shares | D36: ='2_FINANCIALS'!C27 -> 0 | E36: ='2_FINANCIALS'!D27 -> 0 | F36: Sec II 1.1a | G36: LIST OF SHAREHOLDER
A37: 28 | B37: 1(b) | C37: Participating Preference Shares | D37: =IF('1_APPLICABILITY'!C21="Yes",'2_FINANCIALS'!C29,"N/A") -> N/A | E37: =IF('1_APPLICABILITY'!C21="Yes",'2_FINANCIALS'!D29,"N/A") -> N/A | G37: LIST OF SHAREHOLDER
A38: 29 | B38: 1.2 | C38: Non-Participating Preference Shares | D38: =IF('1_APPLICABILITY'!C22="Yes",'2_FINANCIALS'!C31,"N/A") -> N/A | E38: =IF('1_APPLICABILITY'!C22="Yes",'2_FINANCIALS'!D31,"N/A") -> N/A | G38: LIST OF SHAREHOLDER
A39: 2. Non-Resident Holdings (No. of shares – Actuals)
A40: Sr. | B40: Item No. | C40: Field Name (as per RBI FLAIR portal) | D40: Shares PY | E40: Shares FY | F40: Category
A41: 30 | B41: 2.1.1 | C41: Foreign Individuals | D41: ='2_FINANCIALS'!C64 -> 0 | E41: ='2_FINANCIALS'!D64 -> 0 | G41: LIST OF SHAREHOLDER
A42: 31 | B42: 2.1.2 | C42: Foreign Companies | D42: ='2_FINANCIALS'!C65 -> 0 | E42: ='2_FINANCIALS'!D65 -> 0 | G42: LIST OF SHAREHOLDER
A43: 32 | B43: 2.1.3 | C43: Foreign Institutional Investors (FIIs) | D43: ='2_FINANCIALS'!C66 -> 0 | E43: ='2_FINANCIALS'!D66 -> 0 | G43: LIST OF SHAREHOLDER
A44: 33 | B44: 2.1.4 | C44: Foreign Venture Capital Investors (FVCIs) | D44: ='2_FINANCIALS'!C67 -> 0 | E44: ='2_FINANCIALS'!D67 -> 0 | G44: LIST OF SHAREHOLDER
A45: 34 | B45: 2.1.5 | C45: Foreign Trusts | D45: ='2_FINANCIALS'!C68 -> 0 | E45: ='2_FINANCIALS'!D68 -> 0 | G45: LIST OF SHAREHOLDER
A46: 35 | B46: 2.1.6 | C46: Foreign Private Equity Funds | D46: ='2_FINANCIALS'!C69 -> 0 | E46: ='2_FINANCIALS'!D69 -> 0 | G46: LIST OF SHAREHOLDER
A47: 36 | B47: 2.1.7 | C47: Foreign Pension / Provident Funds | D47: ='2_FINANCIALS'!C70 -> 0 | E47: ='2_FINANCIALS'!D70 -> 0 | G47: LIST OF SHAREHOLDER
A48: 37 | B48: 2.1.8 | C48: Sovereign Wealth Funds (SWF) | D48: ='2_FINANCIALS'!C71 -> 0 | E48: ='2_FINANCIALS'!D71 -> 0 | G48: LIST OF SHAREHOLDER
A49: 38 | B49: 2.1.9 | C49: Foreign Partnership / Proprietorship Firms | D49: ='2_FINANCIALS'!C72 -> 0 | E49: ='2_FINANCIALS'!D72 -> 0 | G49: LIST OF SHAREHOLDER
A50: 39 | B50: 2.1.10 | C50: Foreign Financial Institutions | D50: ='2_FINANCIALS'!C73 -> 0 | E50: ='2_FINANCIALS'!D73 -> 0 | G50: LIST OF SHAREHOLDER
A51: 40 | B51: 2.1.11 | C51: NRIs / PIOs | D51: ='2_FINANCIALS'!C74 -> 0 | E51: ='2_FINANCIALS'!D74 -> 0 | G51: LIST OF SHAREHOLDER
A52: 41 | B52: 2.1 | C52: TOTAL NR Equity & Part.Pref Shares (auto) | D52: ='2_FINANCIALS'!C76 -> 0 | E52: ='2_FINANCIALS'!D76 -> 0 | G52: LIST OF SHAREHOLDER + FINANCIALS
A53: 42 | B53: 2.2 | C53: NR Non-Participating Preference Shares | D53: =IF('1_APPLICABILITY'!C22="Yes",'2_FINANCIALS'!C75,"N/A") -> N/A | E53: =IF('1_APPLICABILITY'!C22="Yes",'2_FINANCIALS'!D75,"N/A") -> N/A | G53: LIST OF SHAREHOLDER
A54: 43 | B54: 2.3 | C54: NR Equity & Part.Pref % (auto on portal) | D54: → auto on portal | F54: Auto-calculated by FLAIR
A55: 3. Profit & Loss Account (₹ Lakhs)
A56: Sr. | B56: Item No. | C56: Field Name (as per RBI FLAIR portal) | D56: PY (₹ Lakhs) | E56: FY (₹ Lakhs) | F56: Source
A57: 44 | B57: 3.1 | C57: Profit (+) / Loss (–) Before Tax | D57: ='2_FINANCIALS'!C38 -> 0 | E57: ='2_FINANCIALS'!D38 -> 0 | F57: P&L Statement | G57: FINANCIALS
A58: 45 | B58: 3.2 | C58: Profit (+) / Loss (–) After Tax | D58: ='2_FINANCIALS'!C39 -> 0 | E58: ='2_FINANCIALS'!D39 -> 0 | G58: FINANCIALS
A59: 46 | B59: 3.3 | C59: Dividend (Interim + Final) | D59: ='2_FINANCIALS'!C40 -> 0 | E59: ='2_FINANCIALS'!D40 -> 0 | G59: FINANCIALS
A60: 47 | B60: 3.4 | C60: Tax on Dividend | D60: ='2_FINANCIALS'!C41 -> 0 | E60: ='2_FINANCIALS'!D41 -> 0 | G60: FINANCIALS
A61: 48 | B61: 3.5 | C61: Retained Profit (auto: PAT – Div) | D61: ='2_FINANCIALS'!C42 -> 0 | E61: ='2_FINANCIALS'!D42 -> 0 | G61: FINANCIALS
A62: 4. Reserves & Surplus and Net Worth (₹ Lakhs)
A63: 49 | B63: 4.1 | C63: Reserves & Surplus | D63: ='2_FINANCIALS'!C46 -> 0 | E63: ='2_FINANCIALS'!D46 -> 0 | F63: Balance Sheet | G63: FINANCIALS
A64: 50 | B64: 4.2 | C64: Of which: P&L Account Balance | D64: ='2_FINANCIALS'!C47 -> 0 | E64: ='2_FINANCIALS'!D47 -> 0 | G64: FINANCIALS
A65: 51 | B65: 4.3 | C65: Net Worth (auto: Paid-up Cap + R&S) | D65: ='2_FINANCIALS'!C48 -> 0 | E65: ='2_FINANCIALS'!D48 -> 0 | G65: FINANCIALS
A66: 5. Sales & Purchases (₹ Lakhs)
A67: 52 | B67: 5.1 | C67: Domestic Sales | D67: ='2_FINANCIALS'!C51 -> 0 | E67: ='2_FINANCIALS'!D51 -> 0 | F67: P&L / Revenue schedule | G67: INPUT FROM COMPANY
A68: 53 | B68: 5.2 | C68: Exports | D68: ='2_FINANCIALS'!C52 -> 0 | E68: ='2_FINANCIALS'!D52 -> 0 | G68: INPUT FROM COMPANY
A69: 54 | B69: 5.3 | C69: Total Sales (auto) | D69: ='2_FINANCIALS'!C53 -> 0 | E69: ='2_FINANCIALS'!D53 -> 0 | G69: FINANCIALS
A70: 55 | B70: 5.4 | C70: Domestic Purchases | D70: ='2_FINANCIALS'!C54 -> 0 | E70: ='2_FINANCIALS'!D54 -> 0 | F70: P&L / Cost schedule | G70: INPUT FROM COMPANY
A71: 56 | B71: 5.5 | C71: Imports | D71: ='2_FINANCIALS'!C55 -> 0 | E71: ='2_FINANCIALS'!D55 -> 0 | G71: INPUT FROM COMPANY
A72: 57 | B72: 5.6 | C72: Total Purchase (auto) | D72: ='2_FINANCIALS'!C56 -> 0 | E72: ='2_FINANCIALS'!D56 -> 0 | G72: FINANCIALS
A73: 6. Employee Information
A74: 58 | B74: 6.1 | C74: No. of Employees on Payroll (actuals) | D74: ='2_FINANCIALS'!C59 -> 0 | E74: ='2_FINANCIALS'!D59 -> 0 | F74: HR records | G74: INPUT FROM COMPANY
A75: SECTION III – FOREIGN LIABILITIES (Shown based on Applicability)
A76: Block 1 – FDI ≥10% (per investor)
A77: Sr. | B77: Item No. | C77: Field Name (as per RBI FLAIR portal) | D77: End-March PY (₹L) | E77: End-March FY (₹L) | F77: Notes
A78: FDI Investor 1 – (shown only if FDI ≥10% = Yes in Applicability)
A79: 59 | B79: 1.a | C79: FDI1: No. of FDI investors (≥10%) | D79: =IF('1_APPLICABILITY'!C6="Yes",'2_FINANCIALS'!C72,"N/A") -> 0 | F79: Count only | G79: PREVIOUS FLA - UNLESS THERE IS CHANGE
A80: 60 | B80: 1.a.1 | C80: FDI1: Month of First FDI received | D80: =IF('1_APPLICABILITY'!C6="Yes",'2_FINANCIALS'!C82,"N/A") -> 0 | G80: PREVIOUS FLA
A81: 61 | B81: — | C81: FDI1: Year of First FDI received | D81: =IF('1_APPLICABILITY'!C6="Yes",'2_FINANCIALS'!C83,"N/A") -> 0 | G81: PREVIOUS FLA
A82: 62 | B82: — | C82: FDI1: Investor Name | D82: =IF('1_APPLICABILITY'!C6="Yes",'2_FINANCIALS'!C73,"N/A") -> 0 | G82: PREVIOUS FLA
A83: 63 | B83: — | C83: FDI1: Country of Investor | D83: =IF('1_APPLICABILITY'!C6="Yes",'2_FINANCIALS'!C74,"N/A") -> 0 | G83: PREVIOUS FLA
A84: 64 | B84: — | C84: FDI1: Equity & Part.Pref % holding | D84: =IF('1_APPLICABILITY'!C6="Yes",'2_FINANCIALS'!C75,"N/A") -> N/A – set applicability to Yes | E84: =IF('1_APPLICABILITY'!C6="Yes",'2_FINANCIALS'!D75,"N/A") -> N/A – set applicability to Yes | G84: FORMULA
A85: 65 | B85: 1.b | C85: FDI1: Equity & Part.Pref Capital | D85: =IF('1_APPLICABILITY'!C6="Yes",'2_FINANCIALS'!C76,"N/A") -> 0 | E85: =IF('1_APPLICABILITY'!C6="Yes",'2_FINANCIALS'!D76,"N/A") -> 0
A86: 66 | B86: 1.1 | C86: FDI1: Liabilities to Direct Investor (NW × %) | D86: =IF('1_APPLICABILITY'!C16="Yes",'2_FINANCIALS'!C77,"N/A") -> N/A | E86: =IF('1_APPLICABILITY'!C16="Yes",'2_FINANCIALS'!D77,"N/A") -> N/A | G86: FINANCIALS + FORMULA
A87: 67 | B87: 1.2 | C87: FDI1: Claims on Direct Investor | D87: =IF('1_APPLICABILITY'!C16="Yes",'2_FINANCIALS'!C78,"N/A") -> N/A | E87: =IF('1_APPLICABILITY'!C16="Yes",'2_FINANCIALS'!D78,"N/A") -> N/A | G87: FINANCIALS
A88: 68 | B88: 2.1 | C88: FDI1: Other Capital – Liabilities (trade payables, ECB, CCDs) | D88: =IF('1_APPLICABILITY'!C6="Yes",'2_FINANCIALS'!C79,"N/A") -> 0 | E88: =IF('1_APPLICABILITY'!C6="Yes",'2_FINANCIALS'!D79,"N/A") -> 0 | G88: FINANCIALS
A89: 69 | B89: 2.2 | C89: FDI1: Other Capital – Claims (trade receivables) | D89: =IF('1_APPLICABILITY'!C6="Yes",'2_FINANCIALS'!C80,"N/A") -> 0 | E89: =IF('1_APPLICABILITY'!C6="Yes",'2_FINANCIALS'!D80,"N/A") -> 0 | G89: FINANCIALS
A90: 70 | B90: 3 | C90: FDI1: Disinvestments in India during the year | D90: =IF('1_APPLICABILITY'!C23="Yes",'2_FINANCIALS'!C81,"N/A") -> N/A | E90: =IF('1_APPLICABILITY'!C23="Yes",'2_FINANCIALS'!D81,"N/A") -> N/A | G90: FINANCIALS
A91: FDI Investor 2 – (shown only if FDI ≥10% = Yes in Applicability)
A92: 71 | B92: 1.a | C92: FDI2: No. of FDI investors (≥10%) | D92: =IF('1_APPLICABILITY'!C6="Yes",'2_FINANCIALS'!C72,"N/A") -> 0 | F92: Count only | G92: PREVIOUS FLA - UNLESS THERE IS CHANGE
A93: 72 | B93: 1.a.1 | C93: FDI2: Month of First FDI received | D93: =IF('1_APPLICABILITY'!C6="Yes",'2_FINANCIALS'!C94,"N/A") -> 0 | G93: PREVIOUS FLA
A94: 73 | B94: — | C94: FDI2: Year of First FDI received | D94: =IF('1_APPLICABILITY'!C6="Yes",'2_FINANCIALS'!C95,"N/A") -> 0 | G94: PREVIOUS FLA
A95: 74 | B95: — | C95: FDI2: Investor Name | D95: =IF('1_APPLICABILITY'!C6="Yes",'2_FINANCIALS'!C85,"N/A") -> 0 | G95: PREVIOUS FLA
A96: 75 | B96: — | C96: FDI2: Country of Investor | D96: =IF('1_APPLICABILITY'!C6="Yes",'2_FINANCIALS'!C86,"N/A") -> N/A – set applicability to Yes | G96: PREVIOUS FLA
A97: 76 | B97: — | C97: FDI2: Equity & Part.Pref % holding | D97: =IF('1_APPLICABILITY'!C6="Yes",'2_FINANCIALS'!C87,"N/A") -> N/A – set applicability to Yes | E97: =IF('1_APPLICABILITY'!C6="Yes",'2_FINANCIALS'!D87,"N/A") -> N/A – set applicability to Yes
A98: 77 | B98: 1.b | C98: FDI2: Equity & Part.Pref Capital | D98: =IF('1_APPLICABILITY'!C6="Yes",'2_FINANCIALS'!C88,"N/A") | E98: =IF('1_APPLICABILITY'!C6="Yes",'2_FINANCIALS'!D88,"N/A")
A99: 78 | B99: 1.1 | C99: FDI2: Liabilities to Direct Investor ( NW × %) | D99: =IF('1_APPLICABILITY'!C16="Yes",'2_FINANCIALS'!C89,"N/A") -> N/A | E99: =IF('1_APPLICABILITY'!C16="Yes",'2_FINANCIALS'!D89,"N/A") -> N/A | G99: FINANCIALS + FORMULA
A100: 79 | B100: 1.2 | C100: FDI2: Claims on Direct Investor (Reverse Invest.) | D100: =IF('1_APPLICABILITY'!C16="Yes",'2_FINANCIALS'!C90,"N/A") -> N/A | E100: =IF('1_APPLICABILITY'!C16="Yes",'2_FINANCIALS'!D90,"N/A") -> N/A | G100: FINANCIALS
...

Sheet 4_VALIDATION
A1: FLA RETURN – VALIDATION CHECKS & FILING READINESS
A2: All checks below must be ✅ PASS before filing. Fix errors in '2_FINANCIALS' sheet.
A3: # | B3: Rule | C3: Check Description | D3: Current Value / Detail | E3: Result | F3: How to Fix
A4: 1 | B4: RBI-001 | C4: Paid-up Capital cannot be zero | D4: =TEXT('2_FINANCIALS'!D25*'2_FINANCIALS'!D26/100000,"#,##0.00")&" lakhs" -> 0.00 lakhs | E4: =IF('2_FINANCIALS'!D25*'2_FINANCIALS'!D26>0,"✅ PASS","❌ FAIL – Capital is zero") -> ❌ FAIL – Capital is zero | F4: Enter equity share count and face value in Financials sheet
A5: 2 | B5: RBI-002 | C5: Net Worth = Paid-up Capital + Reserves & Surplus (verify match) | D5: =TEXT('2_FINANCIALS'!D57,"#,##0.00")&" vs expected: "&TEXT(('2_FINANCIALS'!D25*'2_FINANCIALS'!D26)/100000+'2_FINANCIALS'!D55,"#,##0.00") -> 0.00 vs expected: 0.00 | E5: =IF(ABS('2_FINANCIALS'!D57-(('2_FINANCIALS'!D25*'2_FINANCIALS'!D26)/100000+'2_FINANCIALS'!D55))<1,"✅ PASS","⚠️ CHECK – Net Worth formula mismatch") -> ✅ PASS | F5: Verify R&S and share data in Financials. Net Worth = (Eq.Shares × FV)/1L + Reserves
A6: 3 | B6: RBI-003 | C6: Retained Profit = PAT minus Dividend | D6: =TEXT('2_FINANCIALS'!D53,"#,##0.00")&" (PAT "&TEXT('2_FINANCIALS'!D50,"0")&" – Div "&TEXT('2_FINANCIALS'!D51,"0")&")" -> 0.00 (PAT 0 – Div 0) | E6: =IF(ABS('2_FINANCIALS'!D53-('2_FINANCIALS'!D50-'2_FINANCIALS'!D51))<0.01,"✅ PASS","❌ FAIL") -> ✅ PASS | F6: Check PAT, Dividend in P&L section of Financials
A7: 4 | B7: RBI-004 | C7: Total Sales = Domestic Sales + Exports | D7: =TEXT('2_FINANCIALS'!D62,"#,##0")&" = "&TEXT('2_FINANCIALS'!D60,"#,##0")&" + "&TEXT('2_FINANCIALS'!D61,"#,##0") -> 0 = 0 + 0 | E7: =IF(ABS('2_FINANCIALS'!D62-('2_FINANCIALS'!D60+'2_FINANCIALS'!D61))<0.01,"✅ PASS","❌ FAIL") -> ✅ PASS | F7: Check Domestic Sales and Exports in Financials
A8: 5 | B8: RBI-005 | C8: Total Purchase = Domestic Purchase + Imports | D8: =TEXT('2_FINANCIALS'!D65,"#,##0")&" = "&TEXT('2_FINANCIALS'!D63,"#,##0")&" + "&TEXT('2_FINANCIALS'!D64,"#,##0") -> 0 = 0 + 0 | E8: =IF(ABS('2_FINANCIALS'!D65-('2_FINANCIALS'!D63+'2_FINANCIALS'!D64))<0.01,"✅ PASS","❌ FAIL") -> ✅ PASS | F8: Check Domestic Purchase and Imports in Financials
A9: 6 | B9: RBI-006 | C9: NR equity % sum (Block1 FDI + Block2 DI + Block3 PI) should not exceed 100% | D9: =TEXT('2_FINANCIALS'!C75,"0.0")&"% + (other blocks) ≤ 100%" -> N/A – set applicability to Yes% + (other blocks) ≤ 100% | E9: =IF('2_FINANCIALS'!C75<=100,"✅ PASS","❌ FAIL – Total NR% >100") -> ❌ FAIL – Total NR% >100 | F9: Check FDI investor % in Financials – total cannot exceed 100%
A10: 7 | B10: RBI-007 | C10: FDI ≥10% selected – at least one investor name must be entered | D10: =IF('1_APPLICABILITY'!C6="Yes","Investor 1: "&'2_FINANCIALS'!C73,"Not applicable") -> Investor 1: 0 | E10: =IF('1_APPLICABILITY'!C6="No","✅ N/A",IF('2_FINANCIALS'!C73="","❌ FAIL – Enter investor name","✅ PASS")) -> ✅ PASS | F10: Enter FDI investor name in Financials > Section III > FDI Investor 1
A11: 8 | B11: RBI-008 | C11: If Listed = Yes, market value per share must be entered | D11: =IF('1_APPLICABILITY'!C18="Yes",TEXT('2_FINANCIALS'!D31,"#,##0.00"),"Not listed") -> Not listed | E11: =IF('1_APPLICABILITY'!C18="No","✅ N/A",IF('2_FINANCIALS'!D31=0,"❌ FAIL – Enter market value","✅ PASS")) -> ✅ N/A | F11: Enter market price per share (BSE/NSE closing price on 31-March) in Financials
A12: 9 | B12: RBI-009 | C12: ODI ≥10% selected – exchange rate must be non-zero | D12: =IF('1_APPLICABILITY'!C11="Yes","Exchange rate entered: check Financials Sec IV","Not applicable") -> Exchange rate entered: check Financials Sec IV | E12: =IF('1_APPLICABILITY'!C11="No","✅ N/A","⚠️ Verify exchange rate in Financials Sec IV") -> ⚠️ Verify exchange rate in Financials Sec IV | F12: Enter exchange rate (₹ per FC unit) for each DIE in Financials Section IV
A13: 10 | B13: RBI-010 | C13: ECB selected – loan amount must be non-zero | D13: =IF('1_APPLICABILITY'!C17="Yes",TEXT('2_FINANCIALS'!D139,"#,##0.00")&" lakhs","Not applicable") -> 0.00 lakhs | E13: =IF('1_APPLICABILITY'!C17="No","✅ N/A",IF('2_FINANCIALS'!D139=0,"❌ FAIL – Enter ECB amount","✅ PASS")) -> ❌ FAIL – Enter ECB amount | F13: Enter ECB/loan amount in Financials > Section III > Block 4 > Loans
A14: 11 | B14: RBI-011 | C14: Reverse Investment selected – claims on FDI investor must be entered | D14: =IF('1_APPLICABILITY'!C16="Yes",TEXT('2_FINANCIALS'!D78,"#,##0.00"),"Not applicable") -> Not applicable | E14: =IF('1_APPLICABILITY'!C16="No","✅ N/A",IF('2_FINANCIALS'!D78=0,"⚠️ CHECK – Claims on investor is zero","✅ PASS")) -> ✅ N/A | F14: Enter Claims on Direct Investor (1.2) in FDI Investor 1 block of Financials
A15: 12 | B15: RBI-012 | C15: Applicability completeness – all mandatory flags set | D15: =COUNTIF('1_APPLICABILITY'!C6:C23,"Yes")&" applicable | "&COUNTIF('1_APPLICABILITY'!C6:C23,"No")&" not applicable" -> 5 applicable | 11 not applicable | E15: =IF(COUNTA('1_APPLICABILITY'!C6:C23)=18,"✅ All flags set","⚠️ "&(18-COUNTA('1_APPLICABILITY'!C6:C23))&" flags not set") -> ⚠️ 2 flags not set | F15: Complete all Yes/No flags in the Applicability sheet
A17: FILING READINESS SCORE → | E17: =COUNTIF(E4:E16,"✅*")&"/"&COUNTA(E4:E16)&" checks passed" -> 7/12 checks passed

Sheet ANNEX – NIC Codes
A1: NIC 2008 Division Description | B1: NIC Code
A2: Crop and animal production, hunting and related service activities | B2: 1
A3: Forestry and logging | B3: 2
A4: Fishing and aquaculture | B4: 3
A5: Mining of coal and lignite | B5: 5
A6: Extraction of crude petroleum and natural gas | B6: 6
A7: Mining of metal ores | B7: 7
A8: Other mining and quarrying | B8: 8
A9: Manufacture of food products | B9: 10
A10: Manufacture of beverages | B10: 11
A11: Manufacture of tobacco products | B11: 12
A12: Manufacture of textiles | B12: 13
A13: Manufacture of wearing apparel | B13: 14
... A42: Human health activities | B42: 86
