Workbook
Name \a: #N/A
Name \B: #REF!
Name \B: #REF!
Name \C: #REF!
Name \C: #REF!
Name \e: #N/A
Name \m: #N/A
Name \P: #REF!
Name \P: #REF!
Name \q: #N/A
Name \x: #REF!
Name \x: #REF!
Name \y: #REF!
Name \y: #REF!
Name \z: #REF!
Name \z: #REF!
Name _: #REF!
Name _.ignore9._: #REF!
Name ___????: #REF!
Name ___?????????: #REF!
Name ___??_???: #REF!
Name ___?_??: #REF!
Name _________?: #REF!
Name ________a2: #REF!
Name _______UCE08: #REF!
Name _______UCE09: #REF!
Name _______UCE10: #REF!
Name _______UCE11: #REF!
Name _______UCE12: #REF!
Name _______UCE13: #REF!
Name _______UCE14: #REF!
Name _______UCE15: #REF!
Name _______UCE16: #REF!
Name _______UCE17: #REF!
Name _______UCE18: #REF!
Name _______UCE19: #REF!
Name _______UCE20: #REF!
Name _______UCE21: #REF!
Name _______UCE22: #REF!
Name _______UCE23: #REF!
Name _______UCE24: #REF!
Name _______UCE25: #REF!
Name _______UCE26: #REF!
Name _______UCE27: #REF!
Name _______UCE28: #REF!
Name _______UCE29: #REF!
Name _______UCE30: #REF!
Name _______UCE31: #REF!
Name _______UCE32: #REF!
Name _______UCE33: #REF!
Name _______UCE34: #REF!
Name _______UCE35: #REF!
Name _______UCE36: #REF!
Name _______UCE37: #REF!
Name _______UCE38: #REF!
Name _______UCE39: #REF!
Name _______UCE40: #REF!
Name ______UCE01: #REF!
Name ______UCE02: #REF!
Name ______UCE03: #REF!

Sheet Financial Statements
A2: MARKETSOF1 ANALYTICAL MARKETING SERVICES PRIVATE LIMITED
A3: CIN: U72501TN2019PTC129911
A5: Balance Sheet as on March 31, 2026
A6: (All amounts are in thousands Indian Rupees, unless otherwise stated)
G7: ( Amount in Rs. )
A8: Particulars | D8: Note No. | E8: As at 31st March 2026 | F8: As at 31st March 2025 | G8: As at 31st March 2023
A9: I | B9: EQUITY AND LIABILITIES
A10: 1. | B10: Shareholders' Funds
B11: a. | C11: Share Capital | D11: ='3-15'!A9 -> 3 | E11: ='3-15'!E15 -> 100000 | F11: ='3-15'!F15 -> 100000 | G11: ='3-15'!#REF! -> #REF! | J11: =E11-F11 -> 0
B12: b. | C12: Reserves and Surplus | D12: ='3-15'!A44 -> 4 | E12: =+'3-15'!E50 -> 55465687 | F12: =+'3-15'!F50 -> 44411901 | G12: =+'3-15'!#REF! -> #REF! | J12: =E12-F12 -> 11053787
B13: c. | C13: Money received against share warrants | E13: 0 | F13: 0 | G13: 0
A14: 2. | B14: Share application money pending allotment | E14: 0 | F14: 0 | G14: 0
A16: 3. | B16: Non-Current Liabilities
B17: a. | C17: Long-term borrowings | E17: 0 | F17: 0 | G17: ='3-15'!#REF! -> #REF!
B18: b. | C18: Deferred tax liabilities (Net) | D18: =D12+1 -> 5 | E18: ='3-15'!E65 -> 19661.91 | F18: ='3-15'!F65 -> 64525.59 | G18: 0 | J18: =E18-F18 -> -44863.68
B19: c. | C19: Other Long term liabilities | E19: 0 | F19: 0 | G19: ='3-15'!#REF! -> #REF!
B20: d. | C20: Long Term Provisions | D20: =D18+1 -> 6 | E20: ='3-15'!E72 -> 4470006 | F20: ='3-15'!F72 -> 79164 | G20: ='3-15'!#REF! -> #REF! | J20: =E20-F20 -> 4390842
A22: 4. | B22: Current Liabilities
B23: a. | C23: Short-term borrowings | E23: 0 | F23: 0 | G23: ='3-15'!#REF! -> #REF!
B24: b. | C24: Trade payables | D24: =D20+1 -> 7 | G24: =+'3-15'!#REF! -> #REF! | H24: =+#REF!-G24 -> #REF!
C25: -total outstanding dues of micro and small enterprises | E25: ='Ageing schedule'!G13 -> 0 | F25: ='Ageing schedule'!H13 -> 0 | G25: ='Ageing schedule'!J13 -> 0
C26: -total outstanding dues of creditors other than micro and small enterprises | E26: =+'3-15'!E78 -> 31351590 | F26: =+'3-15'!F78-2 -> 32229650 | G26: ='Ageing schedule'!J14 -> 0 | J26: =E26-F26 -> -878059.5 | K26: a
B27: c. | C27: Other current liabilities | D27: =D24+1 -> 8 | E27: ='3-15'!E88-0.5 -> 29470755 | F27: ='3-15'!F88 -> 22980524 | G27: ='3-15'!#REF! -> #REF! | H27: =+#REF!-G27+11000000 -> #REF! | J27: =E27-F27 -> 6490230.9 | K27: a
B28: d. | C28: Short - term provisions | D28: =D27+1 -> 9 | E28: ='3-15'!E95 -> 55650000 | F28: ='3-15'!F95 -> 8450000 | G28: ='3-15'!#REF! -> #REF! | J28: =E28-F28 -> 47200000
C30: Total | E30: =SUM(E11:E28)+0.5 -> 1.765277e+08 | F30: =SUM(F11:F28)+0.5 -> 1.0831576e+08 | G30: =SUM(G11:G28) -> #REF!
A32: II | B32: ASSETS
A33: 1. | B33: Non-current assets
B34: a. | C34: Property, Plant & Equipments and Intangible assets | D34: =D28+1 -> 10
C35: (i) Property, Plant and Equipment | E35: ='10'!K24 -> 5439341.5 | F35: ='10'!K25 -> 4478032.3 | G35: 1572250 | H35: =+#REF!-G35 -> #REF! | J35: =E35-F35 -> 961309.17
C36: (ii) Intangible Assets | E36: ='10'!J30 -> 0 | F36: 0 | G36: 0 | H36: =+#REF!+#REF! -> #REF!
C37: (iii) Capital Work in Progress | E37: 0 | F37: 0 | G37: 0
B38: b. | C38: Non Current Investments | E38: 0 | F38: 0 | G38: ='3-15'!#REF! -> #REF!
B39: c. | C39: Deferred tax assets (net) | D39: =D18 -> 5 | E39: 0 | F39: 0 | G39: =-'3-15'!#REF! -> #REF!
B40: d. | C40: Long term loans and advances | D40: =D34+1 -> 11 | E40: ='3-15'!E103 -> 10709306 | F40: ='3-15'!F103 -> 6408655 | G40: ='3-15'!#REF! -> #REF! | H40: =+#REF!-G40 -> #REF! | J40: =E40-F40 -> 4300651 | K40: a
B41: e. | C41: Other Non Current Assets | E41: 0 | F41: 0 | G41: ='3-15'!#REF! -> #REF!
A43: 2. | B43: Current Assets
B44: a. | C44: Current Investments | E44: 0 | F44: 0 | G44: ='3-15'!#REF! -> #REF!
B45: b. | C45: Inventories | E45: 0 | F45: 0 | G45: ='3-15'!#REF! -> #REF!
B46: c. | C46: Trade Receivables | D46: =D40+1 -> 12 | E46: ='3-15'!E110 -> 4317419.3 | F46: ='3-15'!F110 -> 1242797.4 | G46: ='3-15'!#REF! -> #REF! | H46: =+#REF!-G46 -> #REF! | J46: =E46-F46 -> 3074621.8 | K46: a
B47: d. | C47: Cash and Bank Balance | D47: =D46+1 -> 13 | E47: ='3-15'!E119 -> 66610087 | F47: ='3-15'!F119 -> 81786790 | G47: ='3-15'!#REF! -> #REF! | H47: =+#REF!-G47 -> #REF! | J47: =E47-F47 -> -15176703
B48: e. | C48: Short Term Loans and Advances | D48: =D47+1 -> 14 | E48: ='3-15'!E125 -> 80942.1 | F48: ='3-15'!F125 -> 174506.18 | G48: ='3-15'!#REF! -> #REF! | H48: =+#REF!-G48 -> #REF! | J48: =E48-F48 -> -93564.08 | K48: a
B49: f. | C49: Other Current Assets | D49: =D48+1 -> 15 | E49: ='3-15'!E134 -> 89370605 | F49: ='3-15'!F134 -> 14224983 | G49: ='3-15'!#REF! -> #REF! | J49: =E49-F49 -> 75145622 | K49: a
E50: =SUM(E35:E49) -> 1.765277e+08 | F50: =SUM(F35:F49) -> 1.0831576e+08 | G50: =SUM(G35:G49) -> #REF! | H50: =#REF!-#REF! -> #REF! | I50: =E30-E50 -> -0.15735745 | J50: =F30-F50 -> -0.068486094
A51: Accompanying notes form part of the financial statements | D51: 1-41
A53: In accordance with our report of even date attached
A55: for M.R.NARAIN & Co., | D55: For and on behalf of the Board of Directors
A56: Chartered Accountants FRN 002330S | D56: MARKETSOF1 ANALYTICAL MARKETING SERVICES PRIVATE LIMITED
A61: M. Prabakar | D61: Mahadevan Jayaraman | F61: Deepa Mahadevan | G61: MAHADEVAN JAYARAMAN
A62: Partner | D62: Director | F62: Director | G62: Director
A63: M.No 201987 | D63: DIN: 07032354 | F63: DIN: 07032485 | G63: DIN:07032354
A65: UDIN:
A67: Place: Chennai
A68: Date:
A70: =A2 -> MARKETSOF1 ANALYTICAL MARKETING SERVICES PRIVATE LIMITED
A71: =A3 -> CIN: U72501TN2019PTC129911
A73: Statement of Profit & Loss for the Year ended on March 31, 2026
A74: (All amounts are in thousands Indian Rupees, unless otherwise stated)
A76: Particulars | D76: Note No. | E76: For the year ended 31st March, 2026 | F76: For the year ended 31st March, 2025 | G76: =G8 -> As at 31st March 2023
A78: I | C78: Revenue from Operations | D78: =D49+1 -> 16 | E78: ='16-23'!C14 -> 6.0174095e+08 | F78: ='16-23'!D14 -> 453621097 | G78: ='16-23'!#REF! -> #REF!
A79: II | C79: Other Income | D79: =D78+1 -> 17 | E79: ='16-23'!C34 -> 11818590 | F79: ='16-23'!D34 -> 3612471.9 | G79: ='16-23'!#REF! -> #REF!
A80: III | B80: Total Income | E80: =SUM(E78:E79) -> 6.1355954e+08 | F80: =SUM(F78:F79) -> 4.5723357e+08 | G80: =SUM(G78:G79) -> #REF!
A82: IV | B82: EXPENSES
C83: Operating Expenses | D83: =D79+1 -> 18 | E83: ='16-23'!C42 -> 2.2592241e+08 | F83: ='16-23'!D42 -> 2.3650187e+08 | G83: ='16-23'!#REF! -> #REF!
C84: Employee Benefits Expenses | D84: =D83+1 -> 19 | E84: ='16-23'!C51 -> 2.3532725e+08 | F84: ='16-23'!D51 -> 1.3530534e+08 | G84: ='16-23'!#REF! -> #REF!
C85: Finance Cost | D85: =D84+1 -> 20 | E85: ='16-23'!C62 -> 18687.8 | F85: ='16-23'!D62 -> 3342.85 | G85: ='16-23'!#REF! -> #REF!
C86: Depreciation and Amortization Expense | D86: =D85+1 -> 21 | E86: ='16-23'!C68 -> 2045608.1 | F86: ='10'!H25 -> 1363387.2 | G86: 329381.26
C87: Other Expenses | D87: =D86+1 -> 22 | E87: ='16-23'!C95 -> 1.3408909e+08 | F87: ='16-23'!D95 -> 52687538 | G87: ='16-23'!#REF! -> #REF!
E88: =SUM(E83:E87) -> 5.9740305e+08 | F88: =SUM(F83:F87) -> 4.2586148e+08 | G88: =SUM(G83:G87) -> #REF!
A91: V | B91: Profit before exceptional and extraordinary items and tax | E91: =E80-E88 -> 16156488 | F91: =F80-F88 -> 31372090 | G91: =G80-G88-1 -> #REF!
A93: VI | C93: Exceptional items | D93: 25 | E93: =SUMIF(Table2[FS Subgroup],C93,Table2[Adjusted balance as on 31-03-2026]) -> 0 | F93: 0 | G93: 0
A94: VII | B94: Profit before extraordinary items and tax | E94: =E91-E93 -> 16156488 | F94: =F91-F93 -> 31372090 | G94: =G91-G93 -> #REF! | I94: =F94-F79 -> 27759619
A95: VIII | C95: Extraordinary items | E95: 0 | F95: 0 | G95: 0
A97: IX | B97: Profit before tax | E97: =E94-E95 -> 16156488 | F97: =F94-F95 -> 31372090 | G97: =G94-G95 -> #REF!
A99: X | B99: Tax Expense
B100: a. | C100: Current Tax | D100: =D87+1 -> 23 | E100: ='16-23'!C101 -> 5147565.4 | F100: ='16-23'!D101 -> 8000000 | G100: 0
B101: b. | C101: Deferred Tax | E101: =-'3-15'!F65+'3-15'!E65 -> -44863.68 | F101: ='Deferred Tax'!C11 -> -10930.32
B102: c. | C102: Tax related to Previous years
E103: =SUM(E100:E102) -> 5102701.7 | F103: =SUM(F100:F102) -> 7989069.7 | G103: =SUM(G100:G102) -> 0
A105: XI | B105: Profit (Loss) for the period from continuing operations | E105: =E97-E103 -> 11053787 | F105: =F91-F103 -> 23383021 | G105: =G91-G103 -> #REF! | H105: -4923596.4
A107: XII | B107: Profit/(loss) from discontinuing operations | E107: 0 | F107: 0
A108: XIII | B108: Tax expense of discontinuing operations | E108: 0 | F108: 0
A109: XIV | B109: Profit/(loss) from Discontinuing operations (after tax) (XII-XIII) | E109: =E107-E108 -> 0 | F109: =F107-F108 -> 0
A111: XV | B111: Profit/ (Loss) after tax (XI + XIV) | E111: =E105+E109 -> 11053787 | F111: =F105+F109 -> 23383021
A113: XVI | B113: Earning per equity share of Rs. 10/- each
B114: a. | C114: Basic | E114: =E105/10000 -> 1105.3787 | F114: =F105/10000 -> 2338.3021 | G114: =G105/10000 -> #REF!
B115: b. | C115: Diluted | E115: =E105/10000 -> 1105.3787 | F115: =F105/10000 -> 2338.3021 | G115: =G105/10000 -> #REF!
A116: Accompanying notes form part of the financial statements | D116: =D51 -> 1-41
A118: In accordance with our report of even date attached
A120: for M.R.NARAIN & Co., | D120: For and on behalf of the Board of Directors
A121: Chartered Accountants FRN 002330S | D121: MARKETSOF1 ANALYTICAL MARKETING SERVICES PRIVATE LIMITED
A125: M. Prabakar | D125: Mahadevan Jayaraman | F125: Deepa Mahadevan | G125: MAHADEVAN JAYARAMAN
A126: Partner | D126: Director | F126: Director | G126: Director
A127: M.No 201987 | D127: DIN: 07032354 | F127: DIN: 07032485 | G127: DIN:07032354
A129: =A65 -> UDIN:
A131: Place: Chennai
A132: =A68 -> Date:
A134: MARKETSOF1 ANALYTICAL MARKETING SERVICES PRIVATE LIMITED
A135: CIN: U72501TN2019PTC129911
A137: Cash Flow Statement for the year ended as on March 31, 2026
A138: (All amounts are in thousands Indian Rupees, unless otherwise stated)
...

Sheet 1-2
B2: MARKETSOF1 ANALYTICAL MARKETING SERVICES PRIVATE LIMITED
B3: CIN: U72501TN2019PTC129911
B5: Notes to Financial Statements for the year ended March 31, 2026
B6: (All amounts are in thousands Indian Rupees, unless otherwise stated)
B9: 1. General Information
B11: MARKETSOF1 ANALYTICAL MARKETING SERVICES Pvt Ltd, having its registered office at Ram Nivas apart-7, 1st floor, old No.79, New No.82, DRT Ranga Road, Mylapore, Chennai-600004. The Subscribers to the Memorandum of association of this company are:- a. M1 Marketing Services Pvt Ltd – having 50% stake b. Jayaram K Iyer – having 50% stake
B13: 2. Summary of Significant Accounting Policies
B15: 2.1 Basis of Preparation
B17: These financial statements have been prepared in accordance with the generally accepted accounting principles in India under the historical cost convention on accrual basis. Pursuant to Section 133 of the Companies Act, 2013 read with Rule 7(1) of the Companies (Accounts) Rules, 2014, till the standards of accounting or any addendum thereto are prescribed by Central Government in consultation and recommendation of the National Financial Reporting Authority, the existing Accounting Standards notified under the Companies Act, 1956 shall continue to apply. Consequently, these financial statements have been prepared to comply in all material aspects with the Accounting Standards notified under Section 211(3C) of the Companies Act, 1956 [Companies (Accounting Standards) Rules, 2006, as amended] and other relevant provisions of the Companies Act, 2013.
B18: All assets and liabilities have been classified as current or non-current as per the Company’s normal operating cycle and other criteria set out in the Schedule III (Division I) to the Companies Act, 2013. Based on the nature of products and the time between the acquisition of assets for processing and their realisation in cash and cash equivalents, the Company has ascertained its operating cycle as 12 months for the purpose of current - non-current classification of assets and liabilities.
B20: 2.2 Use of Estimates
B22: The preparation of the financial statements in conformity with the accounting principles generally accepted in India requires the Management to make estimates and assumptions that affect the reported amount of assets and liabilities as of the Balance Sheet date, reported amount of revenues and expenses for the period and disclosure of contingent liabilities as of the Balance Sheet date. The estimates and assumptions used in the financial statements are based on Management’s evaluation of the relevant facts and circumstances as of the date of the financial statements. The actual results may differ from these estimates and the difference between the actual results and the estimates are recognised in the period in which the results are known/materialise.
... B119: Based on the nature of activities of the Company and the normal time between acquisition of assets and their realisation in cash or cash equivalents, the Company has determined its operating cycle as 12 months for the purpose of classification of its assets and liabilities as current and non-current.

Sheet 3-15
A1: MARKETSOF1 ANALYTICAL MARKETING SERVICES PRIVATE LIMITED
A2: CIN: U72501TN2019PTC129911
A4: Notes to Financial Statements for the year ended March 31, 2026
A5: (All amounts are in thousands Indian Rupees, unless otherwise stated)
A7: Note No. | B7: Particulars | E7: As at 31st March, 2026 | F7: As at 31st March, 2025
A9: 3 | B9: Share Capital
A10: =A9+0.1 -> 3.1 | B10: Authorized Share Capital
B11: 10,000 (Previous Year 10,000) Equity Shares of Rs. 10/- each. | E11: =-SUMIF(Table2[FS Subgroup],"Share Capital",Table2[Adjusted balance as on 31-03-2026]) -> 100000 | F11: =E11 -> 100000
A13: =A10+0.1 -> 3.2 | B13: Issued , Subscribed & Fully Paid up Capital
B14: 10,000 (Previous Year 10,000) Equity Shares of Rs. 10/- each. | E14: =E11 -> 100000 | F14: =E14 -> 100000
E15: =SUM(E14) -> 100000 | F15: =SUM(F14) -> 100000
A17: =A13+0.1 -> 3.3 | B17: Reconciliation Of Number of Shares
B18: Number Of Equity Shares as at the beginning of the Financial year | E18: 10000 | F18: 10000
B19: Add: Number of Shares Issued during the period | E19: 0 | F19: 0
B20: Number Of Equity Shares as at the end of the financial Years | E20: =SUM(E18:E19) -> 10000 | F20: =SUM(F18:F19) -> 10000
A22: =A17+0.1 -> 3.4 | B22: List of Shareholders holding more than 5% of Equity Shares of the company
B23: Name | C23: % of Shares | E23: Number of Shares | F23: Number of Shares
C24: 46112 | D24: 45747 | E24: 46112 | F24: 45747
B25: 5000 equity shares held by M1 Marketing Services Private Limited | C25: =E25/E$18 -> 0.5 | D25: =F25/F$18 -> 0.5 | E25: 5000 | F25: 5000
B26: 5000 equity shares held by Mr. Jayaram K Iyer | C26: =E26/E$18 -> 0.5 | D26: =F26/F$18 -> 0.5 | E26: 5000 | F26: 5000
A28: =A22+0.1 -> 3.5 | B28: Details of Shares held by promoters
B29: Promoter Name | E29: 2025-26
E30: No. of Shares | F30: % of total shares
B31: 5000 equity shares held by Mr. Jayaram K Iyer | E31: =E25 -> 5000 | F31: =C26 -> 0.5
B32: 5000 equity shares held by M1 Marketing Services Private Limited | E32: =E26 -> 5000 | F32: 0.5
B34: Promoter Name | E34: 2024-25
E35: No. of Shares | F35: % of total shares
B36: 5000 equity shares held by Mr. Jayaram K Iyer | E36: =E31 -> 5000 | F36: =F31 -> 0.5
B37: 5000 equity shares held by M1 Marketing Services Private Limited | E37: =E32 -> 5000 | F37: =F32 -> 0.5
A39: =A28+0.1 -> 3.6 | B39: Terms / Rights attached to Equity Shares
B40: The company has only one class of equity share having par value of Rs.10 per share. Each holder of the equity share is entilted to one vote per share. Whenever the company declares dividend it will be paid in Indian Rupees.
B41: In the event of liquidation of the Company, the holders of Equity Shares will be entitled to receive any of the remaining assets of the Company, after distribution of all preferential amounts. However, no such preferential amounts exist curently. The distribution will be in proportion to the number of Equity Shares held by the Shareholders.
A44: =A9+1 -> 4 | B44: Reserves & Surplus
B45: Surplus (Statement of Profit & Loss )
B46: Opening balance | E46: =-SUMIF(Table2[FS Subgroup],B46,Table2[Adjusted balance as on 31-03-2026]) -> 44411901 | F46: 21028880 | H46: ='Trial Balance'!C62+'3-15'!E46 -> 8820
B47: Add : Profit During the Year | E47: ='Financial Statements'!E105 -> 11053787 | F47: ='Financial Statements'!F105 -> 23383021
B48: Less : Loss during the year / Appropriations | E48: 0 | F48: 0
B50: Total | E50: =E46+E47-E48 -> 55465687 | F50: =F46+F47-F48 -> 44411901
A52: =A44+1 -> 5 | B52: Deferred Tax Liability/ Asset (Net)
A53: =A52+0.1 -> 5.1 | B53: Deferred Tax Liability
B54: Impact of WDV difference on Property, plant and equipment | E54: =-SUMIF(Table2[FS Subgroup],B54,Table2[Adjusted balance as on 31-03-2026]) -> 19661.91 | F54: ='Deferred Tax'!C9 -> 64525.59
B55: Others | E55: =-SUMIF(Table2[FS Subgroup],B55,Table2[Adjusted balance as on 31-03-2026]) -> 0 | F55: 0
B56: Gross deferred tax liability | E56: =SUM(E54:E55) -> 19661.91 | F56: =SUM(F54:F55) -> 64525.59
A58: =A53+0.1 -> 5.2 | B58: Deferred Tax Asset
B59: Opening balance | E59: =#REF! -> #REF! | F59: =#REF! -> #REF!
B60: During the Year | E60: 0 | F60: 0
B61: Impact of Provisions | E61: =-SUMIF(Table2[FS Subgroup],B61,Table2[Adjusted balance as on 31-03-2026]) -> 0 | F61: =-SUMIF(Table2[FS Subgroup],C61,Table2[Adjusted balance as on 31-03-2026]) -> 0
B62: Others | E62: =-SUMIF(Table2[FS Subgroup],B62,Table2[Adjusted balance as on 31-03-2026]) -> 0 | F62: =-SUMIF(Table2[FS Subgroup],C62,Table2[Adjusted balance as on 31-03-2026]) -> 0
A63: 5.2 | B63: Gross deferred tax asset | E63: =SUM(E61:E62) -> 0 | F63: =SUM(F61:F62) -> 0
B65: Net deferred tax liability | E65: =E56-E63 -> 19661.91 | F65: =F56-F63 -> 64525.59
A67: =A52+1 -> 6 | B67: Long Term Provisions
A68: =A67+0.1 -> 6.1 | B68: Provision for employee benefits
B69: Provision for gratuity | E69: =-SUMIF(Table2[FS Subgroup],B69,Table2[Adjusted balance as on 31-03-2026]) -> 1469911 | F69: 0
B70: Provision for leave benefits | E70: =-SUMIF(Table2[FS Subgroup],B70,Table2[Adjusted balance as on 31-03-2026]) -> 3000095 | F70: =-'TB 2025'!E44 -> 79164
B72: Total | E72: =SUM(E67:E70) -> 4470006 | F72: =SUM(F67:F70) -> 79164
A74: =A67+1 -> 7 | B74: Trade Payables
B75: -total outstanding dues of micro and small enterprises | E75: =-SUMIF(Table2[FS Subgroup],B75,Table2[Adjusted balance as on 31-03-2026]) -> 0 | F75: 0
B76: -total outstanding dues of creditors other than micro and small enterprises | E76: =-SUMIF(Table2[FS Subgroup],B76,Table2[Adjusted balance as on 31-03-2026]) -> 31351590 | F76: ='Ageing schedule'!J23 -> 32229652
B78: Total | E78: =SUM(E74:E76) -> 31351590 | F78: =SUM(F74:F76) -> 32229652
A80: =A74+1 -> 8 | B80: Other Current Liabilities
A81: =A80+0.1 -> 8.1 | B81: Statutory dues including provident fund and tax deducted at source | E81: =-SUMIF(Table2[FS Subgroup],B81,Table2[Adjusted balance as on 31-03-2026]) -> 8203548.3 | F81: ='Sub Schedule BS'!C17-F70 -> 4835549
A82: =A81+0.1 -> 8.2 | B82: Other payables (specify nature)
B83: Salary and Wages Payable | E83: =-SUMIF(Table2[FS Subgroup],B83,Table2[Adjusted balance as on 31-03-2026]) -> 14385984 | F83: =-'TB 2025'!E62 -> 9089952
B84: Director Remuneration Payable | E84: =-SUMIF(Table2[FS Subgroup],B84,Table2[Adjusted balance as on 31-03-2026]) -> 4967905 | F84: 0
B85: Other Employee Payable | E85: =-SUMIF(Table2[FS Subgroup],B85,Table2[Adjusted balance as on 31-03-2026]) -> 1225034.2 | F85: =-'TB 2025'!E54-'TB 2025'!E61 -> 759807
B86: Other Payable | E86: =-SUMIF(Table2[FS Subgroup],B86,Table2[Adjusted balance as on 31-03-2026]) -> 688283.64 | F86: =-'TB 2025'!E57-'TB 2025'!E53 -> 8295215.9
B88: Total | E88: =SUM(E81:E87) -> 29470755 | F88: =SUM(F81:F87) -> 22980524
A90: =A80+1 -> 9 | B90: Short Term Provisions
A91: =A90+0.1 -> 9.1 | B91: Provision for Taxation | E91: =-SUMIF(Table2[FS Subgroup],B91,Table2[Adjusted balance as on 31-03-2026]) -> 5200000 | F91: ='Financial Statements'!F100 -> 8000000
A92: =A91+0.1 -> 9.2 | B92: Provision for Audit fees | E92: =-SUMIF(Table2[FS Subgroup],B92,Table2[Adjusted balance as on 31-03-2026]) -> 450000 | F92: =-'TB 2025'!E56 -> 450000
A93: =A92+0.1 -> 9.3 | B93: Provision for Litigation and Court claim | C93: (Refer Note No. 39) | E93: =-SUMIF(Table2[FS Subgroup],B93,Table2[Adjusted balance as on 31-03-2026]) -> 50000000 | F93: 0
B95: Total | E95: =SUM(E91:E94) -> 55650000 | F95: =SUM(F91:F94) -> 8450000
A97: =A90+1+1 -> 11 | B97: Long Term Loans & Advances
A98: =A97+0.1 -> 11.1 | B98: Other loans and advances (Specify Nature)
B99: Security Deposit | E99: =SUMIF(Table2[FS Subgroup],B99,Table2[Adjusted balance as on 31-03-2026]) -> 8738521 | F99: ='Sub Schedule BS'!C37 -> 6201321
B100: Employee Advances | E100: =SUMIF(Table2[FS Subgroup],B100,Table2[Adjusted balance as on 31-03-2026]) -> 1970785 | F100: ='Sub Schedule BS'!C43 -> 207334
B103: Total | E103: =SUM(E98:E102) -> 10709306 | F103: =SUM(F98:F102) -> 6408655
A105: =A97+1 -> 12 | B105: Trade Receivables
A106: =A105+0.1 -> 12.1 | B106: Unsecured, Considered good
B107: -with related parties | E107: 0 | F107: 0
B108: -with others | E108: =SUMIF(Table2[FS Subgroup],B108,Table2[Adjusted balance as on 31-03-2026]) -> 4317419.3 | F108: 1242797.4
B110: Total | E110: =SUM(E106:E109) -> 4317419.3 | F110: =SUM(F106:F109) -> 1242797.4
A112: =A105+1 -> 13 | B112: Cash and cash equivalents
A113: =A112+0.1 -> 13.1 | B113: Balances with Banks
B114: - in current account | E114: =SUMIF(Table2[FS Subgroup],B114,Table2[Adjusted balance as on 31-03-2026]) -> 26073630 | F114: =+'Sub Schedule BS'!C46 -> 39235461
A115: =A113+0.1 -> 13.2 | B115: Cheques, drafts on hand | E115: 0 | F115: 0
A116: =A115+0.1 -> 13.3 | B116: Cash on hand | E116: =SUMIF(Table2[FS Subgroup],B116,Table2[Adjusted balance as on 31-03-2026]) -> 162254 | F116: 130808
A117: =A116+0.1 -> 13.4 | B117: Fixed Deposit with Bank | E117: =SUMIF(Table2[FS Subgroup],B117,Table2[Adjusted balance as on 31-03-2026])-E132 -> 40374203 | F117: =+'Sub Schedule BS'!C47-F131 -> 42420521
B119: Total | E119: =SUM(E113:E118) -> 66610087 | F119: =SUM(F113:F118) -> 81786790
A121: =A112+1 -> 14 | B121: Short term Loan & Advances
A122: =A121+0.1 -> 14.1 | B122: Others (Unsecured and considerd Good)
B123: Advances to Supplier | E123: =SUMIF(Table2[FS Subgroup],B123,Table2[Adjusted balance as on 31-03-2026]) -> 80942.1 | F123: =+'Sub Schedule BS'!C58 -> 174506.18
B125: Total | E125: =SUM(E122:E124) -> 80942.1 | F125: =SUM(F122:F124) -> 174506.18
A127: =A121+1 -> 15 | B127: Other Current Assets
A128: =A127+0.1 -> 15.1 | B128: Balance with Government Authorities | E128: =SUMIF(Table2[FS Subgroup],B128,Table2[Adjusted balance as on 31-03-2026]) -> 12300178 | F128: =+'Sub Schedule BS'!C69 -> 8656496.9
A129: =A128+0.1 -> 15.2 | B129: Prepaid Expenses | E129: =SUMIF(Table2[FS Subgroup],B129,Table2[Adjusted balance as on 31-03-2026]) -> 0 | F129: =24422.41+372301.37 -> 396723.78
A130: =A129+0.1 -> 15.3 | B130: Accrued Revenue | E130: =SUMIF(Table2[FS Subgroup],B130,Table2[Adjusted balance as on 31-03-2026]) -> 26920883 | F130: 5000000
A131: =A130+0.1 -> 15.4 | B131: Accrued Interest on FD | E131: =SUMIF(Table2[FS Subgroup],B131,Table2[Adjusted balance as on 31-03-2026]) -> 149543.83 | F131: ='TB 2025'!E163 -> 171762.5
A132: =A131+0.1 -> 15.5 | B132: Court Claim Fixed Deposit (Refer Note No. 39) | E132: =50000000 -> 50000000 | F132: 0
B134: Total | E134: =SUM(E128:E133) -> 89370605 | F134: =SUM(F128:F133) -> 14224983

Sheet Sub Schedule BS
B2: MARKETSOF1 ANALYTICAL MARKETING SERVICES PRIVATE LIMITED
B3: Notes forming part of Financial Statements as on March 31, 2025
C4: For the year ended 31.03.2025 | D4: For the year ended 31.03.2024 | E4: For the year ended 31.03.2023
B6: a) Trade Payable
B7: Trade Payables | C7: ='Ageing schedule'!J12 -> 31351590 | D7: ='Ageing schedule'!J23 -> 32229652 | E7: ='Ageing schedule'!J20 -> 32229652
C8: =+SUM(C7) -> 31351590 | D8: =+SUM(D7) -> 32229652 | E8: =+SUM(E7) -> 32229652
B10: b) Statutory dues including provident fund and tax deducted at source
B11: - TDS Payable | C11: 3111621 | D11: =#REF! -> #REF! | E11: 1367262
B12: - Professional Tax Payable | C12: 107180 | D12: =#REF! -> #REF! | E12: 69427
B13: - ESI Payable | C13: 220927 | D13: =#REF! -> #REF! | E13: 164547
B14: - GST Payable | C14: -132905 | D14: =#REF! -> #REF! | E14: 997540
B15: - PF Payable | C15: 1528726 | D15: =#REF! -> #REF! | E15: 868018
B16: - Earned leave Encashment Payable | C16: 79164 | D16: =#REF! -> #REF!
C17: =SUM(C11:C16) -> 4914713 | D17: =SUM(D11:D16) -> #REF! | E17: =SUM(E11:E15) -> 3466794
B19: c) Other Liabilities
B20: - Accounts payable | C20: =+'Groupings BS'!C10 -> 759807 | D20: =+'Groupings BS'!D10 -> #REF! | E20: 322821
B21: - Accrued expense | C21: 0 | D21: 0 | E21: 0
B22: - Salary Payable | C22: 9089952 | D22: =#REF! -> #REF! | E22: 4798580
B23: - Provision for Audit Fees | C23: 450000 | E23: 100000
B24: - HDFC Credit Card | C24: 295215.86 | D24: =#REF! -> #REF! | E24: 70760.7
B25: - Loan from director
B26: - Provision for COVID-19
B27: - Provision for Current Tax | C27: 8000000 | D27: =#REF! -> #REF! | E27: 103840
C29: =SUM(C20:C28) -> 18594975 | D29: =SUM(D20:D28) -> #REF! | E29: =SUM(E20:E28) -> 5396001.7
B32: e) Security Deposit
B33: Rent Advance - Guindy | C33: 1000000 | D33: =#REF! -> #REF! | E33: 1000000
B34: Rent Advance - VLV Complex | C34: 1102520 | D34: =#REF! -> #REF! | E34: 1102520
B35: Rental Advance - Temple Steps | C35: 1680000 | D35: =#REF! -> #REF!
B36: Rental Advance Coimbatore | C36: 2354801
C37: =SUM(C33:C36)+C40+C41 -> 6201321 | D37: =SUM(D33:D36) -> #REF! | E37: =SUM(E33:E34) -> 2102520
B39: f) Other Advance
B40: Deposit - UPS | C40: 24000 | D40: =#REF! -> #REF! | E40: 24000
B41: Deposit - Computers | C41: 40000 | D41: =#REF! -> #REF! | E41: 40000
B42: Salary Advance | C42: 207334 | D42: =#REF! -> #REF! | E42: 188250
C43: =C42 -> 207334 | D43: =SUM(D40:D42) -> #REF! | E43: =SUM(E40:E42) -> 252250
B45: g) Balances with Bank
B46: - Current account | C46: =1588011.23+37647450 -> 39235461 | D46: =#REF!+#REF! -> #REF! | E46: 3210639.6
B47: - in Fixed deposit accounts (including Interest accrued) | C47: =42420521+171762.5 -> 42592284 | D47: =#REF!+#REF! -> #REF! | E47: 27974875
C49: =SUM(C46:C48) -> 81827745 | D49: =SUM(D46:D48) -> #REF! | E49: =SUM(E46:E48) -> 31185515
B51: h)Trade receivables (unsecured considered good)
B52: Kalyan Jewellers | C52: 0 | D52: 0 | E52: 0
C53: =SUM(C52) -> 0 | D53: =SUM(D52) -> 0 | E53: =SUM(E52) -> 0
B55: i)Advances to suppliers
B56: Volatile Tele System | C56: 0 | D56: 0 | E56: 0
B57: Eupraxia Telecom | C57: 174506.18 | D57: =#REF! -> #REF! | E57: 103840
C58: 174506.18 | D58: =SUM(D56:D57) -> #REF! | E58: =SUM(E56:E57) -> 103840
B60: j)Income tax payments
B61: TDS Receivable-AY-20-21 | C61: 0 | D61: 0 | E61: 0
B62: TDS Receivable-AY-21-22
B63: Input GST | C63: =+'Groupings BS'!C16 -> 101951.91 | D63: =+'Groupings BS'!D16 -> #REF! | E63: 91588.52
B64: Interest Accrued but not due | C64: 0 | D64: 0 | E64: 0
B65: Income Tax Refund AY-20-21 | D65: =#REF! -> #REF! | E65: 5496530
B66: Income Tax Refund AY-21-22
B67: TDS Receivable-AY-23-24 | D67: =#REF! -> #REF! | E67: 5811066.2
B68: TDS Receivable-AY-24-25 | C68: 8554545
C69: =SUM(C61:C68) -> 8656496.9 | D69: =SUM(D61:D67) -> #REF! | E69: =SUM(E61:E67) -> 11399185

Sheet 10
A1: MARKETSOF1 ANALYTICAL MARKETING SERVICES PRIVATE LIMITED
A2: CIN: U72501TN2019PTC129911
A4: Notes to Financial Statements for the year ended March 31, 2026
A5: (All amounts are in thousands Indian Rupees, unless otherwise stated)
A7: Note No. 10 : Property, Plant & Equipments
A9: Particulars | C9: Gross Block | G9: Accumulated Depreciation | K9: Net Block
C10: As on 01-04-2025 | D10: Addition during the year | E10: Deduction during the year | F10: As on 31-03-2026 | G10: As on 01-04-2025 | H10: Addition during the year | I10: Deduction during the year | J10: As on 31-03-2026 | K10: As on 31-03-2026 | L10: As on 31-03-2025
A11: 10.1 | B11: Tangible Assets
A12: a. | B12: Office Building | C12: 0 | D12: =SUMIF(Table2[FS Subgroup],'10'!B12,Table2[Adjusted balance as on 31-03-2026])-'10'!C12 -> 0 | E12: 0 | F12: =+C12+D12-E12 -> 0 | G12: 0 | H12: 0 | I12: 0 | J12: =+G12+H12-I12 -> 0 | K12: =+F12-J12 -> 0 | L12: =+C12-G12 -> 0
A13: b. | B13: Factory Building | C13: 0 | D13: =SUMIF(Table2[FS Subgroup],'10'!B13,Table2[Adjusted balance as on 31-03-2026])-'10'!C13 -> 0 | E13: 0 | F13: =+C13+D13-E13 -> 0 | G13: 0 | H13: 0 | I13: 0 | J13: =+G13+H13-I13 -> 0 | K13: =+F13-J13 -> 0 | L13: =+C13-G13 -> 0
A14: c. | B14: Computers Software | C14: 50000 | D14: =SUMIF(Table2[FS Subgroup],'10'!B14,Table2[Adjusted balance as on 31-03-2026])-'10'!C14 -> 0 | E14: 0 | F14: =+C14+D14-E14 -> 50000 | G14: 39713.448 | H14: 7916.67 | I14: 0 | J14: =+G14+H14-I14 -> 47630.118 | K14: =+F14-J14 -> 2369.8819 | L14: =+C14-G14 -> 10286.552
A15: d. | B15: Furniture & Fittings | C15: 2635970.4 | D15: =SUMIF(Table2[FS Subgroup],'10'!B15,Table2[Adjusted balance as on 31-03-2026])-'10'!C15 -> 558379.01 | E15: 0 | F15: =+C15+D15-E15 -> 3194349.4 | G15: 609890.07 | H15: 281256.85 | I15: 0 | J15: =+G15+H15-I15 -> 891146.92 | K15: =+F15-J15 -> 2303202.5 | L15: =+C15-G15 -> 2026080.3 | N15: 2635971
A16: e. | B16: Leasehold Land | C16: 0 | D16: =SUMIF(Table2[FS Subgroup],'10'!B16,Table2[Adjusted balance as on 31-03-2026])-'10'!C16 -> 0 | E16: 0 | F16: =+C16+D16-E16 -> 0 | G16: 0 | H16: 0 | I16: 0 | J16: =+G16+H16-I16 -> 0 | K16: =+F16-J16 -> 0 | L16: =+C16-G16 -> 0
A17: f. | B17: Freehold Land | C17: 0 | D17: =SUMIF(Table2[FS Subgroup],'10'!B17,Table2[Adjusted balance as on 31-03-2026])-'10'!C17 -> 0 | E17: 0 | F17: =+C17+D17-E17 -> 0 | G17: 0 | H17: 0 | I17: 0 | J17: =+G17+H17-I17 -> 0 | K17: =+F17-J17 -> 0 | L17: =+C17-G17 -> 0
A18: g. | B18: Motor Vehicles | C18: 0 | D18: =SUMIF(Table2[FS Subgroup],'10'!B18,Table2[Adjusted balance as on 31-03-2026])-'10'!C18 -> 0 | E18: 0 | F18: =+C18+D18-E18 -> 0 | G18: 0 | H18: 0 | I18: 0 | J18: =+G18+H18-I18 -> 0 | K18: =+F18-J18 -> 0 | L18: =+C18-G18 -> 0
A19: h. | B19: Office Equipments | C19: 3110.16 | D19: =SUMIF(Table2[FS Subgroup],'10'!B19,Table2[Adjusted balance as on 31-03-2026])-'10'!C19 -> 0 | E19: 0 | F19: =+C19+D19-E19 -> 3110.16 | G19: 2955.78 | H19: 3630.93 | I19: 0 | J19: =+G19+H19-I19 -> 6586.71 | K19: =+F19-J19 -> -3476.55 | L19: =+C19-G19 -> 154.38002
A20: i. | B20: Computers & Accessories | C20: 4563131 | D20: =SUMIF(Table2[FS Subgroup],'10'!B20,Table2[Adjusted balance as on 31-03-2026])-'10'!C20 -> 2398648.8 | E20: 0 | F20: =+C20+D20-E20 -> 6961779.8 | G20: 2159469.2 | H20: 1736655.8 | I20: 0 | J20: =+G20+H20-I20 -> 3896125 | K20: =+F20-J20 -> 3065654.8 | L20: =+C20-G20 -> 2403661.8
A21: j. | B21: Printer | C21: 62575 | D21: =SUMIF(Table2[FS Subgroup],'10'!B21,Table2[Adjusted balance as on 31-03-2026])-'10'!C21 -> 49889.41 | E21: 0 | F21: =+C21+D21-E21 -> 112464.41 | G21: 24725.682 | H21: 16147.87 | I21: 0 | J21: =+G21+H21-I21 -> 40873.552 | K21: =+F21-J21 -> 71590.858 | L21: =+C21-G21 -> 37849.318
A22: k. | B22: Plant & Machinery | C22: 0 | D22: =SUMIF(Table2[FS Subgroup],'10'!B22,Table2[Adjusted balance as on 31-03-2026])-'10'!C22 -> 0 | E22: 0 | F22: =+C22+D22-E22 -> 0 | G22: 0 | H22: 0 | I22: 0 | J22: =+G22+H22-I22 -> 0 | K22: =+F22-J22 -> 0 | L22: =+C22-G22 -> 0
B24: Total | C24: =SUM(C12:C23) -> 7314786.6 | D24: =SUM(D12:D23) -> 3006917.3 | E24: =SUM(E12:E23) -> 0 | F24: =SUM(F12:F23) -> 10321704 | G24: =SUM(G12:G23) -> 2836754.2 | H24: =SUM(H12:H23) -> 2045608.1 | I24: =SUM(I12:I23) -> 0 | J24: =SUM(J12:J23) -> 4882362.3 | K24: =+F24-J24 -> 5439341.5 | L24: =SUM(L12:L23) -> 4478032.3
B25: (Previous Year) | C25: 5167958.6 | D25: 2146828 | E25: 0 | F25: 7314786.6 | G25: 1473367 | H25: 1363387.2 | I25: 0 | J25: 2836754.2 | K25: 4478032.3 | L25: 3694591.5
A27: =A11+0.1 -> 10.2 | B27: Intangible Asset
A28: a. | B28: Computer Software | C28: 0 | D28: 0 | E28: 0 | F28: =+C28+D28-E28 -> 0 | G28: 0 | H28: 0 | I28: 0 | J28: =+G28+H28-I28 -> 0 | K28: =+F28-J28 -> 0 | L28: =+C28-G28 -> 0 | R28: =D24+D30 -> 3006917.3
R29: =R28-D16 -> 3006917.3
B30: Total | C30: =SUM(C28:C29) -> 0 | D30: =SUM(D28:D29) -> 0 | E30: =SUM(E28:E29) -> 0 | F30: =SUM(F28:F29) -> 0 | G30: =SUM(G28:G29) -> 0 | H30: =SUM(H28:H29) -> 0 | I30: =SUM(I28:I29) -> 0 | J30: =SUM(J28:J29) -> 0 | ... L30: =SUM(L28:L29) -> 0
B31: (Previous Year) | C31: 0 | D31: 0 | E31: 0 | F31: 0 | G31: 0 | H31: 0 | I31: 0 | J31: 0 | K31: 0 | L31: 0
A33: =A27+0.1 -> 10.3 | B33: Capital Work in Progress | C33: 0 | E33: 0 | F33: =+C33+D33-E33 -> 0 | G33: 0 | H33: 0 | I33: 0 | J33: =+G33+H33-I33 -> 0 | K33: =+F33-J33 -> 0 | L33: =+C33-G33 -> 0
B35: Total | C35: =SUM(C33) -> 0 | D35: =SUM(D33) -> 0 | E35: =SUM(E33) -> 0 | F35: =SUM(F33) -> 0 | G35: =SUM(G33) -> 0 | H35: =SUM(H33) -> 0 | I35: =SUM(I33) -> 0 | J35: =SUM(J33) -> 0 | ... L35: =SUM(L33) -> 0
B36: (Previous Year) | C36: 0 | D36: 0 | E36: 0 | F36: 0 | G36: 0 | H36: 0 | I36: 0 | J36: 0 | K36: 0 | L36: 0
A38: =A33+0.1 -> 10.4 | B38: Intangible assets under development | C38: 0 | E38: 0 | F38: =+C38+D38-E38 -> 0 | G38: 0 | H38: 0 | I38: 0 | J38: =+G38+H38-I38 -> 0 | K38: =+F38-J38 -> 0 | L38: =+C38-G38 -> 0
B40: Total | C40: =SUM(C38) -> 0 | D40: =SUM(D38) -> 0 | E40: =SUM(E38) -> 0 | F40: =SUM(F38) -> 0 | G40: =SUM(G38) -> 0 | H40: =SUM(H38) -> 0 | I40: =SUM(I38) -> 0 | J40: =SUM(J38) -> 0 | ... L40: =SUM(L38) -> 0
B41: (Previous Year) | C41: 0 | D41: 0 | E41: 0 | F41: 0 | G41: 0 | H41: 0 | I41: 0 | J41: 0 | K41: 0 | L41: 0
A43: TOTAL | C43: =C40+C35+C30+C24 -> 7314786.6 | D43: =D40+D35+D30+D24 -> 3006917.3 | E43: =E40+E35+E30+E24 -> 0 | F43: =F40+F35+F30+F24 -> 10321704 | G43: =G40+G35+G30+G24 -> 2836754.2 | H43: =H40+H35+H30+H24 -> 2045608.1 | I43: =I40+I35+I30+I24 -> 0 | J43: =J40+J35+J30+J24 -> 4882362.3 | ... L43: =L40+L35+L30+L24 -> 4478032.3

Sheet Ageing schedule
A1: MARKETSOF1 ANALYTICAL MARKETING SERVICES PRIVATE LIMITED
A2: CIN: U72501TN2019PTC129911
A4: Notes to Financial Statements for the year ended March 31, 2026
A5: (All amounts are in thousands Indian Rupees, unless otherwise stated)
A7: Note No. 7 | B7: Trade payable ageing schedule
B9: Outstanding for following periods from due date of payment (2025-26)
A10: S.No. | B10: Particulars | C10: Not due | D10: Unbilled amount | E10: < 6 months | F10: 6 month -1 year | G10: 1-2 years | H10: 2-3 years | I10: > 3 years | J10: Total
A11: ='3-15'!A74+0.1 -> 7.1 | B11: MSME | C11: 0 | D11: 0 | E11: 0 | F11: 0 | G11: 0 | H11: 0 | I11: 0 | J11: =SUM(C11:I11) -> 0
A12: =A11+0.1 -> 7.2 | B12: Others | C12: 0 | D12: 0 | E12: ='3-15'!E76 -> 31351590 | F12: 0 | G12: 0 | H12: 0 | I12: 0 | J12: =SUM(C12:I12) -> 31351590
A13: =A12+0.1 -> 7.3 | B13: Disputed dues-MSME | E13: 0 | F13: 0 | G13: 0 | H13: 0 | I13: 0 | J13: =SUM(D13:I13) -> 0
A14: =A13+0.1 -> 7.4 | B14: Disputed dues-Other | E14: 0 | F14: 0 | G14: 0 | H14: 0 | I14: 0 | J14: =SUM(D14:I14) -> 0
B15: Total | C15: =SUM(C11:C14) -> 0 | D15: =SUM(D11:D14) -> 0 | E15: =SUM(E11:E14) -> 31351590 | F15: =SUM(F11:F14) -> 0 | G15: =SUM(G11:G14) -> 0 | H15: =SUM(H11:H14) -> 0 | I15: =SUM(I11:I14) -> 0 | J15: =SUM(J11:J14) -> 31351590
B17: Outstanding for following periods from due date of payment (2024-25)
A18: S.No. | B18: Particulars | C18: Not due | D18: Unbilled amount | E18: < 6 months | F18: 6 month -1 year | G18: 1-2 years | H18: 2-3 years | I18: > 3 years | J18: Total
A19: ='3-15'!A74+0.1 -> 7.1 | B19: MSME | C19: 0 | D19: 0 | E19: 0 | F19: 0 | G19: 0 | H19: 0 | I19: 0 | J19: 0
A20: =A19+0.1 -> 7.2 | B20: Others | C20: 0 | D20: 0 | E20: =31998228.36+231423.21 -> 32229652 | G20: 0 | H20: 0 | I20: 0 | J20: =SUM(D20:I20) -> 32229652
A21: =A20+0.1 -> 7.3 | B21: Disputed dues-MSME | E21: 0 | I21: 0 | J21: 0
A22: =A21+0.1 -> 7.4 | B22: Disputed dues-Other | E22: 0 | I22: 0 | J22: 0
B23: Total | C23: =SUM(C19:C22) -> 0 | D23: =SUM(D19:D22) -> 0 | E23: =SUM(E19:E22) -> 32229652 | F23: =SUM(F19:F22) -> 0 | G23: =SUM(G19:G22) -> 0 | H23: =SUM(H19:H22) -> 0 | I23: =SUM(I19:I22) -> 0 | J23: =SUM(J19:J22) -> 32229652
A26: Note No. 12 | B26: Trade receivable ageing schedule
B28: Outstanding for following periods from due date of payment (2025-26)
A29: S.No. | B29: Particulars | C29: Not due | D29: Unbilled amount | E29: < 6 months | F29: 6 month -1 year | G29: 1-2 years | H29: 2-3 years | I29: > 3 years | J29: Total
A30: 12.1 | B30: Undisputed Trade Receivables – considered good | C30: 0 | D30: ='3-15'!E130 -> 26920883 | E30: ='3-15'!E110 -> 4317419.3 | F30: 0 | G30: 0 | H30: 0 | I30: 0 | J30: =SUM(C30:I30) -> 31238302
A31: =A30+0.1 -> 12.2 | B31: Undisputed Trade Receivables – considered doubtful | C31: 0 | D31: 0 | E31: 0 | F31: 0 | G31: 0 | H31: 0 | I31: 0 | J31: =SUM(C31:I31) -> 0
A32: =A31+0.1 -> 12.3 | B32: Disputed Trade Receivables – considered good | C32: 0 | D32: 0 | E32: 0 | F32: 0 | G32: 0 | H32: 0 | I32: 0 | J32: =SUM(C32:I32) -> 0
A33: =A32+0.1 -> 12.4 | B33: Disputed Trade Receivables – considered doubtful | C33: 0 | D33: 0 | E33: 0 | F33: 0 | G33: 0 | H33: 0 | I33: 0 | J33: =SUM(C33:I33) -> 0
B34: Total | C34: =SUM(C30:C33) -> 0 | D34: =SUM(D30:D33) -> 26920883 | E34: =SUM(E30:E33) -> 4317419.3 | F34: =SUM(F30:F33) -> 0 | G34: =SUM(G30:G33) -> 0 | H34: =SUM(H30:H33) -> 0 | I34: =SUM(I30:I33) -> 0 | J34: =SUM(J30:J33) -> 31238302
B36: Outstanding for following periods from due date of payment (2024-25)
A37: S.No. | B37: Particulars | C37: Not due | D37: Unbilled amount | E37: < 6 months | F37: 6 month -1 year | G37: 1-2 years | H37: 2-3 years | I37: > 3 years | J37: Total
A38: 12.1 | B38: Undisputed Trade Receivables – considered good | C38: 0 | D38: 5000000 | E38: ='Financial Statements'!F46 -> 1242797.4 | F38: 0 | G38: 0 | H38: 0 | I38: 0 | J38: =SUM(C38:I38) -> 6242797.4
A39: =A38+0.1 -> 12.2 | B39: Undisputed Trade Receivables – considered doubtful | C39: 0 | D39: 0 | E39: 0 | F39: 0 | G39: 0 | H39: 0 | I39: 0 | J39: =SUM(C39:I39) -> 0
A40: =A39+0.1 -> 12.3 | B40: Disputed Trade Receivables – considered good | C40: 0 | D40: 0 | E40: 0 | F40: 0 | G40: 0 | H40: 0 | I40: 0 | J40: =SUM(C40:I40) -> 0
A41: =A40+0.1 -> 12.4 | B41: Disputed Trade Receivables – considered doubtful | C41: 0 | D41: 0 | E41: 0 | F41: 0 | G41: 0 | H41: 0 | I41: 0 | J41: =SUM(C41:I41) -> 0
B42: Total | C42: =SUM(C38:C41) -> 0 | D42: =SUM(D38:D41) -> 5000000 | E42: =SUM(E38:E41) -> 1242797.4 | F42: =SUM(F38:F41) -> 0 | G42: =SUM(G38:G41) -> 0 | H42: =SUM(H38:H41) -> 0 | I42: =SUM(I38:I41) -> 0 | J42: =SUM(J38:J41) -> 6242797.4

Sheet 16-23
A1: MARKETSOF1 ANALYTICAL MARKETING SERVICES PRIVATE LIMITED
A2: CIN: U72501TN2019PTC129911
A4: Notes to Financial Statements for the year ended March 31, 2026
A5: (All amounts are in thousands Indian Rupees, unless otherwise stated)
A7: Note No. | B7: Particulars | C7: For the year ended 31st March, 2026 | D7: For the year ended 31st March, 2025
A9: ='3-15'!A127+1 -> 16 | B9: Revenue from Operations
A10: =A9+0.1 -> 16.1 | B10: Sale of Products | C10: {=-SUMIF(Table2[FS Subgroup],'16-23'!B10:B10,Table2[Adjusted balance as on 31-03-2026])} -> 0 | D10: =D19 -> 0
A11: =A10+0.1 -> 16.2 | B11: Sale of Services | C11: {=-SUMIF(Table2[FS Subgroup],'16-23'!B11:B11,Table2[Adjusted balance as on 31-03-2026])} -> 6.0174095e+08 | D11: =449121097+4500000 -> 453621097
A12: =A11+0.1 -> 16.3 | B12: Other Operating Revenue | C12: 0 | D12: 0
B14: Total | C14: =SUM(C10:C12) -> 6.0174095e+08 | D14: =SUM(D10:D12) -> 453621097
A15: Note : | B15: Sale of Products Comprise of
B17: i.) | D17: 0
B18: ii.) | D18: 0
B19: Total | D19: =SUM(D17:D18) -> 0
A21: Note : | B21: Sale of Services Comprise of
B22: Revenue from Services | C22: =C11 -> 6.0174095e+08 | D22: =D11 -> 453621097
B23: Total | C23: =SUM(C22:C22) -> 6.0174095e+08 | D23: =SUM(D22:D22) -> 453621097
A25: =A9+1 -> 17 | B25: Other Income
A26: =A25+0.1 -> 17.1 | B26: Interest Income
B27: Interest on FD | C27: {=-SUMIF(Table2[FS Subgroup],'16-23'!B27:B27,Table2[Adjusted balance as on 31-03-2026])} -> 3782232.6 | D27: 3500599.8
B28: Interest on Staff Loans | C28: {=-SUMIF(Table2[FS Subgroup],'16-23'!B28:B28,Table2[Adjusted balance as on 31-03-2026])} -> 31353 | D28: 0
B29: Interest from Income Tax Refund | C29: {=-SUMIF(Table2[FS Subgroup],'16-23'!B29:B29,Table2[Adjusted balance as on 31-03-2026])} -> 0 | D29: 111865
A30: =A26+0.1 -> 17.2 | B30: Bad debts recovered | C30: {=-SUMIF(Table2[FS Subgroup],'16-23'!B30:B30,Table2[Adjusted balance as on 31-03-2026])} -> 5000 | D30: 0
A31: =A30+0.1 -> 17.3 | B31: Excess provision reversed | C31: {=-SUMIF(Table2[FS Subgroup],'16-23'!B31:B31,Table2[Adjusted balance as on 31-03-2026])} -> 8000000 | D31: 0
A32: =A31+0.1 -> 17.4 | B32: Miscellaneous Income | C32: {=-SUMIF(Table2[FS Subgroup],'16-23'!B32:B32,Table2[Adjusted balance as on 31-03-2026])} -> 4.14 | D32: 7.17
B34: Total | C34: =SUM(C26:C32) -> 11818590 | D34: =SUM(D26:D32) -> 3612471.9
A36: =A25+1 -> 18 | B36: Operating Expenses
A37: =A36+0.1 -> 18.1 | B37: Campaign Expenses | C37: {=SUMIF(Table2[FS Subgroup],'16-23'!B37:B37,Table2[Adjusted balance as on 31-03-2026])} -> 70563000 | D37: 41381396
A38: =A37+0.1 -> 18.2 | B38: Direct Costs-User licences for algorithms | C38: {=SUMIF(Table2[FS Subgroup],'16-23'!B38:B38,Table2[Adjusted balance as on 31-03-2026])} -> 81620248 | D38: 92575051
A39: =A38+0.1 -> 18.3 | B39: Direct Costs:Professional Fees for Analytics and UI/UX | C39: {=SUMIF(Table2[FS Subgroup],'16-23'!B39:B39,Table2[Adjusted balance as on 31-03-2026])} -> 73739161 | D39: 97545428
A40: =A39+0.1 -> 18.4 | B40: Direct Costs: Predictive modeling and updates | C40: {=SUMIF(Table2[FS Subgroup],'16-23'!B40:B40,Table2[Adjusted balance as on 31-03-2026])} -> 0 | D40: 5000000
B42: Total | C42: =SUM(C37:C40) -> 2.2592241e+08 | D42: =SUM(D37:D40) -> 2.3650187e+08
A44: =A36+1 -> 19 | B44: Employee Benefit Expenses
A45: =A44+0.1 -> 19.1 | B45: Salary & Wages (Inculding bonus) | C45: {=SUMIF(Table2[FS Subgroup],'16-23'!B45:B45,Table2[Adjusted balance as on 31-03-2026])} -> 163491002 | D45: =+'Sub Schedule P & L'!C34 -> 1.1168932e+08
A46: =A45+0.1 -> 19.2 | B46: Director's Salary | C46: {=SUMIF(Table2[FS Subgroup],'16-23'!B46:B46,Table2[Adjusted balance as on 31-03-2026])} -> 38000000 | D46: =+'Sub Schedule P & L'!C50 -> 0
A47: =A46+0.1 -> 19.3 | B47: Staff welfare Expenses | C47: {=SUMIF(Table2[FS Subgroup],'16-23'!B47:B47,Table2[Adjusted balance as on 31-03-2026])} -> 16980923 | D47: =+'Sub Schedule P & L'!C44-D53 -> 13935381
A48: =A47+0.1 -> 19.4 | B48: Contribution to Various Funds | C48: {=SUMIF(Table2[FS Subgroup],'16-23'!B48:B48,Table2[Adjusted balance as on 31-03-2026])} -> 12131036 | D48: =D56 -> 9623827.4
A49: =A48+0.1 -> 19.5 | B49: Gratuity and Leave Encashment | C49: {=SUMIF(Table2[FS Subgroup],'16-23'!B49:B49,Table2[Adjusted balance as on 31-03-2026])} -> 4724292 | D49: 56811
B51: Total | C51: =SUM(C45:C50) -> 2.3532725e+08 | D51: =SUM(D45:D50) -> 1.3530534e+08
A52: Note : | B52: Details of Contribution to various Funds
B53: Employees State Insurance | C53: {=SUMIF(Table2[FS Group],'16-23'!B53:B53,Table2[Adjusted balance as on 31-03-2026])} -> 1749457 | D53: ='Sub Schedule P & L'!C43 -> 1914430
B54: Provident fund | C54: {=SUMIF(Table2[FS Group],'16-23'!B54:B54,Table2[Adjusted balance as on 31-03-2026])} -> 10355354 | D54: ='Sub Schedule P & L'!C37 -> 7684444
B55: Labour Welfare Fund | C55: {=SUMIF(Table2[FS Group],'16-23'!B55:B55,Table2[Adjusted balance as on 31-03-2026])} -> 26225.26 | D55: 24953.36
B56: Total | C56: =SUM(C53:C55) -> 12131036 | D56: =SUM(D53:D55) -> 9623827.4
A58: =A44+1 -> 20 | B58: Finance Costs
A59: =A58+0.1 -> 20.1 | B59: Interest Expense | C59: {=SUMIF(Table2[FS Subgroup],'16-23'!B59:B59,Table2[Adjusted balance as on 31-03-2026])} -> 0 | D59: 0
A60: =A59+0.1 -> 20.2 | B60: Other Finance Costs | C60: {=SUMIF(Table2[FS Subgroup],'16-23'!B60:B60,Table2[Adjusted balance as on 31-03-2026])} -> 18687.8 | D60: 3342.85
B62: Total | C62: =SUM(C58:C61) -> 18687.8 | D62: =SUM(D58:D61) -> 3342.85
A64: =A58+1 -> 21 | B64: Depreciation and Amortization Expense
A65: =A64+0.1 -> 21.1 | B65: Depreciation | C65: {=SUMIF(Table2[FS Subgroup],'16-23'!B65:B65,Table2[Adjusted balance as on 31-03-2026])} -> 2045608.1 | D65: 1363386.9
A66: =A65+0.1 -> 21.2 | B66: Amortization | C66: {=SUMIF(Table2[FS Subgroup],'16-23'!B66:B66,Table2[Adjusted balance as on 31-03-2026])} -> 0 | D66: 0
B68: Total | C68: =SUM(C64:C67) -> 2045608.1 | D68: =SUM(D64:D67) -> 1363386.9
A70: =A64+1 -> 22 | B70: Other Expenses
B71: Consumption of Stores & Spares | C71: {=SUMIF(Table2[FS Subgroup],'16-23'!B71:B71,Table2[Adjusted balance as on 31-03-2026])} -> 1087960.6 | D71: ='TB 2025'!E233 -> 724690.52 | E71: 1
B72: Power & Fuel Expenses | C72: {=SUMIF(Table2[FS Subgroup],'16-23'!B72:B72,Table2[Adjusted balance as on 31-03-2026])} -> 7429986.8 | D72: ='TB 2025'!E231+'TB 2025'!E232 -> 5382331.8 | E72: 2
B73: Rent of Building | C73: {=SUMIF(Table2[FS Subgroup],'16-23'!B73:B73,Table2[Adjusted balance as on 31-03-2026])} -> 13849650 | D73: =SUM('TB 2025'!E280:E283) -> 8521568
B74: Rent of Plant and Machinery | C74: {=SUMIF(Table2[FS Subgroup],'16-23'!B74:B74,Table2[Adjusted balance as on 31-03-2026])} -> 3503612 | D74: =+'Groupings P &L'!C20-D73 -> 3278591.2 | E74: 3
B75: Repair & Maintenance - Plant & Machinery | C75: {=SUMIF(Table2[FS Subgroup],'16-23'!B75:B75,Table2[Adjusted balance as on 31-03-2026])} -> 661181.49 | D75: 973377.35 | E75: 4
B76: Building Maintenance | C76: {=SUMIF(Table2[FS Subgroup],'16-23'!B76:B76,Table2[Adjusted balance as on 31-03-2026])} -> 3115077 | D76: =SUM('TB 2025'!E276:E279) -> 2416541
B77: Internet and Telephone charges | C77: {=SUMIF(Table2[FS Subgroup],'16-23'!B77:B77,Table2[Adjusted balance as on 31-03-2026])} -> 14963049 | D77: =862233.74+5210188.01+3631400+623359 -> 10327181 | E77: 14
B78: Software & Subscription Charges | C78: {=SUMIF(Table2[FS Subgroup],'16-23'!B78:B78,Table2[Adjusted balance as on 31-03-2026])} -> 19105356 | D78: ='TB 2025'!E238 -> 10280672
B79: Legal Expenses | C79: {=SUMIF(Table2[FS Subgroup],'16-23'!B79:B79,Table2[Adjusted balance as on 31-03-2026])} -> 54382500 | D79: 0 | E79: 15
B80: Payment to Auditor | E80: 5
B81: - as Statutory Audit | C81: 250000 | D81: 200000 | E81: 6
B82: - as Tax Audit | C82: 200000 | D82: 199120 | E82: 7
B83: - Income Tax Matters | C83: {=SUMIF(Table2[FS Subgroup],'16-23'!B83:B83,Table2[Adjusted balance as on 31-03-2026])} -> 0 | E83: 8
B84: - Other Services | C84: 379800 | D84: =750000+450000 -> 1200000 | E84: 9
B85: Corporate Social responsibility Expenses | C85: {=SUMIF(Table2[FS Subgroup],'16-23'!B85:B85,Table2[Adjusted balance as on 31-03-2026])} -> 0 | D85: 0 | E85: 10
B86: Travelling & Conveyance | C86: {=SUMIF(Table2[FS Subgroup],'16-23'!B86:B86,Table2[Adjusted balance as on 31-03-2026])} -> 508333.23 | D86: =+'Sub Schedule P & L'!C66 -> 245350 | E86: 11
B87: Office Expenses | C87: {=SUMIF(Table2[FS Subgroup],'16-23'!B87:B87,Table2[Adjusted balance as on 31-03-2026])} -> 4521698 | D87: =+'Sub Schedule P & L'!C61-D71-'TB 2025'!E231-D76 -> 2042955.1 | E87: 12
B88: Professional Fees | C88: {=SUMIF(Table2[FS Subgroup],'16-23'!B88:B88,Table2[Adjusted balance as on 31-03-2026])-SUM(C81:C84)} -> 6832628.8 | D88: =5280763 -> 5280763 | E88: 13
B89: Insurance | C89: {=SUMIF(Table2[FS Subgroup],'16-23'!B89:B89,Table2[Adjusted balance as on 31-03-2026])} -> 1941845.2 | D89: 764776.07 | E89: 16
B90: Postage and courier | C90: {=SUMIF(Table2[FS Subgroup],'16-23'!B90:B90,Table2[Adjusted balance as on 31-03-2026])} -> 17109 | D90: 5355 | E90: 17
B91: Printing & Stationery | C91: {=SUMIF(Table2[FS Subgroup],'16-23'!B91:B91,Table2[Adjusted balance as on 31-03-2026])} -> 473064.78 | D91: =+'Sub Schedule P & L'!C54-D78 -> 310043.21 | E91: 18
B92: Miscellaneous Expenses | C92: {=SUMIF(Table2[FS Subgroup],'16-23'!B92:B92,Table2[Adjusted balance as on 31-03-2026])} -> 866242.15 | D92: =500793.24+4749+337.52 -> 505879.76 | E92: 19
B93: Bad debts | C93: {=SUMIF(Table2[FS Subgroup],'16-23'!B93:B93,Table2[Adjusted balance as on 31-03-2026])} -> 0 | D93: 28343 | E93: 21
B95: Total | C95: =SUM(C71:C93) -> 1.3408909e+08 | D95: =SUM(D71:D93) -> 52687538
A97: =+A70+1 -> 23 | B97: Current tax
B98: Current tax | C98: {=SUMIF(Table2[FS Subgroup],'16-23'!B98:B98,Table2[Adjusted balance as on 31-03-2026])} -> 5200000 | D98: 8000000
B99: Less : Prior years Excess Provision | C99: {=SUMIF(Table2[FS Subgroup],'16-23'!B99:B99,Table2[Adjusted balance as on 31-03-2026])} -> -52434.6
B100: Less : MAT credit entitlement | D100: 0
B101: Net Current tax | C101: =SUM(C98:C100) -> 5147565.4 | D101: =SUM(D98:D100) -> 8000000

Sheet 24-41
B2: MARKETSOF1 ANALYTICAL MARKETING SERVICES PRIVATE LIMITED
B3: CIN: U72501TN2019PTC129911
B5: Notes to Financial Statements for the year ended March 31, 2026
B6: (All amounts are in thousands Indian Rupees, unless otherwise stated)
B8: ='16-23'!A97+1 -> 24 | C8: Contingent liabilities
C9: Based on the assessment made by the management, adequate provision have been provided for the contingent liabilities.
B12: =OLE_LINK7+1 -> 25 | C12: Exceptional Items
C13: Particulars | F13: =+$F$166 -> Year Ended March 31, 2026 | G13: =+$G$166 -> Year Ended March 31, 2025
C14: Provision for Litigation and Court claim (refer note no. 39) | F14: 0 | G14: 0
C16: Total | F16: =SUM(F10:F15) -> 0 | G16: =SUM(G10:G15) -> 0
B18: =B12+1 -> 26 | C18: Capital commitment (net of advances)
C19: As at 31st March, 2026 Rs. Nil. (31-Mar-2025: Rs. Nil).
B21: =+B18+1 -> 27 | C21: Segment Reporting
C22: In the opinion of the management, there is only one reportable segment. i.e. Marketing Consultancy Services and Company operates in only one geographic country i.e. India. Accordingly, no separate disclosure is required to be made under Accounting Standard 17, Segment Reporting.
B26: =+B21+1 -> 28 | C26: Related Party Disclosures
C28: A. List of Related Parties
C29: Nature of Relationship | E29: Party
C30: Key Managerial Personnel | E30: Jayaram Krishnamoorthy
E31: Deepa Mahadevan
E32: Mahul H Shah
E33: Mahadevan Jayaraman
C34: Entities in which key management personnel are interested | E34: Ganitscience Artificial Intelligence and analytics P Ltd (OPC)
E35: ILIVE Daily Creations P Ltd(OPC)
E36: M1 Marketing Services Pvt Ltd
E37: DQAI Telesales Pvt Ltd
E38: DeepQuanty Artificial Intelligence Labs Pvt Ltd
C40: B. Transactions with Related Parties during the year (excluding directors remuneration*)
C41: Transaction | D41: Related Party | F41: Year Ended March 31, 2026 | G41: Year Ended March 31, 2025
D42: Ganitscience Artificial Intelligence and analytics P Ltd (OPC)
D43: ILIVE Daily Creations P Ltd(OPC)
D44: M1 Marketing Services Pvt Ltd
D45: DQAI Telesales Pvt Ltd
D46: DeepQuanty Artificial Intelligence Labs Pvt Ltd
C48: *- Refer C for Directors remuneration.
C50: C. Directors’ Remuneration
C52: Particulars | F52: =+$F$166 -> Year Ended March 31, 2026 | G52: =+$G$166 -> Year Ended March 31, 2025
C53: Executive Directors
C54: Jayaram Krishnamoorthy | F54: 0 | G54: 0
C55: Deepa Mahadevan | F55: ='Trial Balance'!C88 -> 15000000 | G55: 0
C56: Mahul H Shah | F56: 0 | G56: 0
C57: Mahadevan Jayaraman | F57: ='Trial Balance'!C89 -> 23000000 | G57: 0
C58: Non-Executive Directors
C59: Sitting Fees | F59: 0 | G59: 0
C61: D. Balances as at year end
C62: Nature of Balance | D62: Related Party | F62: As at March 31, 2026 | G62: As at March 31, 2025
C63: Payable
C64: Payable
B68: =+B26+1 -> 29 | C68: Retirement Benefit
C69: (1) Description of the Gratuity Plan:
C70: The Company provides for gratuity a defined benefit retirement plan covering eligible employees. Gratuity plan provides for a lump sum payment to employees on retirement, death, incapacitation, termination of employment, of amounts that are based on salaries and tenure of the employees. ‘ Gratuity liability is funded with Life Insurance Corporation of India (LIC)’
C75: (2) Amount recognized in the Balance Sheet and movements in net liability:
C77: Particulars | F77: As at March 31, 2026 | G77: As at March 31, 2025
C78: Present Value of Funded Obligations | G78: 0
C79: Fair Value of Plan Assets | G79: 0
C80: Net Liability / (Asset) recognized in the Balance Sheet | G80: 0
C82: The fair value of the plan assets does not include the Company’s own financial instruments
C84: (3) Expenses recognized in the Statement of Profit & Loss
C85: Particulars | F85: As at March 31, 2026 | G85: As at March 31, 2025
C86: Current Service Cost | F86: 0 | G86: 0
C87: Interest on Defined Benefit Obligation | F87: 0 | G87: 0
C88: Expected Return on Plan Assets | F88: 0 | G88: 0
C89: Net Actuarial Losses/ (Gains) Recognized in the year | F89: 0 | G89: 0
C90: Past Service Cost | F90: 0 | G90: 0
C91: Other Charges | F91: 0 | G91: 0
C92: Total | F92: =SUM(F86:F91) -> 0 | G92: =SUM(G86:G91) -> 0
C94: (4)Reconciliation of Benefit Obligation & Plan assets for the Period
C96: Change in Defined Benefit Obligation
C97: Particulars | F97: As at March 31, 2026 | G97: As at March 31, 2025
C98: Opening Defined Benefit Obligation | F98: 0 | G98: 0
C99: Current Service Cost | F99: 0 | G99: 0
C100: Interest Cost | F100: 0 | G100: 0
C101: Actuarial Losses /(Gain ) | F101: 0 | G101: 0
C102: Past Service Cost | F102: 0 | G102: 0
C103: Actuarial Losses / (Gain ) due to Curtailment | F103: 0 | G103: 0
C104: Liabilities Extinguished on Settlements | F104: 0 | G104: 0
C105: Liabilities Assumed on Acquisition / (Settled on Divestiture) | F105: 0 | G105: 0
C106: Exchange Difference on Foreign Plans | F106: 0 | G106: 0
C107: Benefits Paid | F107: 0 | G107: 0
C108: Closing Defined Benefit Obligation | F108: =SUM(F98:F107) -> 0 | G108: =SUM(G98:G107) -> 0
C110: Change in Fair Value of Assets
C111: Particulars | F111: As at March 31, 2026 | G111: As at March 31, 2025
C112: Opening Fair Value of Plan Assets | F112: 0 | G112: 0
C113: Expected Return on Plan Assets | F113: 0 | G113: 0
C114: Actuarial Gain / ( Losses ) | F114: 0 | G114: 0
C115: Assets Distributed on Settlements | F115: 0 | G115: 0
C116: Contributions by Employer | F116: 0 | G116: 0
C117: Assets Acquired on Acquisition /(Distributed on Divestiture) | F117: 0 | G117: 0
C118: Exchange Difference on Foreign Plans | F118: 0 | G118: 0
C119: Benefits Paid | F119: 0 | G119: 0 | M119: =F119-F89 -> 0 | N119: Check Number
C120: Closing Fair Value of Plan Assets | F120: =SUM(F112:F119) -> 0 | G120: =SUM(G112:G119) -> 0
C122: (5)Actuarial Assumptions at the Valuation date
C123: Particulars | F123: As at March 31, 2026 | G123: As at March 31, 2025
C124: Discount Rate | F124: 0.0695 | G124: 0.0695
C125: Expected Rate of Return on Plan Assets* | F125: 0.0695 | G125: 0.0695
C126: Salary Escalation Rate | F126: 0.11 | G126: 0.11
C127: *This is based on expectation of the average long term rate of return expected on investments of the Fund during the estimated term of the obligations.
C129: (6) Descriptions of the Plan Assets
C130: Category of Assets | F130: 2025-2026 | G130: 2024-2025
C131: Government of India Securities | F131: 0 | G131: 0
C132: Corporate Bonds | F132: 0 | G132: 0
...

Sheet Trial Balance
C2: =SUM(Table2[Adjusted balance as on 31-03-2026]) -> -2.30968e-07 | D2: =SUM(Table2[Adjusted balance as on 31-03-2026]) -> -2.30968e-07 | E2: =SUM(Table2[Adjusted balance as on 31-03-2026]) -> -2.30968e-07
A3: Zoho Group | B3: Zoho Ledger | C3: Balance as on 31-03-2026 | D3: Adjustments | E3: Adjusted balance as on 31-03-2026 | F3: FS Subgroup | G3: FS Group | H3: FS Head
A4: Assets | B4: Accounts Receivable | C4: =IFERROR(VLOOKUP(B4,'TB 2026'!$A$4:$E$155,5,),0) -> 4317419.3 | E4: =Table2[[#This Row],[Balance as on 31-03-2026]]+Table2[[#This Row],[Adjustments]] -> 4317419.3 | F4: -with others | G4: Trade Receivables | H4: Current Asset
A5: Assets | B5: Accounts Receivable (Debtors) | C5: =IFERROR(VLOOKUP(B5,'TB 2026'!$A$4:$E$155,5,),0) -> 23125223 | D5: =J5-Table2[[#This Row],[Balance as on 31-03-2026]] -> 3795659.6 | E5: =Table2[[#This Row],[Balance as on 31-03-2026]]+Table2[[#This Row],[Adjustments]] -> 26920883 | F5: Accrued Revenue | G5: Other Current Assets | H5: Current Asset | J5: 26920883
A6: Assets | B6: Accumulated Depreciation | C6: =IFERROR(VLOOKUP(B6,'TB 2026'!$A$4:$E$155,5,),0) -> -2836754 | D6: =-D99 -> -2045608.1 | E6: =Table2[[#This Row],[Balance as on 31-03-2026]]+Table2[[#This Row],[Adjustments]] -> -4882362.1 | F6: Fixed Assets | G6: Fixed Assets | H6: Non-Current Assets
A7: Assets | B7: Accured Interest On FD | C7: =IFERROR(VLOOKUP(B7,'TB 2026'!$A$4:$E$155,5,),0) -> 149543.83 | E7: =Table2[[#This Row],[Balance as on 31-03-2026]]+Table2[[#This Row],[Adjustments]] -> 149543.83 | F7: Accrued Interest on FD | G7: Other Current Assets | H7: Current Asset
A8: Assets | B8: Advance to Suppliers | C8: =IFERROR(VLOOKUP(B8,'TB 2026'!$A$4:$E$155,5,),0) -> 80942.1 | E8: =Table2[[#This Row],[Balance as on 31-03-2026]]+Table2[[#This Row],[Adjustments]] -> 80942.1 | F8: Advances to Supplier | G8: Short term Loan & Advances | H8: Current Asset
A9: Assets | B9: computer software | C9: =IFERROR(VLOOKUP(B9,'TB 2026'!$A$4:$E$155,5,),0) -> 50000 | E9: =Table2[[#This Row],[Balance as on 31-03-2026]]+Table2[[#This Row],[Adjustments]] -> 50000 | F9: Computers Software | G9: Fixed Assets | H9: Non-Current Assets
A10: Assets | B10: Computers | C10: =IFERROR(VLOOKUP(B10,'TB 2026'!$A$4:$E$155,5,),0) -> 6961779.8 | E10: =Table2[[#This Row],[Balance as on 31-03-2026]]+Table2[[#This Row],[Adjustments]] -> 6961779.8 | F10: Computers & Accessories | G10: Fixed Assets | H10: Non-Current Assets
A11: Assets | B11: Current Account-LITTLE MOUNT ANNASALAI-xxxxxxxxxx7205 | C11: =IFERROR(VLOOKUP(B11,'TB 2026'!$A$4:$E$155,5,),0) -> 25939002 | E11: =Table2[[#This Row],[Balance as on 31-03-2026]]+Table2[[#This Row],[Adjustments]] -> 25939002 | F11: - in current account | G11: Cash and cash equivalents | H11: Current Asset
A12: Assets | B12: Deposits - Rental Advance Coimbatore | C12: =IFERROR(VLOOKUP(B12,'TB 2026'!$A$4:$E$155,5,),0) -> 2354801 | E12: =Table2[[#This Row],[Balance as on 31-03-2026]]+Table2[[#This Row],[Adjustments]] -> 2354801 | F12: Security Deposit | G12: Long Term Loans & Advances | H12: Non-Current Assets
A13: Assets | B13: Deposits - Rental Advance Kochi | C13: =IFERROR(VLOOKUP(B13,'TB 2026'!$A$4:$E$155,5,),0) -> 1537200 | E13: =Table2[[#This Row],[Balance as on 31-03-2026]]+Table2[[#This Row],[Adjustments]] -> 1537200 | F13: Security Deposit | G13: Long Term Loans & Advances | H13: Non-Current Assets
A14: Assets | B14: Deposits - Rental Advance Temple Steps | C14: =IFERROR(VLOOKUP(B14,'TB 2026'!$A$4:$E$155,5,),0) -> 1680000 | E14: =Table2[[#This Row],[Balance as on 31-03-2026]]+Table2[[#This Row],[Adjustments]] -> 1680000 | F14: Security Deposit | G14: Long Term Loans & Advances | H14: Non-Current Assets
A15: Assets | B15: Deposits - Rental Advance VLV Complex | C15: =IFERROR(VLOOKUP(B15,'TB 2026'!$A$4:$E$155,5,),0) -> 1102520 | E15: =Table2[[#This Row],[Balance as on 31-03-2026]]+Table2[[#This Row],[Adjustments]] -> 1102520 | F15: Security Deposit | G15: Long Term Loans & Advances | H15: Non-Current Assets
A16: Assets | B16: Deposits - Rental Advance:Rent Advance - Guindy | C16: =IFERROR(VLOOKUP(B16,'TB 2026'!$A$4:$E$155,5,),0) -> 2000000 | E16: =Table2[[#This Row],[Balance as on 31-03-2026]]+Table2[[#This Row],[Adjustments]] -> 2000000 | F16: Security Deposit | G16: Long Term Loans & Advances | H16: Non-Current Assets
A17: Assets | B17: Deposits - Rental Advance:Rental Deposit Computers | C17: =IFERROR(VLOOKUP(B17,'TB 2026'!$A$4:$E$155,5,),0) -> 40000 | E17: =Table2[[#This Row],[Balance as on 31-03-2026]]+Table2[[#This Row],[Adjustments]] -> 40000 | F17: Security Deposit | G17: Long Term Loans & Advances | H17: Non-Current Assets
A18: Assets | B18: Deposits - Rental Advance:Rental Deposit UPS | C18: =IFERROR(VLOOKUP(B18,'TB 2026'!$A$4:$E$155,5,),0) -> 24000 | E18: =Table2[[#This Row],[Balance as on 31-03-2026]]+Table2[[#This Row],[Adjustments]] -> 24000 | F18: Security Deposit | G18: Long Term Loans & Advances | H18: Non-Current Assets
... A21: Assets | B21: IDFC First Bank | C21: =IFERROR(VLOOKUP(B21,'TB 2026'!$A$4:$E$155,5,),0) -> 134628 | E21: =Table2[[#This Row],[Balance as on 31-03-2026]]+Table2[[#This Row],[Adjustments]] -> 134628 | F21: - in current account | G21: Cash and cash equivalents | H21: Current Asset
A22: Assets | B22: Input Tax Credits | C22: =IFERROR(VLOOKUP(B22,'TB 2026'!$A$4:$E$155,5,),0) -> 0 | E22: =Table2[[#This Row],[Balance as on 31-03-2026]]+Table2[[#This Row],[Adjustments]] -> 0
A23: Assets | B23: Input CGST | C23: =IFERROR(VLOOKUP(B23,'TB 2026'!$A$4:$E$155,5,),0) -> 129394.01 | E23: =Table2[[#This Row],[Balance as on 31-03-2026]]+Table2[[#This Row],[Adjustments]] -> 129394.01 | F23: Balance with Government Authorities | G23: Other Current Assets | H23: Current Asset
A24: Assets | B24: Input IGST | C24: =IFERROR(VLOOKUP(B24,'TB 2026'!$A$4:$E$155,5,),0) -> 128160.6 | E24: =Table2[[#This Row],[Balance as on 31-03-2026]]+Table2[[#This Row],[Adjustments]] -> 128160.6 | F24: Balance with Government Authorities | G24: Other Current Assets | H24: Current Asset
A25: Assets | B25: Input SGST | C25: =IFERROR(VLOOKUP(B25,'TB 2026'!$A$4:$E$155,5,),0) -> 129394 | E25: =Table2[[#This Row],[Balance as on 31-03-2026]]+Table2[[#This Row],[Adjustments]] -> 129394 | F25: Balance with Government Authorities | G25: Other Current Assets | H25: Current Asset
A26: Assets | B26: Petty Cash | C26: =IFERROR(VLOOKUP(B26,'TB 2026'!$A$4:$E$155,5,),0) -> 162254 | E26: =Table2[[#This Row],[Balance as on 31-03-2026]]+Table2[[#This Row],[Adjustments]] -> 162254 | F26: Cash on hand | G26: Cash and cash equivalents | H26: Current Asset
A27: Assets | B27: Prepaid Expenses | C27: =IFERROR(VLOOKUP(B27,'TB 2026'!$A$4:$E$155,5,),0) -> 87762.95 | D27: -87762.95 | E27: =Table2[[#This Row],[Balance as on 31-03-2026]]+Table2[[#This Row],[Adjustments]] -> 0 | F27: Prepaid Expenses | G27: Other Current Assets | H27: Current Asset
A28: Assets | B28: Prepaid Insurance | C28: =IFERROR(VLOOKUP(B28,'TB 2026'!$A$4:$E$155,5,),0) -> 0 | E28: =Table2[[#This Row],[Balance as on 31-03-2026]]+Table2[[#This Row],[Adjustments]] -> 0
A29: Assets | B29: Printers | C29: =IFERROR(VLOOKUP(B29,'TB 2026'!$A$4:$E$155,5,),0) -> 112464.41 | E29: =Table2[[#This Row],[Balance as on 31-03-2026]]+Table2[[#This Row],[Adjustments]] -> 112464.41 | F29: Printer | G29: Fixed Assets | H29: Non-Current Assets
A30: Assets | B30: Refund Due FY25 | C30: =IFERROR(VLOOKUP(B30,'TB 2026'!$A$4:$E$155,5,),0) -> 0 | E30: =Table2[[#This Row],[Balance as on 31-03-2026]]+Table2[[#This Row],[Adjustments]] -> 0
A31: Assets | B31: Reverse Charge Tax Input but not due | C31: =IFERROR(VLOOKUP(B31,'TB 2026'!$A$4:$E$155,5,),0) -> 612.38 | E31: =Table2[[#This Row],[Balance as on 31-03-2026]]+Table2[[#This Row],[Adjustments]] -> 612.38 | F31: Balance with Government Authorities | G31: Other Current Assets | H31: Current Asset
A32: Assets | B32: Salary Advance | C32: =IFERROR(VLOOKUP(B32,'TB 2026'!$A$4:$E$155,5,),0) -> 1970785 | E32: =Table2[[#This Row],[Balance as on 31-03-2026]]+Table2[[#This Row],[Adjustments]] -> 1970785 | F32: Employee Advances | G32: Long Term Loans & Advances | H32: Non-Current Assets
A33: Assets | B33: TDS Receivable AY 25-26 | C33: =IFERROR(VLOOKUP(B33,'TB 2026'!$A$4:$E$155,5,),0) -> 0 | E33: =Table2[[#This Row],[Balance as on 31-03-2026]]+Table2[[#This Row],[Adjustments]] -> 0
A34: Assets | B34: TDS Receivable AY 26-27 | C34: =IFERROR(VLOOKUP(B34,'TB 2026'!$A$4:$E$155,5,),0) -> 11912617 | E34: =Table2[[#This Row],[Balance as on 31-03-2026]]+Table2[[#This Row],[Adjustments]] -> 11912617 | F34: Balance with Government Authorities | G34: Other Current Assets | H34: Current Asset
A35: Assets | B35: Telephone | C35: =IFERROR(VLOOKUP(B35,'TB 2026'!$A$4:$E$155,5,),0) -> 3110.16 | E35: =Table2[[#This Row],[Balance as on 31-03-2026]]+Table2[[#This Row],[Adjustments]] -> 3110.16 | F35: Office Equipments | G35: Fixed Assets | H35: Non-Current Assets
A36: Assets | B36: Undeposited Funds | C36: =IFERROR(VLOOKUP(B36,'TB 2026'!$A$4:$E$155,5,),0) -> 0 | E36: =Table2[[#This Row],[Balance as on 31-03-2026]]+Table2[[#This Row],[Adjustments]] -> 0
A37: Liabilities | B37: Accounts Payable | C37: =IFERROR(VLOOKUP(B37,'TB 2026'!$A$4:$E$155,5,),0) -> -15989116 | D37: =-'TB 2026'!H41 -> 8820 | E37: =Table2[[#This Row],[Balance as on 31-03-2026]]+Table2[[#This Row],[Adjustments]] -> -15980296 | F37: -total outstanding dues of creditors other than micro and small enterprises | G37: Trade Payables | H37: Current Liabilities
A38: Liabilities | B38: Accounts payable (Creditors) | C38: =IFERROR(VLOOKUP(B38,'TB 2026'!$A$4:$E$155,5,),0) -> -54850294 | D38: =-D86 -> 39479000 | E38: =Table2[[#This Row],[Balance as on 31-03-2026]]+Table2[[#This Row],[Adjustments]] -> -15371294 | F38: -total outstanding dues of creditors other than micro and small enterprises | G38: Trade Payables | H38: Current Liabilities
A39: Liabilities | B39: Deferred Income Tax | C39: =IFERROR(VLOOKUP(B39,'TB 2026'!$A$4:$E$155,5,),0) -> -64525.91 | D39: =-D98 -> 44864 | E39: =Table2[[#This Row],[Balance as on 31-03-2026]]+Table2[[#This Row],[Adjustments]] -> -19661.91 | F39: Impact of WDV difference on Property, plant and equipment | G39: Deferred tax liabilities (Net) | H39: Non-Current Liabilities
A40: Liabilities | B40: Directors Remuneration Payable | C40: =IFERROR(VLOOKUP(B40,'TB 2026'!$A$4:$E$155,5,),0) -> -4967905 | E40: =Table2[[#This Row],[Balance as on 31-03-2026]]+Table2[[#This Row],[Adjustments]] -> -4967905 | F40: Director Remuneration Payable | G40: Other Current Liabilities | H40: Current Liabilities
A41: Liabilities | B41: Earned leave Encashment Payable | C41: =IFERROR(VLOOKUP(B41,'TB 2026'!$A$4:$E$155,5,),0) -> -3000095 | E41: =Table2[[#This Row],[Balance as on 31-03-2026]]+Table2[[#This Row],[Adjustments]] -> -3000095 | F41: Provision for leave benefits | G41: Long Term Provisions | H41: Non-Current Liabilities
A42: Liabilities | B42: Employee Reimbursements | C42: =IFERROR(VLOOKUP(B42,'TB 2026'!$A$4:$E$155,5,),0) -> -104665.23 | E42: =Table2[[#This Row],[Balance as on 31-03-2026]]+Table2[[#This Row],[Adjustments]] -> -104665.23 | F42: Other Employee Payable | G42: Other Current Liabilities | H42: Current Liabilities
A43: Liabilities | B43: ESIC Payable | C43: =IFERROR(VLOOKUP(B43,'TB 2026'!$A$4:$E$155,5,),0) -> -186955 | E43: =Table2[[#This Row],[Balance as on 31-03-2026]]+Table2[[#This Row],[Adjustments]] -> -186955 | F43: Statutory dues including provident fund and tax deducted at source | G43: Other Current Liabilities | H43: Current Liabilities
A44: Liabilities | B44: Gratuity Payable | C44: =IFERROR(VLOOKUP(B44,'TB 2026'!$A$4:$E$155,5,),0) -> -1469911 | E44: =Table2[[#This Row],[Balance as on 31-03-2026]]+Table2[[#This Row],[Adjustments]] -> -1469911 | F44: Provision for gratuity | G44: Long Term Provisions | H44: Non-Current Liabilities
A45: Liabilities | B45: GST Payable | C45: =IFERROR(VLOOKUP(B45,'TB 2026'!$A$4:$E$155,5,),0) -> -2765559 | E45: =Table2[[#This Row],[Balance as on 31-03-2026]]+Table2[[#This Row],[Adjustments]] -> -2765559 | F45: Statutory dues including provident fund and tax deducted at source | G45: Other Current Liabilities | H45: Current Liabilities
A46: Liabilities | B46: Output CGST | C46: =IFERROR(VLOOKUP(B46,'TB 2026'!$A$4:$E$155,5,),0) -> 0 | E46: =Table2[[#This Row],[Balance as on 31-03-2026]]+Table2[[#This Row],[Adjustments]] -> 0
A47: Liabilities | B47: Output IGST | C47: =IFERROR(VLOOKUP(B47,'TB 2026'!$A$4:$E$155,5,),0) -> -612.34 | E47: =Table2[[#This Row],[Balance as on 31-03-2026]]+Table2[[#This Row],[Adjustments]] -> -612.34 | F47: Statutory dues including provident fund and tax deducted at source | G47: Other Current Liabilities | H47: Current Liabilities
A48: Liabilities | B48: Output SGST | C48: =IFERROR(VLOOKUP(B48,'TB 2026'!$A$4:$E$155,5,),0) -> 0 | E48: =Table2[[#This Row],[Balance as on 31-03-2026]]+Table2[[#This Row],[Adjustments]] -> 0
A49: Liabilities | B49: HDFC Credit Card *2119 | C49: =IFERROR(VLOOKUP(B49,'TB 2026'!$A$4:$E$155,5,),0) -> -259359.37 | E49: =Table2[[#This Row],[Balance as on 31-03-2026]]+Table2[[#This Row],[Adjustments]] -> -259359.37 | F49: Other Payable | G49: Other Current Liabilities | H49: Current Liabilities
A50: Liabilities | B50: HDFC Credit Card *6141 | C50: =IFERROR(VLOOKUP(B50,'TB 2026'!$A$4:$E$155,5,),0) -> -428924.27 | E50: =Table2[[#This Row],[Balance as on 31-03-2026]]+Table2[[#This Row],[Adjustments]] -> -428924.27 | F50: Other Payable | G50: Other Current Liabilities | H50: Current Liabilities
A51: Liabilities | B51: Incentive Payable | C51: =IFERROR(VLOOKUP(B51,'TB 2026'!$A$4:$E$155,5,),0) -> -1090369 | E51: =Table2[[#This Row],[Balance as on 31-03-2026]]+Table2[[#This Row],[Adjustments]] -> -1090369 | F51: Other Employee Payable | G51: Other Current Liabilities | H51: Current Liabilities
A52: Liabilities | B52: PF Payable | C52: =IFERROR(VLOOKUP(B52,'TB 2026'!$A$4:$E$155,5,),0) -> -2202753 | E52: =Table2[[#This Row],[Balance as on 31-03-2026]]+Table2[[#This Row],[Adjustments]] -> -2202753 | F52: Statutory dues including provident fund and tax deducted at source | G52: Other Current Liabilities | H52: Current Liabilities
A53: Liabilities | B53: Provision for Audit Fee | C53: =IFERROR(VLOOKUP(B53,'TB 2026'!$A$4:$E$155,5,),0) -> 0 | D53: -450000 | E53: =Table2[[#This Row],[Balance as on 31-03-2026]]+Table2[[#This Row],[Adjustments]] -> -450000 | F53: Provision for Audit fees | G53: Short Term Provisions | H53: Current Liabilities
A54: Liabilities | B54: Provision For Liabilities | C54: =IFERROR(VLOOKUP(B54,'TB 2026'!$A$4:$E$155,5,),0) -> 0 | E54: =Table2[[#This Row],[Balance as on 31-03-2026]]+Table2[[#This Row],[Adjustments]] -> 0
A55: Liabilities | B55: Provision for Taxation | C55: =IFERROR(VLOOKUP(B55,'TB 2026'!$A$4:$E$155,5,),0) -> 0 | D55: =-'Current Tax'!C24 -> -5200000 | E55: =Table2[[#This Row],[Balance as on 31-03-2026]]+Table2[[#This Row],[Adjustments]] -> -5200000 | F55: Provision for Taxation | G55: Short Term Provisions | H55: Current Liabilities
A56: Liabilities | B56: Provision for Litigation and Court claim | C56: =IFERROR(VLOOKUP(B56,'TB 2026'!$A$4:$E$155,5,),0) -> 0 | D56: -50000000 | E56: =Table2[[#This Row],[Balance as on 31-03-2026]]+Table2[[#This Row],[Adjustments]] -> -50000000 | F56: Provision for Litigation and Court claim | G56: Short Term Provisions | H56: Current Liabilities
A57: Liabilities | B57: PT Payable | C57: =IFERROR(VLOOKUP(B57,'TB 2026'!$A$4:$E$155,5,),0) -> -304841 | E57: =Table2[[#This Row],[Balance as on 31-03-2026]]+Table2[[#This Row],[Adjustments]] -> -304841 | F57: Statutory dues including provident fund and tax deducted at source | G57: Other Current Liabilities | H57: Current Liabilities
A58: Liabilities | B58: Referral Bonus Payable | C58: =IFERROR(VLOOKUP(B58,'TB 2026'!$A$4:$E$155,5,),0) -> -30000 | E58: =Table2[[#This Row],[Balance as on 31-03-2026]]+Table2[[#This Row],[Adjustments]] -> -30000 | F58: Other Employee Payable | G58: Other Current Liabilities | H58: Current Liabilities
A59: Liabilities | B59: Salary Payable | C59: =IFERROR(VLOOKUP(B59,'TB 2026'!$A$4:$E$155,5,),0) -> -14385984 | E59: =Table2[[#This Row],[Balance as on 31-03-2026]]+Table2[[#This Row],[Adjustments]] -> -14385984 | F59: Salary and Wages Payable | G59: Other Current Liabilities | H59: Current Liabilities
A60: Liabilities | B60: Spot Incentive Payable | C60: =IFERROR(VLOOKUP(B60,'TB 2026'!$A$4:$E$155,5,),0) -> 0 | E60: =Table2[[#This Row],[Balance as on 31-03-2026]]+Table2[[#This Row],[Adjustments]] -> 0
A61: Liabilities | B61: TDS Payable | C61: =IFERROR(VLOOKUP(B61,'TB 2026'!$A$4:$E$155,5,),0) -> -2742828 | E61: =Table2[[#This Row],[Balance as on 31-03-2026]]+Table2[[#This Row],[Adjustments]] -> -2742828 | F61: Statutory dues including provident fund and tax deducted at source | G61: Other Current Liabilities | H61: Current Liabilities
A62: Equities | B62: Retained Earnings | C62: =IFERROR(VLOOKUP(B62,'TB 2026'!$A$4:$E$155,5,),0) -> -44403081 | D62: =-'TB 2026'!H68 -> -8820 | E62: =Table2[[#This Row],[Balance as on 31-03-2026]]+Table2[[#This Row],[Adjustments]] -> -44411901 | F62: Opening balance
A63: Equities | B63: Share Capital | C63: =IFERROR(VLOOKUP(B63,'TB 2026'!$A$4:$E$155,5,),0) -> -100000 | E63: =Table2[[#This Row],[Balance as on 31-03-2026]]+Table2[[#This Row],[Adjustments]] -> -100000 | F63: Share Capital
A64: Income | B64: Home Loan Interest | C64: =IFERROR(VLOOKUP(B64,'TB 2026'!$A$4:$E$155,5,),0) -> -31353 | E64: =Table2[[#This Row],[Balance as on 31-03-2026]]+Table2[[#This Row],[Adjustments]] -> -31353 | F64: Interest on Staff Loans | G64: Other Income | H64: Income
A65: Income | B65: Income from Provision | C65: =IFERROR(VLOOKUP(B65,'TB 2026'!$A$4:$E$155,5,),0) -> -18125223 | D65: =-D5 -> -3795659.6 | E65: =Table2[[#This Row],[Balance as on 31-03-2026]]+Table2[[#This Row],[Adjustments]] -> -21920883 | F65: Sale of Services | G65: Revenue from Operations | H65: Income
A66: Income | B66: Interest Income | C66: =IFERROR(VLOOKUP(B66,'TB 2026'!$A$4:$E$155,5,),0) -> -3782232.6 | E66: =Table2[[#This Row],[Balance as on 31-03-2026]]+Table2[[#This Row],[Adjustments]] -> -3782232.6 | F66: Interest on FD | G66: Other Income | H66: Income
A67: Income | B67: Other Charges | C67: =IFERROR(VLOOKUP(B67,'TB 2026'!$A$4:$E$155,5,),0) -> -4.14 | E67: =Table2[[#This Row],[Balance as on 31-03-2026]]+Table2[[#This Row],[Adjustments]] -> -4.14 | F67: Miscellaneous Income | G67: Other Income | H67: Income
A68: Income | B68: Sales | C68: =IFERROR(VLOOKUP(B68,'TB 2026'!$A$4:$E$155,5,),0) -> -5.6851238e+08 | E68: =Table2[[#This Row],[Balance as on 31-03-2026]]+Table2[[#This Row],[Adjustments]] -> -5.6851238e+08 | F68: Sale of Services | G68: Revenue from Operations | H68: Income
A69: Income | B69: Sales Reimbursement | C69: =IFERROR(VLOOKUP(B69,'TB 2026'!$A$4:$E$155,5,),0) -> -11307687 | E69: =Table2[[#This Row],[Balance as on 31-03-2026]]+Table2[[#This Row],[Adjustments]] -> -11307687 | F69: Sale of Services | G69: Revenue from Operations | H69: Income
A70: Expense | B70: All Infra Related: Diesel & Water Charges | C70: =IFERROR(VLOOKUP(B70,'TB 2026'!$A$4:$E$155,5,),0) -> 530885 | E70: =Table2[[#This Row],[Balance as on 31-03-2026]]+Table2[[#This Row],[Adjustments]] -> 530885 | F70: Power & Fuel Expenses | G70: Other Expenses | H70: Expenses
A71: Expense | B71: All Infra Related: EB | C71: =IFERROR(VLOOKUP(B71,'TB 2026'!$A$4:$E$155,5,),0) -> 6899101.8 | E71: =Table2[[#This Row],[Balance as on 31-03-2026]]+Table2[[#This Row],[Adjustments]] -> 6899101.8 | F71: Power & Fuel Expenses | G71: Other Expenses | H71: Expenses
A72: Expense | B72: All Infra Related: Electrical & Electronic Consumables | C72: =IFERROR(VLOOKUP(B72,'TB 2026'!$A$4:$E$155,5,),0) -> 1087960.6 | E72: =Table2[[#This Row],[Balance as on 31-03-2026]]+Table2[[#This Row],[Adjustments]] -> 1087960.6 | F72: Consumption of Stores & Spares | G72: Other Expenses | H72: Expenses
A73: Expense | B73: All Infra Related: Internet & Communication-Internal | C73: =IFERROR(VLOOKUP(B73,'TB 2026'!$A$4:$E$155,5,),0) -> 870163.22 | D73: =-D27 -> 87762.95 | E73: =Table2[[#This Row],[Balance as on 31-03-2026]]+Table2[[#This Row],[Adjustments]] -> 957926.17 | F73: Internet and Telephone charges | G73: Other Expenses | H73: Expenses
A74: Expense | B74: All Infra Related: Internet & Communication-OPS | C74: =IFERROR(VLOOKUP(B74,'TB 2026'!$A$4:$E$155,5,),0) -> 7367968.7 | E74: =Table2[[#This Row],[Balance as on 31-03-2026]]+Table2[[#This Row],[Adjustments]] -> 7367968.7 | F74: Internet and Telephone charges | G74: Other Expenses | H74: Expenses
A75: Expense | B75: All Infra Related: Internet & Communication-OPS & Jewellery | C75: =IFERROR(VLOOKUP(B75,'TB 2026'!$A$4:$E$155,5,),0) -> 5749350 | E75: =Table2[[#This Row],[Balance as on 31-03-2026]]+Table2[[#This Row],[Adjustments]] -> 5749350 | F75: Internet and Telephone charges | G75: Other Expenses | H75: Expenses
A76: Expense | B76: All Infra Related: Repairs and Maintenance | C76: =IFERROR(VLOOKUP(B76,'TB 2026'!$A$4:$E$155,5,),0) -> 661181.49 | E76: =Table2[[#This Row],[Balance as on 31-03-2026]]+Table2[[#This Row],[Adjustments]] -> 661181.49 | F76: Repair & Maintenance - Plant & Machinery | G76: Other Expenses | H76: Expenses
A77: Expense | B77: All Infra Related: Software & Subscription Charges | C77: =IFERROR(VLOOKUP(B77,'TB 2026'!$A$4:$E$155,5,),0) -> 19105356 | E77: =Table2[[#This Row],[Balance as on 31-03-2026]]+Table2[[#This Row],[Adjustments]] -> 19105356 | F77: Software & Subscription Charges | G77: Other Expenses | H77: Expenses
A78: Expense | B78: All Infra Related: System Rental & Infra Rental | C78: =IFERROR(VLOOKUP(B78,'TB 2026'!$A$4:$E$155,5,),0) -> 2417612 | E78: =Table2[[#This Row],[Balance as on 31-03-2026]]+Table2[[#This Row],[Adjustments]] -> 2417612 | F78: Rent of Plant and Machinery | G78: Other Expenses | H78: Expenses
A79: Expense | B79: All Infra Related: UPS Rent | C79: =IFERROR(VLOOKUP(B79,'TB 2026'!$A$4:$E$155,5,),0) -> 1086000 | E79: =Table2[[#This Row],[Balance as on 31-03-2026]]+Table2[[#This Row],[Adjustments]] -> 1086000 | F79: Rent of Plant and Machinery | G79: Other Expenses | H79: Expenses
A80: Expense | B80: All Infra Related: Water Tax | C80: =IFERROR(VLOOKUP(B80,'TB 2026'!$A$4:$E$155,5,),0) -> 17448 | E80: =Table2[[#This Row],[Balance as on 31-03-2026]]+Table2[[#This Row],[Adjustments]] -> 17448 | F80: Office Expenses
A81: Expense | B81: All Miscellaneous Expenses: Printing and Stationery | C81: =IFERROR(VLOOKUP(B81,'TB 2026'!$A$4:$E$155,5,),0) -> 473064.78 | E81: =Table2[[#This Row],[Balance as on 31-03-2026]]+Table2[[#This Row],[Adjustments]] -> 473064.78 | F81: Printing & Stationery | G81: Other Expenses | H81: Expenses
A82: Expense | B82: All Miscellaneous Expenses:Couriers Expenses | C82: =IFERROR(VLOOKUP(B82,'TB 2026'!$A$4:$E$155,5,),0) -> 17109 | E82: =Table2[[#This Row],[Balance as on 31-03-2026]]+Table2[[#This Row],[Adjustments]] -> 17109 | F82: Postage and courier | G82: Other Expenses | H82: Expenses
A83: Expense | B83: All Miscellaneous Expenses:Housekeeping Expenses | C83: =IFERROR(VLOOKUP(B83,'TB 2026'!$A$4:$E$155,5,),0) -> 425975.4 | E83: =Table2[[#This Row],[Balance as on 31-03-2026]]+Table2[[#This Row],[Adjustments]] -> 425975.4 | F83: Office Expenses
A84: Expense | B84: All Miscellaneous Expenses:Insurance Expenses | C84: =IFERROR(VLOOKUP(B84,'TB 2026'!$A$4:$E$155,5,),0) -> 1941845.2 | E84: =Table2[[#This Row],[Balance as on 31-03-2026]]+Table2[[#This Row],[Adjustments]] -> 1941845.2 | F84: Insurance | G84: Other Expenses | H84: Expenses
A85: Expense | B85: All Miscellaneous Expenses:Pooja Expenses | C85: =IFERROR(VLOOKUP(B85,'TB 2026'!$A$4:$E$155,5,),0) -> 157986.88 | E85: =Table2[[#This Row],[Balance as on 31-03-2026]]+Table2[[#This Row],[Adjustments]] -> 157986.88 | F85: Office Expenses
A86: Expense | B86: All Other Direct Costs-User licences for algorithms | C86: =IFERROR(VLOOKUP(B86,'TB 2026'!$A$4:$E$155,5,),0) -> 121099248 | D86: -39479000 | E86: =Table2[[#This Row],[Balance as on 31-03-2026]]+Table2[[#This Row],[Adjustments]] -> 81620248 | F86: Direct Costs-User licences for algorithms | G86: Operating Expenses | H86: Expenses
A87: Expense | B87: All Other Direct Costs: Directors Remuneration | C87: =IFERROR(VLOOKUP(B87,'TB 2026'!$A$4:$E$155,5,),0) -> 0 | E87: =Table2[[#This Row],[Balance as on 31-03-2026]]+Table2[[#This Row],[Adjustments]] -> 0
A88: Expense | B88: Deepa Mahadevan | C88: =IFERROR(VLOOKUP(B88,'TB 2026'!$A$4:$E$155,5,),0) -> 15000000 | E88: =Table2[[#This Row],[Balance as on 31-03-2026]]+Table2[[#This Row],[Adjustments]] -> 15000000 | F88: Director's Salary | G88: Employee Benefit Expenses | H88: Expenses
A89: Expense | B89: Mahadevan Jayaraman | C89: =IFERROR(VLOOKUP(B89,'TB 2026'!$A$4:$E$155,5,),0) -> 23000000 | E89: =Table2[[#This Row],[Balance as on 31-03-2026]]+Table2[[#This Row],[Adjustments]] -> 23000000 | F89: Director's Salary | G89: Employee Benefit Expenses | H89: Expenses
A90: Expense | B90: All Other Direct Costs:Professional Fees for Analytics and UI/UX | C90: =IFERROR(VLOOKUP(B90,'TB 2026'!$A$4:$E$155,5,),0) -> 73739161 | E90: =Table2[[#This Row],[Balance as on 31-03-2026]]+Table2[[#This Row],[Adjustments]] -> 73739161 | F90: Direct Costs:Professional Fees for Analytics and UI/UX | G90: Operating Expenses | H90: Expenses
A91: Expense | B91: Bad Debt | C91: =IFERROR(VLOOKUP(B91,'TB 2026'!$A$4:$E$155,5,),0) -> -5000 | E91: =Table2[[#This Row],[Balance as on 31-03-2026]]+Table2[[#This Row],[Adjustments]] -> -5000 | F91: Bad debts recovered
A92: Expense | B92: Bank Fees and Charges | C92: =IFERROR(VLOOKUP(B92,'TB 2026'!$A$4:$E$155,5,),0) -> 18687.8 | E92: =Table2[[#This Row],[Balance as on 31-03-2026]]+Table2[[#This Row],[Adjustments]] -> 18687.8 | F92: Other Finance Costs | G92: Finance Costs | H92: Expenses
A93: Expense | B93: Campaigns-Advertising & Marketing | C93: =IFERROR(VLOOKUP(B93,'TB 2026'!$A$4:$E$155,5,),0) -> 140250 | E93: =Table2[[#This Row],[Balance as on 31-03-2026]]+Table2[[#This Row],[Adjustments]] -> 140250 | F93: Campaign Expenses | G93: Operating Expenses | H93: Expenses
A94: Expense | B94: Campaigns-Affiliate | C94: =IFERROR(VLOOKUP(B94,'TB 2026'!$A$4:$E$155,5,),0) -> 13749679 | E94: =Table2[[#This Row],[Balance as on 31-03-2026]]+Table2[[#This Row],[Adjustments]] -> 13749679 | F94: Campaign Expenses | G94: Operating Expenses | H94: Expenses
A95: Expense | B95: Campaigns-Expenses: Campaigns-Google | C95: =IFERROR(VLOOKUP(B95,'TB 2026'!$A$4:$E$155,5,),0) -> 26678141 | E95: =Table2[[#This Row],[Balance as on 31-03-2026]]+Table2[[#This Row],[Adjustments]] -> 26678141 | F95: Campaign Expenses | G95: Operating Expenses | H95: Expenses
A96: Expense | B96: Campaigns-Facebook | C96: =IFERROR(VLOOKUP(B96,'TB 2026'!$A$4:$E$155,5,),0) -> 29994931 | E96: =Table2[[#This Row],[Balance as on 31-03-2026]]+Table2[[#This Row],[Adjustments]] -> 29994931 | F96: Campaign Expenses | G96: Operating Expenses | H96: Expenses
A97: Expense | B97: Data Payment | C97: =IFERROR(VLOOKUP(B97,'TB 2026'!$A$4:$E$155,5,),0) -> 887804 | E97: =Table2[[#This Row],[Balance as on 31-03-2026]]+Table2[[#This Row],[Adjustments]] -> 887804 | F97: Internet and Telephone charges | G97: Other Expenses | H97: Expenses
A98: Expense | B98: Deferred Tax Expense | C98: =IFERROR(VLOOKUP(B98,'TB 2026'!$A$4:$E$155,5,),0) -> 0 | D98: ='TB 2026'!G110 -> -44864 | E98: =Table2[[#This Row],[Balance as on 31-03-2026]]+Table2[[#This Row],[Adjustments]] -> -44864
A99: Expense | B99: Depreciation Expense | C99: =IFERROR(VLOOKUP(B99,'TB 2026'!$A$4:$E$155,5,),0) -> 0 | D99: =-'TB 2026'!H111 -> 2045608.1 | E99: =Table2[[#This Row],[Balance as on 31-03-2026]]+Table2[[#This Row],[Adjustments]] -> 2045608.1 | F99: Depreciation
A100: Expense | B100: Earned leave Encashment | C100: =IFERROR(VLOOKUP(B100,'TB 2026'!$A$4:$E$155,5,),0) -> 3254381 | E100: =Table2[[#This Row],[Balance as on 31-03-2026]]+Table2[[#This Row],[Adjustments]] -> 3254381 | F100: Gratuity and Leave Encashment | G100: Employee Benefit Expenses | H100: Expenses
A101: Expense | B101: Govt Filing charges | C101: =IFERROR(VLOOKUP(B101,'TB 2026'!$A$4:$E$155,5,),0) -> 866050 | E101: =Table2[[#This Row],[Balance as on 31-03-2026]]+Table2[[#This Row],[Adjustments]] -> 866050 | F101: Miscellaneous Expenses
A102: Expense | B102: Gratuity | C102: =IFERROR(VLOOKUP(B102,'TB 2026'!$A$4:$E$155,5,),0) -> 1469911 | E102: =Table2[[#This Row],[Balance as on 31-03-2026]]+Table2[[#This Row],[Adjustments]] -> 1469911 | F102: Gratuity and Leave Encashment | G102: Employee Benefit Expenses | H102: Expenses
A103: Expense | B103: Housekeeping Charges Off-roll | C103: =IFERROR(VLOOKUP(B103,'TB 2026'!$A$4:$E$155,5,),0) -> 1641826.3 | E103: =Table2[[#This Row],[Balance as on 31-03-2026]]+Table2[[#This Row],[Adjustments]] -> 1641826.3 | F103: Office Expenses
...

Sheet TB 2026
A1: Marketsof1 Analytical Marketing Services Private Limited Trial Balance Basis: Accrual From 01/04/2025 To 31/03/2026
A2: Account | B2: Opening Balance | C2: Debit | D2: Credit | E2: Closing Balance
A4: Assets
A5: Accounts Receivable | B5: 1242797.4 | C5: 6.8418768e+08 | D5: 6.8111306e+08 | E5: 4317419.3 | G5: 4317419.3 | H5: =E5-G5 -> 0
A6: Accounts Receivable (Debtors) | B6: 5000000 | C6: 23125223 | D6: 5000000 | E6: 23125223 | G6: 23125223 | H6: =E6-G6 -> 0
A7: Accumulated Depreciation | B7: -2836754 | C7: 0 | D7: 0 | E7: -2836754 | G7: -4882362.1 | H7: =E7-G7 -> 2045608.1
A8: Accured Interest On FD | B8: 171762.8 | C8: 149543.83 | D8: 171762.8 | E8: 149543.83 | G8: 149543.83 | H8: =E8-G8 -> 0
A9: Advance to Suppliers | B9: 174506.18 | C9: 4097931.8 | D9: 4191495.9 | E9: 80942.1 | G9: 80942.1 | H9: =E9-G9 -> 0
A10: computer software | B10: 50000 | C10: 0 | D10: 0 | E10: 50000 | G10: 50000 | H10: =E10-G10 -> 0
A11: Computers | B11: 4563131.4 | C11: 2398648.4 | D11: 0 | E11: 6961779.8 | G11: 6961779.8 | H11: =E11-G11 -> 0
A12: Current Account-LITTLE MOUNT ANNASALAI-xxxxxxxxxx7205 | B12: 1588011.2 | C12: 1.4059439e+09 | D12: 1.3815929e+09 | E12: 25939002 | G12: 25939002 | H12: =E12-G12 -> 0
A13: Deposits - Rental Advance Coimbatore | B13: 2354801 | C13: 0 | D13: 0 | E13: 2354801 | G13: 2354801 | H13: =E13-G13 -> 0
A14: Deposits - Rental Advance Kochi | B14: 0 | C14: 1537200 | D14: 0 | E14: 1537200 | G14: 1537200 | H14: =E14-G14 -> 0
A15: Deposits - Rental Advance Temple Steps | B15: 1680000 | C15: 0 | D15: 0 | E15: 1680000 | G15: 1680000 | H15: =E15-G15 -> 0
A16: Deposits - Rental Advance VLV Complex | B16: 1102520 | C16: 0 | D16: 0 | E16: 1102520 | G16: 1102520 | H16: =E16-G16 -> 0
... A27: Total for Input Tax Credits | B27: 101951.91 | C27: 52991568 | D27: 52706571 | E27: 386948.61 | G27: 386948.61 | H27: =E27-G27 -> 0
H28: =E28-G28 -> 0
A29: Petty Cash | B29: 130808 | C29: 1205000 | D29: 1173554 | E29: 162254 | G29: 162254 | H29: =E29-G29 -> 0
A30: Prepaid Expenses | B30: 24422.41 | C30: 4650581.2 | D30: 4587240.6 | E30: 87762.95 | G30: 87762.95 | H30: =E30-G30 -> 0
A31: Prepaid Insurance | B31: 372301.37 | C31: 0 | D31: 372301.37 | E31: 0 | G31: 0 | H31: =E31-G31 -> 0
A32: Printers | B32: 62574.58 | C32: 73949.15 | D32: 24059.32 | E32: 112464.41 | G32: 112464.41 | H32: =E32-G32 -> 0
A33: Refund Due FY25 | B33: 0 | C33: 649430 | D33: 649430 | E33: 0 | G33: 0 | H33: =E33-G33 -> 0
A34: Reverse Charge Tax Input but not due | B34: 0 | C34: 2524116.5 | D34: 2523504.1 | E34: 612.38 | G34: 612.38 | H34: =E34-G34 -> 0
A35: Salary Advance | B35: 207334 | C35: 3047500 | D35: 1284049 | E35: 1970785 | G35: 1970785 | H35: =E35-G35 -> 0
A36: TDS Receivable AY 25-26 | B36: 8554545.4 | C36: 0 | D36: 8554545.4 | E36: 0 | G36: 0 | H36: =E36-G36 -> 0
A37: TDS Receivable AY 26-27 | B37: 0 | C37: 11912617 | D37: 0 | E37: 11912617 | G37: 11912617 | H37: =E37-G37 -> 0
A38: Telephone | B38: 3110.16 | C38: 0 | D38: 0 | E38: 3110.16 | G38: 3110.16 | H38: =E38-G38 -> 0
A39: Undeposited Funds | B39: 0 | C39: 4226.43 | D39: 4226.43 | E39: 0 | G39: 0 | H39: =E39-G39 -> 0
A40: Liabilities | H40: =E40-G40 -> #VALUE!
A41: Accounts Payable | B41: -32007048 | C41: 3.7163775e+08 | D41: 3.5561982e+08 | E41: -15989116 | G41: -15980296 | H41: =E41-G41 -> -8820
A42: Accounts payable (Creditors) | B42: -231423.21 | C42: 231423.21 | D42: 54850294 | E42: -54850294 | G42: -54850294 | H42: =E42-G42 -> 0
A43: Deferred Income Tax | B43: -64525.91 | C43: 0 | D43: 0 | E43: -64525.91 | G43: -19661.91 | H43: =E43-G43 -> -44864
A44: Directors Remuneration Payable | B44: 0 | C44: 19784575 | D44: 24752480 | E44: -4967905 | G44: -4967905 | H44: =E44-G44 -> 0
A45: Earned leave Encashment Payable | B45: -79164 | C45: 370412 | D45: 3291343 | E45: -3000095 | G45: -3000095 | H45: =E45-G45 -> 0
A46: Employee Reimbursements | B46: 0 | C46: 1052080.4 | D46: 1156745.6 | E46: -104665.23 | G46: -104665.23 | H46: =E46-G46 -> 0
A47: ESIC Payable | B47: -220927 | C47: 2189756.5 | D47: 2155784.5 | E47: -186955 | G47: -186955 | H47: =E47-G47 -> 0
A48: Gratuity Payable | B48: 0 | C48: 0 | D48: 1469911 | E48: -1469911 | G48: -1469911 | H48: =E48-G48 -> 0
A49: GST Payable | B49: 283435 | C49: 53241012 | D49: 56290006 | E49: -2765559 | G49: -2765559 | H49: =E49-G49 -> 0
A50: Output CGST | B50: -61332.78 | C50: 1292351.3 | D50: 1231018.5 | E50: 0 | G50: 0 | H50: =E50-G50 -> 0
A51: Output IGST | B51: -27864.52 | C51: 1.0445694e+08 | D51: 1.0442969e+08 | E51: -612.34 | G51: -612.34 | H51: =E51-G51 -> 0
A52: Output SGST | B52: -61332.78 | C52: 1292351.3 | D52: 1231018.5 | E52: 0 | G52: 0 | H52: =E52-G52 -> 0
A53: Total for GST Payable | B53: 132904.92 | C53: 1.6028266e+08 | D53: 1.6318174e+08 | E53: -2766171.3 | G53: -2766171.3 | H53: =E53-G53 -> 0
H54: =E54-G54 -> 0
A55: HDFC Credit Card *2119 | B55: 0 | C55: 109683 | D55: 369042.37 | E55: -259359.37 | G55: -259359.37 | H55: =E55-G55 -> 0
A56: HDFC Credit Card *6141 | B56: -295215.86 | C56: 3891949.1 | D56: 4025657.5 | E56: -428924.27 | G56: -428924.27 | H56: =E56-G56 -> 0
A57: Incentive Payable | B57: -726307 | C57: 9191336 | D57: 9555398 | E57: -1090369 | G57: -1090369 | H57: =E57-G57 -> 0
A58: PF Payable | B58: -1528726 | C58: 21211999 | D58: 21886026 | E58: -2202753 | G58: -2202753 | H58: =E58-G58 -> 0
A59: Provision for Audit Fee | B59: -450000 | C59: 450000 | D59: 0 | E59: 0 | G59: 0 | H59: =E59-G59 -> 0
A60: Provision For Liabilities | B60: -8000000 | C60: 8000000 | D60: 0 | E60: 0 | G60: 0 | H60: =E60-G60 -> 0
A61: Provision for Taxation | B61: -8000000 | C61: 8000000 | D61: 0 | E61: 0 | G61: 0 | H61: =E61-G61 -> 0
A62: PT Payable | B62: -107180 | C62: 1260465 | D62: 1458126 | E62: -304841 | G62: -304841 | H62: =E62-G62 -> 0
A63: Referral Bonus Payable | B63: -33500 | C63: 517500 | D63: 514000 | E63: -30000 | G63: -30000 | H63: =E63-G63 -> 0
A64: Salary Payable | B64: -9089952 | C64: 143433520 | D64: 148729552 | E64: -14385984 | G64: -14385984 | H64: =E64-G64 -> 0
A65: Spot Incentive Payable | B65: 0 | C65: 389315 | D65: 389315 | E65: 0 | G65: 0 | H65: =E65-G65 -> 0
A66: TDS Payable | B66: -3111621 | C66: 33273871 | D66: 32905078 | E66: -2742828 | G66: -2742828 | H66: =E66-G66 -> 0
A67: Equities | H67: =E67-G67 -> #VALUE!
A68: Retained Earnings | B68: -44403081 | C68: 0 | D68: 0 | E68: -44403081 | G68: -44411901 | H68: =E68-G68 -> 8820
A69: Share Capital | B69: -100000 | C69: 0 | D69: 0 | E69: -100000 | G69: -100000 | H69: =E69-G69 -> 0
A70: Income | H70: =E70-G70 -> #VALUE!
A71: Home Loan Interest | B71: 0 | C71: 0 | D71: 31353 | E71: -31353 | G71: -31353 | H71: =E71-G71 -> 0
A72: Income from Provision | B72: 0 | C72: 5000000 | D72: 23125223 | E72: -18125223 | G72: -18125223 | H72: =E72-G72 -> 0
A73: Interest Income | B73: 0 | C73: 0 | D73: 3782232.6 | E73: -3782232.6 | G73: -3782232.6 | H73: =E73-G73 -> 0
A74: Other Charges | B74: 0 | C74: 0 | D74: 4.14 | E74: -4.14 | G74: -4.14 | H74: =E74-G74 -> 0
A75: Sales | B75: 0 | C75: 0 | D75: 5.6851238e+08 | E75: -5.6851238e+08 | G75: -5.6851238e+08 | H75: =E75-G75 -> 0.029999971
A76: Sales Reimbursement | B76: 0 | C76: 0 | D76: 11307687 | E76: -11307687 | G76: -11307687 | H76: =E76-G76 -> 0
A77: Total for Sales | B77: 0 | C77: 0 | D77: 5.7982007e+08 | E77: -5.7982007e+08 | G77: -5.7982007e+08 | H77: =E77-G77 -> 0.0099999905
H78: =E78-G78 -> 0
A79: Expense | H79: =E79-G79 -> #VALUE!
A80: All Infra Related: Diesel & Water Charges | B80: 0 | C80: 530885 | D80: 0 | E80: 530885 | G80: 530885 | H80: =E80-G80 -> 0
A81: All Infra Related: EB | B81: 0 | C81: 6899101.8 | D81: 0 | E81: 6899101.8 | G81: 6899101.8 | H81: =E81-G81 -> 0
A82: All Infra Related: Electrical & Electronic Consumables | B82: 0 | C82: 1174930.8 | D82: 86970.23 | E82: 1087960.6 | G82: 1087960.6 | H82: =E82-G82 -> 0
A83: All Infra Related: Internet & Communication-Internal | B83: 0 | C83: 942963.18 | D83: 72799.96 | E83: 870163.22 | G83: 870163.22 | H83: =E83-G83 -> 0
A84: All Infra Related: Internet & Communication-OPS | B84: 0 | C84: 7881452.1 | D84: 513483.35 | E84: 7367968.7 | G84: 7367968.7 | H84: =E84-G84 -> 0
A85: All Infra Related: Internet & Communication-OPS & Jewellery | B85: 0 | C85: 5749350 | D85: 0 | E85: 5749350 | G85: 5749350 | H85: =E85-G85 -> 0
A86: All Infra Related: Repairs and Maintenance | B86: 0 | C86: 707546.49 | D86: 46365 | E86: 661181.49 | G86: 661181.49 | H86: =E86-G86 -> 0
A87: All Infra Related: Software & Subscription Charges | B87: 0 | C87: 19116448 | D87: 11092 | E87: 19105356 | G87: 19105356 | H87: =E87-G87 -> 0
A88: All Infra Related: System Rental & Infra Rental | B88: 0 | C88: 2417612 | D88: 0 | E88: 2417612 | G88: 2417612 | H88: =E88-G88 -> 0
A89: All Infra Related: UPS Rent | B89: 0 | C89: 1086000 | D89: 0 | E89: 1086000 | G89: 1086000 | H89: =E89-G89 -> 0
A90: All Infra Related: Water Tax | B90: 0 | C90: 17448 | D90: 0 | E90: 17448 | G90: 17448 | H90: =E90-G90 -> 0
A91: All Miscellaneous Expenses: Printing and Stationery | B91: 0 | C91: 473064.78 | D91: 0 | E91: 473064.78 | G91: 473064.78 | H91: =E91-G91 -> 0
... A100: Total for All Other Direct Costs: Directors Remuneration | B100: 0 | C100: 38000000 | D100: 0 | E100: 38000000 | G100: 38000000 | H100: =E100-G100 -> 0
H101: =E101-G101 -> 0
A102: All Other Direct Costs:Professional Fees for Analytics and UI/UX | B102: 0 | C102: 73739161 | D102: 0 | E102: 73739161 | G102: 73739161 | H102: =E102-G102 -> 0
A103: Bad Debt | B103: 0 | C103: 0 | D103: 5000 | E103: -5000 | G103: -5000 | H103: =E103-G103 -> 0
A104: Bank Fees and Charges | B104: 0 | C104: 21277.8 | D104: 2590 | E104: 18687.8 | G104: 18687.8 | H104: =E104-G104 -> 0
A105: Campaigns-Advertising & Marketing | B105: 0 | C105: 140250 | D105: 0 | E105: 140250 | G105: 140250 | H105: =E105-G105 -> 0
A106: Campaigns-Affiliate | B106: 0 | C106: 13926053 | D106: 176373.41 | E106: 13749679 | G106: 13749679 | H106: =E106-G106 -> 0
A107: Campaigns-Expenses: Campaigns-Google | B107: 0 | C107: 26678141 | D107: 0 | E107: 26678141 | G107: 26678141 | H107: =E107-G107 -> 0
A108: Campaigns-Facebook | B108: 0 | C108: 29994945 | D108: 14 | E108: 29994931 | G108: 29994931 | H108: =E108-G108 -> 0
A109: Data Payment | B109: 0 | C109: 887804 | D109: 0 | E109: 887804 | G109: 887804 | H109: =E109-G109 -> 0
G110: -44864 | H110: =E110-G110 -> 44864
G111: 2045608.1 | H111: =E111-G111 -> -2045608.1
A112: Earned leave Encashment | B112: 0 | C112: 3291343 | D112: 36962 | E112: 3254381 | G112: 3254381 | H112: =E112-G112 -> 0
A113: Govt Filing charges | B113: 0 | C113: 881750 | D113: 15700 | E113: 866050 | G113: 866050 | H113: =E113-G113 -> 0
A114: Gratuity | B114: 0 | C114: 1469911 | D114: 0 | E114: 1469911 | G114: 1469911 | H114: =E114-G114 -> 0
A115: Housekeeping Charges Off-roll | B115: 0 | C115: 1641826.3 | D115: 0 | E115: 1641826.3 | G115: 1641826.3 | H115: =E115-G115 -> 0
A116: Labour Welfare Fund | B116: 0 | C116: 26225.26 | D116: 0 | E116: 26225.26 | G116: 26225.26 | H116: =E116-G116 -> 0
A117: Legal Fees | B117: 0 | C117: 4382500 | D117: 0 | E117: 4382500 | G117: 4382500 | H117: =E117-G117 -> 0
A118: Non-Payroll & Professional Expenses: Company Secretary Fees | B118: 0 | C118: 164449 | D118: 0 | E118: 164449 | G118: 164449 | H118: =E118-G118 -> 0
A119: Non-Payroll & Professional Expenses:Accounting & Audit Charges | B119: 0 | C119: 2935260 | D119: 1142460.2 | E119: 1792799.8 | G119: 1792799.8 | H119: =E119-G119 -> 0
...

Sheet TB 2025
A1: Marketsof1 Analytical Marketing Services Private Limited Trial Balance Basis: Accrual From 01/03/2024 To 31/03/2025
A2: Account | B2: Opening Balance | C2: Debit | D2: Credit | E2: Closing Balance
A4: Assets
A5: Accounts Receivable | B5: 0 | C5: 5.8980937e+08 | D5: 5.8856657e+08 | E5: 1242797.4
A6: Accounts Receivable (Debtors) | B6: 0 | C6: 5500000 | D6: 500000 | E6: 5000000
A7: Accumulated Depreciation | B7: -1283683.2 | C7: 0 | D7: 1553070.8 | E7: -2836754
A8: Accured Interest On FD | B8: 211719.75 | C8: 255725 | D8: 295681.95 | E8: 171762.8
A9: Advance to Suppliers | B9: 71131.91 | C9: 2110505.9 | D9: 2007131.6 | E9: 174506.18
A10: Amazon Pay | B10: 0 | C10: 720.1 | D10: 720.1 | E10: 0
A11: computer software | B11: 50000 | C11: 0 | D11: 0 | E11: 50000
A12: Computers | B12: 2548918.1 | C12: 2014213.3 | D12: 0 | E12: 4563131.4
A13: Current Account-LITTLE MOUNT ANNASALAI-xxxxxxxxxx7205 | B13: 2435995.1 | C13: 1.097068e+09 | D13: 1.0979159e+09 | E13: 1588011.2
A14: Deposits - Rental Advance Coimbatore | B14: 0 | C14: 2354801 | D14: 0 | E14: 2354801
A15: Deposits - Rental Advance Temple Steps | B15: 1680000 | C15: 0 | D15: 0 | E15: 1680000
A16: Deposits - Rental Advance VLV Complex | B16: 1102520 | C16: 0 | D16: 0 | E16: 1102520
... A20: Fixed Deposit | B20: 41338890 | C20: 612515000 | D20: 611433369 | E20: 42420521
A21: Furniture and Equipment | B21: 2457557.2 | C21: 178413.96 | D21: 0 | E21: 2635971.2 | F21: 2640971.2 | G21: =E21-F21 -> -5000
A22: IDFC First Bank | B22: 1500191.1 | C22: 3.4709906e+08 | D22: 310951798 | E22: 37647450
A23: Input Tax Credits | B23: 0 | C23: 0 | D23: 0 | E23: 0
A24: Input CGST | B24: 67045.41 | C24: 22654609 | D24: 22670719 | E24: 50935.6
A25: Input IGST | B25: 11422.71 | C25: 9704469.6 | D25: 9715811.6 | E25: 80.71
A26: Input SGST | B26: 67045.41 | C26: 22654609 | D26: 22670719 | E26: 50935.6
A27: Total for Input Tax Credits | B27: 145513.53 | C27: 55013687 | D27: 55057249 | E27: 101951.91
A29: Petty Cash | B29: 149668 | C29: 1471111 | D29: 1489971 | E29: 130808
A30: Prepaid Expenses | B30: 0 | C30: 3082301.1 | D30: 3057878.7 | E30: 24422.41
A31: Prepaid Insurance | B31: 0 | C31: 722707.11 | D31: 350405.74 | E31: 372301.37
A32: Printers | B32: 42372.04 | C32: 42849.59 | D32: 22647.05 | E32: 62574.58
A33: Refund Due FY24 | B33: 0 | C33: 2485995 | D33: 2485995 | E33: 0
A34: Reverse Charge Tax Input but not due | B34: 20468.77 | C34: 509940.11 | D34: 530408.88 | E34: 0
... A39: Undeposited Funds | B39: 0 | C39: 12900.1 | D39: 12900.1 | E39: 0
A40: Liabilities
A41: Accounts Payable | B41: -28896199 | C41: 3.6011723e+08 | D41: 3.6321926e+08 | E41: -31998228
A42: Accounts payable (Creditors) | B42: 0 | C42: 1018636 | D42: 1250059.2 | E42: -231423.21
A43: Deferred Income Tax | B43: 12118.09 | C43: 0 | D43: 109992.7 | E43: -97874.61 | F43: 64526 | G43: =-E43-F43 -> 33348.61
A44: Earned leave Encashment Payable | B44: -27622 | C44: 311603 | D44: 363145 | E44: -79164
A45: Employee Reimbursements | B45: 0 | C45: 510463.02 | D45: 510463.02 | E45: 0
A46: ESIC Payable | B46: -189951 | C46: 2530742 | D46: 2561718 | E46: -220927
A47: GST Payable | B47: -640096.3 | C47: 36701715 | D47: 35778184 | E47: 283435
A48: Output CGST | B48: 0 | C48: 172433.72 | D48: 233766.5 | E48: -61332.78
A49: Output IGST | B49: 0.72 | C49: 89986675 | D49: 90014540 | E49: -27864.52
A50: Output SGST | B50: 0 | C50: 172433.72 | D50: 233766.5 | E50: -61332.78
A51: Total for GST Payable | B51: -640095.58 | C51: 1.2703326e+08 | D51: 1.2626026e+08 | E51: 132904.92
A53: HDFC Credit Card *6141 | B53: -234041.56 | C53: 2083327.4 | D53: 2144501.7 | E53: -295215.86
A54: Incentive Payable | B54: -363343 | C54: 6146567 | D54: 6509531 | E54: -726307
A55: PF Payable | B55: -1041064 | C55: 16683515 | D55: 17171177 | E55: -1528726
A56: Provision for Audit Fee | B56: 0 | C56: 0 | D56: 450000 | E56: -450000
... A64: TDS Payable | B64: -1793256 | C64: 23459458 | D64: 24777823 | E64: -3111621
A65: Equities
A66: Current Year Earnings | B66: -9358056.4 | C66: 0 | D66: 0 | E66: -9358056.4
A67: Retained Earnings | B67: -9064410.5 | C67: 0 | D67: 0 | E67: -9064410.5
A68: Share Capital | B68: -100000 | C68: 0 | D68: 0 | E68: -100000
A71: Income
A72: Income from Provision | B72: 0 | C72: 500000 | D72: 5500000 | E72: -5000000
A73: Interest Income | B73: 0 | C73: 36330.2 | D73: 3626184 | E73: -3589853.8
A74: Interest on Income Tax Refund | B74: 0 | C74: 0 | D74: 111865 | E74: -111865
A75: Other Charges | B75: 0 | C75: 0 | D75: 7.17 | E75: -7.17
A76: Sales | B76: 0 | C76: 0 | D76: 4.9969736e+08 | E76: -4.9969736e+08
A77: Sales Reimbursement | B77: 0 | C77: 0 | D77: 141090 | E77: -141090
A78: Total for Sales | B78: 0 | C78: 0 | D78: 4.9983845e+08 | E78: -4.9983845e+08
A80: Expense
A81: All Infra Related: Diesel Charges | B81: 0 | C81: 303863 | D81: 0 | E81: 303863
A82: All Infra Related: EB | B82: 0 | C82: 5378209.7 | D82: 0 | E82: 5378209.7
A83: All Infra Related: Electrical & Electronic Consumables | B83: 0 | C83: 873540.31 | D83: 31320 | E83: 842220.31
A84: All Infra Related: Internet & Communication-Internal | B84: 0 | C84: 1002267.3 | D84: 87047.53 | E84: 915219.74
A85: All Infra Related: Internet & Communication-OPS | B85: 0 | C85: 5872920.4 | D85: 290752.47 | E85: 5582167.9
A86: All Infra Related: Internet & Communication-OPS & Jewellery | B86: 0 | C86: 3631400 | D86: 0 | E86: 3631400
A87: All Infra Related: Repairs and Maintenance | B87: 0 | C87: 1039734.4 | D87: 637.29 | E87: 1039097.2
A88: All Infra Related: Software & Subscription Charges | B88: 0 | C88: 10545745 | D88: 5252 | E88: 10540493
A89: All Infra Related: System Rental & Infra Rental | B89: 0 | C89: 2992646.2 | D89: 0 | E89: 2992646.2
A90: All Infra Related: UPS Rent | B90: 0 | C90: 853000 | D90: 0 | E90: 853000
A91: All Infra Related: Water Tax | B91: 0 | C91: 51852 | D91: 0 | E91: 51852
A92: All Miscellaneous Expenses: Printing and Stationery | B92: 0 | C92: 347453.97 | D92: 19046.1 | E92: 328407.87
... A149: Travel Expenses:Outstation | B149: 0 | C149: 94929.59 | D149: 13705.34 | E149: 81224.25
A150: Total for Trial Balance | C150: 3.8777697e+09 | D150: 3.8777697e+09
A156: Marketsof1 Analytical Marketing Services Private Limited Trial Balance Basis: Accrual From 01/04/2024 To 31/03/2025
A157: Account | B157: Opening Balance | C157: Debit | D157: Credit | E157: Closing Balance
A159: Assets
A160: Accounts Receivable | B160: 0 | C160: 5.2996289e+08 | D160: 5.287201e+08 | E160: 1242797.4
A161: Accounts Receivable (Debtors) | B161: 500000 | C161: 5000000 | D161: 500000 | E161: 5000000
A162: Accumulated Depreciation | B162: -1473367.1 | C162: 0 | D162: 1363386.9 | E162: -2836754
A163: Accured Interest On FD | B163: 217386.25 | C163: 171762.5 | D163: 217386.25 | E163: 171762.5
A164: Advance to Suppliers | B164: 20000 | C164: 2110505.9 | D164: 1955999.7 | E164: 174506.18
A165: Amazon Pay | B165: 0 | C165: 720.1 | D165: 720.1 | E165: 0
A166: computer software | B166: 50000 | C166: 0 | D166: 0 | E166: 50000
A167: Computers | B167: 2548918.1 | C167: 2014213.3 | D167: 0 | E167: 4563131.4
A168: Current Account-LITTLE MOUNT ANNASALAI-xxxxxxxxxx7205 | B168: 2077191.4 | C168: 1.0021923e+09 | D168: 1.0026815e+09 | E168: 1588011.2
A169: Deposits - Rental Advance Coimbatore | B169: 0 | C169: 2354801 | D169: 0 | E169: 2354801
A170: Deposits - Rental Advance Temple Steps | B170: 1680000 | C170: 0 | D170: 0 | E170: 1680000
A171: Deposits - Rental Advance VLV Complex | B171: 1102520 | C171: 0 | D171: 0 | E171: 1102520
... A194: Undeposited Funds | B194: 0 | C194: 12900.1 | D194: 12900.1 | E194: 0
A195: Liabilities
A196: Accounts Payable | B196: -32887781 | C196: 3.3340882e+08 | D196: 3.3251926e+08 | E196: -31998228
A197: Accounts payable (Creditors) | B197: -1012506 | C197: 1018636 | D197: 237553.21 | E197: -231423.21
A198: Deferred Income Tax | B198: -75455.91 | C198: 0 | D198: 0 | E198: -75455.91
A199: Earned leave Encashment Payable | B199: -27622 | C199: 311603 | D199: 363145 | E199: -79164
A200: Employee Reimbursements | B200: 0 | C200: 498924.2 | D200: 498924.2 | E200: 0
A201: ESIC Payable | B201: -203545 | C201: 2340791 | D201: 2358173 | E201: -220927
A202: GST Payable | B202: -4591551 | C202: 36061619 | D202: 31186633 | E202: 283435
A203: Output CGST | B203: 0 | C203: 172433.72 | D203: 233766.5 | E203: -61332.78
A204: Output IGST | B204: 0 | C204: 80855876 | D204: 80883740 | E204: -27864.52
...

Sheet Sub Schedule P & L
B2: =+'Sub Schedule BS'!B2:E2 -> MARKETSOF1 ANALYTICAL MARKETING SERVICES PRIVATE LIMITED
B3: Notes forming part of Financial Statements as on March 31, 2025
C4: For the year ended 31.03.2025 | D4: For the year ended 31.03.2024 | E4: For the year ended 31.03.2023
B6: (i) Revenue From Services
B7: - Digital Design
B8: - Digital Profile | E8: 76544665
B9: - FTE & Sales Process | E9: 47773061
B10: - MLMS | E10: 12882556
B11: - Offline Profile-Affiliate | E11: 32790159
B12: - Project operation | E12: 23810000
B13: - Services | E13: 0
B14: - Sales reimbursements | C14: 141090
C15: =448980007+C14 -> 449121097 | D15: =#REF! -> #REF! | E15: =SUM(E7:E13) -> 1.9380044e+08
B17: (ii) Operating Expenses
E18: 0
B19: Campaign Expenses | C19: ='Groupings P &L'!C39 -> 41381396 | D19: ='Groupings P &L'!D39 -> #REF! | E19: 31685424
B20: Brokerage Expenses | D20: 0 | E20: 0
B21: ICT-Service | D21: =#REF! -> #REF! | E21: 10436080
B22: Provision for Expenses | D22: =+'Groupings P &L'!D24 -> 0 | E22: 0
B23: All Other Direct Costs-User licences for algorithms | C23: =92575050.64 -> 92575051 | D23: =#REF!+#REF! -> #REF! | E23: 46366000
B24: All Other Direct Costs:Professional Fees for Analytics and UI/UX | C24: 97545428 | D24: =#REF! -> #REF! | E24: 45750000
B25: All Other Direct Costs: Predictive modeling and updates | C25: 5000000
C26: =SUM(C18:C25) -> 2.3650187e+08 | D26: =SUM(D18:D25) -> #REF! | E26: =SUM(E18:E25) -> 1.342375e+08
B28: (iii) Salaries, wages and bonus
B29: Salaries & Wages | C29: 104050187 | D29: =#REF!+#REF! -> #REF! | E29: 30837186
B30: Bonus | C30: 0 | D30: 0 | E30: 0
B31: Performance Payouts | C31: =+'Groupings P &L'!C12 -> 6965842 | D31: =+'Groupings P &L'!D12 -> #REF! | E31: 2605633 | G31: =78438+894965+55361+148512.5+132000 -> 1309276.5
B32: Staff Recriitment expenses | C32: 310142.98 | D32: =#REF! -> #REF! | E32: 199000
B33: Earned leave encashment | C33: 363145 | D33: =#REF! -> #REF! | E33: 30225
C34: =SUM(C29:C33) -> 1.1168932e+08 | D34: =SUM(D29:D33) -> #REF! | E34: =SUM(E29:E33) -> 33672044
B36: (iv) Contribution to provident fund & NPS
B37: Contribution to EPF | C37: 7684444 | D37: =#REF! -> #REF! | E37: 2435672
C38: =SUM(C37:C37) -> 7684444 | D38: =SUM(D37:D37) -> #REF! | E38: =SUM(E37:E37) -> 2435672
B40: (v) Staff welfare expenses
B41: Staff Welfare Expenses | C41: =42650+9436453+8011+911763+313772+149000+2396807 -> 13258456 | D41: =#REF!+#REF!+#REF!+#REF!+#REF! -> #REF! | E41: 5675282.1
B42: Staff Entertainment | C42: 676925 | D42: =#REF! -> #REF! | E42: 395330.62
B43: Contribution to ESIC | C43: 1914430 | D43: =#REF! -> #REF! | E43: 786030
C44: =SUM(C41:C43) -> 15849811 | D44: =SUM(D41:D43) -> #REF! | E44: =SUM(E41:E43) -> 6856642.7
B46: (vi) Directors Remuneration
B47: Jayaram Iyer krishnamoorthy | D47: 0 | E47: 0
B48: Mahadevan Jayaraman | D48: 0 | E48: 0
D50: =SUM(D47:D49) -> 0 | E50: =SUM(E47:E49) -> 0
B51: (vi) Printing & Stationery
B52: Printing and stationery | C52: 310043.21 | D52: =#REF! -> #REF! | E52: 154631.84
B53: Subscriptions | C53: 10280672 | D53: =#REF! -> #REF! | E53: 387540.57
C54: =SUM(C52:C53) -> 10590715 | D54: =SUM(D52:D53) -> #REF! | E54: =SUM(E52:E53) -> 542172.41
B56: (vii) Office Maintenance
B57: Office Expenses | C57: =+'Groupings P &L'!C31 -> 3368227.9 | D57: =+'Groupings P &L'!D31 -> #REF! | E57: 818329.47
B58: Housekeeping expenses | C58: =226386.58+1089484.89 -> 1315871.5 | D58: =#REF!+#REF! -> #REF! | E58: 475152.5
B59: Security expense | C59: 729277.3 | D59: =#REF! -> #REF! | E59: 299310.5
B60: Other expenses | C60: ='Groupings P &L'!C52 -> 70904 | D60: ='Groupings P &L'!D52 -> #REF! | E60: 691038
C61: =SUM(C57:C60) -> 5484280.6 | D61: =SUM(D57:D60) -> #REF! | E61: =SUM(E57:E60) -> 2283830.5
B63: (viii) Travelling & Conveyance
B64: Domestic | C64: =173753+71597 -> 245350 | D64: =#REF!+#REF! -> #REF! | E64: 76000.84
B65: Foreign | E65: 0
C66: =SUM(C64:C65) -> 245350 | D66: =SUM(D64:D65) -> #REF! | E66: =SUM(E64:E65) -> 76000.84

Sheet Groupings P &L
B2: MARKETSOF1 ANALYTICAL MARKETING SERVICES PRIVATE LIMITED
B3: Notes forming part of Financial Statements
C4: For the year ended 31.03.2025 | D4: For the year ended 31.03.2024 | E4: For the year ended 31.03.2023
B6: (i) Performance payout
B7: Attendance Bonus | E7: 0
B8: Holiday pay | E8: 0
B9: Incentive | C9: 5927627 | D9: =#REF! -> #REF! | E9: 2154508
B10: Spot Incentive | C10: 349215 | D10: =#REF! -> #REF! | E10: 224125
B11: Referral Bonus | C11: 689000 | D11: =#REF! -> #REF! | E11: 227000
C12: =SUM(C7:C11) -> 6965842 | D12: =SUM(D7:D11) -> #REF! | E12: =SUM(E7:E11) -> 2605633
B13: (ii) Rent
B14: System Rent | C14: 2540591.2 | D14: =#REF! -> #REF! | E14: 1449707.2
B15: UPS Rent | C15: 738000 | D15: =#REF! -> #REF! | E15: 284000
B16: Rent - VLV Complex | C16: 2708838 | D16: =#REF! -> #REF! | E16: 2297109
B17: Rent - Guindy | C17: 1777277 | D17: =#REF! -> #REF! | E17: 529250
B18: Rent for Temple Steps | C18: 3486000 | D18: =#REF! -> #REF!
B19: Rent for Coimbatore | C19: 549453
C20: =SUM(C14:C19) -> 11800159 | D20: =SUM(D14:D18) -> #REF! | E20: =SUM(E14:E17) -> 4560066.2
B21: (iii)Provision for Expenses
B22: Provision for Expenses
B23: Provision for COVID | D23: 0 | E23: 0
D24: =SUM(D22:D23) -> 0 | E24: =SUM(E22:E23) -> 0
B26: (iv) Office Expenses
B27: Pooja Expenses | C27: 111705.64 | D27: =#REF! -> #REF! | E27: 44250
B28: Office Expenses | C28: 110292.21 | D28: =#REF! -> #REF! | E28: 34902.39
B29: Office Maintenance Charges | C29: =28419+193706+840000+1354416 -> 2416541 | D29: =#REF!+#REF!+#REF! -> #REF! | E29: 269315
B30: Electrical & Electronic Consumables | C30: 729689 | D30: =#REF! -> #REF! | E30: 469862.08
C31: =SUM(C27:C30) -> 3368227.9 | D31: =SUM(D27:D30) -> #REF! | E31: =SUM(E27:E30) -> 818329.47
B33: (v) Campaigns Expenses
B35: Campaigns-Affiliate | C35: 9856490.7 | D35: =#REF! -> #REF! | E35: 7431935.4
B36: Campaigns-Facebook | C36: 1402539 | D36: =#REF! -> #REF! | E36: 3042747.1
B37: Campaigns-Google | C37: 30122366 | D37: =#REF! -> #REF! | E37: 21210742
B38: Campaigns-Others
C39: =SUM(C35:C38) -> 41381396 | D39: =SUM(D35:D38) -> #REF! | E39: =SUM(E35:E38) -> 31685424
B41: (vi) Other Expenses
B43: Water Tax | C43: 15852 | D43: =#REF! -> #REF! | E43: 45299
B44: Asset Written Off | C44: -500000 | D44: =#REF! -> #REF! | E44: -113280
B45: Professional charges | C45: 254958 | D45: =#REF! -> #REF! | E45: 230424
B46: Diesel Charges | C46: 300094 | D46: =#REF! -> #REF! | E46: 398595
B47: Interest on TDS payment | D47: 513
B48: Interest on GST payment
B49: Interest on EPF payment | D49: 182
B50: Donation | D50: =#REF! -> #REF! | E50: 50000
B51: Lease Brokerage | D51: =#REF! -> #REF! | E51: 80000
C52: =SUM(C43:C51) -> 70904 | D52: =SUM(D43:D51) -> #REF! | E52: =SUM(E43:E48) -> 561038

Sheet Groupings BS
B3: Notes forming part of Financial Statements as on March 31, 2025
C4: For the year ended 31.03.2025 | D4: For the year ended 31.03.2024 | E4: For the year ended 31.03.2023
B6: (i) Accounts payable
B7: Referral Bonus payable | C7: 33500 | D7: =#REF! -> #REF! | E7: 65000
B8: Incentive Payable | C8: 726307 | D8: =#REF! -> #REF! | E8: 257821
B9: Government charges payable | D9: 0 | E9: 0
C10: =SUM(C7:C9) -> 759807 | D10: =SUM(D7:D9) -> #REF! | E10: =SUM(E7:E9) -> 322821
B12: (ii) Input GST
B13: Input CGST | C13: 50935.6 | D13: =#REF! -> #REF! | E13: 38490.38
B14: Input SGST | C14: 50935.6 | D14: =#REF! -> #REF! | E14: 38490.38 | F14: 9750857 | G14: =+D14-F14 -> #REF!
B15: Input IGST | C15: 80.71 | D15: =#REF! -> #REF! | E15: 14607.76 | G15: 26330
C16: =SUM(C13:C15) -> 101951.91 | D16: =SUM(D13:D15) -> #REF! | E16: =SUM(E13:E15) -> 91588.52 | G16: =+G14-G15 -> #REF!
B29: (i) Trade payable
B30: Aachi Masala Foods Pvt.Ltd.
B31: ACR INFOSYSTEMS
B32: Akshaya Security Services
B33: Airtel
B34: Bharani Kumar
B35: DeepQuanty Artificial Intelligence Labs Pvt Ltd
B36: DIGITAL CREST
B37: DQAI Telesales Pvt Ltd
B38: Facebook India Online services Pvt.Ltd.
B39: Freedom solution
B40: GALAXY POWER SOLUTION
... B64: Vodafone Idea Limited
E65: =SUM(E30:E64) -> 0

Sheet Deferred Tax
B2: Computation of Deffered Tax
B3: Particulars | C3: Amount
B4: WDV as per IT act | C4: 4229857 | J4: 5363721
B5: WDV as per Books of Accounts | C5: ='10'!L43 -> 4478032.3 | J5: ='Financial Statements'!E35 -> 5439341.5
B6: Difference | C6: =C5-C4 -> 248175.35 | E6: Deferred tax exp | G6: =C11 -> -10930.32 | H6: (P&L item) | J6: =J5-J4 -> 75620.518
B7: Tax @22% | C7: =+C6*25% -> 62043.837 | F7: to def liab | H7: =G6 -> -10930.32 | J7: =J6*0.25*1.04 -> 19661.335
B8: Cess @4% | C8: =+C7*4% -> 2481.7535
B9: Closing Deferred Tax Liability (DTL) | C9: =+C7+C8 -> 64525.59
B10: Opening Balance | C10: 75455.91
B11: Current year DTL | C11: =+C9-C10 -> -10930.32

Sheet Current Tax
A4: PBT | C4: ='Financial Statements'!E97 -> 16156488
A6: Add:
A7: Provision | B7: ='Financial Statements'!E93 -> 0
A8: Gratuity | B8: ='3-15'!E69 -> 1469911
A9: Leave Encashment | B9: ='3-15'!E70-'3-15'!F70 -> 2920931
A10: Depreciation | B10: ='Financial Statements'!E86 -> 2045608.1 | C10: =SUM(B7:B10) -> 6436450.1
A12: Less:
A13: Provision reversal | B13: 0
A14: Depreciation | B14: 1868302 | C14: =SUM(B13:B14) -> 1868302
C16: =C4+C10-C14 -> 20724637
A18: Tax @ 22% | C18: =C16*0.22 -> 4559420
A19: Surcharge @ 10% | C19: =C18*0.1 -> 455942
A20: Cess @ 4% | C20: =SUM(C18:C19)*0.04 -> 200614.48
C22: =SUM(C18:C21) -> 5215976.5
C24: =ROUNDDOWN(C22,-5) -> 5200000
A26: TDS 92k disallowance not considered

Sheet Depreciation 2025
A2: Particulars | B2: Date of Purchase | C2: Useful Life | D2: Purchase amount | E2: Salvage Value | F2: Net amount | G2: Amt to be depreciated every year | J2: No of days used | K2: Depreciable Amount | M2: Dep as per client workings
A3: Computer Software | B3: 44280 | C3: 6 | D3: 50000 | E3: =+D3*5% -> 2500 | F3: =+D3-E3 -> 47500 | G3: =+F3/C3 -> 7916.6667 | H3: 45382 | I3: 45017 | J3: =H3-I3 -> 365 | K3: =+G3*J3/365 -> 7916.6667 | M3: 7917 | N3: 0
A4: Computer
A5: - | B5: 43747 | C5: 3 | D5: 6355.94 | E5: =+D5*5% -> 317.797 | F5: =+D5-E5 -> 6038.143 | G5: =+F5/C5 -> 2012.7143 | J5: =H5-I5 -> 0 | K5: =+G5*J5/365 -> 0
B6: 43778 | C6: 3 | D6: 2542.37 | E6: =+D6*5% -> 127.1185 | F6: =+D6-E6 -> 2415.2515 | G6: =+F6/C6 -> 805.08383 | K6: =+G6*J6/365 -> 0
B7: 43785 | C7: 3 | D7: 92000 | E7: =+D7*5% -> 4600 | F7: =+D7-E7 -> 87400 | G7: =+F7/C7 -> 29133.333 | K7: =+G7*J7/365 -> 0
B8: 43832 | C8: 3 | D8: 31271.18 | E8: =+D8*5% -> 1563.559 | F8: =+D8-E8 -> 29707.621 | G8: =+F8/C8 -> 9902.5403 | K8: =+G8*J8/365 -> 0
B9: 43837 | C9: 3 | D9: 11610.17 | E9: =+D9*5% -> 580.5085 | F9: =+D9-E9 -> 11029.662 | G9: =+F9/C9 -> 3676.5538 | K9: =+G9*J9/365 -> 0
B10: 43894 | C10: 3 | D10: 84000 | E10: =+D10*5% -> 4200 | F10: =+D10-E10 -> 79800 | G10: =+F10/C10 -> 26600 | K10: =+G10*J10/365 -> 0
B11: 43906 | C11: 3 | D11: 42200 | E11: =+D11*5% -> 2110 | F11: =+D11-E11 -> 40090 | G11: =+F11/C11 -> 13363.333 | K11: =+G11*J11/365 -> 0
B12: 01.01.2021 | C12: 3 | D12: =369857.48-98102 -> 271755.48 | E12: =+D12*5% -> 13587.774 | F12: =+D12-E12 -> 258167.71 | G12: =+F12/C12 -> 86055.902 | H12: 45292 | I12: 45017 | K12: =+G12*J12/365 -> 0
B13: 44675 | C13: 3 | D13: 96000 | E13: =D13*5% -> 4800 | F13: =D13-E13 -> 91200 | G13: =F13/C13 -> 30400 | H13: 45747 | I13: 45383 | J13: =H13-I13+1 -> 365 | K13: =+G13*J13/365 -> 30400 | M13: 30400 | N13: =K13-M13 -> 0
B14: 44755 | C14: 3 | D14: 62000 | E14: =D14*5% -> 3100 | F14: =D14-E14 -> 58900 | G14: =F14/C14 -> 19633.333 | H14: 45747 | I14: 45383 | J14: =H14-I14+1 -> 365 | K14: =+G14*J14/365 -> 19633.333 | M14: 19633.333 | N14: =K14-M14 -> 0
B15: 44757 | C15: 3 | D15: 80000 | E15: =D15*5% -> 4000 | F15: =D15-E15 -> 76000 | G15: =F15/C15 -> 25333.333 | H15: 45747 | I15: 45383 | J15: =H15-I15+1 -> 365 | K15: =+G15*J15/365 -> 25333.333 | M15: 25333.333 | N15: =K15-M15 -> 0
B16: 44855 | C16: 3 | D16: 160000 | E16: =D16*5% -> 8000 | F16: =D16-E16 -> 152000 | G16: =F16/C16 -> 50666.667 | H16: 45747 | I16: 45383 | J16: =H16-I16+1 -> 365 | K16: =+G16*J16/365 -> 50666.667 | M16: 50666.667 | N16: =K16-M16 -> 0
B17: 44872 | C17: 3 | D17: 186000 | E17: =D17*5% -> 9300 | F17: =D17-E17 -> 176700 | G17: =F17/C17 -> 58900 | H17: 45747 | I17: 45383 | J17: =H17-I17+1 -> 365 | K17: =+G17*J17/365 -> 58900 | M17: 58900 | N17: =K17-M17 -> 0
B18: 44890 | C18: 3 | D18: 65932.04 | E18: =D18*5% -> 3296.602 | F18: =D18-E18 -> 62635.438 | G18: =F18/C18 -> 20878.479 | H18: 45747 | I18: 45383 | J18: =H18-I18+1 -> 365 | K18: =+G18*J18/365 -> 20878.479 | M18: 20878.467 | N18: =K18-M18 -> 0.012666667
B19: 44575 | C19: 3 | D19: 200000 | E19: =D19*5% -> 10000 | F19: =D19-E19 -> 190000 | G19: =F19/C19 -> 63333.333 | H19: 45747 | I19: 45383 | J19: =H19-I19+1 -> 365 | K19: =+G19*J19/365 -> 63333.333 | M19: 63333.333 | N19: =K19-M19 -> 0
B20: 44985 | C20: 3 | D20: 37287.28 | E20: =D20*5% -> 1864.364 | F20: =D20-E20 -> 35422.916 | G20: =F20/C20 -> 11807.639 | H20: 45747 | I20: 45383 | J20: =H20-I20+1 -> 365 | K20: =+G20*J20/365 -> 11807.639 | M20: 11807.639 | N20: =K20-M20 -> 0
B21: 45008 | C21: 3 | D21: 169491.44 | E21: =D21*5% -> 8474.572 | F21: =D21-E21 -> 161016.87 | G21: =F21/C21 -> 53672.289 | H21: 45747 | I21: 45383 | J21: =H21-I21+1 -> 365 | K21: =+G21*J21/365 -> 53672.289 | M21: 53672.289 | N21: =K21-M21 -> 0
B22: 45009 | C22: 3 | D22: 16000 | E22: =D22*5% -> 800 | F22: =D22-E22 -> 15200 | G22: =F22/C22 -> 5066.6667 | H22: 45747 | I22: 45383 | J22: =H22-I22+1 -> 365 | K22: =+G22*J22/365 -> 5066.6667 | M22: 5066.6667 | N22: =K22-M22 -> 0
B23: 45068 | C23: 3 | D23: 46323.58 | E23: =D23*5% -> 2316.179 | F23: =D23-E23 -> 44007.401 | G23: =F23/C23 -> 14669.134 | H23: 45747 | I23: 45383 | J23: =H23-I23+1 -> 365 | K23: =+G23*J23/365 -> 14669.134 | M23: 14669.134 | N23: =K23-M23 -> 0
B24: 45068 | C24: 3 | D24: 43806.81 | E24: =D24*5% -> 2190.3405 | F24: =D24-E24 -> 41616.469 | G24: =F24/C24 -> 13872.156 | H24: 45747 | I24: 45383 | J24: =H24-I24+1 -> 365 | K24: =+G24*J24/365 -> 13872.156 | M24: 13872.156 | N24: =K24-M24 -> 0
... B52: 45711 | C52: 3 | D52: 81000 | E52: =D52*5% -> 4050 | F52: =D52-E52 -> 76950 | G52: =F52/C52 -> 25650 | H52: 45747 | I52: 45711 | J52: =H52-I52+1 -> 37 | K52: =+G52*J52/365 -> 2600.137 | M52: 2600.137 | N52: =K52-M52 -> 0
D53: =SUM(D5:D52) -> 4563131.5 | G53: =SUM(G5:G52) -> 1444991.6 | K53: =SUM(K5:K52) -> 978490.32 | M53: =SUM(M5:M52) -> 978490.3 | N53: =SUM(N5:N52) -> 0.012666667
A55: Furniture
B56: 43811 | C56: 10 | D56: 11957.62 | E56: =+D56*5% -> 597.881 | F56: =+D56-E56 -> 11359.739 | G56: =+F56/C56 -> 1135.9739 | H56: 45747 | I56: 45383 | J56: =H56-I56+1 -> 365 | K56: =+G56*J56/365 -> 1135.9739 | M56: 1135.9739 | N56: =K56-M56 -> 0
B57: 44211 | C57: 10 | D57: 8000 | E57: =+D57*5% -> 400 | F57: =+D57-E57 -> 7600 | G57: =+F57/C57 -> 760 | H57: 45747 | I57: 45383 | J57: =H57-I57+1 -> 365 | K57: =+G57*J57/365 -> 760 | M57: 760 | N57: =K57-M57 -> 0
B58: 44562 | C58: 10 | D58: 184674.77 | E58: 9233.7385 | F58: 175441.03 | G58: =+F58/C58 -> 17544.103 | H58: 45747 | I58: 45383 | J58: =H58-I58+1 -> 365 | K58: =+G58*J58/365 -> 17544.103 | M58: 17544 | N58: =K58-M58 -> 0.10315
B59: 44855 | C59: 10 | D59: 61250 | E59: =D59*5% -> 3062.5 | F59: =D59-E59 -> 58187.5 | G59: =+F59/C59 -> 5818.75 | H59: 45747 | I59: 45383 | J59: =H59-I59+1 -> 365 | K59: =+G59*J59/365 -> 5818.75 | M59: 5818.75 | N59: =K59-M59 -> 0
B60: 44859 | C60: 10 | D60: 61250 | E60: =D60*5% -> 3062.5 | F60: =D60-E60 -> 58187.5 | G60: =+F60/C60 -> 5818.75 | H60: 45747 | I60: 45383 | J60: =H60-I60+1 -> 365 | K60: =+G60*J60/365 -> 5818.75 | M60: 5818.75 | N60: =K60-M60 -> 0
B61: 44882 | C61: 10 | D61: 63590 | E61: =D61*5% -> 3179.5 | F61: =D61-E61 -> 60410.5 | G61: =+F61/C61 -> 6041.05 | H61: 45747 | I61: 45383 | J61: =H61-I61+1 -> 365 | K61: =+G61*J61/365 -> 6041.05 | M61: 6041.05 | N61: =K61-M61 -> 0
B62: 44894 | C62: 10 | D62: 73500 | E62: =D62*5% -> 3675 | F62: =D62-E62 -> 69825 | G62: =+F62/C62 -> 6982.5 | H62: 45747 | I62: 45383 | J62: =H62-I62+1 -> 365 | K62: =+G62*J62/365 -> 6982.5 | M62: 6982.5 | N62: =K62-M62 -> 0
B63: 44894 | C63: 10 | D63: 12250 | E63: =D63*5% -> 612.5 | F63: =D63-E63 -> 11637.5 | G63: =+F63/C63 -> 1163.75 | H63: 45747 | I63: 45383 | J63: =H63-I63+1 -> 365 | K63: =+G63*J63/365 -> 1163.75 | M63: 1163.75 | N63: =K63-M63 -> 0
B64: 44917 | C64: 10 | D64: 19600 | E64: =D64*5% -> 980 | F64: =D64-E64 -> 18620 | G64: =+F64/C64 -> 1862 | H64: 45747 | I64: 45383 | J64: =H64-I64+1 -> 365 | K64: =+G64*J64/365 -> 1862 | M64: 1862 | N64: =K64-M64 -> 0
B65: 44923 | C65: 10 | D65: 8177.98 | E65: =D65*5% -> 408.899 | F65: =D65-E65 -> 7769.081 | G65: =+F65/C65 -> 776.9081 | H65: 45747 | I65: 45383 | J65: =H65-I65+1 -> 365 | K65: =+G65*J65/365 -> 776.9081 | M65: 776.9081 | N65: =K65-M65 -> 0
B66: 44932 | C66: 10 | D66: 25780.46 | E66: =D66*5% -> 1289.023 | F66: =D66-E66 -> 24491.437 | G66: =+F66/C66 -> 2449.1437 | H66: 45747 | I66: 45383 | J66: =H66-I66+1 -> 365 | K66: =+G66*J66/365 -> 2449.1437 | M66: 2449.1437 | N66: =K66-M66 -> 0
B67: 44957 | C67: 10 | D67: 7033.9 | E67: =D67*5% -> 351.695 | F67: =D67-E67 -> 6682.205 | G67: =+F67/C67 -> 668.2205 | H67: 45747 | I67: 45383 | J67: =H67-I67+1 -> 365 | K67: =+G67*J67/365 -> 668.2205 | M67: 668.2205 | N67: =K67-M67 -> 0
B68: 44960 | C68: 10 | D68: 22050 | E68: =D68*5% -> 1102.5 | F68: =D68-E68 -> 20947.5 | G68: =+F68/C68 -> 2094.75 | H68: 45747 | I68: 45383 | J68: =H68-I68+1 -> 365 | K68: =+G68*J68/365 -> 2094.75 | M68: 2094.75 | N68: =K68-M68 -> 0
B69: 44996 | C69: 10 | D69: 14000 | E69: =D69*5% -> 700 | F69: =D69-E69 -> 13300 | G69: =+F69/C69 -> 1330 | H69: 45747 | I69: 45383 | J69: =H69-I69+1 -> 365 | K69: =+G69*J69/365 -> 1330 | M69: 1330 | N69: =K69-M69 -> 0
B70: 45006 | C70: 10 | D70: 8600 | E70: =D70*5% -> 430 | F70: =D70-E70 -> 8170 | G70: =+F70/C70 -> 817 | H70: 45747 | I70: 45383 | J70: =H70-I70+1 -> 365 | K70: =+G70*J70/365 -> 817 | M70: 817 | N70: =K70-M70 -> 0
... B92: 45700 | C92: 10 | D92: 2499.15 | E92: =D92*5% -> 124.9575 | F92: =D92-E92 -> 2374.1925 | G92: =+F92/C92 -> 237.41925 | H92: 45747 | I92: 45700 | J92: =H92-I92+1 -> 48 | K92: =+G92*J92/365 -> 31.222258 | M92: 31.222258 | N92: =K92-M92 -> 0
D94: =SUM(D56:D92) -> 2624969.7 | G94: =SUM(G56:G92) -> 249372.12 | K94: =SUM(K56:K92) -> 241727.06 | M94: =SUM(M56:M92) -> 365358.02 | N94: =K94-M94 -> -123630.96
A95: Office Equipment
B96: 44770 | C96: 5 | D96: 16000 | E96: =D96*5% -> 800 | F96: =D96-E96 -> 15200 | G96: =F96/C96 -> 3040 | H96: 45747 | I96: 45383 | J96: =H96-I96+1 -> 365 | K96: =+G96*J96/365 -> 3040 | M96: 3040 | N96: =K96-M96 -> 0
A100: Telephone | B100: 43810 | C100: 5 | D100: 3110.16 | E100: =+D100*5% -> 155.508 | F100: =+D100-E100 -> 2954.652 | G100: =+F100/5 -> 590.9304 | H100: 45637 | I100: 45383 | J100: =H100-I100+1 -> 255 | K100: =+G100*J100/365 -> 412.84179 | M100: 412.84179 | N100: =K100-M100 -> 0
A102: Printer | B102: 25.07.2021 | C102: 5 | D102: 21610.17 | E102: =+D102*5% -> 1080.5085 | F102: =+D102-E102 -> 20529.661 | G102: =+F102/5 -> 4105.9323 | H102: 45747 | I102: 45383 | J102: =H102-I102+1 -> 365 | K102: =+G102*J102/365 -> 4105.9323 | M102: 4105.9323 | N102: =K102-M102 -> 0
B103: 45250 | C103: 5 | D103: 20762 | E103: =+D103*5% -> 1038.1 | F103: =+D103-E103 -> 19723.9 | G103: =+F103/5 -> 3944.78 | H103: 45747 | I103: 45383 | J103: =H103-I103+1 -> 365 | K103: =+G103*J103/365 -> 3944.78 | M103: 3944.7553 | N103: =K103-M103 -> 0.0247
B104: 45702 | C104: 5 | D104: 20202.54 | E104: =+D104*5% -> 1010.127 | F104: =+D104-E104 -> 19192.413 | G104: =+F104/5 -> 3838.4826 | H104: 45747 | I104: 45702 | J104: =H104-I104+1 -> 46 | K104: =+G104*J104/365 -> 483.75397 | M104: 118.3094 | N104: =K104-M104 -> 365.44458
D105: =SUM(D102:D104) -> 62574.71 | G105: =SUM(G102:G104) -> 11889.195 | H105: =SUM(H102:H104) -> 137241 | I105: =SUM(I102:I104) -> 136468 | J105: =SUM(J102:J104) -> 776 | K105: =SUM(K102:K104) -> 8534.4663 | M105: =SUM(M102:M104) -> 8168.997 | N105: =K105-M105 -> 365.46928
A106: Total
D107: =+D100+D94+D53+D96+D105+D3 -> 7319786.1 | E107: =SUM(E3:E104) -> 365989.3 | F107: =SUM(F3:F104) -> 6953796.7 | J107: TOTAL | K107: =+K100+K94+K53+K3+K96+K105 -> 1240121.4 | M107: =+M100+M94+M53+M3+M96+M105 -> 1363387.2 | N107: =+N100+N94+N53+N3+N96+N105 -> -123265.48
