Workbook
Name Deno: 'Master data'!$B$2

Sheet Master data
A2: Lakhs | B2: =+SUMIF(A4:A10,A2,B4:B10) -> 100000 | C2: =+Deno -> 100000
A4: Millions | B4: 1000000
A5: Lakhs | B5: 100000
A6: Ten Thousands | B6: 10000
A7: Thousands | B7: 1000
A8: Hundreds | B8: 100
A9: Tens | B9: 10
A10: Ones | B10: 1

Sheet Sheet1
A2: As per RBI Prevailing Rates
A3: Date | B3: Currency | C3: Rate/ INR
A4: 45747 | B4: USD | C4: 85.424
A5: 45747 | B5: EUR | C5: 92.415
A6: 45747 | B6: GBP | C6: 110.53

Sheet Audit entry
B2: Audit Entry for FY 2024-25 | E2: =+D3-E3 -> -1.94
D3: =+SUM(D5:D1048576) -> 29995065 | E3: =+SUM(E5:E1048576) -> 29995067
B4: SI no | C4: Particulars | D4: Debit | E4: Credit | F4: Remarks | M4: Check
H5: Assest break ups | M5: Income Tax payable | N5: ='Statement of Income'!E44 -> 654762.49 | O5: =E149 -> 654762.49 | P5: =N5-O5 -> 1.4202669e-08
B6: 1 | C6: INSURANCE. | D6: 122066.25 | F6: Given | H6: 44109 | I6: NETWORK CHSING PURCHSED FOR MAA NEW OFFICE | J6: 2928 | M6: TDS Receivables | N6: ='Statement of Income'!E47 -> 3660953 | O6: ='TB 24-25'!I61 -> 3255908.4 | P6: =N6-O6 -> 405044.67
C7: To PREPAID INSURANCES | E7: =+D6 -> 122066.25 | F7: Given | H7: 44119 | I7: AC INSTALATION CHARGES | J7: 1500
C8: (Prepaid of FY 23-24 Transferred to Exp)
H9: 44119 | I9: PLUG - INR 60 1/2" NUTS - INR 150 ANGLR FLANZ - INR 90 | J9: 400
B10: 2 | C10: PREPAID INSURANCES | D10: =392364.68/12*4 -> 130788.23 | F10: Given | H10: 44119 | I10: NETWORKING ACCESSORIES | J10: 1684
C11: To INSURANCE. | E11: =+D10 -> 130788.23 | F11: Given | H11: 44141 | J11: 2142
C12: (Prepaid of FY 24-25 Transferred to Exp) | H12: 44989 | I12: Stablizer FOR AC | J12: 1550
B14: 3 | C14: AUDIT FEES PAYABLE | D14: 225000 | F14: Given | H14: 44013 | J14: 638.98
C15: To Accurals | E15: =+D14 -> 225000 | F15: Given | H15: 44032 | J15: 4287.05
C16: (Transfer entry - reversal of audit fee payable for the Previous FY & GST audit fee payable for the FY 2022-23) | H16: 44119 | I16: STABLIZER | J16: 1100
H17: 44124 | I17: Stabiliser | J17: 2400
B18: 4 | C18: STATUTORY EXPENSES | D18: 10000 | F18: Given | H18: 44965 | I18: AIRTEL DONGLE | J18: 2200
C19: ACCRUALS | E19: 10000 | F19: Given | H19: 44983 | I19: Window Curtain | J19: 2500
C20: (IT filing transferred) | H20: 44162 | J20: 960
B22: 5 | C22: ACCRUALS | D22: 1315 | F22: Given
C23: INTEREST ON DEPOSIT | E23: =+D22 -> 1315 | F23: Given
C24: Interest trf entry)
B26: 6 | C26: Stat Audit | D26: 125000 | F26: Given
C27: Tax audit | D27: 100000 | F27: Given
C28: AUDIT FEES PAYABLE | E28: =SUM(D26:D27) -> 225000 | F28: Given
C29: (FY 24-25 audit fee)
B31: 7 | C31: Profit and loss ac | D31: =-'Deffered Tax'!H23 -> 0.37521685 | F31: Given
C32: Deffered Tax | E32: =+D31 -> 0.37521685 | F32: Given
B34: 8 | C34: LOCAL CREDITORS - FREIGHT FORWARDING | D34: 12250 | F34: Given
C35: REPAIRS & MAINTENANCE FOR COMPUTERS HARDWARE | E35: =+D34 -> 12250 | F35: Given
B37: 9 | C37: INTERNET | D37: 8846.46 | F37: Given
C38: LOCAL CREDITORS - FREIGHT FORWARDING | E38: =+D37 -> 8846.46 | F38: Given
B40: 10 | C40: BLUE DART | D40: 177 | F40: Given
C41: I2 IMPEX | D41: 298.62
C42: STAR HEALTH AND ALLIED INSURANCE COMPANY LIMITED | D42: 38558.96
C43: THE PROFESSIONAL COURIERS CHENNAI LLP | D43: 197.97
C44: UNIQUE PEST MANAGEMENT | D44: 1000
C45: BABU RAO | D45: 2144
C46: BANGALORE ELECTRICITY (BESCOM) | D46: 2022.48
C47: GURUASHISH LOGISTICS PVT LTD | D47: 885
C48: MOKSHITA TRANSPORT | D48: 3120
C49: SOLAI TRANS CARRIER | D49: 500
C50: THE HONGKONG AND SHANGHAI BANKING CORPORATION LTD | D50: 275
C51: YEHWEH SECURED FUMIGATION SERVICES | D51: 870
C52: ZENCO LOGISTICS | D52: 3540
C53: ROYAL SUNDARAM GENERAL INSURANCE CO. LIMITED | D53: . | E53: 667
C54: YES BANK | E54: 16203.19
C55: To Write BacK | E55: =SUM(D40:D52)-SUM(E53:E54) -> 36718.84
C56: (Creditors write back refer Trade payable ageing)
B58: 11 | C58: Wirte off | D58: =SUM(E70:E83)-D69 -> 3084106 | F58: Given
C59: Rounding off | E59: =+SUM(E64:E68)-SUM(D60:D63) -> 0.97
C60: BUNDY INDIA LIMITED | D60: 0.3
C61: HEADWIN EXIM PRIVATE LIMITED | D61: 0.25
C62: KERRY INGREDIENTS INDIA PVT LTD | D62: 0.45
C63: SIGNODE INDIA LIMITED | D63: 0.04
C64: SASTRA UNIVERSITY | E64: 0.36
C65: WINVERTEX EXIM PRIVATE LIMITED | E65: 0.48
C66: MARUVUR ARASI LOGISTICS PRIVATE LIMITED | E66: 0.08
C67: MA APPARELS | E67: 0.93
C68: KVSS PROJECTS | E68: 0.16
C69: GOPATHI SHIPPING SERVICES | D69: 11000
C70: DAISY ENTERPRISES | E70: 801725.59
C71: THRIVENI EARTHMOVERS PVT LTD | E71: 33.72
C72: VASUDHA PHARMA CHEM LIMITED.. | E72: 12333.28
C73: ALAN LOGISTICS | E73: 59661.98
C74: ANNAI FREIGHT SYSTEM | E74: 812293.32
C75: BRAKES INDIA PRIVATE LIMITED | E75: 123161.32
C76: CRUSHER AND MINING EQUIPMENTS MANUFACTURER | E76: 4000.35
C77: JESSICA PICKLEZ PRIVATE LIMITED | E77: 419133.3
C78: M/S.SRI SAI IMPEX | E78: 55032
C79: PROPEL INDUSTRIES PVT LTD | E79: 902.04
C80: PRYM INDUSTRIES | E80: 102188.69
C81: VIZ TECHNOLOIES (P) LTD | E81: 96
... C83: MCLEAD ENTERPRISES | E83: 633694.3
C84: (bad debts transferred refer Trade receivable ageing )
B86: 12 | C86: INTER CONTINENTAL LOGISTICS LTD | D86: 13319.801
C87: QUALITY FREIGHT SERVICES LTD | D87: 4760.9967
C88: Foreign Exchange gain/loss | D88: =SUM(E89:E97)-SUM(D86:D87) -> 86921.929
C89: TAZMANIAN FREIGHT SYSTEMS INC | E89: 77551.82
C90: CARE FREIGHT LOGISTICS (PTY) LTD | E90: 19047.418
C91: CARGONIZER LOGISTICS INC | E91: 53.769351
C92: ZOVKO ENTERPRISES INC | E92: 199.75035
C93: SCT LOGISTICS JOINT STOCK COMPANY (OS90029) HO CHI MINH | E93: 393.17961
C94: ELTO FREIGHT | E94: 2470.8512
C95: GREAT LINK LOGISTICS CO LTD | E95: 18.1755
C96: FLY LOG | E96: 259.33678
C97: SKG THESSALONIKI CARGO MON IKE | E97: 5008.4266
C98: (Reversal of Restatement entry of FY 23-24 - Debtors)
B100: 13 | C100: INTER CONTINENTAL LOGISTICS LTD | D100: 65217.568
C101: DYJ LOGISTICS | D101: 7566.0877
C102: FOCUS GLOBAL LOGISTICS (HK) CORPORATION LIMITED | D102: 1043.338
C103: INFRANORDIC SHIPPING AND FORWARDING AB | D103: 85.5465
C104: TRANSCARGO WORLDWIDE (M) SDN BHD | D104: 782.10854
C105: VECTOR SPA | D105: 1365.6995
C106: GENEL TRANSPORT LTD. STI. | D106: 6152.533
C107: TAZMANIAN FREIGHT SYSTEMS INC | D107: 294.52592
C108: EXPO FREIGHT LIMITED.. | D108: 88.53115
C109: Foreign Exchange gain/loss | E109: =SUM(D100:D108)-SUM(E110:E119) -> 40722.077
C110: LIFT FREIGHT SERVICES B.V. | E110: 8936.1128
C111: ISCM CHINA CO LTD | E111: 328.7755
C112: QCS QUICK CARGO SERVICE GMBH | E112: 20458.067
...

Sheet TB 24-25
D1: =Deno -> 100000 | F1: =+F2-E2 -> -3.685464e-06 | H1: =+H2-G2 -> 408.63145 | J1: =+J2-I2 -> -408.63 | L1: =+L2-K2 -> 0.0014525056 | N1: =+N2-M2 -> -0.059999999 | P1: =(O2-P2)*Deno -> 0.05854763 | V1: -99152768
E2: =SUBTOTAL(9,E6:E342) -> 3279.2606 | F2: =SUBTOTAL(9,F6:F342) -> 3279.2606 | G2: =SUBTOTAL(9,G6:G342) -> 1.6962661e+08 | H2: =SUBTOTAL(9,H6:H342) -> 1.6962702e+08 | I2: =SUBTOTAL(9,I6:I342) -> 3.2757994e+08 | J2: =SUBTOTAL(9,J6:J342) -> 3.2757953e+08 | K2: =SUBTOTAL(9,K6:K342) -> 4.6262336e+08 | L2: =SUBTOTAL(9,L6:L342) -> 4.6262336e+08 | ... P2: =SUBTOTAL(9,P6:P342) -> 4665.1232 | R2: =+E2-F2 -> 3.685464e-06 | S2: 1930545.7 | T2: =+R2-S2 -> -1930545.7 | V2: 1.0118639e+08 | W2: =+SUM(V1:V2) -> 2033619.2
E3: Closing Balance after AR | G3: Opening Balance | I3: During the Year Transaction | K3: Closing Balance | M3: Audit entries | O3: Closing Balance after AR
D4: Particulars | E4: FY 23-24 | G4: FY 24-25 | I4: FY 24-25 | K4: FY 24-25 | M4: FY 24-25 | O4: FY 24-25
E5: Debit | F5: Credit | G5: Debit | H5: Credit | I5: Debit | J5: Credit | K5: Debit | L5: Credit | M5: Debit | N5: Credit | O5: Debit | P5: Credit | Q5: Sumif | R5: Note no | S5: CY Grouping | T5: Sub sch Ref
A6: ASSETS
B7: FIXED ASSETS
C8: FIXED ASSETS AT COST
D9: COMPUTER | E9: =139899.35933321/(Deno) -> 1.3989936 | F9: =0/(Deno) -> 0 | G9: 139899.36 | H9: 0 | I9: 32966.11 | J9: 0 | K9: =+IF((G9+I9-H9-J9>0),G9+I9-H9-J9,0) -> 172865.47 | L9: =+IF((H9+J9-G9-I9)>0,H9+J9-G9-I9,0) -> 0 | O9: =+IF((K9+M9-L9-N9>0),K9+M9-L9-N9,0)/Deno -> 1.7286547 | P9: =+IF((L9+N9-K9-M9)>0,L9+N9-K9-M9,0)/Deno -> 0 | R9: 8 | S9: Fixed Assets
D10: OFFICE EQUIPMENTS | E10: =517825.649127016/(Deno) -> 5.1782565 | F10: =0/(Deno) -> 0 | G10: 517825.65 | H10: 0 | I10: 0 | J10: 0 | K10: =+IF((G10+I10-H10-J10>0),G10+I10-H10-J10,0) -> 517825.65 | L10: =+IF((H10+J10-G10-I10)>0,H10+J10-G10-I10,0) -> 0 | O10: =+IF((K10+M10-L10-N10>0),K10+M10-L10-N10,0)/Deno -> 5.1782565 | P10: =+IF((L10+N10-K10-M10)>0,L10+N10-K10-M10,0)/Deno -> 0 | R10: 8 | S10: Fixed Assets
D11: FURNITURE & FIXTURES | E11: =125082.421142074/(Deno) -> 1.2508242 | F11: =0/(Deno) -> 0 | G11: 125082.42 | H11: 0 | I11: 0 | J11: 0 | K11: =+IF((G11+I11-H11-J11>0),G11+I11-H11-J11,0) -> 125082.42 | L11: =+IF((H11+J11-G11-I11)>0,H11+J11-G11-I11,0) -> 0 | O11: =+IF((K11+M11-L11-N11>0),K11+M11-L11-N11,0)/Deno -> 1.2508242 | P11: =+IF((L11+N11-K11-M11)>0,L11+N11-K11-M11,0)/Deno -> 0 | R11: 8 | S11: Fixed Assets
D12: MOTOR VEHICLES - CAR | E12: =0.00022921827621758/(Deno) -> 2.2921828e-09 | F12: =0/(Deno) -> 0 | G12: 0.00022921828 | H12: 0 | I12: 0 | J12: 0 | K12: =+IF((G12+I12-H12-J12>0),G12+I12-H12-J12,0) -> 0.00022921828 | L12: =+IF((H12+J12-G12-I12)>0,H12+J12-G12-I12,0) -> 0 | O12: =+IF((K12+M12-L12-N12>0),K12+M12-L12-N12,0)/Deno -> 2.2921828e-09 | P12: =+IF((L12+N12-K12-M12)>0,L12+N12-K12-M12,0)/Deno -> 0 | R12: 8 | S12: Fixed Assets
D13: ELECTRICAL INSTALLATIONS | E13: =37190.2148490844/(Deno) -> 0.37190215 | F13: =0/(Deno) -> 0 | G13: 37190.215 | H13: 0 | I13: 56000 | J13: 0 | K13: =+IF((G13+I13-H13-J13>0),G13+I13-H13-J13,0) -> 93190.215 | L13: =+IF((H13+J13-G13-I13)>0,H13+J13-G13-I13,0) -> 0 | O13: =+IF((K13+M13-L13-N13>0),K13+M13-L13-N13,0)/Deno -> 0.93190215 | P13: =+IF((L13+N13-K13-M13)>0,L13+N13-K13-M13,0)/Deno -> 0 | R13: 8 | S13: Fixed Assets
D14: MOBILE PURCHASE | E14: =19061/(Deno) -> 0.19061 | F14: =0/(Deno) -> 0 | G14: 19061 | H14: 0 | I14: 0 | J14: 0 | K14: =+IF((G14+I14-H14-J14>0),G14+I14-H14-J14,0) -> 19061 | L14: =+IF((H14+J14-G14-I14)>0,H14+J14-G14-I14,0) -> 0 | O14: =+IF((K14+M14-L14-N14>0),K14+M14-L14-N14,0)/Deno -> 0.19061 | P14: =+IF((L14+N14-K14-M14)>0,L14+N14-K14-M14,0)/Deno -> 0 | R14: 8 | S14: Fixed Assets
D15: OFFICE EQUIPMENTS | E15: =39297.176257463/(Deno) -> 0.39297176 | F15: =0/(Deno) -> 0 | G15: 39297.176 | H15: 0 | I15: 0 | J15: 0 | K15: =+IF((G15+I15-H15-J15>0),G15+I15-H15-J15,0) -> 39297.176 | L15: =+IF((H15+J15-G15-I15)>0,H15+J15-G15-I15,0) -> 0 | O15: =+IF((K15+M15-L15-N15>0),K15+M15-L15-N15,0)/Deno -> 0.39297176 | P15: =+IF((L15+N15-K15-M15)>0,L15+N15-K15-M15,0)/Deno -> 0 | R15: 8 | S15: Fixed Assets
D16: OFFICE EQUIP | E16: =35787.5/(Deno) -> 0.357875 | F16: =0/(Deno) -> 0 | G16: 35787.5 | H16: 0 | I16: 0 | J16: 0 | K16: =+IF((G16+I16-H16-J16>0),G16+I16-H16-J16,0) -> 35787.5 | L16: =+IF((H16+J16-G16-I16)>0,H16+J16-G16-I16,0) -> 0 | O16: =+IF((K16+M16-L16-N16>0),K16+M16-L16-N16,0)/Deno -> 0.357875 | P16: =+IF((L16+N16-K16-M16)>0,L16+N16-K16-M16,0)/Deno -> 0 | R16: 8 | S16: Fixed Assets
D17: MACHINERY & ELECTRICAL | E17: =0/(Deno) -> 0 | F17: =0.30000000000291/(Deno) -> 3e-06 | G17: 0 | H17: 0.3 | I17: 0 | J17: 0 | K17: =+IF((G17+I17-H17-J17>0),G17+I17-H17-J17,0) -> 0 | L17: =+IF((H17+J17-G17-I17)>0,H17+J17-G17-I17,0) -> 0.3 | O17: =+IF((K17+M17-L17-N17>0),K17+M17-L17-N17,0)/Deno -> 0 | P17: =+IF((L17+N17-K17-M17)>0,L17+N17-K17-M17,0)/Deno -> 3e-06 | R17: 8 | S17: Fixed Assets
B18: CURRENT ASSETS | E18: =0/(Deno) -> 0 | F18: =0/(Deno) -> 0 | K18: =+IF((G18+I18-H18-J18>0),G18+I18-H18-J18,0) -> 0 | L18: =+IF((H18+J18-G18-I18)>0,H18+J18-G18-I18,0) -> 0 | O18: =+IF((K18+M18-L18-N18>0),K18+M18-L18-N18,0)/Deno -> 0 | P18: =+IF((L18+N18-K18-M18)>0,L18+N18-K18-M18,0)/Deno -> 0
C19: SUNDRY DEBTORS | F19: =0/(Deno) -> 0 | K19: =+IF((G19+I19-H19-J19>0),G19+I19-H19-J19,0) -> 0 | L19: =+IF((H19+J19-G19-I19)>0,H19+J19-G19-I19,0) -> 0 | O19: =+IF((K19+M19-L19-N19>0),K19+M19-L19-N19,0)/Deno -> 0 | P19: =+IF((L19+N19-K19-M19)>0,L19+N19-K19-M19,0)/Deno -> 0
D20: OVERSEAS DEBTORS - FREIGHT FORWARDING | E20: =129065551.851325/(Deno) -> 1290.6555 | F20: =0/(Deno) -> 0 | G20: 1.2906555e+08 | H20: 0 | I20: 0 | J20: 855729.83 | K20: =+IF((G20+I20-H20-J20>0),G20+I20-H20-J20,0) -> 1.2820982e+08 | L20: =+IF((H20+J20-G20-I20)>0,H20+J20-G20-I20,0) -> 0 | M20: =+'Audit entry'!D122 -> 4081269.3 | O20: =+IF((K20+M20-L20-N20>0),K20+M20-L20-N20,0)/Deno -> 1322.9109 | P20: =+IF((L20+N20-K20-M20)>0,L20+N20-K20-M20,0)/Deno -> 0 | R20: 11 | S20: Trade Receivable
D21: LOCAL DEBTORS - FREIGHT FORWARDING | E21: =0/(Deno) -> 0 | F21: =65357815.8800001/(Deno) -> 653.57816 | G21: 0 | H21: 65357816 | I21: 36471481 | J21: 0 | K21: =+IF((G21+I21-H21-J21>0),G21+I21-H21-J21,0) -> 0 | L21: =+IF((H21+J21-G21-I21)>0,H21+J21-G21-I21,0) -> 28886335 | N21: =SUM('Audit entry'!E64:E83)-SUM('Audit entry'!D60:D83)+SUM('Audit entry'!E89:E97)-SUM('Audit entry'!D86:D87) -> 3171028.9 | O21: =+IF((K21+M21-L21-N21>0),K21+M21-L21-N21,0)/Deno -> 0 | P21: =+IF((L21+N21-K21-M21)>0,L21+N21-K21-M21,0)/Deno -> 320.57364 | R21: 11 | S21: Trade Receivable
C22: CASH AND BANK BALANCE | E22: =0/(Deno) -> 0 | F22: =0/(Deno) -> 0 | K22: =+IF((G22+I22-H22-J22>0),G22+I22-H22-J22,0) -> 0 | L22: =+IF((H22+J22-G22-I22)>0,H22+J22-G22-I22,0) -> 0 | O22: =+IF((K22+M22-L22-N22>0),K22+M22-L22-N22,0)/Deno -> 0 | P22: =+IF((L22+N22-K22-M22)>0,L22+N22-K22-M22,0)/Deno -> 0
D23: CASH IN HAND | E23: =371979.04/(Deno) -> 3.7197904 | F23: =0/(Deno) -> 0 | G23: 371979.04 | H23: 0 | I23: 0 | J23: 0 | K23: =+IF((G23+I23-H23-J23>0),G23+I23-H23-J23,0) -> 371979.04 | L23: =+IF((H23+J23-G23-I23)>0,H23+J23-G23-I23,0) -> 0 | N23: ='Audit entry'!E138+'Audit entry'!E142 -> 371979.04 | O23: =+IF((K23+M23-L23-N23>0),K23+M23-L23-N23,0)/Deno -> 0 | P23: =+IF((L23+N23-K23-M23)>0,L23+N23-K23-M23,0)/Deno -> 0 | Q23: Cash in hand | R23: 12 | S23: Cash and cash equivalents
D24: BANK BALANCE LOCAL CURRENCY | E24: =3691589.10000008/(Deno) -> 36.915891 | F24: =0/(Deno) -> 0 | G24: 3691589.1 | H24: 0 | I24: 17744544 | J24: 0 | K24: =+IF((G24+I24-H24-J24>0),G24+I24-H24-J24,0) -> 21436133 | L24: =+IF((H24+J24-G24-I24)>0,H24+J24-G24-I24,0) -> 0 | O24: =+IF((K24+M24-L24-N24>0),K24+M24-L24-N24,0)/Deno -> 214.36133 | P24: =+IF((L24+N24-K24-M24)>0,L24+N24-K24-M24,0)/Deno -> 0 | Q24: Cash at Bank - Local Currency | R24: 12 | S24: Cash and cash equivalents
D25: FIXED DEPOSIT IN BANK | E25: =500000/(Deno) -> 5 | F25: =0/(Deno) -> 0 | G25: 500000 | H25: 0 | I25: 0 | J25: 500000 | K25: =+IF((G25+I25-H25-J25>0),G25+I25-H25-J25,0) -> 0 | L25: =+IF((H25+J25-G25-I25)>0,H25+J25-G25-I25,0) -> 0 | O25: =+IF((K25+M25-L25-N25>0),K25+M25-L25-N25,0)/Deno -> 0 | P25: =+IF((L25+N25-K25-M25)>0,L25+N25-K25-M25,0)/Deno -> 0 | Q25: Cash at Bank - Local Currency | R25: 12 | S25: Cash and cash equivalents
D26: MAA PETTY CASH | E26: =7465/(Deno) -> 0.07465 | F26: =0/(Deno) -> 0 | G26: 7465 | H26: 0 | I26: 0 | J26: 7452 | K26: =+IF((G26+I26-H26-J26>0),G26+I26-H26-J26,0) -> 13 | L26: =+IF((H26+J26-G26-I26)>0,H26+J26-G26-I26,0) -> 0 | M26: ='Audit entry'!D137 -> 5148 | O26: =+IF((K26+M26-L26-N26>0),K26+M26-L26-N26,0)/Deno -> 0.05161 | P26: =+IF((L26+N26-K26-M26)>0,L26+N26-K26-M26,0)/Deno -> 0 | Q26: Petty Cash | R26: 12 | S26: Cash and cash equivalents
D27: AIRPORT PETTY CASH | E27: =0/(Deno) -> 0 | F27: =0/(Deno) -> 0 | G27: 0 | H27: 0 | I27: 0 | J27: 0 | K27: =+IF((G27+I27-H27-J27>0),G27+I27-H27-J27,0) -> 0 | L27: =+IF((H27+J27-G27-I27)>0,H27+J27-G27-I27,0) -> 0 | O27: =+IF((K27+M27-L27-N27>0),K27+M27-L27-N27,0)/Deno -> 0 | P27: =+IF((L27+N27-K27-M27)>0,L27+N27-K27-M27,0)/Deno -> 0 | Q27: Petty Cash | R27: 12 | S27: Cash and cash equivalents
D28: BANK BALANCE OVERSEAS CURRENCY | E28: =1494951.55499099/(Deno) -> 14.949516 | F28: =0/(Deno) -> 0 | G28: 1494951.6 | H28: 0 | I28: 0 | J28: 1253840.1 | K28: =+IF((G28+I28-H28-J28>0),G28+I28-H28-J28,0) -> 241111.49 | L28: =+IF((H28+J28-G28-I28)>0,H28+J28-G28-I28,0) -> 0 | O28: =+IF((K28+M28-L28-N28>0),K28+M28-L28-N28,0)/Deno -> 2.4111149 | P28: =+IF((L28+N28-K28-M28)>0,L28+N28-K28-M28,0)/Deno -> 0 | Q28: Cash at Bank - Foreign Currency | R28: 12 | S28: Cash and cash equivalents
D29: ATM CASH W/D | E29: =0/(Deno) -> 0 | F29: =0/(Deno) -> 0 | G29: 0 | H29: 0 | I29: 0 | J29: 0 | K29: =+IF((G29+I29-H29-J29>0),G29+I29-H29-J29,0) -> 0 | L29: =+IF((H29+J29-G29-I29)>0,H29+J29-G29-I29,0) -> 0 | O29: =+IF((K29+M29-L29-N29>0),K29+M29-L29-N29,0)/Deno -> 0 | P29: =+IF((L29+N29-K29-M29)>0,L29+N29-K29-M29,0)/Deno -> 0 | Q29: Cash in hand | R29: 12 | S29: Cash and cash equivalents
D30: INTER BANK ACCOUNT TRANSFER | E30: =0/(Deno) -> 0 | F30: =0/(Deno) -> 0 | G30: 0 | H30: 0 | I30: 0 | J30: 0 | K30: =+IF((G30+I30-H30-J30>0),G30+I30-H30-J30,0) -> 0 | L30: =+IF((H30+J30-G30-I30)>0,H30+J30-G30-I30,0) -> 0 | O30: =+IF((K30+M30-L30-N30>0),K30+M30-L30-N30,0)/Deno -> 0 | P30: =+IF((L30+N30-K30-M30)>0,L30+N30-K30-M30,0)/Deno -> 0 | Q30: Cash at Bank - Local Currency | R30: 12 | S30: Cash and cash equivalents
D31: SECURITY DEPOSIT | E31: =0/(Deno) -> 0 | F31: =0/(Deno) -> 0 | G31: 0 | H31: 0 | I31: 0 | J31: 0 | K31: =+IF((G31+I31-H31-J31>0),G31+I31-H31-J31,0) -> 0 | L31: =+IF((H31+J31-G31-I31)>0,H31+J31-G31-I31,0) -> 0 | O31: =+IF((K31+M31-L31-N31>0),K31+M31-L31-N31,0)/Deno -> 0 | P31: =+IF((L31+N31-K31-M31)>0,L31+N31-K31-M31,0)/Deno -> 0 | Q31: Security Deposit | R31: 12 | S31: Cash and cash equivalents
D32: TUT PETTY CASH | E32: =1988/(Deno) -> 0.01988 | F32: =0/(Deno) -> 0 | G32: 1988 | H32: 0 | I32: 0 | J32: 0 | K32: =+IF((G32+I32-H32-J32>0),G32+I32-H32-J32,0) -> 1988 | L32: =+IF((H32+J32-G32-I32)>0,H32+J32-G32-I32,0) -> 0 | O32: =+IF((K32+M32-L32-N32>0),K32+M32-L32-N32,0)/Deno -> 0.01988 | P32: =+IF((L32+N32-K32-M32)>0,L32+N32-K32-M32,0)/Deno -> 0 | Q32: Petty Cash | R32: 12 | S32: Cash and cash equivalents
D33: HYD PETTY CASH | E33: =0/(Deno) -> 0 | F33: =2993.62/(Deno) -> 0.0299362 | G33: 0 | H33: 2993.62 | I33: 11684.77 | J33: 0 | K33: =+IF((G33+I33-H33-J33>0),G33+I33-H33-J33,0) -> 8691.15 | L33: =+IF((H33+J33-G33-I33)>0,H33+J33-G33-I33,0) -> 0 | O33: =+IF((K33+M33-L33-N33>0),K33+M33-L33-N33,0)/Deno -> 0.0869115 | P33: =+IF((L33+N33-K33-M33)>0,L33+N33-K33-M33,0)/Deno -> 0 | Q33: Petty Cash | R33: 12 | S33: Cash and cash equivalents
D34: BLR PETTY CASH | E34: =0/(Deno) -> 0 | F34: =0/(Deno) -> 0 | G34: 0 | H34: 0 | I34: 0 | J34: 0 | K34: =+IF((G34+I34-H34-J34>0),G34+I34-H34-J34,0) -> 0 | L34: =+IF((H34+J34-G34-I34)>0,H34+J34-G34-I34,0) -> 0 | O34: =+IF((K34+M34-L34-N34>0),K34+M34-L34-N34,0)/Deno -> 0 | P34: =+IF((L34+N34-K34-M34)>0,L34+N34-K34-M34,0)/Deno -> 0 | Q34: Petty Cash | R34: 12 | S34: Cash and cash equivalents
D35: CBE PETTY CASH | E35: =2590.5/(Deno) -> 0.025905 | F35: =0/(Deno) -> 0 | G35: 2590.5 | H35: 0 | I35: 0 | J35: 2131 | K35: =+IF((G35+I35-H35-J35>0),G35+I35-H35-J35,0) -> 459.5 | L35: =+IF((H35+J35-G35-I35)>0,H35+J35-G35-I35,0) -> 0 | O35: =+IF((K35+M35-L35-N35>0),K35+M35-L35-N35,0)/Deno -> 0.004595 | P35: =+IF((L35+N35-K35-M35)>0,L35+N35-K35-M35,0)/Deno -> 0 | Q35: Petty Cash | R35: 12 | S35: Cash and cash equivalents
C36: WORK IN PROGRESS JOBS | E36: =0/(Deno) -> 0 | F36: =0/(Deno) -> 0 | K36: =+IF((G36+I36-H36-J36>0),G36+I36-H36-J36,0) -> 0 | L36: =+IF((H36+J36-G36-I36)>0,H36+J36-G36-I36,0) -> 0 | O36: =+IF((K36+M36-L36-N36>0),K36+M36-L36-N36,0)/Deno -> 0 | P36: =+IF((L36+N36-K36-M36)>0,L36+N36-K36-M36,0)/Deno -> 0
D37: WORK IN PROGRESS JOBS | E37: =0/(Deno) -> 0 | F37: =0/(Deno) -> 0 | G37: 0 | H37: 0 | I37: 0 | J37: 0 | K37: =+IF((G37+I37-H37-J37>0),G37+I37-H37-J37,0) -> 0 | L37: =+IF((H37+J37-G37-I37)>0,H37+J37-G37-I37,0) -> 0 | O37: =+IF((K37+M37-L37-N37>0),K37+M37-L37-N37,0)/Deno -> 0 | P37: =+IF((L37+N37-K37-M37)>0,L37+N37-K37-M37,0)/Deno -> 0 | Q37: Unbilled Income | R37: 13 | S37: Short-term loans and advances
D38: WORK IN PROGRESS JOBS REV | E38: =0/(Deno) -> 0 | F38: =0/(Deno) -> 0 | G38: 0 | H38: 0 | I38: 0 | J38: 0 | K38: =+IF((G38+I38-H38-J38>0),G38+I38-H38-J38,0) -> 0 | L38: =+IF((H38+J38-G38-I38)>0,H38+J38-G38-I38,0) -> 0 | O38: =+IF((K38+M38-L38-N38>0),K38+M38-L38-N38,0)/Deno -> 0 | P38: =+IF((L38+N38-K38-M38)>0,L38+N38-K38-M38,0)/Deno -> 0 | Q38: Unbilled Income | R38: 13 | S38: Short-term loans and advances
C39: ACCRUALS | E39: =0/(Deno) -> 0 | F39: =0/(Deno) -> 0 | K39: =+IF((G39+I39-H39-J39>0),G39+I39-H39-J39,0) -> 0 | L39: =+IF((H39+J39-G39-I39)>0,H39+J39-G39-I39,0) -> 0 | O39: =+IF((K39+M39-L39-N39>0),K39+M39-L39-N39,0)/Deno -> 0 | P39: =+IF((L39+N39-K39-M39)>0,L39+N39-K39-M39,0)/Deno -> 0
D40: PREPAID INTERNET EXPESES | E40: =0/(Deno) -> 0 | F40: =0/(Deno) -> 0 | G40: 0 | H40: 0 | I40: 0 | J40: 0 | K40: =+IF((G40+I40-H40-J40>0),G40+I40-H40-J40,0) -> 0 | L40: =+IF((H40+J40-G40-I40)>0,H40+J40-G40-I40,0) -> 0 | O40: =+IF((K40+M40-L40-N40>0),K40+M40-L40-N40,0)/Deno -> 0 | P40: =+IF((L40+N40-K40-M40)>0,L40+N40-K40-M40,0)/Deno -> 0 | Q40: Prepaid Expenses | R40: 13 | S40: Short-term loans and advances
D41: PREPAID INSURANCES | E41: =122066.25/(Deno) -> 1.2206625 | F41: =0/(Deno) -> 0 | G41: 122066.25 | H41: 0 | K41: =+IF((G41+I41-H41-J41>0),G41+I41-H41-J41,0) -> 122066.25 | L41: =+IF((H41+J41-G41-I41)>0,H41+J41-G41-I41,0) -> 0 | M41: =+'Audit entry'!D10 -> 130788.23 | N41: =+'Audit entry'!E7 -> 122066.25 | O41: =+IF((K41+M41-L41-N41>0),K41+M41-L41-N41,0)/Deno -> 1.3078823 | P41: =+IF((L41+N41-K41-M41)>0,L41+N41-K41-M41,0)/Deno -> 0 | Q41: Prepaid Expenses | R41: 13 | S41: Short-term loans and advances
B42: LOANS AND ADVANCES | E42: =0/(Deno) -> 0 | F42: =0/(Deno) -> 0 | K42: =+IF((G42+I42-H42-J42>0),G42+I42-H42-J42,0) -> 0 | L42: =+IF((H42+J42-G42-I42)>0,H42+J42-G42-I42,0) -> 0 | O42: =+IF((K42+M42-L42-N42>0),K42+M42-L42-N42,0)/Deno -> 0 | P42: =+IF((L42+N42-K42-M42)>0,L42+N42-K42-M42,0)/Deno -> 0
C43: ADVANCE RECOVERABLE IN CASH OR KIND OR FOR VALUE TO BE RECEIVED | E43: =0/(Deno) -> 0 | F43: =0/(Deno) -> 0 | K43: =+IF((G43+I43-H43-J43>0),G43+I43-H43-J43,0) -> 0 | L43: =+IF((H43+J43-G43-I43)>0,H43+J43-G43-I43,0) -> 0 | O43: =+IF((K43+M43-L43-N43>0),K43+M43-L43-N43,0)/Deno -> 0 | P43: =+IF((L43+N43-K43-M43)>0,L43+N43-K43-M43,0)/Deno -> 0
D44: STAFF ADVANCES | E44: =0/(Deno) -> 0 | F44: =0/(Deno) -> 0 | G44: 0 | H44: 0 | I44: 0 | J44: 0 | K44: =+IF((G44+I44-H44-J44>0),G44+I44-H44-J44,0) -> 0 | L44: =+IF((H44+J44-G44-I44)>0,H44+J44-G44-I44,0) -> 0 | O44: =+IF((K44+M44-L44-N44>0),K44+M44-L44-N44,0)/Deno -> 0 | P44: =+IF((L44+N44-K44-M44)>0,L44+N44-K44-M44,0)/Deno -> 0 | Q44: Staff Advance | R44: 13 | S44: Short-term loans and advances
D45: STAFF LOAN | E45: =29999.97/(Deno) -> 0.2999997 | F45: =0/(Deno) -> 0 | G45: 29999.97 | H45: 0 | I45: 0 | J45: 30000 | K45: =+IF((G45+I45-H45-J45>0),G45+I45-H45-J45,0) -> 0 | L45: =+IF((H45+J45-G45-I45)>0,H45+J45-G45-I45,0) -> 0.03 | O45: =+IF((K45+M45-L45-N45>0),K45+M45-L45-N45,0)/Deno -> 0 | P45: =+IF((L45+N45-K45-M45)>0,L45+N45-K45-M45,0)/Deno -> 3e-07 | Q45: Staff Advance | R45: 13 | S45: Short-term loans and advances
D46: TRAVEL ADVANCE | E46: =25604.67/(Deno) -> 0.2560467 | F46: =0/(Deno) -> 0 | G46: 25604.67 | H46: 0 | I46: 17577.1 | J46: 0 | K46: =+IF((G46+I46-H46-J46>0),G46+I46-H46-J46,0) -> 43181.77 | L46: =+IF((H46+J46-G46-I46)>0,H46+J46-G46-I46,0) -> 0 | O46: =+IF((K46+M46-L46-N46>0),K46+M46-L46-N46,0)/Deno -> 0.4318177 | P46: =+IF((L46+N46-K46-M46)>0,L46+N46-K46-M46,0)/Deno -> 0 | Q46: Staff Advance | R46: 13 | S46: Short-term loans and advances
D47: PREPAID SUBSCRIPTION | E47: =0/(Deno) -> 0 | F47: =0/(Deno) -> 0 | G47: 0 | H47: 0 | I47: 0 | J47: 0 | K47: =+IF((G47+I47-H47-J47>0),G47+I47-H47-J47,0) -> 0 | L47: =+IF((H47+J47-G47-I47)>0,H47+J47-G47-I47,0) -> 0 | O47: =+IF((K47+M47-L47-N47>0),K47+M47-L47-N47,0)/Deno -> 0 | P47: =+IF((L47+N47-K47-M47)>0,L47+N47-K47-M47,0)/Deno -> 0 | Q47: Prepaid Subscriptions | R47: 13 | S47: Short-term loans and advances
D48: PREPAID RENT | E48: =1473158/(Deno) -> 14.73158 | F48: =0/(Deno) -> 0 | G48: 1473158 | H48: 0 | I48: 0 | J48: 300000 | K48: =+IF((G48+I48-H48-J48>0),G48+I48-H48-J48,0) -> 1173158 | L48: =+IF((H48+J48-G48-I48)>0,H48+J48-G48-I48,0) -> 0 | O48: =+IF((K48+M48-L48-N48>0),K48+M48-L48-N48,0)/Deno -> 11.73158 | P48: =+IF((L48+N48-K48-M48)>0,L48+N48-K48-M48,0)/Deno -> 0 | Q48: Rental Deposit | R48: 9 | S48: Long-term loans and advances
D49: INTEREST ACCRUED BUT NOT RECEIVED | E49: =0/(Deno) -> 0 | F49: =0/(Deno) -> 0 | G49: 0 | H49: 0 | I49: 0 | J49: 0 | K49: =+IF((G49+I49-H49-J49>0),G49+I49-H49-J49,0) -> 0 | L49: =+IF((H49+J49-G49-I49)>0,H49+J49-G49-I49,0) -> 0 | O49: =+IF((K49+M49-L49-N49>0),K49+M49-L49-N49,0)/Deno -> 0 | P49: =+IF((L49+N49-K49-M49)>0,L49+N49-K49-M49,0)/Deno -> 0 | Q49: Interest Accrued | R49: 13 | S49: Short-term loans and advances
D50: DEPOSITS OFFICE | E50: =496500/(Deno) -> 4.965 | F50: =0/(Deno) -> 0 | G50: 496500 | H50: 0 | I50: 0 | J50: 0 | K50: =+IF((G50+I50-H50-J50>0),G50+I50-H50-J50,0) -> 496500 | L50: =+IF((H50+J50-G50-I50)>0,H50+J50-G50-I50,0) -> 0 | O50: =+IF((K50+M50-L50-N50>0),K50+M50-L50-N50,0)/Deno -> 4.965 | P50: =+IF((L50+N50-K50-M50)>0,L50+N50-K50-M50,0)/Deno -> 0 | Q50: Rental Deposit | R50: 9 | S50: Long-term loans and advances
D51: CGST RECEIVABLE | E51: =4179062/(Deno) -> 41.79062 | F51: =0/(Deno) -> 0 | G51: 4179062 | H51: 0 | I51: 7875864.4 | J51: 0 | K51: =+IF((G51+I51-H51-J51>0),G51+I51-H51-J51,0) -> 12054926 | L51: =+IF((H51+J51-G51-I51)>0,H51+J51-G51-I51,0) -> 0 | O51: =+IF((K51+M51-L51-N51>0),K51+M51-L51-N51,0)/Deno -> 120.54926 | P51: =+IF((L51+N51-K51-M51)>0,L51+N51-K51-M51,0)/Deno -> 0 | Q51: GST - Input tax credit | R51: 13 | S51: Short-term loans and advances | T51: GST Input tax credit
D52: IGST RECEIVABLE | E52: =76342/(Deno) -> 0.76342 | F52: =0/(Deno) -> 0 | G52: 76342 | H52: 0 | I52: 4830183 | J52: 0 | K52: =+IF((G52+I52-H52-J52>0),G52+I52-H52-J52,0) -> 4906525 | L52: =+IF((H52+J52-G52-I52)>0,H52+J52-G52-I52,0) -> 0 | O52: =+IF((K52+M52-L52-N52>0),K52+M52-L52-N52,0)/Deno -> 49.06525 | P52: =+IF((L52+N52-K52-M52)>0,L52+N52-K52-M52,0)/Deno -> 0 | Q52: GST - Input tax credit | R52: 13 | S52: Short-term loans and advances | T52: GST Input tax credit
D53: SGST RECEIVABLE | E53: =3028379/(Deno) -> 30.28379 | F53: =0/(Deno) -> 0 | G53: 3028379 | H53: 0 | I53: 7875862.3 | J53: 0 | K53: =+IF((G53+I53-H53-J53>0),G53+I53-H53-J53,0) -> 10904241 | L53: =+IF((H53+J53-G53-I53)>0,H53+J53-G53-I53,0) -> 0 | O53: =+IF((K53+M53-L53-N53>0),K53+M53-L53-N53,0)/Deno -> 109.04241 | P53: =+IF((L53+N53-K53-M53)>0,L53+N53-K53-M53,0)/Deno -> 0 | Q53: GST - Input tax credit | R53: 13 | S53: Short-term loans and advances | T53: GST Input tax credit
D54: GST ELECTRONIC CASH LEDGER | E54: =0/(Deno) -> 0 | F54: =0/(Deno) -> 0 | G54: 0 | H54: 0 | I54: 4235617 | J54: 0 | K54: =+IF((G54+I54-H54-J54>0),G54+I54-H54-J54,0) -> 4235617 | L54: =+IF((H54+J54-G54-I54)>0,H54+J54-G54-I54,0) -> 0 | O54: =+IF((K54+M54-L54-N54>0),K54+M54-L54-N54,0)/Deno -> 42.35617 | P54: =+IF((L54+N54-K54-M54)>0,L54+N54-K54-M54,0)/Deno -> 0 | Q54: GST - Input tax credit | R54: 13 | S54: Short-term loans and advances | T54: GST Input tax credit
D55: CENVAT CREDIT CHS | E55: =0/(Deno) -> 0 | F55: =0/(Deno) -> 0 | G55: 0 | H55: 0 | I55: 0 | J55: 0 | K55: =+IF((G55+I55-H55-J55>0),G55+I55-H55-J55,0) -> 0 | L55: =+IF((H55+J55-G55-I55)>0,H55+J55-G55-I55,0) -> 0 | O55: =+IF((K55+M55-L55-N55>0),K55+M55-L55-N55,0)/Deno -> 0 | P55: =+IF((L55+N55-K55-M55)>0,L55+N55-K55-M55,0)/Deno -> 0 | Q55: Cenvat Credit | R55: 13 | S55: Short-term loans and advances
D56: CENVAT CREDIT - KRISHI KALYAN CESS - CHS | E56: =0/(Deno) -> 0 | F56: =0/(Deno) -> 0 | G56: 0 | H56: 0 | I56: 0 | J56: 0 | K56: =+IF((G56+I56-H56-J56>0),G56+I56-H56-J56,0) -> 0 | L56: =+IF((H56+J56-G56-I56)>0,H56+J56-G56-I56,0) -> 0 | O56: =+IF((K56+M56-L56-N56>0),K56+M56-L56-N56,0)/Deno -> 0 | P56: =+IF((L56+N56-K56-M56)>0,L56+N56-K56-M56,0)/Deno -> 0 | Q56: Cenvat Credit | R56: 13 | S56: Short-term loans and advances
D57: ADVANCE FOR CAPITAL EXPENSES | E57: =0/(Deno) -> 0 | F57: =0/(Deno) -> 0 | G57: 0 | H57: 0 | I57: 0 | J57: 0 | K57: =+IF((G57+I57-H57-J57>0),G57+I57-H57-J57,0) -> 0 | L57: =+IF((H57+J57-G57-I57)>0,H57+J57-G57-I57,0) -> 0 | O57: =+IF((K57+M57-L57-N57>0),K57+M57-L57-N57,0)/Deno -> 0 | P57: =+IF((L57+N57-K57-M57)>0,L57+N57-K57-M57,0)/Deno -> 0 | Q57: Advance for capital expenses | R57: 13 | S57: Short-term loans and advances
D58: ADVANCE PAID \ RECEIVED | E58: =0/(Deno) -> 0 | F58: =13926026.75/(Deno) -> 139.26027 | G58: 0 | H58: 13926027 | I58: 0 | J58: 380165.39 | K58: =+IF((G58+I58-H58-J58>0),G58+I58-H58-J58,0) -> 0 | L58: =+IF((H58+J58-G58-I58)>0,H58+J58-G58-I58,0) -> 14306192 | O58: =+IF((K58+M58-L58-N58>0),K58+M58-L58-N58,0)/Deno -> 0 | P58: =+IF((L58+N58-K58-M58)>0,L58+N58-K58-M58,0)/Deno -> 143.06192 | Q58: advance paid \ received | R58: 7 | S58: Short-term loans and advances
D59: RK CHEQUE | E59: =50000/(Deno) -> 0.5 | F59: =0/(Deno) -> 0 | G59: 50000 | H59: 0 | I59: 0 | J59: 0 | K59: =+IF((G59+I59-H59-J59>0),G59+I59-H59-J59,0) -> 50000 | L59: =+IF((H59+J59-G59-I59)>0,H59+J59-G59-I59,0) -> 0 | N59: ='Audit entry'!E146 -> 50000 | O59: =+IF((K59+M59-L59-N59>0),K59+M59-L59-N59,0)/Deno -> 0 | P59: =+IF((L59+N59-K59-M59)>0,L59+N59-K59-M59,0)/Deno -> 0 | Q59: Cash in hand | R59: 12 | S59: Cash and cash equivalents
C60: ADVANCE TAX | E60: =0/(Deno) -> 0 | F60: =0/(Deno) -> 0 | K60: =+IF((G60+I60-H60-J60>0),G60+I60-H60-J60,0) -> 0 | L60: =+IF((H60+J60-G60-I60)>0,H60+J60-G60-I60,0) -> 0 | O60: =+IF((K60+M60-L60-N60>0),K60+M60-L60-N60,0)/Deno -> 0 | P60: =+IF((L60+N60-K60-M60)>0,L60+N60-K60-M60,0)/Deno -> 0
D61: TDS RECEIVABLE | E61: =18513073.8316667/(Deno) -> 185.13074 | F61: =0/(Deno) -> 0 | G61: 18513074 | H61: 0 | I61: 3255908.4 | J61: 0 | K61: =+IF((G61+I61-H61-J61>0),G61+I61-H61-J61,0) -> 21768982 | L61: =+IF((H61+J61-G61-I61)>0,H61+J61-G61-I61,0) -> 0 | N61: ='Audit entry'!E152 -> 654762.49 | O61: =+IF((K61+M61-L61-N61>0),K61+M61-L61-N61,0)/Deno -> 211.1422 | P61: =+IF((L61+N61-K61-M61)>0,L61+N61-K61-M61,0)/Deno -> 0 | Q61: TDS Receivable | R61: 9 | S61: Long-term loans and advances
C62: DIRECTOR LOAN | E62: =0/(Deno) -> 0 | F62: =0/(Deno) -> 0 | K62: =+IF((G62+I62-H62-J62>0),G62+I62-H62-J62,0) -> 0 | L62: =+IF((H62+J62-G62-I62)>0,H62+J62-G62-I62,0) -> 0 | O62: =+IF((K62+M62-L62-N62>0),K62+M62-L62-N62,0)/Deno -> 0 | P62: =+IF((L62+N62-K62-M62)>0,L62+N62-K62-M62,0)/Deno -> 0
D63: DIRECTOR LOAN | E63: =0/(Deno) -> 0 | F63: =0/(Deno) -> 0 | G63: 0 | H63: 0 | I63: 0 | J63: 0 | K63: =+IF((G63+I63-H63-J63>0),G63+I63-H63-J63,0) -> 0 | L63: =+IF((H63+J63-G63-I63)>0,H63+J63-G63-I63,0) -> 0 | O63: =+IF((K63+M63-L63-N63>0),K63+M63-L63-N63,0)/Deno -> 0 | P63: =+IF((L63+N63-K63-M63)>0,L63+N63-K63-M63,0)/Deno -> 0
C64: IATA SHIPMENT ADVANCE | E64: =0/(Deno) -> 0 | F64: =0/(Deno) -> 0 | K64: =+IF((G64+I64-H64-J64>0),G64+I64-H64-J64,0) -> 0 | L64: =+IF((H64+J64-G64-I64)>0,H64+J64-G64-I64,0) -> 0 | O64: =+IF((K64+M64-L64-N64>0),K64+M64-L64-N64,0)/Deno -> 0 | P64: =+IF((L64+N64-K64-M64)>0,L64+N64-K64-M64,0)/Deno -> 0
D65: IATA SHIPMENT ADVANCE | E65: =25000/(Deno) -> 0.25 | F65: =0/(Deno) -> 0 | G65: 25000 | H65: 0 | I65: 0 | J65: 0 | K65: =+IF((G65+I65-H65-J65>0),G65+I65-H65-J65,0) -> 25000 | L65: =+IF((H65+J65-G65-I65)>0,H65+J65-G65-I65,0) -> 0 | O65: =+IF((K65+M65-L65-N65>0),K65+M65-L65-N65,0)/Deno -> 0.25 | P65: =+IF((L65+N65-K65-M65)>0,L65+N65-K65-M65,0)/Deno -> 0 | Q65: advance paid \ received | R65: 7 | S65: Short-term loans and advances
B66: DEFERRED TAX ASSET | E66: =0/(Deno) -> 0 | F66: =0/(Deno) -> 0 | K66: =+IF((G66+I66-H66-J66>0),G66+I66-H66-J66,0) -> 0 | L66: =+IF((H66+J66-G66-I66)>0,H66+J66-G66-I66,0) -> 0 | O66: =+IF((K66+M66-L66-N66>0),K66+M66-L66-N66,0)/Deno -> 0 | P66: =+IF((L66+N66-K66-M66)>0,L66+N66-K66-M66,0)/Deno -> 0 | S66: *
D67: DEFERRED TAX ASSET | E67: =634958.005078724/(Deno) -> 6.3495801 | F67: =0/(Deno) -> 0 | G67: 634958.01 | H67: 0 | I67: 0 | J67: 0 | K67: =+IF((G67+I67-H67-J67>0),G67+I67-H67-J67,0) -> 634958.01 | L67: =+IF((H67+J67-G67-I67)>0,H67+J67-G67-I67,0) -> 0 | N67: =+'Audit entry'!E32 -> 0.37521685 | O67: =+IF((K67+M67-L67-N67>0),K67+M67-L67-N67,0)/Deno -> 6.3495763 | P67: =+IF((L67+N67-K67-M67)>0,L67+N67-K67-M67,0)/Deno -> 0 | R67: 10 | S67: Deferred tax asset
D68: INCOME TAX PAID | E68: =0/(Deno) -> 0 | F68: =0/(Deno) -> 0 | G68: 0 | H68: 0 | I68: 0 | J68: 0 | K68: =+IF((G68+I68-H68-J68>0),G68+I68-H68-J68,0) -> 0 | L68: =+IF((H68+J68-G68-I68)>0,H68+J68-G68-I68,0) -> 0 | O68: =+IF((K68+M68-L68-N68>0),K68+M68-L68-N68,0)/Deno -> 0 | P68: =+IF((L68+N68-K68-M68)>0,L68+N68-K68-M68,0)/Deno -> 0
A69: LIABILITIES | E69: =0/(Deno) -> 0 | F69: =0/(Deno) -> 0 | K69: =+IF((G69+I69-H69-J69>0),G69+I69-H69-J69,0) -> 0 | L69: =+IF((H69+J69-G69-I69)>0,H69+J69-G69-I69,0) -> 0 | O69: =+IF((K69+M69-L69-N69>0),K69+M69-L69-N69,0)/Deno -> 0 | P69: =+IF((L69+N69-K69-M69)>0,L69+N69-K69-M69,0)/Deno -> 0
B70: SHARE HOLDERS FUND | E70: =0/(Deno) -> 0 | F70: =0/(Deno) -> 0 | K70: =+IF((G70+I70-H70-J70>0),G70+I70-H70-J70,0) -> 0 | L70: =+IF((H70+J70-G70-I70)>0,H70+J70-G70-I70,0) -> 0 | O70: =+IF((K70+M70-L70-N70>0),K70+M70-L70-N70,0)/Deno -> 0 | P70: =+IF((L70+N70-K70-M70)>0,L70+N70-K70-M70,0)/Deno -> 0
C71: SHARE CAPITAL | E71: =0/(Deno) -> 0 | F71: =0/(Deno) -> 0 | K71: =+IF((G71+I71-H71-J71>0),G71+I71-H71-J71,0) -> 0 | L71: =+IF((H71+J71-G71-I71)>0,H71+J71-G71-I71,0) -> 0 | O71: =+IF((K71+M71-L71-N71>0),K71+M71-L71-N71,0)/Deno -> 0 | P71: =+IF((L71+N71-K71-M71)>0,L71+N71-K71-M71,0)/Deno -> 0
D72: EQUITY SHARE CAPITAL | E72: =0/(Deno) -> 0 | F72: =200000/(Deno) -> 2 | G72: 0 | H72: 200000 | I72: 0 | J72: 0 | K72: =+IF((G72+I72-H72-J72>0),G72+I72-H72-J72,0) -> 0 | L72: =+IF((H72+J72-G72-I72)>0,H72+J72-G72-I72,0) -> 200000 | O72: =+IF((K72+M72-L72-N72>0),K72+M72-L72-N72,0)/Deno -> 0 | P72: =+IF((L72+N72-K72-M72)>0,L72+N72-K72-M72,0)/Deno -> 2 | Q72: Equity Share Capital | R72: 3 | S72: Share capital
D73: RETAINED EARNINGS | E73: =0/(Deno) -> 0 | F73: =12289768.56/(Deno) -> 122.89769 | G73: 0 | H73: =12289768.56 -> 12289769 | I73: 0 | J73: 0 | K73: =+IF((G73+I73-H73-J73>0),G73+I73-H73-J73,0) -> 0 | L73: =+IF((H73+J73-G73-I73)>0,H73+J73-G73-I73,0) -> 12289769 | O73: =+IF((K73+M73-L73-N73>0),K73+M73-L73-N73,0)/Deno -> 0 | P73: =+IF((L73+N73-K73-M73)>0,L73+N73-K73-M73,0)/Deno -> 122.89769 | R73: 4 | S73: Reserve and surplus
C74: RESERVES AND SURPLUS | E74: =0/(Deno) -> 0 | F74: =0/(Deno) -> 0 | K74: =+IF((G74+I74-H74-J74>0),G74+I74-H74-J74,0) -> 0 | L74: =+IF((H74+J74-G74-I74)>0,H74+J74-G74-I74,0) -> 0 | O74: =+IF((K74+M74-L74-N74>0),K74+M74-L74-N74,0)/Deno -> 0 | P74: =+IF((L74+N74-K74-M74)>0,L74+N74-K74-M74,0)/Deno -> 0
D75: PROFIT AND LOSS ACCOUNT | E75: =3589998.79411491/(Deno) -> 35.899988 | F75: =0/(Deno) -> 0 | G75: 3589998.8 | H75: -4992850.2 | I75: 0 | J75: 0 | K75: =+IF((G75+I75-H75-J75>0),G75+I75-H75-J75,0) -> 8582849 | L75: =+IF((H75+J75-G75-I75)>0,H75+J75-G75-I75,0) -> 0 | M75: =+'Audit entry'!D31+'Audit entry'!D148 -> 654762.86 | N75: =+'Audit entry'!E127 -> 14106836 | O75: =+IF((K75+M75-L75-N75>0),K75+M75-L75-N75,0)/Deno -> 0 | P75: =+IF((L75+N75-K75-M75)>0,L75+N75-K75-M75,0)/Deno -> 48.692245 | R75: 4 | S75: Reserve and surplus
B76: LOAN FUND | E76: =0/(Deno) -> 0 | F76: =0/(Deno) -> 0 | K76: =+IF((G76+I76-H76-J76>0),G76+I76-H76-J76,0) -> 0 | L76: =+IF((H76+J76-G76-I76)>0,H76+J76-G76-I76,0) -> 0 | O76: =+IF((K76+M76-L76-N76>0),K76+M76-L76-N76,0)/Deno -> 0 | P76: =+IF((L76+N76-K76-M76)>0,L76+N76-K76-M76,0)/Deno -> 0
C77: SECURED LOAN | E77: =0/(Deno) -> 0 | F77: =0/(Deno) -> 0 | K77: =+IF((G77+I77-H77-J77>0),G77+I77-H77-J77,0) -> 0 | L77: =+IF((H77+J77-G77-I77)>0,H77+J77-G77-I77,0) -> 0 | O77: =+IF((K77+M77-L77-N77>0),K77+M77-L77-N77,0)/Deno -> 0 | P77: =+IF((L77+N77-K77-M77)>0,L77+N77-K77-M77,0)/Deno -> 0
D78: LOAN - CIL OMAN | E78: =0/(Deno) -> 0 | F78: =0/(Deno) -> 0 | G78: 0 | H78: 0 | I78: 0 | J78: 0 | K78: =+IF((G78+I78-H78-J78>0),G78+I78-H78-J78,0) -> 0 | L78: =+IF((H78+J78-G78-I78)>0,H78+J78-G78-I78,0) -> 0 | O78: =+IF((K78+M78-L78-N78>0),K78+M78-L78-N78,0)/Deno -> 0 | P78: =+IF((L78+N78-K78-M78)>0,L78+N78-K78-M78,0)/Deno -> 0 | Q78: Loan - CIL Oman | S78: Longterm Borrowings
D79: LOAN - ICL UK | E79: =0/(Deno) -> 0 | F79: =0/(Deno) -> 0 | G79: 0 | H79: 0 | I79: 0 | J79: 0 | K79: =+IF((G79+I79-H79-J79>0),G79+I79-H79-J79,0) -> 0 | L79: =+IF((H79+J79-G79-I79)>0,H79+J79-G79-I79,0) -> 0 | O79: =+IF((K79+M79-L79-N79>0),K79+M79-L79-N79,0)/Deno -> 0 | P79: =+IF((L79+N79-K79-M79)>0,L79+N79-K79-M79,0)/Deno -> 0 | Q79: Loan- ICL UK | S79: Longterm Borrowings
D80: HDFC CAR LOAN | E80: =0/(Deno) -> 0 | F80: =0/(Deno) -> 0 | G80: 0 | H80: 0 | I80: 0 | J80: 0 | K80: =+IF((G80+I80-H80-J80>0),G80+I80-H80-J80,0) -> 0 | L80: =+IF((H80+J80-G80-I80)>0,H80+J80-G80-I80,0) -> 0 | O80: =+IF((K80+M80-L80-N80>0),K80+M80-L80-N80,0)/Deno -> 0 | P80: =+IF((L80+N80-K80-M80)>0,L80+N80-K80-M80,0)/Deno -> 0 | Q80: HDFC Car Loan | S80: Longterm Borrowings
C81: UNSECURED LOAN | E81: =0/(Deno) -> 0 | F81: =0/(Deno) -> 0 | K81: =+IF((G81+I81-H81-J81>0),G81+I81-H81-J81,0) -> 0 | L81: =+IF((H81+J81-G81-I81)>0,H81+J81-G81-I81,0) -> 0 | O81: =+IF((K81+M81-L81-N81>0),K81+M81-L81-N81,0)/Deno -> 0 | P81: =+IF((L81+N81-K81-M81)>0,L81+N81-K81-M81,0)/Deno -> 0
D82: LOAN - CIL DUBAI | E82: =0/(Deno) -> 0 | F82: =0/(Deno) -> 0 | G82: 0 | H82: 0 | I82: 0 | J82: 0 | K82: =+IF((G82+I82-H82-J82>0),G82+I82-H82-J82,0) -> 0 | L82: =+IF((H82+J82-G82-I82)>0,H82+J82-G82-I82,0) -> 0 | O82: =+IF((K82+M82-L82-N82>0),K82+M82-L82-N82,0)/Deno -> 0 | P82: =+IF((L82+N82-K82-M82)>0,L82+N82-K82-M82,0)/Deno -> 0 | Q82: Loan - CIL Dubai | S82: Longterm Borrowings
D83: UNSECURED LOAN | E83: =0/(Deno) -> 0 | F83: =0/(Deno) -> 0 | G83: 0 | H83: 0 | I83: 0 | J83: 0 | K83: =+IF((G83+I83-H83-J83>0),G83+I83-H83-J83,0) -> 0 | L83: =+IF((H83+J83-G83-I83)>0,H83+J83-G83-I83,0) -> 0 | O83: =+IF((K83+M83-L83-N83>0),K83+M83-L83-N83,0)/Deno -> 0 | P83: =+IF((L83+N83-K83-M83)>0,L83+N83-K83-M83,0)/Deno -> 0 | Q83: Unsecured Loan | S83: Longterm Borrowings
D84: Mobile Emi | E84: =0/(Deno) -> 0 | F84: =0/(Deno) -> 0 | G84: 0 | H84: 0 | I84: 0 | J84: 0 | K84: =+IF((G84+I84-H84-J84>0),G84+I84-H84-J84,0) -> 0 | L84: =+IF((H84+J84-G84-I84)>0,H84+J84-G84-I84,0) -> 0 | O84: =+IF((K84+M84-L84-N84>0),K84+M84-L84-N84,0)/Deno -> 0 | P84: =+IF((L84+N84-K84-M84)>0,L84+N84-K84-M84,0)/Deno -> 0 | Q84: Mobile EMI | S84: Longterm Borrowings
B85: CURRENT LIABILITIES | E85: =0/(Deno) -> 0 | F85: =0/(Deno) -> 0 | K85: =+IF((G85+I85-H85-J85>0),G85+I85-H85-J85,0) -> 0 | L85: =+IF((H85+J85-G85-I85)>0,H85+J85-G85-I85,0) -> 0 | O85: =+IF((K85+M85-L85-N85>0),K85+M85-L85-N85,0)/Deno -> 0 | P85: =+IF((L85+N85-K85-M85)>0,L85+N85-K85-M85,0)/Deno -> 0
C86: SUNDRY CREDITORS | E86: =0/(Deno) -> 0 | F86: =0/(Deno) -> 0 | K86: =+IF((G86+I86-H86-J86>0),G86+I86-H86-J86,0) -> 0 | L86: =+IF((H86+J86-G86-I86)>0,H86+J86-G86-I86,0) -> 0 | O86: =+IF((K86+M86-L86-N86>0),K86+M86-L86-N86,0)/Deno -> 0 | P86: =+IF((L86+N86-K86-M86)>0,L86+N86-K86-M86,0)/Deno -> 0
D87: LOCAL CREDITORS - FREIGHT FORWARDING | E87: =0/(Deno) -> 0 | F87: =39845262.9399998/(Deno) -> 398.45263 | G87: 0 | H87: 39845263 | I87: 0 | J87: 415912.29 | K87: =+IF((G87+I87-H87-J87>0),G87+I87-H87-J87,0) -> 0 | L87: =+IF((H87+J87-G87-I87)>0,H87+J87-G87-I87,0) -> 40261175 | M87: =+'Audit entry'!D34+SUM('Audit entry'!D40:D52)-SUM('Audit entry'!E53:E54)+SUM('Audit entry'!D100:D108)-SUM('Audit entry'!E110:E119) -> 89690.917 | N87: =+'Audit entry'!E38+'Audit entry'!E130+'Audit entry'!E134 -> 6012740.5 | O87: =+IF((K87+M87-L87-N87>0),K87+M87-L87-N87,0)/Deno -> 0 | P87: =+IF((L87+N87-K87-M87)>0,L87+N87-K87-M87,0)/Deno -> 461.84225 | R87: 5 | S87: Trade Payables
D88: INTER BRANCH ACCOUNT | E88: =0/(Deno) -> 0 | F88: =1072835.62/(Deno) -> 10.728356 | G88: 0 | H88: 1072835.6 | I88: 0 | J88: 3.7252903e-09 | K88: =+IF((G88+I88-H88-J88>0),G88+I88-H88-J88,0) -> 0 | L88: =+IF((H88+J88-G88-I88)>0,H88+J88-G88-I88,0) -> 1072835.6 | O88: =+IF((K88+M88-L88-N88>0),K88+M88-L88-N88,0)/Deno -> 0 | P88: =+IF((L88+N88-K88-M88)>0,L88+N88-K88-M88,0)/Deno -> 10.728356 | R88: 5 | S88: Trade Payables
D89: INTER BRANCH SUSPENSE ACCOUNT | E89: =1004426/(Deno) -> 10.04426 | F89: =0/(Deno) -> 0 | G89: 1004426 | H89: 0 | I89: 7734 | J89: 0 | K89: =+IF((G89+I89-H89-J89>0),G89+I89-H89-J89,0) -> 1012160 | L89: =+IF((H89+J89-G89-I89)>0,H89+J89-G89-I89,0) -> 0 | O89: =+IF((K89+M89-L89-N89>0),K89+M89-L89-N89,0)/Deno -> 10.1216 | P89: =+IF((L89+N89-K89-M89)>0,L89+N89-K89-M89,0)/Deno -> 0 | R89: 5 | S89: Trade Payables
D90: OVERSEAS CREDITORS - FREIGHT FORWARDING | E90: =0/(Deno) -> 0 | F90: =17438152.028043/(Deno) -> 174.38152 | G90: 0 | H90: 17438152 | I90: 0 | J90: 37639710 | K90: =+IF((G90+I90-H90-J90>0),G90+I90-H90-J90,0) -> 0 | L90: =+IF((H90+J90-G90-I90)>0,H90+J90-G90-I90,0) -> 55077863 | O90: =+IF((K90+M90-L90-N90>0),K90+M90-L90-N90,0)/Deno -> 0 | P90: =+IF((L90+N90-K90-M90)>0,L90+N90-K90-M90,0)/Deno -> 550.77863 | R90: 5 | S90: Trade Payables
D91: OTHER LIABILITY | E91: =0/(Deno) -> 0 | F91: =0/(Deno) -> 0 | G91: 0 | H91: 0 | I91: 0 | J91: 0 | K91: =+IF((G91+I91-H91-J91>0),G91+I91-H91-J91,0) -> 0 | L91: =+IF((H91+J91-G91-I91)>0,H91+J91-G91-I91,0) -> 0 | O91: =+IF((K91+M91-L91-N91>0),K91+M91-L91-N91,0)/Deno -> 0 | P91: =+IF((L91+N91-K91-M91)>0,L91+N91-K91-M91,0)/Deno -> 0 | Q91: Other Liabilities | R91: 6 | S91: Other Current Liabilities
D92: AUDIT FEES PAYABLE | E92: =0/(Deno) -> 0 | F92: =725000/(Deno) -> 7.25 | G92: 0 | H92: 725000 | K92: =+IF((G92+I92-H92-J92>0),G92+I92-H92-J92,0) -> 0 | L92: =+IF((H92+J92-G92-I92)>0,H92+J92-G92-I92,0) -> 725000 | M92: =+'Audit entry'!D14 -> 225000 | N92: =+'Audit entry'!E28 -> 225000 | O92: =+IF((K92+M92-L92-N92>0),K92+M92-L92-N92,0)/Deno -> 0 | P92: =+IF((L92+N92-K92-M92)>0,L92+N92-K92-M92,0)/Deno -> 7.25 | Q92: Audit Fee payable | R92: 6 | S92: Other Current Liabilities | T92: Expense payable
D93: GST Audit Fees payable | E93: =0/(Deno) -> 0 | F93: =90000/(Deno) -> 0.9 | G93: 0 | H93: 90000 | K93: =+IF((G93+I93-H93-J93>0),G93+I93-H93-J93,0) -> 0 | L93: =+IF((H93+J93-G93-I93)>0,H93+J93-G93-I93,0) -> 90000 | O93: =+IF((K93+M93-L93-N93>0),K93+M93-L93-N93,0)/Deno -> 0 | P93: =+IF((L93+N93-K93-M93)>0,L93+N93-K93-M93,0)/Deno -> 0.9 | Q93: GST Audit Fees payable | R93: 6 | S93: Other Current Liabilities | T93: Expense payable
C94: OTHER LIABILITIES | E94: =0/(Deno) -> 0 | F94: =0/(Deno) -> 0 | K94: =+IF((G94+I94-H94-J94>0),G94+I94-H94-J94,0) -> 0 | L94: =+IF((H94+J94-G94-I94)>0,H94+J94-G94-I94,0) -> 0 | O94: =+IF((K94+M94-L94-N94>0),K94+M94-L94-N94,0)/Deno -> 0 | P94: =+IF((L94+N94-K94-M94)>0,L94+N94-K94-M94,0)/Deno -> 0
E95: =0/(Deno) -> 0 | F95: =0/(Deno) -> 0 | K95: =+IF((G95+I95-H95-J95>0),G95+I95-H95-J95,0) -> 0 | L95: =+IF((H95+J95-G95-I95)>0,H95+J95-G95-I95,0) -> 0 | O95: =+IF((K95+M95-L95-N95>0),K95+M95-L95-N95,0)/Deno -> 0 | P95: =+IF((L95+N95-K95-M95)>0,L95+N95-K95-M95,0)/Deno -> 0
D96: CONVEYANCE PAYABLE | E96: =0/(Deno) -> 0 | F96: =198883.37/(Deno) -> 1.9888337 | G96: 0 | H96: 198883.37 | I96: 0 | J96: 704970.69 | K96: =+IF((G96+I96-H96-J96>0),G96+I96-H96-J96,0) -> 0 | L96: =+IF((H96+J96-G96-I96)>0,H96+J96-G96-I96,0) -> 903854.06 | O96: =+IF((K96+M96-L96-N96>0),K96+M96-L96-N96,0)/Deno -> 0 | P96: =+IF((L96+N96-K96-M96)>0,L96+N96-K96-M96,0)/Deno -> 9.0385406 | Q96: Convenyance Payable | R96: 6 | S96: Other Current Liabilities | T96: Expense payable
D97: ACCRUALS | E97: =0/(Deno) -> 0 | F97: =0/(Deno) -> 0 | G97: 0 | H97: 0 | I97: 233685 | J97: 0 | K97: =+IF((G97+I97-H97-J97>0),G97+I97-H97-J97,0) -> 233685 | L97: =+IF((H97+J97-G97-I97)>0,H97+J97-G97-I97,0) -> 0 | M97: =+'Audit entry'!D22 -> 1315 | N97: ='Audit entry'!E15+'Audit entry'!E19 -> 235000 | O97: =+IF((K97+M97-L97-N97>0),K97+M97-L97-N97,0)/Deno -> 0 | P97: =+IF((L97+N97-K97-M97)>0,L97+N97-K97-M97,0)/Deno -> 0 | Q97: Audit Fee payable | R97: 6 | S97: Other Current Liabilities | T97: Expense payable
D98: CORPORATE CARD 9003 | E98: =0/(Deno) -> 0 | F98: =0/(Deno) -> 0 | G98: 0 | H98: 0 | I98: 0 | J98: 797544.98 | K98: =+IF((G98+I98-H98-J98>0),G98+I98-H98-J98,0) -> 0 | L98: =+IF((H98+J98-G98-I98)>0,H98+J98-G98-I98,0) -> 797544.98 | O98: =+IF((K98+M98-L98-N98>0),K98+M98-L98-N98,0)/Deno -> 0 | P98: =+IF((L98+N98-K98-M98)>0,L98+N98-K98-M98,0)/Deno -> 7.9754498 | Q98: Other Liabilities | R98: 6 | S98: Other Current Liabilities | T98: Expense payable
D99: CORPORATE CARD 0007 | E99: =0/(Deno) -> 0 | F99: =0/(Deno) -> 0 | G99: 0 | H99: 0 | I99: 0 | J99: 0 | K99: =+IF((G99+I99-H99-J99>0),G99+I99-H99-J99,0) -> 0 | L99: =+IF((H99+J99-G99-I99)>0,H99+J99-G99-I99,0) -> 0 | O99: =+IF((K99+M99-L99-N99>0),K99+M99-L99-N99,0)/Deno -> 0 | P99: =+IF((L99+N99-K99-M99)>0,L99+N99-K99-M99,0)/Deno -> 0 | Q99: Other Liabilities | R99: 6 | S99: Other Current Liabilities | T99: Expense payable
C100: STATUTORY LIABILITIES | E100: =0/(Deno) -> 0 | F100: =0/(Deno) -> 0 | K100: =+IF((G100+I100-H100-J100>0),G100+I100-H100-J100,0) -> 0 | L100: =+IF((H100+J100-G100-I100)>0,H100+J100-G100-I100,0) -> 0 | O100: =+IF((K100+M100-L100-N100>0),K100+M100-L100-N100,0)/Deno -> 0 | P100: =+IF((L100+N100-K100-M100)>0,L100+N100-K100-M100,0)/Deno -> 0
...

Sheet BS
A1: CARGO INTERNATIONAL (INDIA) PRIVATE LIMITED
A2: BALANCE SHEET AS AT 31ST MARCH, 2025
A3: CIN : U63000TN2010PTC077296
A4: Old No.7 / New No.13, First Floor, First Cross Street, Trustpuram, Kodambakkam, Chennai - 600024, India
A5: =+"(Unless otherwise specified, all amounts are "&IF('Master data'!A2="Ones","Indian Rupees","in "&'Master data'!A2&" of INR)") -> (Unless otherwise specified, all amounts are in Lakhs of INR)
A6: Particulars | B6: Note No. | C6: As on | D6: As on
C7: 31st March, 2025 | D7: 31st March, 2024
A9: I.EQUITY AND LIABILITIES | F9: +RC[-2]*100000 | G9: +RC[-2]*100000
A10: SHARE HOLDERS FUNDS | F10: +RC[-2]*100000 | G10: +RC[-2]*100000
A11: a. Share capital | B11: 3 | C11: =+'NOTE 3'!D15 -> 2 | D11: =+'NOTE 3'!E15 -> 2 | F11: +RC[-2]*100000
A12: b. Reserve and surplus | B12: 4 | C12: =+'NOTE 4-8'!B15 -> 197.74662 | D12: =+'NOTE 4-8'!C15 -> 37.069193 | E12: =+C12*100000 -> 19774662 | F12: +RC[-2]*100000 | G12: +RC[-2]*100000
C13: =SUM(C11:C12) -> 199.74662 | D13: =SUM(D11:D12) -> 39.069193 | E13: =+C13*100000 -> 19974662 | F13: +RC[-2]*100000 | G13: +RC[-2]*100000
A14: NON CURRENT LIABILITIES | E14: =+C14*100000 -> 0 | F14: +RC[-2]*100000 | G14: +RC[-2]*100000
A15: a. Other Long term Liabilities | B15: 5 | C15: =+'NOTE 4-8'!B20 -> 148.44185 | D15: =+'NOTE 4-8'!C20 -> 148.44185 | E15: =+C15*100000 -> 14844185 | F15: +RC[-2]*100000 | G15: +RC[-2]*100000
C16: =+C15 -> 148.44185 | D16: =+D15 -> 148.44185 | E16: =+C16*100000 -> 14844185 | F16: +RC[-2]*100000 | G16: +RC[-2]*100000
A17: CURRENT LIABILITIES | E17: =+C17*100000 -> 0 | F17: +RC[-2]*100000 | G17: +RC[-2]*100000
A18: a. Trade payables | B18: 6 | E18: =+C18*100000 -> 0 | F18: +RC[-2]*100000 | G18: +RC[-2]*100000
A19: i. Outstanding due against MSME | C19: =+'NOTE 6'!G12 -> 0 | D19: =+'NOTE 6'!G24 -> 0 | E19: =+C19*100000 -> 0 | F19: +RC[-2]*100000 | G19: +RC[-2]*100000
A20: ii.Outstanding due against Other than MSME | C20: =+'NOTE 6'!G17 -> 904.28354 | D20: =+SUM('NOTE 6'!G25:G27) -> 464.57415 | E20: =+C20*100000 -> 90428354 | F20: +RC[-2]*100000 | G20: +RC[-2]*100000
A21: b. Other current liabilities | B21: 7 | C21: =+'NOTE 4-8'!B28 -> 89.501951 | D21: =+'NOTE 4-8'!C28 -> 32.999611 | E21: =+C21*100000 -> 8950195.1 | F21: +RC[-2]*100000 | G21: +RC[-2]*100000 | K21: Regroupping Reconciliation
A22: c. Short term provisions | B22: 8 | C22: =+'NOTE 4-8'!B36 -> 67.553088 | D22: =+'NOTE 4-8'!C36 -> 204.8198 | E22: =+C22*100000 -> 6755308.8 | F22: +RC[-2]*100000 | G22: +RC[-2]*100000 | K22: Particulars | L22: Debit | M22: Credit | N22: Variance
C23: =SUM(C18:C22) -> 1061.3386 | D23: =SUM(D18:D22) -> 702.39356 | E23: =+C23*100000 -> 1.0613386e+08 | F23: +RC[-2]*100000 | G23: +RC[-2]*100000 | K23: As per Financials
E24: =+C24*100000 -> 0 | F24: +RC[-2]*100000 | G24: +RC[-2]*100000 | K24: TR | L24: 88995355 | M24: 0 | P24: 53379604 | Q24: 35615751 | R24: =+P24+Q24 -> 88995355 | S24: =+L24-R24 -> -0.001905784
A25: TOTAL | C25: =C13+C16+C23 -> 1409.527 | D25: =D13+D16+D23 -> 889.9046 | E25: =+C25*100000 -> 1.409527e+08 | F25: +RC[-2]*100000 | G25: +RC[-2]*100000 | K25: TP | L25: 0 | M25: 84505304 | P25: 46457415 | Q25: 38055623 | R25: =+P25+Q25 -> 84513038 | S25: =+M25-R25 -> -7734.002
E26: =+C26*100000 -> 0 | F26: +RC[-2]*100000 | G26: +RC[-2]*100000 | K26: AP/AR | L26: 0 | M26: =+'NOTE 4-8'!B34 -> 0.032858 | P26: 14467305 | Q26: 380165.39 | R26: =+P26+Q26 -> 14847471 | S26: =+M26-R26 -> -14847471
A27: II.ASSETS | E27: =+C27*100000 -> 0 | F27: +RC[-2]*100000 | G27: +RC[-2]*100000 | K27: Provision for Operation | L27: 0 | M27: =+'NOTE 4-8'!B33 -> 0
A28: NON-CURRENT ASSETS | E28: =+C28*100000 -> 0 | F28: +RC[-2]*100000 | G28: +RC[-2]*100000 | K28: Total | L28: =SUM(L24:L27) -> 88995355 | M28: =SUM(M24:M27) -> 84505304 | N28: =+L28-M28 -> 4490051
A29: a. Property, Plant & Equipment | B29: 9 | E29: =+C29*100000 -> 0 | F29: +RC[-2]*100000 | G29: +RC[-2]*100000 | K29: As per TB
A30: (i) Tangible assets | C30: =+'Note 9'!J20 -> 7.3320925 | D30: =+'Note 9'!K20 -> 9.1414207 | E30: =+C30*100000 -> 733209.25 | F30: +RC[-2]*100000 | G30: +RC[-2]*100000 | K30: TR | L30: =+'TB 24-25'!O20-'TB 24-25'!P21 -> 1002.3373 | M30: 0 | P30: 63707736 | Q30: 35615751 | R30: =+P30+Q30 -> 99323487 | S30: =+L30-R30 -> -99322485
C31: =SUM(C30:C30) -> 7.3320925 | D31: =SUM(D30:D30) -> 9.1414207 | E31: =+C31*100000 -> 733209.25 | F31: +RC[-2]*100000 | G31: +RC[-2]*100000 | K31: TP | L31: 0 | M31: =+SUM('TB 24-25'!P87:P90)-'TB 24-25'!O89 -> 1013.2276 | P31: 57351825 | Q31: 38055623 | R31: =+P31+Q31 -> 95407447 | S31: =+M31-R31 -> -95406434
E32: =+C32*100000 -> 0 | F32: +RC[-2]*100000 | G32: +RC[-2]*100000 | K32: AP/AR | L32: 0 | M32: =+'TB 24-25'!P58-'TB 24-25'!O65 -> 142.81192 | P32: 13901027 | Q32: 380165.39 | R32: =+P32+Q32 -> 14281192 | S32: =+M32-R32 -> -14281049
A33: b. Long-term loans and advances | B33: 10 | C33: =+'NOTE 10-14'!B12 -> 227.83878 | D33: =+'NOTE 10-14'!C12 -> 204.82732 | E33: =+C33*100000 -> 22783878 | F33: +RC[-2]*100000 | G33: +RC[-2]*100000 | K33: Provision for Operation | L33: 0 | M33: =+'TB 24-25'!P142 -> 0
A34: c. Deffered Tax Assets | B34: 11 | C34: =+'NOTE 10-14'!B18 -> 5.9743601 | D34: =+'NOTE 10-14'!C18 -> 6.349577 | E34: =+C34*100000 -> 597436.01 | F34: +RC[-2]*100000 | G34: +RC[-2]*100000 | K34: Total | L34: =SUM(L30:L33) -> 1002.3373 | M34: =SUM(M30:M33) -> 1156.0396 | N34: =+L34-M34 -> -153.70228
B35: 0 | C35: =+C33+C34 -> 233.81314 | D35: =D33+D34 -> 211.1769 | E35: =+C35*100000 -> 23381314 | F35: =+D35*100000 -> 21117690 | N35: =+N28-N34 -> 4490204.7
A36: CURRENT ASSETS | E36: =+C36*100000 -> 0 | F36: =+D36*100000 -> 0 | N36: =+N35*Deno -> 4.4902047e+11
A37: a. Trade receivables | B37: 12 | C37: =+'NOTE 12'!G18 -> 899.05595 | D37: =+'NOTE 12'!G30 -> 533.79604 | E37: =+C37*100000 -> 89905595 | F37: =+D37*100000 -> 53379604
A38: b. cash and cash equivalents | B38: 13 | C38: =+'NOTE 10-14'!B24+(1.99/Deno) -> 216.93546 | D38: =+'NOTE 10-14'!C24+(1.99/Deno) -> 61.175716 | E38: =+C38*100000 -> 21693546 | F38: =+D38*100000 -> 6117571.6
A39: c. Short-term loans and advances | B39: 14 | C39: =+'NOTE 10-14'!B31 -> 52.3904 | D39: =+'NOTE 10-14'!C31 -> 74.614539 | E39: =+C39*100000 -> 5239040 | F39: =+D39*100000 -> 7461453.9
C40: =SUM(C37:C39) -> 1168.3818 | D40: =SUM(D37:D39) -> 669.58629 | E40: =+C40*100000 -> 1.1683818e+08 | F40: =+D40*100000 -> 66958629
E41: =+C41*100000 -> 0 | F41: =+D41*100000 -> 0
A42: TOTAL | C42: =C31+C35+C40 -> 1409.527 | D42: =D31+D35+D40 -> 889.90461 | E42: =+C42*100000 -> 1.409527e+08 | F42: =+D42*100000 -> 88990461
E43: =+E42*Deno -> 1.409527e+13 | F43: =+F42*Deno -> 8.8990461e+12
A44: Significant Accounting Policies in Note 1 & 2
A45: The accompanying notes are integral part of the financial statements
A47: As per our report of even date | B47: For and on behalf of
A48: For Kalyanasundaram & Associates | B48: CARGO INTERNATIONAL (INDIA) PVT. LTD
A49: Chartered accountants
A50: FRN : 05455s
A52: SD/- | B52: SD/- | D52: SD/-
A54: K M Sethu | B54: Suresh Padmanabhan | D54: Vignesh Natarajan
A55: Partner | B55: Director | D55: Director
A56: M.No.231703 | B56: DIN: 08284074 | D56: DIN: 08284068
A57: Place : Chennai | B57: Place : Birmingham | D57: Place : Chennai
A58: Date : | B58: Date: | D58: Date:
A59: UDIN :

Sheet PL
A1: CARGO INTERNATIONAL (INDIA) PRIVATE LIMITED
A2: STATEMENT OF PROFIT AND LOSS FOR YEAR ENDED 31ST MARCH, 2025
A3: CIN: U63000TN2010PTC077296
A4: =+BS!A4 -> Old No.7 / New No.13, First Floor, First Cross Street, Trustpuram, Kodambakkam, Chennai - 600024, India
A5: =+"(Unless otherwise specified, all amounts are "&IF('Master data'!A2="Ones","Indian Rupees","in "&'Master data'!A2&" of INR)") -> (Unless otherwise specified, all amounts are in Lakhs of INR)
A6: Particulars | C6: Note | D6: For Year Ended | E6: For Year Ended
D7: 45747 | E7: 45382
A9: I | B9: Revenue from Operation | C9: 15 | D9: ='NOTE 15-20'!B14 -> 2510.5688 | E9: ='NOTE 15-20'!C14 -> 1484.7668 | F9: =+D9*100000 -> 2.5105688e+08 | G9: =+E9*100000 -> 1.4847668e+08
A10: II | B10: Other Income | C10: 16 | D10: ='NOTE 15-20'!B20 -> 62.750698 | E10: ='NOTE 15-20'!C20 -> 46.56197 | F10: =+D10*100000 -> 6275069.8 | G10: =+E10*100000 -> 4656197
F11: =+D11*100000 -> 0
A12: III | B12: TOTAL | D12: =SUM(D9:D11) -> 2573.3195 | E12: =SUM(E9:E11) -> 1531.3288 | F12: =+D12*100000 -> 2.5733195e+08 | G12: =+E12*100000 -> 1.5313288e+08
F13: =+D13*100000 -> 0 | G13: =+E13*100000 -> 0
A14: IV | B14: EXPENSES | F14: =+D14*100000 -> 0 | G14: =+E14*100000 -> 0
B15: Operating expenses | C15: 17 | D15: ='NOTE 15-20'!B28 -> 2153.6675 | E15: ='NOTE 15-20'!C28 -> 1216.7373 | F15: =+D15*100000 -> 2.1536675e+08 | G15: =+E15*100000 -> 1.2167373e+08
B16: Employee Benefit Expenses | C16: 18 | D16: ='NOTE 15-20'!B34 -> 230.47531 | E16: ='NOTE 15-20'!C34 -> 220.628 | F16: =+D16*100000 -> 23047531 | G16: =+E16*100000 -> 22062800
B17: Finance cost | C17: 19 | D17: =+'NOTE 15-20'!B41 -> 2.664397 | E17: =+'NOTE 15-20'!C41 -> 1.879493 | F17: =+D17*100000 -> 266439.7 | G17: =+E17*100000 -> 187949.3
B18: Administrative expenses | C18: 20 | D18: ='NOTE 15-20'!B57 -> 157.28139 | E18: ='NOTE 15-20'!C57 -> 138.65936 | F18: =+D18*100000 -> 15728139 | G18: =+E18*100000 -> 13865936
B19: Depreciation | C19: 9 | D19: =+'Note 9'!G20 -> 2.6989893 | E19: =+'Note 9'!G22 -> 3.3532017 | F19: =+D19*100000 -> 269898.93 | G19: =+E19*100000 -> 335320.17
F20: =+D20*100000 -> 0 | G20: =+E20*100000 -> 0
A21: V | B21: TOTAL | D21: =SUM(D15:D20) -> 2546.7876 | E21: =SUM(E15:E20) -> 1581.2573 | F21: =+D21*100000 -> 2.5467876e+08 | G21: =+E21*100000 -> 1.5812573e+08
F22: =+D22*100000 -> 0 | G22: =+E22*100000 -> 0
A23: VI | B23: Profit before exceptional and extraordinary item and tax (III - V) | D23: =D12-D21 -> 26.531903 | E23: =E12-E21 -> -49.928502 | F23: =+D23*100000 -> 2653190.3 | G23: =+E23*100000 -> -4992850.2
F24: =+D24*100000 -> 0 | G24: =+E24*100000 -> 0
A25: VII | B25: Exceptional items/extra-ordinary items | D25: 0 | E25: 0 | F25: =+D25*100000 -> 0 | G25: =+E25*100000 -> 0
F26: =+D26*100000 -> 0 | G26: =+E26*100000 -> 0
A27: VIII | B27: Profit before extra-ordinary item and tax (VI - VII) | D27: =D23-D25 -> 26.531903 | E27: =E23-E25 -> -49.928502 | F27: =+D27*100000 -> 2653190.3 | G27: =+E27*100000 -> -4992850.2
F28: =+D28*100000 -> 0 | G28: =+E28*100000 -> 0
A29: IX | B29: Profit before tax (VIII) | D29: =D27 -> 26.531903 | E29: =E27 -> -49.928502 | F29: =+D29*100000 -> 2653190.3 | G29: =+E29*100000 -> -4992850.2
A30: X | B30: Tax expenses | F30: =+D30*100000 -> 0 | G30: =+E30*100000 -> 0
B31: (1) Current Tax | D31: =+'Audit entry'!D148/Deno -> 6.5476249 | E31: 0 | F31: =+D31*100000 -> 654762.49 | G31: =+E31*100000 -> 0
B32: (2) Deferred Tax | D32: =-'Audit entry'!D31 -> -0.37521685 | E32: =-28240.312/Deno -> -0.28240312 | F32: =+D32*100000 -> -37521.685 | G32: =+E32*100000 -> -28240.312
B33: Prior period items | F33: =+D33*100000 -> 0 | G33: =+E33*100000 -> 0
A34: XI | B34: Profit/(Loss) for the period from continuing operation (IX-X) | D34: =D29-D31+D32+D33 -> 19.609062 | E34: =E29-E31+E32+E33 -> -50.210905 | F34: =+D34*100000 -> 1960906.2 | G34: =+E34*100000 -> -5021090.5
A36: XII | B36: EPS
B37: Basic | D37: =+(D34/'NOTE 3'!D40)*Deno -> 98.045308 | E37: =+(E34/'NOTE 3'!D30)*Deno -> -251.07963
B38: Diluted | D38: =+D37 -> 98.045308 | E38: =+E37 -> -251.07963
A40: =BS!A44 -> Significant Accounting Policies in Note 1 & 2
A41: The accompanying notes are integral part of the financial statements
A43: As per our report of even date | C43: For and on behalf of
A44: For Kalyanasundaram & Associates | C44: =+BS!B48 -> CARGO INTERNATIONAL (INDIA) PVT. LTD
A45: Chartered accountants
A46: FRN : 005455S
A50: K M Sethu | C50: =+BS!B54 -> Suresh Padmanabhan | E50: =+BS!D54 -> Vignesh Natarajan
A51: Partner | C51: =+BS!B55 -> Director | E51: =+BS!D55 -> Director
A52: M.No.231703 | C52: =+BS!B56 -> DIN: 08284074 | E52: =+BS!D56 -> DIN: 08284068
A53: Place : Chennai | C53: =+BS!B57 -> Place : Birmingham | E53: =+BS!D57 -> Place : Chennai
A54: =+BS!A58 -> Date : | C54: =+BS!B58 -> Date: | E54: =+BS!D58 -> Date:
A55: =+BS!A59 -> UDIN :

Sheet CFS
A1: =+PL!A1 -> CARGO INTERNATIONAL (INDIA) PRIVATE LIMITED
A2: CASH FLOW STATEMENT FOR THE YEAR ENDED ON 31ST MARCH 2025
A3: CIN: U63000TN2010PTC077296
A4: =+PL!A4 -> Old No.7 / New No.13, First Floor, First Cross Street, Trustpuram, Kodambakkam, Chennai - 600024, India
A5: =+"(Unless otherwise specified, all amounts are "&IF('Master data'!A2="Ones","Indian Rupees","in "&'Master data'!A2&" of INR)") -> (Unless otherwise specified, all amounts are in Lakhs of INR)
A6: Particulars | C6: For Year Ended | D6: For Year Ended
C7: 45747 | D7: 45382
A9: [A] Cash Flow from Operating Activities:
A11: Profit before Tax | C11: =+PL!D27 -> 26.531903 | D11: =+PL!E27 -> -49.928502 | E11: =+C11*100000 -> 2653190.3 | F11: =+D11*100000 -> -4992850.2
A12: Adjustments for non cash items & Non operating activity: | E12: =+C12*100000 -> 0 | F12: =+D12*100000 -> 0
A13: Depreciation | C13: =+PL!D19 -> 2.6989893 | D13: =+PL!E19 -> 3.3532017 | E13: =+C13*100000 -> 269898.93 | F13: =+D13*100000 -> 335320.17
A14: GST Input reversal | C14: =+'NOTE 4-8'!B12 -> 0 | D14: =-14902244.9/Deno -> -149.02245 | E14: =+C14*100000 -> 0 | F14: =+D14*100000 -> -14902245
A15: Provision Operation reversal | C15: =+'NOTE 4-8'!B13 -> 141.06836 | E15: =+C15*100000 -> 14106836 | F15: =+D15*100000 -> 0
A16: Interest & Finance Charges | C16: =+PL!D17 -> 2.664397 | D16: =+PL!E17 -> 1.879493 | E16: =+C16*100000 -> 266439.7 | F16: =+D16*100000 -> 187949.3
A17: Operating Profit before Working Capital changes | C17: =SUM(C11:C16) -> 172.96365 | D17: =SUM(D11:D16) -> -193.71826 | E17: =+C17*100000 -> 17296365 | F17: =+D17*100000 -> -19371826
E18: =+C18*100000 -> 0 | F18: =+D18*100000 -> 0
A19: Adjusted for : | E19: =+C19*100000 -> 0 | F19: =+D19*100000 -> 0
A20: (Increase)/Decrease in Loans & Advances | C20: =-BS!C39+BS!D39 -> 22.224139 | D20: =11919207.85/Deno -> 119.19208 | E20: =+C20*100000 -> 2222413.9 | F20: =+D20*100000 -> 11919208
A21: (Increase)/Decrease in Sundry Debtors | C21: =-BS!C37+BS!D37 -> -365.25991 | D21: =-2879939.29/Deno -> -28.799393 | E21: =+C21*100000 -> -36525991 | F21: =+D21*100000 -> -2879939.3
A22: Increase/(Decrease) in Current liabilities | C22: =+BS!C23-BS!D23 -> 358.94501 | D22: =12411981.16/Deno -> 124.11981 | E22: =+C22*100000 -> 35894501 | F22: =+D22*100000 -> 12411981
E23: =+C23*100000 -> 0 | F23: =+D23*100000 -> 0
A24: Current year Tax: | C24: =-PL!D31 -> -6.5476249 | D24: =-PL!E31 -> 0 | E24: =+C24*100000 -> -654762.49 | F24: =+D24*100000 -> 0
E25: =+C25*100000 -> 0 | F25: =+D25*100000 -> 0
A26: Net Cash from Operating Activities | C26: =SUM(C17:C24) -> 182.32527 | D26: =SUM(D17:D24) -> 20.794241 | E26: =+C26*100000 -> 18232527 | F26: =+D26*100000 -> 2079424.1
E27: =+C27*100000 -> 0 | F27: =+D27*100000 -> 0
A28: [B] Cash flow from Investing Activities | E28: =+C28*100000 -> 0 | F28: =+D28*100000 -> 0
A29: Additions to fixed assets | C29: =-'Note 9'!C20+'Note 9'!D20 -> -0.8896611 | D29: =-56567.79/Deno -> -0.5656779 | E29: =+C29*100000 -> -88966.11 | F29: =+D29*100000 -> -56567.79
A30: Increase in Long term loans and advances | C30: =-BS!C33+BS!D33 -> -23.011459 | D30: =-2434939.76/Deno -> -24.349398 | E30: =+C30*100000 -> -2301145.9 | F30: =+D30*100000 -> -2434939.8
A31: Net cash from/(used in) investing activities | C31: =SUM(C29:C30) -> -23.90112 | D31: =SUM(D29:D30) -> -24.915075 | E31: =+C31*100000 -> -2390112 | F31: =+D31*100000 -> -2491507.5
E32: =+C32*100000 -> 0 | F32: =+D32*100000 -> 0
A33: [C] Cash flow from Financing Activities | E33: =+C33*100000 -> 0 | F33: =+D33*100000 -> 0
A34: Interest & Finance Charges | C34: =-C16 -> -2.664397 | D34: =-D16 -> -1.879493 | E34: =+C34*100000 -> -266439.7 | F34: =+D34*100000 -> -187949.3
E35: =+C35*100000 -> 0 | F35: =+D35*100000 -> 0
A36: Net cash from/(used in) Financing activities | C36: =SUM(C34:C35) -> -2.664397 | D36: =SUM(D34:D35) -> -1.879493 | E36: =+C36*100000 -> -266439.7 | F36: =+D36*100000 -> -187949.3
E37: =+C37*100000 -> 0 | F37: =+D37*100000 -> 0
A38: Net Cash flow during the year [A + B + C] | C38: =C26+C31+C36 -> 155.75975 | D38: =D26+D31+D36 -> -6.0003275 | E38: =+C38*100000 -> 15575975 | F38: =+D38*100000 -> -600032.75
E39: =+C39*100000 -> 0 | F39: =+D39*100000 -> 0
A40: Cash & Cash equivalents (Opening Balance) | C40: =+D41 -> 61.175716 | D40: =6717604.32/Deno -> 67.176043 | E40: =+C40*100000 -> 6117571.6 | F40: =+D40*100000 -> 6717604.3
A41: Cash & Cash equivalents (Closing Balance) | C41: =+BS!C38 -> 216.93546 | D41: =+BS!D38 -> 61.175716 | E41: =+C41*100000 -> 21693546 | F41: =+D41*100000 -> 6117571.6
E42: =+C42*100000 -> 0 | F42: =+D42*100000 -> 0
A43: Net Cash flow during the year | C43: =C41-C40 -> 155.75975 | D43: =D41-D40 -> -6.0003276 | E43: =+C43*100000 -> 15575975 | F43: =+D43*100000 -> -600032.76
A45: Significant Accounting Policies in Note 1 & 2 | E45: =+E43*Deno -> 1.5575975e+12 | F45: =+F43*Deno -> -6.0003276e+10
A46: The accompanying notes are integral part of the financial statements
A48: As per our report of even date | B48: For and on behalf of
A49: For Kalyanasundaram & Associates | B49: =+PL!C44 -> CARGO INTERNATIONAL (INDIA) PVT. LTD
A50: Chartered accountants
A51: FRN : 05455s
A55: K M Sethu | B55: =+PL!C50 -> Suresh Padmanabhan | D55: =+PL!E50 -> Vignesh Natarajan
A56: Partner | B56: Director | D56: =+PL!E51 -> Director
A57: M.No.231703 | B57: =+PL!C52 -> DIN: 08284074 | D57: =+PL!E52 -> DIN: 08284068
A58: Place : Chennai | B58: =+PL!C53 -> Place : Birmingham | D58: =+PL!E53 -> Place : Chennai
A59: =+PL!A54 -> Date : | B59: =+PL!C54 -> Date: | D59: =+PL!E54 -> Date:
A60: =+PL!A55 -> UDIN :

Sheet Note 1-2
A1: CARGO INTERNATIONAL (INDIA) PRIVATE LIMITED
A2: NOTES TO THE FINANCIAL STATEMENTS FOR THE YEAR ENDED 31st MARCH, 2025
A3: CAPITAL TOWERS, NO.G-3/1, G-3/2 & G-2 DOOR NO.180 KODAMBAKKAM HIGH ROAD, NUNGAMBAKKAM CHENNAI 600034
A5: NOTE 1: GENERAL INFORMATION
A6: CARGO INTERNATIONAL (INDIA) PVT LTD is a Private Limited Company incorporated under the provisions of Companies Act 2013. The company is providing clearing and Forwarding services. The company is providing clearing & forwarding Transport Services to their clients through Air, Road and Sea Transport
A8: NOTE 2: SIGNIFICANT ACCOUNTING POLICIES
A9: 2.1) Basis of preparation of Financial statements:
A10: All financial transactions have been recognized on accrual basis in accordance of companies Act 2013 and Accounting Standards as adopted consistently by the company. The preparation of financial statements in conformity with the GAAP requires that the management makes estimates and assumptions that affect the reported amounts of assets and liabilities, disclosure of contingent liabilities as at the date of the financial statements and the reported amounts of revenue and expenses during the period.
A12: 2.2) Use of Estimates
A13: The preparation of financial statements requires management to make estimates and assumptions that affect the reported amount of asset and liabilities, the disclosure of contingent assets and liabilities on the date of financial statements and the reported amount of revenue and expenses during the period reported. Actual result could differ from those estimates.
A15: 2.3) Property, Plant and Equipment
A16: Property, Plant and Equipment has been accounted at their cost including all expenses such as transportation charges, installation expenses etc., incurred wholly and exclusively for the purpose of putting the assets into the use.
... A40: Contingent Assets are neither disclosed nor provided for in the financial statements.

Sheet NOTE 3
A1: CARGO INTERNATIONAL (INDIA) PRIVATE LIMITED
A2: NOTES TO THE FINANCIAL STATEMENTS FOR THE YEAR ENDED 31st MARCH, 2025
A3: =+CFS!A4 -> Old No.7 / New No.13, First Floor, First Cross Street, Trustpuram, Kodambakkam, Chennai - 600024, India
E4: =+"(Unless otherwise specified, all amounts are "&IF('Master data'!A2="Ones","Indian Rupees","in "&'Master data'!A2&" of INR)") -> (Unless otherwise specified, all amounts are in Lakhs of INR)
A5: =+'NOTE 4-8'!A5 -> Particulars | D5: As on | E5: As on
D6: 31st March, 2025 | E6: 31st March, 2024
A7: NOTE 3 : SHARE CAPITAL
A8: Authorised share capital
A9: Equity Share Capital | D9: =5000000/Deno -> 50 | E9: =5000000/Deno -> 50 | F9: =+D9*100000 -> 5000000 | G9: =+E9*100000 -> 5000000
A10: (500,000 equity shares of Rs.10 each) | F10: =+D10*100000 -> 0 | G10: =+E10*100000 -> 0
D11: =D9 -> 50 | E11: =E9 -> 50 | F11: =+D11*100000 -> 5000000 | G11: =+E11*100000 -> 5000000
A12: Issued, subscribed and paid up capital | F12: =+D12*100000 -> 0 | G12: =+E12*100000 -> 0
A13: Equity Share Capital | D13: =200000/Deno -> 2 | E13: =200000/Deno -> 2 | F13: =+D13*100000 -> 200000 | G13: =+E13*100000 -> 200000
A14: (20,000 equity shares of Rs.10 each) | F14: =+D14*100000 -> 0 | G14: =+E14*100000 -> 0
D15: =SUM(D12:D13) -> 2 | E15: =SUM(E12:E13) -> 2 | F15: =+D15*100000 -> 200000 | G15: =+E15*100000 -> 200000
A17: A. Terms and Rights attached to equity shares
A18: The company has only one class of equity shares having a par value of Rs. 10 per share. Each holder of equity share entitled to one vote per share. The company declares and pays dividend in Indian Rupees The dividend proposed by the Board of directors is subject o the approval of the shareholders in the ensuring Annual General Meeting.
A20: During the year ended 31st March 2025, the amount per share dividend recognised as distrubition to shareholders was Rs. NIL (31st march 2024 - NIL)
A23: B. Shareholders holding more than 5 percent of equity shares
A24: Name of the Shareholder | B24: =+D6 -> 31st March, 2025 | D24: =+E6 -> 31st March, 2024
B25: No. Of Shares | C25: % holding | D25: No. Of Shares | E25: % holding
A26: Suresh Padmanabhan | B26: 15998 | C26: =+B26/$B$30 -> 0.79998 | D26: 15998 | E26: =+D26/$B$30 -> 0.79998 | G26: =+D26/20000 -> 0.7999
A27: Ramkumar | B27: 2000 | C27: =+B27/$B$30 -> 0.10001 | D27: 2000 | E27: =+D27/$B$30 -> 0.10001
A28: Prasath | B28: 2000 | C28: =+B28/$B$30 -> 0.10001 | D28: 2000 | E28: =+D28/$B$30 -> 0.10001
A30: Total | B30: =SUM(B26:B29) -> 19998 | C30: =SUM(C26:C29) -> 1 | D30: =SUM(D26:D29) -> 19998 | E30: =SUM(E26:E29) -> 1
A33: C. Reconciliation of shares outstanding at the beginning and at the end of the reporting period.
A35: Particulars | B35: =+B24 -> 31st March, 2025 | D35: =+D24 -> 31st March, 2024
B36: No. Of Shares | C36: Amount | D36: No. Of Shares | E36: Amount
A37: Shares outstanding at the beginning of the year | B37: 20000 | C37: =+B37*10 -> 200000 | D37: 20000 | E37: =+D37*10 -> 200000
A38: Shares issued during the year | B38: 0 | C38: 0 | D38: 0 | E38: =+D38*10 -> 0
A39: Shares bought back during the year | B39: 0 | C39: =+B39*10 -> 0 | D39: 0 | E39: =+D39*10 -> 0
A40: Shares outstanding at the end of the year | B40: =SUM(B37:B39) -> 20000 | C40: =SUM(C37:C39) -> 200000 | D40: =SUM(D37:D39) -> 20000 | E40: =SUM(E37:E39) -> 200000
A43: D. Shares held by promoters at the end of the year
A44: Shares held by promoters at the end of the year 31st March 2025
A45: Name of the Promoter | B45: No. Of Shares | C45: Amount (Rs.) | D45: % of Total shares | E45: % Change during the year 2024
A46: Suresh Padmanabhan | B46: 15998 | C46: =+B46*10 -> 159980 | D46: =+B46/$B$50 -> 0.79998 | E46: =+(C55-C46)/C46 -> 0
A47: Ramkumar | B47: 2000 | C47: =+B47*10 -> 20000 | D47: =+B47/$B$50 -> 0.10001 | E47: =+(C56-C47)/C47 -> 0
A48: Prasath | B48: 2000 | C48: =+B48*10 -> 20000 | D48: =+B48/$B$50 -> 0.10001 | E48: =+(C57-C48)/C48 -> 0
A50: Total | B50: =SUM(B46:B48) -> 19998 | C50: =SUM(C46:C48) -> 199980 | D50: =SUM(D46:D48) -> 1
A53: Shares held by promoters at the end of the year 31st March 2024
A54: Name of the Promoter | B54: No. Of Shares | C54: Amount (Rs.) | D54: % of Total shares | E54: % Change during the year 2023
A55: Suresh Padmanabhan | B55: 15998 | C55: =+B55*10 -> 159980 | D55: =+B55/$B$50 -> 0.79998 | E55: 0
A56: Ramkumar | B56: 2000 | C56: =+B56*10 -> 20000 | D56: =+B56/$B$59 -> 0.10001 | E56: 0
A57: Prasath | B57: 2000 | C57: =+B57*10 -> 20000 | D57: =+B57/$B$59 -> 0.10001 | E57: 0
A59: Total | B59: =SUM(B55:B58) -> 19998 | C59: =SUM(C55:C58) -> 199980 | D59: =SUM(D55:D58) -> 1

Sheet NOTE 4-8
A1: =BS!A1 -> CARGO INTERNATIONAL (INDIA) PRIVATE LIMITED
A2: NOTES TO THE FINANCIAL STATEMENTS FOR THE YEAR ENDED 31st MARCH, 2025
A3: CAPITAL TOWERS, NO.G-3/1, G-3/2 & G-2 ,DOOR NO.180 KODAMBAKKAM HIGH ROAD, NUNGAMBAKKAM, CHENNAI - 600034
C4: =+"(Unless otherwise specified, all amounts are "&IF('Master data'!A2="Ones","Indian Rupees","in "&'Master data'!A2&" of INR)") -> (Unless otherwise specified, all amounts are in Lakhs of INR)
A5: Particulars | B5: As on | C5: As on
B6: 31st March, 2025 | C6: 31st March, 2024
A8: NOTE 4 : RESERVES AND SURPLUS
A9: General Reserve
A10: Opening balance | B10: =+C15 -> 37.069193 | C10: =23630254.6984153/Deno -> 236.30255 | E10: =+B10*100000 -> 3706919.3 | F10: =+C10*100000 -> 23630255
A11: Add:Net Profit/(Loss) for the current year | B11: =PL!D34 -> 19.609062 | C11: =PL!E34 -> -50.210905 | E11: =+B11*100000 -> 1960906.2 | F11: =+C11*100000 -> -5021090.5
A12: Less: GST Input reversal | B12: 0 | C12: =-14902244.9/Deno -> -149.02245 | E12: =+B12*100000 -> 0 | F12: =+C12*100000 -> -14902245
A13: Add: Provision operation reversal | B13: =+'Audit entry'!E127/Deno -> 141.06836 | E13: =+B13*100000 -> 14106836 | F13: =+C13*100000 -> 0
A14: (Refer Note. 21(9)) | E14: =+B14*100000 -> 0 | F14: =+C14*100000 -> 0
B15: =SUM(B10:B14) -> 197.74662 | C15: =SUM(C10:C14) -> 37.069193 | E15: =+B15*100000 -> 19774662 | F15: =+C15*100000 -> 3706919.3
E16: =+B16*100000 -> 0 | F16: =+C16*100000 -> 0
A17: NOTE 5 : NON CURRENT LIABILITIES | E17: =+B17*100000 -> 0 | F17: =+C17*100000 -> 0
A18: Other Long term Liabilities | B18: =(SUMIF('Sub-Schedule'!F4:F32,"RPT",'Sub-Schedule'!C4:C32)-SUMIF('Sub-Schedule'!F4:F32,"RPT",'Sub-Schedule'!B4:B32))/(+Deno) -> 148.44185 | C18: =(SUMIF('Sub-Schedule'!F4:F32,"RPT",'Sub-Schedule'!E4:E32)-SUMIF('Sub-Schedule'!F4:F32,"RPT",'Sub-Schedule'!D4:D32))/(+Deno) -> 148.44185 | E18: =+B18*100000 -> 14844185 | F18: =+C18*100000 -> 14844185
E19: =+B19*100000 -> 0 | F19: =+C19*100000 -> 0
B20: =SUM(B18:B19) -> 148.44185 | C20: =SUM(C18:C19) -> 148.44185 | E20: =+B20*100000 -> 14844185 | F20: =+C20*100000 -> 14844185
E21: =+B21*100000 -> 0 | F21: =+C21*100000 -> 0
E22: =+B22*100000 -> 0 | F22: =+C22*100000 -> 0
A23: NOTE 7 : OTHER CURRENT LIABILITIES | E23: =+B23*100000 -> 0 | F23: =+C23*100000 -> 0
A24: Expense payable | B24: =(+'Sub Sch - BS'!B12) -> 37.309243 | C24: =(+'Sub Sch - BS'!C12) -> 13.188326 | E24: =+B24*100000 -> 3730924.3 | F24: =+C24*100000 -> 1318832.6
A25: Other Liabilities | B25: =(SUMIF('TB 24-25'!$Q:$Q,$A25,'TB 24-25'!$P:$P)-SUMIF('TB 24-25'!$Q:$Q,$A25,'TB 24-25'!$O:$O)) -> 7.9754498 | C25: =(SUMIF('TB 24-25'!$Q:$Q,$A25,'TB 24-25'!$F:$F)-SUMIF('TB 24-25'!$Q:$Q,$A25,'TB 24-25'!$E:$E)) -> 0 | E25: =+B25*100000 -> 797544.98 | F25: =+C25*100000 -> 0
A26: Statutory Dues payables | B26: =(+'Sub Sch - BS'!B25) -> 44.217258 | C26: =(+'Sub Sch - BS'!C25) -> 19.811285 | E26: =+B26*100000 -> 4421725.8 | F26: =+C26*100000 -> 1981128.5
E27: =+B27*100000 -> 0 | F27: =+C27*100000 -> 0
B28: =SUM(B24:B27) -> 89.501951 | C28: =SUM(C24:C27) -> 32.999611 | E28: =+B28*100000 -> 8950195.1 | F28: =+C28*100000 -> 3299961.1
E29: =+B29*100000 -> 0 | F29: =+C29*100000 -> 0
A30: NOTE 8 : SHORT TERM PROVISIONS | E30: =+B30*100000 -> 0 | F30: =+C30*100000 -> 0
A31: Provision for income tax | B31: =(SUMIF('TB 24-25'!$Q:$Q,$A31,'TB 24-25'!$P:$P)-SUMIF('TB 24-25'!$Q:$Q,$A31,'TB 24-25'!$O:$O)) -> 67.52023 | C31: =(SUMIF('TB 24-25'!$Q:$Q,$A31,'TB 24-25'!$F:$F)-SUMIF('TB 24-25'!$Q:$Q,$A31,'TB 24-25'!$E:$E)) -> 67.52023 | E31: =+B31*100000 -> 6752023 | F31: =+C31*100000 -> 6752023
A32: Provisions non business | B32: =(SUMIF('TB 24-25'!$Q:$Q,$A32,'TB 24-25'!$P:$P)-SUMIF('TB 24-25'!$Q:$Q,$A32,'TB 24-25'!$O:$O)) -> 0 | C32: =(SUMIF('TB 24-25'!$Q:$Q,$A32,'TB 24-25'!$F:$F)-SUMIF('TB 24-25'!$Q:$Q,$A32,'TB 24-25'!$E:$E)) -> 0 | E32: =+B32*100000 -> 0 | F32: =+C32*100000 -> 0
A33: Provisions operations | B33: =(SUMIF('TB 24-25'!$Q:$Q,$A33,'TB 24-25'!$P:$P)-SUMIF('TB 24-25'!$Q:$Q,$A33,'TB 24-25'!$O:$O)) -> 0 | C33: =(SUMIF('TB 24-25'!$Q:$Q,$A33,'TB 24-25'!$F:$F)-SUMIF('TB 24-25'!$Q:$Q,$A33,'TB 24-25'!$E:$E)) -> 141.06836 | D33: CY tax included | E33: =+B33*100000 -> 0 | F33: =+C33*100000 -> 14106836
A34: Advance paid \ received | B34: =(SUMIF('Sub-Schedule'!F4:F32,"others",'Sub-Schedule'!C4:C32)-SUMIF('Sub-Schedule'!F4:F32,"others",'Sub-Schedule'!B4:B32))/(+Deno) -> 0.032858 | C34: =(SUMIF('Sub-Schedule'!F4:F32,"Others",'Sub-Schedule'!E4:E32)-SUMIF('Sub-Schedule'!F4:F32,"Others",'Sub-Schedule'!D4:D32))/(+Deno) -> -3.7687959 | E34: =+B34*100000 -> 3285.8 | F34: =+C34*100000 -> -376879.59
E35: =+B35*100000 -> 0 | F35: =+C35*100000 -> 0
B36: =SUM(B31:B35) -> 67.553088 | C36: =SUM(C31:C35) -> 204.8198 | E36: =+B36*100000 -> 6755308.8 | F36: =+C36*100000 -> 20481980

Sheet NOTE 6
A1: =BS!A1 -> CARGO INTERNATIONAL (INDIA) PRIVATE LIMITED
A2: NOTES TO THE FINANCIAL STATEMENTS FOR THE YEAR ENDED 31st MARCH, 2025
A3: CAPITAL TOWERS, NO.G-3/1, G-3/2 & G-2 ,DOOR NO.180 KODAMBAKKAM HIGH ROAD, NUNGAMBAKKAM, CHENNAI - 600034
A5: NOTE 6 : TRADE PAYABLES
A6: Sundry creditors
G7: =+"(Unless otherwise specified, all amounts are "&IF('Master data'!A2="Ones","Indian Rupees","in "&'Master data'!A2&" of INR)") -> (Unless otherwise specified, all amounts are in Lakhs of INR)
A8: Particulars | B8: As on Mar 31,2025
B9: Outstanding for following periods from due date of payment
B10: Less than 6 months | C10: 6 months to 1 year | D10: 1 - 2 years | E10: 2 - 3 years | F10: more than 3 years | G10: TOTAL
A12: MSME | B12: =0/(+Deno) -> 0 | C12: =0/(+Deno) -> 0 | D12: =0/(+Deno) -> 0 | E12: =0/(+Deno) -> 0 | F12: =0/(+Deno) -> 0 | G12: 0
A13: Others | B13: =0/(+Deno) -> 0 | C13: =87765031.46/Deno -> 877.65031 | D13: =1246926.2/(+Deno) -> 12.469262 | E13: =431714.91/(+Deno) -> 4.3171491 | F13: =984680.99/(+Deno) -> 9.8468099 | G13: =+SUM(B13:F13) -> 904.28354
A14: Disputed Dues (MSME) | B14: =0/(+Deno) -> 0 | C14: =0/(+Deno) -> 0 | D14: =0/(+Deno) -> 0 | E14: =0/(+Deno) -> 0 | F14: =0/(+Deno) -> 0 | G14: 0
A15: Disputed Dues (Others) | B15: =0/(+Deno) -> 0 | C15: =0/(+Deno) -> 0 | D15: =0/(+Deno) -> 0 | E15: =0/(+Deno) -> 0 | F15: =0/(+Deno) -> 0 | G15: 0
A17: TOTAL | B17: =SUM(B12:B16) -> 0 | C17: =SUM(C12:C16) -> 877.65031 | D17: =SUM(D12:D16) -> 12.469262 | E17: =SUM(E12:E16) -> 4.3171491 | F17: =SUM(F12:F16) -> 9.8468099 | G17: =SUM(G12:G16) -> 904.28354 | H17: =+C17*100000 -> 87765031 | I17: =+D17*100000 -> 1246926.2 | J17: =+E17*100000 -> 431714.91 | K17: =+F17*100000 -> 984680.99 | L17: =+G17*100000 -> 90428354
A20: Particulars | B20: As on Mar 31, 2024
B21: Outstanding for following periods from due date of payment
B22: Less than 6 months | C22: 6 months to 1 year | D22: 1 - 2 years | E22: 2 - 3 years | F22: more than 3 years | G22: TOTAL
A24: MSME | B24: =0/(+Deno) -> 0 | C24: =0/(+Deno) -> 0 | D24: =0/(+Deno) -> 0 | E24: =0/(+Deno) -> 0 | F24: =0/(+Deno) -> 0 | G24: =+SUM(B24:F24) -> 0
A25: Others | B25: 0 | C25: =26149952.35/Deno -> 261.49952 | D25: =5125281.95/Deno -> 51.25282 | E25: =5986824.57/Deno -> 59.868246 | F25: =9195356.38/Deno -> 91.953564 | G25: =+SUM(B25:F25) -> 464.57415
A26: Disputed Dues (MSME) | B26: =0/(+Deno) -> 0 | C26: =0/(+Deno) -> 0 | D26: =0/(+Deno) -> 0 | E26: =0/(+Deno) -> 0 | F26: =0/(+Deno) -> 0 | G26: =+SUM(B26:F26) -> 0
A27: Disputed Dues (Others) | B27: =0/(+Deno) -> 0 | C27: =0/(+Deno) -> 0 | D27: =0/(+Deno) -> 0 | E27: =0/(+Deno) -> 0 | F27: =0/(+Deno) -> 0 | G27: =+SUM(B27:F27) -> 0
A29: TOTAL | B29: =SUM(B24:B28) -> 0 | C29: =SUM(C24:C28) -> 261.49952 | D29: =SUM(D24:D28) -> 51.25282 | E29: =SUM(E24:E28) -> 59.868246 | F29: =SUM(F24:F28) -> 91.953564 | G29: =SUM(G24:G28) -> 464.57415 | H29: =+C29*100000 -> 26149952 | I29: =+D29*100000 -> 5125282 | J29: =+E29*100000 -> 5986824.6 | K29: =+F29*100000 -> 9195356.4 | L29: =+G29*100000 -> 46457415
B33: Note : Amount is derived from TP reconcilation from Ageing folder
C35: =+Deno -> 100000

Sheet Note 9
A1: CARGO INTERNATIONAL (INDIA) PRIVATE LIMITED
A2: =+'NOTE 4-8'!A2:C2 -> NOTES TO THE FINANCIAL STATEMENTS FOR THE YEAR ENDED 31st MARCH, 2025
A3: =+'NOTE 4-8'!A3:C3 -> CAPITAL TOWERS, NO.G-3/1, G-3/2 & G-2 ,DOOR NO.180 KODAMBAKKAM HIGH ROAD, NUNGAMBAKKAM, CHENNAI - 600034
A5: Note 9 - Property, Plant & Equipment
K6: =+"(Unless otherwise specified, all amounts are "&IF('Master data'!A2="Ones","Indian Rupees","in "&'Master data'!A2&" of INR)") -> (Unless otherwise specified, all amounts are in Lakhs of INR)
A7: Asset Category | B7: Gross Block | F7: Depreciation | J7: Net Block
B8: As on 01.04.2024 | C8: Additions | D8: Deletion | E8: As on 31.03.2025 | F8: =+B8 -> As on 01.04.2024 | G8: For the Year | H8: Deletion | I8: =+E8 -> As on 31.03.2025 | J8: =+I8 -> As on 31.03.2025 | K8: =+B8 -> As on 01.04.2024
A11: Tangible Assets
A12: Motor Car | B12: =0/(Deno) -> 0 | C12: 0 | D12: =(0/(+Deno))/(Deno) -> 0 | E12: =B12+C12-D12 -> 0 | F12: =0/(Deno) -> 0 | G12: 0 | H12: =(0/(+Deno))/(Deno) -> 0 | I12: =F12+G12-H12 -> 0 | J12: =+E12-I12 -> 0 | K12: =+B12-F12 -> 0
A13: Interior Decoration | B13: =4191829.7/(Deno) -> 41.918297 | C13: 0 | D13: =(0/(+Deno))/(Deno) -> 0 | E13: =B13+C13-D13 -> 41.918297 | F13: =3674004.05087299/(Deno) -> 36.740041 | G13: =136364.39/Deno -> 1.3636439 | H13: =(0/(+Deno))/(Deno) -> 0 | I13: =F13+G13-H13 -> 38.103684 | J13: =+E13-I13 -> 3.8146126 | K13: =+B13-F13 -> 5.1782565
A14: Computers | B14: =1847560.05/(Deno) -> 18.4756 | C14: =32966.11/Deno -> 0.3296611 | D14: =(0/(+Deno))/(Deno) -> 0 | E14: =B14+C14-D14 -> 18.805262 | F14: =1707661.14066679/(Deno) -> 17.076611 | G14: =49176.93/Deno -> 0.4917693 | H14: =(0/(+Deno))/(Deno) -> 0 | I14: =F14+G14-H14 -> 17.568381 | J14: =+E14-I14 -> 1.2368809 | K14: =+B14-F14 -> 1.3989891
A15: Communication Equiptments | B15: =381194/(Deno) -> 3.81194 | C15: 0 | D15: =(0/(+Deno))/(Deno) -> 0 | E15: =B15+C15-D15 -> 3.81194 | F15: =362133/(Deno) -> 3.62133 | G15: =0/Deno -> 0 | H15: =(0/(+Deno))/(Deno) -> 0 | I15: =F15+G15-H15 -> 3.62133 | J15: =+E15-I15 -> 0.19061 | K15: =+B15-F15 -> 0.19061
A16: Furniture and fixtures | B16: =1288569.39/(Deno) -> 12.885694 | C16: 0 | D16: =(0/(+Deno))/(Deno) -> 0 | E16: =B16+C16-D16 -> 12.885694 | F16: =1163486.96885793/(Deno) -> 11.63487 | G16: =31560.56/Deno -> 0.3156056 | H16: =(0/(+Deno))/(Deno) -> 0 | I16: =F16+G16-H16 -> 11.950475 | J16: =+E16-I16 -> 0.93521861 | K16: =+B16-F16 -> 1.2508242
A17: Electrical equipments | B17: =664330.5/(Deno) -> 6.643305 | C17: =56000/Deno -> 0.56 | D17: =(0/(+Deno))/(Deno) -> 0 | E17: =B17+C17-D17 -> 7.203305 | F17: =627140.285150916/(Deno) -> 6.2714029 | G17: =22733.66/Deno -> 0.2273366 | H17: =(0/(+Deno))/(Deno) -> 0 | I17: =F17+G17-H17 -> 6.4987395 | J17: =+E17-I17 -> 0.70456555 | K17: =+B17-F17 -> 0.37190215
A18: Office Equipments | B18: =571389.5/(Deno) -> 5.713895 | C18: 0 | D18: =(0/(+Deno))/(Deno) -> 0 | E18: =B18+C18-D18 -> 5.713895 | F18: =496305.623742537/(Deno) -> 4.9630562 | G18: =30063.39/Deno -> 0.3006339 | H18: =(0/(+Deno))/(Deno) -> 0 | I18: =F18+G18-H18 -> 5.2636901 | J18: =+E18-I18 -> 0.45020486 | K18: =+B18-F18 -> 0.75083876
A20: Total | B20: =SUM(B12:B18) -> 89.448731 | C20: =SUM(C12:C18) -> 0.8896611 | D20: =SUM(D12:D18) -> 0 | E20: =SUM(E12:E18) -> 90.338393 | F20: =SUM(F12:F18) -> 80.307311 | G20: =SUM(G12:G18) -> 2.6989893 | H20: =SUM(H12:H18) -> 0 | I20: =SUM(I12:I18) -> 83.0063 | ... K20: =SUM(K12:K18) -> 9.1414207
A22: Previous Year figure | B22: =8888305.35/(Deno) -> 88.883054 | C22: =56567.79/(Deno) -> 0.5656779 | D22: =0/(Deno) -> 0 | E22: =8944873.14/(Deno) -> 89.448731 | F22: =7695410.89794036/(Deno) -> 76.954109 | G22: =335320.171350791/(Deno) -> 3.3532017 | H22: =0/(Deno) -> 0 | I22: =8030731.06929115/(Deno) -> 80.307311 | J22: =914142.07070885/(Deno) -> 9.1414207 | K22: =1192894.45205964/(Deno) -> 11.928945
B26: =+B20*100000 -> 8944873.1 | C26: =+C20*100000 -> 88966.11 | D26: =+D20*100000 -> 0 | E26: =+E20*100000 -> 9033839.3 | F26: =+F20*100000 -> 8030731.1 | G26: =+G20*100000 -> 269898.93 | H26: =+H20*100000 -> 0 | I26: =+I20*100000 -> 8300630 | ... K26: =+K20*100000 -> 914142.07

Sheet NOTE 12
A1: =BS!A1 -> CARGO INTERNATIONAL (INDIA) PRIVATE LIMITED
A2: NOTES TO THE FINANCIAL STATEMENTS FOR THE YEAR ENDED 31st MARCH, 2025
A3: CAPITAL TOWERS, NO.G-3/1, G-3/2 & G-2 ,DOOR NO.180 KODAMBAKKAM HIGH ROAD, NUNGAMBAKKAM, CHENNAI - 600034
A5: NOTE 12 : TRADE RECEIVABLES
A6: Sundry Debtors
G8: =+"(Unless otherwise specified, all amounts are "&IF('Master data'!A2="Ones","Indian Rupees","in "&'Master data'!A2&" of INR)") -> (Unless otherwise specified, all amounts are in Lakhs of INR)
A9: Particulars | B9: As on Mar 31,2025
B10: Outstanding for following periods from due date of payment
B11: Less than 6 months | C11: 6 months to 1 year | D11: 1 - 2 years | E11: 2 - 3 years | F11: more than 3 years | G11: TOTAL
A13: Undisputed Trade receivables considered Good | B13: 0 | C13: =61414470.29/(+Deno) -> 614.1447 | D13: =149040.24/(+Deno) -> 1.4904024 | E13: =19056.25/(+Deno) -> 0.1905625 | F13: =28323028.71/Deno -> 283.23029 | G13: =SUM(B13:F13) -> 899.05595
A14: Undisputed Trade receivables considered doubtful | B14: 0 | C14: 0 | D14: 0 | E14: 0 | F14: 0 | G14: =SUM(B14:F14) -> 0
A15: Disputed Trade receivable considered Good | B15: 0 | C15: 0 | D15: 0 | E15: 0 | F15: 0 | G15: =SUM(B15:F15) -> 0
A16: Disputed Trade receivable considered doubtful | B16: 0 | C16: 0 | D16: 0 | E16: 0 | F16: 0 | G16: =SUM(B16:F16) -> 0
A18: TOTAL | B18: =SUM(B13:B17) -> 0 | C18: =SUM(C13:C17) -> 614.1447 | D18: =SUM(D13:D17) -> 1.4904024 | E18: =SUM(E13:E17) -> 0.1905625 | F18: =SUM(F13:F17) -> 283.23029 | G18: =SUM(G13:G17) -> 899.05595 | H18: =+C18*100000 -> 61414470 | I18: =+D18*100000 -> 149040.24 | J18: =+E18*100000 -> 19056.25 | K18: =+F18*100000 -> 28323029 | L18: =+G18*100000 -> 89905595
A21: Particulars | B21: As on Mar 31, 2024
B22: Outstanding for following periods from due date of payment
B23: Less than 6 months | C23: 6 months to 1 year | D23: 1 - 2 years | E23: 2 - 3 years | F23: more than 3 years | G23: TOTAL
A25: Undisputed Trade receivables considered Good | B25: 0 | C25: =26658528.09/Deno -> 266.58528 | D25: =729673.35/Deno -> 7.2967335 | E25: =92044.95/Deno -> 0.9204495 | F25: =25087064.29/Deno -> 250.87064 | G25: =SUM(B25:F25) -> 525.67311
A26: Undisputed Trade receivables considered doubtful | B26: =0/(+Deno) -> 0 | C26: =0/(+Deno) -> 0 | D26: =0/(+Deno) -> 0 | E26: =0/(+Deno) -> 0 | F26: =0/(+Deno) -> 0 | G26: =SUM(B26:F26) -> 0
A27: Disputed Trade receivable considered Good | B27: =0/(+Deno) -> 0 | C27: =0/(+Deno) -> 0 | D27: =0/(+Deno) -> 0 | E27: =812293.32/Deno -> 8.1229332 | F27: =0/(+Deno) -> 0 | G27: =SUM(B27:F27) -> 8.1229332
A28: Disputed Trade receivable considered doubtful | B28: =0/(+Deno) -> 0 | C28: =0/(+Deno) -> 0 | D28: =0/(+Deno) -> 0 | E28: =0/(+Deno) -> 0 | F28: =0/(+Deno) -> 0 | G28: =SUM(B28:F28) -> 0
A30: TOTAL | B30: =SUM(B25:B29) -> 0 | C30: =SUM(C25:C29) -> 266.58528 | D30: =SUM(D25:D29) -> 7.2967335 | E30: =SUM(E25:E29) -> 9.0433827 | F30: =SUM(F25:F29) -> 250.87064 | G30: =SUM(G25:G29) -> 533.79604 | H30: =+C30*100000 -> 26658528 | I30: =+D30*100000 -> 729673.35 | J30: =+E30*100000 -> 904338.27 | K30: =+F30*100000 -> 25087064 | L30: =+G30*100000 -> 53379604

Sheet NOTE 10-14
A1: =BS!A1 -> CARGO INTERNATIONAL (INDIA) PRIVATE LIMITED
A2: NOTES TO THE FINANCIAL STATEMENTS FOR THE YEAR ENDED 31st MARCH, 2025
A3: CAPITAL TOWERS, NO.G-3/1, G-3/2 & G-2 ,DOOR NO.180 KODAMBAKKAM HIGH ROAD, NUNGAMBAKKAM, CHENNAI - 600034
C4: =+"(Unless otherwise specified, all amounts are "&IF('Master data'!A2="Ones","Indian Rupees","in "&'Master data'!A2&" of INR)") -> (Unless otherwise specified, all amounts are in Lakhs of INR)
A5: Particulars | B5: As on | C5: As on
B6: 31st March, 2025 | C6: 31st March, 2024
A8: NOTE 10 : LONG TERM LOANS AND ADVANCES
A9: Rental Deposit | B9: =(SUMIF('TB 24-25'!$Q:$Q,$A9,'TB 24-25'!$O:$O)-SUMIF('TB 24-25'!$Q:$Q,$A9,'TB 24-25'!$P:$P)) -> 16.69658 | C9: =(SUMIF('TB 24-25'!$Q:$Q,$A9,'TB 24-25'!$E:$E)-SUMIF('TB 24-25'!$Q:$Q,$A9,'TB 24-25'!$F:$F)) -> 19.69658 | D9: =+B9*100000 -> 1669658 | E9: =+C9*100000 -> 1969658
A10: TDS Receivable | B10: =(SUMIF('TB 24-25'!$Q:$Q,$A10,'TB 24-25'!$O:$O)-SUMIF('TB 24-25'!$Q:$Q,$A10,'TB 24-25'!$P:$P)) -> 211.1422 | C10: =(SUMIF('TB 24-25'!$Q:$Q,$A10,'TB 24-25'!$E:$E)-SUMIF('TB 24-25'!$Q:$Q,$A10,'TB 24-25'!$F:$F)) -> 185.13074 | D10: =+B10*100000 -> 21114220 | E10: =+C10*100000 -> 18513074
D11: =+B11*100000 -> 0 | E11: =+C11*100000 -> 0
B12: =SUM(B9:B11) -> 227.83878 | C12: =SUM(C9:C11) -> 204.82732 | D12: =+B12*100000 -> 22783878 | E12: =+C12*100000 -> 20482732
D13: =+B13*100000 -> 0 | E13: =+C13*100000 -> 0
A14: NOTE 11 : DEFERRED TAX ASSETS | D14: =+B14*100000 -> 0 | E14: =+C14*100000 -> 0
A15: Opening Balance | B15: =+C18 -> 6.349577 | C15: =663198.01/Deno -> 6.6319801 | D15: =+B15*100000 -> 634957.7 | E15: =+C15*100000 -> 663198.01
A16: Add: Current year | B16: =PL!D32 -> -0.37521685 | C16: =PL!E32 -> -0.28240312 | D16: =+B16*100000 -> -37521.685 | E16: =+C16*100000 -> -28240.312
D17: =+B17*100000 -> 0 | E17: =+C17*100000 -> 0
A18: Deferred Tax Assets/(Liabilty) | B18: =SUM(B15:B17) -> 5.9743601 | C18: =SUM(C15:C17) -> 6.349577 | D18: =+B18*100000 -> 597436.01 | E18: =+C18*100000 -> 634957.7
D19: =+B19*100000 -> 0 | E19: =+C19*100000 -> 0
A20: NOTE 13 : CASH AND CASH EQUIVALENTS | D20: =+B20*100000 -> 0 | E20: =+C20*100000 -> 0
A21: Balance with banks | B21: =(+'Sub Sch - BS'!B38) -> 216.77245 | C21: =(+'Sub Sch - BS'!C38) -> 56.865407 | D21: =+B21*100000 -> 21677245 | E21: =+C21*100000 -> 5686540.7
A22: Cash on hand | B22: =(+'Sub Sch - BS'!B32) -> 0.1629965 | C22: =(+'Sub Sch - BS'!C32) -> 4.3102892 | D22: =+B22*100000 -> 16299.65 | E22: =+C22*100000 -> 431028.92
D23: =+B23*100000 -> 0 | E23: =+C23*100000 -> 0
B24: =SUM(B21:B23) -> 216.93544 | C24: =SUM(C21:C23) -> 61.175696 | D24: =+B24*100000 -> 21693544 | E24: =+C24*100000 -> 6117569.6
D25: =+B25*100000 -> 0 | E25: =+C25*100000 -> 0
A26: NOTE 14 : SHORT TERM LOANS AND ADVANCES | D26: =+B26*100000 -> 0 | E26: =+C26*100000 -> 0
A27: GST Input tax credit | B27: =(+'Sub Sch - BS'!B44) -> 50.6507 | C27: =(+'Sub Sch - BS'!C44) -> 72.83783 | D27: =+B27*100000 -> 5065070 | E27: =+C27*100000 -> 7283783
A28: Prepaid Expenses | B28: =(SUMIF('TB 24-25'!$Q:$Q,$A28,'TB 24-25'!$O:$O)-SUMIF('TB 24-25'!$Q:$Q,$A28,'TB 24-25'!$P:$P)) -> 1.3078823 | C28: =(SUMIF('TB 24-25'!$Q:$Q,$A28,'TB 24-25'!$E:$E)-SUMIF('TB 24-25'!$Q:$Q,$A28,'TB 24-25'!$F:$F)) -> 1.2206625 | D28: =+B28*100000 -> 130788.23 | E28: =+C28*100000 -> 122066.25
A29: Staff Advance | B29: =(SUMIF('TB 24-25'!$Q:$Q,$A29,'TB 24-25'!$O:$O)-SUMIF('TB 24-25'!$Q:$Q,$A29,'TB 24-25'!$P:$P)) -> 0.4318174 | C29: =(SUMIF('TB 24-25'!$Q:$Q,$A29,'TB 24-25'!$E:$E)-SUMIF('TB 24-25'!$Q:$Q,$A29,'TB 24-25'!$F:$F)) -> 0.5560464 | D29: =+B29*100000 -> 43181.74 | E29: =+C29*100000 -> 55604.64
D30: =+B30*100000 -> 0 | E30: =+C30*100000 -> 0
B31: =SUM(B27:B30) -> 52.3904 | C31: =SUM(C27:C30) -> 74.614539 | D31: =+B31*100000 -> 5239040 | E31: =+C31*100000 -> 7461453.9

Sheet NOTE 15-20
A1: CARGO INTERNATIONAL (INDIA) PRIVATE LIMITED
A2: =+'NOTE 3'!A2:E2 -> NOTES TO THE FINANCIAL STATEMENTS FOR THE YEAR ENDED 31st MARCH, 2025
C4: =+"(Unless otherwise specified, all amounts are "&IF('Master data'!A2="Ones","Indian Rupees","in "&'Master data'!A2&" of INR)") -> (Unless otherwise specified, all amounts are in Lakhs of INR)
A5: Particulars | B5: For Year Ended | C5: For Year Ended
B6: 45747 | C6: 45382 | F6: =10^5 -> 100000
A8: NOTE 15 : REVENUE FROM OPERATIONS
A9: Export Operating Income | B9: =(SUMIF('TB 24-25'!$Q:$Q,'NOTE 15-20'!$A9,'TB 24-25'!$P:$P)-SUMIF('TB 24-25'!$Q:$Q,'NOTE 15-20'!$A9,'TB 24-25'!$O:$O)) -> 1414.428 | C9: =(SUMIF('TB 24-25'!$Q:$Q,'NOTE 15-20'!$A9,'TB 24-25'!$F:$F)-SUMIF('TB 24-25'!$Q:$Q,'NOTE 15-20'!$A9,'TB 24-25'!$E:$E)) -> 552.11691 | D9: =+B9*100000 -> 1.414428e+08 | E9: =+C9*100000 -> 55211691
A10: Import Operating Income | B10: =(SUMIF('TB 24-25'!$Q:$Q,'NOTE 15-20'!$A10,'TB 24-25'!$P:$P)-SUMIF('TB 24-25'!$Q:$Q,'NOTE 15-20'!$A10,'TB 24-25'!$O:$O)) -> 273.74244 | C10: =(SUMIF('TB 24-25'!$Q:$Q,'NOTE 15-20'!$A10,'TB 24-25'!$F:$F)-SUMIF('TB 24-25'!$Q:$Q,'NOTE 15-20'!$A10,'TB 24-25'!$E:$E)) -> 120.00801 | D10: =+B10*100000 -> 27374244 | E10: =+C10*100000 -> 12000801
A11: Air Export Revenue Account | B11: =(SUMIF('TB 24-25'!$Q:$Q,'NOTE 15-20'!$A11,'TB 24-25'!$P:$P)-SUMIF('TB 24-25'!$Q:$Q,'NOTE 15-20'!$A11,'TB 24-25'!$O:$O)) -> 722.99417 | C11: =(SUMIF('TB 24-25'!$Q:$Q,'NOTE 15-20'!$A11,'TB 24-25'!$F:$F)-SUMIF('TB 24-25'!$Q:$Q,'NOTE 15-20'!$A11,'TB 24-25'!$E:$E)) -> 711.08395 | D11: =+B11*100000 -> 72299417 | E11: =+C11*100000 -> 71108395
A12: Air Import Revenue Account | B12: =(SUMIF('TB 24-25'!$Q:$Q,'NOTE 15-20'!$A12,'TB 24-25'!$P:$P)-SUMIF('TB 24-25'!$Q:$Q,'NOTE 15-20'!$A12,'TB 24-25'!$O:$O)) -> 99.404203 | C12: =(SUMIF('TB 24-25'!$Q:$Q,'NOTE 15-20'!$A12,'TB 24-25'!$F:$F)-SUMIF('TB 24-25'!$Q:$Q,'NOTE 15-20'!$A12,'TB 24-25'!$E:$E)) -> 101.55796 | D12: =+B12*100000 -> 9940420.3 | E12: =+C12*100000 -> 10155796
D13: =+B13*100000 -> 0 | E13: =+C13*100000 -> 0
B14: =SUM(B9:B13) -> 2510.5688 | C14: =SUM(C9:C13) -> 1484.7668 | D14: =+B14*100000 -> 2.5105688e+08 | E14: =+C14*100000 -> 1.4847668e+08
D15: =+B15*100000 -> 0 | E15: =+C15*100000 -> 0
A16: NOTE 16 : OTHER INCOME | D16: =+B16*100000 -> 0 | E16: =+C16*100000 -> 0
A17: Service Job Revenue | B17: =(SUMIF('TB 24-25'!$Q:$Q,'NOTE 15-20'!$A17,'TB 24-25'!$P:$P)-SUMIF('TB 24-25'!$Q:$Q,'NOTE 15-20'!$A17,'TB 24-25'!$O:$O)) -> 62.736728 | C17: =(SUMIF('TB 24-25'!$Q:$Q,'NOTE 15-20'!$A17,'TB 24-25'!$F:$F)-SUMIF('TB 24-25'!$Q:$Q,'NOTE 15-20'!$A17,'TB 24-25'!$E:$E)) -> 46.56197 | D17: =+B17*100000 -> 6273672.8 | E17: =+C17*100000 -> 4656197
A18: Interest Income | B18: =(SUMIF('TB 24-25'!$Q:$Q,'NOTE 15-20'!$A18,'TB 24-25'!$P:$P)-SUMIF('TB 24-25'!$Q:$Q,'NOTE 15-20'!$A18,'TB 24-25'!$O:$O)) -> 0.01397 | C18: =(SUMIF('TB 24-25'!$Q:$Q,'NOTE 15-20'!$A18,'TB 24-25'!$F:$F)-SUMIF('TB 24-25'!$Q:$Q,'NOTE 15-20'!$A18,'TB 24-25'!$E:$E)) -> 0 | D18: =+B18*100000 -> 1397 | E18: =+C18*100000 -> 0
D19: =+B19*100000 -> 0 | E19: =+C19*100000 -> 0
B20: =SUM(B17:B19) -> 62.750698 | C20: =SUM(C17:C19) -> 46.56197 | D20: =+B20*100000 -> 6275069.8 | E20: =+C20*100000 -> 4656197
D21: =+B21*100000 -> 0 | E21: =+C21*100000 -> 0
A22: NOTE 17 : OPERATING EXPENSES | D22: =+B22*100000 -> 0 | E22: =+C22*100000 -> 0
A23: Export Operating Expenses | B23: =(SUMIF('TB 24-25'!$Q:$Q,'NOTE 15-20'!$A23,'TB 24-25'!$O:$O)-SUMIF('TB 24-25'!$Q:$Q,'NOTE 15-20'!$A23,'TB 24-25'!$P:$P)) -> 1176.0631 | C23: =(SUMIF('TB 24-25'!$Q:$Q,'NOTE 15-20'!$A23,'TB 24-25'!$E:$E)-SUMIF('TB 24-25'!$Q:$Q,'NOTE 15-20'!$A23,'TB 24-25'!$F:$F)) -> 418.97627 | D23: =+B23*100000 -> 1.1760631e+08 | E23: =+C23*100000 -> 41897627
A24: Import Operating Expenses | B24: =(SUMIF('TB 24-25'!$Q:$Q,'NOTE 15-20'!$A24,'TB 24-25'!$O:$O)-SUMIF('TB 24-25'!$Q:$Q,'NOTE 15-20'!$A24,'TB 24-25'!$P:$P)) -> 240.87738 | C24: =(SUMIF('TB 24-25'!$Q:$Q,'NOTE 15-20'!$A24,'TB 24-25'!$E:$E)-SUMIF('TB 24-25'!$Q:$Q,'NOTE 15-20'!$A24,'TB 24-25'!$F:$F)) -> 125.69191 | D24: =+B24*100000 -> 24087738 | E24: =+C24*100000 -> 12569191
A25: Air Export Operating Expenses | B25: =(SUMIF('TB 24-25'!$Q:$Q,'NOTE 15-20'!$A25,'TB 24-25'!$O:$O)-SUMIF('TB 24-25'!$Q:$Q,'NOTE 15-20'!$A25,'TB 24-25'!$P:$P)) -> 656.18241 | C25: =(SUMIF('TB 24-25'!$Q:$Q,'NOTE 15-20'!$A25,'TB 24-25'!$E:$E)-SUMIF('TB 24-25'!$Q:$Q,'NOTE 15-20'!$A25,'TB 24-25'!$F:$F)) -> 593.05508 | D25: =+B25*100000 -> 65618241 | E25: =+C25*100000 -> 59305508
A26: Air Import Operating Expenses | B26: =(SUMIF('TB 24-25'!$Q:$Q,'NOTE 15-20'!$A26,'TB 24-25'!$O:$O)-SUMIF('TB 24-25'!$Q:$Q,'NOTE 15-20'!$A26,'TB 24-25'!$P:$P)) -> 80.544631 | C26: =(SUMIF('TB 24-25'!$Q:$Q,'NOTE 15-20'!$A26,'TB 24-25'!$E:$E)-SUMIF('TB 24-25'!$Q:$Q,'NOTE 15-20'!$A26,'TB 24-25'!$F:$F)) -> 79.013997 | D26: =+B26*100000 -> 8054463.1 | E26: =+C26*100000 -> 7901399.7
D27: =+B27*100000 -> 0 | E27: =+C27*100000 -> 0
B28: =SUM(B23:B27) -> 2153.6675 | C28: =SUM(C23:C27) -> 1216.7373 | D28: =+B28*100000 -> 2.1536675e+08 | E28: =+C28*100000 -> 1.2167373e+08
D29: =+B29*100000 -> 0 | E29: =+C29*100000 -> 0
A30: NOTE 18 : EMPLOYEE BENEFIT EXPENSE | D30: =+B30*100000 -> 0 | E30: =+C30*100000 -> 0
A31: Salaries | B31: =(SUMIF('TB 24-25'!$Q:$Q,'NOTE 15-20'!$A31,'TB 24-25'!$O:$O)-SUMIF('TB 24-25'!$Q:$Q,'NOTE 15-20'!$A31,'TB 24-25'!$P:$P))+32685/Deno -> 225.38028 | C31: =(SUMIF('TB 24-25'!$Q:$Q,'NOTE 15-20'!$A31,'TB 24-25'!$E:$E)-SUMIF('TB 24-25'!$Q:$Q,'NOTE 15-20'!$A31,'TB 24-25'!$F:$F))+36369/Deno -> 214.75304 | D31: =+B31*100000 -> 22538028 | E31: =+C31*100000 -> 21475304
A32: Staff welfare Expense | B32: =(SUMIF('TB 24-25'!$Q:$Q,'NOTE 15-20'!$A32,'TB 24-25'!$O:$O)-SUMIF('TB 24-25'!$Q:$Q,'NOTE 15-20'!$A32,'TB 24-25'!$P:$P)) -> 5.09503 | C32: =(SUMIF('TB 24-25'!$Q:$Q,'NOTE 15-20'!$A32,'TB 24-25'!$E:$E)-SUMIF('TB 24-25'!$Q:$Q,'NOTE 15-20'!$A32,'TB 24-25'!$F:$F)) -> 5.87496 | D32: =+B32*100000 -> 509503 | E32: =+C32*100000 -> 587496
D33: =+B33*100000 -> 0 | E33: =+C33*100000 -> 0
B34: =SUM(B31:B33) -> 230.47531 | C34: =SUM(C31:C33) -> 220.628 | D34: =+B34*100000 -> 23047531 | E34: =+C34*100000 -> 22062800
D35: =+B35*100000 -> 0 | E35: =+C35*100000 -> 0
D36: =+B36*100000 -> 0 | E36: =+C36*100000 -> 0
A37: NOTE 19 : FINANCIAL COST | D37: =+B37*100000 -> 0 | E37: =+C37*100000 -> 0
A38: Bank Charges | B38: =(SUMIF('TB 24-25'!$Q:$Q,'NOTE 15-20'!$A38,'TB 24-25'!$O:$O)-SUMIF('TB 24-25'!$Q:$Q,'NOTE 15-20'!$A38,'TB 24-25'!$P:$P)) -> 2.6556022 | C38: =(SUMIF('TB 24-25'!$Q:$Q,'NOTE 15-20'!$A38,'TB 24-25'!$E:$E)-SUMIF('TB 24-25'!$Q:$Q,'NOTE 15-20'!$A38,'TB 24-25'!$F:$F)) -> 1.879493 | D38: =+B38*100000 -> 265560.22 | E38: =+C38*100000 -> 187949.3
A39: Interest | B39: =(SUMIF('TB 24-25'!$Q:$Q,'NOTE 15-20'!$A39,'TB 24-25'!$O:$O)-SUMIF('TB 24-25'!$Q:$Q,'NOTE 15-20'!$A39,'TB 24-25'!$P:$P)) -> 0.0087948 | C39: =(SUMIF('TB 24-25'!$Q:$Q,'NOTE 15-20'!$A39,'TB 24-25'!$E:$E)-SUMIF('TB 24-25'!$Q:$Q,'NOTE 15-20'!$A39,'TB 24-25'!$F:$F)) -> 0 | D39: =+B39*100000 -> 879.48 | E39: =+C39*100000 -> 0
D40: =+B40*100000 -> 0 | E40: =+C40*100000 -> 0
B41: =SUM(B38:B40) -> 2.664397 | C41: =SUM(C38:C40) -> 1.879493 | D41: =+B41*100000 -> 266439.7 | E41: =+C41*100000 -> 187949.3
D42: =+B42*100000 -> 0 | E42: =+C42*100000 -> 0
A43: NOTE 20 : ADMINISTRATION EXPENSES | D43: =+B43*100000 -> 0 | E43: =+C43*100000 -> 0
A44: Audit Fees | B44: =(SUMIF('TB 24-25'!$Q:$Q,'NOTE 15-20'!$A44,'TB 24-25'!$O:$O)-SUMIF('TB 24-25'!$Q:$Q,'NOTE 15-20'!$A44,'TB 24-25'!$P:$P)) -> 2.25 | C44: =(SUMIF('TB 24-25'!$Q:$Q,'NOTE 15-20'!$A44,'TB 24-25'!$E:$E)-SUMIF('TB 24-25'!$Q:$Q,'NOTE 15-20'!$A44,'TB 24-25'!$F:$F)) -> 2.25 | D44: =+B44*100000 -> 225000 | E44: =+C44*100000 -> 225000
A45: Bad and Doubtful Debts | B45: =(SUMIF('TB 24-25'!$Q:$Q,'NOTE 15-20'!$A45,'TB 24-25'!$O:$O)-SUMIF('TB 24-25'!$Q:$Q,'NOTE 15-20'!$A45,'TB 24-25'!$P:$P)) -> 30.973872 | C45: =(SUMIF('TB 24-25'!$Q:$Q,'NOTE 15-20'!$A45,'TB 24-25'!$E:$E)-SUMIF('TB 24-25'!$Q:$Q,'NOTE 15-20'!$A45,'TB 24-25'!$F:$F)) -> 0.342 | D45: =+B45*100000 -> 3097387.2 | E45: =+C45*100000 -> 34200
A46: Business Promotion Expense | B46: =(+'Sub Sch - p&l'!B12) -> 16.33321 | C46: =(+'Sub Sch - p&l'!C12) -> 5.733903 | D46: =+B46*100000 -> 1633321.1 | E46: =+C46*100000 -> 573390.3
A47: Communication Expense | B47: =(+'Sub Sch - p&l'!B20) -> 10.604403 | C47: =(+'Sub Sch - p&l'!C20) -> 9.1345412 | D47: =+B47*100000 -> 1060440.3 | E47: =+C47*100000 -> 913454.12
A48: Foreign Exchange gain/loss | B48: =(SUMIF('TB 24-25'!$Q:$Q,'NOTE 15-20'!$A48,'TB 24-25'!$O:$O)-SUMIF('TB 24-25'!$Q:$Q,'NOTE 15-20'!$A48,'TB 24-25'!$P:$P)) -> -0.33920907 | C48: =(SUMIF('TB 24-25'!$Q:$Q,'NOTE 15-20'!$A48,'TB 24-25'!$E:$E)-SUMIF('TB 24-25'!$Q:$Q,'NOTE 15-20'!$A48,'TB 24-25'!$F:$F)) -> 3.5844668 | D48: =+B48*100000 -> -33920.907 | E48: =+C48*100000 -> 358446.68
A49: Insurance | B49: =(SUMIF('TB 24-25'!$Q:$Q,'NOTE 15-20'!$A49,'TB 24-25'!$O:$O)-SUMIF('TB 24-25'!$Q:$Q,'NOTE 15-20'!$A49,'TB 24-25'!$P:$P)) -> 3.865907 | C49: =(SUMIF('TB 24-25'!$Q:$Q,'NOTE 15-20'!$A49,'TB 24-25'!$E:$E)-SUMIF('TB 24-25'!$Q:$Q,'NOTE 15-20'!$A49,'TB 24-25'!$F:$F)) -> 3.4406091 | D49: =+B49*100000 -> 386590.7 | E49: =+C49*100000 -> 344060.91
A50: Other Expense | B50: =(+'Sub Sch - p&l'!B35) -> 19.349467 | C50: =(+'Sub Sch - p&l'!C35) -> 35.382689 | D50: =+B50*100000 -> 1934946.7 | E50: =+C50*100000 -> 3538268.9
A51: Professional charges | B51: =(+'Sub Sch - p&l'!B43) -> 19.999709 | C51: =(+'Sub Sch - p&l'!C43) -> 18.3924 | D51: =+B51*100000 -> 1999970.9 | E51: =+C51*100000 -> 1839240
A52: Rates and Taxes | B52: =(SUMIF('TB 24-25'!$Q:$Q,'NOTE 15-20'!$A52,'TB 24-25'!$O:$O)-SUMIF('TB 24-25'!$Q:$Q,'NOTE 15-20'!$A52,'TB 24-25'!$P:$P)) -> 3.61217 | C52: =(SUMIF('TB 24-25'!$Q:$Q,'NOTE 15-20'!$A52,'TB 24-25'!$E:$E)-SUMIF('TB 24-25'!$Q:$Q,'NOTE 15-20'!$A52,'TB 24-25'!$F:$F)) -> 16.04225 | D52: =+B52*100000 -> 361217 | E52: =+C52*100000 -> 1604225
A53: Rent | B53: =(+'Sub Sch - p&l'!B51) -> 21.35065 | C53: =(+'Sub Sch - p&l'!C51) -> 25.26275 | D53: =+B53*100000 -> 2135065 | E53: =+C53*100000 -> 2526275
A54: Repairs & maintenance | B54: =(+'Sub Sch - p&l'!B60) -> 6.0953795 | C54: =(+'Sub Sch - p&l'!C60) -> 3.3584586 | D54: =+B54*100000 -> 609537.95 | E54: =+C54*100000 -> 335845.86
A55: Travelling expense | B55: =(+'Sub Sch - p&l'!B67) -> 23.185836 | C55: =(+'Sub Sch - p&l'!C67) -> 15.735289 | D55: =+B55*100000 -> 2318583.6 | E55: =+C55*100000 -> 1573528.9
D56: =+B56*100000 -> 0 | E56: =+C56*100000 -> 0
B57: =SUM(B44:B56) -> 157.28139 | C57: =SUM(C44:C56) -> 138.65936 | D57: =+B57*100000 -> 15728139 | E57: =+C57*100000 -> 13865936
A59: REMUNERATION TO AUDITOR
A60: Statutory Audit fees | B60: =(+'TB 24-25'!M286)/Deno -> 1 | C60: =125000/Deno -> 1.25
A61: Tax Audit Fees | B61: =(+'TB 24-25'!M287)/Deno -> 1.25 | C61: =100000/Deno -> 1
B63: =SUM(B60:B62) -> 2.25 | C63: =SUM(C60:C62) -> 2.25

Sheet Add Notes
A1: CARGO INTERNATIONAL (INDIA) PRIVATE LIMITED
A2: NOTES TO THE FINANCIAL STATEMENTS FOR THE YEAR ENDED 31st MARCH, 2025
A3: CIN: U63000TN2010PTC077296
A4: Old No.7 / New No.13, First Floor, First Cross Street, Trustpuram, Kodambakkam, Chennai - 600024, India
A6: NOTE 21: ADDITIONAL NOTES AND INFORMATION:
A7: (1) Contingent Liabilities:
A8: There is no contingent liability in respect of the company.
A10: (2) Earnings Per Share (EPS) | C10: (Absolute Numbers)
A11: Particulars | B11: 2024 - 25 | C11: 2023 - 24
A12: a) Net Profit / (Loss) available for Equity Shareholders | B12: =+PL!D34*Deno -> 1960906.2 | C12: =+PL!E34*Deno -> -5021090.5
A13: b) Weighed average number of Shares outstanding | B13: 20000 | C13: 20000
A14: c) Basic Earnings per Share of Rs.10 each | B14: =B12/B13 -> 98.045308 | C14: =C12/C13 -> -251.05453
A15: d) Net Profit / (Loss) available for Equity Shareholders | B15: =B12 -> 1960906.2 | C15: =C12 -> -5021090.5
A16: e) Weighed average number of Shares outstanding | B16: 20000 | C16: 20000
A17: Dilutive Earnings per Share of Rs.10 each | B17: =B15/B16 -> 98.045308 | C17: =C15/C16 -> -251.05453
A19: (3) Earnings in foreign currency during the year (on realisation basis)
A20: Particulars | B20: 2024 - 25 | C20: 2023 - 24
A21: Income realised | B21: =+"Rs. "&42171960.92/Deno -> Rs. 421.7196092 | C21: =+"Rs. "&44486684.12/Deno -> Rs. 444.8668412
A23: (4) Expenditure in foreign currency during the year (on realisation basis)
A24: Particulars | B24: 2024 - 25 | C24: 2023 - 24
A25: Expenses | B25: =+"Rs. "&71090808.79/Deno -> Rs. 710.9080879 | C25: =+"Rs. "&50032407.77/Deno -> Rs. 500.3240777
A27: (5) Related Party Disclosures of the year ended 31st March 2025
A28: a) List of Related Parties:
A29: Key Management Personnel (KMP)
A30: Suresh Padmanabhan - Director
A31: Vignesh Natarajan - Director
A33: Associate/Joint venture Companies/Firms
A34: Cargo International Logistics LLC-Oman
A35: Inter Continental Logistics Limited-UK
A36: Cargo International Limited-Dubai
A38: b) Details of Transaction
A39: Name of the party and Nature of transaction | B39: Closing Balance as on 31/03/2024 Dr. / (Cr.) | C39: Transaction during the year | E39: Closing Balance as on 31/03/2025 Dr. / (Cr.)
C40: Debit Rs. | D40: Credit Rs.
A41: Cargo International Logistics LLC-Oman
A42: Overseas Payable (Cr.) | B42: -106848.22 | C42: 0 | D42: 822420.92 | E42: =+B42-D42 -> -929269.14
A43: Overseas Receivables (Dr.) | B43: -589181.47 | C43: 436105.24 | D43: 0 | E43: =+B43+C43-D43 -> -153076.23
A44: Inter Continental Logistics Limited-UK
A45: Overseas Payable (Cr.) | B45: -1029992.7 | C45: 65217.568 | D45: 33195208 | E45: =+B45+C45-D45 -> -34159983
A46: Overseas Receivables (Dr.) | B46: -117479.42 | C46: 579932.95 | D46: 0 | E46: =+B46+C46-D46 -> 462453.53
A47: Cargo International Limited-Dubai
A48: Overseas Receivables (Dr.) | B48: 26639514 | C48: =8031445.53+4081269.3 -> 12112715 | D48: 12675243 | E48: =+B48+C48-D48 -> 26076986
A49: Overseas Payable (Cr.) | B49: -26074600 | C49: 0 | D49: 135504.67 | E49: =+B49+C49-D49 -> -26210105
A50: Advances to Creditors (Dr.) | B50: =+'Sub-Schedule'!B9-'Sub-Schedule'!C9 -> 214646.99 | C50: 0 | D50: 0 | E50: =+'Sub-Schedule'!D9-'Sub-Schedule'!E9 -> 214646.99
A51: Advances From Debtors (Cr.) | B51: =+SUM('Sub-Schedule'!B5:B6)-SUM('Sub-Schedule'!C5:C6) -> -15934802 | C51: 0 | D51: 0 | E51: =+SUM('Sub-Schedule'!D5:D6)-SUM('Sub-Schedule'!E5:E6) -> -15934802
A53: c) Shareholders having Substantial Interest
A54: Suresh Padmanabhan
A56: d) Director's Remuneration
A57: Name of Director | B57: Amount in Rs.
A58: Vignesh Natarajan | B58: 1800000
A60: (6) Micro, Small and Medium Enterprises :
A61: As per the information available and as certified by the management, creditors includes payable to Micro, Small and Medium Enterprises amount Rs NIL.as on 31stMarch, 2025.
A62: As per the information available and explanation provided to us and as certified by the management, there is no delay in payment of dues to Enterprises as defined under the "Micro, Small and Medium Enterprises Development Act, 2006.
A63: The company has not received any intimation from “suppliers” regarding their status under the Micro; Small and Medium, Enterprises Development Act, 2006. Hence, disclosure, if any, relating to amount unpaid as at the year-end together with the interest paid/payable as required under the said Act has not been furnished.
A64: (7) Balances with customers and suppliers have been stated at book values and are subject to confirmation.
A65: (8) Previous Year’s figures are re-grouped, re-arranged and re-classified, wherever necessary to conform to current year's classification.
A66: (9) The below amounts represent opening balance differences in the respective ledgers as compared to Financials with the Books of accounts maintained by the company as on 01st April 2017. the amount are written off/ Written back are as under
A67: Particulars | B67: Amount | C67: Remarks
A68: Provision operation | B68: 14110730 | C68: Exceptional / Extraordinary item relating to FY 2017-18 has been Written off in FY 24-25.
A69: GST Input Tax credit | B69: -14902245 | C69: Opening balance difference of GST input tax credit adjusted against opening reserves in FY 23-24
A70: Reserves and Surplus Balance | B70: -5959480 | C70: Opening Balance difference since FY 2017-18, adjusted against reserves and surplus.
A71: Sundry Creditors | B71: -228009 | C71: Written off to Exceptional/ Extraordinary item in P &L in FY 2020-21
A72: Statutory Dues Payable | B72: -287114 | C72: Written off to Exceptional/ Extraordinary item in P &L in FY 2020-21
A73: Short Term Provision | B73: 424989 | C73: Written off to Exceptional/ Extraordinary item in P &L in FY 2020-21
A74: Trade Receivables | B74: 195027 | C74: Written off to Exceptional/ Extraordinary item in P &L in FY 2020-21
A75: Advance To suppliers | B75: -488812 | C75: Written off to Exceptional/ Extraordinary item in P &L in FY 2020-21
A76: (10) There is opening balance differences 2017-18, which has shown in Notes to accounts as suspense account.
A77: (11) The Company has filed litigation against the previous directors of the company under Section 166, 241, 242, 246 and 340 of the companies act 2013 (Case Number: CP/519/2019). The matter is pending for resolution with the National Company Law Tribunal. also Company has filed a case against previous directors with the Chennai Central Crime Branch Officeon 28.7.2021 (Case Number: C.NO.124/CCB/COP/Visitors/2021).
A78: (12) Nature of the Matter Arising out of FIR No. 196/2024 registered at Chennai under Sections 406, 420 r/w 34 IPC, an allegation of criminal breach of trust and cheating involving an amount of ₹2,20,00,000 has been made against the Company (M/s. Cargo International India Pvt. Ltd.) and its directors/officers. The Hon’ble Supreme Court, vide final order dated 20 May 2025, has: a) Upheld the de-freezing of the aforesaid four bank accounts; b) Directed continuation of freeze on the fifth bank account (ICICI Bank A/c No. 399505000812) having a balance of ₹2,49,99,437.29 as on 16 May 2025; c) Recorded an undertaking by the Company to maintain a minimum balance of ₹2,20,00,000 in the said account until final adjudication of the dispute on merits by the appropriate forum.
A79: (12) The company has also done Forensic audit for the year FY 2017-18, in the Forensic Report the auditor has given many qualifications regarding the mis - appropriateness of accounts and balances and also siphoning of funds of Rs.53,28,168 by the previous directors of the company. The above mentioned amounts has been routed through the following parties according to the report:
A80: Party Name | B80: Amount
A81: Mobis | B81: 3587968
A82: Glovis | B82: 1278000
A83: Cryolar | B83: 277200
A84: NSK Sales | B84: 145000
A85: Kerry Ingredients | B85: 40000
A88: For KALYANASUNDARAM & ASSOCIATES | C88: =+CFS!B48 -> For and on behalf of
A89: Chartered Accountants | C89: =+CFS!B49 -> CARGO INTERNATIONAL (INDIA) PVT. LTD
A90: FRN: 005455S
A94: =+CFS!A55 -> K M Sethu | C94: =+CFS!B55 -> Suresh Padmanabhan | E94: Vignesh Natarajan
A95: =+CFS!A56 -> Partner | C95: =+CFS!B56 -> Director | E95: Director
A96: =+CFS!A57 -> M.No.231703 | C96: =+CFS!B57 -> DIN: 08284074 | E96: DIN: 08284068
A97: =+CFS!A58 -> Place : Chennai | C97: =+CFS!B58 -> Place : Birmingham | E97: =+CFS!D58 -> Place : Chennai
A98: =+CFS!A59 -> Date : | C98: =+CFS!B59 -> Date: | E98: =+CFS!D59 -> Date:
A99: =+CFS!A60 -> UDIN :

Sheet Add Notes (2)
A1: CARGO INTERNATIONAL (INDIA) PRIVATE LIMITED
A2: NOTES TO THE FINANCIAL STATEMENTS FOR THE YEAR ENDED 31st MARCH, 2025
A3: CIN: U63000TN2010PTC077296
A4: Old No.7 / New No.13, First Floor, First Cross Street, Trustpuram, Kodambakkam, Chennai - 600024, India | I4: Old No.7 / New No.13, First Floor, First Cross Street, Trustpuram, Kodambakkam, Chennai - 600024, India
A6: NOTE 21: ADDITIONAL NOTES AND INFORMATION:
A8: (13) Analytical Ratios of the year ended 31st March 2025
A9: Particulars | B9: =+'Add Notes'!B11 -> 2024 - 25 | C9: =+'Add Notes'!C11 -> 2023 - 24 | D9: Variance | E9: Remarks (Variance above 25%) | J9: Workings
A10: Current ratio | B10: =+L11/L12 -> 1.1008568 | C10: =+M11/M12 -> 0.95329219 | D10: =IFERROR(+((B10-C10)/C10),"NA") -> 0.15479476 | L10: FY 2024-25 | M10: FY 2023-24 | N10: FY 2022-23 | V10: FY 2022-23
A11: Debt-Equity ratio | B11: =+L14/L15 -> 0 | C11: =+M14/M15 -> 0 | D11: =IFERROR(+((B11-C11)/C11),"NA") -> NA | I11: 1 | J11: Current Ratio | K11: Current Assets | L11: =+BS!C40 -> 1168.3818 | M11: =+BS!D40 -> 669.58629 | N11: 76597931 | Q11: =10^5 -> 100000 | S11: -14447447 | V11: 76597929 | W11: =+M11-V11 -> -76597259
A12: Debt service coverage ratio | B12: 0 | C12: 0 | D12: =IFERROR(+((B12-C12)/C12),"NA") -> NA | J12: =+"CA/CL" -> CA/CL | K12: Current liabilities | L12: =+BS!C23 -> 1061.3386 | M12: =+BS!D23 -> 702.39356 | N12: 72671561 | Q12: =+N11-N12 -> 3926369.5 | V12: 72671561 | W12: =+M12-V12 -> -72670859
A13: Return on equity | B13: =+L17/L18 -> 0.16421912 | C13: =+M17/M18 -> -4.21404e-06 | D13: =IFERROR(+((B13-C13)/C13),"NA") -> -38970.522 | E13: The ROE has swung from a positive 25% to a negative 32%, which is a drastic decline. This indicates a severe reduction in profitability or substantial losses relative to shareholders' equity | W13: =+M13-V13 -> 0
A14: Inventory turnover | B14: 0 | C14: 0 | D14: =IFERROR(+((B14-C14)/C14),"NA") -> NA | I14: 2 | J14: Debt-Equity ratio | K14: Debt | L14: =0*(10^5) -> 0 | M14: =0*(10^5) -> 0 | N14: 0 | V14: 0 | W14: =+M14-V14 -> 0
A15: Trade receivables turnover | B15: =+L25/L26 -> 3.5042961 | C15: =+M25/M26 -> 1.4859065e-05 | D15: =IFERROR(+((B15-C15)/C15),"NA") -> 235834.58 | E15: The decrease in trade receivables turnover suggests a slower collection period for receivables, which might impact cash flow. | J15: Debt/Equity | K15: Equity | L15: =(+BS!C13) -> 199.74662 | M15: =(+BS!D13) -> 39.069193 | N15: 23830255 | V15: 23830255 | W15: =+M15-V15 -> -23830216
A16: Trade payables turnover | B16: =+L29/L30 -> 3.1466639 | C16: =+M29/M30 -> 1.4157269e-05 | D16: =IFERROR(+((B16-C16)/C16),"NA") -> 222263.9 | E16: The significant decrease in trade payables turnover indicates that the company is taking longer to pay its suppliers. | W16: =+M16-V16 -> 0
A17: Net capital turnover | B17: =+L33/L34 -> 67.637524 | C17: =+M33/M34 -> 0.00075631151 | D17: =IFERROR(+((B17-C17)/C17),"NA") -> 89429.775 | E17: The Variance is attributable due to change in working Capital - being as compared to PY 2022-23. | I17: 3 | J17: ROE | K17: Net profits after taxes-preference dividend | L17: =(+PL!D34) -> 19.609062 | M17: =(+PL!E34) -> -50.210905 | N17: 5357583.1 | P17: =(+M17-L17)/M17 -> 1.3905339 | V17: 5357583.1 | W17: =+M17-V17 -> -5357633.3
A18: Net profit | B18: =+L37/L38 -> 0.007810605 | C18: =+M37/M38 -> -0.033817367 | D18: =IFERROR(+((B18-C18)/C18),"NA") -> -1.2309643 | E18: The Variance is attributable due to change in Net profits/ returns. | K18: Average shareholders equity | L18: =+(L15+M15)/2 -> 119.40791 | M18: =+(M15+N15)/2 -> 11915147 | N18: 21151463 | V18: 21151463 | W18: =+M18-V18 -> -9236316.3
A19: Return on capital employed | B19: =+L41/L42 -> 1.0250233 | C19: =+M41/M42 -> 1.4294069 | D19: =IFERROR(+((B19-C19)/C19),"NA") -> -0.28290305 | E19: The Variance is attributable due to change in Operating profits/ returns. | W19: =+M19-V19 -> 0
A20: Return on Investment | B20: =+L48/L49 -> 0.09816968 | C20: =+M48/M49 -> -1.285179 | D20: =IFERROR(+((B20-C20)/C20),"NA") -> -1.076386 | E20: The Variance is attributable due to change in Net profits/ returns. | I20: 4 | J20: Inventory turnover ratio | W20: =+M20-V20 -> 0
K21: Cost of goods sold/sales | L21: 0 | M21: 0 | N21: 0 | V21: 0 | W21: =+M21-V21 -> 0
K22: Average inventory | L22: 0 | M22: 0 | N22: 0 | V22: 0 | W22: =+M22-V22 -> 0
A23: Note 21: Additional Notes | W23: =+M23-V23 -> 0
I24: 5 | J24: Trade receivables turnover ratio | W24: =+M24-V24 -> 0
A25: (i) Title deeds of Immovable Property not held in name of the Company | K25: Net credit sales | L25: =(+PL!D9) -> 2510.5688 | M25: =(+PL!E9) -> 1484.7668 | N25: 1.9984607e+08 | P25: =+(M25-L25)/M25 -> -0.69088423 | V25: 1.9984607e+08 | W25: =+M25-V25 -> -1.9984459e+08
A26: The company holds no immovable property in any other name. | K26: Average accounts receivable | L26: =(+(BS!C37+BS!D37)/2) -> 716.426 | M26: =+(BS!D37+N25)/2 -> 99923303 | N26: 55706979 | V26: 55706979 | W26: =+M26-V26 -> 44216324
W27: =+M27-V27 -> 0
A28: (ii) Where the Company has revalued its Property, Plant and Equipment, the company shall disclose as to whether the | I28: 6 | J28: Trade payables turnover ratio | W28: =+M28-V28 -> 0
A29: revaluation is based on the valuation by a registered valuer as defined under rule 2 of the Companies | K29: Net credit purchases | L29: =(+PL!D15) -> 2153.6675 | M29: =(+PL!E15) -> 1216.7373 | N29: 1.7188823e+08 | V29: 1.7188823e+08 | W29: =+M29-V29 -> -1.7188702e+08
A30: (Registered Valuers and Valuation) Rules,2017 | K30: Average trade payables | L30: =(+(BS!C20+BS!D20)/2) -> 684.42884 | M30: =+((BS!D20)+N29)/2 -> 85944349 | N30: 38755425 | V30: 38755425 | W30: =+M30-V30 -> 47188924
A31: There is no revaluation of Property Plant and Equipment | W31: =+M31-V31 -> 0
I32: 7 | J32: Net capital turnover ratio | W32: =+M32-V32 -> 0
A33: (iii) Following disclosures shall be made where Loans or Advances in the nature of loans are granted to promoters, directors, | K33: Net sales | L33: =+L25 -> 2510.5688 | M33: =+M25 -> 1484.7668 | N33: 1.9984607e+08 | V33: 1.9984607e+08 | W33: =+M33-V33 -> -1.9984459e+08
A34: KMPs and the related parties (as defined under Companies Act, 2013,) either severally or jointly with any other person, that are: | K34: Average working capital | L34: =+((L11-L12)+(M11-M12))/2 -> 37.117988 | M34: =+((M11-M12)+(N11-N12))/2 -> 1963168.4 | N34: 1064785.5 | V34: 1064784.5 | W34: =+M34-V34 -> 898383.84
A35: (a) repayable on demand or | W35: =+M35-V35 -> 0
A36: (b) without specifying any terms or period of repayment | I36: 8 | J36: Net profit ratio | W36: =+M36-V36 -> 0
A37: The company has not granted any loans or advances to promoters, directors, KMPs and the other related parties. | K37: Net profit | L37: =(+PL!D34) -> 19.609062 | M37: =(+PL!E34) -> -50.210905 | N37: 5357583.1 | V37: 5357583.1 | W37: =+M37-V37 -> -5357633.3
K38: Net sales | L38: =+L25 -> 2510.5688 | M38: =+M25 -> 1484.7668 | N38: 1.9984607e+08 | V38: 1.9984607e+08 | W38: =+M38-V38 -> -1.9984459e+08
A39: (iv) Capital-Work-in Progress (CWIP) / Intangible assets under development (ITAUD) | W39: =+M39-V39 -> 0
A40: 1.There is no Capital-Work-in Progress | I40: 9 | J40: ROCE | W40: =+M40-V40 -> 0
A41: 2.There is no Intangible assets under development | K41: Earnings before interest and taxes | L41: =+(PL!D9-PL!D15) -> 356.9013 | M41: =+(PL!E9-PL!E15) -> 268.02958 | N41: 27957840 | V41: 27957840 | W41: =+M41-V41 -> -27957572
K42: Capital employed | L42: =(+BS!C42-BS!C23) -> 348.18847 | M42: =(+BS!D42-BS!D23) -> 187.51105 | N42: 23830254 | V42: 23830252 | W42: =+M42-V42 -> -23830065
A43: (v) Details of Benami Property held | W43: =+M43-V43 -> 0
A44: The company holds no benami property under Benami transactions Prohibitions Act ( 1988) | J44: Earnings before interest and taxes | K44: Operating Profitt | W44: =+M44-V44 -> 0
J45: Capital employed: | K45: Total assets- Current liabilities | W45: =+M45-V45 -> 0
A46: (vi) Where the Company has borrowings from banks or financial institutions on the basis of security of current | W46: =+M46-V46 -> 0
A47: assets, it shall disclose the following:- | I47: 10 | J47: Return on Investment | W47: =+M47-V47 -> 0
A48: The Company has no borrowing from banks or financial institutions on the basis of security of current assets. | K48: Net profit | L48: =(+PL!D34) -> 19.609062 | M48: =(+PL!E34) -> -50.210905 | N48: 5357583.1 | V48: 5357583.1 | W48: =+M48-V48 -> -5357633.3
K49: Total investment | L49: =(+BS!C13) -> 199.74662 | M49: =(+BS!D13) -> 39.069193 | N49: 23830255 | V49: 23830255 | W49: =+M49-V49 -> -23830216
A50: (vii) Wilful Defaulter
A51: The company is not declared as a wilful defaulter by any bank or financial Institution or other lender.
A53: (viii) Registration of charges or satisfaction with Registrar of Companies
A54: The Company has not made any registration of charges with registrar of companies
A55: (ix) Compliance with number of layers of companies
A56: The company has complied with the number of layers prescribed under clause (87) of section 2 of the Act read with
A57: Companies (Restriction on number of Layers) Rules, 2017.
A59: (x) Compliance with approved Scheme(s) of Arrangements
A60: There are no scheme of arrangements for the company
A62: (xi) Utilisation of Borrowed funds and share premium:
A63: The company has not advanced or loaned or invested funds (either borrowed funds or share premium or any other sources or
A64: kind of funds) to any other person(s) or entity(ies), including foreign entities (Intermediaries).
... A71: The company has no borrowings from banks or any financial institutions.

Sheet Sub Sch - BS
A1: CARGO INTERNTIONAL INDIA PRIVATE LIMITED
A2: SUB SCHEDULE FOR THE YEAR END 31ST MARCH 2024
A3: Particulars | B3: =+'NOTE 4-8'!B5 -> As on | C3: =+'NOTE 4-8'!C5 -> As on
B4: 31st March, 2024 | C4: 31st March, 2023
A6: SS 1 : Expense Payable
A7: Audit Fee payable | B7: =SUMIF('TB 24-25'!$Q:$Q,$A7,'TB 24-25'!$P:$P)-SUMIF('TB 24-25'!$Q:$Q,$A7,'TB 24-25'!$O:$O) -> 7.25 | C7: =SUMIF('TB 24-25'!$Q:$Q,$A7,'TB 24-25'!$F:$F)-SUMIF('TB 24-25'!$Q:$Q,$A7,'TB 24-25'!$E:$E) -> 7.25 | E7: Audit Fee payable
A8: GST Audit Fees payable | B8: =SUMIF('TB 24-25'!$Q:$Q,$A8,'TB 24-25'!$P:$P)-SUMIF('TB 24-25'!$Q:$Q,$A8,'TB 24-25'!$O:$O) -> 0.9 | C8: =SUMIF('TB 24-25'!$Q:$Q,$A8,'TB 24-25'!$F:$F)-SUMIF('TB 24-25'!$Q:$Q,$A8,'TB 24-25'!$E:$E) -> 0.9 | E8: Tax audit 4 Yrs | F8: =125000*4 -> 500000
A9: Convenyance Payable | B9: =SUMIF('TB 24-25'!$Q:$Q,$A9,'TB 24-25'!$P:$P)-SUMIF('TB 24-25'!$Q:$Q,$A9,'TB 24-25'!$O:$O) -> 9.0385406 | C9: =SUMIF('TB 24-25'!$Q:$Q,$A9,'TB 24-25'!$F:$F)-SUMIF('TB 24-25'!$Q:$Q,$A9,'TB 24-25'!$E:$E) -> 1.9888337 | E9: FY 24-25 provision | F9: 225000
A10: Salary Payable | B10: =SUMIF('TB 24-25'!$Q:$Q,$A10,'TB 24-25'!$P:$P)-SUMIF('TB 24-25'!$Q:$Q,$A10,'TB 24-25'!$O:$O) -> 20.120702 | C10: =SUMIF('TB 24-25'!$Q:$Q,$A10,'TB 24-25'!$F:$F)-SUMIF('TB 24-25'!$Q:$Q,$A10,'TB 24-25'!$E:$E) -> 3.0494923
B12: =SUM(B7:B11) -> 37.309243 | C12: =SUM(C7:C11) -> 13.188326
A14: SS 2 : Statutory Dues payables
A15: Income tax payable | B15: =SUMIF('TB 24-25'!$Q:$Q,$A15,'TB 24-25'!$P:$P)-SUMIF('TB 24-25'!$Q:$Q,$A15,'TB 24-25'!$O:$O) -> 38.53278 | C15: =SUMIF('TB 24-25'!$Q:$Q,$A15,'TB 24-25'!$F:$F)-SUMIF('TB 24-25'!$Q:$Q,$A15,'TB 24-25'!$E:$E) -> 15.44634
A16: Krishi kalyan Cess Payable | B16: =SUMIF('TB 24-25'!$Q:$Q,$A16,'TB 24-25'!$P:$P)-SUMIF('TB 24-25'!$Q:$Q,$A16,'TB 24-25'!$O:$O) -> 0.8604877 | C16: =SUMIF('TB 24-25'!$Q:$Q,$A16,'TB 24-25'!$F:$F)-SUMIF('TB 24-25'!$Q:$Q,$A16,'TB 24-25'!$E:$E) -> 0.8604877 | E16: Old | F16: Duty Vat Account
A17: Professional Tax Payable | B17: =SUMIF('TB 24-25'!$Q:$Q,$A17,'TB 24-25'!$P:$P)-SUMIF('TB 24-25'!$Q:$Q,$A17,'TB 24-25'!$O:$O) -> 1.38835 | C17: =SUMIF('TB 24-25'!$Q:$Q,$A17,'TB 24-25'!$F:$F)-SUMIF('TB 24-25'!$Q:$Q,$A17,'TB 24-25'!$E:$E) -> 0.89539 | F17: Reimbursement Account
A18: Provident Fund Payables | B18: =SUMIF('TB 24-25'!$Q:$Q,$A18,'TB 24-25'!$P:$P)-SUMIF('TB 24-25'!$Q:$Q,$A18,'TB 24-25'!$O:$O) -> 0.3993337 | C18: =SUMIF('TB 24-25'!$Q:$Q,$A18,'TB 24-25'!$F:$F)-SUMIF('TB 24-25'!$Q:$Q,$A18,'TB 24-25'!$E:$E)-409/Deno -> 0.34616
A19: Service tax Payable | B19: =SUMIF('TB 24-25'!$Q:$Q,$A19,'TB 24-25'!$P:$P)-SUMIF('TB 24-25'!$Q:$Q,$A19,'TB 24-25'!$O:$O) -> 0 | C19: =SUMIF('TB 24-25'!$Q:$Q,$A19,'TB 24-25'!$F:$F)-SUMIF('TB 24-25'!$Q:$Q,$A19,'TB 24-25'!$E:$E) -> 0
A20: Swachh Bharath payable | B20: =SUMIF('TB 24-25'!$Q:$Q,$A20,'TB 24-25'!$P:$P)-SUMIF('TB 24-25'!$Q:$Q,$A20,'TB 24-25'!$O:$O) -> -0.5352727 | C20: =SUMIF('TB 24-25'!$Q:$Q,$A20,'TB 24-25'!$F:$F)-SUMIF('TB 24-25'!$Q:$Q,$A20,'TB 24-25'!$E:$E) -> -0.5352727 | E20: Old
A21: TDS Payables | B21: =SUMIF('TB 24-25'!$Q:$Q,$A21,'TB 24-25'!$P:$P)-SUMIF('TB 24-25'!$Q:$Q,$A21,'TB 24-25'!$O:$O) -> 3.6938996 | C21: =SUMIF('TB 24-25'!$Q:$Q,$A21,'TB 24-25'!$F:$F)-SUMIF('TB 24-25'!$Q:$Q,$A21,'TB 24-25'!$E:$E) -> 2.7981796
A22: Duty Vat Account | B22: =SUMIF('TB 24-25'!$Q:$Q,$A22,'TB 24-25'!$P:$P)-SUMIF('TB 24-25'!$Q:$Q,$A22,'TB 24-25'!$O:$O) -> -0.08577 | E22: need to check
A23: Reimbursement Account | B23: =SUMIF('TB 24-25'!$Q:$Q,$A23,'TB 24-25'!$P:$P)-SUMIF('TB 24-25'!$Q:$Q,$A23,'TB 24-25'!$O:$O) -> -0.03655
B25: =SUM(B15:B24) -> 44.217258 | C25: =SUM(C15:C24) -> 19.811285
A27: SS 3 : Cash and cash equivalents
A28: Cash in hand
A29: Cash in hand | B29: =SUMIF('TB 24-25'!$Q:$Q,$A29,'TB 24-25'!$O:$O)-SUMIF('TB 24-25'!$Q:$Q,$A29,'TB 24-25'!$P:$P) -> 0 | C29: =SUMIF('TB 24-25'!$Q:$Q,$A29,'TB 24-25'!$E:$E)-SUMIF('TB 24-25'!$Q:$Q,$A29,'TB 24-25'!$F:$F) -> 4.2197904
A30: Petty Cash | B30: =SUMIF('TB 24-25'!$Q:$Q,$A30,'TB 24-25'!$O:$O)-SUMIF('TB 24-25'!$Q:$Q,$A30,'TB 24-25'!$P:$P) -> 0.1629965 | C30: =SUMIF('TB 24-25'!$Q:$Q,$A30,'TB 24-25'!$E:$E)-SUMIF('TB 24-25'!$Q:$Q,$A30,'TB 24-25'!$F:$F) -> 0.0904988
B32: =SUM(B29:B31) -> 0.1629965 | C32: =SUM(C29:C31) -> 4.3102892
A34: Balance with bank
A35: Cash at Bank - Foreign Currency | B35: =SUMIF('TB 24-25'!$Q:$Q,$A35,'TB 24-25'!$O:$O)-SUMIF('TB 24-25'!$Q:$Q,$A35,'TB 24-25'!$P:$P) -> 2.4111149 | C35: =SUMIF('TB 24-25'!$Q:$Q,$A35,'TB 24-25'!$E:$E)-SUMIF('TB 24-25'!$Q:$Q,$A35,'TB 24-25'!$F:$F) -> 14.949516
A36: Cash at Bank - Local Currency | B36: =SUMIF('TB 24-25'!$Q:$Q,$A36,'TB 24-25'!$O:$O)-SUMIF('TB 24-25'!$Q:$Q,$A36,'TB 24-25'!$P:$P) -> 214.36133 | C36: =SUMIF('TB 24-25'!$Q:$Q,$A36,'TB 24-25'!$E:$E)-SUMIF('TB 24-25'!$Q:$Q,$A36,'TB 24-25'!$F:$F) -> 41.915891
B38: =SUM(B35:B37) -> 216.77245 | C38: =SUM(C35:C37) -> 56.865407
A40: SS 4 : GST Input tax credit
A41: GST - Input tax credit | B41: =SUMIF('TB 24-25'!$Q:$Q,$A41,'TB 24-25'!$O:$O)-SUMIF('TB 24-25'!$Q:$Q,$A41,'TB 24-25'!$P:$P) -> 321.0131 | C41: =SUMIF('TB 24-25'!$Q:$Q,$A41,'TB 24-25'!$E:$E)-SUMIF('TB 24-25'!$Q:$Q,$A41,'TB 24-25'!$F:$F) -> 72.83783
A42: GST payable | B42: =SUMIF('TB 24-25'!$Q:$Q,$A42,'TB 24-25'!$O:$O)-SUMIF('TB 24-25'!$Q:$Q,$A42,'TB 24-25'!$P:$P) -> -270.3624 | C42: =SUMIF('TB 24-25'!$Q:$Q,$A42,'TB 24-25'!$E:$E)-SUMIF('TB 24-25'!$Q:$Q,$A42,'TB 24-25'!$F:$F) -> 0
B44: =SUM(B41:B43) -> 50.6507 | C44: =SUM(C41:C43) -> 72.83783

Sheet Sub Sch - p&l
A1: CARGO INTERNTIONAL INDIA PRIVATE LIMITED
A2: SUB SCHEDULE FOR THE YEAR END 31ST MARCH 2024
A3: Particulars | B3: =+'NOTE 15-20'!B5 -> For Year Ended | C3: =+'NOTE 15-20'!C5 -> For Year Ended
B4: 45382 | C4: 45016
A6: SS 7 : Business Promotion Expense
A7: Advertising & Publicity | B7: =SUMIF('TB 24-25'!Q:Q,'Sub Sch - p&l'!A7,'TB 24-25'!O:O)-SUMIF('TB 24-25'!Q:Q,'Sub Sch - p&l'!A7,'TB 24-25'!P:P) -> 0.0192 | C7: =SUMIF('TB 24-25'!Q:Q,'Sub Sch - p&l'!A7,'TB 24-25'!E:E)-SUMIF('TB 24-25'!Q:Q,'Sub Sch - p&l'!A7,'TB 24-25'!F:F) -> 0.0192
A8: Business Promotion | B8: =SUMIF('TB 24-25'!Q:Q,'Sub Sch - p&l'!A8,'TB 24-25'!O:O)-SUMIF('TB 24-25'!Q:Q,'Sub Sch - p&l'!A8,'TB 24-25'!P:P) -> 12.10196 | C8: =SUMIF('TB 24-25'!Q:Q,'Sub Sch - p&l'!A8,'TB 24-25'!E:E)-SUMIF('TB 24-25'!Q:Q,'Sub Sch - p&l'!A8,'TB 24-25'!F:F) -> 1.91559 | D8: =+(C8-B8)/C8 -> -5.3176151
A9: Conference Expenses | B9: =SUMIF('TB 24-25'!Q:Q,'Sub Sch - p&l'!A9,'TB 24-25'!O:O)-SUMIF('TB 24-25'!Q:Q,'Sub Sch - p&l'!A9,'TB 24-25'!P:P) -> 1.2770291 | C9: =SUMIF('TB 24-25'!Q:Q,'Sub Sch - p&l'!A9,'TB 24-25'!E:E)-SUMIF('TB 24-25'!Q:Q,'Sub Sch - p&l'!A9,'TB 24-25'!F:F) -> 2.002785 | E9: =84.765*999 -> 84680.235 | F9: =B9-E9 -> -84678.958
A10: Entertainment Expenses | B10: =SUMIF('TB 24-25'!Q:Q,'Sub Sch - p&l'!A10,'TB 24-25'!O:O)-SUMIF('TB 24-25'!Q:Q,'Sub Sch - p&l'!A10,'TB 24-25'!P:P) -> 2.935021 | C10: =SUMIF('TB 24-25'!Q:Q,'Sub Sch - p&l'!A10,'TB 24-25'!E:E)-SUMIF('TB 24-25'!Q:Q,'Sub Sch - p&l'!A10,'TB 24-25'!F:F) -> 1.796328 | D10: =+(C10-B10)/C10 -> -0.63390038
B12: =SUM(B7:B11) -> 16.33321 | C12: =SUM(C7:C11) -> 5.733903
A14: SS 5 : Communication Expense
A15: Courier Expense | B15: =SUMIF('TB 24-25'!Q:Q,'Sub Sch - p&l'!A15,'TB 24-25'!O:O)-SUMIF('TB 24-25'!Q:Q,'Sub Sch - p&l'!A15,'TB 24-25'!P:P) -> 0.3227429 | C15: =SUMIF('TB 24-25'!Q:Q,'Sub Sch - p&l'!A15,'TB 24-25'!E:E)-SUMIF('TB 24-25'!Q:Q,'Sub Sch - p&l'!A15,'TB 24-25'!F:F) -> 0.3417769 | D15: =+(C15-B15)/C15 -> 0.0556913
A16: Internet Expense | B16: =SUMIF('TB 24-25'!Q:Q,'Sub Sch - p&l'!A16,'TB 24-25'!O:O)-SUMIF('TB 24-25'!Q:Q,'Sub Sch - p&l'!A16,'TB 24-25'!P:P) -> 9.224667 | C16: =SUMIF('TB 24-25'!Q:Q,'Sub Sch - p&l'!A16,'TB 24-25'!E:E)-SUMIF('TB 24-25'!Q:Q,'Sub Sch - p&l'!A16,'TB 24-25'!F:F) -> 7.4842797 | D16: =+(C16-B16)/C16 -> -0.23253905
A17: Mobile Expense | B17: =SUMIF('TB 24-25'!Q:Q,'Sub Sch - p&l'!A17,'TB 24-25'!O:O)-SUMIF('TB 24-25'!Q:Q,'Sub Sch - p&l'!A17,'TB 24-25'!P:P) -> 0.8838076 | C17: =SUMIF('TB 24-25'!Q:Q,'Sub Sch - p&l'!A17,'TB 24-25'!E:E)-SUMIF('TB 24-25'!Q:Q,'Sub Sch - p&l'!A17,'TB 24-25'!F:F) -> 1.1184246 | D17: =+(C17-B17)/C17 -> 0.20977453
A18: Telephone Expense | B18: =SUMIF('TB 24-25'!Q:Q,'Sub Sch - p&l'!A18,'TB 24-25'!O:O)-SUMIF('TB 24-25'!Q:Q,'Sub Sch - p&l'!A18,'TB 24-25'!P:P) -> 0.1731857 | C18: =SUMIF('TB 24-25'!Q:Q,'Sub Sch - p&l'!A18,'TB 24-25'!E:E)-SUMIF('TB 24-25'!Q:Q,'Sub Sch - p&l'!A18,'TB 24-25'!F:F) -> 0.19006 | D18: =+(C18-B18)/C18 -> 0.088784068
C19: =SUMIF('TB 24-25'!Q:Q,'Sub Sch - p&l'!A19,'TB 24-25'!E:E)-SUMIF('TB 24-25'!Q:Q,'Sub Sch - p&l'!A19,'TB 24-25'!F:F) -> 0
B20: =SUM(B15:B19) -> 10.604403 | C20: =SUM(C15:C19) -> 9.1345412
A22: SS 6 : Other Expense
A23: Budget Meeting Expenses | B23: =SUMIF('TB 24-25'!Q:Q,'Sub Sch - p&l'!A23,'TB 24-25'!O:O)-SUMIF('TB 24-25'!Q:Q,'Sub Sch - p&l'!A23,'TB 24-25'!P:P) -> 4.616668 | C23: =SUMIF('TB 24-25'!Q:Q,'Sub Sch - p&l'!A23,'TB 24-25'!E:E)-SUMIF('TB 24-25'!Q:Q,'Sub Sch - p&l'!A23,'TB 24-25'!F:F) -> 3.1053784 | D23: =+(C23-B23)/C23 -> -0.48666842
A24: ITC Write-off | B24: =SUMIF('TB 24-25'!Q:Q,'Sub Sch - p&l'!A24,'TB 24-25'!O:O)-SUMIF('TB 24-25'!Q:Q,'Sub Sch - p&l'!A24,'TB 24-25'!P:P) -> 0 | C24: =SUMIF('TB 24-25'!Q:Q,'Sub Sch - p&l'!A24,'TB 24-25'!E:E)-SUMIF('TB 24-25'!Q:Q,'Sub Sch - p&l'!A24,'TB 24-25'!F:F) -> 0
A25: Donation | B25: =SUMIF('TB 24-25'!Q:Q,'Sub Sch - p&l'!A25,'TB 24-25'!O:O)-SUMIF('TB 24-25'!Q:Q,'Sub Sch - p&l'!A25,'TB 24-25'!P:P) -> 0 | C25: =SUMIF('TB 24-25'!Q:Q,'Sub Sch - p&l'!A25,'TB 24-25'!E:E)-SUMIF('TB 24-25'!Q:Q,'Sub Sch - p&l'!A25,'TB 24-25'!F:F) -> 0 | D25: =+(C25-B25)/C25 -> #DIV/0!
A26: Festival Expenses | B26: =SUMIF('TB 24-25'!Q:Q,'Sub Sch - p&l'!A26,'TB 24-25'!O:O)-SUMIF('TB 24-25'!Q:Q,'Sub Sch - p&l'!A26,'TB 24-25'!P:P) -> 1.44763 | C26: =SUMIF('TB 24-25'!Q:Q,'Sub Sch - p&l'!A26,'TB 24-25'!E:E)-SUMIF('TB 24-25'!Q:Q,'Sub Sch - p&l'!A26,'TB 24-25'!F:F) -> 0.09255 | D26: =+(C26-B26)/C26 -> -14.641599
A27: Miscellaneous Expenses | B27: =SUMIF('TB 24-25'!Q:Q,'Sub Sch - p&l'!A27,'TB 24-25'!O:O)-SUMIF('TB 24-25'!Q:Q,'Sub Sch - p&l'!A27,'TB 24-25'!P:P) -> 1.7400626 | C27: =SUMIF('TB 24-25'!Q:Q,'Sub Sch - p&l'!A27,'TB 24-25'!E:E)-SUMIF('TB 24-25'!Q:Q,'Sub Sch - p&l'!A27,'TB 24-25'!F:F) -> 21.67729 | D27: =+(C27-B27)/C27 -> 0.91972878 | F27: Service Job cost - Explaination need to be provided
A28: Printing & Stationary | B28: =SUMIF('TB 24-25'!Q:Q,'Sub Sch - p&l'!A28,'TB 24-25'!O:O)-SUMIF('TB 24-25'!Q:Q,'Sub Sch - p&l'!A28,'TB 24-25'!P:P) -> 1.055016 | C28: =SUMIF('TB 24-25'!Q:Q,'Sub Sch - p&l'!A28,'TB 24-25'!E:E)-SUMIF('TB 24-25'!Q:Q,'Sub Sch - p&l'!A28,'TB 24-25'!F:F) -> 0.8365975 | D28: =+(C28-B28)/C28 -> -0.26107955
A29: Office Shifting Expense | B29: =SUMIF('TB 24-25'!Q:Q,'Sub Sch - p&l'!A29,'TB 24-25'!O:O)-SUMIF('TB 24-25'!Q:Q,'Sub Sch - p&l'!A29,'TB 24-25'!P:P) -> 0 | C29: =SUMIF('TB 24-25'!Q:Q,'Sub Sch - p&l'!A29,'TB 24-25'!E:E)-SUMIF('TB 24-25'!Q:Q,'Sub Sch - p&l'!A29,'TB 24-25'!F:F) -> 0.145 | D29: =+(C29-B29)/C29 -> 1 | F29: Bangalore office
A30: Subscription Charges | B30: =SUMIF('TB 24-25'!Q:Q,'Sub Sch - p&l'!A30,'TB 24-25'!O:O)-SUMIF('TB 24-25'!Q:Q,'Sub Sch - p&l'!A30,'TB 24-25'!P:P) -> 7.6455954 | C30: =SUMIF('TB 24-25'!Q:Q,'Sub Sch - p&l'!A30,'TB 24-25'!E:E)-SUMIF('TB 24-25'!Q:Q,'Sub Sch - p&l'!A30,'TB 24-25'!F:F) -> 6.6989031 | D30: =+(C30-B30)/C30 -> -0.14132049
A31: Utility Expenses | B31: =SUMIF('TB 24-25'!Q:Q,'Sub Sch - p&l'!A31,'TB 24-25'!O:O)-SUMIF('TB 24-25'!Q:Q,'Sub Sch - p&l'!A31,'TB 24-25'!P:P) -> 2.5062177 | C31: =SUMIF('TB 24-25'!Q:Q,'Sub Sch - p&l'!A31,'TB 24-25'!E:E)-SUMIF('TB 24-25'!Q:Q,'Sub Sch - p&l'!A31,'TB 24-25'!F:F) -> 2.8265646 | D31: =+(C31-B31)/C31 -> 0.11333436
A32: Training Expenses | B32: =SUMIF('TB 24-25'!Q:Q,'Sub Sch - p&l'!A32,'TB 24-25'!O:O)-SUMIF('TB 24-25'!Q:Q,'Sub Sch - p&l'!A32,'TB 24-25'!P:P) -> 0.33 | C32: =SUMIF('TB 24-25'!Q:Q,'Sub Sch - p&l'!A32,'TB 24-25'!E:E)-SUMIF('TB 24-25'!Q:Q,'Sub Sch - p&l'!A32,'TB 24-25'!F:F) -> 0 | D32: =+(C32-B32)/C32 -> #DIV/0!
A33: Rounding off balance | B33: =SUMIF('TB 24-25'!Q:Q,'Sub Sch - p&l'!A33,'TB 24-25'!O:O)-SUMIF('TB 24-25'!Q:Q,'Sub Sch - p&l'!A33,'TB 24-25'!P:P) -> 0.0082776 | C33: =SUMIF('TB 24-25'!Q:Q,'Sub Sch - p&l'!A33,'TB 24-25'!E:E)-SUMIF('TB 24-25'!Q:Q,'Sub Sch - p&l'!A33,'TB 24-25'!F:F) -> 0.0004051 | D33: =+(C33-B33)/C33 -> -19.433473
B35: =SUM(B23:B34) -> 19.349467 | C35: =SUM(C23:C34) -> 35.382689
A37: SS 7 : Professional Charges
A38: GST Audit Fee | B38: =SUMIF('TB 24-25'!Q:Q,'Sub Sch - p&l'!A38,'TB 24-25'!O:O)-SUMIF('TB 24-25'!Q:Q,'Sub Sch - p&l'!A38,'TB 24-25'!P:P) -> 0 | C38: =SUMIF('TB 24-25'!Q:Q,'Sub Sch - p&l'!A38,'TB 24-25'!E:E)-SUMIF('TB 24-25'!Q:Q,'Sub Sch - p&l'!A38,'TB 24-25'!F:F) -> 0.9
A39: Legal Fees | B39: =SUMIF('TB 24-25'!Q:Q,'Sub Sch - p&l'!A39,'TB 24-25'!O:O)-SUMIF('TB 24-25'!Q:Q,'Sub Sch - p&l'!A39,'TB 24-25'!P:P) -> 14.316 | C39: =SUMIF('TB 24-25'!Q:Q,'Sub Sch - p&l'!A39,'TB 24-25'!E:E)-SUMIF('TB 24-25'!Q:Q,'Sub Sch - p&l'!A39,'TB 24-25'!F:F) -> 9.237 | D39: =+(B39-C39)/C39 -> 0.54985385
A40: Retainer/ Professional fee | B40: =SUMIF('TB 24-25'!Q:Q,'Sub Sch - p&l'!A40,'TB 24-25'!O:O)-SUMIF('TB 24-25'!Q:Q,'Sub Sch - p&l'!A40,'TB 24-25'!P:P) -> 0.3 | C40: =SUMIF('TB 24-25'!Q:Q,'Sub Sch - p&l'!A40,'TB 24-25'!E:E)-SUMIF('TB 24-25'!Q:Q,'Sub Sch - p&l'!A40,'TB 24-25'!F:F) -> 0
A41: Statutory Expenses | B41: =SUMIF('TB 24-25'!Q:Q,'Sub Sch - p&l'!A41,'TB 24-25'!O:O)-SUMIF('TB 24-25'!Q:Q,'Sub Sch - p&l'!A41,'TB 24-25'!P:P) -> 5.3837089 | C41: =SUMIF('TB 24-25'!Q:Q,'Sub Sch - p&l'!A41,'TB 24-25'!E:E)-SUMIF('TB 24-25'!Q:Q,'Sub Sch - p&l'!A41,'TB 24-25'!F:F) -> 8.2554
B43: =SUM(B38:B42) -> 19.999709 | C43: =SUM(C38:C42) -> 18.3924
A46: SS 8 : Rent
A47: Office Rent | B47: =SUMIF('TB 24-25'!Q:Q,'Sub Sch - p&l'!A47,'TB 24-25'!O:O)-SUMIF('TB 24-25'!Q:Q,'Sub Sch - p&l'!A47,'TB 24-25'!P:P) -> 18.76065 | C47: =SUMIF('TB 24-25'!Q:Q,'Sub Sch - p&l'!A47,'TB 24-25'!E:E)-SUMIF('TB 24-25'!Q:Q,'Sub Sch - p&l'!A47,'TB 24-25'!F:F) -> 23.73275 | D47: =+(C47-B47)/C47 -> 0.20950374
A48: Utility Rent | B48: =SUMIF('TB 24-25'!Q:Q,'Sub Sch - p&l'!A48,'TB 24-25'!O:O)-SUMIF('TB 24-25'!Q:Q,'Sub Sch - p&l'!A48,'TB 24-25'!P:P) -> 0.48 | C48: =SUMIF('TB 24-25'!Q:Q,'Sub Sch - p&l'!A48,'TB 24-25'!E:E)-SUMIF('TB 24-25'!Q:Q,'Sub Sch - p&l'!A48,'TB 24-25'!F:F) -> 0.48
A49: GUEST HOUSE RENT | B49: =SUMIF('TB 24-25'!Q:Q,'Sub Sch - p&l'!A49,'TB 24-25'!O:O)-SUMIF('TB 24-25'!Q:Q,'Sub Sch - p&l'!A49,'TB 24-25'!P:P) -> 2.11 | C49: =SUMIF('TB 24-25'!Q:Q,'Sub Sch - p&l'!A49,'TB 24-25'!E:E)-SUMIF('TB 24-25'!Q:Q,'Sub Sch - p&l'!A49,'TB 24-25'!F:F) -> 1.05
B51: =SUM(B47:B50) -> 21.35065 | C51: =SUM(C47:C50) -> 25.26275
A53: SS 9 : Repairs and Maintenance
A54: Repairs & Maintenance for computers hardware | B54: =SUMIF('TB 24-25'!Q:Q,'Sub Sch - p&l'!A54,'TB 24-25'!O:O)-SUMIF('TB 24-25'!Q:Q,'Sub Sch - p&l'!A54,'TB 24-25'!P:P) -> 0.781322 | C54: =SUMIF('TB 24-25'!Q:Q,'Sub Sch - p&l'!A54,'TB 24-25'!E:E)-SUMIF('TB 24-25'!Q:Q,'Sub Sch - p&l'!A54,'TB 24-25'!F:F) -> 0.3137738
A55: Repairs & Maintenance for computers software | B55: =SUMIF('TB 24-25'!Q:Q,'Sub Sch - p&l'!A55,'TB 24-25'!O:O)-SUMIF('TB 24-25'!Q:Q,'Sub Sch - p&l'!A55,'TB 24-25'!P:P) -> 0.3400847 | C55: =SUMIF('TB 24-25'!Q:Q,'Sub Sch - p&l'!A55,'TB 24-25'!E:E)-SUMIF('TB 24-25'!Q:Q,'Sub Sch - p&l'!A55,'TB 24-25'!F:F) -> 0.0460848
A56: Repairs & Maintenance for office | B56: =SUMIF('TB 24-25'!Q:Q,'Sub Sch - p&l'!A56,'TB 24-25'!O:O)-SUMIF('TB 24-25'!Q:Q,'Sub Sch - p&l'!A56,'TB 24-25'!P:P) -> 4.7215228 | C56: =SUMIF('TB 24-25'!Q:Q,'Sub Sch - p&l'!A56,'TB 24-25'!E:E)-SUMIF('TB 24-25'!Q:Q,'Sub Sch - p&l'!A56,'TB 24-25'!F:F) -> 2.7589
A57: Repairs & Maintenance for office equipments | B57: =SUMIF('TB 24-25'!Q:Q,'Sub Sch - p&l'!A57,'TB 24-25'!O:O)-SUMIF('TB 24-25'!Q:Q,'Sub Sch - p&l'!A57,'TB 24-25'!P:P) -> 0.25245 | C57: =SUMIF('TB 24-25'!Q:Q,'Sub Sch - p&l'!A57,'TB 24-25'!E:E)-SUMIF('TB 24-25'!Q:Q,'Sub Sch - p&l'!A57,'TB 24-25'!F:F) -> 0.2397
A58: Repairs & Maintenance for vehicles | B58: =SUMIF('TB 24-25'!Q:Q,'Sub Sch - p&l'!A58,'TB 24-25'!O:O)-SUMIF('TB 24-25'!Q:Q,'Sub Sch - p&l'!A58,'TB 24-25'!P:P) -> 0 | C58: =SUMIF('TB 24-25'!Q:Q,'Sub Sch - p&l'!A58,'TB 24-25'!E:E)-SUMIF('TB 24-25'!Q:Q,'Sub Sch - p&l'!A58,'TB 24-25'!F:F) -> 0
B60: =SUM(B54:B59) -> 6.0953795 | C60: =SUM(C54:C59) -> 3.3584586
A62: SS 10 : Travelling Expense
A63: Foreign Travel | B63: =SUMIF('TB 24-25'!Q:Q,'Sub Sch - p&l'!A63,'TB 24-25'!O:O)-SUMIF('TB 24-25'!Q:Q,'Sub Sch - p&l'!A63,'TB 24-25'!P:P) -> 21.029521 | C63: =SUMIF('TB 24-25'!Q:Q,'Sub Sch - p&l'!A63,'TB 24-25'!E:E)-SUMIF('TB 24-25'!Q:Q,'Sub Sch - p&l'!A63,'TB 24-25'!F:F) -> 13.128556
A64: Local Travel | B64: =SUMIF('TB 24-25'!Q:Q,'Sub Sch - p&l'!A64,'TB 24-25'!O:O)-SUMIF('TB 24-25'!Q:Q,'Sub Sch - p&l'!A64,'TB 24-25'!P:P) -> 0.048 | C64: =SUMIF('TB 24-25'!Q:Q,'Sub Sch - p&l'!A64,'TB 24-25'!E:E)-SUMIF('TB 24-25'!Q:Q,'Sub Sch - p&l'!A64,'TB 24-25'!F:F) -> 0.033
A65: Petrol Charges | B65: =SUMIF('TB 24-25'!Q:Q,'Sub Sch - p&l'!A65,'TB 24-25'!O:O)-SUMIF('TB 24-25'!Q:Q,'Sub Sch - p&l'!A65,'TB 24-25'!P:P) -> 2.1083146 | C65: =SUMIF('TB 24-25'!Q:Q,'Sub Sch - p&l'!A65,'TB 24-25'!E:E)-SUMIF('TB 24-25'!Q:Q,'Sub Sch - p&l'!A65,'TB 24-25'!F:F) -> 2.5737329
B67: =SUM(B63:B66) -> 23.185836 | C67: =SUM(C63:C66) -> 15.735289

Sheet Sub-Schedule
A1: Advance Paid/Received | B1: Closing Balance as of FY 2024-25 | D1: Closing Balance as of FY 2023-24
A2: Particulars | B2: Debit Rs. | C2: Credit Rs. | D2: Debit Rs. | E2: Credit Rs.
A3: Advance From Debtors
A4: CARGO INTERNATIONAL (INDIA) PRIVATE LTD | B4: 0 | C4: 1750 | D4: 0 | E4: 1750 | F4: RPT | G4: Non current
A5: CIL Dubai | B5: 0 | C5: 10067831 | D5: 0 | E5: 10067831 | F5: RPT | G5: Non current
A6: CARGO INTERNATIONAL LTD | B6: 0 | C6: 5866971.3 | D6: 0 | E6: 5866971.3 | F6: RPT | G6: Non current
A7: CARGO INTERNATIONAL (INDIA) PRIVATE LTD | B7: 0 | C7: 110628 | D7: 0 | E7: 110628 | F7: RPT | G7: Non current
A8: ADVANCE TO CREDITORS
A9: CARGO INTERNATIONAL LTD | B9: 214646.99 | C9: 0 | D9: 214646.99 | E9: 0 | F9: RPT | G9: Non current
A10: CATHAY PACIFIC | B10: 0.3 | C10: 0 | D10: 0.3 | E10: 0 | F10: Others | G10: Current
A11: CMA CGM | B11: 198625.57 | C11: 0 | D11: 198625.57 | E11: 0 | F11: Others | G11: Current
A12: CONTAINER CORPORATION OF INDIA LIMITED | B12: 193519.1 | C12: 0 | D12: 193519.1 | E12: 0 | F12: Others | G12: Current
A13: MAERSK | B13: 31739.96 | C13: 0 | D13: 31739.96 | E13: 0 | F13: Others | G13: Current
A14: CARGO INTERNATIONAL (INDIA) PRIVATE LTD | B14: 988348 | C14: 0 | D14: 988348 | E14: 0 | F14: RPT | G14: Non current
A15: ASHA LUBE SOLUTIONS PVT LTD | B15: 0.18 | C15: 0 | D15: 0 | E15: 1506.35 | F15: Others | G15: Current
A16: BELL PRINTERS (P) LTD | B16: 0 | C16: 9732 | D16: 0 | E16: 9732 | F16: Others | G16: Current
A17: RL FINE CHEM PVT LTD | B17: 0 | C17: 19072 | D17: 0 | E17: 19072 | F17: Others | G17: Current
A18: AURONATURE | B18: 0 | C18: 33 | D18: 0 | E18: 33 | F18: Others | G18: Current
A19: EXPRESS CARGO MOVERS | B19: 0 | C19: 5220 | D19: 0 | E19: 5220 | F19: Others | G19: Current
A20: SRI VBL ASSOCIATES | B20: 0 | C20: 270 | D20: 0 | E20: 270 | F20: Others | G20: Current
... A32: COGENT EXPORTS | B32: 236 | C32: 0 | D32: 0 | E32: 0 | F32: Others | G32: Current
A34: TOTAL | B34: =SUBTOTAL(9,B4:B33) -> 1627116.1 | C34: =SUBTOTAL(9,C4:C33) -> 16474587 | D34: =SUBTOTAL(9,D4:D33) -> 1626879.9 | E34: =SUBTOTAL(9,E4:E33) -> 16094185
C35: =+B34-C34 -> -14847471 | E35: =+D34-E34 -> -14467305
C38: =+C39-B39 -> 0 | E38: =+E39-D39 -> 0 | G38: =+G39-F39 -> 0
B39: =+_xlfn.AGGREGATE(9,0,B42:B42) -> 0 | C39: =+_xlfn.AGGREGATE(9,0,C42:C42) -> 0 | D39: =+_xlfn.AGGREGATE(9,0,D42:D42) -> 0 | E39: =+_xlfn.AGGREGATE(9,0,E42:E42) -> 0 | F39: =+_xlfn.AGGREGATE(9,0,F42:F42) -> 0 | G39: =+_xlfn.AGGREGATE(9,0,G42:G42) -> 0
A40: Provision for Operation | B40: Closing Balance as of FY 2023-24 | D40: During the yr Transaction/Audit entry | F40: Closing Balance as of FY 2024-25
A41: Particulars | B41: Debit Rs. | C41: Credit Rs. | D41: Debit Rs. | E41: Credit Rs. | F41: Debit Rs. | G41: Credit Rs.
A42: Creditors From Provisions GL
A44: Note : Balance in Provision operation has been closed and transferred to reserves

Sheet IT Dep
A2: CARGO INTERNATIONAL (INDIA) PRIVATE LIMITED
A3: Schedule of depreciation as per Income Tax Act 1961.
A5: NAME OF THE ASSETS | B5: Op WDV as on 01.04.2024 | C5: Addition | E5: Deletions | F5: As on 31.03.2025 | G5: Rate of Dep | H5: Dep. Amt | I5: WDV As on 31.03.2025
C6: > 180 | D6: < 180
A8: Mobiles | B8: 131272 | C8: 0 | D8: 0 | E8: 0 | F8: =B8+C8+D8-E8 -> 131272 | G8: 0.15 | H8: =ROUND(((B8+C8)*G8)+(D8*G8/2),0) -> 19691 | I8: =F8-H8 -> 111581
A10: Computers | B10: 106903.59 | C10: 32966.11 | D10: 0 | E10: 0 | F10: =B10+C10+D10-E10 -> 139869.7 | G10: 0.4 | H10: =ROUND(((B10+C10)*G10)+(D10*G10/2),0) -> 55948 | I10: =F10-H10 -> 83921.7
A12: Furniture and fittings | B12: 529371.39 | C12: 0 | D12: 0 | E12: 0 | F12: =B12+C12+D12-E12 -> 529371.39 | G12: 0.1 | H12: =ROUND(((B12+C12)*G12)+(D12*G12/2),0) -> 52937 | I12: =F12-H12 -> 476434.39
A14: Motor Car | B14: 0 | C14: 0 | D14: 0 | E14: 0 | F14: =B14+C14+D14-E14 -> 0 | G14: 0.15 | H14: 0 | I14: =F14-H14 -> 0
A16: Interior decoration | B16: 1931015 | C16: 0 | D16: 0 | E16: 0 | F16: =B16+C16+D16-E16 -> 1931015 | G16: 0.1 | H16: =ROUND(((B16+C16)*G16)+(D16*G16/2),0) -> 193102 | I16: =F16-H16 -> 1737913
A18: Electrical equipments | B18: 196279 | C18: 56000 | D18: 0 | E18: 0 | F18: =B18+C18+D18-E18 -> 252279 | G18: 0.15 | H18: =ROUND(((B18+C18)*G18)+(D18*G18/2),0) -> 37842 | I18: =F18-H18 -> 214437
A20: Office Equipment | B20: 301679.6 | C20: 0 | D20: 0 | E20: 0 | F20: =B20+C20+D20-E20 -> 301679.6 | G20: 0.15 | H20: =ROUND(((B20+C20)*G20)+(D20*G20/2),0) -> 45252 | I20: =F20-H20 -> 256427.6
A22: TOTAL | B22: =SUM(B8:B21) -> 3196520.6 | C22: =SUM(C8:C21) -> 88966.11 | D22: =SUM(D8:D21) -> 0 | E22: =SUM(E8:E21) -> 0 | F22: =SUM(F8:F21) -> 3285486.7 | G22: =SUM(G8:G21) -> 1.2 | H22: =SUM(H8:H21) -> 404772 | I22: =SUM(I8:I21) -> 2880714.7
A24: Total Addition as per IT Dep | C24: =+C22+D22 -> 88966.11 | E24: =+E22 -> 0
A25: Total Addition as per CA Dep | C25: =+'Note 9'!C20 -> 0.8896611 | E25: =+'Note 9'!D20 -> 0
C26: =+C24-C25 -> 88965.22 | E26: =+E24-E25 -> 0

Sheet Deffered Tax
A2: =+'IT Dep'!A2:I2 -> CARGO INTERNATIONAL (INDIA) PRIVATE LIMITED | F2: =+A2 -> CARGO INTERNATIONAL (INDIA) PRIVATE LIMITED
A3: Schedule for Deffered Tax Calculation | F3: =+A3 -> Schedule for Deffered Tax Calculation
A4: P&L Approach | F4: BL Approach
F7: Particulars | G7: Amount of expenses | H7: Deffered Tax Amount | I7: DTA/DTL
F9: Opening balance as on 01.04.2024 | H9: =634957.698/Deno -> 6.349577 | I9: DTA
F11: on account of Depreciation
F12: WDV as per Income Tax Act | G12: =+'IT Dep'!I22/Deno -> 28.807147
F13: WDV as per Companies Act | G13: =+'Note 9'!J20 -> 7.3320925 | H13: =(G12-G13)*27.82% -> 5.9743601 | I13: DTA
F16: on account of expenses allowed on payable basis
F17: Provision as per IT | G17: 0
F18: Provision as per CA | G18: 0 | H18: =(G17-G18)*27.82% -> 0
I19: DTA
F21: Closing balance as on 31.03.25 | H21: =+H13+H18 -> 5.9743601
F23: Provision to be reversed for the year | H23: =+H21-H9 -> -0.37521685 | I23: DTI

Sheet Statement of Income
A1: =+BS!A1 -> CARGO INTERNATIONAL (INDIA) PRIVATE LIMITED
A2: =+BS!A4 -> Old No.7 / New No.13, First Floor, First Cross Street, Trustpuram, Kodambakkam, Chennai - 600024, India
A4: D.O.I | B4: 40430 | D4: AY | E4: 2024 - 25
A5: E MAIL ID | B5: accounts@cargo-int.com | D5: FY | E5: 2023 - 24
A6: PH NO | B6: 9600100917 | D6: PAN NO | E6: AAECC1295N
A8: Statement of Income
A10: INCOME FROM BUSINESS
B12: Profit as per Profit and loss account | E12: =+PL!D29*Deno -> 2653190.3
A14: Add: | B14: Disallowed Expenses
B15: a) Depreciation as per Companies Act | D15: =+'Note 9'!G20*Deno -> 269898.93
B16: b) ICDS Unrealised Forex
B17: c) PT Disallowances
B18: d) PF Disallowances
B19: e) Expenses Disallowed
B20: i) Liabilities Writeback/Writeoff as expenses | D20: 0
B21: ii) Exceptional items/extra-ordinary items | D21: 0
D22: 0 | E22: =+SUM(D15:D22) -> 269898.93
E24: =+SUM(E12:E22) -> 2923089.3
A26: Less: | B26: Allowable Expenses
B27: Depreciation as per Income Tax Act | D27: =+'IT Dep'!H22 -> 404772 | E27: =-SUM(D26:D27) -> -404772
B29: Business income | E29: =SUM(E24:E27) -> 2518317.3
A31: Less: | B31: Business loss carried forward from earlier year | E31: 0
B32: set off current year
A34: TAXABLE INCOME | E34: =E29-E31 -> 2518317.3
B36: Tax on normal slab @ 25% | D36: (A) | E36: =E34*25% -> 629579.31
B38: Tax payable under section 115JB | D38: (B) | E38: =+D89 -> 413898 | G38: Calculation for the Interest under 234B & C
I39: 45382
B40: Tax under normal computation = higher of | D40: ( A ) or ( B ) | E40: =+MAX(E36,E38) -> 629579.31 | H40: 234B
A41: Add: | B41: Surcharge 7% | E41: =IF(E29>10000000,E40*7%,0) -> 0 | G41: 55402.98 | H41: Total Tax Liability | I41: =+E44 -> 654762.49
E42: =SUM(E40:E41) -> 629579.31 | G42: 609432.78 | H42: Less TDS | I42: =+C47 -> 3660953
A43: Add: | B43: Health and Education cess | E43: =E42*4% -> 25183.173 | G43: 633810.09 | I43: =+I41-I42 -> -3006190.5
E44: =SUM(E42:E43) -> 654762.49 | G44: 654762.49 | H44: 90% of the Tax | I44: =+I43*90% -> -2705571.5
G45: =G43-G44 -> -20952.4 | H45: Advance Tax Paid | I45: =+F29 -> 0
A46: Less: | B46: Advance Tax | C46: 0 | H46: Difference | I46: =I43-I45 -> -3006190.5
B47: Tax deducted at source | C47: 3660953 | E47: =SUM(C46:C47) -> 3660953 | F47: As on 25-09-2025 | H47: Interest | I47: =I46*1%*(ROUND(((EOMONTH(TODAY(),0)-I39)/365)*12,0)) -> -601238.11
E48: =E44-E47 -> -3006190.5
A50: Add: | B50: Interest u/s 234 A | C50: 0 | H50: 234C | J50: Actual Paid | K50: Difference | L50: Interest
B51: Interest u/s 234 B | C51: =+IF(E48<0,0,I47) -> 0 | H51: Total Tax Liability | I51: =+E44-C47 -> -3006190.5 | J51: 0 | K51: 0
B52: Interest u/s 234 C | C52: =+IF(E48<0,0,L56) -> 0 | E52: =+SUM(C50:C52) -> 0 | H52: 15% upto 15.06.2020 | I52: =+ROUND(I51*15%,0) -> -450929 | J52: 0 | K52: =+I52-J52 -> -450929 | L52: =+ROUND(K52*1%*3,0) -> -13528
H53: 45% upto 15.09.2020 | I53: =+ROUND(I51*45%,0) -> -1352786 | J53: 0 | K53: =+I53-J53 -> -1352786 | L53: =+ROUND(K53*1%*3,0) -> -40584
B54: Tax Payable/(Refund) | E54: =ROUND(E48+E52,-1) -> -3006190 | H54: 75% Upto 15.12.2020 | I54: =+ROUND(I51*75%,0) -> -2254643 | J54: 0 | K54: =+I54-J54 -> -2254643 | L54: =+ROUND(K54*1%*3,0) -> -67639
H55: 100% up to 15.03.2021 | I55: =+I51 -> -3006190.5 | J55: =+F29 -> 0 | K55: =+I55-J55 -> -3006190.5 | L55: =+ROUND(K55*1%*1,0) -> -30062
H56: Total Interest | L56: =ROUND(SUM(L52:L55),0) -> -151813
A58: Computation of Book Profit as per Sec. 115JB | C58: Amount in Rs.
A60: Net Profit as per Profit & Loss Account before tax | D60: =+E12 -> 2653190.3
A62: Add : -
A63: i. | B63: Income Tax Paid or Payble | C63: 0
A64: ii. | B64: Amount carried to reserves | C64: 0
A65: iii. | B65: Provisions for uncertain liabilities | C65: 0
A66: iv. | B66: Provisions for losses of Subsidiary companies | C66: 0
A67: v. | B67: Dividends paid or proposed | C67: 0
A68: vi. | B68: Expenditure relatable to any income to which any of the | C68: 0
B69: Sections 10/10A/10B/11/12 applies | C69: 0
A70: vii. | B70: Depriciation debited to P&L A/C (Normal & Revaluation) | C70: =+'Note 9'!G20*10^5 -> 269898.93
A71: viii. | B71: Deffered Tax Liability | C71: 0
A72: ix. | B72: Value of Revaluation of Asset Which effects the Rev Reserve | C72: 0
A73: x. | B73: Income/Loss In the case of units in Sec 47(xvii) | C73: 0
D74: =SUM(C63:C73) -> 269898.93
A75: Less:-
A76: i. | B76: Amount withdrawn from reserves or provisions | C76: 0
A77: ii. | B77: Any income to which any of the Sections 10/10A/10B/11/12 applies | C77: 0
A78: iii. | B78: Depriciation debited to P&L A/C (Normal) | C78: =+C70 -> 269898.93
A79: iv. | B79: Withdrawn from Revaluation Reserve Credited to P&L A/c | C79: 0
A80: v. | B80: Loss brought forward or unabsorbed depriciation, whichever is less | C80: 0
A81: vi. | B81: Amount of deduction u/s 80HHC ,HHE,HHF | C81: 0
A82: vii. | B82: Profit of Sick Industrial Unit | C82: 0
A83: viii. | B83: Deffered Tax Asset | C83: 0
A84: ix. | B84: Income/Loss In the case of units in Sec 47(xvii) | C84: 0
D85: =SUM(C76:C84) -> 269898.93
B88: Book profit as per Section 115JB | C88: =D60+D74-D85 -> 2653190.3
B89: 15 % of Book Profit u/s 115JB | D89: =ROUND(IF(C88>0,15.6%*C88,0),0) -> 413898
