Workbook
Name Deno: 'Master data'!$B$2

Sheet Master data
A2: Ones | B2: =+SUMIF(A4:A10,A2,B4:B10) -> 1 | C2: =+Deno -> 1
A4: Millions | B4: 1000000
A5: Lakhs | B5: 100000
A6: Ten Thousands | B6: 10000
A7: Thousands | B7: 1000
A8: Hundreds | B8: 100
A9: Tens | B9: 10
A10: Ones | B10: 1

Sheet Sheet1
A2: As per RBI Prevailing Rates
A3: Date | B3: Currency | C3: Rate/ INR
A4: 45747 | B4: USD | C4: 85.424
A5: 45747 | B5: EUR | C5: 92.415
A6: 45747 | B6: GBP | C6: 110.53

Sheet Audit entry
B2: Audit Entry for FY 2025-26 | E2: =+D3-E3 -> 0
D3: =+SUM(D5:D1048576) -> 2880221.6 | E3: =+SUM(E5:E1048576) -> 2880221.6
B4: SI no | C4: Particulars | D4: Debit | E4: Credit | F4: Remarks | M4: Check
M5: Income Tax payable | N5: ='Statement of Income'!E44 -> 0 | O5: =E135 -> 3.4924597e-10 | P5: =N5-O5 -> -3.4924597e-10
B6: 1 | C6: PREPAID INSURANCES | D6: =K8 -> 180753.41 | G6: Insurance Amount | H6: Assest break ups | K6: 433808.19 | M6: TDS Receivables | N6: ='Statement of Income'!E47 -> 3660953 | O6: ='TB 25-26'!I62 -> 3434574.7 | P6: =N6-O6 -> 226378.33
C7: INSURANCE. | E7: =D6 -> 180753.41 | G7: Prepaid Months | H7: 44109 | I7: NETWORK CHSING PURCHSED FOR MAA NEW OFFICE | J7: 2928 | K7: 5
C8: (Marine Insurance of Rs.4,33,808.19 for the period 30th August 2025 to 29th August 2026) | G8: Prepaid Amount | H8: 44119 | I8: AC INSTALATION CHARGES | J8: 1500 | K8: =K6*K7/12 -> 180753.41
B10: 2 | C10: PREPAID SUBSCRIPTION | D10: =K12 -> 59381 | G10: Membership Amount | H10: 44119 | I10: PLUG - INR 60 1/2" NUTS - INR 150 ANGLR FLANZ - INR 90 | J10: 400 | K10: 296905
C11: SUBSCRIPTION & MEMBERSHIP | E11: =D10 -> 59381 | G11: Prepaid days | H11: 44119 | I11: NETWORKING ACCESSORIES | J11: 1684 | K11: =30+31+12 -> 73
C12: (WCA USA, INC.- Lognet Global Annual Membership Fees of Rs. 2,96,905 for the Period June 13, 2025 to June 13, 2026) | G12: Prepaid Amount | H12: 44119 | I12: AC INSTALATION CHARGES | J12: 1500 | K12: =K10*K11/365 -> 59381
H13: 44989 | I13: Stablizer FOR AC | J13: 1550
B14: 3 | C14: INSURANCE. | D14: 130788.23
C15: PREPAID INSURANCES | E15: =D14 -> 130788.23 | H15: 44032 | J15: 4287.05
C16: (Last year Prepaid Expenses brought forward as Current year Expenses) | H16: 44119 | I16: STABLIZER | J16: 1100
H17: 44124 | I17: Stabiliser | J17: 2400
B18: 4 | C18: DEPRECIATION ON COMPUTER | D18: 90412 | H18: 44965 | I18: AIRTEL DONGLE | J18: 2200
C19: DEPRECIATION OFFICE EQUIPMENTS | D19: 19308 | H19: 44983 | I19: Window Curtain | J19: 2500
C20: DEPRECIATION FURNITURE & FIXTURES | D20: 32819 | H20: 44162 | J20: 960
C21: DEPRECIATION ELECTRICAL INSTALLATIONS | D21: 22039
C22: DEPRECIATION ON INTERIOR DECORATION | D22: 99731
C23: COMPUTER | E23: =+D18 -> 90412
C24: OFFICE EQUIPMENTS | E24: =+D19 -> 19308
C25: FURNITURE & FIXTURES | E25: =+D20 -> 32819
C26: ELECTRICAL INSTALLATIONS | E26: =+D21 -> 22039
C27: OFFICE EQUIP | E27: =+D22 -> 99731
C28: (Depreciation FY 25-26 - Refer Dep Working file)
B30: 5 | C30: LIFT FREIGHT SERVICES B.V. | D30: 754.87
C31: DYJ LOGISTICS | E31: 8139.017
C32: FOCUS GLOBAL LOGISTICS (HK) CORPORATION LIMITED | E32: 2436.018
C33: QCS QUICK CARGO SERVICE GMBH | E33: 12149.65
C34: TRANSCARGO WORLDWIDE (M) SDN BHD | E34: 782.108
C35: VECTOR SPA | E35: 1622.4
C36: AIR INTERNATIONAL FREIGHT CO., LTD | E36: 497.83
C37: GENEL TRANSPORT LTD. STI. | E37: 6808.102
C38: TAZMANIAN FREIGHT SYSTEMS INC | D38: 355.59
C39: FOREIGN EXCHANGE GAIN/LOSS | D39: =+SUM(E30:E38)-SUM(D30:D38) -> 31324.665
C40: (Reversal of Reinstatement of FY 22-23 - Refer Payable ageing file)
B43: 6 | C43: TEAM GLOBAL LOGISITICS PVT.LTD. | D43: 38844.76
C44: TEAM GLOBAL LOGISTICS PVT LTD HYD | E44: =+D43 -> 38844.76
C45: (Reclass from Debtors to Creditors)
B47: 7 | C47: CTS INTERNATIONAL LOGISTICS CO LTD | E47: 1596.36
C48: MSC AGENCY INDIA PVT. LTD. | D48: 10378.1
C49: ACS AIR FREIGHT | E49: 569.66
C50: ALL WORLD SHIPPING CORP. | D50: 164.75
C51: CARE4 CARGO GMBH. | D51: 1487.12
C52: CARGOMIND SPEDITIONS GMBH | E52: 1378.54
C53: CARIBEX WORLDWIDE | D53: 358.44
C54: COMBI LINE INTL SPA | E54: 1131.92
C55: DGX | D55: 1571.35
C56: INTEREUROPA D.D. | D56: 122.25
C57: ITS LOGISTICS HUNGARY LTD | D57: 525.99
C58: NITTSU NEC LOGISTICS LTD | D58: 5426.39
C59: NORTH AMERICAN CARGO SOLUTIONS INC. | E59: 1623.97
C60: PACIFIC - AIRLIFT (SINGAPORE) PTE LTD | E60: 165.5
C61: PREMIUM LOGISTICS SDN BHD | E61: 1676.73
C62: TOMAX LOGISTICS AUSTRALIA | D62: 451.85
C63: AKTIS SHIPPING AND FORWARDING LTD | E63: 961.77
C64: CHINA WELLFAST LOGISTICS CO.,LTD. | D64: 1590.23
C65: HECKSHER LINEAGENTURER A/S | D65: 1814.05
C66: KARGOSMART GLOBAL (M) SDN BHD | D66: 513.16
C67: PANDA LOGISTICS CO., LTD | D67: 786.7
C68: SOTRAMAR & DE KEYSER NV | D68: 1492.16
C69: VIN WORLD WIDE TRANPORT LLC | D69: 252.25
C70: AIRCARGO.NL B.V. | E70: 657.43
C71: ATAKO TASIMACILIK DENIZCILIK A.S. | D71: 973.55
C72: ATS INTERNATIONAL | E72: 342.49
C73: CARGOMIND (GERMANY) GMBH | E73: 1578.52
C74: DPL LOJISTIK AS | E74: 1936.8
C75: EVO LOGISTICS PTE LTD | E75: 427.27
C76: PANDA GLOBAL (BEIJING) CO LTD | D76: 83.3
C77: PRO CARGO CANADA LTD | D77: 179.95
C78: TOPMOST SHIPPING LLC | E78: 1009.33
C79: BIN YOUSEF CARGO EXPRESS W.L.L | D79: 1452.81
C80: JOURNEY FREIGHT | D80: 224.13
C81: SHENZHEN MAXSPEED GLOBAL FORWARDING CO LTD | D81: 176.3
C82: AERO LINES GMBH | D82: 444.15
C83: AIF GLOBAL LOGISTICS CO., LTD. | E83: 312.28
C84: CARGOSAVVY PTE. LTD. | D84: 771.31
C85: CTS INTERNATIONAL LOGISTICS CORPORATION LIMITED XIAMEN BRANCH | D85: 210.44
C86: FOCUS GLOBAL LOGISTICS (HK) CORPORATION LIMITED | D86: 790.92
C87: JJB LINK LOGISTICS COMPANY LIMITED | E87: 723.72
C88: QCS QUICK CARGO SERVICE GMBH | D88: 11047.47
C89: VECTOR SPA | E89: 182.37
C90: AIR INTERNATIONAL FREIGHT CO., LTD | D90: 19508.03
C91: OCEANWIDE FREIGHT SERVICES LTD | D91: 1752.85
C92: B&C INTERNATIONAL LOGISTICS LTD | D92: 1277.16
C93: RONGHUA INTERNATIONAL LOGISTICS TIANJIN CO., LTD | E93: 123.43
C94: DOUBTFUL CREDITORS | E94: =+SUM(D47:D93)-SUM(E47:E93) -> 49429.07
C95: (Write back of creditors - refer Payable ageing file)
B97: 8 | C97: AIR CARGO CONNECTIONS(I)PVT.LTD | D97: 6.519258e-09 | E97: 0
C98: ALLIED AVIATION PVT LTD | D98: 0.01 | E98: 0
C99: AVS CARGO MANAGEMENT SERVICES PRIVATE LIMITED (CHENNAI) | D99: 2.88 | E99: 0
C100: COSCO SHIPPING LINES (INDIA) PRIVATE LIMITED | D100: 0.98 | E100: 0
C101: GBR FREIGHT FORWARDER PRIVATE LIMITED | D101: 0 | E101: 1.0913936e-10
C102: HONGKONG DRAGON AIRLINES LIMITED | D102: 0 | E102: 6.8212103e-13
C103: POTA GLOBAL LOGISTICS (INDIA) PVT. LTD. | D103: 5.8207661e-11 | E103: 0
C104: SAUDI ARABIAN AIRLINES | D104: 0 | E104: 5.8207661e-11
C105: SEAWAYS SHIPPING AND LOGISTICS LTD | D105: 0 | E105: 1.1641532e-10
C106: SKN FREIGHT SYSTEMS | D106: 0 | E106: 0.5
C107: SREE VENKATESHWARA LOGISTICS INDIA LLP | D107: 1.4551915e-11 | E107: 0
...

Sheet TB 25-26
F1: =+F2-E2 -> 500000 | H1: =+H2-G2 -> 725000 | J1: =+J2-I2 -> -235000 | L1: =+L2-K2 -> 490000 | N1: =+N2-M2 -> 10000 | P1: =(O2-P2)*Deno -> -500000 | Q1: 75015376 | R1: =+P1-Q1 -> -75515376
E2: =SUBTOTAL(9,E6:E344) -> 225000 | F2: =SUBTOTAL(9,F6:F344) -> 725000 | G2: =SUBTOTAL(9,G6:G344) -> 0 | H2: =SUBTOTAL(9,H6:H344) -> 725000 | I2: =SUBTOTAL(9,I6:I344) -> 235000 | J2: =SUBTOTAL(9,J6:J344) -> 0 | K2: =SUBTOTAL(9,K6:K344) -> 235000 | L2: =SUBTOTAL(9,L6:L344) -> 725000 | ... P2: =SUBTOTAL(9,P6:P344) -> 725000
E3: Closing Balance after AR | G3: Opening Balance | I3: During the Year Transaction | K3: Closing Balance | M3: Audit entries | O3: Closing Balance after AR
D4: Particulars | E4: FY 24-25 | G4: FY 25-26 | I4: FY 25-26 | K4: FY 25-26 | M4: FY 25-26 | O4: FY 25-26
E5: Debit | F5: Credit | G5: Debit | H5: Credit | I5: Debit | J5: Credit | K5: Debit | L5: Credit | M5: Debit | N5: Credit | O5: Debit | P5: Credit | Q5: Sumif | R5: B/P | S5: Note no | T5: CY Grouping | U5: Sub sch Ref
A6: ASSETS
B7: FIXED ASSETS
C8: FIXED ASSETS AT COST
D9: COMPUTER | E9: 123688.09 | F9: 0 | G9: =+E9 -> 123688.09 | H9: =+F9 -> 0 | I9: 162329 | J9: 0 | K9: =+IF((G9+I9-H9-J9>0),G9+I9-H9-J9,0) -> 286017.09 | L9: =+IF((H9+J9-G9-I9)>0,H9+J9-G9-I9,0) -> 0 | M9: =SUMIF('Audit entry'!$C:$C,'TB 25-26'!$D9,'Audit entry'!$D:$D) -> 0 | N9: =SUMIF('Audit entry'!$C:$C,'TB 25-26'!$D9,'Audit entry'!$E:$E) -> 90412 | O9: =+IF((K9+M9-L9-N9>0),K9+M9-L9-N9,0)/Deno -> 195605.09 | P9: =+IF((L9+N9-K9-M9)>0,L9+N9-K9-M9,0)/Deno -> 0 | Q9: Fixed Assets | R9: BS | S9: 9 | T9: Fixed Assets
D10: OFFICE EQUIPMENTS | E10: 45020.486 | F10: 0 | G10: =+E10 -> 45020.486 | H10: =+F10 -> 0 | I10: 0 | J10: 0 | K10: =+IF((G10+I10-H10-J10>0),G10+I10-H10-J10,0) -> 45020.486 | L10: =+IF((H10+J10-G10-I10)>0,H10+J10-G10-I10,0) -> 0 | M10: =SUMIF('Audit entry'!$C:$C,'TB 25-26'!$D10,'Audit entry'!$D:$D) -> 0 | N10: =SUMIF('Audit entry'!$C:$C,'TB 25-26'!$D10,'Audit entry'!$E:$E) -> 19308 | O10: =+IF((K10+M10-L10-N10>0),K10+M10-L10-N10,0)/Deno -> 25712.486 | P10: =+IF((L10+N10-K10-M10)>0,L10+N10-K10-M10,0)/Deno -> 0 | Q10: Fixed Assets | R10: BS | S10: 9 | T10: Fixed Assets
D11: FURNITURE & FIXTURES | E11: 93521.861 | F11: 0 | G11: =+E11 -> 93521.861 | H11: =+F11 -> 0 | I11: 94800 | J11: 0 | K11: =+IF((G11+I11-H11-J11>0),G11+I11-H11-J11,0) -> 188321.86 | L11: =+IF((H11+J11-G11-I11)>0,H11+J11-G11-I11,0) -> 0 | M11: =SUMIF('Audit entry'!$C:$C,'TB 25-26'!$D11,'Audit entry'!$D:$D) -> 0 | N11: =SUMIF('Audit entry'!$C:$C,'TB 25-26'!$D11,'Audit entry'!$E:$E) -> 32819 | O11: =+IF((K11+M11-L11-N11>0),K11+M11-L11-N11,0)/Deno -> 155502.86 | P11: =+IF((L11+N11-K11-M11)>0,L11+N11-K11-M11,0)/Deno -> 0 | Q11: Fixed Assets | R11: BS | S11: 9 | T11: Fixed Assets
D12: MOTOR VEHICLES - CAR | E12: 0 | F12: 0 | G12: =+E12 -> 0 | H12: =+F12 -> 0 | I12: 0 | J12: 0 | K12: =+IF((G12+I12-H12-J12>0),G12+I12-H12-J12,0) -> 0 | L12: =+IF((H12+J12-G12-I12)>0,H12+J12-G12-I12,0) -> 0 | M12: =SUMIF('Audit entry'!$C:$C,'TB 25-26'!$D12,'Audit entry'!$D:$D) -> 0 | N12: =SUMIF('Audit entry'!$C:$C,'TB 25-26'!$D12,'Audit entry'!$E:$E) -> 0 | O12: =+IF((K12+M12-L12-N12>0),K12+M12-L12-N12,0)/Deno -> 0 | P12: =+IF((L12+N12-K12-M12)>0,L12+N12-K12-M12,0)/Deno -> 0 | Q12: Fixed Assets | R12: BS | S12: 9 | T12: Fixed Assets
D13: ELECTRICAL INSTALLATIONS | E13: 70456.555 | F13: 0 | G13: =+E13 -> 70456.555 | H13: =+F13 -> 0 | I13: 35178 | J13: 0 | K13: =+IF((G13+I13-H13-J13>0),G13+I13-H13-J13,0) -> 105634.55 | L13: =+IF((H13+J13-G13-I13)>0,H13+J13-G13-I13,0) -> 0 | M13: =SUMIF('Audit entry'!$C:$C,'TB 25-26'!$D13,'Audit entry'!$D:$D) -> 0 | N13: =SUMIF('Audit entry'!$C:$C,'TB 25-26'!$D13,'Audit entry'!$E:$E) -> 22039 | O13: =+IF((K13+M13-L13-N13>0),K13+M13-L13-N13,0)/Deno -> 83595.555 | P13: =+IF((L13+N13-K13-M13)>0,L13+N13-K13-M13,0)/Deno -> 0 | Q13: Fixed Assets | R13: BS | S13: 9 | T13: Fixed Assets
D14: MOBILE PURCHASE | E14: 19061 | F14: 0 | G14: =+E14 -> 19061 | H14: =+F14 -> 0 | I14: 0 | J14: 0 | K14: =+IF((G14+I14-H14-J14>0),G14+I14-H14-J14,0) -> 19061 | L14: =+IF((H14+J14-G14-I14)>0,H14+J14-G14-I14,0) -> 0 | M14: =SUMIF('Audit entry'!$C:$C,'TB 25-26'!$D14,'Audit entry'!$D:$D) -> 0 | N14: =SUMIF('Audit entry'!$C:$C,'TB 25-26'!$D14,'Audit entry'!$E:$E) -> 0 | O14: =+IF((K14+M14-L14-N14>0),K14+M14-L14-N14,0)/Deno -> 19061 | P14: =+IF((L14+N14-K14-M14)>0,L14+N14-K14-M14,0)/Deno -> 0 | Q14: Fixed Assets | R14: BS | S14: 9 | T14: Fixed Assets
D15: OFFICE EQUIPMENTS | E15: 0 | F15: 0 | G15: =+E15 -> 0 | H15: =+F15 -> 0 | I15: 0 | J15: 0 | K15: =+IF((G15+I15-H15-J15>0),G15+I15-H15-J15,0) -> 0 | L15: =+IF((H15+J15-G15-I15)>0,H15+J15-G15-I15,0) -> 0 | M15: =SUMIF('Audit entry'!$C:$C,'TB 25-26'!$D15,'Audit entry'!$D:$D) -> 0 | N15: 0 | O15: =+IF((K15+M15-L15-N15>0),K15+M15-L15-N15,0)/Deno -> 0 | P15: =+IF((L15+N15-K15-M15)>0,L15+N15-K15-M15,0)/Deno -> 0 | Q15: Fixed Assets | R15: BS | S15: 9 | T15: Fixed Assets
D16: OFFICE EQUIP | E16: 381461.26 | F16: 0 | G16: =+E16 -> 381461.26 | H16: =+F16 -> 0 | I16: 82020.06 | J16: 0 | K16: =+IF((G16+I16-H16-J16>0),G16+I16-H16-J16,0) -> 463481.32 | L16: =+IF((H16+J16-G16-I16)>0,H16+J16-G16-I16,0) -> 0 | M16: =SUMIF('Audit entry'!$C:$C,'TB 25-26'!$D16,'Audit entry'!$D:$D) -> 0 | N16: =SUMIF('Audit entry'!$C:$C,'TB 25-26'!$D16,'Audit entry'!$E:$E) -> 99731 | O16: =+IF((K16+M16-L16-N16>0),K16+M16-L16-N16,0)/Deno -> 363750.32 | P16: =+IF((L16+N16-K16-M16)>0,L16+N16-K16-M16,0)/Deno -> 0 | Q16: Fixed Assets | R16: BS | S16: 9 | T16: Fixed Assets
D17: MACHINERY & ELECTRICAL | E17: 0 | F17: 0 | G17: =+E17 -> 0 | H17: =+F17 -> 0 | I17: 0 | J17: 0 | K17: =+IF((G17+I17-H17-J17>0),G17+I17-H17-J17,0) -> 0 | L17: =+IF((H17+J17-G17-I17)>0,H17+J17-G17-I17,0) -> 0 | M17: =SUMIF('Audit entry'!$C:$C,'TB 25-26'!$D17,'Audit entry'!$D:$D) -> 0 | N17: =SUMIF('Audit entry'!$C:$C,'TB 25-26'!$D17,'Audit entry'!$E:$E) -> 0 | O17: =+IF((K17+M17-L17-N17>0),K17+M17-L17-N17,0)/Deno -> 0 | P17: =+IF((L17+N17-K17-M17)>0,L17+N17-K17-M17,0)/Deno -> 0 | Q17: Fixed Assets | R17: BS | S17: 9 | T17: Fixed Assets
B18: CURRENT ASSETS | E18: 0 | F18: 0 | G18: =+E18 -> 0 | H18: =+F18 -> 0 | I18: 0 | J18: 0 | K18: =+IF((G18+I18-H18-J18>0),G18+I18-H18-J18,0) -> 0 | L18: =+IF((H18+J18-G18-I18)>0,H18+J18-G18-I18,0) -> 0 | M18: =SUMIF('Audit entry'!$C:$C,'TB 25-26'!$D18,'Audit entry'!$D:$D) -> 0 | N18: =SUMIF('Audit entry'!$C:$C,'TB 25-26'!$D18,'Audit entry'!$E:$E) -> 0 | O18: =+IF((K18+M18-L18-N18>0),K18+M18-L18-N18,0)/Deno -> 0 | P18: =+IF((L18+N18-K18-M18)>0,L18+N18-K18-M18,0)/Deno -> 0
C19: SUNDRY DEBTORS | E19: 0 | F19: 0 | G19: =+E19 -> 0 | H19: =+F19 -> 0 | I19: 0 | J19: 0 | K19: =+IF((G19+I19-H19-J19>0),G19+I19-H19-J19,0) -> 0 | L19: =+IF((H19+J19-G19-I19)>0,H19+J19-G19-I19,0) -> 0 | M19: =SUMIF('Audit entry'!$C:$C,'TB 25-26'!$D19,'Audit entry'!$D:$D) -> 0 | N19: =SUMIF('Audit entry'!$C:$C,'TB 25-26'!$D19,'Audit entry'!$E:$E) -> 0 | O19: =+IF((K19+M19-L19-N19>0),K19+M19-L19-N19,0)/Deno -> 0 | P19: =+IF((L19+N19-K19-M19)>0,L19+N19-K19-M19,0)/Deno -> 0
D20: OVERSEAS DEBTORS - FREIGHT FORWARDING | E20: 32440135 | F20: 0 | G20: =+E20 -> 32440135 | H20: =+F20 -> 0 | I20: 6292794.7 | J20: 0 | K20: =+IF((G20+I20-H20-J20>0),G20+I20-H20-J20,0) -> 38732930 | L20: =+IF((H20+J20-G20-I20)>0,H20+J20-G20-I20,0) -> 0 | M20: =+SUM('Audit entry'!D216:D217)+SUM('Audit entry'!D221:D231)-SUM('Audit entry'!E221:E231) -> 117689.93 | N20: =+SUM('Audit entry'!E211:E212) -> 42904.38 | O20: =+IF((K20+M20-L20-N20>0),K20+M20-L20-N20,0)/Deno -> 38807715 | P20: =+IF((L20+N20-K20-M20)>0,L20+N20-K20-M20,0)/Deno -> 0 | R20: BS | S20: 12 | T20: Trade Receivable
D21: LOCAL DEBTORS - FREIGHT FORWARDING | E21: 57465461 | F21: 0 | G21: =+E21 -> 57465461 | H21: =+F21 -> 0 | I21: 0 | J21: 21213806 | K21: =+IF((G21+I21-H21-J21>0),G21+I21-H21-J21,0) -> 36251654 | L21: =+IF((H21+J21-G21-I21)>0,H21+J21-G21-I21,0) -> 0 | M21: =SUMIF('Audit entry'!$C:$C,'TB 25-26'!$D21,'Audit entry'!$D:$D) -> 0 | N21: =+'Audit entry'!E44+'Audit entry'!E210-'Audit entry'!D209+SUM('Audit entry'!E232:E235)-SUM('Audit entry'!D232:D235) -> 43327.22 | O21: =+IF((K21+M21-L21-N21>0),K21+M21-L21-N21,0)/Deno -> 36208327 | P21: =+IF((L21+N21-K21-M21)>0,L21+N21-K21-M21,0)/Deno -> 0 | R21: BS | S21: 12 | T21: Trade Receivable
C22: CASH AND BANK BALANCE | E22: 0 | F22: 0 | G22: =+E22 -> 0 | H22: =+F22 -> 0 | I22: 0 | J22: 0 | K22: =+IF((G22+I22-H22-J22>0),G22+I22-H22-J22,0) -> 0 | L22: =+IF((H22+J22-G22-I22)>0,H22+J22-G22-I22,0) -> 0 | M22: =SUMIF('Audit entry'!$C:$C,'TB 25-26'!$D22,'Audit entry'!$D:$D) -> 0 | N22: =SUMIF('Audit entry'!$C:$C,'TB 25-26'!$D22,'Audit entry'!$E:$E) -> 0 | O22: =+IF((K22+M22-L22-N22>0),K22+M22-L22-N22,0)/Deno -> 0 | P22: =+IF((L22+N22-K22-M22)>0,L22+N22-K22-M22,0)/Deno -> 0
D23: CASH IN HAND | E23: 0 | F23: 0 | G23: =+E23 -> 0 | H23: =+F23 -> 0 | I23: 0 | J23: 0 | K23: =+IF((G23+I23-H23-J23>0),G23+I23-H23-J23,0) -> 0 | L23: =+IF((H23+J23-G23-I23)>0,H23+J23-G23-I23,0) -> 0 | M23: =SUMIF('Audit entry'!$C:$C,'TB 25-26'!$D23,'Audit entry'!$D:$D) -> 0 | N23: =SUMIF('Audit entry'!$C:$C,'TB 25-26'!$D23,'Audit entry'!$E:$E) -> 0 | O23: =+IF((K23+M23-L23-N23>0),K23+M23-L23-N23,0)/Deno -> 0 | P23: =+IF((L23+N23-K23-M23)>0,L23+N23-K23-M23,0)/Deno -> 0 | Q23: Cash in hand | R23: BS | S23: 13 | T23: Cash and cash equivalents
D24: BANK BALANCE LOCAL CURRENCY | E24: 21436133 | F24: 0 | G24: =+E24 -> 21436133 | H24: =+F24 -> 0 | I24: 11152456 | J24: 0 | K24: =+IF((G24+I24-H24-J24>0),G24+I24-H24-J24,0) -> 32588589 | L24: =+IF((H24+J24-G24-I24)>0,H24+J24-G24-I24,0) -> 0 | M24: =SUMIF('Audit entry'!$C:$C,'TB 25-26'!$D24,'Audit entry'!$D:$D) -> 0 | N24: =SUMIF('Audit entry'!$C:$C,'TB 25-26'!$D24,'Audit entry'!$E:$E) -> 0 | O24: =+IF((K24+M24-L24-N24>0),K24+M24-L24-N24,0)/Deno -> 32588589 | P24: =+IF((L24+N24-K24-M24)>0,L24+N24-K24-M24,0)/Deno -> 0 | Q24: Cash at Bank - Local Currency | R24: BS | S24: 13 | T24: Cash and cash equivalents
D25: FIXED DEPOSIT IN BANK | E25: 0 | F25: 0 | G25: =+E25 -> 0 | H25: =+F25 -> 0 | I25: 0 | J25: 0 | K25: =+IF((G25+I25-H25-J25>0),G25+I25-H25-J25,0) -> 0 | L25: =+IF((H25+J25-G25-I25)>0,H25+J25-G25-I25,0) -> 0 | M25: =SUMIF('Audit entry'!$C:$C,'TB 25-26'!$D25,'Audit entry'!$D:$D) -> 0 | N25: =SUMIF('Audit entry'!$C:$C,'TB 25-26'!$D25,'Audit entry'!$E:$E) -> 0 | O25: =+IF((K25+M25-L25-N25>0),K25+M25-L25-N25,0)/Deno -> 0 | P25: =+IF((L25+N25-K25-M25)>0,L25+N25-K25-M25,0)/Deno -> 0 | Q25: Cash at Bank - Local Currency | R25: BS | S25: 13 | T25: Cash and cash equivalents
D26: MAA PETTY CASH | E26: 5161 | F26: 0 | G26: =+E26 -> 5161 | H26: =+F26 -> 0 | I26: 731 | J26: 0 | K26: =+IF((G26+I26-H26-J26>0),G26+I26-H26-J26,0) -> 5892 | L26: =+IF((H26+J26-G26-I26)>0,H26+J26-G26-I26,0) -> 0 | M26: =SUMIF('Audit entry'!$C:$C,'TB 25-26'!$D26,'Audit entry'!$D:$D) -> 0 | N26: =SUMIF('Audit entry'!$C:$C,'TB 25-26'!$D26,'Audit entry'!$E:$E) -> 0 | O26: =+IF((K26+M26-L26-N26>0),K26+M26-L26-N26,0)/Deno -> 5892 | P26: =+IF((L26+N26-K26-M26)>0,L26+N26-K26-M26,0)/Deno -> 0 | Q26: Petty Cash | R26: BS | S26: 13 | T26: Cash and cash equivalents
D27: AIRPORT PETTY CASH | E27: 0 | F27: 0 | G27: =+E27 -> 0 | H27: =+F27 -> 0 | I27: 0 | J27: 0 | K27: =+IF((G27+I27-H27-J27>0),G27+I27-H27-J27,0) -> 0 | L27: =+IF((H27+J27-G27-I27)>0,H27+J27-G27-I27,0) -> 0 | M27: =SUMIF('Audit entry'!$C:$C,'TB 25-26'!$D27,'Audit entry'!$D:$D) -> 0 | N27: =SUMIF('Audit entry'!$C:$C,'TB 25-26'!$D27,'Audit entry'!$E:$E) -> 0 | O27: =+IF((K27+M27-L27-N27>0),K27+M27-L27-N27,0)/Deno -> 0 | P27: =+IF((L27+N27-K27-M27)>0,L27+N27-K27-M27,0)/Deno -> 0 | Q27: Petty Cash | R27: BS | S27: 13 | T27: Cash and cash equivalents
D28: BANK BALANCE OVERSEAS CURRENCY | E28: 241111.49 | F28: 0 | G28: =+E28 -> 241111.49 | H28: =+F28 -> 0 | I28: 1335622.7 | J28: 0 | K28: =+IF((G28+I28-H28-J28>0),G28+I28-H28-J28,0) -> 1576734.2 | L28: =+IF((H28+J28-G28-I28)>0,H28+J28-G28-I28,0) -> 0 | M28: =SUMIF('Audit entry'!$C:$C,'TB 25-26'!$D28,'Audit entry'!$D:$D) -> 0 | N28: =SUMIF('Audit entry'!$C:$C,'TB 25-26'!$D28,'Audit entry'!$E:$E) -> 0 | O28: =+IF((K28+M28-L28-N28>0),K28+M28-L28-N28,0)/Deno -> 1576734.2 | P28: =+IF((L28+N28-K28-M28)>0,L28+N28-K28-M28,0)/Deno -> 0 | Q28: Cash at Bank - Foreign Currency | R28: BS | S28: 13 | T28: Cash and cash equivalents
D29: ATM CASH W/D | E29: 0 | F29: 0 | G29: =+E29 -> 0 | H29: =+F29 -> 0 | I29: 0 | J29: 0 | K29: =+IF((G29+I29-H29-J29>0),G29+I29-H29-J29,0) -> 0 | L29: =+IF((H29+J29-G29-I29)>0,H29+J29-G29-I29,0) -> 0 | M29: =SUMIF('Audit entry'!$C:$C,'TB 25-26'!$D29,'Audit entry'!$D:$D) -> 0 | N29: =SUMIF('Audit entry'!$C:$C,'TB 25-26'!$D29,'Audit entry'!$E:$E) -> 0 | O29: =+IF((K29+M29-L29-N29>0),K29+M29-L29-N29,0)/Deno -> 0 | P29: =+IF((L29+N29-K29-M29)>0,L29+N29-K29-M29,0)/Deno -> 0 | Q29: Cash in hand | R29: BS | S29: 13 | T29: Cash and cash equivalents
D30: INTER BANK ACCOUNT TRANSFER | E30: 0 | F30: 0 | G30: =+E30 -> 0 | H30: =+F30 -> 0 | I30: 0 | J30: 0 | K30: =+IF((G30+I30-H30-J30>0),G30+I30-H30-J30,0) -> 0 | L30: =+IF((H30+J30-G30-I30)>0,H30+J30-G30-I30,0) -> 0 | M30: =SUMIF('Audit entry'!$C:$C,'TB 25-26'!$D30,'Audit entry'!$D:$D) -> 0 | N30: =SUMIF('Audit entry'!$C:$C,'TB 25-26'!$D30,'Audit entry'!$E:$E) -> 0 | O30: =+IF((K30+M30-L30-N30>0),K30+M30-L30-N30,0)/Deno -> 0 | P30: =+IF((L30+N30-K30-M30)>0,L30+N30-K30-M30,0)/Deno -> 0 | Q30: Cash at Bank - Local Currency | R30: BS | S30: 13 | T30: Cash and cash equivalents
D31: SECURITY DEPOSIT | E31: 0 | F31: 0 | G31: =+E31 -> 0 | H31: =+F31 -> 0 | I31: 0 | J31: 0 | K31: =+IF((G31+I31-H31-J31>0),G31+I31-H31-J31,0) -> 0 | L31: =+IF((H31+J31-G31-I31)>0,H31+J31-G31-I31,0) -> 0 | M31: =SUMIF('Audit entry'!$C:$C,'TB 25-26'!$D31,'Audit entry'!$D:$D) -> 0 | N31: =SUMIF('Audit entry'!$C:$C,'TB 25-26'!$D31,'Audit entry'!$E:$E) -> 0 | O31: =+IF((K31+M31-L31-N31>0),K31+M31-L31-N31,0)/Deno -> 0 | P31: =+IF((L31+N31-K31-M31)>0,L31+N31-K31-M31,0)/Deno -> 0 | Q31: Security Deposit | R31: BS | S31: 13 | T31: Cash and cash equivalents
D32: TUT PETTY CASH | E32: 1988 | F32: 0 | G32: =+E32 -> 1988 | H32: =+F32 -> 0 | I32: 0 | J32: 0 | K32: =+IF((G32+I32-H32-J32>0),G32+I32-H32-J32,0) -> 1988 | L32: =+IF((H32+J32-G32-I32)>0,H32+J32-G32-I32,0) -> 0 | M32: =SUMIF('Audit entry'!$C:$C,'TB 25-26'!$D32,'Audit entry'!$D:$D) -> 0 | N32: =SUMIF('Audit entry'!$C:$C,'TB 25-26'!$D32,'Audit entry'!$E:$E) -> 0 | O32: =+IF((K32+M32-L32-N32>0),K32+M32-L32-N32,0)/Deno -> 1988 | P32: =+IF((L32+N32-K32-M32)>0,L32+N32-K32-M32,0)/Deno -> 0 | Q32: Petty Cash | R32: BS | S32: 13 | T32: Cash and cash equivalents
D33: HYD PETTY CASH | E33: 8691.15 | F33: 0 | G33: =+E33 -> 8691.15 | H33: =+F33 -> 0 | I33: 0 | J33: 5776.06 | K33: =+IF((G33+I33-H33-J33>0),G33+I33-H33-J33,0) -> 2915.09 | L33: =+IF((H33+J33-G33-I33)>0,H33+J33-G33-I33,0) -> 0 | M33: =SUMIF('Audit entry'!$C:$C,'TB 25-26'!$D33,'Audit entry'!$D:$D) -> 0 | N33: =SUMIF('Audit entry'!$C:$C,'TB 25-26'!$D33,'Audit entry'!$E:$E) -> 0 | O33: =+IF((K33+M33-L33-N33>0),K33+M33-L33-N33,0)/Deno -> 2915.09 | P33: =+IF((L33+N33-K33-M33)>0,L33+N33-K33-M33,0)/Deno -> 0 | Q33: Petty Cash | R33: BS | S33: 13 | T33: Cash and cash equivalents
D34: BLR PETTY CASH | E34: 0 | F34: 0 | G34: =+E34 -> 0 | H34: =+F34 -> 0 | I34: 17165 | J34: 0 | K34: =+IF((G34+I34-H34-J34>0),G34+I34-H34-J34,0) -> 17165 | L34: =+IF((H34+J34-G34-I34)>0,H34+J34-G34-I34,0) -> 0 | M34: =SUMIF('Audit entry'!$C:$C,'TB 25-26'!$D34,'Audit entry'!$D:$D) -> 0 | N34: =SUMIF('Audit entry'!$C:$C,'TB 25-26'!$D34,'Audit entry'!$E:$E) -> 0 | O34: =+IF((K34+M34-L34-N34>0),K34+M34-L34-N34,0)/Deno -> 17165 | P34: =+IF((L34+N34-K34-M34)>0,L34+N34-K34-M34,0)/Deno -> 0 | Q34: Petty Cash | R34: BS | S34: 13 | T34: Cash and cash equivalents
D35: CBE PETTY CASH | E35: 459.5 | F35: 0 | G35: =+E35 -> 459.5 | H35: =+F35 -> 0 | I35: 29965.19 | J35: 0 | K35: =+IF((G35+I35-H35-J35>0),G35+I35-H35-J35,0) -> 30424.69 | L35: =+IF((H35+J35-G35-I35)>0,H35+J35-G35-I35,0) -> 0 | M35: =SUMIF('Audit entry'!$C:$C,'TB 25-26'!$D35,'Audit entry'!$D:$D) -> 0 | N35: =SUMIF('Audit entry'!$C:$C,'TB 25-26'!$D35,'Audit entry'!$E:$E) -> 0 | O35: =+IF((K35+M35-L35-N35>0),K35+M35-L35-N35,0)/Deno -> 30424.69 | P35: =+IF((L35+N35-K35-M35)>0,L35+N35-K35-M35,0)/Deno -> 0 | Q35: Petty Cash | R35: BS | S35: 13 | T35: Cash and cash equivalents
C36: WORK IN PROGRESS JOBS | E36: 0 | F36: 0 | G36: =+E36 -> 0 | H36: =+F36 -> 0 | I36: 0 | J36: 0 | K36: =+IF((G36+I36-H36-J36>0),G36+I36-H36-J36,0) -> 0 | L36: =+IF((H36+J36-G36-I36)>0,H36+J36-G36-I36,0) -> 0 | M36: =SUMIF('Audit entry'!$C:$C,'TB 25-26'!$D36,'Audit entry'!$D:$D) -> 0 | N36: =SUMIF('Audit entry'!$C:$C,'TB 25-26'!$D36,'Audit entry'!$E:$E) -> 0 | O36: =+IF((K36+M36-L36-N36>0),K36+M36-L36-N36,0)/Deno -> 0 | P36: =+IF((L36+N36-K36-M36)>0,L36+N36-K36-M36,0)/Deno -> 0
D37: WORK IN PROGRESS JOBS | E37: 0 | F37: 0 | G37: =+E37 -> 0 | H37: =+F37 -> 0 | I37: 0 | J37: 0 | K37: =+IF((G37+I37-H37-J37>0),G37+I37-H37-J37,0) -> 0 | L37: =+IF((H37+J37-G37-I37)>0,H37+J37-G37-I37,0) -> 0 | M37: =SUMIF('Audit entry'!$C:$C,'TB 25-26'!$D37,'Audit entry'!$D:$D) -> 0 | N37: =SUMIF('Audit entry'!$C:$C,'TB 25-26'!$D37,'Audit entry'!$E:$E) -> 0 | O37: =+IF((K37+M37-L37-N37>0),K37+M37-L37-N37,0)/Deno -> 0 | P37: =+IF((L37+N37-K37-M37)>0,L37+N37-K37-M37,0)/Deno -> 0 | Q37: Unbilled Income | R37: BS | S37: 14 | T37: Short-term loans and advances
D38: WORK IN PROGRESS JOBS REV | E38: 0 | F38: 0 | G38: =+E38 -> 0 | H38: =+F38 -> 0 | I38: 0 | J38: 0 | K38: =+IF((G38+I38-H38-J38>0),G38+I38-H38-J38,0) -> 0 | L38: =+IF((H38+J38-G38-I38)>0,H38+J38-G38-I38,0) -> 0 | M38: =SUMIF('Audit entry'!$C:$C,'TB 25-26'!$D38,'Audit entry'!$D:$D) -> 0 | N38: =SUMIF('Audit entry'!$C:$C,'TB 25-26'!$D38,'Audit entry'!$E:$E) -> 0 | O38: =+IF((K38+M38-L38-N38>0),K38+M38-L38-N38,0)/Deno -> 0 | P38: =+IF((L38+N38-K38-M38)>0,L38+N38-K38-M38,0)/Deno -> 0 | Q38: Unbilled Income | R38: BS | S38: 14 | T38: Short-term loans and advances
C39: ACCRUALS | E39: 0 | F39: 0 | G39: =+E39 -> 0 | H39: =+F39 -> 0 | I39: 0 | J39: 0 | K39: =+IF((G39+I39-H39-J39>0),G39+I39-H39-J39,0) -> 0 | L39: =+IF((H39+J39-G39-I39)>0,H39+J39-G39-I39,0) -> 0 | M39: =SUMIF('Audit entry'!$C:$C,'TB 25-26'!$D39,'Audit entry'!$D:$D) -> 0 | N39: =SUMIF('Audit entry'!$C:$C,'TB 25-26'!$D39,'Audit entry'!$E:$E) -> 0 | O39: =+IF((K39+M39-L39-N39>0),K39+M39-L39-N39,0)/Deno -> 0 | P39: =+IF((L39+N39-K39-M39)>0,L39+N39-K39-M39,0)/Deno -> 0
D40: PREPAID INTERNET EXPESES | E40: 0 | F40: 0 | G40: =+E40 -> 0 | H40: =+F40 -> 0 | I40: 0 | J40: 0 | K40: =+IF((G40+I40-H40-J40>0),G40+I40-H40-J40,0) -> 0 | L40: =+IF((H40+J40-G40-I40)>0,H40+J40-G40-I40,0) -> 0 | M40: =SUMIF('Audit entry'!$C:$C,'TB 25-26'!$D40,'Audit entry'!$D:$D) -> 0 | N40: =SUMIF('Audit entry'!$C:$C,'TB 25-26'!$D40,'Audit entry'!$E:$E) -> 0 | O40: =+IF((K40+M40-L40-N40>0),K40+M40-L40-N40,0)/Deno -> 0 | P40: =+IF((L40+N40-K40-M40)>0,L40+N40-K40-M40,0)/Deno -> 0 | Q40: Prepaid Expenses | R40: BS | S40: 14 | T40: Short-term loans and advances
D41: PREPAID INSURANCES | E41: 130788.23 | F41: 0 | G41: =+E41 -> 130788.23 | H41: =+F41 -> 0 | I41: 0 | J41: 0 | K41: =+IF((G41+I41-H41-J41>0),G41+I41-H41-J41,0) -> 130788.23 | L41: =+IF((H41+J41-G41-I41)>0,H41+J41-G41-I41,0) -> 0 | M41: =SUMIF('Audit entry'!$C:$C,'TB 25-26'!$D41,'Audit entry'!$D:$D) -> 180753.41 | N41: =SUMIF('Audit entry'!$C:$C,'TB 25-26'!$D41,'Audit entry'!$E:$E) -> 130788.23 | O41: =+IF((K41+M41-L41-N41>0),K41+M41-L41-N41,0)/Deno -> 180753.41 | P41: =+IF((L41+N41-K41-M41)>0,L41+N41-K41-M41,0)/Deno -> 0 | Q41: Prepaid Expenses | R41: BS | S41: 14 | T41: Short-term loans and advances
B42: LOANS AND ADVANCES | E42: 0 | F42: 0 | G42: =+E42 -> 0 | H42: =+F42 -> 0 | I42: 0 | J42: 0 | K42: =+IF((G42+I42-H42-J42>0),G42+I42-H42-J42,0) -> 0 | L42: =+IF((H42+J42-G42-I42)>0,H42+J42-G42-I42,0) -> 0 | M42: =SUMIF('Audit entry'!$C:$C,'TB 25-26'!$D42,'Audit entry'!$D:$D) -> 0 | N42: =SUMIF('Audit entry'!$C:$C,'TB 25-26'!$D42,'Audit entry'!$E:$E) -> 0 | O42: =+IF((K42+M42-L42-N42>0),K42+M42-L42-N42,0)/Deno -> 0 | P42: =+IF((L42+N42-K42-M42)>0,L42+N42-K42-M42,0)/Deno -> 0
C43: ADVANCE RECOVERABLE IN CASH OR KIND OR FOR VALUE TO BE RECEIVED | E43: 0 | F43: 0 | G43: =+E43 -> 0 | H43: =+F43 -> 0 | I43: 0 | J43: 0 | K43: =+IF((G43+I43-H43-J43>0),G43+I43-H43-J43,0) -> 0 | L43: =+IF((H43+J43-G43-I43)>0,H43+J43-G43-I43,0) -> 0 | M43: =SUMIF('Audit entry'!$C:$C,'TB 25-26'!$D43,'Audit entry'!$D:$D) -> 0 | N43: =SUMIF('Audit entry'!$C:$C,'TB 25-26'!$D43,'Audit entry'!$E:$E) -> 0 | O43: =+IF((K43+M43-L43-N43>0),K43+M43-L43-N43,0)/Deno -> 0 | P43: =+IF((L43+N43-K43-M43)>0,L43+N43-K43-M43,0)/Deno -> 0
D44: STAFF ADVANCES | E44: 0 | F44: 0 | G44: =+E44 -> 0 | H44: =+F44 -> 0 | I44: 0 | J44: 0 | K44: =+IF((G44+I44-H44-J44>0),G44+I44-H44-J44,0) -> 0 | L44: =+IF((H44+J44-G44-I44)>0,H44+J44-G44-I44,0) -> 0 | M44: =SUMIF('Audit entry'!$C:$C,'TB 25-26'!$D44,'Audit entry'!$D:$D) -> 0 | N44: =SUMIF('Audit entry'!$C:$C,'TB 25-26'!$D44,'Audit entry'!$E:$E) -> 0 | O44: =+IF((K44+M44-L44-N44>0),K44+M44-L44-N44,0)/Deno -> 0 | P44: =+IF((L44+N44-K44-M44)>0,L44+N44-K44-M44,0)/Deno -> 0 | Q44: Staff Advance | R44: BS | S44: 14 | T44: Short-term loans and advances
D45: STAFF LOAN | E45: 0 | F45: 0.03 | G45: =+E45 -> 0 | H45: =+F45 -> 0.03 | I45: 0 | J45: 0 | K45: =+IF((G45+I45-H45-J45>0),G45+I45-H45-J45,0) -> 0 | L45: =+IF((H45+J45-G45-I45)>0,H45+J45-G45-I45,0) -> 0.03 | M45: =SUMIF('Audit entry'!$C:$C,'TB 25-26'!$D45,'Audit entry'!$D:$D) -> 0 | N45: =SUMIF('Audit entry'!$C:$C,'TB 25-26'!$D45,'Audit entry'!$E:$E) -> 0 | O45: =+IF((K45+M45-L45-N45>0),K45+M45-L45-N45,0)/Deno -> 0 | P45: =+IF((L45+N45-K45-M45)>0,L45+N45-K45-M45,0)/Deno -> 0.03 | Q45: Staff Advance | R45: BS | S45: 14 | T45: Short-term loans and advances
D46: TRAVEL ADVANCE | E46: 43181.77 | F46: 0 | G46: =+E46 -> 43181.77 | H46: =+F46 -> 0 | I46: 52349.5 | J46: 0 | K46: =+IF((G46+I46-H46-J46>0),G46+I46-H46-J46,0) -> 95531.27 | L46: =+IF((H46+J46-G46-I46)>0,H46+J46-G46-I46,0) -> 0 | M46: =SUMIF('Audit entry'!$C:$C,'TB 25-26'!$D46,'Audit entry'!$D:$D) -> 0 | N46: =SUMIF('Audit entry'!$C:$C,'TB 25-26'!$D46,'Audit entry'!$E:$E) -> 0 | O46: =+IF((K46+M46-L46-N46>0),K46+M46-L46-N46,0)/Deno -> 95531.27 | P46: =+IF((L46+N46-K46-M46)>0,L46+N46-K46-M46,0)/Deno -> 0 | Q46: Staff Advance | R46: BS | S46: 14 | T46: Short-term loans and advances
D47: PREPAID ADMIN EXPENSES OTHERS | E47: 0 | F47: 0 | G47: =+E47 -> 0 | H47: =+F47 -> 0 | I47: 6000 | J47: 0 | K47: =+IF((G47+I47-H47-J47>0),G47+I47-H47-J47,0) -> 6000 | L47: =+IF((H47+J47-G47-I47)>0,H47+J47-G47-I47,0) -> 0 | M47: =SUMIF('Audit entry'!$C:$C,'TB 25-26'!$D47,'Audit entry'!$D:$D) -> 0 | N47: =SUMIF('Audit entry'!$C:$C,'TB 25-26'!$D47,'Audit entry'!$E:$E) -> 0 | O47: =+IF((K47+M47-L47-N47>0),K47+M47-L47-N47,0)/Deno -> 6000 | P47: =+IF((L47+N47-K47-M47)>0,L47+N47-K47-M47,0)/Deno -> 0 | Q47: Prepaid Expenses | R47: BS | S47: 14 | T47: Short-term loans and advances
D48: PREPAID SUBSCRIPTION | E48: 0 | F48: 0 | G48: =+E48 -> 0 | H48: =+F48 -> 0 | I48: 0 | J48: 0 | K48: =+IF((G48+I48-H48-J48>0),G48+I48-H48-J48,0) -> 0 | L48: =+IF((H48+J48-G48-I48)>0,H48+J48-G48-I48,0) -> 0 | M48: =SUMIF('Audit entry'!$C:$C,'TB 25-26'!$D48,'Audit entry'!$D:$D) -> 59381 | N48: =SUMIF('Audit entry'!$C:$C,'TB 25-26'!$D48,'Audit entry'!$E:$E) -> 0 | O48: =+IF((K48+M48-L48-N48>0),K48+M48-L48-N48,0)/Deno -> 59381 | P48: =+IF((L48+N48-K48-M48)>0,L48+N48-K48-M48,0)/Deno -> 0 | Q48: Prepaid Expenses | R48: BS | S48: 14 | T48: Short-term loans and advances
D49: PREPAID RENT | E49: 1173158 | F49: 0 | G49: =+E49 -> 1173158 | H49: =+F49 -> 0 | I49: 0 | J49: 35977.48 | K49: =+IF((G49+I49-H49-J49>0),G49+I49-H49-J49,0) -> 1137180.5 | L49: =+IF((H49+J49-G49-I49)>0,H49+J49-G49-I49,0) -> 0 | M49: =SUMIF('Audit entry'!$C:$C,'TB 25-26'!$D49,'Audit entry'!$D:$D) -> 0 | N49: =SUMIF('Audit entry'!$C:$C,'TB 25-26'!$D49,'Audit entry'!$E:$E) -> 0 | O49: =+IF((K49+M49-L49-N49>0),K49+M49-L49-N49,0)/Deno -> 1137180.5 | P49: =+IF((L49+N49-K49-M49)>0,L49+N49-K49-M49,0)/Deno -> 0 | Q49: Rental Deposit | R49: BS | S49: 10 | T49: Long-term loans and advances
D50: INTEREST ACCRUED BUT NOT RECEIVED | E50: 0 | F50: 0 | G50: =+E50 -> 0 | H50: =+F50 -> 0 | I50: 0 | J50: 0 | K50: =+IF((G50+I50-H50-J50>0),G50+I50-H50-J50,0) -> 0 | L50: =+IF((H50+J50-G50-I50)>0,H50+J50-G50-I50,0) -> 0 | M50: =SUMIF('Audit entry'!$C:$C,'TB 25-26'!$D50,'Audit entry'!$D:$D) -> 0 | N50: =SUMIF('Audit entry'!$C:$C,'TB 25-26'!$D50,'Audit entry'!$E:$E) -> 0 | O50: =+IF((K50+M50-L50-N50>0),K50+M50-L50-N50,0)/Deno -> 0 | P50: =+IF((L50+N50-K50-M50)>0,L50+N50-K50-M50,0)/Deno -> 0 | Q50: Interest Accrued | R50: BS | S50: 14 | T50: Short-term loans and advances
D51: DEPOSITS OFFICE | E51: 496500 | F51: 0 | G51: =+E51 -> 496500 | H51: =+F51 -> 0 | I51: 0 | J51: 0 | K51: =+IF((G51+I51-H51-J51>0),G51+I51-H51-J51,0) -> 496500 | L51: =+IF((H51+J51-G51-I51)>0,H51+J51-G51-I51,0) -> 0 | M51: =SUMIF('Audit entry'!$C:$C,'TB 25-26'!$D51,'Audit entry'!$D:$D) -> 0 | N51: =SUMIF('Audit entry'!$C:$C,'TB 25-26'!$D51,'Audit entry'!$E:$E) -> 0 | O51: =+IF((K51+M51-L51-N51>0),K51+M51-L51-N51,0)/Deno -> 496500 | P51: =+IF((L51+N51-K51-M51)>0,L51+N51-K51-M51,0)/Deno -> 0 | Q51: Rental Deposit | R51: BS | S51: 10 | T51: Long-term loans and advances
D52: CGST RECEIVABLE | E52: 12054926 | F52: 0 | G52: =+E52 -> 12054926 | H52: =+F52 -> 0 | I52: 5046645.8 | J52: 0 | K52: =+IF((G52+I52-H52-J52>0),G52+I52-H52-J52,0) -> 17101572 | L52: =+IF((H52+J52-G52-I52)>0,H52+J52-G52-I52,0) -> 0 | M52: =SUMIF('Audit entry'!$C:$C,'TB 25-26'!$D52,'Audit entry'!$D:$D) -> 0 | N52: =SUMIF('Audit entry'!$C:$C,'TB 25-26'!$D52,'Audit entry'!$E:$E) -> 0 | O52: =+IF((K52+M52-L52-N52>0),K52+M52-L52-N52,0)/Deno -> 17101572 | P52: =+IF((L52+N52-K52-M52)>0,L52+N52-K52-M52,0)/Deno -> 0 | Q52: GST - Input tax credit | R52: BS | S52: 14 | T52: Short-term loans and advances | U52: GST Input tax credit
D53: IGST RECEIVABLE | E53: 4906525 | F53: 0 | G53: =+E53 -> 4906525 | H53: =+F53 -> 0 | I53: 4861184.1 | J53: 0 | K53: =+IF((G53+I53-H53-J53>0),G53+I53-H53-J53,0) -> 9767709.1 | L53: =+IF((H53+J53-G53-I53)>0,H53+J53-G53-I53,0) -> 0 | M53: =SUMIF('Audit entry'!$C:$C,'TB 25-26'!$D53,'Audit entry'!$D:$D) -> 0 | N53: =SUMIF('Audit entry'!$C:$C,'TB 25-26'!$D53,'Audit entry'!$E:$E) -> 0 | O53: =+IF((K53+M53-L53-N53>0),K53+M53-L53-N53,0)/Deno -> 9767709.1 | P53: =+IF((L53+N53-K53-M53)>0,L53+N53-K53-M53,0)/Deno -> 0 | Q53: GST - Input tax credit | R53: BS | S53: 14 | T53: Short-term loans and advances | U53: GST Input tax credit
D54: SGST RECEIVABLE | E54: 10904241 | F54: 0 | G54: =+E54 -> 10904241 | H54: =+F54 -> 0 | I54: 5046645.5 | J54: 0 | K54: =+IF((G54+I54-H54-J54>0),G54+I54-H54-J54,0) -> 15950887 | L54: =+IF((H54+J54-G54-I54)>0,H54+J54-G54-I54,0) -> 0 | M54: =SUMIF('Audit entry'!$C:$C,'TB 25-26'!$D54,'Audit entry'!$D:$D) -> 0 | N54: =SUMIF('Audit entry'!$C:$C,'TB 25-26'!$D54,'Audit entry'!$E:$E) -> 0 | O54: =+IF((K54+M54-L54-N54>0),K54+M54-L54-N54,0)/Deno -> 15950887 | P54: =+IF((L54+N54-K54-M54)>0,L54+N54-K54-M54,0)/Deno -> 0 | Q54: GST - Input tax credit | R54: BS | S54: 14 | T54: Short-term loans and advances | U54: GST Input tax credit
D55: GST ELECTRONIC CASH LEDGER | E55: 4235617 | F55: 0 | G55: =+E55 -> 4235617 | H55: =+F55 -> 0 | I55: 14010982 | J55: 0 | K55: =+IF((G55+I55-H55-J55>0),G55+I55-H55-J55,0) -> 18246599 | L55: =+IF((H55+J55-G55-I55)>0,H55+J55-G55-I55,0) -> 0 | M55: =SUMIF('Audit entry'!$C:$C,'TB 25-26'!$D55,'Audit entry'!$D:$D) -> 0 | N55: =SUMIF('Audit entry'!$C:$C,'TB 25-26'!$D55,'Audit entry'!$E:$E) -> 0 | O55: =+IF((K55+M55-L55-N55>0),K55+M55-L55-N55,0)/Deno -> 18246599 | P55: =+IF((L55+N55-K55-M55)>0,L55+N55-K55-M55,0)/Deno -> 0 | Q55: GST - Input tax credit | R55: BS | S55: 14 | T55: Short-term loans and advances | U55: GST Input tax credit
D56: CENVAT CREDIT CHS | E56: 0 | F56: 0 | G56: =+E56 -> 0 | H56: =+F56 -> 0 | I56: 0 | J56: 0 | K56: =+IF((G56+I56-H56-J56>0),G56+I56-H56-J56,0) -> 0 | L56: =+IF((H56+J56-G56-I56)>0,H56+J56-G56-I56,0) -> 0 | M56: =SUMIF('Audit entry'!$C:$C,'TB 25-26'!$D56,'Audit entry'!$D:$D) -> 0 | N56: =SUMIF('Audit entry'!$C:$C,'TB 25-26'!$D56,'Audit entry'!$E:$E) -> 0 | O56: =+IF((K56+M56-L56-N56>0),K56+M56-L56-N56,0)/Deno -> 0 | P56: =+IF((L56+N56-K56-M56)>0,L56+N56-K56-M56,0)/Deno -> 0 | Q56: Cenvat Credit | R56: BS | S56: 14 | T56: Short-term loans and advances
D57: CENVAT CREDIT - KRISHI KALYAN CESS - CHS | E57: 0 | F57: 0 | G57: =+E57 -> 0 | H57: =+F57 -> 0 | I57: 0 | J57: 0 | K57: =+IF((G57+I57-H57-J57>0),G57+I57-H57-J57,0) -> 0 | L57: =+IF((H57+J57-G57-I57)>0,H57+J57-G57-I57,0) -> 0 | M57: =SUMIF('Audit entry'!$C:$C,'TB 25-26'!$D57,'Audit entry'!$D:$D) -> 0 | N57: =SUMIF('Audit entry'!$C:$C,'TB 25-26'!$D57,'Audit entry'!$E:$E) -> 0 | O57: =+IF((K57+M57-L57-N57>0),K57+M57-L57-N57,0)/Deno -> 0 | P57: =+IF((L57+N57-K57-M57)>0,L57+N57-K57-M57,0)/Deno -> 0 | Q57: Cenvat Credit | R57: BS | S57: 14 | T57: Short-term loans and advances
D58: ADVANCE FOR CAPITAL EXPENSES | E58: 0 | F58: 0 | G58: =+E58 -> 0 | H58: =+F58 -> 0 | I58: 0 | J58: 0 | K58: =+IF((G58+I58-H58-J58>0),G58+I58-H58-J58,0) -> 0 | L58: =+IF((H58+J58-G58-I58)>0,H58+J58-G58-I58,0) -> 0 | M58: =SUMIF('Audit entry'!$C:$C,'TB 25-26'!$D58,'Audit entry'!$D:$D) -> 0 | N58: =SUMIF('Audit entry'!$C:$C,'TB 25-26'!$D58,'Audit entry'!$E:$E) -> 0 | O58: =+IF((K58+M58-L58-N58>0),K58+M58-L58-N58,0)/Deno -> 0 | P58: =+IF((L58+N58-K58-M58)>0,L58+N58-K58-M58,0)/Deno -> 0 | Q58: Advance for capital expenses | R58: BS | S58: 14 | T58: Short-term loans and advances
D59: ADVANCE PAID \ RECEIVED | E59: 0 | F59: 14847471 | G59: =+E59 -> 0 | H59: =+F59 -> 14847471 | I59: 0 | J59: 719591.45 | K59: =+IF((G59+I59-H59-J59>0),G59+I59-H59-J59,0) -> 0 | L59: =+IF((H59+J59-G59-I59)>0,H59+J59-G59-I59,0) -> 15567062 | M59: =SUMIF('Audit entry'!$C:$C,'TB 25-26'!$D59,'Audit entry'!$D:$D) -> 1481780 | N59: =SUMIF('Audit entry'!$C:$C,'TB 25-26'!$D59,'Audit entry'!$E:$E) -> 0 | O59: =+IF((K59+M59-L59-N59>0),K59+M59-L59-N59,0)/Deno -> 0 | P59: =+IF((L59+N59-K59-M59)>0,L59+N59-K59-M59,0)/Deno -> 14085282 | Q59: advance paid \ received | R59: BS | S59: 5 | T59: Other long term Liabilities
D60: RK CHEQUE | E60: 0 | F60: 0 | G60: =+E60 -> 0 | H60: =+F60 -> 0 | I60: 0 | J60: 0 | K60: =+IF((G60+I60-H60-J60>0),G60+I60-H60-J60,0) -> 0 | L60: =+IF((H60+J60-G60-I60)>0,H60+J60-G60-I60,0) -> 0 | M60: =SUMIF('Audit entry'!$C:$C,'TB 25-26'!$D60,'Audit entry'!$D:$D) -> 0 | N60: =SUMIF('Audit entry'!$C:$C,'TB 25-26'!$D60,'Audit entry'!$E:$E) -> 0 | O60: =+IF((K60+M60-L60-N60>0),K60+M60-L60-N60,0)/Deno -> 0 | P60: =+IF((L60+N60-K60-M60)>0,L60+N60-K60-M60,0)/Deno -> 0 | Q60: Cash in hand | R60: BS | S60: 13 | T60: Cash and cash equivalents
C61: ADVANCE TAX | E61: 0 | F61: 0 | G61: =+E61 -> 0 | H61: =+F61 -> 0 | I61: 0 | J61: 0 | K61: =+IF((G61+I61-H61-J61>0),G61+I61-H61-J61,0) -> 0 | L61: =+IF((H61+J61-G61-I61)>0,H61+J61-G61-I61,0) -> 0 | M61: =SUMIF('Audit entry'!$C:$C,'TB 25-26'!$D61,'Audit entry'!$D:$D) -> 0 | N61: =SUMIF('Audit entry'!$C:$C,'TB 25-26'!$D61,'Audit entry'!$E:$E) -> 0 | O61: =+IF((K61+M61-L61-N61>0),K61+M61-L61-N61,0)/Deno -> 0 | P61: =+IF((L61+N61-K61-M61)>0,L61+N61-K61-M61,0)/Deno -> 0
D62: TDS RECEIVABLE | E62: 21114220 | F62: 0 | G62: =+E62 -> 21114220 | H62: =+F62 -> 0 | I62: 3434574.7 | J62: 0 | K62: =+IF((G62+I62-H62-J62>0),G62+I62-H62-J62,0) -> 24548794 | L62: =+IF((H62+J62-G62-I62)>0,H62+J62-G62-I62,0) -> 0 | M62: =SUMIF('Audit entry'!$C:$C,'TB 25-26'!$D62,'Audit entry'!$D:$D) -> 0 | N62: =SUMIF('Audit entry'!$C:$C,'TB 25-26'!$D62,'Audit entry'!$E:$E) -> 0 | O62: =+IF((K62+M62-L62-N62>0),K62+M62-L62-N62,0)/Deno -> 24548794 | P62: =+IF((L62+N62-K62-M62)>0,L62+N62-K62-M62,0)/Deno -> 0 | Q62: TDS Receivable | R62: BS | S62: 10 | T62: Long-term loans and advances
C63: DIRECTOR LOAN | E63: 0 | F63: 0 | G63: =+E63 -> 0 | H63: =+F63 -> 0 | I63: 0 | J63: 0 | K63: =+IF((G63+I63-H63-J63>0),G63+I63-H63-J63,0) -> 0 | L63: =+IF((H63+J63-G63-I63)>0,H63+J63-G63-I63,0) -> 0 | M63: =SUMIF('Audit entry'!$C:$C,'TB 25-26'!$D63,'Audit entry'!$D:$D) -> 0 | N63: =SUMIF('Audit entry'!$C:$C,'TB 25-26'!$D63,'Audit entry'!$E:$E) -> 0 | O63: =+IF((K63+M63-L63-N63>0),K63+M63-L63-N63,0)/Deno -> 0 | P63: =+IF((L63+N63-K63-M63)>0,L63+N63-K63-M63,0)/Deno -> 0
D64: DIRECTOR LOAN | E64: 0 | F64: 0 | G64: =+E64 -> 0 | H64: =+F64 -> 0 | I64: 0 | J64: 0 | K64: =+IF((G64+I64-H64-J64>0),G64+I64-H64-J64,0) -> 0 | L64: =+IF((H64+J64-G64-I64)>0,H64+J64-G64-I64,0) -> 0 | M64: =SUMIF('Audit entry'!$C:$C,'TB 25-26'!$D64,'Audit entry'!$D:$D) -> 0 | N64: =SUMIF('Audit entry'!$C:$C,'TB 25-26'!$D64,'Audit entry'!$E:$E) -> 0 | O64: =+IF((K64+M64-L64-N64>0),K64+M64-L64-N64,0)/Deno -> 0 | P64: =+IF((L64+N64-K64-M64)>0,L64+N64-K64-M64,0)/Deno -> 0
C65: IATA SHIPMENT ADVANCE | E65: 0 | F65: 0 | G65: =+E65 -> 0 | H65: =+F65 -> 0 | I65: 0 | J65: 0 | K65: =+IF((G65+I65-H65-J65>0),G65+I65-H65-J65,0) -> 0 | L65: =+IF((H65+J65-G65-I65)>0,H65+J65-G65-I65,0) -> 0 | M65: =SUMIF('Audit entry'!$C:$C,'TB 25-26'!$D65,'Audit entry'!$D:$D) -> 0 | N65: =SUMIF('Audit entry'!$C:$C,'TB 25-26'!$D65,'Audit entry'!$E:$E) -> 0 | O65: =+IF((K65+M65-L65-N65>0),K65+M65-L65-N65,0)/Deno -> 0 | P65: =+IF((L65+N65-K65-M65)>0,L65+N65-K65-M65,0)/Deno -> 0
D66: IATA SHIPMENT ADVANCE | E66: 0 | F66: 0 | G66: =+E66 -> 0 | H66: =+F66 -> 0 | I66: 0 | J66: 0 | K66: =+IF((G66+I66-H66-J66>0),G66+I66-H66-J66,0) -> 0 | L66: =+IF((H66+J66-G66-I66)>0,H66+J66-G66-I66,0) -> 0 | M66: =SUMIF('Audit entry'!$C:$C,'TB 25-26'!$D66,'Audit entry'!$D:$D) -> 0 | N66: =SUMIF('Audit entry'!$C:$C,'TB 25-26'!$D66,'Audit entry'!$E:$E) -> 0 | O66: =+IF((K66+M66-L66-N66>0),K66+M66-L66-N66,0)/Deno -> 0 | P66: =+IF((L66+N66-K66-M66)>0,L66+N66-K66-M66,0)/Deno -> 0
B67: DEFERRED TAX ASSET | E67: 0 | F67: 0 | G67: =+E67 -> 0 | H67: =+F67 -> 0 | I67: 0 | J67: 0 | K67: =+IF((G67+I67-H67-J67>0),G67+I67-H67-J67,0) -> 0 | L67: =+IF((H67+J67-G67-I67)>0,H67+J67-G67-I67,0) -> 0 | M67: =SUMIF('Audit entry'!$C:$C,'TB 25-26'!$D67,'Audit entry'!$D:$D) -> 0 | N67: =SUMIF('Audit entry'!$C:$C,'TB 25-26'!$D67,'Audit entry'!$E:$E) -> 0 | O67: =+IF((K67+M67-L67-N67>0),K67+M67-L67-N67,0)/Deno -> 0 | P67: =+IF((L67+N67-K67-M67)>0,L67+N67-K67-M67,0)/Deno -> 0
D68: DEFERRED TAX ASSET | E68: 597436.32 | F68: 0 | G68: =+E68 -> 597436.32 | H68: =+F68 -> 0 | I68: 0 | J68: 0 | K68: =+IF((G68+I68-H68-J68>0),G68+I68-H68-J68,0) -> 597436.32 | L68: =+IF((H68+J68-G68-I68)>0,H68+J68-G68-I68,0) -> 0 | M68: =SUMIF('Audit entry'!$C:$C,'TB 25-26'!$D68,'Audit entry'!$D:$D) -> 0 | N68: =SUMIF('Audit entry'!$C:$C,'TB 25-26'!$D68,'Audit entry'!$E:$E) -> 0 | O68: =+IF((K68+M68-L68-N68>0),K68+M68-L68-N68,0)/Deno -> 597436.32 | P68: =+IF((L68+N68-K68-M68)>0,L68+N68-K68-M68,0)/Deno -> 0 | R68: BS | S68: 11 | T68: Deferred tax asset
D69: INCOME TAX PAID | E69: 0 | F69: 0 | G69: =+E69 -> 0 | H69: =+F69 -> 0 | I69: 0 | J69: 0 | K69: =+IF((G69+I69-H69-J69>0),G69+I69-H69-J69,0) -> 0 | L69: =+IF((H69+J69-G69-I69)>0,H69+J69-G69-I69,0) -> 0 | M69: =SUMIF('Audit entry'!$C:$C,'TB 25-26'!$D69,'Audit entry'!$D:$D) -> 0 | N69: =SUMIF('Audit entry'!$C:$C,'TB 25-26'!$D69,'Audit entry'!$E:$E) -> 0 | O69: =+IF((K69+M69-L69-N69>0),K69+M69-L69-N69,0)/Deno -> 0 | P69: =+IF((L69+N69-K69-M69)>0,L69+N69-K69-M69,0)/Deno -> 0
A70: LIABILITIES | E70: 0 | F70: 0 | G70: =+E70 -> 0 | H70: =+F70 -> 0 | I70: 0 | J70: 0 | K70: =+IF((G70+I70-H70-J70>0),G70+I70-H70-J70,0) -> 0 | L70: =+IF((H70+J70-G70-I70)>0,H70+J70-G70-I70,0) -> 0 | M70: =SUMIF('Audit entry'!$C:$C,'TB 25-26'!$D70,'Audit entry'!$D:$D) -> 0 | N70: =SUMIF('Audit entry'!$C:$C,'TB 25-26'!$D70,'Audit entry'!$E:$E) -> 0 | O70: =+IF((K70+M70-L70-N70>0),K70+M70-L70-N70,0)/Deno -> 0 | P70: =+IF((L70+N70-K70-M70)>0,L70+N70-K70-M70,0)/Deno -> 0
B71: SHARE HOLDERS FUND | E71: 0 | F71: 0 | G71: =+E71 -> 0 | H71: =+F71 -> 0 | I71: 0 | J71: 0 | K71: =+IF((G71+I71-H71-J71>0),G71+I71-H71-J71,0) -> 0 | L71: =+IF((H71+J71-G71-I71)>0,H71+J71-G71-I71,0) -> 0 | M71: =SUMIF('Audit entry'!$C:$C,'TB 25-26'!$D71,'Audit entry'!$D:$D) -> 0 | N71: =SUMIF('Audit entry'!$C:$C,'TB 25-26'!$D71,'Audit entry'!$E:$E) -> 0 | O71: =+IF((K71+M71-L71-N71>0),K71+M71-L71-N71,0)/Deno -> 0 | P71: =+IF((L71+N71-K71-M71)>0,L71+N71-K71-M71,0)/Deno -> 0
C72: SHARE CAPITAL | E72: 0 | F72: 0 | G72: =+E72 -> 0 | H72: =+F72 -> 0 | I72: 0 | J72: 0 | K72: =+IF((G72+I72-H72-J72>0),G72+I72-H72-J72,0) -> 0 | L72: =+IF((H72+J72-G72-I72)>0,H72+J72-G72-I72,0) -> 0 | M72: =SUMIF('Audit entry'!$C:$C,'TB 25-26'!$D72,'Audit entry'!$D:$D) -> 0 | N72: =SUMIF('Audit entry'!$C:$C,'TB 25-26'!$D72,'Audit entry'!$E:$E) -> 0 | O72: =+IF((K72+M72-L72-N72>0),K72+M72-L72-N72,0)/Deno -> 0 | P72: =+IF((L72+N72-K72-M72)>0,L72+N72-K72-M72,0)/Deno -> 0
D73: EQUITY SHARE CAPITAL | E73: 0 | F73: 200000 | G73: =+E73 -> 0 | H73: =+F73 -> 200000 | I73: 0 | J73: 0 | K73: =+IF((G73+I73-H73-J73>0),G73+I73-H73-J73,0) -> 0 | L73: =+IF((H73+J73-G73-I73)>0,H73+J73-G73-I73,0) -> 200000 | M73: =SUMIF('Audit entry'!$C:$C,'TB 25-26'!$D73,'Audit entry'!$D:$D) -> 0 | N73: =SUMIF('Audit entry'!$C:$C,'TB 25-26'!$D73,'Audit entry'!$E:$E) -> 0 | O73: =+IF((K73+M73-L73-N73>0),K73+M73-L73-N73,0)/Deno -> 0 | P73: =+IF((L73+N73-K73-M73)>0,L73+N73-K73-M73,0)/Deno -> 200000 | Q73: Equity Share Capital | R73: BS | S73: 3 | T73: Share capital
D74: RETAINED EARNINGS | E74: 0 | F74: 12289769 | G74: =+E74 -> 0 | H74: =+F74 -> 12289769 | I74: 0 | J74: 0 | K74: =+IF((G74+I74-H74-J74>0),G74+I74-H74-J74,0) -> 0 | L74: =+IF((H74+J74-G74-I74)>0,H74+J74-G74-I74,0) -> 12289769 | M74: =SUMIF('Audit entry'!$C:$C,'TB 25-26'!$D74,'Audit entry'!$D:$D) -> 0 | N74: =SUMIF('Audit entry'!$C:$C,'TB 25-26'!$D74,'Audit entry'!$E:$E) -> 0 | O74: =+IF((K74+M74-L74-N74>0),K74+M74-L74-N74,0)/Deno -> 0 | P74: =+IF((L74+N74-K74-M74)>0,L74+N74-K74-M74,0)/Deno -> 12289769 | R74: BS | S74: 4 | T74: Reserve and surplus
C75: RESERVES AND SURPLUS | E75: 0 | F75: 0 | G75: =+E75 -> 0 | H75: =+F75 -> 0 | I75: 0 | J75: 0 | K75: =+IF((G75+I75-H75-J75>0),G75+I75-H75-J75,0) -> 0 | L75: =+IF((H75+J75-G75-I75)>0,H75+J75-G75-I75,0) -> 0 | M75: =SUMIF('Audit entry'!$C:$C,'TB 25-26'!$D75,'Audit entry'!$D:$D) -> 0 | N75: =SUMIF('Audit entry'!$C:$C,'TB 25-26'!$D75,'Audit entry'!$E:$E) -> 0 | O75: =+IF((K75+M75-L75-N75>0),K75+M75-L75-N75,0)/Deno -> 0 | P75: =+IF((L75+N75-K75-M75)>0,L75+N75-K75-M75,0)/Deno -> 0
D76: PROFIT AND LOSS ACCOUNT | E76: 0 | F76: 4831701.5 | G76: =+E76 -> 0 | H76: 7484891.8 | I76: 0 | J76: 0 | K76: =+IF((G76+I76-H76-J76>0),G76+I76-H76-J76,0) -> 0 | L76: =+IF((H76+J76-G76-I76)>0,H76+J76-G76-I76,0) -> 7484891.8 | M76: =SUMIF('Audit entry'!$C:$C,'TB 25-26'!$D76,'Audit entry'!$D:$D) -> 0 | N76: =SUMIF('Audit entry'!$C:$C,'TB 25-26'!$D76,'Audit entry'!$E:$E) -> 0 | O76: =+IF((K76+M76-L76-N76>0),K76+M76-L76-N76,0)/Deno -> 0 | P76: =+IF((L76+N76-K76-M76)>0,L76+N76-K76-M76,0)/Deno -> 7484891.8 | R76: BS | S76: 4 | T76: Reserve and surplus
B77: LOAN FUND | E77: 0 | F77: 0 | G77: =+E77 -> 0 | H77: =+F77 -> 0 | I77: 0 | J77: 0 | K77: =+IF((G77+I77-H77-J77>0),G77+I77-H77-J77,0) -> 0 | L77: =+IF((H77+J77-G77-I77)>0,H77+J77-G77-I77,0) -> 0 | M77: =SUMIF('Audit entry'!$C:$C,'TB 25-26'!$D77,'Audit entry'!$D:$D) -> 0 | N77: =SUMIF('Audit entry'!$C:$C,'TB 25-26'!$D77,'Audit entry'!$E:$E) -> 0 | O77: =+IF((K77+M77-L77-N77>0),K77+M77-L77-N77,0)/Deno -> 0 | P77: =+IF((L77+N77-K77-M77)>0,L77+N77-K77-M77,0)/Deno -> 0
C78: SECURED LOAN | E78: 0 | F78: 0 | G78: =+E78 -> 0 | H78: =+F78 -> 0 | I78: 0 | J78: 0 | K78: =+IF((G78+I78-H78-J78>0),G78+I78-H78-J78,0) -> 0 | L78: =+IF((H78+J78-G78-I78)>0,H78+J78-G78-I78,0) -> 0 | M78: =SUMIF('Audit entry'!$C:$C,'TB 25-26'!$D78,'Audit entry'!$D:$D) -> 0 | N78: =SUMIF('Audit entry'!$C:$C,'TB 25-26'!$D78,'Audit entry'!$E:$E) -> 0 | O78: =+IF((K78+M78-L78-N78>0),K78+M78-L78-N78,0)/Deno -> 0 | P78: =+IF((L78+N78-K78-M78)>0,L78+N78-K78-M78,0)/Deno -> 0
D79: LOAN - CIL OMAN | E79: 0 | F79: 0 | G79: =+E79 -> 0 | H79: =+F79 -> 0 | I79: 0 | J79: 0 | K79: =+IF((G79+I79-H79-J79>0),G79+I79-H79-J79,0) -> 0 | L79: =+IF((H79+J79-G79-I79)>0,H79+J79-G79-I79,0) -> 0 | M79: =SUMIF('Audit entry'!$C:$C,'TB 25-26'!$D79,'Audit entry'!$D:$D) -> 0 | N79: =SUMIF('Audit entry'!$C:$C,'TB 25-26'!$D79,'Audit entry'!$E:$E) -> 0 | O79: =+IF((K79+M79-L79-N79>0),K79+M79-L79-N79,0)/Deno -> 0 | P79: =+IF((L79+N79-K79-M79)>0,L79+N79-K79-M79,0)/Deno -> 0
D80: LOAN - ICL UK | E80: 0 | F80: 0 | G80: =+E80 -> 0 | H80: =+F80 -> 0 | I80: 0 | J80: 0 | K80: =+IF((G80+I80-H80-J80>0),G80+I80-H80-J80,0) -> 0 | L80: =+IF((H80+J80-G80-I80)>0,H80+J80-G80-I80,0) -> 0 | M80: =SUMIF('Audit entry'!$C:$C,'TB 25-26'!$D80,'Audit entry'!$D:$D) -> 0 | N80: =SUMIF('Audit entry'!$C:$C,'TB 25-26'!$D80,'Audit entry'!$E:$E) -> 0 | O80: =+IF((K80+M80-L80-N80>0),K80+M80-L80-N80,0)/Deno -> 0 | P80: =+IF((L80+N80-K80-M80)>0,L80+N80-K80-M80,0)/Deno -> 0
D81: HDFC CAR LOAN | E81: 0 | F81: 0 | G81: =+E81 -> 0 | H81: =+F81 -> 0 | I81: 0 | J81: 0 | K81: =+IF((G81+I81-H81-J81>0),G81+I81-H81-J81,0) -> 0 | L81: =+IF((H81+J81-G81-I81)>0,H81+J81-G81-I81,0) -> 0 | M81: =SUMIF('Audit entry'!$C:$C,'TB 25-26'!$D81,'Audit entry'!$D:$D) -> 0 | N81: =SUMIF('Audit entry'!$C:$C,'TB 25-26'!$D81,'Audit entry'!$E:$E) -> 0 | O81: =+IF((K81+M81-L81-N81>0),K81+M81-L81-N81,0)/Deno -> 0 | P81: =+IF((L81+N81-K81-M81)>0,L81+N81-K81-M81,0)/Deno -> 0
C82: UNSECURED LOAN | E82: 0 | F82: 0 | G82: =+E82 -> 0 | H82: =+F82 -> 0 | I82: 0 | J82: 0 | K82: =+IF((G82+I82-H82-J82>0),G82+I82-H82-J82,0) -> 0 | L82: =+IF((H82+J82-G82-I82)>0,H82+J82-G82-I82,0) -> 0 | M82: =SUMIF('Audit entry'!$C:$C,'TB 25-26'!$D82,'Audit entry'!$D:$D) -> 0 | N82: =SUMIF('Audit entry'!$C:$C,'TB 25-26'!$D82,'Audit entry'!$E:$E) -> 0 | O82: =+IF((K82+M82-L82-N82>0),K82+M82-L82-N82,0)/Deno -> 0 | P82: =+IF((L82+N82-K82-M82)>0,L82+N82-K82-M82,0)/Deno -> 0
D83: LOAN - CIL DUBAI | E83: 0 | F83: 0 | G83: =+E83 -> 0 | H83: =+F83 -> 0 | I83: 0 | J83: 0 | K83: =+IF((G83+I83-H83-J83>0),G83+I83-H83-J83,0) -> 0 | L83: =+IF((H83+J83-G83-I83)>0,H83+J83-G83-I83,0) -> 0 | M83: =SUMIF('Audit entry'!$C:$C,'TB 25-26'!$D83,'Audit entry'!$D:$D) -> 0 | N83: =SUMIF('Audit entry'!$C:$C,'TB 25-26'!$D83,'Audit entry'!$E:$E) -> 0 | O83: =+IF((K83+M83-L83-N83>0),K83+M83-L83-N83,0)/Deno -> 0 | P83: =+IF((L83+N83-K83-M83)>0,L83+N83-K83-M83,0)/Deno -> 0
D84: UNSECURED LOAN | E84: 0 | F84: 0 | G84: =+E84 -> 0 | H84: =+F84 -> 0 | I84: 0 | J84: 0 | K84: =+IF((G84+I84-H84-J84>0),G84+I84-H84-J84,0) -> 0 | L84: =+IF((H84+J84-G84-I84)>0,H84+J84-G84-I84,0) -> 0 | M84: =SUMIF('Audit entry'!$C:$C,'TB 25-26'!$D84,'Audit entry'!$D:$D) -> 0 | N84: =SUMIF('Audit entry'!$C:$C,'TB 25-26'!$D84,'Audit entry'!$E:$E) -> 0 | O84: =+IF((K84+M84-L84-N84>0),K84+M84-L84-N84,0)/Deno -> 0 | P84: =+IF((L84+N84-K84-M84)>0,L84+N84-K84-M84,0)/Deno -> 0
D85: Mobile Emi | E85: 0 | F85: 0 | G85: =+E85 -> 0 | H85: =+F85 -> 0 | I85: 0 | J85: 0 | K85: =+IF((G85+I85-H85-J85>0),G85+I85-H85-J85,0) -> 0 | L85: =+IF((H85+J85-G85-I85)>0,H85+J85-G85-I85,0) -> 0 | M85: =SUMIF('Audit entry'!$C:$C,'TB 25-26'!$D85,'Audit entry'!$D:$D) -> 0 | N85: =SUMIF('Audit entry'!$C:$C,'TB 25-26'!$D85,'Audit entry'!$E:$E) -> 0 | O85: =+IF((K85+M85-L85-N85>0),K85+M85-L85-N85,0)/Deno -> 0 | P85: =+IF((L85+N85-K85-M85)>0,L85+N85-K85-M85,0)/Deno -> 0
B86: CURRENT LIABILITIES | E86: 0 | F86: 0 | G86: =+E86 -> 0 | H86: =+F86 -> 0 | I86: 0 | J86: 0 | K86: =+IF((G86+I86-H86-J86>0),G86+I86-H86-J86,0) -> 0 | L86: =+IF((H86+J86-G86-I86)>0,H86+J86-G86-I86,0) -> 0 | M86: =SUMIF('Audit entry'!$C:$C,'TB 25-26'!$D86,'Audit entry'!$D:$D) -> 0 | N86: =SUMIF('Audit entry'!$C:$C,'TB 25-26'!$D86,'Audit entry'!$E:$E) -> 0 | O86: =+IF((K86+M86-L86-N86>0),K86+M86-L86-N86,0)/Deno -> 0 | P86: =+IF((L86+N86-K86-M86)>0,L86+N86-K86-M86,0)/Deno -> 0
C87: SUNDRY CREDITORS | E87: 0 | F87: 0 | G87: =+E87 -> 0 | H87: =+F87 -> 0 | I87: 0 | J87: 0 | K87: =+IF((G87+I87-H87-J87>0),G87+I87-H87-J87,0) -> 0 | L87: =+IF((H87+J87-G87-I87)>0,H87+J87-G87-I87,0) -> 0 | M87: =SUMIF('Audit entry'!$C:$C,'TB 25-26'!$D87,'Audit entry'!$D:$D) -> 0 | N87: =SUMIF('Audit entry'!$C:$C,'TB 25-26'!$D87,'Audit entry'!$E:$E) -> 0 | O87: =+IF((K87+M87-L87-N87>0),K87+M87-L87-N87,0)/Deno -> 0 | P87: =+IF((L87+N87-K87-M87)>0,L87+N87-K87-M87,0)/Deno -> 0
D88: LOCAL CREDITORS - FREIGHT FORWARDING | E88: 0 | F88: 50051493 | G88: =+E88 -> 0 | H88: =+F88 -> 50051493 | I88: 0 | J88: 3313350 | K88: =+IF((G88+I88-H88-J88>0),G88+I88-H88-J88,0) -> 0 | L88: =+IF((H88+J88-G88-I88)>0,H88+J88-G88-I88,0) -> 53364843 | M88: =+'Audit entry'!D43+'Audit entry'!D48-'Audit entry'!E47+SUM('Audit entry'!D181:D201)-SUM('Audit entry'!E181:E201) -> 47629.13 | N88: =+'Audit entry'!E206 -> 1481780 | O88: =+IF((K88+M88-L88-N88>0),K88+M88-L88-N88,0)/Deno -> 0 | P88: =+IF((L88+N88-K88-M88)>0,L88+N88-K88-M88,0)/Deno -> 54798994 | R88: BS | S88: 6 | T88: Trade Payables
D89: INTER BRANCH ACCOUNT | E89: 0 | F89: 1072835.6 | G89: =+E89 -> 0 | H89: =+F89 -> 1072835.6 | I89: 101133.41 | J89: 0 | K89: =+IF((G89+I89-H89-J89>0),G89+I89-H89-J89,0) -> 0 | L89: =+IF((H89+J89-G89-I89)>0,H89+J89-G89-I89,0) -> 971702.21 | M89: =SUMIF('Audit entry'!$C:$C,'TB 25-26'!$D89,'Audit entry'!$D:$D) -> 0 | N89: =SUMIF('Audit entry'!$C:$C,'TB 25-26'!$D89,'Audit entry'!$E:$E) -> 0 | O89: =+IF((K89+M89-L89-N89>0),K89+M89-L89-N89,0)/Deno -> 0 | P89: =+IF((L89+N89-K89-M89)>0,L89+N89-K89-M89,0)/Deno -> 971702.21 | R89: BS | S89: 6 | T89: Trade Payables
D90: INTER BRANCH SUSPENSE ACCOUNT | E90: 1012160 | F90: 0 | G90: =+E90 -> 1012160 | H90: =+F90 -> 0 | I90: 0 | J90: 0 | K90: =+IF((G90+I90-H90-J90>0),G90+I90-H90-J90,0) -> 1012160 | L90: =+IF((H90+J90-G90-I90)>0,H90+J90-G90-I90,0) -> 0 | M90: =SUMIF('Audit entry'!$C:$C,'TB 25-26'!$D90,'Audit entry'!$D:$D) -> 0 | N90: =SUMIF('Audit entry'!$C:$C,'TB 25-26'!$D90,'Audit entry'!$E:$E) -> 0 | O90: =+IF((K90+M90-L90-N90>0),K90+M90-L90-N90,0)/Deno -> 1012160 | P90: =+IF((L90+N90-K90-M90)>0,L90+N90-K90-M90,0)/Deno -> 0 | R90: BS | S90: 6 | T90: Trade Payables
D91: OVERSEAS CREDITORS - FREIGHT FORWARDING | E91: 0 | F91: 40316185 | G91: =+E91 -> 0 | H91: =+F91 -> 40316185 | I91: 0 | J91: 15733491 | K91: =+IF((G91+I91-H91-J91>0),G91+I91-H91-J91,0) -> 0 | L91: =+IF((H91+J91-G91-I91)>0,H91+J91-G91-I91,0) -> 56049676 | M91: =+SUM('Audit entry'!D49:D93)-SUM('Audit entry'!E49:E93)+SUM('Audit entry'!D97:D180)-SUM('Audit entry'!E97:E180) -> 40585.97 | N91: =+SUM('Audit entry'!E30:E38)-SUM('Audit entry'!D30:D38) -> 31324.665 | O91: =+IF((K91+M91-L91-N91>0),K91+M91-L91-N91,0)/Deno -> 0 | P91: =+IF((L91+N91-K91-M91)>0,L91+N91-K91-M91,0)/Deno -> 56040414 | R91: BS | S91: 6 | T91: Trade Payables
D92: OTHER LIABILITY | E92: 0 | F92: 0 | G92: =+E92 -> 0 | H92: =+F92 -> 0 | I92: 151228.32 | J92: 0 | K92: =+IF((G92+I92-H92-J92>0),G92+I92-H92-J92,0) -> 151228.32 | L92: =+IF((H92+J92-G92-I92)>0,H92+J92-G92-I92,0) -> 0 | M92: =SUMIF('Audit entry'!$C:$C,'TB 25-26'!$D92,'Audit entry'!$D:$D) -> 0 | N92: =SUMIF('Audit entry'!$C:$C,'TB 25-26'!$D92,'Audit entry'!$E:$E) -> 0 | O92: =+IF((K92+M92-L92-N92>0),K92+M92-L92-N92,0)/Deno -> 151228.32 | P92: =+IF((L92+N92-K92-M92)>0,L92+N92-K92-M92,0)/Deno -> 0 | Q92: Other Liabilities | R92: BS | S92: 7 | T92: Other Current Liabilities
D93: AUDIT FEES PAYABLE | E93: 0 | F93: 725000 | G93: =+E93 -> 0 | H93: =+F93 -> 725000 | I93: 0 | J93: 0 | K93: =+IF((G93+I93-H93-J93>0),G93+I93-H93-J93,0) -> 0 | L93: =+IF((H93+J93-G93-I93)>0,H93+J93-G93-I93,0) -> 725000 | M93: =SUMIF('Audit entry'!$C:$C,'TB 25-26'!$D93,'Audit entry'!$D:$D) -> 225000 | N93: =SUMIF('Audit entry'!$C:$C,'TB 25-26'!$D93,'Audit entry'!$E:$E) -> 225000 | O93: =+IF((K93+M93-L93-N93>0),K93+M93-L93-N93,0)/Deno -> 0 | P93: =+IF((L93+N93-K93-M93)>0,L93+N93-K93-M93,0)/Deno -> 725000 | Q93: Audit Fee payable | R93: BS | S93: 7 | T93: Other Current Liabilities | U93: Expense payable
D94: GST Audit Fees payable | E94: 0 | F94: 90000 | G94: =+E94 -> 0 | H94: =+F94 -> 90000 | I94: 0 | J94: 0 | K94: =+IF((G94+I94-H94-J94>0),G94+I94-H94-J94,0) -> 0 | L94: =+IF((H94+J94-G94-I94)>0,H94+J94-G94-I94,0) -> 90000 | M94: =SUMIF('Audit entry'!$C:$C,'TB 25-26'!$D94,'Audit entry'!$D:$D) -> 0 | N94: =SUMIF('Audit entry'!$C:$C,'TB 25-26'!$D94,'Audit entry'!$E:$E) -> 0 | O94: =+IF((K94+M94-L94-N94>0),K94+M94-L94-N94,0)/Deno -> 0 | P94: =+IF((L94+N94-K94-M94)>0,L94+N94-K94-M94,0)/Deno -> 90000 | Q94: GST Audit Fees payable | R94: BS | S94: 7 | T94: Other Current Liabilities | U94: Expense payable
C95: OTHER LIABILITIES | E95: 0 | F95: 0 | G95: =+E95 -> 0 | H95: =+F95 -> 0 | I95: 0 | J95: 0 | K95: =+IF((G95+I95-H95-J95>0),G95+I95-H95-J95,0) -> 0 | L95: =+IF((H95+J95-G95-I95)>0,H95+J95-G95-I95,0) -> 0 | M95: =SUMIF('Audit entry'!$C:$C,'TB 25-26'!$D95,'Audit entry'!$D:$D) -> 0 | N95: =SUMIF('Audit entry'!$C:$C,'TB 25-26'!$D95,'Audit entry'!$E:$E) -> 0 | O95: =+IF((K95+M95-L95-N95>0),K95+M95-L95-N95,0)/Deno -> 0 | P95: =+IF((L95+N95-K95-M95)>0,L95+N95-K95-M95,0)/Deno -> 0
E96: 0 | F96: 0 | G96: =+E96 -> 0 | H96: =+F96 -> 0 | I96: 0 | J96: 0 | K96: =+IF((G96+I96-H96-J96>0),G96+I96-H96-J96,0) -> 0 | L96: =+IF((H96+J96-G96-I96)>0,H96+J96-G96-I96,0) -> 0 | M96: =SUMIF('Audit entry'!$C:$C,'TB 25-26'!$D96,'Audit entry'!$D:$D) -> 0 | N96: =SUMIF('Audit entry'!$C:$C,'TB 25-26'!$D96,'Audit entry'!$E:$E) -> 0 | O96: =+IF((K96+M96-L96-N96>0),K96+M96-L96-N96,0)/Deno -> 0 | P96: =+IF((L96+N96-K96-M96)>0,L96+N96-K96-M96,0)/Deno -> 0
D97: CONVEYANCE PAYABLE | E97: 0 | F97: 903854.06 | G97: =+E97 -> 0 | H97: =+F97 -> 903854.06 | I97: 943900.03 | J97: 0 | K97: =+IF((G97+I97-H97-J97>0),G97+I97-H97-J97,0) -> 40045.97 | L97: =+IF((H97+J97-G97-I97)>0,H97+J97-G97-I97,0) -> 0 | M97: =SUMIF('Audit entry'!$C:$C,'TB 25-26'!$D97,'Audit entry'!$D:$D) -> 0 | N97: =SUMIF('Audit entry'!$C:$C,'TB 25-26'!$D97,'Audit entry'!$E:$E) -> 0 | O97: =+IF((K97+M97-L97-N97>0),K97+M97-L97-N97,0)/Deno -> 40045.97 | P97: =+IF((L97+N97-K97-M97)>0,L97+N97-K97-M97,0)/Deno -> 0 | Q97: Convenyance Payable | R97: BS | S97: 7 | T97: Other Current Liabilities | U97: Expense payable
D98: ACCRUALS | E98: 0 | F98: 0 | G98: =+E98 -> 0 | H98: =+F98 -> 0 | I98: 235000 | J98: 0 | K98: =+IF((G98+I98-H98-J98>0),G98+I98-H98-J98,0) -> 235000 | L98: =+IF((H98+J98-G98-I98)>0,H98+J98-G98-I98,0) -> 0 | M98: =SUMIF('Audit entry'!$C:$C,'TB 25-26'!$D98,'Audit entry'!$D:$D) -> 0 | N98: =SUMIF('Audit entry'!$C:$C,'TB 25-26'!$D98,'Audit entry'!$E:$E) -> 235000 | O98: =+IF((K98+M98-L98-N98>0),K98+M98-L98-N98,0)/Deno -> 0 | P98: =+IF((L98+N98-K98-M98)>0,L98+N98-K98-M98,0)/Deno -> 0 | Q98: Audit Fee payable | R98: BS | S98: 7 | T98: Other Current Liabilities | U98: Expense payable
D99: CORPORATE CARD 9003 | E99: 0 | F99: 797544.98 | G99: =+E99 -> 0 | H99: =+F99 -> 797544.98 | I99: 607903.93 | J99: 0 | K99: =+IF((G99+I99-H99-J99>0),G99+I99-H99-J99,0) -> 0 | L99: =+IF((H99+J99-G99-I99)>0,H99+J99-G99-I99,0) -> 189641.05 | M99: =SUMIF('Audit entry'!$C:$C,'TB 25-26'!$D99,'Audit entry'!$D:$D) -> 0 | N99: =SUMIF('Audit entry'!$C:$C,'TB 25-26'!$D99,'Audit entry'!$E:$E) -> 0 | O99: =+IF((K99+M99-L99-N99>0),K99+M99-L99-N99,0)/Deno -> 0 | P99: =+IF((L99+N99-K99-M99)>0,L99+N99-K99-M99,0)/Deno -> 189641.05 | Q99: Other Liabilities | R99: BS | S99: 7 | T99: Other Current Liabilities | U99: Expense payable
D100: CORPORATE CARD 0007 | E100: 0 | F100: 0 | G100: =+E100 -> 0 | H100: =+F100 -> 0 | I100: 0.09 | J100: 0 | K100: =+IF((G100+I100-H100-J100>0),G100+I100-H100-J100,0) -> 0.09 | L100: =+IF((H100+J100-G100-I100)>0,H100+J100-G100-I100,0) -> 0 | M100: =SUMIF('Audit entry'!$C:$C,'TB 25-26'!$D100,'Audit entry'!$D:$D) -> 0 | N100: =SUMIF('Audit entry'!$C:$C,'TB 25-26'!$D100,'Audit entry'!$E:$E) -> 0 | O100: =+IF((K100+M100-L100-N100>0),K100+M100-L100-N100,0)/Deno -> 0.09 | P100: =+IF((L100+N100-K100-M100)>0,L100+N100-K100-M100,0)/Deno -> 0 | Q100: Other Liabilities | R100: BS | S100: 7 | T100: Other Current Liabilities | U100: Expense payable
...

Sheet BS
A1: CARGO INTERNATIONAL (INDIA) PRIVATE LIMITED
A2: BALANCE SHEET AS AT 31ST MARCH, 2026
A3: CIN : U63000TN2010PTC077296
A4: Old No.7 / New No.13, First Floor, First Cross Street, Trustpuram, Kodambakkam, Chennai - 600024, India
A5: =+"(Unless otherwise specified, all amounts are "&IF('Master data'!A2="Ones","Indian Rupees","in "&'Master data'!A2&" of INR)") -> (Unless otherwise specified, all amounts are Indian Rupees
A6: Particulars | B6: Note No. | C6: As on | D6: As on
C7: 31st March, 2026 | D7: 31st March, 2025
A9: I.EQUITY AND LIABILITIES
A10: SHARE HOLDERS FUNDS
A11: a. Share capital | B11: 3 | C11: =+'NOTE 3'!D15 -> 200000 | D11: =+'NOTE 3'!E15 -> 200000
A12: b. Reserve and surplus | B12: 4 | C12: =+'NOTE 4-8'!B15 -> 10342049 | D12: =+'NOTE 4-8'!C15 -> 19774662
C13: =SUM(C11:C12) -> 10542049 | D13: =SUM(D11:D12) -> 19974662
A14: NON CURRENT LIABILITIES
A15: a. Other Long term Liabilities | B15: 5 | C15: =+'NOTE 4-8'!B20 -> 14085282 | D15: =+'NOTE 4-8'!C20 -> 14844185
C16: =+C15 -> 14085282 | D16: =+D15 -> 14844185
A17: CURRENT LIABILITIES
A18: a. Trade payables | B18: 6
A19: i. Outstanding due against MSME | C19: =+'NOTE 6'!G12 -> 0 | D19: =+'NOTE 6'!G24 -> 0
A20: ii.Outstanding due against Other than MSME | C20: =+'NOTE 6'!G17 -> 1.1079895e+08 | D20: =+SUM('NOTE 6'!G25:G27) -> 90428354
A21: b. Other current liabilities | B21: 7 | C21: =+'NOTE 4-8'!B28 -> 7211333.7 | D21: =+'NOTE 4-8'!C28 -> 8950195.1
A22: c. Short term provisions | B22: 8 | C22: =+'NOTE 4-8'!B36 -> 6752023 | D22: =+'NOTE 4-8'!C36 -> 6755308.8
C23: =SUM(C18:C22) -> 1.2476231e+08 | D23: =SUM(D18:D22) -> 1.0613386e+08
A25: TOTAL | C25: =C13+C16+C23 -> 1.4938964e+08 | D25: =D13+D16+D23 -> 1.409527e+08
A27: II.ASSETS
A28: NON-CURRENT ASSETS
A29: a. Property, Plant & Equipment | B29: 9
A30: (i) Tangible assets | C30: =+'Note 9'!J20 -> 843227.31 | D30: =+'Note 9'!K20 -> 733209.25
C31: =SUM(C30:C30) -> 843227.31 | D31: =SUM(D30:D30) -> 733209.25
A33: b. Long-term loans and advances | B33: 10 | C33: =+'NOTE 10-14'!B12 -> 26182475 | D33: =+'NOTE 10-14'!C12 -> 22783878
A34: c. Deffered Tax Assets | B34: 11 | C34: =+'NOTE 10-14'!B18 -> 597436.01 | D34: =+'NOTE 10-14'!C18 -> 597436.01
C35: =+C33+C34 -> 26779911 | D35: =D33+D34 -> 23381314
A36: CURRENT ASSETS
A37: a. Trade receivables | B37: 12 | C37: =+'NOTE 12'!G18 -> 75016042 | D37: =+'NOTE 12'!G30 -> 89905595
A38: b. cash and cash equivalents | B38: 13 | C38: =+'NOTE 10-14'!B24+(1.99/Deno) -> 34223710 | D38: =+'NOTE 10-14'!C24+(1.99/Deno) -> 21693546
A39: c. Short-term loans and advances | B39: 14 | C39: =+'NOTE 10-14'!B31 -> 12526748 | D39: =+'NOTE 10-14'!C31 -> 5239040
C40: =SUM(C37:C39) -> 1.217665e+08 | D40: =SUM(D37:D39) -> 1.1683818e+08
A42: TOTAL | C42: =C31+C35+C40 -> 1.4938964e+08 | D42: =D31+D35+D40 -> 1.409527e+08 | E42: =+C25-C42 -> -0.53688774 | F42: =+D25-D42 -> -0.54755875
E43: =+E42*Deno -> -0.53688774 | F43: =+F42*Deno -> -0.54755875
A44: Significant Accounting Policies in Note 1 & 2
A45: The accompanying notes are integral part of the financial statements
A47: As per our report of even date | B47: For and on behalf of
A48: For Kalyanasundaram & Associates | B48: CARGO INTERNATIONAL (INDIA) PVT. LTD
A49: Chartered accountants
A50: FRN : 05455s
A54: K M Sethu | B54: Suresh Padmanabhan | D54: Vignesh Natarajan
A55: Partner | B55: Director | D55: Director
A56: M.No.231703 | B56: DIN: 08284074 | D56: DIN: 08284068
A57: Place : Chennai | B57: Place : Birmingham | D57: Place : Chennai
A58: Date : | B58: Date: | D58: Date:
A59: UDIN :

Sheet PL
A1: CARGO INTERNATIONAL (INDIA) PRIVATE LIMITED
A2: STATEMENT OF PROFIT AND LOSS FOR YEAR ENDED 31ST MARCH, 2026
A3: CIN: U63000TN2010PTC077296
A4: =+BS!A4 -> Old No.7 / New No.13, First Floor, First Cross Street, Trustpuram, Kodambakkam, Chennai - 600024, India
A5: =+"(Unless otherwise specified, all amounts are "&IF('Master data'!A2="Ones","Indian Rupees","in "&'Master data'!A2&" of INR)") -> (Unless otherwise specified, all amounts are Indian Rupees
A6: Particulars | C6: Note | D6: For Year Ended | E6: For Year Ended
D7: =BS!C7 -> 31st March, 2026 | E7: =BS!D7 -> 31st March, 2025
A9: I | B9: Revenue from Operation | C9: 15 | D9: ='NOTE 15-20'!B14 -> 1.9086401e+08 | E9: ='NOTE 15-20'!C14 -> 2.5105688e+08
A10: II | B10: Other Income | C10: 16 | D10: ='NOTE 15-20'!B20 -> 5016550.7 | E10: ='NOTE 15-20'!C20 -> 6275069.8
A12: III | B12: TOTAL | D12: =SUM(D9:D11) -> 1.9588056e+08 | E12: =SUM(E9:E11) -> 2.5733195e+08
F13: ..
A14: IV | B14: EXPENSES
B15: Operating expenses | C15: 17 | D15: ='NOTE 15-20'!B28 -> 1.5920151e+08 | E15: ='NOTE 15-20'!C28 -> 2.1536675e+08
B16: Employee Benefit Expenses | C16: 18 | D16: ='NOTE 15-20'!B34 -> 19826121 | E16: ='NOTE 15-20'!C34 -> 23047531
B17: Finance cost | C17: 19 | D17: =+'NOTE 15-20'!B41 -> 251861.01 | E17: =+'NOTE 15-20'!C41 -> 266439.7
B18: Administrative expenses | C18: 20 | D18: ='NOTE 15-20'!B57 -> 25769376 | E18: ='NOTE 15-20'!C57 -> 15728139
B19: Depreciation | C19: 9 | D19: ='Note 9'!G20 -> 264309 | E19: =+'Note 9'!G22 -> 269898.93
A21: V | B21: TOTAL | D21: =SUM(D15:D20) -> 2.0531317e+08 | E21: =SUM(E15:E20) -> 2.5467876e+08
A23: VI | B23: Profit before exceptional and extraordinary item and tax (III - V) | D23: =D12-D21 -> -9432613.1 | E23: =E12-E21 -> 2653190.3
A25: VII | B25: Exceptional items/extra-ordinary items | D25: 0 | E25: 0
A27: VIII | B27: Profit before extra-ordinary item and tax (VI - VII) | D27: =D23-D25 -> -9432613.1 | E27: =E23-E25 -> 2653190.3
A29: IX | B29: Profit before tax (VIII) | D29: =D27 -> -9432613.1 | E29: =E27 -> 2653190.3
A30: X | B30: Tax expenses
B31: (1) Current Tax | D31: 0 | E31: =654762.486071762/Deno -> 654762.49
B32: (2) Deferred Tax | D32: 0 | E32: =-37521.6847891985/Deno -> -37521.685
B33: Prior period items
A34: XI | B34: Profit/(Loss) for the period from continuing operation (IX-X) | D34: =D29-D31+D32+D33 -> -9432613.1 | E34: =E29-E31+E32+E33 -> 1960906.2
A36: XII | B36: EPS
B37: Basic | D37: =+(D34/'NOTE 3'!D40)*Deno -> -471.63065 | E37: =+(E34/'NOTE 3'!D30)*Deno -> 98.055113
B38: Diluted | D38: =+D37 -> -471.63065 | E38: =+E37 -> 98.055113
A40: =BS!A44 -> Significant Accounting Policies in Note 1 & 2
A41: The accompanying notes are integral part of the financial statements
A43: As per our report of even date | C43: For and on behalf of
A44: For Kalyanasundaram & Associates | C44: =+BS!B48 -> CARGO INTERNATIONAL (INDIA) PVT. LTD
A45: Chartered accountants
A46: FRN : 005455S
A50: K M Sethu | C50: =+BS!B54 -> Suresh Padmanabhan | E50: =+BS!D54 -> Vignesh Natarajan
A51: Partner | C51: =+BS!B55 -> Director | E51: =+BS!D55 -> Director
A52: M.No.231703 | C52: =+BS!B56 -> DIN: 08284074 | E52: =+BS!D56 -> DIN: 08284068
A53: Place : Chennai | C53: =+BS!B57 -> Place : Birmingham | E53: =+BS!D57 -> Place : Chennai
A54: =+BS!A58 -> Date : | C54: =+BS!B58 -> Date: | E54: =+BS!D58 -> Date:
A55: =+BS!A59 -> UDIN :

Sheet Sub-Schedule
A1: Advance Paid/Received | B1: Closing Balance as of FY 2025-26 | D1: Closing Balance as of FY 2024-25
A2: Particulars | B2: Debit Rs. | C2: Credit Rs. | D2: Debit Rs. | E2: Credit Rs.
A3: Advance From Debtors
A4: CARGO INTERNATIONAL (INDIA) PRIVATE LTD | B4: 0 | C4: =+'TB 25-26'!P59 -> 14085282 | D4: 0 | E4: 1750 | F4: RPT | G4: Non current
A5: CIL Dubai | B5: 0 | C5: 0 | D5: 0 | E5: 10067831 | F5: RPT | G5: Non current
A6: CARGO INTERNATIONAL LTD | B6: 0 | C6: 0 | D6: 0 | E6: 5866971.3 | F6: RPT | G6: Non current
A7: CARGO INTERNATIONAL (INDIA) PRIVATE LTD | B7: 0 | C7: 0 | D7: 0 | E7: 110628 | F7: RPT | G7: Non current
A8: ADVANCE TO CREDITORS
A9: CARGO INTERNATIONAL LTD | B9: 0 | C9: 0 | D9: 214646.99 | E9: 0 | F9: RPT | G9: Non current
A10: CATHAY PACIFIC | B10: 0 | C10: 0 | D10: 0.3 | E10: 0 | F10: Others | G10: Current
A11: CMA CGM | B11: 0 | C11: 0 | D11: 198625.57 | E11: 0 | F11: Others | G11: Current
A12: CONTAINER CORPORATION OF INDIA LIMITED | B12: 0 | C12: 0 | D12: 193519.1 | E12: 0 | F12: Others | G12: Current
A13: MAERSK | B13: 0 | C13: 0 | D13: 31739.96 | E13: 0 | F13: Others | G13: Current
A14: CARGO INTERNATIONAL (INDIA) PRIVATE LTD | B14: 0 | C14: 0 | D14: 988348 | E14: 0 | F14: RPT | G14: Non current
A15: ASHA LUBE SOLUTIONS PVT LTD | B15: 0 | C15: 0 | D15: 0.18 | E15: 0 | F15: Others | G15: Current
A16: BELL PRINTERS (P) LTD | B16: 0 | C16: 0 | D16: 0 | E16: 9732 | F16: Others | G16: Current
A17: RL FINE CHEM PVT LTD | B17: 0 | C17: 0 | D17: 0 | E17: 19072 | F17: Others | G17: Current
A18: AURONATURE | B18: 0 | C18: 0 | D18: 0 | E18: 33 | F18: Others | G18: Current
A19: EXPRESS CARGO MOVERS | B19: 0 | C19: 0 | D19: 0 | E19: 5220 | F19: Others | G19: Current
A20: SRI VBL ASSOCIATES | B20: 0 | C20: 0 | D20: 0 | E20: 270 | F20: Others | G20: Current
... A32: COGENT EXPORTS | B32: 0 | C32: 0 | D32: 236 | E32: 0 | F32: Others | G32: Current
A34: TOTAL | B34: =SUBTOTAL(9,B4:B33) -> 0 | C34: =SUBTOTAL(9,C4:C33) -> 14085282 | D34: =SUBTOTAL(9,D4:D33) -> 1627116.1 | E34: =SUBTOTAL(9,E4:E33) -> 16474587
C35: =+B34-C34 -> -14085282 | E35: =+D34-E34 -> -14847471 | F35: 14844185
C38: =+C39-B39 -> 0 | E38: =+E39-D39 -> 0 | G38: =+G39-F39 -> 0
B39: =+_xlfn.AGGREGATE(9,0,B42:B42) -> 0 | C39: =+_xlfn.AGGREGATE(9,0,C42:C42) -> 0 | D39: =+_xlfn.AGGREGATE(9,0,D42:D42) -> 0 | E39: =+_xlfn.AGGREGATE(9,0,E42:E42) -> 0 | F39: =+_xlfn.AGGREGATE(9,0,F42:F42) -> 0 | G39: =+_xlfn.AGGREGATE(9,0,G42:G42) -> 0
A40: Provision for Operation | B40: Closing Balance as of FY 2023-24 | D40: During the yr Transaction/Audit entry | F40: Closing Balance as of FY 2024-25
A41: Particulars | B41: Debit Rs. | C41: Credit Rs. | D41: Debit Rs. | E41: Credit Rs. | F41: Debit Rs. | G41: Credit Rs.
A42: Creditors From Provisions GL
A44: Note : Balance in Provision operation has been closed and transferred to reserves

Sheet CFS
A1: =+PL!A1 -> CARGO INTERNATIONAL (INDIA) PRIVATE LIMITED
A2: CASH FLOW STATEMENT FOR THE YEAR ENDED ON 31ST MARCH 2026
A3: CIN: U63000TN2010PTC077296
A4: =+PL!A4 -> Old No.7 / New No.13, First Floor, First Cross Street, Trustpuram, Kodambakkam, Chennai - 600024, India
A5: =+"(Unless otherwise specified, all amounts are "&IF('Master data'!A2="Ones","Indian Rupees","in "&'Master data'!A2&" of INR)") -> (Unless otherwise specified, all amounts are Indian Rupees
A6: Particulars | C6: For Year Ended | D6: For Year Ended
C7: =PL!D7 -> 31st March, 2026 | D7: =PL!E7 -> 31st March, 2025
A9: [A] Cash Flow from Operating Activities:
A11: Profit before Tax | C11: =+PL!D27 -> -9432613.1 | D11: =+PL!E27 -> 2653190.3
A12: Adjustments for non cash items & Non operating activity:
A13: Depreciation | C13: =+PL!D19 -> 264309 | D13: =+PL!E19 -> 269898.93
A14: GST Input reversal | C14: =+'NOTE 4-8'!B12 -> 0 | D14: 0
A15: Provision Operation reversal | C15: =+'NOTE 4-8'!B13 -> 5.8207661e-11 | D15: =+'NOTE 4-8'!C13 -> 14106836
A16: Interest & Finance Charges | C16: =+PL!D17 -> 251861.01 | D16: =+PL!E17 -> 266439.7
A17: Operating Profit before Working Capital changes | C17: =SUM(C11:C16) -> -8916443 | D17: =SUM(D11:D16) -> 17296365
A19: Adjusted for :
A20: (Increase)/Decrease in Loans & Advances | C20: =-BS!C39+BS!D39 -> -7287708.5 | D20: =2222413.90333331/Deno -> 2222413.9
A21: (Increase)/Decrease in Sundry Debtors | C21: =-BS!C37+BS!D37 -> 14889553 | D21: =-36525991.49/Deno -> -36525991
A22: Increase/(Decrease) in Current liabilities | C22: =+BS!C23-BS!D23 -> 18628450 | D22: =35894501.36/Deno -> 35894501
A24: Current year Tax: | C24: =-PL!D31 -> 0 | D24: =-PL!E31 -> -654762.49
A26: Net Cash from Operating Activities | C26: =SUM(C17:C24) -> 17313852 | D26: =SUM(D17:D24) -> 18232527
A28: [B] Cash flow from Investing Activities
A29: Additions to fixed assets | C29: =-'Note 9'!C20+'Note 9'!D20 -> -374327.06 | D29: =-88966.11/Deno -> -88966.11
A30: Increase in Long term loans and advances | C30: =-BS!C33+BS!D33 -> -3398597.2 | D30: =-2301145.87392824/Deno -> -2301145.9
A31: Net cash from/(used in) investing activities | C31: =SUM(C29:C30) -> -3772924.3 | D31: =SUM(D29:D30) -> -2390112
A33: [C] Cash flow from Financing Activities
A34: Interest & Finance Charges | C34: =-C16 -> -251861.01 | D34: =-D16 -> -266439.7
A36: Net cash from/(used in) Financing activities | C36: =SUM(C34:C35) -> -251861.01 | D36: =SUM(D34:D35) -> -266439.7
A38: Net Cash flow during the year [A + B + C] | C38: =C26+C31+C36 -> 13289066 | D38: =D26+D31+D36 -> 15575975
A40: Cash & Cash equivalents (Opening Balance) | C40: =+D41 -> 21693546 | D40: =6117571.56499107/Deno -> 6117571.6
A41: Cash & Cash equivalents (Closing Balance) | C41: =+BS!C38 -> 34223710 | D41: =+BS!D38 -> 21693546
A43: Net Cash flow during the year | C43: =C41-C40 -> 12530164 | D43: =D41-D40 -> 15575975 | E43: =+C38-C43 -> 758902.76 | F43: =+D38-D43 -> 0.30745534
A45: Significant Accounting Policies in Note 1 & 2 | E45: =+E43*Deno -> 758902.76 | F45: =+F43*Deno -> 0.30745534
A46: The accompanying notes are integral part of the financial statements
A48: As per our report of even date | B48: For and on behalf of
A49: For Kalyanasundaram & Associates | B49: =+PL!C44 -> CARGO INTERNATIONAL (INDIA) PVT. LTD
A50: Chartered accountants
A51: FRN : 05455s
A55: K M Sethu | B55: =+PL!C50 -> Suresh Padmanabhan | D55: =+PL!E50 -> Vignesh Natarajan
A56: Partner | B56: Director | D56: =+PL!E51 -> Director
A57: M.No.231703 | B57: =+PL!C52 -> DIN: 08284074 | D57: =+PL!E52 -> DIN: 08284068
A58: Place : Chennai | B58: =+PL!C53 -> Place : Birmingham | D58: =+PL!E53 -> Place : Chennai
A59: =+PL!A54 -> Date : | B59: =+PL!C54 -> Date: | D59: =+PL!E54 -> Date:
A60: =+PL!A55 -> UDIN :

Sheet NOTE 3
A1: CARGO INTERNATIONAL (INDIA) PRIVATE LIMITED
A2: NOTES TO THE FINANCIAL STATEMENTS FOR THE YEAR ENDED 31st MARCH, 2026
A3: =+CFS!A4 -> Old No.7 / New No.13, First Floor, First Cross Street, Trustpuram, Kodambakkam, Chennai - 600024, India
E4: =+"(Unless otherwise specified, all amounts are "&IF('Master data'!A2="Ones","Indian Rupees","in "&'Master data'!A2&" of INR)") -> (Unless otherwise specified, all amounts are Indian Rupees
A5: =+'NOTE 4-8'!A5 -> Particulars | D5: As on | E5: As on
D6: =CFS!C7 -> 31st March, 2026 | E6: =CFS!D7 -> 31st March, 2025
A7: NOTE 3 : SHARE CAPITAL
A8: Authorised share capital
A9: Equity Share Capital | D9: =5000000/Deno -> 5000000 | E9: =5000000/Deno -> 5000000 | G9: =10^5 -> 100000
A10: (500,000 equity shares of Rs.10 each)
D11: =D9 -> 5000000 | E11: =E9 -> 5000000
A12: Issued, subscribed and paid up capital
A13: Equity Share Capital | D13: =200000/Deno -> 200000 | E13: =200000/Deno -> 200000
A14: (20,000 equity shares of Rs.10 each)
D15: =SUM(D12:D13) -> 200000 | E15: =SUM(E12:E13) -> 200000
A17: A. Terms and Rights attached to equity shares
A18: The company has only one class of equity shares having a par value of Rs. 10 per share. Each holder of equity share entitled to one vote per share. The company declares and pays dividend in Indian Rupees The dividend proposed by the Board of directors is subject o the approval of the shareholders in the ensuring Annual General Meeting.
A20: During the year ended 31st March 2025, the amount per share dividend recognised as distrubition to shareholders was Rs. NIL (31st march 2024 - NIL)
A23: B. Shareholders holding more than 5 percent of equity shares
A24: Name of the Shareholder | B24: =+D6 -> 31st March, 2026 | D24: =+E6 -> 31st March, 2025
B25: No. Of Shares | C25: % holding | D25: No. Of Shares | E25: % holding
A26: Suresh Padmanabhan | B26: 15998 | C26: =+B26/$B$30 -> 0.79998 | D26: 15998 | E26: =+D26/$B$30 -> 0.79998 | G26: =+D26/20000 -> 0.7999
A27: Ramkumar | B27: 2000 | C27: =+B27/$B$30 -> 0.10001 | D27: 2000 | E27: =+D27/$B$30 -> 0.10001
A28: Prasath | B28: 2000 | C28: =+B28/$B$30 -> 0.10001 | D28: 2000 | E28: =+D28/$B$30 -> 0.10001
A30: Total | B30: =SUM(B26:B29) -> 19998 | C30: =SUM(C26:C29) -> 1 | D30: =SUM(D26:D29) -> 19998 | E30: =SUM(E26:E29) -> 1
A33: C. Reconciliation of shares outstanding at the beginning and at the end of the reporting period.
A35: Particulars | B35: =+B24 -> 31st March, 2026 | D35: =+D24 -> 31st March, 2025
B36: No. Of Shares | C36: Amount | D36: No. Of Shares | E36: Amount
A37: Shares outstanding at the beginning of the year | B37: 20000 | C37: =+B37*10 -> 200000 | D37: 20000 | E37: =+D37*10 -> 200000
A38: Shares issued during the year | B38: 0 | C38: 0 | D38: 0 | E38: =+D38*10 -> 0
A39: Shares bought back during the year | B39: 0 | C39: =+B39*10 -> 0 | D39: 0 | E39: =+D39*10 -> 0
A40: Shares outstanding at the end of the year | B40: =SUM(B37:B39) -> 20000 | C40: =SUM(C37:C39) -> 200000 | D40: =SUM(D37:D39) -> 20000 | E40: =SUM(E37:E39) -> 200000
A43: D. Shares held by promoters at the end of the year
A44: Shares held by promoters at the end of the year 31st March 2026
A45: Name of the Promoter | B45: No. Of Shares | C45: Amount (Rs.) | D45: % of Total shares | E45: % Change during the year 2025
A46: Suresh Padmanabhan | B46: 15998 | C46: =+B46*10 -> 159980 | D46: =+B46/$B$50 -> 0.79998 | E46: =+(C55-C46)/C46 -> 0
A47: Ramkumar | B47: 2000 | C47: =+B47*10 -> 20000 | D47: =+B47/$B$50 -> 0.10001 | E47: =+(C56-C47)/C47 -> 0
A48: Prasath | B48: 2000 | C48: =+B48*10 -> 20000 | D48: =+B48/$B$50 -> 0.10001 | E48: =+(C57-C48)/C48 -> 0
A50: Total | B50: =SUM(B46:B48) -> 19998 | C50: =SUM(C46:C48) -> 199980 | D50: =SUM(D46:D48) -> 1
A53: Shares held by promoters at the end of the year 31st March 2025
A54: Name of the Promoter | B54: No. Of Shares | C54: Amount (Rs.) | D54: % of Total shares | E54: % Change during the year 2024
A55: Suresh Padmanabhan | B55: 15998 | C55: =+B55*10 -> 159980 | D55: =+B55/$B$50 -> 0.79998 | E55: 0
A56: Ramkumar | B56: 2000 | C56: =+B56*10 -> 20000 | D56: =+B56/$B$59 -> 0.10001 | E56: 0
A57: Prasath | B57: 2000 | C57: =+B57*10 -> 20000 | D57: =+B57/$B$59 -> 0.10001 | E57: 0
A59: Total | B59: =SUM(B55:B58) -> 19998 | C59: =SUM(C55:C58) -> 199980 | D59: =SUM(D55:D58) -> 1

Sheet Note 1-2
A1: CARGO INTERNATIONAL (INDIA) PRIVATE LIMITED
A2: NOTES TO THE FINANCIAL STATEMENTS FOR THE YEAR ENDED 31st MARCH, 2026
A3: CAPITAL TOWERS, NO.G-3/1, G-3/2 & G-2 DOOR NO.180 KODAMBAKKAM HIGH ROAD, NUNGAMBAKKAM CHENNAI 600034
A5: NOTE 1: GENERAL INFORMATION
A6: CARGO INTERNATIONAL (INDIA) PVT LTD is a Private Limited Company incorporated under the provisions of Companies Act 2013. The company is providing clearing and Forwarding services. The company is providing clearing & forwarding Transport Services to their clients through Air, Road and Sea Transport
A8: NOTE 2: SIGNIFICANT ACCOUNTING POLICIES
A9: 2.1) Basis of preparation of Financial statements:
A10: All financial transactions have been recognized on accrual basis in accordance of companies Act 2013 and Accounting Standards as adopted consistently by the company. The preparation of financial statements in conformity with the GAAP requires that the management makes estimates and assumptions that affect the reported amounts of assets and liabilities, disclosure of contingent liabilities as at the date of the financial statements and the reported amounts of revenue and expenses during the period.
A12: 2.2) Use of Estimates
A13: The preparation of financial statements requires management to make estimates and assumptions that affect the reported amount of asset and liabilities, the disclosure of contingent assets and liabilities on the date of financial statements and the reported amount of revenue and expenses during the period reported. Actual result could differ from those estimates.
A15: 2.3) Property, Plant and Equipment
A16: Property, Plant and Equipment has been accounted at their cost including all expenses such as transportation charges, installation expenses etc., incurred wholly and exclusively for the purpose of putting the assets into the use.
... A40: Contingent Assets are neither disclosed nor provided for in the financial statements.

Sheet NOTE 4-8
A1: =BS!A1 -> CARGO INTERNATIONAL (INDIA) PRIVATE LIMITED
A2: NOTES TO THE FINANCIAL STATEMENTS FOR THE YEAR ENDED 31st MARCH, 2026
A3: CAPITAL TOWERS, NO.G-3/1, G-3/2 & G-2 ,DOOR NO.180 KODAMBAKKAM HIGH ROAD, NUNGAMBAKKAM, CHENNAI - 600034
C4: =+"(Unless otherwise specified, all amounts are "&IF('Master data'!A2="Ones","Indian Rupees","in "&'Master data'!A2&" of INR)") -> (Unless otherwise specified, all amounts are Indian Rupees
A5: Particulars | B5: As on | C5: As on
B6: ='NOTE 3'!D6 -> 31st March, 2026 | C6: ='NOTE 3'!E6 -> 31st March, 2025
A8: NOTE 4 : RESERVES AND SURPLUS
A9: General Reserve
A10: Opening balance | B10: =+C15 -> 19774662 | C10: =3706919.29565958/Deno -> 3706919.3
A11: Add:Net Profit/(Loss) for the current year | B11: =PL!D34 -> -9432613.1 | C11: =PL!E34 -> 1960906.2
A12: Less: GST Input reversal | B12: 0 | C12: 0
A13: Add: Provision operation reversal | B13: =+'Audit entry'!E113/Deno -> 5.8207661e-11 | C13: =14106836.38/Deno -> 14106836
A14: (Refer Note. 21(9))
B15: =SUM(B10:B14) -> 10342049 | C15: =SUM(C10:C14) -> 19774662
A17: NOTE 5 : NON CURRENT LIABILITIES
A18: Other Long term Liabilities | B18: =(SUMIF('Sub-Schedule'!F4:F32,"RPT",'Sub-Schedule'!C4:C32)-SUMIF('Sub-Schedule'!F4:F32,"RPT",'Sub-Schedule'!B4:B32))/(+Deno) -> 14085282 | C18: =(SUMIF('Sub-Schedule'!F4:F32,"RPT",'Sub-Schedule'!E4:E32)-SUMIF('Sub-Schedule'!F4:F32,"RPT",'Sub-Schedule'!D4:D32))/(+Deno) -> 14844185
B20: =SUM(B18:B19) -> 14085282 | C20: =SUM(C18:C19) -> 14844185
A23: NOTE 7 : OTHER CURRENT LIABILITIES
A24: Expense payable | B24: =(+'Sub Sch - BS'!B12) -> 2591375.3 | C24: =(+'Sub Sch - BS'!C12) -> 3730924.3
A25: Other Liabilities | B25: =(SUMIF('TB 25-26'!$Q:$Q,$A25,'TB 25-26'!$P:$P)-SUMIF('TB 25-26'!$Q:$Q,$A25,'TB 25-26'!$O:$O)) -> 38412.64 | C25: =(SUMIF('TB 25-26'!$Q:$Q,$A25,'TB 25-26'!$F:$F)-SUMIF('TB 25-26'!$Q:$Q,$A25,'TB 25-26'!$E:$E)) -> 797544.98
A26: Statutory Dues payables | B26: =(+'Sub Sch - BS'!B25) -> 4581545.8 | C26: =(+'Sub Sch - BS'!C25) -> 4421725.8
B28: =SUM(B24:B27) -> 7211333.7 | C28: =SUM(C24:C27) -> 8950195.1
A30: NOTE 8 : SHORT TERM PROVISIONS
A31: Provision for income tax | B31: =(SUMIF('TB 25-26'!$Q:$Q,$A31,'TB 25-26'!$P:$P)-SUMIF('TB 25-26'!$Q:$Q,$A31,'TB 25-26'!$O:$O)) -> 6752023 | C31: =(SUMIF('TB 25-26'!$Q:$Q,$A31,'TB 25-26'!$F:$F)-SUMIF('TB 25-26'!$Q:$Q,$A31,'TB 25-26'!$E:$E)) -> 6752023
A32: Provisions non business | B32: =(SUMIF('TB 25-26'!$Q:$Q,$A32,'TB 25-26'!$P:$P)-SUMIF('TB 25-26'!$Q:$Q,$A32,'TB 25-26'!$O:$O)) -> 0 | C32: =(SUMIF('TB 25-26'!$Q:$Q,$A32,'TB 25-26'!$F:$F)-SUMIF('TB 25-26'!$Q:$Q,$A32,'TB 25-26'!$E:$E)) -> 0
A33: Provisions operations | B33: =(SUMIF('TB 25-26'!$Q:$Q,$A33,'TB 25-26'!$P:$P)-SUMIF('TB 25-26'!$Q:$Q,$A33,'TB 25-26'!$O:$O)) -> 0 | C33: =(SUMIF('TB 25-26'!$Q:$Q,$A33,'TB 25-26'!$F:$F)-SUMIF('TB 25-26'!$Q:$Q,$A33,'TB 25-26'!$E:$E)) -> 0 | D33: CY tax included
A34: Advance paid \ received | B34: =(SUMIF('Sub-Schedule'!F4:F32,"others",'Sub-Schedule'!C4:C32)-SUMIF('Sub-Schedule'!F4:F32,"others",'Sub-Schedule'!B4:B32))/(+Deno) -> 0 | C34: =(SUMIF('Sub-Schedule'!F4:F32,"Others",'Sub-Schedule'!E4:E32)-SUMIF('Sub-Schedule'!F4:F32,"Others",'Sub-Schedule'!D4:D32))/(+Deno) -> 3285.8
B36: =SUM(B31:B35) -> 6752023 | C36: =SUM(C31:C35) -> 6755308.8

Sheet NOTE 6
A1: =BS!A1 -> CARGO INTERNATIONAL (INDIA) PRIVATE LIMITED
A2: NOTES TO THE FINANCIAL STATEMENTS FOR THE YEAR ENDED 31st MARCH, 2026
A3: CAPITAL TOWERS, NO.G-3/1, G-3/2 & G-2 ,DOOR NO.180 KODAMBAKKAM HIGH ROAD, NUNGAMBAKKAM, CHENNAI - 600034
A5: NOTE 6 : TRADE PAYABLES
A6: Sundry creditors
G7: =+"(Unless otherwise specified, all amounts are "&IF('Master data'!A2="Ones","Indian Rupees","in "&'Master data'!A2&" of INR)") -> (Unless otherwise specified, all amounts are Indian Rupees
A8: Particulars | B8: As on Mar 31,2026
B9: Outstanding for following periods from due date of payment
B10: Less than 6 months | C10: 6 months to 1 year | D10: 1 - 2 years | E10: 2 - 3 years | F10: more than 3 years | G10: TOTAL
I11: Checking
A12: MSME | B12: =0/(+Deno) -> 0 | C12: =0/(+Deno) -> 0 | D12: =0/(+Deno) -> 0 | E12: =0/(+Deno) -> 0 | F12: =0/(+Deno) -> 0 | G12: 0 | H12: Ageing | I12: =+G17 -> 1.1079895e+08
A13: Others | B13: =0/(+Deno) -> 0 | C13: 78071781 | D13: 31486478 | E13: 86142.71 | F13: 1154548.9 | G13: =+SUM(B13:F13) -> 1.1079895e+08 | H13: TB | I13: =+'TB 25-26'!P88+'TB 25-26'!P89+'TB 25-26'!P91-'TB 25-26'!O90 -> 1.1079895e+08
A14: Disputed Dues (MSME) | B14: =0/(+Deno) -> 0 | C14: =0/(+Deno) -> 0 | D14: =0/(+Deno) -> 0 | E14: =0/(+Deno) -> 0 | F14: =0/(+Deno) -> 0 | G14: 0 | I14: =+I12-I13 -> 0.30817801
A15: Disputed Dues (Others) | B15: =0/(+Deno) -> 0 | C15: =0/(+Deno) -> 0 | D15: =0/(+Deno) -> 0 | E15: =0/(+Deno) -> 0 | F15: =0/(+Deno) -> 0 | G15: 0
A17: TOTAL | B17: =SUM(B12:B16) -> 0 | C17: =SUM(C12:C16) -> 78071781 | D17: =SUM(D12:D16) -> 31486478 | E17: =SUM(E12:E16) -> 86142.71 | F17: =SUM(F12:F16) -> 1154548.9 | G17: =SUM(G12:G16) -> 1.1079895e+08
A20: Particulars | B20: As on Mar 31, 2025
B21: Outstanding for following periods from due date of payment
B22: Less than 6 months | C22: 6 months to 1 year | D22: 1 - 2 years | E22: 2 - 3 years | F22: more than 3 years | G22: TOTAL
A24: MSME | B24: =0/(+Deno) -> 0 | C24: =0/(+Deno) -> 0 | D24: =0/(+Deno) -> 0 | E24: =0/(+Deno) -> 0 | F24: =0/(+Deno) -> 0 | G24: =+SUM(B24:F24) -> 0
A25: Others | B25: 0 | C25: =87765031.46/Deno -> 87765031 | D25: =1246926.2/Deno -> 1246926.2 | E25: =431714.91/Deno -> 431714.91 | F25: =984680.99/Deno -> 984680.99 | G25: =+SUM(B25:F25) -> 90428354
A26: Disputed Dues (MSME) | B26: =0/(+Deno) -> 0 | C26: =0/(+Deno) -> 0 | D26: =0/(+Deno) -> 0 | E26: =0/(+Deno) -> 0 | F26: =0/(+Deno) -> 0 | G26: =+SUM(B26:F26) -> 0
A27: Disputed Dues (Others) | B27: =0/(+Deno) -> 0 | C27: =0/(+Deno) -> 0 | D27: =0/(+Deno) -> 0 | E27: =0/(+Deno) -> 0 | F27: =0/(+Deno) -> 0 | G27: =+SUM(B27:F27) -> 0
A29: TOTAL | B29: =SUM(B24:B28) -> 0 | C29: =SUM(C24:C28) -> 87765031 | D29: =SUM(D24:D28) -> 1246926.2 | E29: =SUM(E24:E28) -> 431714.91 | F29: =SUM(F24:F28) -> 984680.99 | G29: =SUM(G24:G28) -> 90428354
B33: Note : Amount is derived from TP reconcilation from Ageing folder
C35: =+Deno -> 1

Sheet NOTE 12
A1: =BS!A1 -> CARGO INTERNATIONAL (INDIA) PRIVATE LIMITED
A2: NOTES TO THE FINANCIAL STATEMENTS FOR THE YEAR ENDED 31st MARCH, 2026
A3: CAPITAL TOWERS, NO.G-3/1, G-3/2 & G-2 ,DOOR NO.180 KODAMBAKKAM HIGH ROAD, NUNGAMBAKKAM, CHENNAI - 600034
A5: NOTE 12 : TRADE RECEIVABLES
A6: Sundry Debtors
G8: =+"(Unless otherwise specified, all amounts are "&IF('Master data'!A2="Ones","Indian Rupees","in "&'Master data'!A2&" of INR)") -> (Unless otherwise specified, all amounts are Indian Rupees
A9: Particulars | B9: As on Mar 31,2026
B10: Outstanding for following periods from due date of payment
B11: Less than 6 months | C11: 6 months to 1 year | D11: 1 - 2 years | E11: 2 - 3 years | F11: more than 3 years | G11: TOTAL | I11: Checking
H12: Ageing | I12: =+G18 -> 75016042
A13: Undisputed Trade receivables considered Good | B13: 72503775 | C13: 322480.64 | D13: 25493.98 | E13: 2164293.1 | F13: 0 | G13: =SUM(B13:F13) -> 75016042 | H13: TB | I13: =+'TB 25-26'!O20+'TB 25-26'!O21 -> 75016042
A14: Undisputed Trade receivables considered doubtful | B14: 0 | C14: 0 | D14: 0 | E14: 0 | F14: 0 | G14: =SUM(B14:F14) -> 0 | I14: =+I12-I13 -> 0
A15: Disputed Trade receivable considered Good | B15: 0 | C15: 0 | D15: 0 | E15: 0 | F15: 0 | G15: =SUM(B15:F15) -> 0
A16: Disputed Trade receivable considered doubtful | B16: 0 | C16: 0 | D16: 0 | E16: 0 | F16: 0 | G16: =SUM(B16:F16) -> 0
A18: TOTAL | B18: =SUM(B13:B17) -> 72503775 | C18: =SUM(C13:C17) -> 322480.64 | D18: =SUM(D13:D17) -> 25493.98 | E18: =SUM(E13:E17) -> 2164293.1 | F18: =SUM(F13:F17) -> 0 | G18: =SUM(G13:G17) -> 75016042
A21: Particulars | B21: As on Mar 31, 2025
B22: Outstanding for following periods from due date of payment
B23: Less than 6 months | C23: 6 months to 1 year | D23: 1 - 2 years | E23: 2 - 3 years | F23: more than 3 years | G23: TOTAL
A25: Undisputed Trade receivables considered Good | B25: 0 | C25: =61414470.29/Deno -> 61414470 | D25: =149040.24/Deno -> 149040.24 | E25: =19056.25/Deno -> 19056.25 | F25: =28323028.71/Deno -> 28323029 | G25: =SUM(B25:F25) -> 89905595
A26: Undisputed Trade receivables considered doubtful | B26: =0/(+Deno) -> 0 | C26: =0/(+Deno) -> 0 | D26: =0/(+Deno) -> 0 | E26: =0/(+Deno) -> 0 | F26: =0/(+Deno) -> 0 | G26: =SUM(B26:F26) -> 0
A27: Disputed Trade receivable considered Good | B27: =0/(+Deno) -> 0 | C27: =0/(+Deno) -> 0 | D27: =0/(+Deno) -> 0 | E27: 0 | F27: =0/(+Deno) -> 0 | G27: =SUM(B27:F27) -> 0
A28: Disputed Trade receivable considered doubtful | B28: =0/(+Deno) -> 0 | C28: =0/(+Deno) -> 0 | D28: =0/(+Deno) -> 0 | E28: =0/(+Deno) -> 0 | F28: =0/(+Deno) -> 0 | G28: =SUM(B28:F28) -> 0
A30: TOTAL | B30: =SUM(B25:B29) -> 0 | C30: =SUM(C25:C29) -> 61414470 | D30: =SUM(D25:D29) -> 149040.24 | E30: =SUM(E25:E29) -> 19056.25 | F30: =SUM(F25:F29) -> 28323029 | G30: =SUM(G25:G29) -> 89905595

Sheet Note 9
A1: CARGO INTERNATIONAL (INDIA) PRIVATE LIMITED
A2: =+'NOTE 4-8'!A2:C2 -> NOTES TO THE FINANCIAL STATEMENTS FOR THE YEAR ENDED 31st MARCH, 2026
A3: =+'NOTE 4-8'!A3:C3 -> CAPITAL TOWERS, NO.G-3/1, G-3/2 & G-2 ,DOOR NO.180 KODAMBAKKAM HIGH ROAD, NUNGAMBAKKAM, CHENNAI - 600034
A5: Note 9 - Property, Plant & Equipment
K6: =+"(Unless otherwise specified, all amounts are "&IF('Master data'!A2="Ones","Indian Rupees","in "&'Master data'!A2&" of INR)") -> (Unless otherwise specified, all amounts are Indian Rupees
A7: Asset Category | B7: Gross Block | F7: Depreciation | J7: Net Block
B8: As on 01.04.2025 | C8: Additions | D8: Deletion | E8: As on 31.03.2026 | F8: =+B8 -> As on 01.04.2025 | G8: For the Year | H8: Deletion | I8: =+E8 -> As on 31.03.2026 | J8: =+I8 -> As on 31.03.2026 | K8: =+B8 -> As on 01.04.2025
A11: Tangible Assets
A12: Motor Car | B12: =0/(Deno) -> 0 | C12: 0 | D12: =(0/(+Deno))/(Deno) -> 0 | E12: =B12+C12-D12 -> 0 | F12: =0/Deno -> 0 | G12: 0 | H12: =(0/(+Deno))/(Deno) -> 0 | I12: =F12+G12-H12 -> 0 | J12: =+E12-I12 -> 0 | K12: =+B12-F12 -> 0
A13: Interior Decoration | B13: =4191829.7/Deno -> 4191829.7 | C13: 0 | D13: =(0/(+Deno))/(Deno) -> 0 | E13: =B13+C13-D13 -> 4191829.7 | F13: =3810368.44087299/Deno -> 3810368.4 | G13: =99731/Deno -> 99731 | H13: =(0/(+Deno))/(Deno) -> 0 | I13: =F13+G13-H13 -> 3910099.4 | J13: =+E13-I13 -> 281730.26 | K13: =+B13-F13 -> 381461.26
A14: Computers | B14: =1880526.16/Deno -> 1880526.2 | C14: =162329/Deno -> 162329 | D14: =(0/(+Deno))/(Deno) -> 0 | E14: =B14+C14-D14 -> 2042855.2 | F14: =1756838.07066679/Deno -> 1756838.1 | G14: =90412/Deno -> 90412 | H14: =(0/(+Deno))/(Deno) -> 0 | I14: =F14+G14-H14 -> 1847250.1 | J14: =+E14-I14 -> 195605.09 | K14: =+B14-F14 -> 123688.09
A15: Communication Equiptments | B15: =381194/Deno -> 381194 | C15: 0 | D15: =(0/(+Deno))/(Deno) -> 0 | E15: =B15+C15-D15 -> 381194 | F15: =362133/Deno -> 362133 | G15: 0 | H15: =(0/(+Deno))/(Deno) -> 0 | I15: =F15+G15-H15 -> 362133 | J15: =+E15-I15 -> 19061 | K15: =+B15-F15 -> 19061
A16: Furniture and fixtures | B16: =1288569.39/Deno -> 1288569.4 | C16: =94800/Deno -> 94800 | D16: =(0/(+Deno))/(Deno) -> 0 | E16: =B16+C16-D16 -> 1383369.4 | F16: =1195047.52885793/Deno -> 1195047.5 | G16: =32819/Deno -> 32819 | H16: =(0/(+Deno))/(Deno) -> 0 | I16: =F16+G16-H16 -> 1227866.5 | J16: =+E16-I16 -> 155502.86 | K16: =+B16-F16 -> 93521.861
A17: Electrical equipments | B17: =720330.5/Deno -> 720330.5 | C17: =35178/Deno -> 35178 | D17: =(0/(+Deno))/(Deno) -> 0 | E17: =B17+C17-D17 -> 755508.5 | F17: =649873.945150916/Deno -> 649873.95 | G17: =22039/Deno -> 22039 | H17: =(0/(+Deno))/(Deno) -> 0 | I17: =F17+G17-H17 -> 671912.95 | J17: =+E17-I17 -> 83595.555 | K17: =+B17-F17 -> 70456.555
A18: Office Equipments | B18: =571389.5/Deno -> 571389.5 | C18: =82020.06/Deno -> 82020.06 | D18: =(0/(+Deno))/(Deno) -> 0 | E18: =B18+C18-D18 -> 653409.56 | F18: =526369.013742537/Deno -> 526369.01 | G18: =19308/Deno -> 19308 | H18: =(0/(+Deno))/(Deno) -> 0 | I18: =F18+G18-H18 -> 545677.01 | J18: =+E18-I18 -> 107732.55 | K18: =+B18-F18 -> 45020.486
A20: Total | B20: =SUM(B12:B18) -> 9033839.2 | C20: =SUM(C12:C18) -> 374327.06 | D20: =SUM(D12:D18) -> 0 | E20: =SUM(E12:E18) -> 9408166.3 | F20: =SUM(F12:F18) -> 8300630 | G20: =SUM(G12:G18) -> 264309 | H20: =SUM(H12:H18) -> 0 | I20: =SUM(I12:I18) -> 8564939 | ... K20: =SUM(K12:K18) -> 733209.25
A22: Previous Year figure | B22: =8944873.14/Deno -> 8944873.1 | C22: =88966.11/Deno -> 88966.11 | D22: 0 | E22: =9033839.25/Deno -> 9033839.2 | F22: =8030731.06929116/Deno -> 8030731.1 | G22: =269898.93/Deno -> 269898.93 | H22: 0 | I22: =8300629.99929116/Deno -> 8300630 | J22: =733209.250708837/Deno -> 733209.25 | K22: =914142.070708837/Deno -> 914142.07

Sheet NOTE 10-14
A1: =BS!A1 -> CARGO INTERNATIONAL (INDIA) PRIVATE LIMITED
A2: NOTES TO THE FINANCIAL STATEMENTS FOR THE YEAR ENDED 31st MARCH, 2026
A3: CAPITAL TOWERS, NO.G-3/1, G-3/2 & G-2 ,DOOR NO.180 KODAMBAKKAM HIGH ROAD, NUNGAMBAKKAM, CHENNAI - 600034
C4: =+"(Unless otherwise specified, all amounts are "&IF('Master data'!A2="Ones","Indian Rupees","in "&'Master data'!A2&" of INR)") -> (Unless otherwise specified, all amounts are Indian Rupees
A5: Particulars | B5: As on | C5: As on
B6: ='NOTE 4-8'!B6 -> 31st March, 2026 | C6: ='NOTE 4-8'!C6 -> 31st March, 2025
A8: NOTE 10 : LONG TERM LOANS AND ADVANCES
A9: Rental Deposit | B9: =(SUMIF('TB 25-26'!$Q:$Q,$A9,'TB 25-26'!$O:$O)-SUMIF('TB 25-26'!$Q:$Q,$A9,'TB 25-26'!$P:$P)) -> 1633680.5 | C9: =(SUMIF('TB 25-26'!$Q:$Q,$A9,'TB 25-26'!$E:$E)-SUMIF('TB 25-26'!$Q:$Q,$A9,'TB 25-26'!$F:$F)) -> 1669658
A10: TDS Receivable | B10: =(SUMIF('TB 25-26'!$Q:$Q,$A10,'TB 25-26'!$O:$O)-SUMIF('TB 25-26'!$Q:$Q,$A10,'TB 25-26'!$P:$P)) -> 24548794 | C10: =(SUMIF('TB 25-26'!$Q:$Q,$A10,'TB 25-26'!$E:$E)-SUMIF('TB 25-26'!$Q:$Q,$A10,'TB 25-26'!$F:$F)) -> 21114220
B12: =SUM(B9:B11) -> 26182475 | C12: =SUM(C9:C11) -> 22783878
A14: NOTE 11 : DEFERRED TAX ASSETS
A15: Opening Balance | B15: =+C18 -> 597436.01 | C15: =634957.698/Deno -> 634957.7
A16: Add: Current year | B16: =PL!D32 -> 0 | C16: =PL!E32 -> -37521.685
A18: Deferred Tax Assets/(Liabilty) | B18: =SUM(B15:B17) -> 597436.01 | C18: =SUM(C15:C17) -> 597436.01
A20: NOTE 13 : CASH AND CASH EQUIVALENTS
A21: Balance with banks | B21: =(+'Sub Sch - BS'!B38) -> 34165323 | C21: =(+'Sub Sch - BS'!C38) -> 21677245
A22: Cash on hand | B22: =(+'Sub Sch - BS'!B32) -> 58384.78 | C22: =(+'Sub Sch - BS'!C32) -> 16299.65
B24: =SUM(B21:B23) -> 34223708 | C24: =SUM(C21:C23) -> 21693544
A26: NOTE 14 : SHORT TERM LOANS AND ADVANCES
A27: GST Input tax credit | B27: =(+'Sub Sch - BS'!B44) -> 12185083 | C27: =(+'Sub Sch - BS'!C44) -> 5065070
A28: Prepaid Expenses | B28: =(SUMIF('TB 25-26'!$Q:$Q,$A28,'TB 25-26'!$O:$O)-SUMIF('TB 25-26'!$Q:$Q,$A28,'TB 25-26'!$P:$P)) -> 246134.41 | C28: =(SUMIF('TB 25-26'!$Q:$Q,$A28,'TB 25-26'!$E:$E)-SUMIF('TB 25-26'!$Q:$Q,$A28,'TB 25-26'!$F:$F)) -> 130788.23
A29: Staff Advance | B29: =(SUMIF('TB 25-26'!$Q:$Q,$A29,'TB 25-26'!$O:$O)-SUMIF('TB 25-26'!$Q:$Q,$A29,'TB 25-26'!$P:$P)) -> 95531.24 | C29: =(SUMIF('TB 25-26'!$Q:$Q,$A29,'TB 25-26'!$E:$E)-SUMIF('TB 25-26'!$Q:$Q,$A29,'TB 25-26'!$F:$F)) -> 43181.74
B31: =SUM(B27:B30) -> 12526748 | C31: =SUM(C27:C30) -> 5239040

Sheet NOTE 15-20
A1: CARGO INTERNATIONAL (INDIA) PRIVATE LIMITED
A2: =+'NOTE 3'!A2:E2 -> NOTES TO THE FINANCIAL STATEMENTS FOR THE YEAR ENDED 31st MARCH, 2026
C4: =+"(Unless otherwise specified, all amounts are "&IF('Master data'!A2="Ones","Indian Rupees","in "&'Master data'!A2&" of INR)") -> (Unless otherwise specified, all amounts are Indian Rupees
A5: Particulars | B5: For Year Ended | C5: For Year Ended
B6: ='NOTE 10-14'!B6 -> 31st March, 2026 | C6: ='NOTE 10-14'!C6 -> 31st March, 2025
A8: NOTE 15 : REVENUE FROM OPERATIONS
A9: Export Operating Income | B9: =(SUMIF('TB 25-26'!$Q:$Q,'NOTE 15-20'!$A9,'TB 25-26'!$P:$P)-SUMIF('TB 25-26'!$Q:$Q,'NOTE 15-20'!$A9,'TB 25-26'!$O:$O)) -> 96649856 | C9: =(SUMIF('TB 25-26'!$Q:$Q,'NOTE 15-20'!$A9,'TB 25-26'!$F:$F)-SUMIF('TB 25-26'!$Q:$Q,'NOTE 15-20'!$A9,'TB 25-26'!$E:$E)) -> 1.414428e+08
A10: Import Operating Income | B10: =(SUMIF('TB 25-26'!$Q:$Q,'NOTE 15-20'!$A10,'TB 25-26'!$P:$P)-SUMIF('TB 25-26'!$Q:$Q,'NOTE 15-20'!$A10,'TB 25-26'!$O:$O)) -> 26473503 | C10: =(SUMIF('TB 25-26'!$Q:$Q,'NOTE 15-20'!$A10,'TB 25-26'!$F:$F)-SUMIF('TB 25-26'!$Q:$Q,'NOTE 15-20'!$A10,'TB 25-26'!$E:$E)) -> 27374244
A11: Air Export Revenue Account | B11: =(SUMIF('TB 25-26'!$Q:$Q,'NOTE 15-20'!$A11,'TB 25-26'!$P:$P)-SUMIF('TB 25-26'!$Q:$Q,'NOTE 15-20'!$A11,'TB 25-26'!$O:$O)) -> 54512717 | C11: =(SUMIF('TB 25-26'!$Q:$Q,'NOTE 15-20'!$A11,'TB 25-26'!$F:$F)-SUMIF('TB 25-26'!$Q:$Q,'NOTE 15-20'!$A11,'TB 25-26'!$E:$E)) -> 72299417
A12: Air Import Revenue Account | B12: =(SUMIF('TB 25-26'!$Q:$Q,'NOTE 15-20'!$A12,'TB 25-26'!$P:$P)-SUMIF('TB 25-26'!$Q:$Q,'NOTE 15-20'!$A12,'TB 25-26'!$O:$O)) -> 13227934 | C12: =(SUMIF('TB 25-26'!$Q:$Q,'NOTE 15-20'!$A12,'TB 25-26'!$F:$F)-SUMIF('TB 25-26'!$Q:$Q,'NOTE 15-20'!$A12,'TB 25-26'!$E:$E)) -> 9940420.3
B14: =SUM(B9:B13) -> 1.9086401e+08 | C14: =SUM(C9:C13) -> 2.5105688e+08
A16: NOTE 16 : OTHER INCOME
A17: Service Job Revenue | B17: =(SUMIF('TB 25-26'!$Q:$Q,'NOTE 15-20'!$A17,'TB 25-26'!$P:$P)-SUMIF('TB 25-26'!$Q:$Q,'NOTE 15-20'!$A17,'TB 25-26'!$O:$O)) -> 5007389.7 | C17: =(SUMIF('TB 25-26'!$Q:$Q,'NOTE 15-20'!$A17,'TB 25-26'!$F:$F)-SUMIF('TB 25-26'!$Q:$Q,'NOTE 15-20'!$A17,'TB 25-26'!$E:$E)) -> 6273672.8
A18: Interest Income | B18: =(SUMIF('TB 25-26'!$Q:$Q,'NOTE 15-20'!$A18,'TB 25-26'!$P:$P)-SUMIF('TB 25-26'!$Q:$Q,'NOTE 15-20'!$A18,'TB 25-26'!$O:$O)) -> 9161 | C18: =(SUMIF('TB 25-26'!$Q:$Q,'NOTE 15-20'!$A18,'TB 25-26'!$F:$F)-SUMIF('TB 25-26'!$Q:$Q,'NOTE 15-20'!$A18,'TB 25-26'!$E:$E)) -> 1397
B20: =SUM(B17:B19) -> 5016550.7 | C20: =SUM(C17:C19) -> 6275069.8
A22: NOTE 17 : OPERATING EXPENSES
A23: Export Operating Expenses | B23: =(SUMIF('TB 25-26'!$Q:$Q,'NOTE 15-20'!$A23,'TB 25-26'!$O:$O)-SUMIF('TB 25-26'!$Q:$Q,'NOTE 15-20'!$A23,'TB 25-26'!$P:$P)) -> 80535247 | C23: =(SUMIF('TB 25-26'!$Q:$Q,'NOTE 15-20'!$A23,'TB 25-26'!$E:$E)-SUMIF('TB 25-26'!$Q:$Q,'NOTE 15-20'!$A23,'TB 25-26'!$F:$F)) -> 1.1760631e+08
A24: Import Operating Expenses | B24: =(SUMIF('TB 25-26'!$Q:$Q,'NOTE 15-20'!$A24,'TB 25-26'!$O:$O)-SUMIF('TB 25-26'!$Q:$Q,'NOTE 15-20'!$A24,'TB 25-26'!$P:$P)) -> 22075934 | C24: =(SUMIF('TB 25-26'!$Q:$Q,'NOTE 15-20'!$A24,'TB 25-26'!$E:$E)-SUMIF('TB 25-26'!$Q:$Q,'NOTE 15-20'!$A24,'TB 25-26'!$F:$F)) -> 24087738
A25: Air Export Operating Expenses | B25: =(SUMIF('TB 25-26'!$Q:$Q,'NOTE 15-20'!$A25,'TB 25-26'!$O:$O)-SUMIF('TB 25-26'!$Q:$Q,'NOTE 15-20'!$A25,'TB 25-26'!$P:$P)) -> 46072304 | C25: =(SUMIF('TB 25-26'!$Q:$Q,'NOTE 15-20'!$A25,'TB 25-26'!$E:$E)-SUMIF('TB 25-26'!$Q:$Q,'NOTE 15-20'!$A25,'TB 25-26'!$F:$F)) -> 65618241
A26: Air Import Operating Expenses | B26: =(SUMIF('TB 25-26'!$Q:$Q,'NOTE 15-20'!$A26,'TB 25-26'!$O:$O)-SUMIF('TB 25-26'!$Q:$Q,'NOTE 15-20'!$A26,'TB 25-26'!$P:$P)) -> 10518022 | C26: =(SUMIF('TB 25-26'!$Q:$Q,'NOTE 15-20'!$A26,'TB 25-26'!$E:$E)-SUMIF('TB 25-26'!$Q:$Q,'NOTE 15-20'!$A26,'TB 25-26'!$F:$F)) -> 8054463.1
B28: =SUM(B23:B27) -> 1.5920151e+08 | C28: =SUM(C23:C27) -> 2.1536675e+08
A30: NOTE 18 : EMPLOYEE BENEFIT EXPENSE
A31: Salaries | B31: =(SUMIF('TB 25-26'!$Q:$Q,'NOTE 15-20'!$A31,'TB 25-26'!$O:$O)-SUMIF('TB 25-26'!$Q:$Q,'NOTE 15-20'!$A31,'TB 25-26'!$P:$P)) -> 19221568 | C31: =(SUMIF('TB 25-26'!$Q:$Q,'NOTE 15-20'!$A31,'TB 25-26'!$E:$E)-SUMIF('TB 25-26'!$Q:$Q,'NOTE 15-20'!$A31,'TB 25-26'!$F:$F)) -> 22538028
A32: Staff welfare Expense | B32: =(SUMIF('TB 25-26'!$Q:$Q,'NOTE 15-20'!$A32,'TB 25-26'!$O:$O)-SUMIF('TB 25-26'!$Q:$Q,'NOTE 15-20'!$A32,'TB 25-26'!$P:$P)) -> 604553.32 | C32: =(SUMIF('TB 25-26'!$Q:$Q,'NOTE 15-20'!$A32,'TB 25-26'!$E:$E)-SUMIF('TB 25-26'!$Q:$Q,'NOTE 15-20'!$A32,'TB 25-26'!$F:$F)) -> 509503
B34: =SUM(B31:B33) -> 19826121 | C34: =SUM(C31:C33) -> 23047531
A37: NOTE 19 : FINANCIAL COST
A38: Bank Charges | B38: =(SUMIF('TB 25-26'!$Q:$Q,'NOTE 15-20'!$A38,'TB 25-26'!$O:$O)-SUMIF('TB 25-26'!$Q:$Q,'NOTE 15-20'!$A38,'TB 25-26'!$P:$P)) -> 225794.01 | C38: =(SUMIF('TB 25-26'!$Q:$Q,'NOTE 15-20'!$A38,'TB 25-26'!$E:$E)-SUMIF('TB 25-26'!$Q:$Q,'NOTE 15-20'!$A38,'TB 25-26'!$F:$F)) -> 265560.22
A39: Interest | B39: =(SUMIF('TB 25-26'!$Q:$Q,'NOTE 15-20'!$A39,'TB 25-26'!$O:$O)-SUMIF('TB 25-26'!$Q:$Q,'NOTE 15-20'!$A39,'TB 25-26'!$P:$P)) -> 26067 | C39: =(SUMIF('TB 25-26'!$Q:$Q,'NOTE 15-20'!$A39,'TB 25-26'!$E:$E)-SUMIF('TB 25-26'!$Q:$Q,'NOTE 15-20'!$A39,'TB 25-26'!$F:$F)) -> 879.48
B41: =SUM(B38:B40) -> 251861.01 | C41: =SUM(C38:C40) -> 266439.7
A43: NOTE 20 : ADMINISTRATION EXPENSES
A44: Audit Fees | B44: =(SUMIF('TB 25-26'!$Q:$Q,'NOTE 15-20'!$A44,'TB 25-26'!$O:$O)-SUMIF('TB 25-26'!$Q:$Q,'NOTE 15-20'!$A44,'TB 25-26'!$P:$P)) -> 225000 | C44: =(SUMIF('TB 25-26'!$Q:$Q,'NOTE 15-20'!$A44,'TB 25-26'!$E:$E)-SUMIF('TB 25-26'!$Q:$Q,'NOTE 15-20'!$A44,'TB 25-26'!$F:$F)) -> 225000 | D44: Provision to be created | E44: 2.25 | F44: =+C44-E44 -> 224997.75
A45: Bad and Doubtful Debts | B45: =(SUMIF('TB 25-26'!$Q:$Q,'NOTE 15-20'!$A45,'TB 25-26'!$O:$O)-SUMIF('TB 25-26'!$Q:$Q,'NOTE 15-20'!$A45,'TB 25-26'!$P:$P)) -> -2065.16 | C45: =(SUMIF('TB 25-26'!$Q:$Q,'NOTE 15-20'!$A45,'TB 25-26'!$E:$E)-SUMIF('TB 25-26'!$Q:$Q,'NOTE 15-20'!$A45,'TB 25-26'!$F:$F)) -> 3097387.2 | E45: 30.97 | F45: =+C45-E45 -> 3097356.2
A46: Business Promotion Expense | B46: =(+'Sub Sch - p&l'!B13) -> 468067.64 | C46: =(+'Sub Sch - p&l'!C13) -> 1633321.1 | D46: Gold purchased and other nature to be disclosed and also confirm GST Input is not taken | E46: 16.33 | F46: =+C46-E46 -> 1633304.7
A47: Communication Expense | B47: =(+'Sub Sch - p&l'!B21) -> 248680.23 | C47: =(+'Sub Sch - p&l'!C21) -> 203025.92 | D47: Sample, Monthly exp, Mobile exp to whom it is given | E47: 10.6 | F47: =+C47-E47 -> 203015.32
A48: Foreign Exchange gain/loss | B48: =(SUMIF('TB 25-26'!$Q:$Q,'NOTE 15-20'!$A48,'TB 25-26'!$O:$O)-SUMIF('TB 25-26'!$Q:$Q,'NOTE 15-20'!$A48,'TB 25-26'!$P:$P)) -> 445689.64 | C48: =(SUMIF('TB 25-26'!$Q:$Q,'NOTE 15-20'!$A48,'TB 25-26'!$E:$E)-SUMIF('TB 25-26'!$Q:$Q,'NOTE 15-20'!$A48,'TB 25-26'!$F:$F)) -> -33920.907 | E48: 0.34 | F48: =+C48-E48 -> -33921.247
A49: Insurance | B49: =(SUMIF('TB 25-26'!$Q:$Q,'NOTE 15-20'!$A49,'TB 25-26'!$O:$O)-SUMIF('TB 25-26'!$Q:$Q,'NOTE 15-20'!$A49,'TB 25-26'!$P:$P)) -> 463682 | C49: =(SUMIF('TB 25-26'!$Q:$Q,'NOTE 15-20'!$A49,'TB 25-26'!$E:$E)-SUMIF('TB 25-26'!$Q:$Q,'NOTE 15-20'!$A49,'TB 25-26'!$F:$F)) -> 386590.7 | E49: 3.87 | F49: =+C49-E49 -> 386586.83
A50: Other Expense | B50: =(+'Sub Sch - p&l'!B37) -> 2445282.8 | C50: =(+'Sub Sch - p&l'!C37) -> 2792361.1 | E50: 19.35 | F50: =+C50-E50 -> 2792341.8
A51: Professional charges | B51: =(+'Sub Sch - p&l'!B45) -> 15156273 | C51: =(+'Sub Sch - p&l'!C45) -> 1999970.9 | E51: 20 | F51: =+C51-E51 -> 1999950.9
A52: Rates and Taxes | B52: =(SUMIF('TB 25-26'!$Q:$Q,'NOTE 15-20'!$A52,'TB 25-26'!$O:$O)-SUMIF('TB 25-26'!$Q:$Q,'NOTE 15-20'!$A52,'TB 25-26'!$P:$P)) -> 169145 | C52: =(SUMIF('TB 25-26'!$Q:$Q,'NOTE 15-20'!$A52,'TB 25-26'!$E:$E)-SUMIF('TB 25-26'!$Q:$Q,'NOTE 15-20'!$A52,'TB 25-26'!$F:$F)) -> 361217 | E52: 3.61 | F52: =+C52-E52 -> 361213.39
A53: Rent | B53: =(+'Sub Sch - p&l'!B53) -> 2641326 | C53: =(+'Sub Sch - p&l'!C53) -> 2135065 | E53: 21.35065 | F53: =+C53-E53 -> 2135043.6
A54: Repairs & maintenance | B54: =(+'Sub Sch - p&l'!B62) -> 467214.41 | C54: =(+'Sub Sch - p&l'!C62) -> 609537.95 | E54: 6.0953795 | F54: =+C54-E54 -> 609531.85
A55: Travelling expense | B55: =(+'Sub Sch - p&l'!B69) -> 3041080.3 | C55: =(+'Sub Sch - p&l'!C69) -> 2318583.6 | E55: 23.185836 | F55: =+C55-E55 -> 2318560.4
B57: =SUM(B44:B56) -> 25769376 | C57: =SUM(C44:C56) -> 15728139
A59: REMUNERATION TO AUDITOR
A60: Statutory Audit fees | B60: =(+'TB 25-26'!M288)/Deno -> 100000 | C60: =125000/Deno -> 125000
A61: Tax Audit Fees | B61: =(+'TB 25-26'!M289)/Deno -> 125000 | C61: =100000/Deno -> 100000
B63: =SUM(B60:B62) -> 225000 | C63: =SUM(C60:C62) -> 225000

Sheet Add Notes
A1: CARGO INTERNATIONAL (INDIA) PRIVATE LIMITED
A2: NOTES TO THE FINANCIAL STATEMENTS FOR THE YEAR ENDED 31st MARCH, 2026
A3: CIN: U63000TN2010PTC077296
A4: Old No.7 / New No.13, First Floor, First Cross Street, Trustpuram, Kodambakkam, Chennai - 600024, India
A6: NOTE 21: ADDITIONAL NOTES AND INFORMATION:
A7: (1) Contingent Liabilities:
A8: There is no contingent liability in respect of the company.
A10: (2) Earnings Per Share (EPS) | C10: (Absolute Numbers)
A11: Particulars | B11: 2025-26 | C11: 2024-25
A12: a) Net Profit / (Loss) available for Equity Shareholders | B12: =+PL!D34*Deno -> -9432613.1 | C12: =+PL!E34*Deno -> 1960906.2
A13: b) Weighed average number of Shares outstanding | B13: 20000 | C13: 20000
A14: c) Basic Earnings per Share of Rs.10 each | B14: =B12/B13 -> -471.63065 | C14: =C12/C13 -> 98.045308
A15: d) Net Profit / (Loss) available for Equity Shareholders | B15: =B12 -> -9432613.1 | C15: =C12 -> 1960906.2
A16: e) Weighed average number of Shares outstanding | B16: 20000 | C16: 20000
A17: Dilutive Earnings per Share of Rs.10 each | B17: =B15/B16 -> -471.63065 | C17: =C15/C16 -> 98.045308
A19: (3) Earnings in foreign currency during the year (on realisation basis)
A20: Particulars | B20: 2024 - 25 | C20: 2023 - 24
A21: Income realised | B21: =+"Rs. "&42171960.92/Deno -> Rs. 42171960.92 | C21: =+"Rs. "&44486684.12/Deno -> Rs. 44486684.12
A23: (4) Expenditure in foreign currency during the year (on realisation basis)
A24: Particulars | B24: 2024 - 25 | C24: 2023 - 24
A25: Expenses | B25: =+"Rs. "&71090808.79/Deno -> Rs. 71090808.79 | C25: =+"Rs. "&50032407.77/Deno -> Rs. 50032407.77
A27: (5) Related Party Disclosures of the year ended 31st March 2025
A28: a) List of Related Parties:
A29: Key Management Personnel (KMP)
A30: Suresh Padmanabhan - Director
A31: Vignesh Natarajan - Director
A33: Associate/Joint venture Companies/Firms
A34: Cargo International Logistics LLC-Oman
A35: Inter Continental Logistics Limited-UK
A36: Cargo International Limited-Dubai
A38: b) Details of Transaction
A39: Name of the party and Nature of transaction | B39: Closing Balance as on 31/03/2024 Dr. / (Cr.) | C39: Transaction during the year | E39: Closing Balance as on 31/03/2025 Dr. / (Cr.)
C40: Debit Rs. | D40: Credit Rs.
A41: Cargo International Logistics LLC-Oman
A42: Overseas Payable (Cr.) | B42: -106848.22 | C42: 0 | D42: 822420.92 | E42: =+B42-D42 -> -929269.14
A43: Overseas Receivables (Dr.) | B43: -589181.47 | C43: 436105.24 | D43: 0 | E43: =+B43+C43-D43 -> -153076.23
A44: Inter Continental Logistics Limited-UK
A45: Overseas Payable (Cr.) | B45: -1029992.7 | C45: 65217.568 | D45: 33195208 | E45: =+B45+C45-D45 -> -34159983
A46: Overseas Receivables (Dr.) | B46: -117479.42 | C46: 579932.95 | D46: 0 | E46: =+B46+C46-D46 -> 462453.53
A47: Cargo International Limited-Dubai
A48: Overseas Receivables (Dr.) | B48: 26639514 | C48: =8031445.53+4081269.3 -> 12112715 | D48: 12675243 | E48: =+B48+C48-D48 -> 26076986
A49: Overseas Payable (Cr.) | B49: -26074600 | C49: 0 | D49: 135504.67 | E49: =+B49+C49-D49 -> -26210105
A50: Advances to Creditors (Dr.) | B50: =+'Sub-Schedule'!B9-'Sub-Schedule'!C9 -> 0 | C50: 0 | D50: 0 | E50: =+'Sub-Schedule'!D9-'Sub-Schedule'!E9 -> 214646.99
A51: Advances From Debtors (Cr.) | B51: =+SUM('Sub-Schedule'!B5:B6)-SUM('Sub-Schedule'!C5:C6) -> 0 | C51: 0 | D51: 0 | E51: =+SUM('Sub-Schedule'!D5:D6)-SUM('Sub-Schedule'!E5:E6) -> -15934802
A53: c) Shareholders having Substantial Interest
A54: Suresh Padmanabhan
A56: d) Director's Remuneration
A57: Name of Director | B57: Amount in Rs.
A58: Vignesh Natarajan | B58: 1800000
A60: (6) Micro, Small and Medium Enterprises :
A61: As per the information available and as certified by the management, creditors includes payable to Micro, Small and Medium Enterprises amount Rs NIL.as on 31stMarch, 2025.
A62: As per the information available and explanation provided to us and as certified by the management, there is no delay in payment of dues to Enterprises as defined under the "Micro, Small and Medium Enterprises Development Act, 2006.
A63: The company has not received any intimation from “suppliers” regarding their status under the Micro; Small and Medium, Enterprises Development Act, 2006. Hence, disclosure, if any, relating to amount unpaid as at the year-end together with the interest paid/payable as required under the said Act has not been furnished.
A64: (7) Balances with customers and suppliers have been stated at book values and are subject to confirmation.
A65: (8) Previous Year’s figures are re-grouped, re-arranged and re-classified, wherever necessary to conform to current year's classification.
A66: (9) The below amounts represent opening balance differences in the respective ledgers as compared to Financials with the Books of accounts maintained by the company as on 01st April 2017. the amount are written off/ Written back are as under
A67: Particulars | B67: Amount | C67: Remarks
A68: Provision operation | B68: 14110730 | C68: Exceptional / Extraordinary item relating to FY 2017-18 has been Written off in FY 24-25.
A69: GST Input Tax credit | B69: -14902245 | C69: Opening balance difference of GST input tax credit adjusted against opening reserves in FY 23-24
A70: Reserves and Surplus Balance | B70: -5959480 | C70: Opening Balance difference since FY 2017-18, adjusted against reserves and surplus.
A71: Sundry Creditors | B71: -228009 | C71: Written off to Exceptional/ Extraordinary item in P &L in FY 2020-21
A72: Statutory Dues Payable | B72: -287114 | C72: Written off to Exceptional/ Extraordinary item in P &L in FY 2020-21
A73: Short Term Provision | B73: 424989 | C73: Written off to Exceptional/ Extraordinary item in P &L in FY 2020-21
A74: Trade Receivables | B74: 195027 | C74: Written off to Exceptional/ Extraordinary item in P &L in FY 2020-21
A75: Advance To suppliers | B75: -488812 | C75: Written off to Exceptional/ Extraordinary item in P &L in FY 2020-21
A76: (10) There is opening balance differences 2017-18, which has shown in Notes to accounts as suspense account.
A77: (11) The Company has filed litigation against the previous directors of the company under Section 166, 241, 242, 246 and 340 of the companies act 2013 (Case Number: CP/519/2019). The matter is pending for resolution with the National Company Law Tribunal. also Company has filed a case against previous directors with the Chennai Central Crime Branch Officeon 28.7.2021 (Case Number: C.NO.124/CCB/COP/Visitors/2021).
A78: (12) Nature of the Matter Arising out of FIR No. 196/2024 registered at Chennai under Sections 406, 420 r/w 34 IPC, an allegation of criminal breach of trust and cheating involving an amount of ₹2,20,00,000 has been made against the Company (M/s. Cargo International India Pvt. Ltd.) and its directors/officers. The Hon’ble Supreme Court, vide final order dated 20 May 2025, has: a) Upheld the de-freezing of the aforesaid four bank accounts; b) Directed continuation of freeze on the fifth bank account (ICICI Bank A/c No. 399505000812) having a balance of ₹2,49,99,437.29 as on 16 May 2025; c) Recorded an undertaking by the Company to maintain a minimum balance of ₹2,20,00,000 in the said account until final adjudication of the dispute on merits by the appropriate forum.
A79: (13) The company has also done Forensic audit for the year FY 2017-18, in the Forensic Report the auditor has given many qualifications regarding the mis - appropriateness of accounts and balances and also siphoning of funds of Rs.53,28,168 by the previous directors of the company. The above mentioned amounts has been routed through the following parties according to the report:
A80: Party Name | B80: Amount
A81: Mobis | B81: 3587968
A82: Glovis | B82: 1278000
A83: Cryolar | B83: 277200
A84: NSK Sales | B84: 145000
A85: Kerry Ingredients | B85: 40000
A88: For KALYANASUNDARAM & ASSOCIATES | C88: =+CFS!B48 -> For and on behalf of
A89: Chartered Accountants | C89: =+CFS!B49 -> CARGO INTERNATIONAL (INDIA) PVT. LTD
A90: FRN: 005455S
A94: =+CFS!A55 -> K M Sethu | C94: =+CFS!B55 -> Suresh Padmanabhan | E94: Vignesh Natarajan
A95: =+CFS!A56 -> Partner | C95: =+CFS!B56 -> Director | E95: Director
A96: =+CFS!A57 -> M.No.231703 | C96: =+CFS!B57 -> DIN: 08284074 | E96: DIN: 08284068
A97: =+CFS!A58 -> Place : Chennai | C97: =+CFS!B58 -> Place : Birmingham | E97: =+CFS!D58 -> Place : Chennai
A98: =+CFS!A59 -> Date : | C98: =+CFS!B59 -> Date: | E98: =+CFS!D59 -> Date:
A99: =+CFS!A60 -> UDIN :

Sheet Add Notes (2)
A1: CARGO INTERNATIONAL (INDIA) PRIVATE LIMITED
A2: NOTES TO THE FINANCIAL STATEMENTS FOR THE YEAR ENDED 31st MARCH, 2026
A3: CIN: U63000TN2010PTC077296
A4: Old No.7 / New No.13, First Floor, First Cross Street, Trustpuram, Kodambakkam, Chennai - 600024, India | I4: Old No.7 / New No.13, First Floor, First Cross Street, Trustpuram, Kodambakkam, Chennai - 600024, India
A6: NOTE 21: ADDITIONAL NOTES AND INFORMATION:
A8: (14) Analytical Ratios of the year ended 31st March 2025
A9: Particulars | B9: =+'Add Notes'!B11 -> 2025-26 | C9: =+'Add Notes'!C11 -> 2024-25 | D9: Variance | E9: Remarks (Variance above 25%) | J9: Workings
A10: Current ratio | B10: =+L11/L12 -> 0.97598789 | C10: =+M11/M12 -> 1.1008568 | D10: =IFERROR(+((B10-C10)/C10),"NA") -> -0.11342887 | L10: FY 2024-25 | M10: FY 2023-24 | N10: FY 2022-23 | V10: FY 2022-23
A11: Debt-Equity ratio | B11: =+L14/L15 -> 0 | C11: =+M14/M15 -> 0 | D11: =IFERROR(+((B11-C11)/C11),"NA") -> NA | I11: 1 | J11: Current Ratio | K11: Current Assets | L11: =+BS!C40 -> 1.217665e+08 | M11: =+BS!D40 -> 1.1683818e+08 | N11: 76597931 | Q11: =10^5 -> 100000 | S11: -14447447 | V11: 76597929 | W11: =+M11-V11 -> 40240253
A12: Debt service coverage ratio | B12: 0 | C12: 0 | D12: =IFERROR(+((B12-C12)/C12),"NA") -> NA | J12: =+"CA/CL" -> CA/CL | K12: Current liabilities | L12: =+BS!C23 -> 1.2476231e+08 | M12: =+BS!D23 -> 1.0613386e+08 | N12: 72671561 | Q12: =+N11-N12 -> 3926369.5 | V12: 72671561 | W12: =+M12-V12 -> 33462296
A13: Return on equity | B13: =+L17/L18 -> -0.6181933 | C13: =+M17/M18 -> 0.089529044 | D13: =IFERROR(+((B13-C13)/C13),"NA") -> -7.904947 | W13: =+M13-V13 -> 0
A14: Inventory turnover | B14: 0 | C14: 0 | D14: =IFERROR(+((B14-C14)/C14),"NA") -> NA | I14: 2 | J14: Debt-Equity ratio | K14: Debt | L14: =0*(10^5) -> 0 | M14: =0*(10^5) -> 0 | N14: 0 | V14: 0 | W14: =+M14-V14 -> 0
A15: Trade receivables turnover | B15: =+L25/L26 -> 2.3146024 | C15: =+M25/M26 -> 1.7329107 | D15: =IFERROR(+((B15-C15)/C15),"NA") -> 0.33567321 | J15: Debt/Equity | K15: Equity | L15: =(+BS!C13) -> 10542049 | M15: =(+BS!D13) -> 19974662 | N15: 23830255 | V15: 23830255 | W15: =+M15-V15 -> -3855592.9
A16: Trade payables turnover | B16: =+L29/L30 -> 1.5823052 | C16: =+M29/M30 -> 1.6420369 | D16: =IFERROR(+((B16-C16)/C16),"NA") -> -0.036376566 | W16: =+M16-V16 -> 0
A17: Net capital turnover | B17: =+L33/L34 -> 49.52029 | C17: =+M33/M34 -> 34.319204 | D17: =IFERROR(+((B17-C17)/C17),"NA") -> 0.44293236 | I17: 3 | J17: ROE | K17: Net profits after taxes-preference dividend | L17: =(+PL!D34) -> -9432613.1 | M17: =(+PL!E34) -> 1960906.2 | N17: 5357583.1 | P17: =(+M17-L17)/M17 -> 5.8103338 | V17: 5357583.1 | W17: =+M17-V17 -> -3396676.9
A18: Net profit | B18: =+L37/L38 -> -0.049420596 | C18: =+M37/M38 -> 0.007810605 | D18: =IFERROR(+((B18-C18)/C18),"NA") -> -7.327371 | K18: Average shareholders equity | L18: =+(L15+M15)/2 -> 15258355 | M18: =+(M15+N15)/2 -> 21902458 | N18: 21151463 | V18: 21151463 | W18: =+M18-V18 -> 750995.11
A19: Return on capital employed | B19: =+L41/L42 -> 1.2856652 | C19: =+M41/M42 -> 1.0250233 | D19: =IFERROR(+((B19-C19)/C19),"NA") -> 0.25427903 | W19: =+M19-V19 -> 0
A20: Return on Investment | B20: =+L48/L49 -> -0.8947609 | C20: =+M48/M49 -> 0.09816968 | D20: =IFERROR(+((B20-C20)/C20),"NA") -> -10.114432 | I20: 4 | J20: Inventory turnover ratio | W20: =+M20-V20 -> 0
K21: Cost of goods sold/sales | L21: 0 | M21: 0 | N21: 0 | V21: 0 | W21: =+M21-V21 -> 0
K22: Average inventory | L22: 0 | M22: 0 | N22: 0 | V22: 0 | W22: =+M22-V22 -> 0
A23: Note 21(15): Additional Notes | W23: =+M23-V23 -> 0
I24: 5 | J24: Trade receivables turnover ratio | W24: =+M24-V24 -> 0
A25: (i) Title deeds of Immovable Property not held in name of the Company | K25: Net credit sales | L25: =(+PL!D9) -> 1.9086401e+08 | M25: =(+PL!E9) -> 2.5105688e+08 | N25: 1.9984607e+08 | P25: =+(M25-L25)/M25 -> 0.23975791 | V25: 1.9984607e+08 | W25: =+M25-V25 -> 51210811
A26: The company holds no immovable property in any other name. | K26: Average accounts receivable | L26: =(+(BS!C37+BS!D37)/2) -> 82460819 | M26: =+(BS!D37+N25)/2 -> 1.4487583e+08 | N26: 55706979 | V26: 55706979 | W26: =+M26-V26 -> 89168854
W27: =+M27-V27 -> 0
A28: (ii) Where the Company has revalued its Property, Plant and Equipment, the company shall disclose as to whether the | I28: 6 | J28: Trade payables turnover ratio | W28: =+M28-V28 -> 0
A29: revaluation is based on the valuation by a registered valuer as defined under rule 2 of the Companies | K29: Net credit purchases | L29: =(+PL!D15) -> 1.5920151e+08 | M29: =(+PL!E15) -> 2.1536675e+08 | N29: 1.7188823e+08 | V29: 1.7188823e+08 | W29: =+M29-V29 -> 43478521
A30: (Registered Valuers and Valuation) Rules,2017 | K30: Average trade payables | L30: =(+(BS!C20+BS!D20)/2) -> 1.0061365e+08 | M30: =+((BS!D20)+N29)/2 -> 1.3115829e+08 | N30: 38755425 | V30: 38755425 | W30: =+M30-V30 -> 92402868
A31: There is no revaluation of Property Plant and Equipment | W31: =+M31-V31 -> 0
I32: 7 | J32: Net capital turnover ratio | W32: =+M32-V32 -> 0
A33: (iii) Following disclosures shall be made where Loans or Advances in the nature of loans are granted to promoters, directors, | K33: Net sales | L33: =+L25 -> 1.9086401e+08 | M33: =+M25 -> 2.5105688e+08 | N33: 1.9984607e+08 | V33: 1.9984607e+08 | W33: =+M33-V33 -> 51210811
A34: KMPs and the related parties (as defined under Companies Act, 2013,) either severally or jointly with any other person, that are: | K34: Average working capital | L34: =+((L11-L12)+(M11-M12))/2 -> 3854258.7 | M34: =+((M11-M12)+(N11-N12))/2 -> 7315346.9 | N34: 1064785.5 | V34: 1064784.5 | W34: =+M34-V34 -> 6250562.4
A35: (a) repayable on demand or | W35: =+M35-V35 -> 0
A36: (b) without specifying any terms or period of repayment | I36: 8 | J36: Net profit ratio | W36: =+M36-V36 -> 0
A37: The company has not granted any loans or advances to promoters, directors, KMPs and the other related parties. | K37: Net profit | L37: =(+PL!D34) -> -9432613.1 | M37: =(+PL!E34) -> 1960906.2 | N37: 5357583.1 | V37: 5357583.1 | W37: =+M37-V37 -> -3396676.9
K38: Net sales | L38: =+L25 -> 1.9086401e+08 | M38: =+M25 -> 2.5105688e+08 | N38: 1.9984607e+08 | V38: 1.9984607e+08 | W38: =+M38-V38 -> 51210811
A39: (iv) Capital-Work-in Progress (CWIP) / Intangible assets under development (ITAUD) | W39: =+M39-V39 -> 0
A40: 1.There is no Capital-Work-in Progress | I40: 9 | J40: ROCE | W40: =+M40-V40 -> 0
A41: 2.There is no Intangible assets under development | K41: Earnings before interest and taxes | L41: =+(PL!D9-PL!D15) -> 31662504 | M41: =+(PL!E9-PL!E15) -> 35690130 | N41: 27957840 | V41: 27957840 | W41: =+M41-V41 -> 7732290.1
K42: Capital employed | L42: =(+BS!C42-BS!C23) -> 24627331 | M42: =(+BS!D42-BS!D23) -> 34818847 | N42: 23830254 | V42: 23830252 | W42: =+M42-V42 -> 10988595
A43: (v) Details of Benami Property held | W43: =+M43-V43 -> 0
A44: The company holds no benami property under Benami transactions Prohibitions Act ( 1988) | J44: Earnings before interest and taxes | K44: Operating Profitt | W44: =+M44-V44 -> 0
J45: Capital employed: | K45: Total assets- Current liabilities | W45: =+M45-V45 -> 0
A46: (vi) Where the Company has borrowings from banks or financial institutions on the basis of security of current | W46: =+M46-V46 -> 0
A47: assets, it shall disclose the following:- | I47: 10 | J47: Return on Investment | W47: =+M47-V47 -> 0
A48: The Company has no borrowing from banks or financial institutions on the basis of security of current assets. | K48: Net profit | L48: =(+PL!D34) -> -9432613.1 | M48: =(+PL!E34) -> 1960906.2 | N48: 5357583.1 | V48: 5357583.1 | W48: =+M48-V48 -> -3396676.9
K49: Total investment | L49: =(+BS!C13) -> 10542049 | M49: =(+BS!D13) -> 19974662 | N49: 23830255 | V49: 23830255 | W49: =+M49-V49 -> -3855592.9
A50: (vii) Wilful Defaulter
A51: The company is not declared as a wilful defaulter by any bank or financial Institution or other lender.
A53: (viii) Registration of charges or satisfaction with Registrar of Companies
A54: The Company has not made any registration of charges with registrar of companies
A55: (ix) Compliance with number of layers of companies
A56: The company has complied with the number of layers prescribed under clause (87) of section 2 of the Act read with
A57: Companies (Restriction on number of Layers) Rules, 2017.
A59: (x) Compliance with approved Scheme(s) of Arrangements
A60: There are no scheme of arrangements for the company
A62: (xi) Utilisation of Borrowed funds and share premium:
A63: The company has not advanced or loaned or invested funds (either borrowed funds or share premium or any other sources or
A64: kind of funds) to any other person(s) or entity(ies), including foreign entities (Intermediaries).
... A71: The company has no borrowings from banks or any financial institutions.

Sheet Sub Sch - BS
A1: CARGO INTERNTIONAL INDIA PRIVATE LIMITED
A2: SUB SCHEDULE FOR THE YEAR END 31ST MARCH 2026
A3: Particulars | B3: =+'NOTE 4-8'!B5 -> As on | C3: =+'NOTE 4-8'!C5 -> As on
B4: 31st March, 2026 | C4: 31st March, 2025
A6: SS 1 : Expense Payable
A7: Audit Fee payable | B7: =SUMIF('TB 25-26'!$Q:$Q,$A7,'TB 25-26'!$P:$P)-SUMIF('TB 25-26'!$Q:$Q,$A7,'TB 25-26'!$O:$O) -> 725000 | C7: =SUMIF('TB 25-26'!$Q:$Q,$A7,'TB 25-26'!$F:$F)-SUMIF('TB 25-26'!$Q:$Q,$A7,'TB 25-26'!$E:$E) -> 725000 | E7: Audit Fee payable
A8: GST Audit Fees payable | B8: =SUMIF('TB 25-26'!$Q:$Q,$A8,'TB 25-26'!$P:$P)-SUMIF('TB 25-26'!$Q:$Q,$A8,'TB 25-26'!$O:$O) -> 90000 | C8: =SUMIF('TB 25-26'!$Q:$Q,$A8,'TB 25-26'!$F:$F)-SUMIF('TB 25-26'!$Q:$Q,$A8,'TB 25-26'!$E:$E) -> 90000 | E8: Tax audit 4 Yrs | F8: =125000*4 -> 500000
A9: Convenyance Payable | B9: =SUMIF('TB 25-26'!$Q:$Q,$A9,'TB 25-26'!$P:$P)-SUMIF('TB 25-26'!$Q:$Q,$A9,'TB 25-26'!$O:$O) -> -40045.97 | C9: =SUMIF('TB 25-26'!$Q:$Q,$A9,'TB 25-26'!$F:$F)-SUMIF('TB 25-26'!$Q:$Q,$A9,'TB 25-26'!$E:$E) -> 903854.06 | E9: FY 24-25 provision | F9: 225000
A10: Salary Payable | B10: =SUMIF('TB 25-26'!$Q:$Q,$A10,'TB 25-26'!$P:$P)-SUMIF('TB 25-26'!$Q:$Q,$A10,'TB 25-26'!$O:$O) -> 1816421.2 | C10: =SUMIF('TB 25-26'!$Q:$Q,$A10,'TB 25-26'!$F:$F)-SUMIF('TB 25-26'!$Q:$Q,$A10,'TB 25-26'!$E:$E) -> 2012070.2
B12: =SUM(B7:B11) -> 2591375.3 | C12: =SUM(C7:C11) -> 3730924.3
A14: SS 2 : Statutory Dues payables
A15: Income tax payable | B15: =SUMIF('TB 25-26'!$Q:$Q,$A15,'TB 25-26'!$P:$P)-SUMIF('TB 25-26'!$Q:$Q,$A15,'TB 25-26'!$O:$O) -> 3853278 | C15: =SUMIF('TB 25-26'!$Q:$Q,$A15,'TB 25-26'!$F:$F)-SUMIF('TB 25-26'!$Q:$Q,$A15,'TB 25-26'!$E:$E) -> 3853278
A16: Krishi kalyan Cess Payable | B16: =SUMIF('TB 25-26'!$Q:$Q,$A16,'TB 25-26'!$P:$P)-SUMIF('TB 25-26'!$Q:$Q,$A16,'TB 25-26'!$O:$O) -> 86048.77 | C16: =SUMIF('TB 25-26'!$Q:$Q,$A16,'TB 25-26'!$F:$F)-SUMIF('TB 25-26'!$Q:$Q,$A16,'TB 25-26'!$E:$E) -> 86048.77 | E16: Old | F16: Duty Vat Account
A17: Professional Tax Payable | B17: =SUMIF('TB 25-26'!$Q:$Q,$A17,'TB 25-26'!$P:$P)-SUMIF('TB 25-26'!$Q:$Q,$A17,'TB 25-26'!$O:$O) -> 202739 | C17: =SUMIF('TB 25-26'!$Q:$Q,$A17,'TB 25-26'!$F:$F)-SUMIF('TB 25-26'!$Q:$Q,$A17,'TB 25-26'!$E:$E) -> 138835 | F17: Reimbursement Account
A18: Provident Fund Payables | B18: =SUMIF('TB 25-26'!$Q:$Q,$A18,'TB 25-26'!$P:$P)-SUMIF('TB 25-26'!$Q:$Q,$A18,'TB 25-26'!$O:$O) -> 58707.37 | C18: =SUMIF('TB 25-26'!$Q:$Q,$A18,'TB 25-26'!$F:$F)-SUMIF('TB 25-26'!$Q:$Q,$A18,'TB 25-26'!$E:$E) -> 39933.37
A19: Service tax Payable | B19: =SUMIF('TB 25-26'!$Q:$Q,$A19,'TB 25-26'!$P:$P)-SUMIF('TB 25-26'!$Q:$Q,$A19,'TB 25-26'!$O:$O) -> 0 | C19: =SUMIF('TB 25-26'!$Q:$Q,$A19,'TB 25-26'!$F:$F)-SUMIF('TB 25-26'!$Q:$Q,$A19,'TB 25-26'!$E:$E) -> 0
A20: Swachh Bharath payable | B20: =SUMIF('TB 25-26'!$Q:$Q,$A20,'TB 25-26'!$P:$P)-SUMIF('TB 25-26'!$Q:$Q,$A20,'TB 25-26'!$O:$O) -> -53527.27 | C20: =SUMIF('TB 25-26'!$Q:$Q,$A20,'TB 25-26'!$F:$F)-SUMIF('TB 25-26'!$Q:$Q,$A20,'TB 25-26'!$E:$E) -> -53527.27 | E20: Old
A21: TDS Payables | B21: =SUMIF('TB 25-26'!$Q:$Q,$A21,'TB 25-26'!$P:$P)-SUMIF('TB 25-26'!$Q:$Q,$A21,'TB 25-26'!$O:$O) -> 461205.96 | C21: =SUMIF('TB 25-26'!$Q:$Q,$A21,'TB 25-26'!$F:$F)-SUMIF('TB 25-26'!$Q:$Q,$A21,'TB 25-26'!$E:$E) -> 369389.96
A22: Duty Vat Account | B22: =SUMIF('TB 25-26'!$Q:$Q,$A22,'TB 25-26'!$P:$P)-SUMIF('TB 25-26'!$Q:$Q,$A22,'TB 25-26'!$O:$O) -> -10656 | C22: =SUMIF('TB 25-26'!$Q:$Q,$A22,'TB 25-26'!$F:$F)-SUMIF('TB 25-26'!$Q:$Q,$A22,'TB 25-26'!$E:$E) -> -8577 | E22: need to check
A23: Reimbursement Account | B23: =SUMIF('TB 25-26'!$Q:$Q,$A23,'TB 25-26'!$P:$P)-SUMIF('TB 25-26'!$Q:$Q,$A23,'TB 25-26'!$O:$O) -> -16250 | C23: =SUMIF('TB 25-26'!$Q:$Q,$A23,'TB 25-26'!$F:$F)-SUMIF('TB 25-26'!$Q:$Q,$A23,'TB 25-26'!$E:$E) -> -3655
B25: =SUM(B15:B24) -> 4581545.8 | C25: =SUM(C15:C24) -> 4421725.8
A27: SS 3 : Cash and cash equivalents
A28: Cash in hand
A29: Cash in hand | B29: =SUMIF('TB 25-26'!$Q:$Q,$A29,'TB 25-26'!$O:$O)-SUMIF('TB 25-26'!$Q:$Q,$A29,'TB 25-26'!$P:$P) -> 0 | C29: =SUMIF('TB 25-26'!$Q:$Q,$A29,'TB 25-26'!$E:$E)-SUMIF('TB 25-26'!$Q:$Q,$A29,'TB 25-26'!$F:$F) -> 0
A30: Petty Cash | B30: =SUMIF('TB 25-26'!$Q:$Q,$A30,'TB 25-26'!$O:$O)-SUMIF('TB 25-26'!$Q:$Q,$A30,'TB 25-26'!$P:$P) -> 58384.78 | C30: =SUMIF('TB 25-26'!$Q:$Q,$A30,'TB 25-26'!$E:$E)-SUMIF('TB 25-26'!$Q:$Q,$A30,'TB 25-26'!$F:$F) -> 16299.65
B32: =SUM(B29:B31) -> 58384.78 | C32: =SUM(C29:C31) -> 16299.65
A34: Balance with bank
A35: Cash at Bank - Foreign Currency | B35: =SUMIF('TB 25-26'!$Q:$Q,$A35,'TB 25-26'!$O:$O)-SUMIF('TB 25-26'!$Q:$Q,$A35,'TB 25-26'!$P:$P) -> 1576734.2 | C35: =SUMIF('TB 25-26'!$Q:$Q,$A35,'TB 25-26'!$E:$E)-SUMIF('TB 25-26'!$Q:$Q,$A35,'TB 25-26'!$F:$F) -> 241111.49
A36: Cash at Bank - Local Currency | B36: =SUMIF('TB 25-26'!$Q:$Q,$A36,'TB 25-26'!$O:$O)-SUMIF('TB 25-26'!$Q:$Q,$A36,'TB 25-26'!$P:$P) -> 32588589 | C36: =SUMIF('TB 25-26'!$Q:$Q,$A36,'TB 25-26'!$E:$E)-SUMIF('TB 25-26'!$Q:$Q,$A36,'TB 25-26'!$F:$F) -> 21436133
B38: =SUM(B35:B37) -> 34165323 | C38: =SUM(C35:C37) -> 21677245
A40: SS 4 : GST Input tax credit
A41: GST - Input tax credit | B41: =SUMIF('TB 25-26'!$Q:$Q,$A41,'TB 25-26'!$O:$O)-SUMIF('TB 25-26'!$Q:$Q,$A41,'TB 25-26'!$P:$P) -> 61066767 | C41: =SUMIF('TB 25-26'!$Q:$Q,$A41,'TB 25-26'!$E:$E)-SUMIF('TB 25-26'!$Q:$Q,$A41,'TB 25-26'!$F:$F) -> 32101310
A42: GST payable | B42: =SUMIF('TB 25-26'!$Q:$Q,$A42,'TB 25-26'!$O:$O)-SUMIF('TB 25-26'!$Q:$Q,$A42,'TB 25-26'!$P:$P) -> -48881684 | C42: =SUMIF('TB 25-26'!$Q:$Q,$A42,'TB 25-26'!$E:$E)-SUMIF('TB 25-26'!$Q:$Q,$A42,'TB 25-26'!$F:$F) -> -27036240
B44: =SUM(B41:B43) -> 12185083 | C44: =SUM(C41:C43) -> 5065070

Sheet Sub Sch - p&l
A1: CARGO INTERNTIONAL INDIA PRIVATE LIMITED
A2: SUB SCHEDULE FOR THE YEAR END 31ST MARCH 2026
A3: Particulars | B3: =+'NOTE 15-20'!B5 -> For Year Ended | C3: =+'NOTE 15-20'!C5 -> For Year Ended
B4: 31st March, 2025 | C4: 31st March, 2026
A6: SS 7 : Business Promotion Expense
A7: Advertising & Publicity | B7: =SUMIF('TB 25-26'!Q:Q,'Sub Sch - p&l'!A7,'TB 25-26'!O:O)-SUMIF('TB 25-26'!Q:Q,'Sub Sch - p&l'!A7,'TB 25-26'!P:P) -> 1760 | C7: =SUMIF('TB 25-26'!Q:Q,'Sub Sch - p&l'!A7,'TB 25-26'!E:E)-SUMIF('TB 25-26'!Q:Q,'Sub Sch - p&l'!A7,'TB 25-26'!F:F) -> 1920
A8: Business Promotion | B8: =SUMIF('TB 25-26'!Q:Q,'Sub Sch - p&l'!A8,'TB 25-26'!O:O)-SUMIF('TB 25-26'!Q:Q,'Sub Sch - p&l'!A8,'TB 25-26'!P:P) -> 224657.37 | C8: =SUMIF('TB 25-26'!Q:Q,'Sub Sch - p&l'!A8,'TB 25-26'!E:E)-SUMIF('TB 25-26'!Q:Q,'Sub Sch - p&l'!A8,'TB 25-26'!F:F) -> 1210196
A9: Conference Expenses | B9: =SUMIF('TB 25-26'!Q:Q,'Sub Sch - p&l'!A9,'TB 25-26'!O:O)-SUMIF('TB 25-26'!Q:Q,'Sub Sch - p&l'!A9,'TB 25-26'!P:P) -> 98446.56 | C9: =SUMIF('TB 25-26'!Q:Q,'Sub Sch - p&l'!A9,'TB 25-26'!E:E)-SUMIF('TB 25-26'!Q:Q,'Sub Sch - p&l'!A9,'TB 25-26'!F:F) -> 127702.91 | D9: =84.765*999 -> 84680.235 | E9: =B9-D9 -> 13766.325
A10: Entertainment Expenses | B10: =SUMIF('TB 25-26'!Q:Q,'Sub Sch - p&l'!A10,'TB 25-26'!O:O)-SUMIF('TB 25-26'!Q:Q,'Sub Sch - p&l'!A10,'TB 25-26'!P:P) -> 133503.71 | C10: =SUMIF('TB 25-26'!Q:Q,'Sub Sch - p&l'!A10,'TB 25-26'!E:E)-SUMIF('TB 25-26'!Q:Q,'Sub Sch - p&l'!A10,'TB 25-26'!F:F) -> 293502.1
A11: Gifts & Sales Promotion | B11: =SUMIF('TB 25-26'!Q:Q,'Sub Sch - p&l'!A11,'TB 25-26'!O:O)-SUMIF('TB 25-26'!Q:Q,'Sub Sch - p&l'!A11,'TB 25-26'!P:P) -> 9700 | C11: =SUMIF('TB 25-26'!Q:Q,'Sub Sch - p&l'!A11,'TB 25-26'!E:E)-SUMIF('TB 25-26'!Q:Q,'Sub Sch - p&l'!A11,'TB 25-26'!F:F) -> 0
B13: =SUM(B7:B11) -> 468067.64 | C13: =SUM(C7:C11) -> 1633321.1
A15: SS 5 : Communication Expense
A16: Courier Expense | B16: =SUMIF('TB 25-26'!Q:Q,'Sub Sch - p&l'!A16,'TB 25-26'!O:O)-SUMIF('TB 25-26'!Q:Q,'Sub Sch - p&l'!A16,'TB 25-26'!P:P) -> 49309.02 | C16: =SUMIF('TB 25-26'!Q:Q,'Sub Sch - p&l'!A16,'TB 25-26'!E:E)-SUMIF('TB 25-26'!Q:Q,'Sub Sch - p&l'!A16,'TB 25-26'!F:F) -> 32274.29
A17: Internet Expense | B17: =SUMIF('TB 25-26'!Q:Q,'Sub Sch - p&l'!A17,'TB 25-26'!O:O)-SUMIF('TB 25-26'!Q:Q,'Sub Sch - p&l'!A17,'TB 25-26'!P:P) -> 95016.68 | C17: =SUMIF('TB 25-26'!Q:Q,'Sub Sch - p&l'!A17,'TB 25-26'!E:E)-SUMIF('TB 25-26'!Q:Q,'Sub Sch - p&l'!A17,'TB 25-26'!F:F) -> 65052.3
A18: Mobile Expense | B18: =SUMIF('TB 25-26'!Q:Q,'Sub Sch - p&l'!A18,'TB 25-26'!O:O)-SUMIF('TB 25-26'!Q:Q,'Sub Sch - p&l'!A18,'TB 25-26'!P:P) -> 86678.53 | C18: =SUMIF('TB 25-26'!Q:Q,'Sub Sch - p&l'!A18,'TB 25-26'!E:E)-SUMIF('TB 25-26'!Q:Q,'Sub Sch - p&l'!A18,'TB 25-26'!F:F) -> 88380.76
A19: Telephone Expense | B19: =SUMIF('TB 25-26'!Q:Q,'Sub Sch - p&l'!A19,'TB 25-26'!O:O)-SUMIF('TB 25-26'!Q:Q,'Sub Sch - p&l'!A19,'TB 25-26'!P:P) -> 17676 | C19: =SUMIF('TB 25-26'!Q:Q,'Sub Sch - p&l'!A19,'TB 25-26'!E:E)-SUMIF('TB 25-26'!Q:Q,'Sub Sch - p&l'!A19,'TB 25-26'!F:F) -> 17318.57
C20: =SUMIF('TB 25-26'!Q:Q,'Sub Sch - p&l'!A20,'TB 25-26'!E:E)-SUMIF('TB 25-26'!Q:Q,'Sub Sch - p&l'!A20,'TB 25-26'!F:F) -> 0
B21: =SUM(B16:B20) -> 248680.23 | C21: =SUM(C16:C20) -> 203025.92
A23: SS 6 : Other Expense
A24: Budget Meeting Expenses | B24: =SUMIF('TB 25-26'!Q:Q,'Sub Sch - p&l'!A24,'TB 25-26'!O:O)-SUMIF('TB 25-26'!Q:Q,'Sub Sch - p&l'!A24,'TB 25-26'!P:P) -> 120570.48 | C24: =SUMIF('TB 25-26'!Q:Q,'Sub Sch - p&l'!A24,'TB 25-26'!E:E)-SUMIF('TB 25-26'!Q:Q,'Sub Sch - p&l'!A24,'TB 25-26'!F:F) -> 461666.8 | D24: Travel to Dubai
A25: ITC Write-off | B25: =SUMIF('TB 25-26'!Q:Q,'Sub Sch - p&l'!A25,'TB 25-26'!O:O)-SUMIF('TB 25-26'!Q:Q,'Sub Sch - p&l'!A25,'TB 25-26'!P:P) -> 0 | C25: =SUMIF('TB 25-26'!Q:Q,'Sub Sch - p&l'!A25,'TB 25-26'!E:E)-SUMIF('TB 25-26'!Q:Q,'Sub Sch - p&l'!A25,'TB 25-26'!F:F) -> 0
A26: Donation | B26: =SUMIF('TB 25-26'!Q:Q,'Sub Sch - p&l'!A26,'TB 25-26'!O:O)-SUMIF('TB 25-26'!Q:Q,'Sub Sch - p&l'!A26,'TB 25-26'!P:P) -> 0 | C26: =SUMIF('TB 25-26'!Q:Q,'Sub Sch - p&l'!A26,'TB 25-26'!E:E)-SUMIF('TB 25-26'!Q:Q,'Sub Sch - p&l'!A26,'TB 25-26'!F:F) -> 0
A27: Festival Expenses | B27: =SUMIF('TB 25-26'!Q:Q,'Sub Sch - p&l'!A27,'TB 25-26'!O:O)-SUMIF('TB 25-26'!Q:Q,'Sub Sch - p&l'!A27,'TB 25-26'!P:P) -> 145114.3 | C27: =SUMIF('TB 25-26'!Q:Q,'Sub Sch - p&l'!A27,'TB 25-26'!E:E)-SUMIF('TB 25-26'!Q:Q,'Sub Sch - p&l'!A27,'TB 25-26'!F:F) -> 144763 | D27: OAM Industries ind Pvt Ltd - CRJ 252862000235
A28: Miscellaneous Expenses | B28: =SUMIF('TB 25-26'!Q:Q,'Sub Sch - p&l'!A28,'TB 25-26'!O:O)-SUMIF('TB 25-26'!Q:Q,'Sub Sch - p&l'!A28,'TB 25-26'!P:P) -> 370639.41 | C28: =SUMIF('TB 25-26'!Q:Q,'Sub Sch - p&l'!A28,'TB 25-26'!E:E)-SUMIF('TB 25-26'!Q:Q,'Sub Sch - p&l'!A28,'TB 25-26'!F:F) -> 174006.26 | D28: Interest exp from Private person
A29: Printing & Stationary | B29: =SUMIF('TB 25-26'!Q:Q,'Sub Sch - p&l'!A29,'TB 25-26'!O:O)-SUMIF('TB 25-26'!Q:Q,'Sub Sch - p&l'!A29,'TB 25-26'!P:P) -> 143488.7 | C29: =SUMIF('TB 25-26'!Q:Q,'Sub Sch - p&l'!A29,'TB 25-26'!E:E)-SUMIF('TB 25-26'!Q:Q,'Sub Sch - p&l'!A29,'TB 25-26'!F:F) -> 105501.6
A30: Office Shifting Expense | B30: =SUMIF('TB 25-26'!Q:Q,'Sub Sch - p&l'!A30,'TB 25-26'!O:O)-SUMIF('TB 25-26'!Q:Q,'Sub Sch - p&l'!A30,'TB 25-26'!P:P) -> 0 | C30: =SUMIF('TB 25-26'!Q:Q,'Sub Sch - p&l'!A30,'TB 25-26'!E:E)-SUMIF('TB 25-26'!Q:Q,'Sub Sch - p&l'!A30,'TB 25-26'!F:F) -> 0
A31: Subscription Charges | B31: =SUMIF('TB 25-26'!Q:Q,'Sub Sch - p&l'!A31,'TB 25-26'!O:O)-SUMIF('TB 25-26'!Q:Q,'Sub Sch - p&l'!A31,'TB 25-26'!P:P) -> 1417117.2 | C31: =SUMIF('TB 25-26'!Q:Q,'Sub Sch - p&l'!A31,'TB 25-26'!E:E)-SUMIF('TB 25-26'!Q:Q,'Sub Sch - p&l'!A31,'TB 25-26'!F:F) -> 1621973.9
A32: Utility Expenses | B32: =SUMIF('TB 25-26'!Q:Q,'Sub Sch - p&l'!A32,'TB 25-26'!O:O)-SUMIF('TB 25-26'!Q:Q,'Sub Sch - p&l'!A32,'TB 25-26'!P:P) -> 237204.14 | C32: =SUMIF('TB 25-26'!Q:Q,'Sub Sch - p&l'!A32,'TB 25-26'!E:E)-SUMIF('TB 25-26'!Q:Q,'Sub Sch - p&l'!A32,'TB 25-26'!F:F) -> 250621.77
A33: Training Expenses | B33: =SUMIF('TB 25-26'!Q:Q,'Sub Sch - p&l'!A33,'TB 25-26'!O:O)-SUMIF('TB 25-26'!Q:Q,'Sub Sch - p&l'!A33,'TB 25-26'!P:P) -> 0 | C33: =SUMIF('TB 25-26'!Q:Q,'Sub Sch - p&l'!A33,'TB 25-26'!E:E)-SUMIF('TB 25-26'!Q:Q,'Sub Sch - p&l'!A33,'TB 25-26'!F:F) -> 33000
A34: Rounding off balance | B34: =SUMIF('TB 25-26'!Q:Q,'Sub Sch - p&l'!A34,'TB 25-26'!O:O)-SUMIF('TB 25-26'!Q:Q,'Sub Sch - p&l'!A34,'TB 25-26'!P:P) -> 148.55 | C34: =SUMIF('TB 25-26'!Q:Q,'Sub Sch - p&l'!A34,'TB 25-26'!E:E)-SUMIF('TB 25-26'!Q:Q,'Sub Sch - p&l'!A34,'TB 25-26'!F:F) -> 827.76
A35: Registration and filing fees | B35: =SUMIF('TB 25-26'!Q:Q,'Sub Sch - p&l'!A35,'TB 25-26'!O:O)-SUMIF('TB 25-26'!Q:Q,'Sub Sch - p&l'!A35,'TB 25-26'!P:P) -> 11000 | C35: =SUMIF('TB 25-26'!S:S,'Sub Sch - p&l'!B35,'TB 25-26'!P:P)-SUMIF('TB 25-26'!S:S,'Sub Sch - p&l'!B35,'TB 25-26'!Q:Q) -> 0
B37: =SUM(B24:B35) -> 2445282.8 | C37: =SUM(C24:C35) -> 2792361.1
A39: SS 7 : Professional Charges
A40: GST Audit Fee | B40: =SUMIF('TB 25-26'!Q:Q,'Sub Sch - p&l'!A40,'TB 25-26'!O:O)-SUMIF('TB 25-26'!Q:Q,'Sub Sch - p&l'!A40,'TB 25-26'!P:P) -> 0 | C40: =SUMIF('TB 25-26'!Q:Q,'Sub Sch - p&l'!A40,'TB 25-26'!E:E)-SUMIF('TB 25-26'!Q:Q,'Sub Sch - p&l'!A40,'TB 25-26'!F:F) -> 0
A41: Legal Fees | B41: =SUMIF('TB 25-26'!Q:Q,'Sub Sch - p&l'!A41,'TB 25-26'!O:O)-SUMIF('TB 25-26'!Q:Q,'Sub Sch - p&l'!A41,'TB 25-26'!P:P) -> 14304500 | C41: =SUMIF('TB 25-26'!Q:Q,'Sub Sch - p&l'!A41,'TB 25-26'!E:E)-SUMIF('TB 25-26'!Q:Q,'Sub Sch - p&l'!A41,'TB 25-26'!F:F) -> 1431600
A42: Retainer/ Professional fee | B42: =SUMIF('TB 25-26'!Q:Q,'Sub Sch - p&l'!A42,'TB 25-26'!O:O)-SUMIF('TB 25-26'!Q:Q,'Sub Sch - p&l'!A42,'TB 25-26'!P:P) -> 0 | C42: =SUMIF('TB 25-26'!Q:Q,'Sub Sch - p&l'!A42,'TB 25-26'!E:E)-SUMIF('TB 25-26'!Q:Q,'Sub Sch - p&l'!A42,'TB 25-26'!F:F) -> 30000
A43: Statutory Expenses | B43: =SUMIF('TB 25-26'!Q:Q,'Sub Sch - p&l'!A43,'TB 25-26'!O:O)-SUMIF('TB 25-26'!Q:Q,'Sub Sch - p&l'!A43,'TB 25-26'!P:P) -> 851773.16 | C43: =SUMIF('TB 25-26'!Q:Q,'Sub Sch - p&l'!A43,'TB 25-26'!E:E)-SUMIF('TB 25-26'!Q:Q,'Sub Sch - p&l'!A43,'TB 25-26'!F:F) -> 538370.89
B45: =SUM(B40:B44) -> 15156273 | C45: =SUM(C40:C44) -> 1999970.9
A48: SS 8 : Rent
A49: Office Rent | B49: =SUMIF('TB 25-26'!Q:Q,'Sub Sch - p&l'!A49,'TB 25-26'!O:O)-SUMIF('TB 25-26'!Q:Q,'Sub Sch - p&l'!A49,'TB 25-26'!P:P) -> 2187017 | C49: =SUMIF('TB 25-26'!Q:Q,'Sub Sch - p&l'!A49,'TB 25-26'!E:E)-SUMIF('TB 25-26'!Q:Q,'Sub Sch - p&l'!A49,'TB 25-26'!F:F) -> 1876065
A50: Utility Rent | B50: =SUMIF('TB 25-26'!Q:Q,'Sub Sch - p&l'!A50,'TB 25-26'!O:O)-SUMIF('TB 25-26'!Q:Q,'Sub Sch - p&l'!A50,'TB 25-26'!P:P) -> 46309 | C50: =SUMIF('TB 25-26'!Q:Q,'Sub Sch - p&l'!A50,'TB 25-26'!E:E)-SUMIF('TB 25-26'!Q:Q,'Sub Sch - p&l'!A50,'TB 25-26'!F:F) -> 48000
A51: GUEST HOUSE RENT | B51: =SUMIF('TB 25-26'!Q:Q,'Sub Sch - p&l'!A51,'TB 25-26'!O:O)-SUMIF('TB 25-26'!Q:Q,'Sub Sch - p&l'!A51,'TB 25-26'!P:P) -> 408000 | C51: =SUMIF('TB 25-26'!Q:Q,'Sub Sch - p&l'!A51,'TB 25-26'!E:E)-SUMIF('TB 25-26'!Q:Q,'Sub Sch - p&l'!A51,'TB 25-26'!F:F) -> 211000
B53: =SUM(B49:B52) -> 2641326 | C53: =SUM(C49:C52) -> 2135065
A55: SS 9 : Repairs and Maintenance
A56: Repairs & Maintenance for computers hardware | B56: =SUMIF('TB 25-26'!Q:Q,'Sub Sch - p&l'!A56,'TB 25-26'!O:O)-SUMIF('TB 25-26'!Q:Q,'Sub Sch - p&l'!A56,'TB 25-26'!P:P) -> 29932.2 | C56: =SUMIF('TB 25-26'!Q:Q,'Sub Sch - p&l'!A56,'TB 25-26'!E:E)-SUMIF('TB 25-26'!Q:Q,'Sub Sch - p&l'!A56,'TB 25-26'!F:F) -> 78132.2
A57: Repairs & Maintenance for computers software | B57: =SUMIF('TB 25-26'!Q:Q,'Sub Sch - p&l'!A57,'TB 25-26'!O:O)-SUMIF('TB 25-26'!Q:Q,'Sub Sch - p&l'!A57,'TB 25-26'!P:P) -> 0 | C57: =SUMIF('TB 25-26'!Q:Q,'Sub Sch - p&l'!A57,'TB 25-26'!E:E)-SUMIF('TB 25-26'!Q:Q,'Sub Sch - p&l'!A57,'TB 25-26'!F:F) -> 34008.47
A58: Repairs & Maintenance for office | B58: =SUMIF('TB 25-26'!Q:Q,'Sub Sch - p&l'!A58,'TB 25-26'!O:O)-SUMIF('TB 25-26'!Q:Q,'Sub Sch - p&l'!A58,'TB 25-26'!P:P) -> 418462.21 | C58: =SUMIF('TB 25-26'!Q:Q,'Sub Sch - p&l'!A58,'TB 25-26'!E:E)-SUMIF('TB 25-26'!Q:Q,'Sub Sch - p&l'!A58,'TB 25-26'!F:F) -> 472152.28
A59: Repairs & Maintenance for office equipments | B59: =SUMIF('TB 25-26'!Q:Q,'Sub Sch - p&l'!A59,'TB 25-26'!O:O)-SUMIF('TB 25-26'!Q:Q,'Sub Sch - p&l'!A59,'TB 25-26'!P:P) -> 18820 | C59: =SUMIF('TB 25-26'!Q:Q,'Sub Sch - p&l'!A59,'TB 25-26'!E:E)-SUMIF('TB 25-26'!Q:Q,'Sub Sch - p&l'!A59,'TB 25-26'!F:F) -> 25245
A60: Repairs & Maintenance for vehicles | B60: =SUMIF('TB 25-26'!Q:Q,'Sub Sch - p&l'!A60,'TB 25-26'!O:O)-SUMIF('TB 25-26'!Q:Q,'Sub Sch - p&l'!A60,'TB 25-26'!P:P) -> 0 | C60: =SUMIF('TB 25-26'!Q:Q,'Sub Sch - p&l'!A60,'TB 25-26'!E:E)-SUMIF('TB 25-26'!Q:Q,'Sub Sch - p&l'!A60,'TB 25-26'!F:F) -> 0
B62: =SUM(B56:B61) -> 467214.41 | C62: =SUM(C56:C61) -> 609537.95
A64: SS 10 : Travelling Expense
A65: Foreign Travel | B65: =SUMIF('TB 25-26'!Q:Q,'Sub Sch - p&l'!A65,'TB 25-26'!O:O)-SUMIF('TB 25-26'!Q:Q,'Sub Sch - p&l'!A65,'TB 25-26'!P:P) -> 2868117.9 | C65: =SUMIF('TB 25-26'!Q:Q,'Sub Sch - p&l'!A65,'TB 25-26'!E:E)-SUMIF('TB 25-26'!Q:Q,'Sub Sch - p&l'!A65,'TB 25-26'!F:F) -> 2102952.1
A66: Local Travel | B66: =SUMIF('TB 25-26'!Q:Q,'Sub Sch - p&l'!A66,'TB 25-26'!O:O)-SUMIF('TB 25-26'!Q:Q,'Sub Sch - p&l'!A66,'TB 25-26'!P:P) -> 7200 | C66: =SUMIF('TB 25-26'!Q:Q,'Sub Sch - p&l'!A66,'TB 25-26'!E:E)-SUMIF('TB 25-26'!Q:Q,'Sub Sch - p&l'!A66,'TB 25-26'!F:F) -> 4800
A67: Petrol Charges | B67: =SUMIF('TB 25-26'!Q:Q,'Sub Sch - p&l'!A67,'TB 25-26'!O:O)-SUMIF('TB 25-26'!Q:Q,'Sub Sch - p&l'!A67,'TB 25-26'!P:P) -> 165762.37 | C67: =SUMIF('TB 25-26'!Q:Q,'Sub Sch - p&l'!A67,'TB 25-26'!E:E)-SUMIF('TB 25-26'!Q:Q,'Sub Sch - p&l'!A67,'TB 25-26'!F:F) -> 210831.46
B69: =SUM(B65:B68) -> 3041080.3 | C69: =SUM(C65:C68) -> 2318583.6

Sheet IT Dep
A2: CARGO INTERNATIONAL (INDIA) PRIVATE LIMITED
A3: Schedule of depreciation as per Income Tax Act 1961.
A5: NAME OF THE ASSETS | B5: Op WDV as on 01.04.2024 | C5: Addition | E5: Deletions | F5: As on 31.03.2025 | G5: Rate of Dep | H5: Dep. Amt | I5: WDV As on 31.03.2025
C6: > 180 | D6: < 180
A8: Mobiles | B8: 131272 | C8: 0 | D8: 0 | E8: 0 | F8: =B8+C8+D8-E8 -> 131272 | G8: 0.15 | H8: =ROUND(((B8+C8)*G8)+(D8*G8/2),0) -> 19691 | I8: =F8-H8 -> 111581
A10: Computers | B10: 106903.59 | C10: 32966.11 | D10: 0 | E10: 0 | F10: =B10+C10+D10-E10 -> 139869.7 | G10: 0.4 | H10: =ROUND(((B10+C10)*G10)+(D10*G10/2),0) -> 55948 | I10: =F10-H10 -> 83921.7
A12: Furniture and fittings | B12: 529371.39 | C12: 0 | D12: 0 | E12: 0 | F12: =B12+C12+D12-E12 -> 529371.39 | G12: 0.1 | H12: =ROUND(((B12+C12)*G12)+(D12*G12/2),0) -> 52937 | I12: =F12-H12 -> 476434.39
A14: Motor Car | B14: 0 | C14: 0 | D14: 0 | E14: 0 | F14: =B14+C14+D14-E14 -> 0 | G14: 0.15 | H14: 0 | I14: =F14-H14 -> 0
A16: Interior decoration | B16: 1931015 | C16: 0 | D16: 0 | E16: 0 | F16: =B16+C16+D16-E16 -> 1931015 | G16: 0.1 | H16: =ROUND(((B16+C16)*G16)+(D16*G16/2),0) -> 193102 | I16: =F16-H16 -> 1737913
A18: Electrical equipments | B18: 196279 | C18: 56000 | D18: 0 | E18: 0 | F18: =B18+C18+D18-E18 -> 252279 | G18: 0.15 | H18: =ROUND(((B18+C18)*G18)+(D18*G18/2),0) -> 37842 | I18: =F18-H18 -> 214437
A20: Office Equipment | B20: 301679.6 | C20: 0 | D20: 0 | E20: 0 | F20: =B20+C20+D20-E20 -> 301679.6 | G20: 0.15 | H20: =ROUND(((B20+C20)*G20)+(D20*G20/2),0) -> 45252 | I20: =F20-H20 -> 256427.6
A22: TOTAL | B22: =SUM(B8:B21) -> 3196520.6 | C22: =SUM(C8:C21) -> 88966.11 | D22: =SUM(D8:D21) -> 0 | E22: =SUM(E8:E21) -> 0 | F22: =SUM(F8:F21) -> 3285486.7 | G22: =SUM(G8:G21) -> 1.2 | H22: =SUM(H8:H21) -> 404772 | I22: =SUM(I8:I21) -> 2880714.7
A24: Total Addition as per IT Dep | C24: =+C22+D22 -> 88966.11 | E24: =+E22 -> 0
A25: Total Addition as per CA Dep | C25: =+'Note 9'!C20 -> 374327.06 | E25: =+'Note 9'!D20 -> 0
C26: =+C24-C25 -> -285360.95 | E26: =+E24-E25 -> 0

Sheet Deffered Tax
A2: =+'IT Dep'!A2:I2 -> CARGO INTERNATIONAL (INDIA) PRIVATE LIMITED | F2: =+A2 -> CARGO INTERNATIONAL (INDIA) PRIVATE LIMITED
A3: Schedule for Deffered Tax Calculation | F3: =+A3 -> Schedule for Deffered Tax Calculation
A4: P&L Approach | F4: BL Approach
F7: Particulars | G7: Amount of expenses | H7: Deffered Tax Amount | I7: DTA/DTL
F9: Opening balance as on 01.04.2024 | H9: =634957.698/Deno -> 634957.7 | I9: DTA
F11: on account of Depreciation
F12: WDV as per Income Tax Act | G12: =+'IT Dep'!I22/Deno -> 2880714.7
F13: WDV as per Companies Act | G13: =+'Note 9'!J20 -> 843227.31 | H13: =(G12-G13)*27.82% -> 566828.99 | I13: DTA
F16: on account of expenses allowed on payable basis
F17: Provision as per IT | G17: 0
F18: Provision as per CA | G18: 0 | H18: =(G17-G18)*27.82% -> 0
I19: DTA
F21: Closing balance as on 31.03.25 | H21: =+H13+H18 -> 566828.99
F23: Provision to be reversed for the year | H23: =+H21-H9 -> -68128.709 | I23: DTI

Sheet Statement of Income
A1: =+BS!A1 -> CARGO INTERNATIONAL (INDIA) PRIVATE LIMITED
A2: =+BS!A4 -> Old No.7 / New No.13, First Floor, First Cross Street, Trustpuram, Kodambakkam, Chennai - 600024, India
A4: D.O.I | B4: 40430 | D4: AY | E4: 2026 - 27
A5: E MAIL ID | B5: accounts@cargo-int.com | D5: FY | E5: 2025 - 26
A6: PH NO | B6: 9600100917 | D6: PAN NO | E6: AAECC1295N
G7: Disallowance FY 25-26
A8: Statement of Income | G8: Interest on TDS Late filing | H8: =+'NOTE 15-20'!B39 -> 26067
G9: Expense not pertaining to Business | H9: =+'NOTE 15-20'!B46 -> 468067.64
A10: INCOME FROM BUSINESS
B12: Profit as per Profit and loss account | E12: =+PL!D29*Deno -> -9432613.1
A14: Add: | B14: Disallowed Expenses
B15: a) Depreciation as per Companies Act | D15: =+'Note 9'!G20*Deno -> 264309
B16: b) ICDS Unrealised Forex
B17: c) PT Disallowances
B18: d) PF Disallowances
B19: e) Expenses Disallowed
B20: i) Liabilities Writeback/Writeoff as expenses | D20: 0
B21: ii) Exceptional items/extra-ordinary items | D21: 0
D22: 0 | E22: =+SUM(D15:D22) -> 264309
E24: =+SUM(E12:E22) -> -9168304.1
A26: Less: | B26: Allowable Expenses
B27: Depreciation as per Income Tax Act | D27: =+'IT Dep'!H22 -> 404772 | E27: =-SUM(D26:D27) -> -404772
B29: Business income | E29: =SUM(E24:E27) -> -9573076.1
A31: Less: | B31: Business loss carried forward from earlier year | E31: 0
B32: set off current year
A34: TAXABLE INCOME | E34: =E29-E31 -> -9573076.1
B36: Tax on normal slab @ 25% | D36: (A) | E36: =E34*25% -> -2393269
B38: Tax payable under section 115JB | D38: (B) | E38: =+D89 -> 0 | G38: Calculation for the Interest under 234B & C
I39: 45382
B40: Tax under normal computation = higher of | D40: ( A ) or ( B ) | E40: =+MAX(E36,E38) -> 0 | H40: 234B
A41: Add: | B41: Surcharge 7% | E41: =IF(E29>10000000,E40*7%,0) -> 0 | G41: 55402.98 | H41: Total Tax Liability | I41: =+E44 -> 0
E42: =SUM(E40:E41) -> 0 | G42: 609432.78 | H42: Less TDS | I42: =+C47 -> 3660953
A43: Add: | B43: Health and Education cess | E43: =E42*4% -> 0 | G43: 633810.09 | I43: =+I41-I42 -> -3660953
E44: =SUM(E42:E43) -> 0 | G44: 654762.49 | H44: 90% of the Tax | I44: =+I43*90% -> -3294857.7
G45: =G43-G44 -> -20952.4 | H45: Advance Tax Paid | I45: =+F29 -> 0
A46: Less: | B46: Advance Tax | C46: 0 | H46: Difference | I46: =I43-I45 -> -3660953
B47: Tax deducted at source | C47: 3660953 | E47: =SUM(C46:C47) -> 3660953 | F47: As on 25-09-2025 | H47: Interest | I47: =I46*1%*(ROUND(((EOMONTH(TODAY(),0)-I39)/365)*12,0)) -> -1061676.4
E48: =E44-E47 -> -3660953
A50: Add: | B50: Interest u/s 234 A | C50: 0 | H50: 234C | J50: Actual Paid | K50: Difference | L50: Interest
B51: Interest u/s 234 B | C51: =+IF(E48<0,0,I47) -> 0 | H51: Total Tax Liability | I51: =+E44-C47 -> -3660953 | J51: 0 | K51: 0
B52: Interest u/s 234 C | C52: =+IF(E48<0,0,L56) -> 0 | E52: =+SUM(C50:C52) -> 0 | H52: 15% upto 15.06.2020 | I52: =+ROUND(I51*15%,0) -> -549143 | J52: 0 | K52: =+I52-J52 -> -549143 | L52: =+ROUND(K52*1%*3,0) -> -16474
H53: 45% upto 15.09.2020 | I53: =+ROUND(I51*45%,0) -> -1647429 | J53: 0 | K53: =+I53-J53 -> -1647429 | L53: =+ROUND(K53*1%*3,0) -> -49423
B54: Tax Payable/(Refund) | E54: =ROUND(E48+E52,-1) -> -3660950 | H54: 75% Upto 15.12.2020 | I54: =+ROUND(I51*75%,0) -> -2745715 | J54: 0 | K54: =+I54-J54 -> -2745715 | L54: =+ROUND(K54*1%*3,0) -> -82371
H55: 100% up to 15.03.2021 | I55: =+I51 -> -3660953 | J55: =+F29 -> 0 | K55: =+I55-J55 -> -3660953 | L55: =+ROUND(K55*1%*1,0) -> -36610
H56: Total Interest | L56: =ROUND(SUM(L52:L55),0) -> -184878
A58: Computation of Book Profit as per Sec. 115JB | C58: Amount in Rs.
A60: Net Profit as per Profit & Loss Account before tax | D60: =+E12 -> -9432613.1
A62: Add : -
A63: i. | B63: Income Tax Paid or Payble | C63: 0
A64: ii. | B64: Amount carried to reserves | C64: 0
A65: iii. | B65: Provisions for uncertain liabilities | C65: 0
A66: iv. | B66: Provisions for losses of Subsidiary companies | C66: 0
A67: v. | B67: Dividends paid or proposed | C67: 0
A68: vi. | B68: Expenditure relatable to any income to which any of the | C68: 0
B69: Sections 10/10A/10B/11/12 applies | C69: 0
A70: vii. | B70: Depriciation debited to P&L A/C (Normal & Revaluation) | C70: =+'Note 9'!G20*10^5 -> 26430900000
A71: viii. | B71: Deffered Tax Liability | C71: 0
A72: ix. | B72: Value of Revaluation of Asset Which effects the Rev Reserve | C72: 0
A73: x. | B73: Income/Loss In the case of units in Sec 47(xvii) | C73: 0
D74: =SUM(C63:C73) -> 26430900000
A75: Less:-
A76: i. | B76: Amount withdrawn from reserves or provisions | C76: 0
A77: ii. | B77: Any income to which any of the Sections 10/10A/10B/11/12 applies | C77: 0
A78: iii. | B78: Depriciation debited to P&L A/C (Normal) | C78: =+C70 -> 26430900000
A79: iv. | B79: Withdrawn from Revaluation Reserve Credited to P&L A/c | C79: 0
A80: v. | B80: Loss brought forward or unabsorbed depriciation, whichever is less | C80: 0
A81: vi. | B81: Amount of deduction u/s 80HHC ,HHE,HHF | C81: 0
A82: vii. | B82: Profit of Sick Industrial Unit | C82: 0
A83: viii. | B83: Deffered Tax Asset | C83: 0
A84: ix. | B84: Income/Loss In the case of units in Sec 47(xvii) | C84: 0
D85: =SUM(C76:C84) -> 26430900000
B88: Book profit as per Section 115JB | C88: =D60+D74-D85 -> -9432613.1
B89: 15 % of Book Profit u/s 115JB | D89: =ROUND(IF(C88>0,15.6%*C88,0),0) -> 0
