Workbook
Name _Hlk135152171: 'Accounting Polices'!$C$26
Name _Hlk525235484: 'Accounting Polices'!$C$44
Name OLE_LINK1: 'Balance Sheet Notes'!#REF!

Sheet About Sheet
A1: TallyOnWheels - Financial Report
A2: Thank you for using Tallyonwheels.
A3: This file is an Excel output of your Financial Report.
A5: Company Name | B5: K.U.M. India Private Limited - (from 1-Apr-23)
A6: Entity Name | B6: Ramanujam & Boovarahan
A7: Financial year | B7: 01-APR-2023 - 31-MAR-2024
A8: Last Synced | B8: 16-MAY-2024 11:27:32AM

Sheet Master Sheet
A1: Basic Details | C1: Data Entry
A2: Company Name | C2: K.U.M. India Private Limited - (from 1-Apr-24)
A3: Current Financial Year | C3: 01-Apr-2024 - 31-Mar-2025
A4: Assessment Year
A5: Rounding Off | C5: Amount in ₹.
A6: Divisor | C6: =VLOOKUP(C5,A40:B45,2,0) -> 1
A7: Name of the Auditee
A8: Nature of Organisation of the Auditee
A9: Address of the Auditee | B9: Line 1 | C9: A5 second floor,
B10: Line 2 | C10: Rajeswari Apartments, 45 Vellalar street,
B11: Line 3 | C11: Kodambakkam,
B12: Line 4 | C12: Chennai- 600024.
A13: PAN
A14: Name of the Person Signing the Auditee's FS | B14: Signatory 1
B15: Signatory 2
B16: Signatory 3
A17: Designation of the Sigining Person | B17: Signatory 1
B18: Signatory 2
B19: Signatory 3
A20: DIN of | B20: Signatory 1
B21: Signatory 2
B22: Signatory 3
A23: Firm Name
A24: ICAI Firm Reg No.
A25: Name of the Signing Partner
A26: Designation of the Signing CA
A27: Membership Number of the Signing Partner
A28: UDIN
A29: Date of Signing the Financials by auditor
A30: Date of Signing the Financials by | B30: Signatory 1
B31: Signatory 2
B32: Signatory 3
A33: Place of Signing the Financials by auditor
A34: Place of Signing the Financials by signatories
A35: Sector (of the Auditee)
A36: Sub-Sector (of the Auditee)
A37: Code (as per Form 3CD)
A38: CIN of Company | C38: U29100TN2020PTC135386
A39: Date of Incorporation | C39: 43972
A40: Amount in ₹. | B40: 1
A41: ₹. In 00's | B41: 100
A42: ₹. In 000 's | B42: 1000
A43: ₹. In Lacs | B43: 100000
A44: ₹. In Million | B44: 1000000
A45: ₹. In Crores | B45: 10000000

Sheet TB
A1: K.U.M. India Private Limited 24-25
A2: Trial Balance
A3: 1-Apr-24 to 31-Mar-25
B4: K.U.M. India Private Limited 24-25
A5: Particulars | B5: 1-Apr-24 to 31-Mar-25
B6: Opening | C6: Transactions | E6: Closing
B7: Balance | C7: Debit | D7: Credit | E7: Balance
A8: Capital Account | B8: 1500000 | E8: 1500000
A9: Authorised Share Capital | B9: 1500000 | E9: 1500000
A10: Loans (Liability) | B10: 11277225 | E10: 11277225
A11: External Commercial Borrowings | B11: 11277225 | E11: 11277225 | K11: will be repaid after 5 years
A12: Current Liabilities | B12: 22642240 | C12: 24428651 | D12: 1840733.9 | E12: 54323.08
A13: Duties & Taxes | B13: 3433207.7 | C13: 3754082.7 | D13: 326355.5 | E13: 5480.5
A14: GST Liability | C14: 284050 | D14: 284050
A15: GST RCM Payable | B15: 3421681.7 | C15: 3441481.7 | D15: 21600 | E15: 1800
A16: Professional Tax | C16: 2500 | D16: 2500
A17: TDS - Contracts | B17: 616 | C17: 2241 | D17: 1855.5 | E17: 230.5
A18: TDS-Professional Services | B18: 10910 | C18: 23810 | D18: 16350 | E18: 3450
A19: Sundry Creditors | B19: 18999343 | C19: 19207390 | D19: 208047.33
A20: Expenses O/s | B20: 208082.4 | C20: 1443321.9 | D20: 1282239.1 | E20: 46999.58
A21: Audit Fee Payable A/c | B21: 67500 | C21: 67500
A22: DB Schenker A/c | C22: 133884.1 | D22: 133884.1
A23: Dinesh A/c | C23: 162604 | D23: 162604 | L23: He is not taking any remuneration
A24: ECB2 Return Filing Charges Payable | B24: 1500 | C24: 1500 | D24: 1000 | E24: 1000
A25: Hapag Lloyd A/c | B25: 85904 | C25: 85904
A26: ICEGATE | C26: 53732 | D26: 53732 | L26: customs duty
A27: Integrated Registry Management Services | C27: 5900 | D27: 5900
A28: Ms.Subhashini | B28: 41178.4 | C28: 538678.82 | D28: 537500 | E28: 39999.58
A29: Professional Fees Payable A/c | B29: 12000 | C29: 12000 | D29: 6000 | E29: 6000
A30: RBCA | C30: 103140 | D30: 103140
A31: RBJV Associates | C31: 158479 | D31: 158479
A32: Vanitha A/c | C32: 120000 | D32: 120000
A33: Deferred Tax Liability | B33: 1607 | E33: 1607
A34: DHL Express | C34: 5310 | D34: 5310
A35: Ms Rajarajeshwari | C35: 2000 | D35: 2000
A36: Ms Subhashini - Reimbursement | C36: 16545.98 | D36: 16781.98 | E36: 236
A37: Fixed Assets | B37: 18426.28 | D37: 15914 | E37: 2512.28
A38: Laptop A/c | B38: 18426.28 | D38: 15914 | E38: 2512.28
A39: Current Assets | B39: 31634446 | C39: 4.1666863e+08 | D39: 4.3891241e+08 | E39: 9390663.6
A40: Deposits (Asset) | C40: 191200000 | D40: 191200000
A41: ICICI Fixed Deposit | C41: 191200000 | D41: 191200000
A42: Loans & Advances (Asset) | C42: 1032125 | D42: 31633 | E42: 1000492
A43: Advance Tax A/c | C43: 1000000 | E43: 1000000
A44: NSDL - Advance | C44: 32125 | D44: 31633 | E44: 492
A45: Sundry Debtors | B45: 28248000 | C45: 1862109 | D45: 30110109
A46: Bank Accounts | B46: 1677070.1 | C46: 2.2228228e+08 | D46: 2.1659405e+08 | E46: 7365299
A47: ICICI Bank | B47: 1677070.1 | C47: 2.2228228e+08 | D47: 2.1659405e+08 | E47: 7365299
A48: GST | B48: 1152769.3 | C48: 245721.62 | D48: 420015.37 | E48: 978475.59
A49: Receivables | B49: 607 | D49: 607
A50: Receivable From DB Schenker | B50: 607 | D50: 607
A51: TDS Receivable | B51: 556000 | C51: 46397 | D51: 556000 | E51: 46397
A52: TDS Receivable - ICICI | C52: 46397 | E52: 46397
A53: TDS Receivable - SMPL | B53: 556000 | D53: 556000
A54: Sales Accounts | D54: 1578059 | E54: 1578059
A55: Business Support Services | D55: 1578059 | E55: 1578059
A56: Direct Expenses | C56: 142121 | D56: 72800 | E56: 69321
A57: Project Expense A/c | C57: 137621 | D57: 72800 | E57: 64821
A58: OBS Air Shipment Expense | C58: 27508 | E58: 27508
A59: OBS Sea Shipment Expense | C59: 67345 | D59: 72800 | E59: 5455
A60: Return Air Shipment | C60: 42768 | E60: 42768
A61: Clearance Charges | C61: 4500 | E61: 4500
A62: Indirect Incomes | C62: 1.83 | D62: 492265.71 | E62: 492263.88
A63: Discount A/c | D63: 6870 | E63: 6870 | K63: just like credit points discount is being provided here
A64: Gain on Forex | D64: 4747.33 | E64: 4747.33
A65: Interest on ICICI FD A/c | D65: 463966 | E65: 463966
A66: Interest Received on IT Refund | D66: 16680 | E66: 16680
A67: Rounding Off | C67: 1.83 | D67: 2.38 | E67: 0.55
A68: Indirect Expenses | C68: 1672781.7 | E68: 1672781.7
A69: Bank Charges | C69: 41615.74 | E69: 41615.74
A70: Bank Charges | C70: 35615.74 | E70: 35615.74
A71: ECB2 Return Filing Charges | C71: 6000 | E71: 6000
A72: Compliance Cost | C72: 255281.33 | E72: 255281.33
A73: Other Compliance Cost | C73: 252397.33 | E73: 252397.33 | K73: Demat account documentation charges
A74: ROC Fees | C74: 2884 | E74: 2884
A75: Audit Fees | C75: 20500 | E75: 20500
A76: Communication Expenses | C76: 13101.98 | E76: 13101.98
A77: Company Tax | C77: 8000 | E77: 8000
A78: Compliance Cost | C78: 500 | E78: 500
A79: Courier Charges | C79: 280 | E79: 280
A80: Depreciation | C80: 15914 | E80: 15914
A81: Festival Bonus | C81: 20000 | E81: 20000
A82: Loss on Forex | C82: 320849.63 | E82: 320849.63
A83: Performance Incentive A/c | C83: 40000 | E83: 40000
A84: Printing & Stationery | C84: 875 | E84: 875
A85: Professional Fees | C85: 151000 | E85: 151000
... A88: Travel Expenses | C88: 163264 | E88: 163264
A89: Profit & Loss A/c | B89: 3766592.4 | E89: 3766592.4
A90: Grand Total | C90: 4.4291219e+08 | D90: 4.4291219e+08

Sheet Sheet1
B2: K.U.M. India Private Limited 25-26
B3: Trial Balance
B4: 1-Apr-25 to 31-Mar-26
C5: K.U.M. India Private Limited 25-26
B6: Particulars | C6: 1-Apr-25 to 31-Mar-26
C7: Opening | D7: Transactions | F7: Closing
C8: Balance | D8: Debit | E8: Credit | F8: Balance
B9: Capital Account | C9: 1500000 | F9: 1500000
B10: Authorised Share Capital | C10: 1500000 | F10: 1500000
B11: Loans (Liability) | C11: 11540575 | D11: 11540575
B12: External Commercial Borrowings | C12: 11540575 | D12: 11540575
B13: Current Liabilities | C13: 135216.5 | D13: 52555948 | E13: 52557032 | F13: 136300
B14: Duties & Taxes | C14: 13730.5 | D14: 13450598 | E14: 13454667 | F14: 17800
B15: GST RCM Payable | C15: 1800 | D15: 5616712 | E15: 5616712 | F15: 1800
B16: Output CGST Payable A/c | D16: 3897000 | E16: 3897000
B17: Output SGST Payable A/c | D17: 3897000 | E17: 3897000
B18: Professional Tax | D18: 2500 | E18: 2500
B19: TDS - Contracts | C19: 230.5 | D19: 10185.5 | E19: 9955
B20: TDS-Professional Services | C20: 11700 | D20: 27200 | E20: 31500 | F20: 16000
B21: Sundry Creditors | D21: 27181386 | E21: 31083954 | F21: 3902568
B22: KUM Germany Creditors-Lease Charges | D22: 27181386 | E22: 27181386
B23: KUM Germany Creditors-Mobalisation Charges | E23: 3902568
B24: Expenses O/s | C24: 121250 | D24: 11906635 | E24: 8001317.1 | F24: 3784068
B25: 6 LABS EUROPE GMBH | D25: 6558750 | E25: 6558750
B26: Airtel | D26: 236 | E26: 236
B27: Audit Fee Payable A/c | C27: 74250 | D27: 74250 | E27: 112500 | F27: 112500
B28: ECB2 Return Filing Charges Payable | C28: 1000 | D28: 1000
B29: ICEGATE | D29: 1000 | E29: 1000
B30: Integrated Registry Management Services | D30: 5900 | E30: 5900
B31: KUM Germany Creditors- Mobilisation Charges Payable | D31: 3902568 | F31: 3902568
B32: Ms.Subhashini | C32: 40000 | D32: 357500 | E32: 317500
B33: NSDL | D33: 5900 | E33: 5900
B34: Professional Fees Payable A/c | C34: 6000 | D34: 6000 | E34: 6000 | F34: 6000
B35: RBCA | D35: 89100 | E35: 89100
B36: RBJV Associates | D36: 207054 | E36: 207054
B37: Tripadam Logistics Private Limited | D37: 484577.08 | E37: 484577.08
B38: Vanitha A/c | D38: 120000 | E38: 120000
B39: Virogreen | D39: 92800 | E39: 92800
B40: Deepika | D40: 10000 | E40: 10000
B41: Ms Subhashini - Reimbursement | C41: 236 | D41: 7329.46 | E41: 7093.46
B42: Fixed Assets | C42: 2512.28 | E42: 2512.28
B43: Laptop A/c | C43: 2512.28 | E43: 2512.28
B44: Current Assets | C44: 9390912.5 | D44: 1.3589708e+08 | E44: 1.3874882e+08 | F44: 6539171.5
B45: Deposits (Asset) | D45: 9800000 | E45: 9800000
B46: ICICI Fixed Deposit | D46: 9800000 | E46: 9800000
B47: Loans & Advances (Asset) | C47: 1000492 | D47: 1450000 | E47: 1000000 | F47: 1450492
B48: Advance Tax A/c | C48: 1000000 | D48: 1450000 | E48: 1000000 | F48: 1450000
B49: NSDL - Advance | C49: 492 | F49: 492
B50: Sundry Debtors | D50: 50228000 | E50: 50228000
B51: Bank Accounts | C51: 7365298.9 | D51: 62013067 | E51: 65309756 | F51: 4068610.2
B52: ICICI Bank | C52: 7365298.9 | D52: 62013067 | E52: 65309756 | F52: 4068610.2
B53: GST | C53: 978475.59 | D53: 11523352 | E53: 12364670 | F53: 137157.28
B54: GST Receivable | C54: 0.02 | D54: 5761676.5 | E54: 5761676.5
B55: Input CGST Receivable A/c | C55: 0.01 | D55: 82437.73 | E55: 82437.74
B56: Input IGST Receivable A/c | D56: 5596802 | E56: 5596802
B57: Input SGST Receivable A/c | C57: 0.01 | D57: 82436.73 | E57: 82436.74
B58: Input CGST | C58: 53010.81 | D58: 82437.33 | E58: 67062 | F58: 68386.14
B59: Input IGST | C59: 872453.95 | D59: 5596801 | E59: 6468870 | F59: 385
B60: Input SGST | C60: 53010.81 | D60: 82437.33 | E60: 67062 | F60: 68386.14
B61: TDS Receivable | C61: 46397 | D61: 882663 | E61: 46397 | F61: 882663
B62: TDS Receivable - ICICI | C62: 46397 | D62: 16663 | E62: 46397 | F62: 16663
B63: TDS Receivable - SMPL | D63: 866000 | F63: 866000
B64: Deferred Tax Asset | C64: 249 | F64: 249
B65: Sales Accounts | E65: 43300000 | F65: 43300000
B66: Service Charges - Domestic | E66: 43300000 | F66: 43300000
B67: Direct Expenses | D67: 37201440 | E67: 6834420 | F67: 30367020
B68: Project Expense A/c | D68: 37201440 | E68: 6834420 | F68: 30367020
B69: OBS Rental A/c | D69: 36679066 | E69: 6103260 | F69: 30575806
B70: OBS Sea Shipment Expense | D70: 58493.26 | E70: 731160 | F70: 672666.74
D71: 463881 | F71: 463881
B72: Indirect Incomes | D72: 7.37 | E72: 224177.18 | F72: 224169.81
B73: Interest on ICICI FD A/c | E73: 166630 | F73: 166630
B74: Interest Received on IT Refund | E74: 57547 | F74: 57547
B75: Rounding Off | D75: 7.37 | E75: 0.18 | F75: 7.19
B76: Indirect Expenses | D76: 4473911.3 | E76: 2000 | F76: 4471911.3
B77: Bank Charges | D77: 53387.17 | E77: 2000 | F77: 51387.17
B78: Bank Charges | D78: 48387.17 | E78: 2000 | F78: 46387.17
B79: ECB2 Return Filing Charges | D79: 5000 | F79: 5000
B80: Compliance Cost | D80: 11854 | F80: 11854
B81: MGT Filing Fee | D81: 824 | F81: 824
B82: Other Compliance Cost | D82: 10000 | F82: 10000
B83: ROC Fees | D83: 1030 | F83: 1030
B84: Audit Fees | D84: 125000 | F84: 125000
B85: Communication Expenses | D85: 8252.92 | F85: 8252.92
B86: Company Tax | D86: 6000 | F86: 6000
B87: Condonation Charges | D87: 1000 | F87: 1000
B88: Depreciation | D88: 2512.28 | F88: 2512.28
B89: Interest on TDS | D89: 60 | F89: 60
B90: Local Conveyance | D90: 194 | F90: 194
... B95: Software Expenses | D95: 4387 | F95: 4387
B96: Profit & Loss A/c | C96: 3782366.7 | F96: 3782366.7
B97: Grand Total | D97: 2.4166896e+08 | E97: 2.4166896e+08

Sheet Working TB
B2: K.U.M India Private Limited
B3: ='Master Sheet'!C9&'Master Sheet'!C10&'Master Sheet'!C11&'Master Sheet'!C12 -> A5 second floor,Rajeswari Apartments, 45 Vellalar street, Kodambakkam,Chennai- 600024.
B4: ='Master Sheet'!C38 -> U29100TN2020PTC135386
B5: Trial Balance for the Year ended March 31, 2026
B7: Particulars | C7: Opening Balance as on 01.04.2025 | E7: Current Transactions | G7: Closing Balance as on 31.03.2026
C8: Debit | D8: Credit | E8: Debit | F8: Credit | G8: Debit | H8: Credit
B10: Capital Account
B11: Issued and Paidup Share Capital | D11: =Sheet1!C10 -> 1500000 | E11: =TB!C8 -> 0 | F11: =TB!D8 -> 0 | G11: =C11+E11-F11 -> 0 | H11: =D11+F11-E11 -> 1500000
B12: Loans (Liability) | E12: =TB!C9 -> 0 | F12: =TB!D9 -> 0 | G12: =C12+E12-F12 -> 0 | H12: =D12+F12-E12 -> 0
B13: External Commercial Borrowings | D13: =Sheet1!C12 -> 11540575 | E13: =Sheet1!D12 -> 11540575 | G13: 0 | H13: =D13+F13-E13 -> 0
B14: Current Liabilities | G14: =C14+E14-F14 -> 0 | H14: =D14+F14-E14 -> 0
B15: Duties & Taxes | G15: =C15+E15-F15 -> 0 | H15: =D15+F15-E15 -> 0
B16: GST RCM Payable | D16: =Sheet1!C15 -> 1800 | E16: =Sheet1!D15 -> 5616712 | F16: =Sheet1!E15 -> 5616712 | H16: =D16+F16-E16 -> 1800
B17: Output CGST Payable | E17: =Sheet1!D16 -> 3897000 | F17: =Sheet1!E16 -> 3897000
B18: Output SGST Payable | E18: =Sheet1!D17 -> 3897000 | F18: =Sheet1!E17 -> 3897000
B19: Professional Tax | E19: =Sheet1!D18 -> 2500 | F19: =Sheet1!E18 -> 2500 | G19: =C19+E19-F19 -> 0 | H19: =D19+F19-E19 -> 0
B20: Provision for Tax FY 25-26 | C20: 0 | D20: 0 | F20: =D134 -> 1255554 | G20: 0 | H20: =D20+F20-E20 -> 1255554
B21: TDS - Contracts | D21: =Sheet1!C19 -> 230.5 | E21: =Sheet1!D19 -> 10185.5 | F21: =Sheet1!E19 -> 9955 | H21: =D21+F21-E21 -> 0
B22: TDS-Professional Services | D22: =Sheet1!C20 -> 11700 | E22: =Sheet1!D20 -> 27200 | F22: =Sheet1!E20 -> 31500 | H22: =D22+F22-E22 -> 16000
B23: Sundry Creditors | H23: =D23+F23-E23 -> 0
B24: KUM Germany Creditors-Lease Charges | E24: =Sheet1!D22 -> 27181386 | F24: =Sheet1!E22 -> 27181386
B25: KUM Germany Creditors-Mobalisation Charges | E25: =C128 -> 3902568 | F25: =Sheet1!E23 -> 3902568
B26: Expenses O/s | G26: =C26+E26-F26 -> 0 | H26: =D26+F26-E26 -> 0
B27: Audit Fee Payable A/c | D27: =Sheet1!C27 -> 74250 | E27: =Sheet1!D27 -> 74250 | F27: =Sheet1!E27 -> 112500 | H27: =D27+F27-E27 -> 112500
B28: 6LABS EUROPH GMBH | E28: =Sheet1!D25 -> 6558750 | F28: =Sheet1!E25 -> 6558750 | G28: =C28+E28-F28 -> 0 | H28: =D28+F28-E28 -> 0
B29: AIRTEL | E29: =Sheet1!D26 -> 236 | F29: =Sheet1!E26+D124 -> 1414.82 | H29: =D29+F29-E29 -> 1178.82
B30: ECB2 Return Filing Charges Payable | D30: =Sheet1!C28 -> 1000 | E30: =Sheet1!D28 -> 1000 | F30: =D119 -> 1000 | H30: =D30+F30-E30 -> 1000
B31: ICEGATE | E31: =Sheet1!D29 -> 1000 | F31: =Sheet1!E29 -> 1000 | G31: =C31+E31-F31 -> 0 | H31: =D31+F31-E31 -> 0
B32: Integrated Registry Management Services | E32: =Sheet1!D30 -> 5900 | F32: =Sheet1!E30 -> 5900 | G32: =C32+E32-F32 -> 0 | H32: =D32+F32-E32 -> 0
B33: Ms.Subhashini | D33: =Sheet1!C32 -> 40000 | E33: =Sheet1!D32 -> 357500 | F33: =Sheet1!E32 -> 317500 | H33: =D33+F33-E33 -> 0
B34: Professional Fees Payable A/c | D34: =Sheet1!C34 -> 6000 | E34: =Sheet1!D34 -> 6000 | F34: =Sheet1!E34 -> 6000 | H34: =D34+F34-E34 -> 6000
B35: RBCA | D35: 0 | E35: =Sheet1!D35 -> 89100 | F35: =Sheet1!E35 -> 89100 | G35: =C35+E35-F35 -> 0 | H35: =D35+F35-E35 -> 0
B36: RBJV Associates | D36: 0 | E36: =Sheet1!D36 -> 207054 | F36: =Sheet1!E36 -> 207054 | G36: =C36+E36-F36 -> 0 | H36: =D36+F36-E36 -> 0
B37: Vanitha A/c | E37: =Sheet1!D38 -> 120000 | F37: =Sheet1!E38 -> 120000 | G37: =C37+E37-F37 -> 0 | H37: =D37+F37-E37 -> 0 | I37: =G36+G37 -> 0
B38: Virogreen | E38: =Sheet1!D39 -> 92800 | F38: =Sheet1!E39 -> 92800 | G38: =C38+E38-F38 -> 0 | H38: =D38+F38-E38 -> 0
B39: KUM Germany Creditors-Mobalisation Charges Payable | E39: =Sheet1!D31 -> 3902568 | F39: =D129 -> 3902568 | G39: =E39-F39 -> 0
B40: NSDL | E40: =Sheet1!D33 -> 5900 | F40: =Sheet1!E33 -> 5900 | H40: =D40+F40-E40 -> 0
B41: Tripadam Logistics Private Limited | E41: =Sheet1!D37 -> 484577.08 | F41: =Sheet1!E37 -> 484577.08 | H41: =D41+F41-E41 -> 0
B42: Deepika | E42: =Sheet1!D40 -> 10000 | F42: =Sheet1!E40 -> 10000 | H42: =D42+F42-E42 -> 0
B43: Ms Subhashini - Reimbursement | D43: =Sheet1!C41 -> 236 | E43: =Sheet1!D41 -> 7329.46 | F43: =Sheet1!E41 -> 7093.46 | H43: =D43+F43-E43 -> 0 | I43: =G43-H38 -> 0
B44: Fixed Assets | G44: =C44+E44-F44 -> 0 | H44: =D44+F44-E44 -> 0
B45: Laptop A/c | C45: =Sheet1!C42-0.28 -> 2512 | E45: =C143 -> 2512.28 | F45: =Sheet1!E43 -> 2512.28 | G45: =C45+E45-F45 -> 2512
B46: Current Assets | G46: =C46+E46-F46 -> 0
B47: Fixed Deposits
B48: ICICI Fixed Deposit | C48: 0 | E48: =Sheet1!D46 -> 9800000 | F48: =Sheet1!E46 -> 9800000 | G48: =C48+E48-F48 -> 0 | H48: =D48+F48-E48 -> 0
B49: Loans & Advances (Asset) | C49: 0 | G49: =C49+E49-F49 -> 0 | H49: =D49+F49-E49 -> 0
B50: Advance Tax A/c | C50: =Sheet1!C48 -> 1000000 | E50: =Sheet1!D48 -> 1450000 | F50: =Sheet1!E48 -> 1000000 | G50: =C50+E50-F50 -> 1450000
B51: NSDL - Advance | C51: =Sheet1!C49 -> 492 | G51: =Sheet1!F49 -> 492
B52: Sundry Debtors | E52: =Sheet1!D50 -> 50228000 | F52: =Sheet1!E50 -> 50228000 | G52: =C52+E52-F52 -> 0
B53: Bank Accounts | G53: =C53+E53-F53 -> 0 | H53: =D53+F53-E53 -> 0
B54: ICICI Bank | C54: =Sheet1!C52-0.05 -> 7365298.9 | E54: =Sheet1!D52+C138 -> 62013067 | F54: =Sheet1!E52 -> 65309756 | G54: =C54+E54-F54 -> 4068610.2
B55: GST
B56: GST Receivable
B57: Input CGST Receivable A/c | C57: =Sheet1!C55 -> 0.01 | E57: =Sheet1!D55 -> 82437.73 | F57: =Sheet1!E55 -> 82437.74 | G57: =C57+E57-F57 -> 0
B58: Input IGST Receivable A/c | C58: =Sheet1!C56 -> 0 | E58: =Sheet1!D56 -> 5596802 | F58: =Sheet1!E56 -> 5596802 | G58: =C58+E58-F58 -> 0
B59: Input SGST Receivable A/c | C59: =Sheet1!C57 -> 0.01 | E59: =Sheet1!D57 -> 82436.73 | F59: =Sheet1!E57 -> 82436.74 | G59: =C59+E59-F59 -> 0
B60: Input CGST | C60: =Sheet1!C58 -> 53010.81 | E60: =Sheet1!D58 -> 82437.33 | F60: =Sheet1!E58 -> 67062 | G60: =C60+E60-F60 -> 68386.14
B61: Input IGST | C61: =Sheet1!C59 -> 872453.95 | E61: =Sheet1!D59 -> 5596801 | F61: =Sheet1!E59 -> 6468870 | G61: =C61+E61-F61 -> 385
B62: Input SGST | C62: =Sheet1!C60 -> 53010.81 | E62: =Sheet1!D60 -> 82437.33 | F62: =Sheet1!E60 -> 67062 | G62: =C62+E62-F62 -> 68386.14
B63: Receivables | G63: =C63+E63-F63 -> 0 | H63: =D63+F63-E63 -> 0
B64: Receivable From DB Schenker | G64: =C64+E64-F64 -> 0
B65: TDS Receivable | G65: =C65+E65-F65 -> 0 | H65: =D65+F65-E65 -> 0
B66: TDS Receivable - ICICI | C66: =Sheet1!C62 -> 46397 | E66: =Sheet1!D62 -> 16663 | F66: =Sheet1!E62 -> 46397 | G66: =C66+E66-F66 -> 16663
B67: TDS Receivable - SMPL | E67: =Sheet1!D63 -> 866000 | G67: =Sheet1!F63 -> 866000
B68: Deferred Tax Asset | C68: =Sheet1!C64 -> 249 | F68: =D109 -> 1289 | G68: 0 | H68: =F68-C68 -> 1040
B69: Sales Accounts
B70: Service Charges - Domestic | F70: =Sheet1!E66 -> 43300000 | H70: =D70+F70-E70 -> 43300000
B71: Direct Expenses | C71: 0 | G71: =C71+E71-F71 -> 0 | H71: =D71+F71-E71 -> 0
B72: Project Expense A/c | C72: 0 | G72: =C72+E72-F72 -> 0
B73: OBS Rental A/c | C73: 0 | E73: =Sheet1!D69 -> 36679066 | F73: =Sheet1!E69 -> 6103260 | G73: =C73+E73-F73 -> 30575806
B74: OBS Sea Shipment Expense | C74: 0 | E74: =Sheet1!D70+C113 -> 731160 | F74: =Sheet1!E70 -> 731160 | H74: =D74+F74-E74 -> 0
B75: Return Sea Shipment - Complete OBS | C75: 0 | E75: =Sheet1!D71 -> 463881 | G75: =C75+E75-F75 -> 463881
B76: Indirect Incomes | C76: 0 | G76: =C76+E76-F76 -> 0 | H76: =D76+F76-E76 -> 0
B77: Interest on ICICI FD A/c | C77: 0 | F77: =Sheet1!E73 -> 166630 | H77: =D77+F77-E77 -> 166630
B78: Interest Received on IT Refund | C78: 0 | F78: =Sheet1!E74 -> 57547 | H78: =D78+F78-E78 -> 57547
B79: Other Income | F79: =D114 -> 672666.74 | H79: =D79+F79-E79 -> 672666.74
B80: Indirect Expenses | C80: 0 | G80: =C80+E80-F80 -> 0 | H80: =D80+F80-E80 -> 0
B81: Bank Charges | C81: 0 | G81: =C81+E81-F81 -> 0 | H81: =D81+F81-E81 -> 0
B82: Bank Charges | C82: 0 | E82: =Sheet1!D78 -> 48387.17 | F82: =Sheet1!E78 -> 2000 | G82: =C82+E82-F82 -> 46387.17
B83: ECB2 Return Filing Charges | C83: 0 | E83: =Sheet1!D79+C118 -> 6000 | G83: =C83+E83-F83 -> 6000
B84: Compliance Cost | C84: 0 | G84: =C84+E84-F84 -> 0 | H84: =D84+F84-E84 -> 0
B85: Other Compliance Cost | C85: 0 | E85: =Sheet1!D82 -> 10000 | G85: =C85+E85-F85 -> 10000
B86: ROC Fees | C86: 0 | E86: =Sheet1!D83 -> 1030 | G86: =C86+E86-F86 -> 1030
B87: Rounding Off | C87: 0 | D87: =-0.33-0.89 -> -1.22 | E87: =Sheet1!D75 -> 7.37 | F87: =Sheet1!E75+D139 -> 0.23 | G87: =E87-F87-D87 -> 8.36
B88: MGT Filing Fee | E88: =Sheet1!D81 -> 824 | G88: =C88+E88-F88 -> 824
B89: Audit Fees | C89: 0 | E89: =Sheet1!D84 -> 125000 | G89: =C89+E89-F89 -> 125000
B90: Communication Expenses | C90: 0 | E90: =Sheet1!D85+C123 -> 9431.74 | G90: =C90+E90-F90 -> 9431.74
B91: Company Tax | C91: 0 | E91: =Sheet1!D86 -> 6000 | G91: =C91+E91-F91 -> 6000
B92: Condonation Charges | C92: 0 | E92: =Sheet1!D87 -> 1000 | G92: =C92+E92-F92 -> 1000
B93: Courier Charges | C93: 0 | G93: =C93+E93-F93 -> 0
B94: Depreciation | C94: 0 | E94: =Sheet1!D88 -> 2512.28 | F94: =D144 -> 2512.28 | G94: =C94+E94-F94 -> 0
B95: Loss On Forex | C95: 0 | E95: =Sheet1!D91 -> 3593664 | G95: =C95+E95-F95 -> 3593664
B96: Interest on TDS | C96: 0 | E96: =Sheet1!D89 -> 60 | G96: =C96+E96-F96 -> 60
B97: Local Conveyance | C97: 0 | E97: =Sheet1!D90 -> 194 | G97: =C97+E97-F97 -> 194
B98: Professional Fees | C98: 0 | E98: =Sheet1!D92 -> 206000 | G98: =C98+E98-F98 -> 206000
B99: Rent A/c | C99: 0 | E99: =Sheet1!D93 -> 141600 | G99: =C99+E99-F99 -> 141600
B100: Salary A/c | C100: 0 | E100: =Sheet1!D94 -> 320000 | G100: =C100+E100-F100 -> 320000
B101: Software Expenses | C101: 0 | E101: =Sheet1!D95 -> 4387 | G101: =C101+E101-F101 -> 4387
B102: Profit & Loss A/c | C102: =Sheet1!C96-0.89 -> 3782365.8 | E102: =C108+C133 -> 1256843 | G102: =C102+E102-F102 -> 5039208.8
C103: =SUM(C45:C102) -> 13175790 | D103: =SUM(D11:D102) -> 13175790 | E103: =SUM(E11:E102) -> 2.4750573e+08 | F103: =SUM(F11:F102) -> 2.4750573e+08 | G103: =SUM(G11:G102) -> 47091917 | H103: =SUM(H11:H102) -> 47091917
...

Sheet Balance Sheet
B2: K.U.M. India Private Limited
B3: ='Working TB'!B3 -> A5 second floor,Rajeswari Apartments, 45 Vellalar street, Kodambakkam,Chennai- 600024.
B4: ='Working TB'!B4 -> U29100TN2020PTC135386
E5: ='Master Sheet'!$C$5 -> Amount in ₹.
B6: Balance Sheet as on 31st March 2026
B7: Particulars | C7: Note no | D7: As at 31st Mar 2026 | E7: As at 31st Mar 2025
B9: I EQUITY AND LIABILITIES
B11: 1. Shareholder's funds
B12: (a) Share capital | C12: 3 | D12: ='Balance Sheet Notes'!C16 -> 1500000 | E12: ='Balance Sheet Notes'!D16 -> 1500000
B13: (b) Reserves and surplus | C13: 4 | D13: =('Balance Sheet Notes'!C121) -> 3646361.7 | E13: ='Balance Sheet Notes'!D121 -> -3782365.8
B14: (c) Money received against share warrants | D14: 0 | E14: 0
D15: =SUM(D12:D14) -> 5146361.7 | E15: =SUM(E12:E13) -> -2282365.8
B16: 2. Share application money pending allotment
B18: 3. Non-current liabilities
B19: (a) Long-term borrowings | C19: 5 | D19: =+'Balance Sheet Notes'!C127 -> 0 | E19: =+'Balance Sheet Notes'!D127 -> 11540575
B20: (b) Deferred tax liabilities (Net) | C20: 6 | D20: ='Balance Sheet Notes'!C140 -> 1040 | E20: ='Balance Sheet Notes'!D139 -> 0
B21: (c) Other Long-term liabilities | D21: 0 | E21: 0
B22: (d) Long-term provisions | D22: 0 | E22: 0
D23: =SUM(D19:D22) -> 1040 | E23: =SUM(E19:E22) -> 11540575
B24: 4. Current liabilities
B25: (a) Short-term borrowings | D25: 0 | E25: 0
B26: (b) Trade payables | D26: 0 | E26: 0
B27: (i) Total outstanding dues of micro enterprises and small enterprises | D27: 0 | E27: 0
B28: (ii) Total outstanding dues of creditors other than micro enterprises and small enterprises | D28: 0 | E28: 0
B29: (c) Other current liabilities | C29: 7 | D29: ='Balance Sheet Notes'!C148 -> 138478.82 | E29: ='Balance Sheet Notes'!D148 -> 135214.94
B30: (d) Short-term provisions | C30: 8 | D30: ='Balance Sheet Notes'!C153 -> 1255554 | E30: 0
D31: =SUM(D25:D30) -> 1394032.8 | E31: =SUM(E25:E30) -> 135214.94
B32: TOTAL | D32: =D31+D23+D15 -> 6541434.5 | E32: =(E31+E23+E15) -> 9393424.1
B34: II ASSETS
B36: 1. Non-current assets
B37: (a) Property, Plant and Equipment and Intangible assets | C37: 9 | D37: ='Balance Sheet Notes'!L159 -> 2512 | E37: ='Balance Sheet Notes'!L162 -> 2512
B38: (i) Property, Plant and Equipment | D38: 0 | E38: 0
B39: (ii) Intangible assets | D39: 0 | E39: 0
B40: (iii) Capital work-in-progress | E40: 0
B41: (iv) Intangible assets under development | D41: 0 | E41: 0
B42: (b) Non-current investments | D42: 0 | E42: 0
B43: (c) Deferred tax assets (net) | C43: 10 | D43: ='Balance Sheet Notes'!C169 -> 0 | E43: ='Balance Sheet Notes'!D170 -> 249
B44: (d) Long-term loans and advances | D44: 0 | E44: 0
B45: (e) Other non-current assets | D45: 0 | E45: 0
D46: =SUM(D37:D45) -> 2512 | E46: =SUM(E37:E45) -> 2761
B47: 2. Current assets
B48: (a) Current investments | D48: 0 | E48: 0
B49: (b) Inventories | D49: 0 | E49: 0
B50: (c) Trade receivables | D50: 0 | E50: 0
B51: (d) Cash and cash equivalents | C51: 11 | D51: ='Balance Sheet Notes'!C182 -> 4068610.2 | E51: ='Balance Sheet Notes'!D182 -> 7365298.9
B52: (e) Short-term loans & advances | C52: 12 | D52: =('Balance Sheet Notes'!C192) -> 2470312.3 | E52: ='Balance Sheet Notes'!D192 -> 2025364.2
B53: (f) Other current assets | D53: 0 | E53: 0
D54: =SUM(D48:D53) -> 6538922.5 | E54: =SUM(E48:E53) -> 9390663.1
B56: TOTAL | D56: =D54+D46 -> 6541434.5 | E56: =E54+E46 -> 9393424.1
B57: See accompanying notes forming part of the financial statements 1 & 2 | D57: =D56-D32 -> 0 | E57: =E32-E56 -> 0
B59: As per our report of even date atttached
B60: =IF('Master Sheet'!$C$23="", "", "For "&'Master Sheet'!$C$23) | C60: =IF('Master Sheet'!$C$7="", "", "For "&'Master Sheet'!$C$7)
B61: For RAMANUJAM and BOOVARAHAN | D61: For and on behalf of the Board of Directors
B62: Firm's Registration No.002945S
B63: Chartered Accountants
B66: N.R. BOOVARAHAN | D66: ONNO NICO HANNES BLISS | E66: SUTTI OMNATH DINESH
B67: Partner | D67: Director | E67: Director
B68: Membership No. 027801 | D68: DIN:10105885 | E68: DIN: 07747125
B70: Place: Chennai
B71: Date:
B72: =IF('Master Sheet'!$C$29="", "", "Date: " & TEXT('Master Sheet'!$C$29, "DD-MM-YYYY")) | C72: =IF('Master Sheet'!$C$30="", "","Date: " & TEXT('Master Sheet'!$C$30, "DD-MM-YYYY"))

Sheet Profit and Loss
B2: =+'Balance Sheet'!B2 -> K.U.M. India Private Limited
B3: ='Balance Sheet'!B3 -> A5 second floor,Rajeswari Apartments, 45 Vellalar street, Kodambakkam,Chennai- 600024.
B4: ='Balance Sheet'!B4 -> U29100TN2020PTC135386
E5: ='Master Sheet'!$C$5 -> Amount in ₹.
B6: Profit & Loss for the year ended 31st March 2026
B7: Particulars | C7: Note no | D7: For the Year Ended 31st Mar 2026 | E7: For the Year Ended 31st Mar 2025
B8: INCOME
B9: I. Revenue from operations | C9: 13 | D9: =+'Profit and Loss Notes'!C12 -> 43300000 | E9: ='Profit and Loss Notes'!D9+'Profit and Loss Notes'!D10+'Profit and Loss Notes'!D11 -> 1578059
B10: II. Other Income | C10: 14 | D10: ='Profit and Loss Notes'!C20 -> 896843.74 | E10: ='Profit and Loss Notes'!D20 -> 492263.33
B11: III. TOTAL INCOME (I+II) | D11: ='Profit and Loss'!D9+'Profit and Loss'!D10 -> 44196844 | E11: ='Profit and Loss'!E9+'Profit and Loss'!E10 -> 2070322.3
B12: IV. EXPENSES
B13: (a) Cost of materials consumed | D13: 0 | E13: 0
B14: (b) Purchases of Stock-in-Trade | D14: 0 | E14: 0
B15: (c)Changes in inventories of finished goods, work-in-progress and Stock-in-Trade | D15: 0 | E15: 0
B16: (d) Employee benefit expenses | C16: 15 | D16: ='Profit and Loss Notes'!C28 -> 320000 | E16: ='Profit and Loss Notes'!D28 -> 540000
B17: (e) Finance costs | C17: 16 | D17: ='Profit and Loss Notes'!C34 -> 0 | E17: ='Profit and Loss Notes'!D34 -> 263350
B18: (f) Depreciation and amortisation | C18: 17 | D18: ='Profit and Loss Notes'!C41 -> 0 | E18: ='Profit and Loss Notes'!D41 -> 15914
B19: (g) Other expenses | C19: 18 | D19: =+'Profit and Loss Notes'!C69 -> 35191273 | E19: ='Profit and Loss Notes'!D69 -> 1268688.1
B21: TOTAL EXPENSES | D21: ='Profit and Loss'!D13+'Profit and Loss'!D14+'Profit and Loss'!D15+'Profit and Loss'!D16+'Profit and Loss'!D17+'Profit and Loss'!D18+'Profit and Loss'!D19 -> 35511273 | E21: ='Profit and Loss'!E13+'Profit and Loss'!E14+'Profit and Loss'!E15+'Profit and Loss'!E16+'Profit and Loss'!E17+'Profit and Loss'!E18+'Profit and Loss'!E19 -> 2087952.1
B22: V. Profit/(Loss) before exceptional and extraordinary items and tax (III - IV) | D22: ='Profit and Loss'!D11-'Profit and Loss'!D21 -> 8685570.5 | E22: ='Profit and Loss'!E11-'Profit and Loss'!E21 -> -17629.8
B23: VI. Exceptional items
B24: Loss on Sale of Tangible assets
B25: VII. Profit/(Loss) before extraordinary items and tax (V-VI) | D25: ='Profit and Loss'!D22-'Profit and Loss'!D24 -> 8685570.5 | E25: ='Profit and Loss'!E22-'Profit and Loss'!E24 -> -17629.8
B26: VIII. Extraordinary Items
B27: IX. Profit/(Loss) before tax (VII - VIII) | D27: ='Profit and Loss'!D25-'Profit and Loss'!D26 -> 8685570.5 | E27: ='Profit and Loss'!E25-'Profit and Loss'!E26 -> -17629.8
B28: X. Tax Expenses | D28: =+D29+D30 -> 1256843 | E28: =(+E29+E30) -> -1856
B29: (a) Current tax | C29: 19 | D29: ='Working TB'!C133 -> 1255554
B30: (b) Deferred tax | C30: 20 | D30: ='Profit and Loss Notes'!C81 -> 1289 | E30: =-'Profit and Loss Notes'!D81 -> -1856
B31: XI. Profit/(Loss) for the period from continuing operations | D31: ='Profit and Loss'!D27-'Profit and Loss'!D28 -> 7428727.5 | E31: ='Profit and Loss'!E27-'Profit and Loss'!E28 -> -15773.8
B32: XII. Profit/(Loss) for the period from discontinuing operations | D32: 0 | E32: 0
B33: XIII. Tax expense of discontinuing operations | D33: 0 | E33: 0
B34: XIV. Profit/(Loss) for the period from discontinuing operations (after tax) | D34: ='Profit and Loss'!D32-'Profit and Loss'!D33 -> 0 | E34: ='Profit and Loss'!E32-'Profit and Loss'!E33 -> 0
B35: XV. Profit/(Loss) for the period | D35: ='Profit and Loss'!D31+'Profit and Loss'!D34 -> 7428727.5 | E35: ='Profit and Loss'!E31+'Profit and Loss'!E34 -> -15773.8
B36: Earnings per equity share | C36: 21
B37: (a) Basic | D37: =+'Profit and Loss Notes'!C90 -> 49.52485 | E37: =+'Profit and Loss Notes'!D90 -> -0.10515867
B38: (b) Diluted | D38: =+'Profit and Loss Notes'!C94 -> 49.52485 | E38: =+'Profit and Loss Notes'!D94 -> -0.10515867
B39: Number of Shares Used in Computing Earnings Per Share
B40: (a) Basic | D40: 150000 | E40: 150000
B41: (b) Diluted | D41: 150000 | E41: 150000
B42: See accompanying notes forming part of the financial statements 1 & 2
B44: As per our report of even date atttached
B45: =IF('Master Sheet'!$C$23="", "", "For "&'Master Sheet'!$C$23) | C45: =IF('Master Sheet'!$C$7="", "", "For "&'Master Sheet'!$C$7)
B46: For RAMANUJAM and BOOVARAHAN | D46: For and on behalf of the Board of Directors
B47: Firm's Registration No.002945S
B48: Chartered Accountants
B51: N.R. BOOVARAHAN | D51: ONNO NICO HANNES BLISS | E51: SUTTI OMNATH DINESH
B52: Partner | D52: Director | E52: Director
B53: Membership No. 027801 | D53: DIN:10105885 | E53: DIN: 07747125
B54: Place: Chennai
B55: Date:
B56: =IF('Master Sheet'!$C$29="", "", "Date: " & TEXT('Master Sheet'!$C$29, "DD-MM-YYYY")) | C56: =IF('Master Sheet'!$C$30="", "","Date: " & TEXT('Master Sheet'!$C$30, "DD-MM-YYYY"))

Sheet CFS
B2: =+'Balance Sheet'!B2 -> K.U.M. India Private Limited | C2: =IF('Master Sheet'!$C$34="", "", "CIN: "&'Master Sheet'!$C$34)
B3: ='Profit and Loss'!B3 -> A5 second floor,Rajeswari Apartments, 45 Vellalar street, Kodambakkam,Chennai- 600024.
B4: ='Profit and Loss'!B4 -> U29100TN2020PTC135386
B6: Cash Flow Statements For The Year Ended 31st March 2026 | E6: ='Master Sheet'!$C$5 -> Amount in ₹.
B7: Particulars | D7: For the year ended 31st March 2026 | E7: For the year ended 31st March 2025
B9: Cash flow from Operating Activities
B10: Net profit as per profit and loss a/c | D10: ='Profit and Loss'!D27 -> 8685570.5 | E10: =-17630 -> -17630
B11: Add: Depreciation and amortisation | D11: ='Profit and Loss'!D18 -> 0 | E11: ='Profit and Loss'!E18 -> 15914
B12: Add: Unrealised Forex Loss | D12: ='Working TB'!H107 -> 0 | E12: =263350 -> 263350
D13: =SUM(D10:D12) -> 8685570.5 | E13: =SUM(E10:E12) -> 261634
B14: Less: Dividend/Interest income received | D14: =-'Working TB'!H77-'Working TB'!H78 -> -224177 | E14: =-463966 -> -463966
B15: Operating profit before working capital changes | D15: =D14+D13 -> 8461393.5 | E15: =SUM(E13:E14) -> -202332
B16: Changes in working capital
B17: Increase/(Decrease) in Trade Payables | D17: ='Balance Sheet'!D26-'Balance Sheet'!E26 -> 0 | E17: =-19085247 -> -19085247
B18: Increase/(Decrease) in Long term Provisions | D18: ='Balance Sheet'!D22-'Balance Sheet'!E22 -> 0
B19: Increase/(Decrease) in Other Current Liabilities | D19: ='Balance Sheet'!D29-'Balance Sheet'!E29 -> 3263.88 | E19: =-3420170.06 -> -3420170.1
B20: (Increase)/Decrease in Inventories | D20: ='Balance Sheet'!E49-'Balance Sheet'!D49 -> 0
B21: (Increase)/Decrease in Other Current Assets | D21: ='Balance Sheet'!E53-'Balance Sheet'!D53 -> 0 | E21: =607 -> 607
B22: (Increase)/Decrease in Trade Receivables | D22: ='Balance Sheet'!E50-'Balance Sheet'!D50 -> 0 | E22: =28248000 -> 28248000
B23: (Increase)/Decrease in Short Term Loans And Advance | D23: ='Balance Sheet'!$E$52-'Balance Sheet'!$D$52 -> -444948.03 | E23: =-316595.25 -> -316595.25
B24: Net change in working capital | D24: =SUM(D17:D23) -> -441684.15 | E24: =SUM(E17:E23) -> 5426594.7
B25: Cash generated from operations | D25: =D15+D24 -> 8019709.4 | E25: =E15+E24 -> 5224262.7
B26: Direct taxes paid
B27: Net cash from / (used in) Operating Activities (A) | D27: =D25-D26 -> 8019709.4 | E27: =SUM(E25:E26) -> 5224262.7
B29: Cash flow from Investing Activities
B30: Purchase / (Sale) of fixed assets
B31: (i) Tangible Assets | D31: 0 | E31: 0
B32: (ii) Intangible Assets | D32: =-('Balance Sheet'!D39-'Balance Sheet'!E39) -> 0 | E32: 0
B33: (iii) Capital work in progress | D33: =-('Balance Sheet'!D40-'Balance Sheet'!E40) -> 0 | E33: 0
B34: (iv) Intangible assets under development | D34: =-('Balance Sheet'!D41-'Balance Sheet'!E41) -> 0 | E34: 0
B35: Proceeds from sale of fixed assets
B36: Purchase / (Sale) of Non Current Investments | D36: ='Balance Sheet'!E42-'Balance Sheet'!D42 -> 0 | E36: 0
B37: Purchase / (Sale) of Current Investments | D37: ='Balance Sheet'!E48-'Balance Sheet'!D48 -> 0 | E37: 0
B38: Dividend/Interest income received | D38: ='Working TB'!H77+'Working TB'!H78 -> 224177 | E38: =463966 -> 463966
B40: Net cash from / (used in) Investing Activities (B) | D40: =SUM(D31:D38) -> 224177 | E40: =SUM(E31:E38) -> 463966
B42: Cash flow from Financing Activities
B43: Share capital raised | D43: ='Balance Sheet'!D12-'Balance Sheet'!E12 -> 0
B44: Money received from share warrants | D44: ='Balance Sheet'!D14-'Balance Sheet'!E14 -> 0
B45: Changes in Reserves and surplus
B46: (Increase)/Decrease in Short term loans and advances
B47: Increase/(Decrease) in Long Term Loans and Advances | D47: =-('Balance Sheet'!D44-'Balance Sheet'!E44) -> 0
B48: Increase/(Decrease) in Long Term Borrowings | D48: ='Balance Sheet'!D19-'Balance Sheet'!E19 -> -11540575
B49: Increase/(Decrease) in Short Term Borrowings | D49: ='Balance Sheet'!D25-'Balance Sheet'!E25 -> 0
B50: Increase/(Decrease) in Long Term Liabilities | D50: =0 -> 0 | E50: =263350 -> 263350
B51: Dividend paid including distribution tax
B52: Finance Cost | D52: =0 -> 0 | E52: =-E50 -> -263350
B53: Net cash from / (used in) Financing Activities ( C ) | D53: =SUM(D43:D52) -> -11540575 | E53: =SUM(E43:E52) -> 0
B55: Net Increase/(Decrease) in cash and cash equivalents during the year (A+B+C) | D55: =(D27+D40+D53) -> -3296688.6 | E55: =+E53+E40+E27 -> 5688228.7
B57: Cash and cash equivalents at the beginning of the year | D57: =+E59 -> 7365298.9 | E57: =1677070 -> 1677070
B59: Cash and cash equivalents at the end of the year | D59: =D55+D57 -> 4068610.3 | E59: =SUM(E55:E57)+0.2 -> 7365298.9
B61: Reconciliation of Cash and cash equivalents with the Balance Sheet:
B62: Cash and Bank Balances as per Balance Sheet - Refer Note No. 11 | D62: ='Balance Sheet Notes'!C182 -> 4068610.2 | E62: ='Balance Sheet'!E51 -> 7365298.9
B63: Less: Bank Balances not considered as Cash and Cash Equivalents as defined in AS 3 Cash Flow Statements | D63: 0
D64: =D62-D63 -> 4068610.2 | E64: =E62-E63 -> 7365298.9
B66: Cash and cash equivalents at the end of the year Comprises:
B67: (a) Cash on Hand | D67: 0 | E67: 0
B68: (b) Balances with banks
B69: (i) In Current Accounts | D69: ='Balance Sheet Notes'!C177 -> 4068610.2 | E69: =ROUNDDOWN('Balance Sheet Notes'!D177,0) -> 7365298
D71: =D69+D67 -> 4068610.2 | E71: =ROUNDDOWN((E69+E67),0) -> 7365298
B73: See accompanying notes forming part of the financial statements | D73: =+D55+D57-D59 -> 0 | E73: -
B74: As per our report of even date atttached
B75: =IF('Master Sheet'!$C$23="", "", "For "&'Master Sheet'!$C$23) | C75: =IF('Master Sheet'!$C$7="", "", "For "&'Master Sheet'!$C$7)
B76: For RAMANUJAM and BOOVARAHAN | D76: For and on behalf of the Board of Directors
B77: Firm's Registration No.002945S
B78: Chartered Accountants
B81: N.R. BOOVARAHAN | C81: ONNO NICO HANNES BLISS | E81: SUTTI OMNATH DINESH
B82: Partner | C82: Director | E82: Director
B83: Membership No. 027801 | C83: DIN:10105885 | E83: DIN: 07747125
B85: Place: Chennai
B86: Date:
B87: =IF('Master Sheet'!$C$29="", "", "Date: " & TEXT('Master Sheet'!$C$29, "DD-MM-YYYY")) | C87: =IF('Master Sheet'!$C$30="", "","Date: " & TEXT('Master Sheet'!$C$30, "DD-MM-YYYY"))

Sheet Accounting Polices
C2: ='Balance Sheet'!B2 -> K.U.M. India Private Limited
C3: =CFS!B3 -> A5 second floor,Rajeswari Apartments, 45 Vellalar street, Kodambakkam,Chennai- 600024.
C4: =CFS!B4 -> U29100TN2020PTC135386
C6: Notes to Financial statements for the year ended 31st March 2026
C8: Note No. 1 Corporate Information
C10: K.U.M India Private Limited ('K.U.M'/'the Company') incorporated on 21 May 2020 under the Companies Act, 2013.
C11: The Company is a subsidiary of 6Labs Europe GmbH, Germany ('Holding Company'). The primary objective of the Company is to provide custom solutions in marine research and development, and innovative turnkey marine solutions.
C13: Note No. 2 Significant Accounting Policies
C15: 2.1 Accounting Conversion
C16: The financial statements have been prepared in accordance with the historical cost convention on an accrual basis and comply with the applicable Accounting Standards specified under section 133 of the Companies Act, 2013 read with Rule 7 of the Companies (Accounts) Rules, 2014.
C17: These financial statements have been prepared as required under relevant provision of the Companies Act, 2013 and the presentation is based on Schedule III of the Companies Act, 2013. All assets and liabilities are classified into current and non-current generally based on the criteria of realization / settlement within twelve months’ period from the balance sheet date
C19: 2.2 Use of Estimates
C20: The preparation of financial statements in conformity with Indian GAAP requires the Management to make estimates and assumptions considered in the reported amounts of assets and liabilities (including contingent liabilities) as of the date of the financial statements and the reported income and expenses during the reporting period like provision for employee benefits, provisioning for receivables, useful lives of fixed assets, provisioning for taxation etc. Management believes that the estimates used in the preparation of the financial statements are prudent and reasonable. Future results could differ from these estimates and the differences between the actual results and the estimates are recognised in the periods in which the results are known / materialise.
C22: 2.3 Cash Flow Statement
C23: Cash flows are reported using the indirect method, whereby profit / (loss) before extraordinary items and tax is adjusted for the effects of transactions of non-cash nature and any deferrals or accruals of past or future cash receipts or payments. The cash flows from operating, investing and financing activities of the Company are segregated based on the available information.
... C55: Assets and Liabilities are classified as Current and Non-Current based on the Operating Cycle which has been estimated to be 12 months. All assets and liabilities which are expected to be realised and settled, within a period of 12 months from the date of Balance Sheet have been classified as Current and other assets and liabilities are classified as Non-current.

Sheet Balance Sheet Notes
B1: K.U.M. India Private Limited
B2: A5 second floor,Rajeswari Apartments, 45 Vellalar street, Kodambakkam,Chennai- 600024.
B3: U29100TN2020PTC135386
B4: Notes forming part of the Financial Statements for the Year ended 31 March 2026
D5: ='Master Sheet'!$C$5 -> Amount in ₹.
B6: =IF(ISBLANK('Balance Sheet'!C12), "", "Note number: "& 'Balance Sheet'!C12) -> Note number: 3
B7: Share Capital
B8: Particulars | C8: As at 31st Mar 2026 | D8: As at 31st Mar 2025
B10: (A) Authorized
B12: 1,50,000 Equity Shares Of Rs. 10/- Each | C12: =Sheet1!C9 -> 1500000 | D12: 1500000
B13: (B) Issued , Subscribed And Fully Paid Up
B14: 1,50,000 Equity Shares Of Rs. 10/- Each | C14: =Sheet1!F9 -> 1500000 | D14: 1500000
B16: TOTAL | C16: ='Balance Sheet Notes'!C11+'Balance Sheet Notes'!C14 -> 1500000 | D16: ='Balance Sheet Notes'!D11+'Balance Sheet Notes'!D14 -> 1500000
D19: ='Master Sheet'!$C$5 -> Amount in ₹.
B20: Reconciliation
B21: Particulars | C21: As at 31st Mar 2026 | D21: As at 31st Mar 2025
B23: 1,50,000 Equity Shares of Rs. 10/- Each | C23: =+C24+C25-C26 -> 1500000 | D23: =+D24+D25-D26 -> 1500000
B24: Opening Balance | C24: =150000*10 -> 1500000 | D24: =150000*10 -> 1500000
B25: Add: Fresh Issue | C25: 0 | D25: 0
B26: Add/(Less) Other Changes | C26: 0 | D26: 0
B28: Rights, Preferences and Restrictions
B30: Equity Shares
B32: The Company has one class of equity shares having a par value of Rs.10/- per share. The equity shares are attached with voting rights. Each shareholder is eligible for one vote per share held. In the event of liquidation, the equity shareholders are eligible to receive the remaining assets of the Company after distribution of all preferential amount, in proportion to their shareholding.
B35: Shares held by shareholders holding more than 5%
B36: Particulars | C36: Typoe of Shares | D36: As at 31 March 2026 | F36: As at 31 March 2025
D37: Number of Shares held | E37: Percentage of Holding | F37: Number of Shares held | G37: Percentage of Holding
B39: 6Labs Europe GmbH (Holding Company) | C39: Equity | D39: 112500 | E39: 0.75 | F39: 112500 | G39: 0.75
B40: Sutti Omnath Dinesh Babu | C40: Equity | D40: 37500 | E40: 0.25 | F40: 37500 | G40: 0.25
B42: Total | D42: =SUM(D39:D40) -> 150000 | E42: =SUM(E39:E40) -> 1 | F42: =SUM(F39:F40) -> 150000 | G42: =SUM(G39:G40) -> 1
B44: Shares held by promoters at the end of the year 31st March 2026
B46: Promoter Name | E46: Number of Shares held | F46: Percentage of Holding | G46: Percentage Change during the year
B48: 6Labs Europe GmbH (Holding Company) | E48: 112500 | F48: 0.75 | G48: 0
B49: Sutti Omnath Dinesh Babu | E49: 37500 | F49: 0.25 | G49: 0
B52: Shares held by promoters at the end of the year 31st March 2025
B54: Promoter Name | E54: Number of Shares held | F54: Percentage of Holding | G54: Percentage Change during the year
B56: 6Labs Europe GmbH (Holding Company) | E56: 112500 | F56: 0.75 | G56: 0
B57: Sutti Omnath Dinesh Babu | E57: 37500 | F57: 0.25 | G57: 0
D60: ='Master Sheet'!$C$5 -> Amount in ₹.
B61: =IF(ISBLANK('Balance Sheet'!C13), "", "Note number: "& 'Balance Sheet'!C13) -> Note number: 4
B62: Reserves and Surplus
B63: Particulars | C63: As at 31st Mar 2026 | D63: As at 31st Mar 2025
B65: Capital Redemption Reserve;
B66: Opening balance | C66: 0 | D66: 0
B67: (+) Additions for the period | C67: 0 | D67: 0
B68: ( - ) utilisation for the period | C68: 0 | D68: 0
B69: Closing Balance(CRR) | C69: =SUM(C66:C68) -> 0 | D69: 0
B71: Security Premium
B72: Opening balance | C72: 0 | D72: 0
B73: (+) Additions for the period | C73: 0 | D73: 0
B74: ( - ) utilisation for the period | C74: 0 | D74: 0
B75: Closing Balance(SP) | C75: =SUM(C72:C74) -> 0 | D75: 0
B77: Revaluation Reserve
B78: Opening balance | C78: 0 | D78: 0
B79: (+) Additions for the period | C79: 0 | D79: 0
B80: ( - ) utilisation for the period | C80: 0 | D80: 0
B81: Closing Balance(RR) | C81: =SUM(C78:C80) -> 0 | D81: 0
B83: Debenture Redemption Reserve;
B84: Opening balance | C84: 0 | D84: 0
B85: (+) Additions for the period | C85: 0 | D85: 0
B86: ( - ) utilisation for the period | C86: 0 | D86: 0
B87: Closing Balance(DRR) | C87: =SUM(C84:C86) -> 0 | D87: 0
B89: Share Options Outstanding Account; and
B90: Opening balance | C90: 0 | D90: 0
B91: (+) Additions for the period | C91: 0 | D91: 0
B92: ( - ) utilisation for the period | C92: 0 | D92: 0
B93: Closing Balance(SOA) | C93: =SUM(C90:C92) -> 0 | D93: 0
B95: General Reserve
B96: Opening balance | C96: 0 | D96: 0
B97: (+) Additions for the period | C97: 0 | D97: 0
B98: ( - ) utilisation for the period | C98: 0 | D98: 0
B99: Closing Balance(GR) | C99: =SUM(C96:C98) -> 0 | D99: 0
B101: Statutory Reserve
B102: Opening balance | C102: 0 | D102: 0
B103: (+) Additions for the period | C103: 0 | D103: 0
B104: ( - ) utilisation for the period | C104: 0 | D104: 0
B105: Closing Balance(SR) | C105: =SUM(C102:C104) -> 0 | D105: 0
B107: others- (specify the nature and purpose of each reserve and the amount in respect thereof);
B108: Opening balance | C108: 0 | D108: 0
B109: (+) Additions for the period | C109: 0 | D109: 0
B110: ( - ) utilisation for the period | C110: 0 | D110: 0
B111: Closing Balance(OTH) | C111: =SUM(C108:C110) -> 0 | D111: 0
B113: Surplus
B114: Surplus i.e., balance in Statement of Profit and Loss
B115: Opening balance | C115: =(D121) -> -3782365.8 | D115: =-3766592 -> -3766592
B116: (+) Additions for the period
B117: ( - ) utilisation for the period
B118: (+) Net Profit/(Net Loss) For the current year | C118: =+'Profit and Loss'!D31 -> 7428727.5 | D118: =-15773.8 -> -15773.8
B119: Closing Balance(Surplus) | C119: ='Balance Sheet Notes'!C115+'Balance Sheet Notes'!C116+'Balance Sheet Notes'!C117+'Balance Sheet Notes'!C118 -> 3646361.7 | D119: ='Balance Sheet Notes'!D115+'Balance Sheet Notes'!D116+'Balance Sheet Notes'!D117+'Balance Sheet Notes'!D118 -> -3782365.8
B121: Total | C121: =('Balance Sheet Notes'!C69+'Balance Sheet Notes'!C75+'Balance Sheet Notes'!C81+'Balance Sheet Notes'!C87+'Balance Sheet Notes'!C93+'Balance Sheet Notes'!C99+'Balance Sheet Notes'!C105+'Balance Sheet Notes'!C111+'Balance Sheet Notes'!C119) -> 3646361.7 | D121: ='Balance Sheet Notes'!D69+'Balance Sheet Notes'!D75+'Balance Sheet Notes'!D81+'Balance Sheet Notes'!D87+'Balance Sheet Notes'!D93+'Balance Sheet Notes'!D99+'Balance Sheet Notes'!D105+'Balance Sheet Notes'!D111+'Balance Sheet Notes'!D119 -> -3782365.8
B123: Note number: 5 | D123: ='Master Sheet'!$C$5 -> Amount in ₹.
B124: Long-term Borrowings
B125: Particulars | C125: As at 31st Mar 2026 | D125: As at 31st Mar 2025
B126: External Commercial Borrowings | C126: ='Annexure BS'!C19 -> 0 | D126: ='Annexure BS'!D19 -> 11540575
B127: Total | C127: =SUM(C126:C126) -> 0 | D127: =SUM(D126:D126) -> 11540575
B129: Note No:5(a)
B130: Particulars | C130: Tranche-1 | D130: Tranche-2
B131: Date of availment - term loan | C131: 17 July 2020 | D131: 18 December 2020
B132: Principal (in Euros) | C132: 62500 | D132: 62500
B133: Rate of Interest | C133: 0 | D133: 0
B134: Date for repayment - term loan | C134: 17 October 2025 | D134: 30 March 2026
...

Sheet Profit and Loss Notes
B1: K.U.M. India Private Limited
B2: A5 second floor,Rajeswari Apartments, 45 Vellalar street, Kodambakkam,Chennai- 600024.
B3: U29100TN2020PTC135386
B4: ='Balance Sheet Notes'!B4 -> Notes forming part of the Financial Statements for the Year ended 31 March 2026
B6: =IF(ISBLANK('Profit and Loss'!C9), "", "Note number: "& 'Profit and Loss'!C9) -> Note number: 13 | D6: ='Master Sheet'!$C$5 -> Amount in ₹.
B7: Revenue from Operations
B8: Particulars | C8: For the Year Ended 31st Mar 2026 | D8: For the Year Ended 31st Mar 2025
B9: Sale of products | C9: 0 | D9: 0
B10: Revenue From Services | C10: =+'Annexure PnL'!C9 -> 43300000 | D10: =+'Annexure PnL'!D9 -> 1578059
B11: Other operating revenues | C11: 0 | D11: 0
B12: Total | C12: ='Profit and Loss Notes'!C9+'Profit and Loss Notes'!C10+'Profit and Loss Notes'!C11 -> 43300000 | D12: ='Profit and Loss Notes'!D9+'Profit and Loss Notes'!D10+'Profit and Loss Notes'!D11 -> 1578059
B14: =IF(ISBLANK('Profit and Loss'!C10), "", "Note number: "& 'Profit and Loss'!C10) -> Note number: 14 | D14: ='Master Sheet'!$C$5 -> Amount in ₹.
B15: Other Income
B16: Particulars | C16: For the Year Ended 31st Mar 2026 | D16: For the Year Ended 31st Mar 2025
B17: Forex gains | C17: ='Annexure PnL'!C15 -> 0 | D17: ='Annexure PnL'!D15 -> 4747.33
B18: Other non-operating income | C18: ='Annexure PnL'!C22 -> 730213.74 | D18: ='Annexure PnL'!D22 -> 23550
B19: Interest on FD | C19: ='Annexure PnL'!C26 -> 166630 | D19: ='Annexure PnL'!D26 -> 463966
B20: Total | C20: =SUM(C17:C19) -> 896843.74 | D20: =SUM(D17:D19) -> 492263.33
B22: =IF(ISBLANK('Profit and Loss'!C16), "", "Note number: "& 'Profit and Loss'!C16) -> Note number: 15 | D22: ='Master Sheet'!$C$5 -> Amount in ₹.
B23: Employee Benefits expenses
B24: Particulars | C24: For the Year Ended 31st Mar 2026 | D24: For the Year Ended 31st Mar 2025
B25: Salary and Wages | C25: ='Annexure PnL'!C38 -> 320000 | D25: =+'Annexure PnL'!D39 -> 480000
B26: Bonus & Incentivies | C26: =+'Annexure PnL'!C35 -> 0 | D26: ='Annexure PnL'!D35 -> 60000
B28: Total | C28: =SUM(C25:C27) -> 320000 | D28: =SUM(D25:D27) -> 540000
B30: =IF(ISBLANK('Profit and Loss'!C17),"","Note number:"&'Profit and Loss'!C17) -> Note number:16 | D30: ='Master Sheet'!$C$5 -> Amount in ₹.
B31: Finance Cost
B32: Particulars | C32: For the Year Ended 31st Mar 2026 | D32: For the Year Ended 31st Mar 2025
B33: Unrealised Loss On Forex | C33: =0 -> 0 | D33: ='Annexure PnL'!D45 -> 263350
B34: Total | C34: ='Profit and Loss Notes'!C33 -> 0 | D34: ='Profit and Loss Notes'!D33 -> 263350
B36: =IF(ISBLANK('Profit and Loss'!C18), "", "Note number: "& 'Profit and Loss'!C18) -> Note number: 17 | D36: ='Master Sheet'!$C$5 -> Amount in ₹.
B37: Depreciation and Amortisation expenses
B38: Particulars | C38: For the Year Ended 31st Mar 2026 | D38: For the Year Ended 31st Mar 2025
B39: Depreciation | C39: ='Annexure PnL'!C51 -> 0 | D39: =+'Annexure PnL'!D51 -> 15914
B41: Total | C41: ='Profit and Loss Notes'!C39 -> 0 | D41: ='Profit and Loss Notes'!D39 -> 15914
B43: =IF(ISBLANK('Profit and Loss'!C19), "", "Note number: "& 'Profit and Loss'!C19) -> Note number: 18 | D43: ='Master Sheet'!$C$5 -> Amount in ₹.
B44: Other Expenses
B45: Particulars | C45: For the Year Ended 31st Mar 2026 | D45: For the Year Ended 31st Mar 2025
B46: Bank Charges | C46: ='Annexure PnL'!C56 -> 46387.17 | D46: ='Annexure PnL'!D56 -> 35615.74
B47: ECB2 Return Filing Charges | C47: ='Annexure PnL'!C57 -> 6000 | D47: ='Annexure PnL'!D57 -> 6000
B48: OBS Air Shipment Expense | C48: ='Annexure PnL'!C63 -> 0 | D48: ='Annexure PnL'!D63 -> 27508
B49: OBS Sea Shipment Expense | C49: ='Annexure PnL'!C64 -> 0 | D49: ='Annexure PnL'!D64 -> -5455
B50: Return Sea Shipment | C50: ='Annexure PnL'!C66 -> 463881 | D50: ='Annexure PnL'!D66 -> 42768
B51: Clearance Charges | C51: ='Annexure PnL'!C67 -> 0 | D51: ='Annexure PnL'!D67 -> 4500
B52: Communication | C52: ='Annexure PnL'!C72 -> 9431.74 | D52: ='Annexure PnL'!D72 -> 13101.98
B53: Compliance Cost | C53: =+'Annexure PnL'!C76 -> 0 | D53: ='Annexure PnL'!D76 -> 500
B54: Other Compliance Cost | C54: ='Annexure PnL'!C78 -> 10000 | D54: ='Annexure PnL'!D78 -> 252397.33
B55: Professional Fees | C55: ='Annexure PnL'!C79 -> 206000 | D55: ='Annexure PnL'!D79 -> 151000
B56: ROC Fees | C56: ='Annexure PnL'!C80 -> 1854 | D56: ='Annexure PnL'!D80 -> 2884
B57: Auditors Remuneration | C57: ='Annexure PnL'!C118 -> 125000 | D57: ='Annexure PnL'!D118 -> 103000
B58: Postal and courier charges | C58: ='Annexure PnL'!C114 -> 0 | D58: ='Annexure PnL'!D87 -> 280
B59: Rates and taxes | C59: ='Annexure PnL'!C91 -> 6000 | D59: ='Annexure PnL'!D91 -> 8000
B60: OBS Rental A/c | C60: ='Annexure PnL'!C96 -> 30575806 | D60: ='Annexure PnL'!D96 -> 0
B61: Rounding Off | C61: ='Annexure PnL'!C68 -> 8.36 | D61: ='Annexure PnL'!D68 -> -0.55
B62: Condonation Charges | C62: ='Annexure PnL'!C81 -> 1000 | D62: 0
B63: Interest on TDS | C63: ='Annexure PnL'!C82 -> 60 | D63: 0
B64: Rent A/c | C64: ='Annexure PnL'!C95 -> 141600 | D64: ='Annexure PnL'!D95 -> 141600
B65: Software Expenses | C65: ='Annexure PnL'!C100 -> 4387 | D65: ='Annexure PnL'!D100 -> 0
B66: Travelling & Conveyance | C66: ='Annexure PnL'!C104 -> 194 | D66: ='Annexure PnL'!D104 -> 163264
B67: Printing & Stationery | C67: ='Annexure PnL'!C114 -> 0 | D67: ='Annexure PnL'!D114 -> 875
B68: Forex Loss | C68: ='Annexure PnL'!C109 -> 3593664 | D68: ='Annexure PnL'!D109 -> 320849.63
B69: Total | C69: =SUM(C46:C68) -> 35191273 | D69: =SUM(D46:D68) -> 1268688.1
B71: Note number: 19 | D71: ='Master Sheet'!$C$5 -> Amount in ₹.
B72: Current Tax
B73: Particulars | C73: For the Year Ended 31st Mar 2026 | D73: For the Year Ended 31st Mar 2025
B74: Current tax | C74: ='Profit and Loss'!D29 -> 1255554 | D74: 0
B75: Total | C75: =+C74 -> 1255554 | D75: =+D74 -> 0
B77: Note number: 20 | D77: ='Master Sheet'!$C$5 -> Amount in ₹.
B78: Deferred Tax
B79: Particulars | C79: For the Year Ended 31st Mar 2026 | D79: For the Year Ended 31st Mar 2025
B80: Deferred Tax | C80: =-'Deferred Tax'!G23 -> 1289 | D80: 1856
B81: Total | C81: =+C80 -> 1289 | D81: =+D80 -> 1856
B83: Note No. 21 Earning Per Share
B84: Particulars | C84: Before Extraordinary Item | E84: After Extraordinary Item
C85: As at 31 March 2026 | D85: As at 31 March 2025 | E85: As at 31 March 2026 | F85: As at 31 March 2025
B87: Basic
B88: Profit after tax (A) | C88: =+'Profit and Loss'!D31 -> 7428727.5 | D88: =+'Profit and Loss'!E31 -> -15773.8 | E88: =+'Profit and Loss'!D31 -> 7428727.5 | F88: =+'Profit and Loss'!E31 -> -15773.8
B89: Weighted average number of shares outstanding (B) | C89: 150000 | D89: 150000 | E89: 150000 | F89: 150000
B90: Basic EPS (A / B) | C90: =C88/C89 -> 49.52485 | D90: =D88/D89 -> -0.10515867 | E90: =E88/E89 -> 49.52485 | F90: =F88/F89 -> -0.10515867
B91: Diluted
B92: Profit after tax (A) | C92: =+C88 -> 7428727.5 | D92: =+D88 -> -15773.8 | E92: =+E88 -> 7428727.5 | F92: =+F88 -> -15773.8
B93: Weighted average number of shares outstanding (B) | C93: 150000 | D93: 150000 | E93: 150000 | F93: 150000
B94: Diluted EPS (A / B) | C94: =C92/C93 -> 49.52485 | D94: =D92/D93 -> -0.10515867 | E94: =E92/E93 -> 49.52485 | F94: =F92/F93 -> -0.10515867
B96: Face value per share | C96: 10 | D96: 10 | E96: 10 | F96: 10
B99: Note No. 22 Earnings In Foreign Currency
B100: Earnings In Foreign Currency
B101: Particulars | C101: For the Year Ended 31st Mar 2026 | D101: For the Year Ended 31st Mar 2025
B102: Sale Of Services | C102: =0 -> 0 | D102: =1578059 -> 1578059
B104: Total | C104: =+C102 -> 0 | D104: =+D102 -> 1578059
B106: Note No. 23 Expenditure in Foreign Currency
B107: Expenditure in Foreign Currency
B108: Particulars | C108: For the Year Ended 31st Mar 2026 | D108: For the Year Ended 31st Mar 2025
B109: Loss on Forex Repayment of Borrowings & Lease rentals | C109: ='Annexure PnL'!C44 -> 3593664 | D109: 0
B111: Total | C111: =+C109 -> 3593664 | D111: =+D109 -> 0

Sheet Other Notes
B1: K.U.M. India Private Limited
B2: A5 second floor,Rajeswari Apartments, 45 Vellalar street, Kodambakkam,Chennai- 600024.
B3: U29100TN2020PTC135386
B4: ='Profit and Loss Notes'!B4 -> Notes forming part of the Financial Statements for the Year ended 31 March 2026
B6: Note No. 24 Related Party Disclosures as per AS-18
B8: Note No. 24 (a) Names of Related Parties and Nature of Relationship
B10: S. No. | C10: Name of the Related Party | F10: Nature of Relationship
B11: 1 | C11: 6Labs Europe GmbH | F11: Holding Company
B12: 2 | C12: Sutti Omnath Dinesh Babu | F12: Director/KMP
B13: 3 | C13: Vanitha S.D | F13: Relative of the Director
B14: 4 | C14: Samhitha Marine Private Limited | F14: Common Director
B15: 5 | C15: K.U.M. Unwelt- und Meerestechnik Kiel GmbH | F15: Common Director
B17: Note: Related party relationships are as identified by the Management.
B19: Note No. 24 (b) Transactions with Related Parties
B21: Name of the Related Party | D21: Nature of Relationship | E21: Nature of the Transaction | F21: For the year ended 31 March 2026 | G21: For the year ended 31 March 2025
B22: 6Labs Europe GmbH | D22: Holding Company | E22: Repayment of External Commercial Borrowings | F22: ='Working TB'!E13 -> 11540575 | G22: 0
B23: K.U.M. Unwelt- und Meerestechnik Kiel GmbH | D23: Common Director | E23: Repayment to Sundry Creditors | F23: ='Working TB'!E24+'Working TB'!E25 -> 31083954 | G23: 18999343
B24: Vanitha S.D | D24: Relative of the Director | E24: Rent | F24: ='Profit and Loss Notes'!C64 -> 141600 | G24: 141600
B25: Samhitha Marine Private Limited | D25: Common Director | E25: Revenue From Operations | F25: ='Working TB'!H70 -> 43300000 | G25: 0
B26: K.U.M. Unwelt- und Meerestechnik Kiel GmbH | D26: Common Director | E26: Revenue From Operations | F26: 0 | G26: 1578059
B27: TOTAL | F27: =SUM(F23:F26) -> 74525554 | G27: =SUM(G23:G26) -> 20719002
B28: Note No. 24 (c) Outstanding Balance with the Related Parties
B30: Name of the Related Party | D30: Nature of Relationship | E30: Nature of the Transaction | F30: As at 31 March 2026 | G30: As at 31 March 2025
B31: 6Labs Europe GmbH | D31: Holding Company | E31: Long Term Borrowings | F31: ='Working TB'!H13 -> 0 | G31: 11540575
B32: TOTAL | F32: =SUM(F31:F31) -> 0 | G32: =SUM(G31:G31) -> 11540575
B33: Note No. 25 Disclosures required under Section 22 of the Micro, Small and Medium Enterprises
B34: Development Act, 2006
B35: Based on and to the extent of information received by the Company from the suppliers during the year
B36: regarding their status under the Micro Small and Medium Enterprises Development Act, 2006 (MSMED
B37: Act), the relevant particulars for the period ended March 31, 2026 is furnished below:
B39: Particulars | G39: 46112
B40: Principal amount remaining unpaid to any supplier as at the end of the accounting year. | G40: 0
B41: Interest due thereon remaining unpaid to any supplier as at the end of the accounting year. | G41: 0
B42: The amount of interest paid along with the amounts of the payment made to the supplier beyond the appointed day | G42: 0
B43: The amount of interest due and payable for the year. | G43: 0
B44: The amount of interest accrued and remaining unpaid at the end of the accounting year. | G44: 0
B45: The amount of further interest due and payable even in the succeeding year, until such date when the interest dues as above are actually paid. | G45: 0
B46: Total | G46: 0
B48: Note No. 26 Derivative instruments and unhedged foreign currency exposure
B49: a) The Company did not have any derivative contracts during the current year and previous period.
B50: b) Particulars of unhedged foreign currency exposure as at the reporting date
D51: As at 31 March 2026 | F51: As at 31 March 2025
B52: Particulars | D52: In EUR | E52: in Rupee equivalent | F52: In EUR | G52: in Rupee equivalent
B53: a) External commercial borrowings | D53: 0 | E53: ='Working TB'!H13 -> 0 | F53: 125000 | G53: 11277225
B54: Note No. 27 Other Statutory Information
B56: 27.1 | C56: The Company do not have any Benami property, where any proceeding has been initiated or pending against the Company for holding any Benami property.
B57: 27.2 | C57: The Company do not have any transactions with companies struck off.
B58: 27.3 | C58: The Company do not have any charges or satisfaction which is yet to be registered with ROC beyond the statutory period.
B59: 27.4 | C59: The Company have not traded or invested in Crypto currency or Virtual Currency during the financial year.
B60: 27.5 | C60: The company has no transactions which are not recorded in the books of accounts, that has been surrendered or disclosed as income during the year under the Income Tax Act, 1961. (such as Search or Survey under the Income Tax Act, 1961)
B61: 27.6 | C61: The Company has complied with the number of layers prescribed under clause (87) of section 2 of the Act read with the Companies (Restriction on number of Layers) Rules, 2017.
B62: 27.7 | C62: The Company have not advanced or loaned or invested funds to any other person(s) or entity(ies), including foreign entities (Intermediaries) with the understanding that the Intermediary shall:
C63: (a) directly or indirectly lend or invest in other persons or entities identified in any manner whatsoever by or on behalf of the Company (Ultimate Beneficiaries); or
C64: (b) provide any guarantee, security or the like to or on behalf of the Ultimate Beneficiaries.
B65: 27.8 | C65: The Company have not received any fund from any person(s) or entity(ies), including foreign entities (Funding Party) with the understanding (whether recorded in writing or otherwise) that the Company shall:
C66: (a) directly or indirectly lend or invest in other persons or entities identified in any manner whatsoever by or on behalf of the Funding Party (Ultimate Beneficiaries); or
C67: (b) provide any guarantee, security or the like on behalf of the Ultimate Beneficiaries.
B68: 27.9 | C68: The company is not declared as a wilful defaulter by any bank or financial Institution or other lender.
B70: Note No. 28 Ratio Analysis
B72: S.No | C72: Particulars | D72: Measurement | E72: Numerator | F72: Denominator | G72: For the year ended 31 March 2026 | H72: For the year ended 31 March 2025 | I72: % Change | J72: Explanation for Significant Change
B73: 1 | C73: Current Ratio | D73: In Times | E73: Current Asset | F73: Current Liabilities | G73: ='Balance Sheet'!D54/'Balance Sheet'!D31 -> 4.6906518 | H73: 69.449893 | I73: =(G73-H73)/H73 -> -0.93245991 | J73: Due to decrease in Bank Balance.
B74: =B73+1 -> 2 | C74: Debt - Equity Ratio | D74: In Times | E74: Debt = Long Term Borrowings + Short Term Borrowings | F74: Total Equity | G74: =('Balance Sheet'!D19+'Balance Sheet'!D25)/'Balance Sheet'!D15 -> 0 | H74: -5.056409 | I74: =(G74-H74)/H74 -> -1 | J74: Due to the Repayment of long term Borrowings
B75: =B74+1 -> 3 | C75: Debt Service Coverage Ratio | D75: In Times | E75: Earnings for Debt Service = Net Profit after Taxes + Non Cash Operating Expenses + Finance Cost | F75: Debt Service = Interest & Lease Payments + Principal Payments | G75: 0 | H75: 0 | I75: 0
B76: =B75+1 -> 4 | C76: Return on Equity Ratio | D76: In Percentage | E76: Profit after Tax | F76: Average Shareholder's Fund | G76: ='Profit and Loss'!D35/(SUM('Balance Sheet'!D15,'Balance Sheet'!E15)/2) -> 5.1876663 | H76: 0.006935127 | I76: =(G76-H76)/H76 -> 747.02758 | J76: Due to Increase in profit for the current year
B77: =B76+1 -> 5 | C77: Inventory Turnover Ration | D77: In Times | E77: Revenue from Operations | F77: Average Inventory | G77: 0 | H77: 0 | I77: 0
B78: =B77+1 -> 6 | C78: Trade Receivables Turnover Ratio | D78: In Times | E78: Net Credit Sales = Gross Credit Sales - Sales Return (Excluding Other Income) | F78: Average Trade Receivable | G78: 0 | H78: 0.06 | I78: =(G78-H78)/H78 -> -1 | J78: Due to the Nil trade receivables in current year.
B79: =B78+1 -> 7 | C79: Trade Payable Turnover Ratio | D79: In Times | E79: Purchases and Other Services | F79: Average Trade Payable | G79: 0 | H79: 0 | I79: 0 | J79: Due to the Nil trade payables in current year.
B80: =B79+1 -> 8 | C80: Net Capital Turnover Ratio | D80: In Times | E80: Net Sales = Total Sales - Sales Return (Including Other Income) | F80: Working Capital = Current Assets - Current Liabilities | G80: ='Profit and Loss'!D11/('Balance Sheet'!D54-'Balance Sheet'!D31) -> 8.5904356 | H80: 0.17 | I80: =(G80-H80)/H80 -> 49.531974 | J80: Due to increase in sales
B81: =B80+1 -> 9 | C81: Net Profit Ratio | D81: In Percentage | E81: Profit After Tax | F81: Net Sales = Total Sales - Sales Return (Including Other Income) | G81: ='Profit and Loss'!D35/'Profit and Loss'!D9 -> 0.17156415 | H81: -0.01 | I81: =(G81-H81)/H81 -> -18.156415 | J81: The difference is due to increase in profit
B82: =B81+1 -> 10 | C82: Return on Capital Employed | D82: In Percentage | E82: Earnings Before Interest and Tax | F82: Capital Employed = Net Worth + Total Debt | G82: 1.69 | H82: 0.03 | I82: =(G82-H82)/H82 -> 55.333333 | J82: Due to Increase in profit during the year
B83: =B82+1 -> 11 | C83: Return on Investment | D83: In Percentage | E83: Profit After Tax | F83: Total Assets | G83: ='Profit and Loss'!D35/'Balance Sheet'!D56 -> 1.135642 | H83: -0.17 | I83: =(G83-H83)/H83 -> -7.6802468 | J83: Due to the increase in profit
B85: Note No. 29 Previous Year’s Figures
B86: The amounts for the previous year have been regrouped wherever necessary.
B87: In terms of our report attached.
B88: For RAMANUJAM and BOOVARAHAN | E88: For and on behalf of the Board of Directors
B89: Firm's Registration No.002945S
B90: Chartered Accountants
B93: N.R. BOOVARAHAN | E93: ONNO NICO HANNES BLISS | F93: SUTTI OMNATH DINESH
B94: Partner | E94: Director | F94: Director
B95: Membership No. 027801 | E95: DIN:10105885 | F95: DIN: 07747125
B97: Place: Chennai
B98: Date:

Sheet Annexure BS
B1: K.U.M. India Private Limited
B2: A5 second floor,Rajeswari Apartments, 45 Vellalar street, Kodambakkam,Chennai- 600024.
B3: U29100TN2020PTC135386
B5: 1. Share Capital
B6: Equity Shares Of Rs. 10/- Each | C6: As at 31st Mar 2026 | D6: As at 31st Mar 2025
B7: Authorised Share Capital | C7: 1500000 | D7: 1500000
B8: Total | C8: =SUM(C7:C7) -> 1500000 | D8: =SUM(D7:D7) -> 1500000
B11: 2. Deferred Tax Liabilities (Net)
B12: Deferred tax liabilities | C12: As at 31st Mar 2026 | D12: As at 31st Mar 2025
B13: Deferred Tax Liabilities | C13: =-'Deferred Tax'!G25 -> 1040 | D13: =0 -> 0
B14: Total | C14: =SUM(C13:C13) -> 1040 | D14: =SUM(D13:D13) -> 0
B17: 3. Short-term Borrowings
B18: (ii) from other parties(ST) | C18: As at 31st Mar 2026 | D18: As at 31st Mar 2025
B19: External Commercial Borrowings | C19: ='Working TB'!H13 -> 0 | D19: ='Working TB'!D13 -> 11540575
B20: Total | C20: =SUM(C19:C19) -> 0 | D20: =SUM(D19:D19) -> 11540575
B23: 4. Trade Payables
B24: (b) Total Outstanding dues of creditors other than Micro Enterprises and Small Enterprises | C24: As at 31st Mar 2026 | D24: As at 31st Mar 2025
B25: K.U.M. Germany Creditors | C25: ='Working TB'!G39 -> 0 | D25: =0 -> 0
B26: Hapag Lloyd | C26: 0
B27: Total | C27: =C25+C26 -> 0 | D27: =SUM(D25:D26) -> 0
B30: 5. Other Current Liabilities
B31: Income received in advance | C31: As at 31st Mar 2026 | D31: As at 31st Mar 2025
B32: SMPL - Advance | C32: 0 | D32: 0
B33: Total | C33: =SUM(C32:C32) -> 0 | D33: =SUM(D32:D32) -> 0
B35: Other current Liabilities | C35: As at 31st Mar 2026 | D35: As at 31st Mar 2025
B36: Airtel | C36: ='Working TB'!H29 -> 1178.82 | D36: 0
B37: CIPET | C37: 0 | D37: 0
B38: DB Schenker A/c | C38: 0 | D38: 0
B39: DHL Express | C39: 0 | D39: 0
B40: Darjen Tours & Travels | C40: 0 | D40: 0
B41: Deepika | C41: 0 | D41: 0
B42: Delhivery Ltd | C42: 0 | D42: 0
B43: Dinesh A/c | C43: 0 | D43: 0
B44: EMudhra | C44: 0 | D44: 0
B45: GeM Portal | C45: 0 | D45: 0
B46: Greater Chennai Corporation | C46: 0 | D46: 0
B47: Hapag Lloyd A/c | C47: 0 | D47: 0
B48: ICEGATE | C48: 0 | D48: 0
... B53: Matrics Consultancy | C53: 0 | D53: 0
B54: Ms.Subhashini | C54: ='Working TB'!H33 -> 0 | D54: =39999.18 -> 39999.18
B55: Praanha A./c | C55: 0 | D55: 0
B56: Ms Subhashini - Reimbursement | C56: ='Working TB'!H43 -> 0 | D56: =236 -> 236
B57: Professional Fees Payable A/c | C57: ='Working TB'!H34 -> 6000 | D57: ='Working TB'!D34 -> 6000
B58: Province Power System | C58: 0 | D58: 0
B59: RBCA | C59: 0 | D59: 0
B60: RBJV Associates | C60: 0 | D60: 0
B61: SMPL A/c | C61: 0 | D61: 0
B62: Vanitha A/c | C62: 0 | D62: 0
B63: ECB2 Filing Charges Payable | C63: 0
B64: Total | C64: =SUM(C36:C63) -> 7178.82 | D64: =SUM(D36:D63) -> 46235.18
B66: Other payables | C66: As at 31st Mar 2026 | D66: As at 31st Mar 2025
B67: Audit Fee Payable A/c | C67: ='Working TB'!H27 -> 112500 | D67: ='Working TB'!D27 -> 74250
B68: ECB2 Return Filing Charges Payable | C68: ='Working TB'!H30 -> 1000 | D68: ='Working TB'!D30 -> 1000
B69: Total | C69: =SUM(C67:C68) -> 113500 | D69: =SUM(D67:D68) -> 75250
B71: Statutory liabilities | C71: As at 31st Mar 2026 | D71: As at 31st Mar 2025
B72: GST Payable | C72: 0 | D72: 0
B73: GST RCM Payable | C73: ='Working TB'!H16 -> 1800 | D73: ='Working TB'!D16-0.74 -> 1799.26
B74: IGST @ 18% | C74: 0 | D74: 0
B75: Output CGST | C75: 0 | D75: 0
B76: Output CGST Payable A/c | D76: 0
B77: Output SGST | C77: 0 | D77: 0
B78: Output SGST Payable A/c | D78: 0
B79: Professional Tax | C79: ='Working TB'!H19 -> 0 | D79: 0
B80: TDS-Contracts | C80: ='Working TB'!H21 -> 0 | D80: ='Working TB'!D21 -> 230.5
B81: TDS-Payable Salary | D81: 0
B82: TDS-Professional Services | C82: ='Working TB'!H22 -> 16000 | D82: ='Working TB'!D22 -> 11700
B83: Total | C83: =SUM(C73:C82) -> 17800 | D83: =SUM(D72:D82) -> 13729.76
B86: 6. Property, Plant and Equipment
B87: Property, Plant and Equipment | C87: As at 31st Mar 2026 | D87: As at 31st Mar 2025
B88: Depreciation Reserve - Panasonic Phone | C88: 0 | D88: 0
B89: Laptop A/c | C89: ='Working TB'!G45 -> 2512 | D89: ='Working TB'!C45 -> 2512
B90: Panasonic Phone | C90: 0 | D90: 0
B91: Total | C91: =SUM(C88:C90) -> 2512 | D91: =SUM(D88:D90) -> 2512
B93: 7. Short Term Provisions | C93: As at 31st Mar 2026 | D93: As at 31st Mar 2025
B94: Provision For Tax FY 25-26 | C94: ='Working TB'!H20 -> 1255554 | D94: =0 -> 0
B96: Total | C96: =SUM(C94:C95) -> 1255554 | D96: =SUM(D94:D95) -> 0
B98: 8. Trade Receivables
B99: Trade Receivables | C99: As at 31st Mar 2026 | D99: As at 31st Mar 2025
B100: K.U.M Germany | C100: 0
B101: MRV Systems | C101: 0 | D101: 0
B102: SMPL Debtors | C102: ='Working TB'!G52 -> 0
B103: Total | C103: =SUM(C100:C102) -> 0 | D103: =SUM(D100:D102) -> 0
B106: 9. Cash and Cash Equivalents
B107: Cash on hand | C107: As at 31st Mar 2026 | D107: As at 31st Mar 2025
B108: Cash | C108: 0 | D108: 0
B109: Total | C109: =SUM(C108:C108) -> 0 | D109: =SUM(D108:D108) -> 0
B111: In current account | C111: As at 31st Mar 2026 | D111: As at 31st Mar 2025
B112: ICICI Bank | C112: ='Working TB'!G54 -> 4068610.2 | D112: ='Working TB'!C54 -> 7365298.9
B113: Total | C113: =SUM(C112:C112) -> 4068610.2 | D113: =SUM(D112:D112) -> 7365298.9
B116: 10. Short-term Loans & Advances
B117: Balance with Government Authorities-IT Refund | C117: As at 31st Mar 2026 | D117: As at 31st Mar 2025
B118: Duty IGST Receivable | C118: 0 | D118: =0 -> 0
B119: Input CGST | C119: ='Working TB'!G60 -> 68386.14 | D119: =53010.81 -> 53010.81
B120: Input CGST Receivable A/c | D120: =0.01 -> 0.01
B121: Input IGST | C121: ='Working TB'!G61 -> 385 | D121: =872453.61 -> 872453.61
B122: TDS RECEIVABLE | C122: ='Working TB'!G66+'Working TB'!G67 -> 882663 | D122: =46397 -> 46397
B123: Output CGST | C123: 0
B124: Output SGST | C124: 0
B125: Input IGST Receivable A/c | C125: 0
B126: Input SGST | C126: ='Working TB'!G62 -> 68386.14 | D126: =53010.81 -> 53010.81 | F126: =C119+C121+C122+C126+C128+C129 -> 2470312.3
...

Sheet Annexure PnL
B1: K.U.M. India Private Limited
B2: A5 second floor,Rajeswari Apartments, 45 Vellalar street, Kodambakkam,Chennai- 600024.
B3: U29100TN2020PTC135386
B5: 1. Revenue from Operations
B6: Sale of services | C6: As at 31st Mar 2026 | D6: As at 31st Mar 2025
B7: Business Support Services | C7: ='Working TB'!H70 -> 43300000 | D7: 1578059
B8: Service Charges - Domestic
B9: Total | C9: =SUM(C7:C8) -> 43300000 | D9: =SUM(D7:D8) -> 1578059
B12: 2. Other Income
B13: Forex gains | C13: As at 31st Mar 2026 | D13: As at 31st Mar 2025
B14: Gain on Forex | C14: =0 -> 0 | D14: =4747.33 -> 4747.33
B15: Total | C15: =SUM(C14:C14) -> 0 | D15: =SUM(D14:D14) -> 4747.33
B17: Other non-operating income | C17: As at 31st Mar 2026 | D17: As at 31st Mar 2025
B18: Discount Received | C18: =0 -> 0 | D18: =6870 -> 6870
B19: Interest Received on IT Refund | C19: ='Working TB'!H78 -> 57547 | D19: =16680 -> 16680
B20: Duty Drawback Refund | C20: ='Working TB'!H79 -> 672666.74
B22: Total | C22: =SUM(C18:C21) -> 730213.74 | D22: =SUM(D18:D21) -> 23550
B24: Interest on FD | C24: As at 31st Mar 2026 | D24: As at 31st Mar 2025
B25: Interest on ICICI FD | C25: ='Working TB'!H77 -> 166630 | D25: =463966 -> 463966
B26: Total | C26: =C25 -> 166630 | D26: =D25 -> 463966
B31: 3. Employee Benefits
B32: Employee benefits and compensation | C32: As at 31st Mar 2026 | D32: As at 31st Mar 2025
B33: Festival Bonus | C33: =0 -> 0 | D33: =20000 -> 20000
B34: Performance Incentive A/c | C34: =0 -> 0 | D34: =40000 -> 40000
B35: Total | C35: =SUM(C33:C34) -> 0 | D35: =SUM(D33:D34) -> 60000
B37: Salary and Wages | C37: As at 31st Mar 2026 | D37: As at 31st Mar 2025
B38: Salary A/c | C38: ='Working TB'!G100 -> 320000 | D38: =480000 -> 480000
B39: Total | C39: =SUM(C38:C38) -> 320000 | D39: =SUM(D38:D38) -> 480000
B42: 4. Finance Costs
B43: Forex loss | C43: As at 31st Mar 2026 | D43: As at 31st Mar 2025
B44: Realised Loss On Forex | C44: ='Working TB'!G95 -> 3593664 | D44: =263350 -> 263350
B45: Total | C45: =SUM(C44:C44) -> 3593664 | D45: =SUM(D44:D44) -> 263350
B48: 5. Depreciation and Amortisation
B49: Depreciation | C49: As at 31st Mar 2026 | D49: As at 31st Mar 2025
B50: Depreciation | C50: ='Working TB'!G94 -> 0 | D50: =15914 -> 15914
B51: Total | C51: =SUM(C50:C50) -> 0 | D51: =SUM(D50:D50) -> 15914
B54: 6. Other Expenses
B55: Bank charges | C55: As at 31st Mar 2026 | D55: As at 31st Mar 2025
B56: Bank Charges | C56: ='Working TB'!G82 -> 46387.17 | D56: =35615.74 -> 35615.74
B57: ECB2 Return Filing Charges | C57: ='Working TB'!G83 -> 6000 | D57: =6000 -> 6000
B58: Interest on TDS Paid | C58: 0 | D58: =0 -> 0
B60: Total | C60: =SUM(C56:C58) -> 52387.17 | D60: =SUM(D56:D58) -> 41615.74
B62: Business support services | C62: As at 31st Mar 2026 | D62: As at 31st Mar 2025
B63: OBS Air Shipment Expense | C63: =0 -> 0 | D63: =27508 -> 27508
B64: OBS Sea Shipment Expense | C64: 0 | D64: =-5455 -> -5455
B65: Project Expenses A/c | C65: 0 | D65: =0 -> 0
B66: Return Sea Shipment | C66: ='Working TB'!G75 -> 463881 | D66: =42768 -> 42768
B67: Clearance Charges | C67: =0 -> 0 | D67: =4500 -> 4500
B68: Rounding Off | C68: ='Working TB'!G87 -> 8.36 | D68: -0.55
B69: Total | C69: =SUM(C63:C68) -> 463889.36 | D69: =SUM(D63:D68) -> 69320.45
B71: Communication | C71: As at 31st Mar 2026 | D71: As at 31st Mar 2025
B72: Communication Expenses | C72: ='Working TB'!G90 -> 9431.74 | D72: =13101.98 -> 13101.98
B73: Total | C73: =SUM(C72:C72) -> 9431.74 | D73: =SUM(D72:D72) -> 13101.98
B75: Legal and professional | C75: As at 31st Mar 2026 | D75: As at 31st Mar 2025
B76: Compliance Cost | C76: =0 -> 0 | D76: =500 -> 500
B77: DSC Charges | C77: 0 | D77: =0 -> 0
B78: Other Complience Cost | C78: ='Working TB'!G85 -> 10000 | D78: =252397.33 -> 252397.33
B79: Professional Fees | C79: ='Working TB'!G98 -> 206000 | D79: =151000 -> 151000
B80: ROC Fees | C80: ='Working TB'!G86+'Working TB'!G88 -> 1854 | D80: =2884 -> 2884
B81: Condonation Charges | C81: ='Working TB'!G92 -> 1000
B82: Interest on TDS | C82: ='Working TB'!G96 -> 60
B83: Tender Fee & Registration Charges | C83: 0 | D83: =0 -> 0
B84: Total | C84: =SUM(C76:C83) -> 218914 | D84: =SUM(D76:D83) -> 406781.33
B86: Postal and courier charges | C86: As at 31st Mar 2026 | D86: As at 31st Mar 2025
B87: Courier Charges | C87: ='Working TB'!G93 -> 0 | D87: =280 -> 280
B88: Total | C88: =SUM(C87:C87) -> 0 | D88: =SUM(D87:D87) -> 280
B90: Rates and taxes | C90: As at 31st Mar 2026 | D90: As at 31st Mar 2025
B91: Company Tax | C91: ='Working TB'!G91 -> 6000 | D91: =8000 -> 8000
B92: Total | C92: =SUM(C91:C91) -> 6000 | D92: =SUM(D91:D91) -> 8000
B94: Rent | C94: As at 31st Mar 2026 | D94: As at 31st Mar 2025
B95: Rent A/c | C95: ='Working TB'!G99 -> 141600 | D95: =141600 -> 141600
B96: OBS rental A/C | C96: ='Working TB'!G73 -> 30575806 | D96: =0 -> 0
B97: Total | C97: =SUM(C95:C96) -> 30717406 | D97: =SUM(D95:D96) -> 141600
B99: Security | C99: As at 31st Mar 2026 | D99: As at 31st Mar 2025
B100: Software Expenses | C100: ='Working TB'!G101 -> 4387 | D100: =0 -> 0
B101: Total | C101: =C100 -> 4387 | D101: =D100 -> 0
B103: Travelling & Conveyance | C103: As at 31st Mar 2026 | D103: As at 31st Mar 2025
B104: Local Conveyance | C104: ='Working TB'!G97 -> 194 | D104: =163264 -> 163264
B105: Darjen Tours and Travel | C105: 0 | D105: =0 -> 0
B106: Total | C106: =C104 -> 194 | D106: =SUM(D104:D105) -> 163264
B108: Loss On Forex | C108: As at 31st Mar 2026 | D108: As at 31st Mar 2025
B109: Loss On Forex | C109: ='Working TB'!G95 -> 3593664 | D109: =320849.63 -> 320849.63
B110: Total | C110: =C109 -> 3593664 | D110: =D109 -> 320849.63
B113: Printing & Stationery | C113: As at 31st Mar 2026 | D113: As at 31st Mar 2025
B114: Printing & Stationery | C114: =0 -> 0 | D114: =875 -> 875
B115: Total | C115: =C114 -> 0 | D115: =D114 -> 875
B116: 7. Auditor Remuneration
B117: for audit | C117: As at 31st Mar 2026 | D117: As at 31st Mar 2025
B118: Audit Fees | C118: ='Working TB'!G89 -> 125000 | D118: =103000 -> 103000
B119: Total | C119: =SUM(C118:C118) -> 125000 | D119: =SUM(D118:D118) -> 103000

Sheet TB PY
A1: Ledger Name | B1: Ledger Parent Name | C1: Ledger Grandparent Name | D1: Primary Group Name | E1: Ledger Ultimate Parent Name | F1: Ledger Type | G1: Opening balance | H1: Debit Transaction | I1: Credit Transaction | J1: Net Transaction | K1: Closing Balance | L1: Balance sheet Primary Classification Display Name | M1: Balance sheet Classification Display Name | N1: PNL Primary Classification Display Name | O1: PNL Classification Display Name | P1: Tally Company Name | Q1: Balance sheet User Defined Classification (Update the customer defined value here) | R1: PnL User Defined Classfication | S1: guid

Sheet Deferred Tax
B3: K.U.M. India Private Limited - 01.04.2024-31.3.2025
B4: ='Annexure PnL'!B2 -> A5 second floor,Rajeswari Apartments, 45 Vellalar street, Kodambakkam,Chennai- 600024.
B5: ='Annexure PnL'!B3 -> U29100TN2020PTC135386
B8: Deferred Tax Caculation
B10: Opening Deffered Tax Asset on account of depreciation and Gratuity | G10: 249
B12: Depreciation | K12: Tax u/s 115BAC | M12: 0.22
B13: Depreciation as per Books | C13: =+'Profit and Loss Notes'!C41 -> 0 | K13: Surcharge @ 10% | M13: =M12*10% -> 0.022
B14: Depreciation as per Income Tax Act | C14: =+'IT Dep'!M12 -> 5123.52
D15: =C13-C14 -> -5123.52 | E15: =M18 -> 0.25168 | M15: =SUM(M12:M14) -> 0.242
F16: =ROUND(D15*E15,0) -> -1289 | K16: HEC @ 4% | M16: =M15*4% -> 0.00968
B18: Performance Incentivies | M18: =SUM(M15:M17) -> 0.25168
B19: Performance Incentivies as per Books | C19: 0
B20: Performance Incentivies as per Income Tax Act | C20: 0
D21: =C19-C20 -> 0 | E21: =M18 -> 0.25168
F22: =ROUND(D21*E21,0) -> 0
B23: Deferred Tax Expense for the year 2024-25 | G23: =SUM(F16:F22) -> -1289
B25: Closing Deffered Tax Liability on account of depreciation and Gratuity | G25: =+G10+G23 -> -1040

Sheet IT Dep
B1: K.U.M India Private Limited
B2: A5 Second Floor Rajeshwari Apartments, 45 Vellalar Street, Kodambakkam,
B3: Assessment Year 2025-26
B4: Depreciation as per Income Tax Act, 1961
B6: S. No. | C6: Name of the Asset | D6: Rate | E6: WDV As at 31 March 2025 | F6: Additions | H6: Deletions | J6: Total | K6: Depreciation | M6: Total Depreciation | N6: WDV as on 31 March 2026
F7: More than 180 Days | G7: Less than 180 Days | H7: Less than 180 Days | I7: More than 180 Days | K7: More than 180 Days | L7: Less than 180 Days
B9: 1 | C9: BLOCK I
C10: Computers- Laptops | D10: 0.4 | E10: 12808.8 | F10: 0 | G10: 0 | H10: 0 | I10: 0 | J10: =+E10+F10+G10-H10-I10 -> 12808.8 | K10: =J10*40% -> 5123.52 | L10: 0 | M10: =+K10+L10 -> 5123.52 | N10: =J10-M10 -> 7685.28
E12: =SUM(E10:E11) -> 12808.8 | F12: =SUM(F10:F11) -> 0 | G12: =SUM(G10:G11) -> 0 | H12: =SUM(H10:H11) -> 0 | I12: =SUM(I10:I11) -> 0 | J12: =SUM(J10:J11) -> 12808.8 | K12: =SUM(K10:K11) -> 5123.52 | L12: =SUM(L10:L11) -> 0 | ... N12: =SUM(N10:N11) -> 7685.28

Sheet IT Computation
B3: Assessment Year | F3: 2026-2027
B5: Opted for Taxation u/s Section 115BAA | F5: YES
B7: I | C7: Income from Business or Profession (Chapter IV D)
D9: Profit as per Profit and Loss Account | F9: =+'Profit and Loss'!D27 -> 8685570.5
D11: Add: Depreciation debited in P&L | E11: =+'Annexure PnL'!C51 -> 0
D12: Add: Donation- Disallowed u/s 37 | E12: 0
D13: Add: Provision for Gratuity -Disallowed u/s 43B | E13: 0
F15: =SUM(E11:E13) -> 0
F17: =SUM(F9:F15) -> 8685570.5
D19: Less: Incomes Considered seperately
D20: (a) Interest Received | E20: ='Annexure PnL'!C25+'Annexure PnL'!C19 -> 224177
D21: (b) Rent Received | E21: 0
F23: =-SUM(E20:E22) -> -224177
D25: Less: Provision for Gratuity (Paid) | E25: 0
D26: Less: Profit on Sale of Fixed Asset | E26: 0
F28: =-SUM(E25:E27) -> 0
D30: Less: Depreciation as per Income Tax Act, 1961 | E30: =IF(F17<0,(0),(+'IT Dep'!K12)) -> 5123.52
F32: =E30 -> 5123.52
F33: =+F17-F32+F23 -> 8456270
D35: Less:Brought Forward Unabsorbed Depreciation
D36: AY 2023-24 | E36: 23720
D37: AY 2025-26 | E37: 8539
F38: =E36+E37 -> 32259
D39: Less:Brought Forward Loss adjsuted
D41: AY 2022-23 | E41: 2333770
D42: AY 2023-24 | E42: 1324008
D43: AY 2025-26 | E43: 1716
F44: =SUM(E41:E43) -> 3659494
G45: =+F33-F44-F38 -> 4764517
B49: II | C49: Capital Gain | G49: 0
B51: III | C51: Income from Other Sources
D52: Interest Received on FD | F52: ='Annexure PnL'!C25 -> 166630
D53: Interest on IT Refund | F53: ='Annexure PnL'!C19 -> 57547
G54: =SUM(F52:F53) -> 224177
C56: Gross Total Income | G56: =SUM(G7:G54) -> 4988694
C58: Less: Deduction
D59: U/s 80JJAA
D60: Employment of New Employees | F60: 0
G61: =-F60 -> 0
C63: Total Income | G63: =SUM(G56:G62) -> 4988694
C64: Total Income Rounded Off u/s 288A | G64: =MROUND(G63,10) -> 4988690
D68: Tax Due u/s 115BAA @ 22% of Total Income | F68: =ROUND(G64*22%,0) -> 1097512
G70: =MAX(F67,F68) -> 1097512
D71: Add: Surcharge @ 10% | F71: =ROUND(G70*10%,0) -> 109751
G73: =SUM(F71:F72) -> 109751
G75: =SUM(G70:G74) -> 1207263
D76: Add : Health and Education Cess @4% | F76: =ROUND(G75*4%,0) -> 48291
G78: =SUM(F76:F77) -> 48291
G80: =SUM(G75:G79) -> 1255554
D81: Less: TDS | F81: ='Annexure BS'!C122 -> 882663
D82: Less: TCS | F82: 0
G84: =-SUM(F81:F83) -> -882663
G85: =SUM(G80:G84) -> 372891
D86: Less: Advance Tax | F86: =ROUND(F102,0) -> 1450000
G87: =-F86 -> -1450000
G88: =SUM(G85:G87) -> -1077109
D89: Add: Interest u/s 234 A | F89: 0
D90: Add: Interest u/s 234 B | F90: =E124 -> 0
D91: Add: Interest u/s 234 C | F91: =K134 -> 0
G92: =SUM(F89:F91) -> 0
D93: =IF(SUM(G88:G92)>0,"Tax Payable","Tax Refundable") -> Tax Refundable | G93: =IF(SUM(G88:G92)>0,SUM(G88:G92),-SUM(G88:G92)) -> 1077109
D97: Advance Tax Schedule
D98: Q1 | F98: 300000
D99: Q2 | F99: 600000
D100: Q3 | F100: 550000
D101: Q4 | F101: 0
F102: =SUM(F98:F101) -> 1450000
D105: Interest u/s 234 A
D107: Tax Due | E107: =G88 -> -1077109
D108: If Tax Payable Exceeds Rs 1.00 lac,due date for the purpose of interest u/s 234A has not been extended(Original Due date - 31st October)
D110: Interest @ 1%(1 Month) | E110: 0
D114: Interest u/s 234 B
D116: Tax Due | E116: =G80 -> 1255554
D117: 90% of Tax due | E117: =E116*90% -> 1129998.6
D118: Tax Paid (TDS, TCS and Advance Tax) | E118: =-SUM(G84,G87) -> 2332663
D120: Difference | E120: =IF((E117-E118)<0,0,E116-E118) -> 0
D122: =IF(E118>E117,"Since 90% of Tax Due has been paid, Section 234 B of Income Tax Act, 1956 has not been attracted.","Since 90% of Tax Due has not been paid Section ,234 B of the Income Tax Act, 1961 has been attracted.") -> Since 90% of Tax Due has been paid, Section 234 B of Income Tax Act, 1956 has not been attracted.
D124: Interest @ 1% | E124: =IF(E120<0,0,ROUND(E120*1%*8,0)) -> 0
D126: Interest u/s 234 C
D128: Due Date | E128: Assessable Tax | F128: Advance Tax Due | H128: Advance Tax Paid | I128: Balance Unpaid | J128: Interest on default
F129: Rate | G129: Amount | J129: Rate | K129: Amount
D130: 45458 | E130: =$G$85 -> 372891 | F130: 0.15 | G130: =ROUND(E130*F130,0) -> 55934 | H130: =F98 -> 300000 | I130: =FLOOR(IF((G130-H130)<=0,0,(G130-H130)),100) -> 0 | J130: 0.03 | K130: 0 | L130: Below 12%
D131: 45550 | E131: =$G$85 -> 372891 | F131: 0.45 | G131: =ROUND(E131*F131,0) -> 167801 | H131: =F99+H130 -> 900000 | I131: =FLOOR(IF((G131-H131)<=0,0,(G131-H131)),100) -> 0 | J131: 0.03 | K131: =I131*J131 -> 0
D132: 45641 | E132: =$G$85 -> 372891 | F132: 0.75 | G132: =ROUND(E132*F132,0) -> 279668 | H132: =F100+H131 -> 1450000 | I132: =FLOOR(IF((G132-H132)<=0,0,(G132-H132)),100) -> 0 | J132: 0.03 | K132: =I132*J132 -> 0
D133: 45731 | E133: =$G$85 -> 372891 | F133: 1 | G133: =ROUND(E133*F133,0) -> 372891 | H133: =F101+H132 -> 1450000 | I133: =FLOOR(IF((G133-H133)<=0,0,(G133-H133)),100) -> 0 | J133: 0.01 | K133: =I133*J133 -> 0
K134: =SUM(K130:K133) -> 0
D137: Brought Forward Loss Setoff
E138: Business Loss | F138: Unabsorbed Dep Loss | G138: Total Loss set off in Previous years | H138: Setoff in Current Year | I138: Balance Carry Forward
D139: AY 2022-23 | E139: 5481873 | F139: 0 | G139: 3148103 | H139: 2333770 | I139: =E139-G139-H139 -> 0
D140: AY 2023-24 | E140: 1324008 | F140: 23720 | G140: 0 | H140: =F140+E140 -> 1347728 | I140: =E140+F140-G140-H140 -> 0
D141: AY 2025-26 | E141: 1716 | F141: 8539 | G141: 0 | H141: =E141+F141 -> 10255 | I141: =E141+F141-H141 -> 0
I143: =SUM(I139:I142) -> 0 | J143: Loss to be C/F
D146: Statement of Unabsorbed Depreciation Brought/Carried Forward
D147: Assessment Year | E147: Brought Forward | F147: Set off | G147: Carried Forward
D148: AY 23-24 | E148: =F140 -> 23720 | F148: =E148 -> 23720 | G148: =E148-F148 -> 0
D149: AY 25-26 | E149: 8539 | F149: =E149 -> 8539 | G149: =E149-F149 -> 0
D150: Current Year
D151: Total | E151: =SUM(E148:E149) -> 32259 | F151: =SUM(F148:F149) -> 32259 | G151: =SUM(G148:G149) -> 0
D154: Statement of Business losses Brought/Carried Forward
D155: Assessment Year | E155: Brought Forward | F155: Set off | G155: Carried Forward
...

Sheet TB CY
A1: Ledger Name | B1: Ledger Parent Name | C1: Ledger Grandparent Name | D1: Primary Group Name | E1: Ledger Ultimate Parent Name | F1: Ledger Type | G1: Opening balance | H1: Debit Transaction | I1: Credit Transaction | J1: Net Transaction | K1: Closing Balance | L1: Balance sheet Primary Classification Display Name | M1: Balance sheet Classification Display Name | N1: PNL Primary Classification Display Name | O1: PNL Classification Display Name | P1: Tally Company Name | Q1: Balance sheet User Defined Classification (Update the customer defined value here) | R1: PnL User Defined Classfication | S1: guid
A2: Authorised Share Capital | B2: Capital Account | C2: _x0004_ Primary | D2: Capital Account | E2: Capital Account | F2: Liability | G2: 1500000 | H2: 0 | I2: 0 | J2: 0 | K2: 1500000 | L2: Share Capital | M2: Equity Shares Of Rs. 10/- Each | P2: K.U.M. India Private Limited - (from 1-Apr-23) | S2: e1c68af5-de76-4b79-88f9-add67b8d3461-000000ab
A3: ICICI Bank | B3: Bank Accounts | C3: Current Assets | D3: Bank Accounts | E3: Current Assets | F3: Asset | G3: -972030.58 | H3: -5760422.5 | I3: 5055383 | J3: -705039.51 | K3: 1677070.1 | L3: Cash and Cash Equivalents | M3: In current account | P3: K.U.M. India Private Limited - (from 1-Apr-23) | S3: e1c68af5-de76-4b79-88f9-add67b8d3461-000000c2
A4: Cash | B4: Cash-in-Hand | C4: Current Assets | D4: Cash-in-Hand | E4: Current Assets | F4: Asset | G4: 0 | H4: 0 | I4: 0 | J4: 0 | K4: 0 | L4: Cash and Cash Equivalents | M4: Cash on hand | P4: K.U.M. India Private Limited - (from 1-Apr-23) | S4: e1c68af5-de76-4b79-88f9-add67b8d3461-0000001f
A5: ICICI FD A/c | B5: Current Assets | C5: _x0004_ Primary | D5: Current Assets | E5: Current Assets | F5: Asset | G5: 0 | H5: 0 | I5: 0 | J5: 0 | K5: 0 | L5: Other Current Assets | M5: Other current assets | P5: K.U.M. India Private Limited - (from 1-Apr-23) | S5: e1c68af5-de76-4b79-88f9-add67b8d3461-000000c3
A6: Superior Computer | B6: Current Assets | C6: _x0004_ Primary | D6: Current Assets | E6: Current Assets | F6: Asset | G6: 0 | H6: 0 | I6: 0 | J6: 0 | K6: 0 | L6: Other Current Assets | M6: Other current assets | P6: K.U.M. India Private Limited - (from 1-Apr-23) | S6: e1c68af5-de76-4b79-88f9-add67b8d3461-000000e7
A7: Duty IGST Receivable | B7: GST | C7: Current Assets | D7: Current Assets | E7: Current Assets | F7: Asset | G7: 0 | H7: -2699029 | I7: 0 | J7: -2699029 | K7: 2699029 | L7: Short-term Loans & Advances | M7: Balance with Government Authorities-IT Refund | P7: K.U.M. India Private Limited - (from 1-Apr-23) | S7: e1c68af5-de76-4b79-88f9-add67b8d3461-00000174
A8: Input CGST | B8: GST | C8: Current Assets | D8: Current Assets | E8: Current Assets | F8: Asset | G8: -62763.8 | H8: -20268.94 | I8: 79432.74 | J8: 59163.8 | K8: 3600 | L8: Short-term Loans & Advances | M8: Balance with Government Authorities-IT Refund | P8: K.U.M. India Private Limited - (from 1-Apr-23) | S8: e1c68af5-de76-4b79-88f9-add67b8d3461-000000c4
A9: Input CGST Receivable A/c | B9: GST | C9: Current Assets | D9: Current Assets | E9: Current Assets | F9: Asset | G9: -9675 | H9: 0 | I9: 9675 | J9: 9675 | K9: 0 | L9: Short-term Loans & Advances | M9: Balance with Government Authorities-IT Refund | P9: K.U.M. India Private Limited - (from 1-Apr-23) | S9: e1c68af5-de76-4b79-88f9-add67b8d3461-000000ea
A10: Input IGST | B10: GST | C10: Current Assets | D10: Current Assets | E10: Current Assets | F10: Asset | G10: -450 | H10: -628 | I10: 1078 | J10: 450 | K10: 0 | L10: Short-term Loans & Advances | M10: Balance with Government Authorities-IT Refund | P10: K.U.M. India Private Limited - (from 1-Apr-23) | S10: e1c68af5-de76-4b79-88f9-add67b8d3461-000000c5
A11: Input IGST Receivable A/c | B11: GST | C11: Current Assets | D11: Current Assets | E11: Current Assets | F11: Asset | G11: 0 | H11: 0 | I11: 0 | J11: 0 | K11: 0 | L11: Short-term Loans & Advances | M11: Balance with Government Authorities-IT Refund | P11: K.U.M. India Private Limited - (from 1-Apr-23) | S11: e1c68af5-de76-4b79-88f9-add67b8d3461-00000183
A12: Input SGST | B12: GST | C12: Current Assets | D12: Current Assets | E12: Current Assets | F12: Asset | G12: -59681.8 | H12: -20268.94 | I12: 76350.74 | J12: 56081.8 | K12: 3600 | L12: Short-term Loans & Advances | M12: Balance with Government Authorities-IT Refund | P12: K.U.M. India Private Limited - (from 1-Apr-23) | S12: e1c68af5-de76-4b79-88f9-add67b8d3461-000000c6
A13: Input SGST Receivable A/c | B13: GST | C13: Current Assets | D13: Current Assets | E13: Current Assets | F13: Asset | G13: -9675 | H13: 0 | I13: 9675 | J13: 9675 | K13: 0 | L13: Short-term Loans & Advances | M13: Balance with Government Authorities-IT Refund | P13: K.U.M. India Private Limited - (from 1-Apr-23) | S13: e1c68af5-de76-4b79-88f9-add67b8d3461-000000eb
... A58: K.U.M. Germany Creditors | B58: Sundry Creditors | C58: Current Liabilities | D58: Sundry Creditors | E58: Current Liabilities | F58: Liability | G58: 0 | H58: 0 | I58: 18999343 | J58: 18999343 | K58: 18999343 | L58: Trade Payables | M58: (b) Total Outstanding dues of creditors other than Micro Enterprises and Small Enterprises | P58: K.U.M. India Private Limited - (from 1-Apr-23) | S58: e1c68af5-de76-4b79-88f9-add67b8d3461-00000182
A59: Clearance Charges | B59: Direct Expenses | C59: _x0004_ Primary | D59: Direct Expenses | E59: Direct Expenses | F59: Expense | G59: 0 | H59: -4720 | I59: 4720 | J59: 0 | K59: 0 | N59: Other Expenses | O59: Rates and taxes | P59: K.U.M. India Private Limited - (from 1-Apr-23) | S59: e1c68af5-de76-4b79-88f9-add67b8d3461-0000016f
A60: OBS Rental A/c | B60: Direct Expenses | C60: _x0004_ Primary | D60: Direct Expenses | E60: Direct Expenses | F60: Expense | G60: 0 | H60: -22419225 | I60: 0 | J60: -22419225 | K60: 22419225 | N60: Other Expenses | O60: Rent | P60: K.U.M. India Private Limited - (from 1-Apr-23) | S60: e1c68af5-de76-4b79-88f9-add67b8d3461-00000181
A61: Project Expenses A/c | B61: Direct Expenses | C61: _x0004_ Primary | D61: Direct Expenses | E61: Direct Expenses | F61: Expense | G61: 0 | H61: -23138.89 | I61: 520 | J61: -22618.89 | K61: 22618.89 | N61: Other Expenses | O61: Bussiness support services | P61: K.U.M. India Private Limited - (from 1-Apr-23) | S61: e1c68af5-de76-4b79-88f9-add67b8d3461-000000e8
A62: Tender Fee & Registration Charges | B62: Direct Expenses | C62: _x0004_ Primary | D62: Direct Expenses | E62: Direct Expenses | F62: Expense | G62: 0 | H62: -5000 | I62: 0 | J62: -5000 | K62: 5000 | N62: Other Expenses | O62: Legal and professional | P62: K.U.M. India Private Limited - (from 1-Apr-23) | S62: e1c68af5-de76-4b79-88f9-add67b8d3461-000000e2
A63: OBS Air Shipment Expense | B63: Project Expense A/c | C63: Direct Expenses | D63: Direct Expenses | E63: Direct Expenses | F63: Expense | G63: 0 | H63: -68416.82 | I63: 720 | J63: -67696.82 | K63: 67696.82 | N63: Other Expenses | O63: Bussiness support services | P63: K.U.M. India Private Limited - (from 1-Apr-23) | S63: e1c68af5-de76-4b79-88f9-add67b8d3461-00000171
A64: OBS Sea Shipment Expense | B64: Project Expense A/c | C64: Direct Expenses | D64: Direct Expenses | E64: Direct Expenses | F64: Expense | G64: 0 | H64: -1188789.2 | I64: 34821.82 | J64: -1153967.4 | K64: 1153967.4 | N64: Other Expenses | O64: Bussiness support services | P64: K.U.M. India Private Limited - (from 1-Apr-23) | S64: e1c68af5-de76-4b79-88f9-add67b8d3461-00000172
A65: Sales | B65: Direct Incomes | C65: _x0004_ Primary | D65: Direct Incomes | E65: Direct Incomes | F65: Income | G65: 0 | H65: 0 | I65: 0 | J65: 0 | K65: 0 | P65: K.U.M. India Private Limited - (from 1-Apr-23) | S65: e1c68af5-de76-4b79-88f9-add67b8d3461-000000ed
A66: Depreciation Reserve - Panasonic Phone | B66: Fixed Assets | C66: _x0004_ Primary | D66: Fixed Assets | E66: Fixed Assets | F66: Asset | G66: 0 | H66: 0 | I66: 0 | J66: 0 | K66: 0 | L66: Property, Plant and Equipment | M66: Property, Plant and Equipment | P66: K.U.M. India Private Limited - (from 1-Apr-23) | S66: e1c68af5-de76-4b79-88f9-add67b8d3461-000000b7
A67: Laptop A/c | B67: Fixed Assets | C67: _x0004_ Primary | D67: Fixed Assets | E67: Fixed Assets | F67: Asset | G67: -34340.28 | H67: 0 | I67: 15914 | J67: 15914 | K67: 18426.28 | L67: Property, Plant and Equipment | M67: Property, Plant and Equipment | P67: K.U.M. India Private Limited - (from 1-Apr-23) | S67: e1c68af5-de76-4b79-88f9-add67b8d3461-000000e6
A68: Panasonic Phone | B68: Fixed Assets | C68: _x0004_ Primary | D68: Fixed Assets | E68: Fixed Assets | F68: Asset | G68: 0 | H68: 0 | I68: 0 | J68: 0 | K68: 0 | L68: Property, Plant and Equipment | M68: Property, Plant and Equipment | P68: K.U.M. India Private Limited - (from 1-Apr-23) | S68: e1c68af5-de76-4b79-88f9-add67b8d3461-000000d3
A69: Audit Fees | B69: Indirect Expenses | C69: _x0004_ Primary | D69: Indirect Expenses | E69: Indirect Expenses | F69: Expense | G69: 0 | H69: -88500 | I69: 13500 | J69: -75000 | K69: 75000 | N69: Auditor Remuneration | O69: for audit | P69: K.U.M. India Private Limited - (from 1-Apr-23) | S69: e1c68af5-de76-4b79-88f9-add67b8d3461-000000aa
A70: Business Promotion Expenses | B70: Indirect Expenses | C70: _x0004_ Primary | D70: Indirect Expenses | E70: Indirect Expenses | F70: Expense | G70: 0 | H70: 0 | I70: 0 | J70: 0 | K70: 0 | P70: K.U.M. India Private Limited - (from 1-Apr-23) | S70: e1c68af5-de76-4b79-88f9-add67b8d3461-000000ad
A71: Communication Expenses | B71: Indirect Expenses | C71: _x0004_ Primary | D71: Indirect Expenses | E71: Indirect Expenses | F71: Expense | G71: 0 | H71: -13391.4 | I71: 1178 | J71: -12213.4 | K71: 12213.4 | N71: Other Expenses | O71: Communication | P71: K.U.M. India Private Limited - (from 1-Apr-23) | S71: e1c68af5-de76-4b79-88f9-add67b8d3461-000000b0
A72: Company Tax | B72: Indirect Expenses | C72: _x0004_ Primary | D72: Indirect Expenses | E72: Indirect Expenses | F72: Expense | G72: 0 | H72: -2000 | I72: 0 | J72: -2000 | K72: 2000 | N72: Other Expenses | O72: Rates and taxes | P72: K.U.M. India Private Limited - (from 1-Apr-23) | S72: e1c68af5-de76-4b79-88f9-add67b8d3461-000000b1
A73: Compliance Cost | B73: Indirect Expenses | C73: _x0004_ Primary | D73: Indirect Expenses | E73: Indirect Expenses | F73: Expense | G73: 0 | H73: -824 | I73: 0 | J73: -824 | K73: 824 | N73: Other Expenses | O73: Legal and professional | P73: K.U.M. India Private Limited - (from 1-Apr-23) | S73: e1c68af5-de76-4b79-88f9-add67b8d3461-000000b2
A74: Courier Charges | B74: Indirect Expenses | C74: _x0004_ Primary | D74: Indirect Expenses | E74: Indirect Expenses | F74: Expense | G74: 0 | H74: -235 | I74: 105 | J74: -130 | K74: 130 | N74: Other Expenses | O74: Postal and courier charges | P74: K.U.M. India Private Limited - (from 1-Apr-23) | S74: e1c68af5-de76-4b79-88f9-add67b8d3461-000000b3
A75: Depreciation | B75: Indirect Expenses | C75: _x0004_ Primary | D75: Indirect Expenses | E75: Indirect Expenses | F75: Expense | G75: 0 | H75: -15914 | I75: 0 | J75: -15914 | K75: 15914 | N75: Depreciation and Amortisation | O75: Depreciation | P75: K.U.M. India Private Limited - (from 1-Apr-23) | S75: e1c68af5-de76-4b79-88f9-add67b8d3461-000000b6
A76: Festival Bonus | B76: Indirect Expenses | C76: _x0004_ Primary | D76: Indirect Expenses | E76: Indirect Expenses | F76: Expense | G76: 0 | H76: -33750 | I76: 0 | J76: -33750 | K76: 33750 | N76: Employee Benefits | O76: Contribution to providend and other funds | P76: K.U.M. India Private Limited - (from 1-Apr-23) | S76: e1c68af5-de76-4b79-88f9-add67b8d3461-000000be
A77: Interest on TDS | B77: Indirect Expenses | C77: _x0004_ Primary | D77: Indirect Expenses | E77: Indirect Expenses | F77: Expense | G77: 0 | H77: 0 | I77: 0 | J77: 0 | K77: 0 | P77: K.U.M. India Private Limited - (from 1-Apr-23) | S77: e1c68af5-de76-4b79-88f9-add67b8d3461-000000c8
A78: Loss on Forex | B78: Indirect Expenses | C78: _x0004_ Primary | D78: Indirect Expenses | E78: Indirect Expenses | F78: Expense | G78: 0 | H78: -3475 | I78: 0 | J78: -3475 | K78: 3475 | N78: Other Expenses | O78: Forex loss | P78: K.U.M. India Private Limited - (from 1-Apr-23) | S78: e1c68af5-de76-4b79-88f9-add67b8d3461-000000ee
A79: MGT Filing Fee | B79: Indirect Expenses | C79: _x0004_ Primary | D79: Indirect Expenses | E79: Indirect Expenses | F79: Expense | G79: 0 | H79: 0 | I79: 0 | J79: 0 | K79: 0 | P79: K.U.M. India Private Limited - (from 1-Apr-23) | S79: e1c68af5-de76-4b79-88f9-add67b8d3461-000000cd
A80: Performance Incentive A/c | B80: Indirect Expenses | C80: _x0004_ Primary | D80: Indirect Expenses | E80: Indirect Expenses | F80: Expense | G80: 0 | H80: -40000 | I80: 0 | J80: -40000 | K80: 40000 | N80: Employee Benefits | O80: Contribution to providend and other funds | P80: K.U.M. India Private Limited - (from 1-Apr-23) | S80: e1c68af5-de76-4b79-88f9-add67b8d3461-00000184
A81: Printing & Stationery | B81: Indirect Expenses | C81: _x0004_ Primary | D81: Indirect Expenses | E81: Indirect Expenses | F81: Expense | G81: 0 | H81: 0 | I81: 0 | J81: 0 | K81: 0 | P81: K.U.M. India Private Limited - (from 1-Apr-23) | S81: e1c68af5-de76-4b79-88f9-add67b8d3461-000000d5
A82: Professional Fees | B82: Indirect Expenses | C82: _x0004_ Primary | D82: Indirect Expenses | E82: Indirect Expenses | F82: Expense | G82: 0 | H82: -182529 | I82: 30914 | J82: -151615 | K82: 151615 | N82: Other Expenses | O82: Legal and professional | P82: K.U.M. India Private Limited - (from 1-Apr-23) | S82: e1c68af5-de76-4b79-88f9-add67b8d3461-000000d6
A83: Rent A/c | B83: Indirect Expenses | C83: _x0004_ Primary | D83: Indirect Expenses | E83: Indirect Expenses | F83: Expense | G83: 0 | H83: -141600 | I83: 0 | J83: -141600 | K83: 141600 | N83: Other Expenses | O83: Rent | P83: K.U.M. India Private Limited - (from 1-Apr-23) | S83: e1c68af5-de76-4b79-88f9-add67b8d3461-000000da
A84: Salary A/c | B84: Indirect Expenses | C84: _x0004_ Primary | D84: Indirect Expenses | E84: Indirect Expenses | F84: Expense | G84: 0 | H84: -405000 | I84: 0 | J84: -405000 | K84: 405000 | N84: Employee Benefits | O84: Salary and Wages | P84: K.U.M. India Private Limited - (from 1-Apr-23) | S84: e1c68af5-de76-4b79-88f9-add67b8d3461-000000dd
A85: Software Expenses | B85: Indirect Expenses | C85: _x0004_ Primary | D85: Indirect Expenses | E85: Indirect Expenses | F85: Expense | G85: 0 | H85: -708 | I85: 108 | J85: -600 | K85: 600 | N85: Other Expenses | O85: Security | P85: K.U.M. India Private Limited - (from 1-Apr-23) | S85: e1c68af5-de76-4b79-88f9-add67b8d3461-000000df
A86: Transportation Charges | B86: Indirect Expenses | C86: _x0004_ Primary | D86: Indirect Expenses | E86: Indirect Expenses | F86: Expense | G86: 0 | H86: 0 | I86: 0 | J86: 0 | K86: 0 | P86: K.U.M. India Private Limited - (from 1-Apr-23) | S86: e1c68af5-de76-4b79-88f9-add67b8d3461-000000f1
A87: Travel Expenses | B87: Indirect Expenses | C87: _x0004_ Primary | D87: Indirect Expenses | E87: Indirect Expenses | F87: Expense | G87: 0 | H87: -124890 | I87: 72 | J87: -124818 | K87: 124818 | N87: Other Expenses | O87: Travelling & Conveyance | P87: K.U.M. India Private Limited - (from 1-Apr-23) | S87: e1c68af5-de76-4b79-88f9-add67b8d3461-000000e3
A88: Unavailed GST RCM | B88: Indirect Expenses | C88: _x0004_ Primary | D88: Indirect Expenses | E88: Indirect Expenses | F88: Expense | G88: 0 | H88: 0 | I88: 0 | J88: 0 | K88: 0 | P88: K.U.M. India Private Limited - (from 1-Apr-23) | S88: e1c68af5-de76-4b79-88f9-add67b8d3461-000000c1
A89: Bank Charges | B89: Bank Charges | C89: Indirect Expenses | D89: Indirect Expenses | E89: Indirect Expenses | F89: Expense | G89: 0 | H89: -1421.88 | I89: 1171.88 | J89: -250 | K89: 250 | N89: Other Expenses | O89: Bank charges | P89: K.U.M. India Private Limited - (from 1-Apr-23) | S89: e1c68af5-de76-4b79-88f9-add67b8d3461-000000ac
A90: ECB2 Return Filing Charges | B90: Bank Charges | C90: Indirect Expenses | D90: Indirect Expenses | E90: Indirect Expenses | F90: Expense | G90: 0 | H90: -5310 | I90: 810 | J90: -4500 | K90: 4500 | N90: Other Expenses | O90: Bank charges | P90: K.U.M. India Private Limited - (from 1-Apr-23) | S90: e1c68af5-de76-4b79-88f9-add67b8d3461-000000bb
A91: DSC Charges | B91: Compliance Cost | C91: Indirect Expenses | D91: Indirect Expenses | E91: Indirect Expenses | F91: Expense | G91: 0 | H91: -3570 | I91: 0 | J91: -3570 | K91: 3570 | N91: Other Expenses | O91: Legal and professional | P91: K.U.M. India Private Limited - (from 1-Apr-23) | S91: e1c68af5-de76-4b79-88f9-add67b8d3461-000000ba
A92: Other Compliance Cost | B92: Compliance Cost | C92: Indirect Expenses | D92: Indirect Expenses | E92: Indirect Expenses | F92: Expense | G92: 0 | H92: 0 | I92: 0 | J92: 0 | K92: 0 | P92: K.U.M. India Private Limited - (from 1-Apr-23) | S92: e1c68af5-de76-4b79-88f9-add67b8d3461-000000d0
A93: ROC Fees | B93: Compliance Cost | C93: Indirect Expenses | D93: Indirect Expenses | E93: Indirect Expenses | F93: Expense | G93: 0 | H93: -5399 | I93: 0 | J93: -5399 | K93: 5399 | N93: Other Expenses | O93: Legal and professional | P93: K.U.M. India Private Limited - (from 1-Apr-23) | S93: e1c68af5-de76-4b79-88f9-add67b8d3461-000000db
A94: Gain on Forex | B94: Indirect Incomes | C94: _x0004_ Primary | D94: Indirect Incomes | E94: Indirect Incomes | F94: Income | G94: 0 | H94: 0 | I94: 18541.78 | J94: 18541.78 | K94: 18541.78 | N94: Other Income | O94: Forex gains | P94: K.U.M. India Private Limited - (from 1-Apr-23) | S94: e1c68af5-de76-4b79-88f9-add67b8d3461-000000bf
A95: Interest on ICICI FD A/c | B95: Indirect Incomes | C95: _x0004_ Primary | D95: Indirect Incomes | E95: Indirect Incomes | F95: Income | G95: 0 | H95: 0 | I95: 0 | J95: 0 | K95: 0 | P95: K.U.M. India Private Limited - (from 1-Apr-23) | S95: e1c68af5-de76-4b79-88f9-add67b8d3461-000000c7
A96: Rounding Off | B96: Indirect Incomes | C96: _x0004_ Primary | D96: Indirect Incomes | E96: Indirect Incomes | F96: Income | G96: 0 | H96: -1.86 | I96: 4.84 | J96: 2.98 | K96: 2.98 | N96: Other Income | O96: Other non-operating income | P96: K.U.M. India Private Limited - (from 1-Apr-23) | S96: e1c68af5-de76-4b79-88f9-add67b8d3461-000000dc
A97: External Commercial Borrowings | B97: Loans (Liability) | C97: _x0004_ Primary | D97: Loans (Liability) | E97: Loans (Liability) | F97: Liability | G97: 11273750 | H97: 0 | I97: 3475 | J97: 3475 | K97: 11277225 | L97: Short-term Borrowings | M97: (ii) from other parties(ST) | P97: K.U.M. India Private Limited - (from 1-Apr-23) | S97: e1c68af5-de76-4b79-88f9-add67b8d3461-000000bd
A98: Profit & Loss A/c | B98: _x0004_ Primary | E98: Primary | F98: Liability | G98: -11722513 | H98: 0 | I98: 0 | J98: 0 | K98: -11722513 | P98: K.U.M. India Private Limited - (from 1-Apr-23) | S98: e1c68af5-de76-4b79-88f9-add67b8d3461-0000001e
A99: Business Support Services | B99: Sales Accounts | C99: _x0004_ Primary | D99: Sales Accounts | E99: Sales Accounts | F99: Income | G99: 0 | H99: 0 | I99: 1476170.1 | J99: 1476170.1 | K99: 1476170.1 | N99: Revenue from Operations | O99: Sale of services | P99: K.U.M. India Private Limited - (from 1-Apr-23) | S99: e1c68af5-de76-4b79-88f9-add67b8d3461-000000ae
A100: Service Charges - Domestic | B100: Sales Accounts | C100: _x0004_ Primary | D100: Sales Accounts | E100: Sales Accounts | F100: Income | G100: 0 | H100: 0 | I100: 27800000 | J100: 27800000 | K100: 27800000 | N100: Revenue from Operations | O100: Sale of services | P100: K.U.M. India Private Limited - (from 1-Apr-23) | S100: e1c68af5-de76-4b79-88f9-add67b8d3461-0000017b
